Workbook

Sheet DATOS
A1: NUTRIMETRÍA · NMX-43 | DATOS
A3: Entradas principales del caso académico.
A5: =HYPERLINK("#'INICIO'!A1","INICIO") -> INICIO | B5: =HYPERLINK("#'DATOS'!A1","DATOS") -> DATOS | C5: =HYPERLINK("#'ENERGÍA'!A1","ENERGÍA") -> ENERGÍA | D5: =HYPERLINK("#'MACRONUTRIENTES'!A1","MACRONUTRIENTES") -> MACRONUTRIENTES | E5: =HYPERLINK("#'AGUA_FIBRA'!A1","AGUA/FIBRA") -> AGUA/FIBRA | F5: =HYPERLINK("#'FICHA_NUTRIENTE'!A1","FICHA/NUTRIENTE") -> FICHA/NUTRIENTE | G5: =HYPERLINK("#'RESULTADOS'!A1","RESULTADOS") -> RESULTADOS | H5: =HYPERLINK("#'DOCUMENTACIÓN'!A1","DOCUMENTACIÓN") -> DOCUMENTACIÓN | I5: =HYPERLINK("#'COBERTURA'!A1","COBERTURA") -> COBERTURA | J5: =HYPERLINK("#'AUDITORÍA_FINAL'!A1","AUDITORÍA") -> AUDITORÍA
A7: CASO ACADÉMICO · ENTRADAS EDITABLES
A8: Código del caso | B8: CASO-DEMO-01 | C8: Identificador interno | E8: RESUMEN AUTOMÁTICO
A9: Nombre opcional | B9: Caso demostrativo | C9: Texto | E9: Edad equivalente (años) | F9: =IF(B12="Meses",B11/12,B11) -> 25
A10: Fecha | B10: 46236 | C10: Fecha | E10: Edad equivalente (meses) | F10: =IF(B12="Meses",B11,B11*12) -> 300
A11: Edad | B11: 25 | C11: Años o meses | E11: IMC informativo | F11: =IF(OR(B14="",B15=""),"",B14/(B15/100)^2) -> 20.82094
A12: Unidad de edad | B12: Años | C12: Lista | E12: Suma de macros (%) | F12: =SUM(B27:B29) -> 100
A13: Sexo | B13: Femenino | C13: Lista | E13: Estado de entrada | F13: =IF(OR(B11="",B14="",B15=""),"INCOMPLETO",IF(ABS(F12-100)>CONFIG!$B$11,"REVISAR MACROS","LISTO")) -> LISTO
A14: Peso | B14: 56 | C14: kg | E14: Uso | F14: Académico; no diagnóstico
A15: Talla | B15: 164 | C15: cm
A16: Estado fisiológico | B16: Ninguno | C16: Lista | E16: Advertencia: los resultados son estimaciones poblacionales. El requerimiento energético individual debe contrastarse con evolución del peso, crecimiento, gestación o lactancia y con el contexto clínico.
A17: Actividad NASEM | B17: Poco activo | C17: Lista
A18: Actividad FAO 6–18 | B18: Ligera | C18: Lista
A19: Método energético | B19: Schofield × PAL | C19: Lista
A20: PAL manual Schofield | B20: 1.6 | C20: múltiplo BMR
A21: Semanas de gestación | B21: 20 | C21: 0–42
A22: IMC pregestacional | B22: Normal | C22: Lista
A23: Meses posparto | B23: 0 | C23: 0–12
A24: Tipo de lactancia | B24: No aplica | C24: Lista
A25: Modo de macronutrientes | B25: Porcentual | C25: Lista
A26: Proteína seleccionada | B26: 1 | C26: g/kg/día
A27: Proteína | B27: 15 | C27: % energía
A28: Lípidos | B28: 30 | C28: % energía
A29: Carbohidratos | B29: 55 | C29: % energía
A30: Agua consumida | B30: 2.5 | C30: L/día
A31: Fibra consumida | B31: 25 | C31: g/día
A32: Energía manual | B32: 2000 | C32: kcal/día

Sheet INICIO
A1: NUTRIMETRÍA · NMX-43 | INICIO
A3: Panel de control y navegación del portafolio académico.
A5: =HYPERLINK("#'INICIO'!A1","INICIO") -> INICIO | B5: =HYPERLINK("#'DATOS'!A1","DATOS") -> DATOS | C5: =HYPERLINK("#'ENERGÍA'!A1","ENERGÍA") -> ENERGÍA | D5: =HYPERLINK("#'MACRONUTRIENTES'!A1","MACRONUTRIENTES") -> MACRONUTRIENTES | E5: =HYPERLINK("#'AGUA_FIBRA'!A1","AGUA/FIBRA") -> AGUA/FIBRA | F5: =HYPERLINK("#'FICHA_NUTRIENTE'!A1","FICHA/NUTRIENTE") -> FICHA/NUTRIENTE | G5: =HYPERLINK("#'RESULTADOS'!A1","RESULTADOS") -> RESULTADOS | H5: =HYPERLINK("#'DOCUMENTACIÓN'!A1","DOCUMENTACIÓN") -> DOCUMENTACIÓN | I5: =HYPERLINK("#'COBERTURA'!A1","COBERTURA") -> COBERTURA | J5: =HYPERLINK("#'AUDITORÍA_FINAL'!A1","AUDITORÍA") -> AUDITORÍA
A7: NMX-43 · Portafolio de Bases de la Nutrición I y II
A9: NUTRIENTES 23 | E9: FASE ACTUAL 9 | I9: PRUEBAS APROBADAS 103 / 106 | M9: ESTADO 69 CASOS ACTIVOS
A15: FASE 9 · BIBLIOTECA UDD Y BANCO CLÍNICO-FORMATIVO El libro incluye 69 casos de micronutrientes: un caso básico, uno intermedio y uno avanzado para cada uno de los 23 micronutrientes. La hoja CASOS_CLÍNICOS permite seleccionar nutriente y nivel, y contiene una matriz de cobertura 69/69. Los casos son educativos: no representan diagnóstico, prescripción ni tratamiento automático.
A24: ACCESOS RÁPIDOS
A26: =HYPERLINK("#'DATOS'!A1","DATOS") -> DATOS | E26: =HYPERLINK("#'ENERGÍA'!A1","ENERGÍA") -> ENERGÍA | I26: =HYPERLINK("#'MACRONUTRIENTES'!A1","MACRONUTRIENTES") -> MACRONUTRIENTES | M26: =HYPERLINK("#'AGUA_FIBRA'!A1","AGUA / FIBRA") -> AGUA / FIBRA
A32: =HYPERLINK("#'ÍNDICE_CARGA_GLICÉMICA'!A1","ÍNDICE / CARGA") -> ÍNDICE / CARGA | E32: =HYPERLINK("#'RESULTADOS'!A1","RESULTADOS") -> RESULTADOS | I32: =HYPERLINK("#'FUENTES'!A1","FUENTES") -> FUENTES | M32: =HYPERLINK("#'PRUEBAS'!A1","PRUEBAS") -> PRUEBAS
A37: =HYPERLINK("#'FICHA_NUTRIENTE'!A1","FICHA NUTRIENTE") -> FICHA NUTRIENTE | E37: =HYPERLINK("#'REQUERIMIENTOS'!A1","REQUERIMIENTOS") -> REQUERIMIENTOS | I37: =HYPERLINK("#'DOCUMENTACIÓN'!A1","DOCUMENTACIÓN") -> DOCUMENTACIÓN | M37: =HYPERLINK("#'AUDITORÍA_FINAL'!A1","AUDITORÍA FINAL") -> AUDITORÍA FINAL

Sheet ENERGÍA
A1: NUTRIMETRÍA · NMX-43 | ENERGÍA
A3: Motores activos: Schofield 1985, FAO/WHO/UNU 2004, factorial de 24 horas y NASEM EER 2023.
A5: =HYPERLINK("#'INICIO'!A1","INICIO") -> INICIO | B5: =HYPERLINK("#'DATOS'!A1","DATOS") -> DATOS | C5: =HYPERLINK("#'ENERGÍA'!A1","ENERGÍA") -> ENERGÍA | D5: =HYPERLINK("#'MACRONUTRIENTES'!A1","MACRONUTRIENTES") -> MACRONUTRIENTES | E5: =HYPERLINK("#'AGUA_FIBRA'!A1","AGUA/FIBRA") -> AGUA/FIBRA | F5: =HYPERLINK("#'FICHA_NUTRIENTE'!A1","FICHA/NUTRIENTE") -> FICHA/NUTRIENTE | G5: =HYPERLINK("#'RESULTADOS'!A1","RESULTADOS") -> RESULTADOS | H5: =HYPERLINK("#'DOCUMENTACIÓN'!A1","DOCUMENTACIÓN") -> DOCUMENTACIÓN | I5: =HYPERLINK("#'COBERTURA'!A1","COBERTURA") -> COBERTURA | J5: =HYPERLINK("#'AUDITORÍA_FINAL'!A1","AUDITORÍA") -> AUDITORÍA
A7: DATOS DEL CASO
A8: Edad equivalente | B8: =CALCULOS_ENERGÍA!B2 -> 25 | C8: años | E8: BMR Schofield 1985 | F8: =CALCULOS_ENERGÍA!B15 -> 1316.408 | G8: kcal/d | I8: Indicador | K8: Resultado
A9: Sexo | B9: =CALCULOS_ENERGÍA!B4 -> Femenino | E9: GET Schofield × PAL | F9: =CALCULOS_ENERGÍA!B16 -> 2106.2528 | G9: kcal/d | I9: Diferencia NASEM vs Schofield (%) | K9: =CALCULOS_ENERGÍA!B25 -> 2.6828309
A10: Peso | B10: =CALCULOS_ENERGÍA!B5 -> 56 | C10: kg | E10: GET método factorial | F10: =CALCULOS_ENERGÍA!B18 -> 1974.612 | G10: kcal/d | I10: Alerta | K10: =CALCULOS_ENERGÍA!B26 -> OK CON LIMITACIONES
A11: Talla | B11: =CALCULOS_ENERGÍA!B6 -> 164 | C11: cm | E11: EER FAO 2004 (0–18) | F11: =CALCULOS_ENERGÍA!B19 -> ND | G11: kcal/d | I11: Uso de resultado | K11: Estimación educativa
A12: Estado fisiológico | B12: =CALCULOS_ENERGÍA!B7 -> Ninguno | E12: EER NASEM 2023 | F12: =CALCULOS_ENERGÍA!B21 -> 2162.76 | G12: kcal/d | I12: Criterio de control | K12: Monitorear peso/crecimiento
A13: Actividad NASEM | B13: =CALCULOS_ENERGÍA!B8 -> Poco activo | E13: Resultado seleccionado | F13: =CALCULOS_ENERGÍA!B23 -> 2106.2528 | G13: kcal/d
A14: Actividad FAO | B14: =CALCULOS_ENERGÍA!B9 -> Ligera | E14: Método seleccionado | F14: =CALCULOS_ENERGÍA!B22 -> Schofield × PAL | I14: Schofield estima metabolismo basal a partir de peso, edad y sexo. El método factorial combina BMR con horas y razones de actividad física (PAR). FAO pediátrico incorpora gasto y crecimiento. NASEM 2023 se presenta como comparador moderno y contempla embarazo/lactancia con entradas adicionales.
A15: PAL manual | B15: =CALCULOS_ENERGÍA!B10 -> 1.6 | E15: Método recomendado | F15: =CALCULOS_ENERGÍA!B24 -> Schofield × PAL y NASEM 2023 como comparación
I19: Instrucciones: 1) Asigne una actividad a cada fila. 2) Registre horas hasta completar 24. 3) El PAL se calcula como Σ(horas × PAR) / 24. 4) Si el total no es 24, el resultado queda ND. Los PAR son ejemplos de FAO/WHO/UNU y no sustituyen una medición individual.
A20: Seleccione una actividad en cualquiera de las 12 filas amarillas y registre sus horas. PAR, Horas × PAR, fuente y estado se completan automáticamente. El total debe ser 24 horas.
A21: MÉTODO FACTORIAL · 24 HORAS
A22: Actividad | B22: Horas/día | C22: PAR | D22: Horas × PAR | E22: Fuente/nota | F22: Estado
A23: Dormir | B23: 8 | C23: =IF(A23="","",IFERROR(INDEX(LISTAS!$L$2:$L$16,MATCH(A23,LISTAS!$K$2:$K$16,0)),"")) -> 1 | D23: =IF(A23="","",N(B23)*N(C23)) -> 8 | E23: =IF(A23="","",IFERROR(INDEX(LISTAS!$M$2:$M$16,MATCH(A23,LISTAS!$K$2:$K$16,0)),"Editable")) -> FAO tabla 5.1 | F23: =IF(A23="","",IF(B23<0,"ERROR",IF(B23>24,"REVISAR","OK"))) -> OK
A24: Cuidado personal | B24: 1 | C24: =IF(A24="","",IFERROR(INDEX(LISTAS!$L$2:$L$16,MATCH(A24,LISTAS!$K$2:$K$16,0)),"")) -> 2.3 | D24: =IF(A24="","",N(B24)*N(C24)) -> 2.3 | E24: =IF(A24="","",IFERROR(INDEX(LISTAS!$M$2:$M$16,MATCH(A24,LISTAS!$K$2:$K$16,0)),"Editable")) -> Vestirse, ducharse | F24: =IF(A24="","",IF(B24<0,"ERROR",IF(B24>24,"REVISAR","OK"))) -> OK
A25: Comer | B25: 1 | C25: =IF(A25="","",IFERROR(INDEX(LISTAS!$L$2:$L$16,MATCH(A25,LISTAS!$K$2:$K$16,0)),"")) -> 1.5 | D25: =IF(A25="","",N(B25)*N(C25)) -> 1.5 | E25: =IF(A25="","",IFERROR(INDEX(LISTAS!$M$2:$M$16,MATCH(A25,LISTAS!$K$2:$K$16,0)),"Editable")) -> Actividad alimentaria | F25: =IF(A25="","",IF(B25<0,"ERROR",IF(B25>24,"REVISAR","OK"))) -> OK
A26: Sentado / oficina | B26: 8 | C26: =IF(A26="","",IFERROR(INDEX(LISTAS!$L$2:$L$16,MATCH(A26,LISTAS!$K$2:$K$16,0)),"")) -> 1.5 | D26: =IF(A26="","",N(B26)*N(C26)) -> 12 | E26: =IF(A26="","",IFERROR(INDEX(LISTAS!$M$2:$M$16,MATCH(A26,LISTAS!$K$2:$K$16,0)),"Editable")) -> Trabajo sedentario | F26: =IF(A26="","",IF(B26<0,"ERROR",IF(B26>24,"REVISAR","OK"))) -> OK
A27: Trabajo doméstico general | B27: 1 | C27: =IF(A27="","",IFERROR(INDEX(LISTAS!$L$2:$L$16,MATCH(A27,LISTAS!$K$2:$K$16,0)),"")) -> 2.8 | D27: =IF(A27="","",N(B27)*N(C27)) -> 2.8 | E27: =IF(A27="","",IFERROR(INDEX(LISTAS!$M$2:$M$16,MATCH(A27,LISTAS!$K$2:$K$16,0)),"Editable")) -> Actividad doméstica | F27: =IF(A27="","",IF(B27<0,"ERROR",IF(B27>24,"REVISAR","OK"))) -> OK
A28: Conducir automóvil | B28: 1 | C28: =IF(A28="","",IFERROR(INDEX(LISTAS!$L$2:$L$16,MATCH(A28,LISTAS!$K$2:$K$16,0)),"")) -> 2 | D28: =IF(A28="","",N(B28)*N(C28)) -> 2 | E28: =IF(A28="","",IFERROR(INDEX(LISTAS!$M$2:$M$16,MATCH(A28,LISTAS!$K$2:$K$16,0)),"Editable")) -> Transporte | F28: =IF(A28="","",IF(B28<0,"ERROR",IF(B28>24,"REVISAR","OK"))) -> OK
A29: Caminar sin carga | B29: 1 | C29: =IF(A29="","",IFERROR(INDEX(LISTAS!$L$2:$L$16,MATCH(A29,LISTAS!$K$2:$K$16,0)),"")) -> 3.2 | D29: =IF(A29="","",N(B29)*N(C29)) -> 3.2 | E29: =IF(A29="","",IFERROR(INDEX(LISTAS!$M$2:$M$16,MATCH(A29,LISTAS!$K$2:$K$16,0)),"Editable")) -> Ritmos variables | F29: =IF(A29="","",IF(B29<0,"ERROR",IF(B29>24,"REVISAR","OK"))) -> OK
A30: Ocio ligero | B30: 3 | C30: =IF(A30="","",IFERROR(INDEX(LISTAS!$L$2:$L$16,MATCH(A30,LISTAS!$K$2:$K$16,0)),"")) -> 1.4 | D30: =IF(A30="","",N(B30)*N(C30)) -> 4.2 | E30: =IF(A30="","",IFERROR(INDEX(LISTAS!$M$2:$M$16,MATCH(A30,LISTAS!$K$2:$K$16,0)),"Editable")) -> TV, conversar | F30: =IF(A30="","",IF(B30<0,"ERROR",IF(B30>24,"REVISAR","OK"))) -> OK
A31: Viaje en bus | B31: 0 | C31: =IF(A31="","",IFERROR(INDEX(LISTAS!$L$2:$L$16,MATCH(A31,LISTAS!$K$2:$K$16,0)),"")) -> 1.2 | D31: =IF(A31="","",N(B31)*N(C31)) -> 0 | E31: =IF(A31="","",IFERROR(INDEX(LISTAS!$M$2:$M$16,MATCH(A31,LISTAS!$K$2:$K$16,0)),"Editable")) -> Transporte sentado | F31: =IF(A31="","",IF(B31<0,"ERROR",IF(B31>24,"REVISAR","OK"))) -> OK
B32: 0 | C32: =IF(A32="","",IFERROR(INDEX(LISTAS!$L$2:$L$16,MATCH(A32,LISTAS!$K$2:$K$16,0)),"")) | D32: =IF(A32="","",N(B32)*N(C32)) | E32: =IF(A32="","",IFERROR(INDEX(LISTAS!$M$2:$M$16,MATCH(A32,LISTAS!$K$2:$K$16,0)),"Editable")) | F32: =IF(A32="","",IF(B32<0,"ERROR",IF(B32>24,"REVISAR","OK")))
B33: 0 | C33: =IF(A33="","",IFERROR(INDEX(LISTAS!$L$2:$L$16,MATCH(A33,LISTAS!$K$2:$K$16,0)),"")) | D33: =IF(A33="","",N(B33)*N(C33)) | E33: =IF(A33="","",IFERROR(INDEX(LISTAS!$M$2:$M$16,MATCH(A33,LISTAS!$K$2:$K$16,0)),"Editable")) | F33: =IF(A33="","",IF(B33<0,"ERROR",IF(B33>24,"REVISAR","OK")))
B34: 0 | C34: =IF(A34="","",IFERROR(INDEX(LISTAS!$L$2:$L$16,MATCH(A34,LISTAS!$K$2:$K$16,0)),"")) | D34: =IF(A34="","",N(B34)*N(C34)) | E34: =IF(A34="","",IFERROR(INDEX(LISTAS!$M$2:$M$16,MATCH(A34,LISTAS!$K$2:$K$16,0)),"Editable")) | F34: =IF(A34="","",IF(B34<0,"ERROR",IF(B34>24,"REVISAR","OK")))
A35: Total horas | B35: =SUM(B23:B34) -> 24 | C35: Suma horas×PAR | E35: =SUM(D23:D34) -> 36 | F35: =IF(B35=24,"OK",IF(B35<24,"FALTAN "&TEXT(24-B35,"0.00")&" h","EXCEDEN "&TEXT(B35-24,"0.00")&" h")) -> OK
A36: PAL factorial | E36: =IF(B35=24,E35/24,"ND") -> 1.5
A37: GET factorial | C37: kcal/d | E37: =IF(ISNUMBER(E36),CALCULOS_ENERGÍA!B15*E36,"ND") -> 1974.612

Sheet MACRONUTRIENTES
A1: NUTRIMETRÍA · NMX-43 | MACRONUTRIENTES
A3: Distribución por porcentaje o proteína g/kg, conversión 4-9-4, DRI y AMDR.
A5: =HYPERLINK("#'INICIO'!A1","INICIO") -> INICIO | B5: =HYPERLINK("#'DATOS'!A1","DATOS") -> DATOS | C5: =HYPERLINK("#'ENERGÍA'!A1","ENERGÍA") -> ENERGÍA | D5: =HYPERLINK("#'MACRONUTRIENTES'!A1","MACRONUTRIENTES") -> MACRONUTRIENTES | E5: =HYPERLINK("#'AGUA_FIBRA'!A1","AGUA/FIBRA") -> AGUA/FIBRA | F5: =HYPERLINK("#'FICHA_NUTRIENTE'!A1","FICHA/NUTRIENTE") -> FICHA/NUTRIENTE | G5: =HYPERLINK("#'RESULTADOS'!A1","RESULTADOS") -> RESULTADOS | H5: =HYPERLINK("#'DOCUMENTACIÓN'!A1","DOCUMENTACIÓN") -> DOCUMENTACIÓN | I5: =HYPERLINK("#'COBERTURA'!A1","COBERTURA") -> COBERTURA | J5: =HYPERLINK("#'AUDITORÍA_FINAL'!A1","AUDITORÍA") -> AUDITORÍA
A7: ENTRADAS DE DISTRIBUCIÓN
A8: Energía seleccionada | B8: =CALCULOS_NUTRIENTES!B2 -> 2106.2528 | C8: kcal/d | E8: Componente | F8: g/día | G8: kcal/día | H8: % energía | I8: Referencia | J8: Adecuación
A9: Modo | B9: =CALCULOS_NUTRIENTES!B7 -> Porcentual | E9: Proteína | F9: =CALCULOS_NUTRIENTES!B12 -> 78.98448 | G9: =CALCULOS_NUTRIENTES!B13 -> 315.93792 | H9: =IF(ISNUMBER(G9),G9/CALCULOS_NUTRIENTES!B2*100,"ND") -> 15 | I9: =CALCULOS_NUTRIENTES!B21 -> 46 | J9: =CALCULOS_NUTRIENTES!B23 -> 171.70539
A10: Peso | B10: =CALCULOS_NUTRIENTES!B6 -> 56 | C10: kg | E10: Lípidos | F10: =CALCULOS_NUTRIENTES!B14 -> 70.208427 | G10: =CALCULOS_NUTRIENTES!B15 -> 631.87584 | H10: =IF(ISNUMBER(G10),G10/CALCULOS_NUTRIENTES!B2*100,"ND") -> 30 | I10: =CALCULOS_NUTRIENTES!B26 -> 20–35
A11: Proteína seleccionada | B11: =CALCULOS_NUTRIENTES!B8 -> 1 | C11: g/kg/d | E11: Carbohidratos | F11: =CALCULOS_NUTRIENTES!B16 -> 289.60976 | G11: =CALCULOS_NUTRIENTES!B17 -> 1158.439 | H11: =IF(ISNUMBER(G11),G11/CALCULOS_NUTRIENTES!B2*100,"ND") -> 55 | I11: =CALCULOS_NUTRIENTES!B22 -> 130 | J11: =CALCULOS_NUTRIENTES!B24 -> 222.77674
A12: Proteína | B12: =CALCULOS_NUTRIENTES!B9 -> 15 | C12: % | E12: TOTAL | G12: =CALCULOS_NUTRIENTES!B18 -> 2106.2528 | H12: =CALCULOS_NUTRIENTES!B19 -> 100
A13: Lípidos | B13: =CALCULOS_NUTRIENTES!B10 -> 30 | C13: %
A14: CHO | B14: =CALCULOS_NUTRIENTES!B11 -> 55 | C14: %
A17: REFERENCIAS Y CONTROL | E17: Interpretación académica: • RDA/AI y AMDR son referencias diferentes. • El modo porcentual convierte energía a gramos mediante factores 4-9-4. • El modo g/kg fija proteína, conserva el porcentaje de grasa y calcula CHO como residuo. • Un porcentaje de adecuación no sustituye la evaluación clínica ni implica seguridad por sobre la referencia.
A18: Indicador | B18: Resultado | C18: Interpretación
A19: RDA/AI proteína | B19: =CALCULOS_NUTRIENTES!B21 -> 46 | C19: g/día
A20: RDA/AI carbohidratos | B20: =CALCULOS_NUTRIENTES!B22 -> 130 | C20: g/día
A21: AMDR proteína | B21: =CALCULOS_NUTRIENTES!B25 -> 10–35 | C21: % energía
A22: AMDR lípidos | B22: =CALCULOS_NUTRIENTES!B26 -> 20–35 | C22: % energía
A23: AMDR CHO | B23: =CALCULOS_NUTRIENTES!B27 -> 45–65 | C23: % energía
A24: Cierre energético | B24: =CALCULOS_NUTRIENTES!B28 -> CIERRE CORRECTO | C24: Tolerancia configurable

Sheet ÍNDICE_CARGA_GLICÉMICA
A1: NUTRIMETRÍA · NMX-43 | ÍNDICE_CARGA_GLICÉMICA
A3: Cálculo por porción, clasificación y trazabilidad del valor publicado.
A5: =HYPERLINK("#'INICIO'!A1","INICIO") -> INICIO | B5: =HYPERLINK("#'DATOS'!A1","DATOS") -> DATOS | C5: =HYPERLINK("#'ENERGÍA'!A1","ENERGÍA") -> ENERGÍA | D5: =HYPERLINK("#'MACRONUTRIENTES'!A1","MACRONUTRIENTES") -> MACRONUTRIENTES | E5: =HYPERLINK("#'AGUA_FIBRA'!A1","AGUA/FIBRA") -> AGUA/FIBRA | F5: =HYPERLINK("#'FICHA_NUTRIENTE'!A1","FICHA/NUTRIENTE") -> FICHA/NUTRIENTE | G5: =HYPERLINK("#'RESULTADOS'!A1","RESULTADOS") -> RESULTADOS | H5: =HYPERLINK("#'DOCUMENTACIÓN'!A1","DOCUMENTACIÓN") -> DOCUMENTACIÓN | I5: =HYPERLINK("#'COBERTURA'!A1","COBERTURA") -> COBERTURA | J5: =HYPERLINK("#'AUDITORÍA_FINAL'!A1","AUDITORÍA") -> AUDITORÍA
A7: ÍNDICE Y CARGA GLICÉMICA · CÁLCULO EDUCATIVO
A9: Entrada | B9: Valor | C9: Unidad/estado | D9: Fuente o nota | F9: Resultado | G9: Valor | H9: Unidad | I9: Clasificación | J9: Fuente_ID | K9: Estado
A10: Alimento o categoría | B10: Productos lácteos (promedio de categoría) | D10: IG_BASE | F10: Índice glicémico | G10: =B13 -> 35 | I10: =IF(NOT(ISNUMBER(G10)),"NO EVALUABLE",IF(G10<=CONFIG!$B$13,"BAJO",IF(G10<=CONFIG!$B$14,"MEDIO","ALTO"))) -> BAJO | J10: =IF(ISNUMBER(B12),"USUARIO",INDEX(IG_BASE!$H$2:$H$8,MATCH(B10,IG_BASE!$B$2:$B$8,0))) -> SRC-GI-2021 | K10: =IF(ISNUMBER(B12),IF(B16="","FALTA FUENTE MANUAL","MANUAL CON FUENTE"),INDEX(IG_BASE!$J$2:$J$8,MATCH(B10,IG_BASE!$B$2:$B$8,0))) -> VERIFICADO_SECUNDARIO
A11: IG recuperado | B11: =IF(B10="","",INDEX(IG_BASE!$E$2:$E$8,MATCH(B10,IG_BASE!$B$2:$B$8,0))) -> 35 | C11: Glucosa=100 | D11: Automático | F11: Carga glicémica | G11: =IF(AND(ISNUMBER(B13),ISNUMBER(B14)),B13*B14/100,"ND") -> 10.5 | I11: =IF(NOT(ISNUMBER(G11)),"NO EVALUABLE",IF(G11<=CONFIG!$B$15,"BAJA",IF(G11<=CONFIG!$B$16,"MEDIA","ALTA"))) -> MEDIA | J11: =J10 -> SRC-GI-2021 | K11: =K10 -> VERIFICADO_SECUNDARIO
A12: IG manual (opcional) | C12: 0–100 | D12: Sobrescribe el recuperado | F12: Carbohidratos disponibles | G12: =B14 -> 30 | H12: g
A13: IG efectivo | B13: =IF(ISNUMBER(B12),B12,B11) -> 35 | C13: Glucosa=100 | D13: Usado en el cálculo | F13: Escala de IG | G13: Glucosa=100
A14: CHO disponibles por porción | B14: 30 | C14: g | D14: Entrada del usuario | F14: Advertencia | G14: =IF(OR(B10="",NOT(ISNUMBER(B13))),"Faltan datos","El IG puede variar por variedad, madurez, procesamiento, cocción, enfriamiento y composición de la comida.") -> El IG puede variar por variedad, madurez, procesamiento, cocción, enfriamiento y composición de la comida.
A15: Descripción de porción | B15: Porción con 30 g de CHO disponibles | C15: texto | D15: Opcional
A16: Fuente específica del valor manual | C16: texto/URL | D16: Obligatoria si se usa IG manual
A20: FÓRMULA, CLASIFICACIÓN Y USO CORRECTO
A21: Carga glicémica = índice glicémico × gramos de carbohidratos disponibles de la porción ÷ 100. Clasificación configurada: IG bajo ≤55, medio 56–69 y alto ≥70; carga glicémica baja ≤10, media 11–19 y alta ≥20. Los valores de categoría incluidos son promedios educativos y no deben asignarse automáticamente a un producto o preparación concreta. Para un caso real, utilice un valor publicado que coincida con el alimento, método y preparación, y registre la fuente.
A29: TRAZABILIDAD DEL REGISTRO SELECCIONADO
A30: ID | B30: Alimento publicado | C30: Preparación/alcance | D30: Ámbito | E30: IG | F30: Escala | G30: Año | H30: Fuente_ID | I30: Observaciones | J30: Estado
A31: =IF(B10="","",INDEX(IG_BASE!$A$2:$A$8,MATCH(B10,IG_BASE!$B$2:$B$8,0))) -> IG-DAIRY-CAT | B31: =IF(B10="","",INDEX(IG_BASE!$B$2:$B$8,MATCH(B10,IG_BASE!$B$2:$B$8,0))) -> Productos lácteos (promedio de categoría) | C31: =IF(B10="","",INDEX(IG_BASE!$C$2:$C$8,MATCH(B10,IG_BASE!$B$2:$B$8,0))) -> Promedio de múltiples productos | D31: =IF(B10="","",INDEX(IG_BASE!$D$2:$D$8,MATCH(B10,IG_BASE!$B$2:$B$8,0))) -> Internacional | E31: =IF(B10="","",INDEX(IG_BASE!$E$2:$E$8,MATCH(B10,IG_BASE!$B$2:$B$8,0))) -> 35 | F31: =IF(B10="","",INDEX(IG_BASE!$F$2:$F$8,MATCH(B10,IG_BASE!$B$2:$B$8,0))) -> Glucosa=100 | G31: =IF(B10="","",INDEX(IG_BASE!$G$2:$G$8,MATCH(B10,IG_BASE!$B$2:$B$8,0))) -> 2021 | H31: =IF(B10="","",INDEX(IG_BASE!$H$2:$H$8,MATCH(B10,IG_BASE!$B$2:$B$8,0))) -> SRC-GI-2021 | I31: =IF(B10="","",INDEX(IG_BASE!$I$2:$I$8,MATCH(B10,IG_BASE!$B$2:$B$8,0))) -> Promedio de categoría; composición y azúcares añadidos modifican el resultado. | J31: =IF(B10="","",INDEX(IG_BASE!$J$2:$J$8,MATCH(B10,IG_BASE!$B$2:$B$8,0))) -> VERIFICADO_SECUNDARIO

Sheet AGUA_FIBRA
A1: NUTRIMETRÍA · NMX-43 | AGUA_FIBRA
A3: AI de agua total y fibra según edad, sexo y estado fisiológico.
A5: =HYPERLINK("#'INICIO'!A1","INICIO") -> INICIO | B5: =HYPERLINK("#'DATOS'!A1","DATOS") -> DATOS | C5: =HYPERLINK("#'ENERGÍA'!A1","ENERGÍA") -> ENERGÍA | D5: =HYPERLINK("#'MACRONUTRIENTES'!A1","MACRONUTRIENTES") -> MACRONUTRIENTES | E5: =HYPERLINK("#'AGUA_FIBRA'!A1","AGUA/FIBRA") -> AGUA/FIBRA | F5: =HYPERLINK("#'FICHA_NUTRIENTE'!A1","FICHA/NUTRIENTE") -> FICHA/NUTRIENTE | G5: =HYPERLINK("#'RESULTADOS'!A1","RESULTADOS") -> RESULTADOS | H5: =HYPERLINK("#'DOCUMENTACIÓN'!A1","DOCUMENTACIÓN") -> DOCUMENTACIÓN | I5: =HYPERLINK("#'COBERTURA'!A1","COBERTURA") -> COBERTURA | J5: =HYPERLINK("#'AUDITORÍA_FINAL'!A1","AUDITORÍA") -> AUDITORÍA
A7: AGUA Y FIBRA · REFERENCIAS DRI Y ADECUACIÓN
A9: Entrada | B9: Valor | C9: Unidad | D9: Procedencia | F9: Indicador | G9: Referencia | H9: Unidad | I9: Ingesta | J9: Adecuación (%) | K9: Estado
A10: Agua total ingresada | B10: =DATOS!B30 -> 2.5 | C10: L/d | D10: DATOS | F10: Agua total | G10: =CALCULOS_ADECUACIÓN!B7 -> 2.7 | H10: L/d | I10: =CALCULOS_ADECUACIÓN!B5 -> 2.5 | J10: =CALCULOS_ADECUACIÓN!B9 -> 92.592593 | K10: =CALCULOS_ADECUACIÓN!B11 -> DENTRO DEL RANGO
A11: Fibra dietaria ingresada | B11: =DATOS!B31 -> 25 | C11: g/d | D11: DATOS | F11: Fibra dietaria | G11: =CALCULOS_ADECUACIÓN!B8 -> 25 | H11: g/d | I11: =CALCULOS_ADECUACIÓN!B6 -> 25 | J11: =CALCULOS_ADECUACIÓN!B10 -> 100 | K11: =CALCULOS_ADECUACIÓN!B12 -> DENTRO DEL RANGO
A15: INTERPRETACIÓN Y LÍMITES
A16: El valor de agua corresponde a agua total (bebidas + humedad de los alimentos) cuando se utiliza la AI de los DRI. La cifra no debe interpretarse como una prescripción universal de agua para beber. La fibra se muestra como AI y puede no estar establecida para lactantes menores de 1 año en esta matriz. Los semáforos usan límites técnicos configurables (90–110 %) y no reemplazan la evaluación clínica.
A24: DATOS DEL PERFIL
A25: Variable | B25: Valor | C25: Unidad
A26: Edad | B26: =CALCULOS_ADECUACIÓN!B2 -> 25 | C26: años
A27: Sexo | B27: =CALCULOS_ADECUACIÓN!B3 -> Femenino
A28: Estado fisiológico | B28: =CALCULOS_ADECUACIÓN!B4 -> Ninguno

Sheet NUTRIENTES
A1: NUTRIMETRÍA · NMX-43 | NUTRIENTES
A3: Estructura de NUTRIENTES preparada para el desarrollo por fases.
A5: =HYPERLINK("#'INICIO'!A1","INICIO") -> INICIO | B5: =HYPERLINK("#'DATOS'!A1","DATOS") -> DATOS | C5: =HYPERLINK("#'ENERGÍA'!A1","ENERGÍA") -> ENERGÍA | D5: =HYPERLINK("#'MACRONUTRIENTES'!A1","MACRONUTRIENTES") -> MACRONUTRIENTES | E5: =HYPERLINK("#'AGUA_FIBRA'!A1","AGUA/FIBRA") -> AGUA/FIBRA | F5: =HYPERLINK("#'FICHA_NUTRIENTE'!A1","FICHA/NUTRIENTE") -> FICHA/NUTRIENTE | G5: =HYPERLINK("#'RESULTADOS'!A1","RESULTADOS") -> RESULTADOS | H5: =HYPERLINK("#'DOCUMENTACIÓN'!A1","DOCUMENTACIÓN") -> DOCUMENTACIÓN | I5: =HYPERLINK("#'COBERTURA'!A1","COBERTURA") -> COBERTURA | J5: =HYPERLINK("#'AUDITORÍA_FINAL'!A1","AUDITORÍA") -> AUDITORÍA
A7: ID | B7: Nombre | C7: Símbolo | D7: Categoría | E7: Subcategoría | F7: Unidad principal | G7: Presente INTA | H7: DRI | I7: UL | J7: Estado ficha | K7: Última revisión
A8: MIN-FE | B8: Hierro | C8: Fe | D8: Mineral | E8: Oligoelemento | F8: mg | G8: Sí | H8: Sí | I8: Sí | J8: VERIFICADO_SECUNDARIO | K8: 46237
A9: MIN-ZN | B9: Zinc | C9: Zn | D9: Mineral | E9: Oligoelemento | F9: mg | G9: Sí | H9: Sí | I9: Sí | J9: VERIFICADO_SECUNDARIO | K9: 46237
A10: MIN-CU | B10: Cobre | C10: Cu | D10: Mineral | E10: Oligoelemento | F10: mg | G10: Sí | H10: Sí | I10: Sí | J10: VERIFICADO_SECUNDARIO | K10: 46237
A11: MIN-CA | B11: Calcio | C11: Ca | D11: Mineral | E11: Macromineral | F11: mg | G11: Sí | H11: Sí | I11: Sí | J11: VERIFICADO_SECUNDARIO | K11: 46237
A12: MIN-P | B12: Fósforo | C12: P | D12: Mineral | E12: Macromineral | F12: mg | G12: Sí | H12: Sí | I12: Sí | J12: VERIFICADO_SECUNDARIO | K12: 46237
A13: MIN-SE | B13: Selenio | C13: Se | D13: Mineral | E13: Oligoelemento | F13: µg | G13: Sí | H13: Sí | I13: Sí | J13: VERIFICADO_SECUNDARIO | K13: 46237
A14: MIN-K | B14: Potasio | C14: K | D14: Mineral | E14: Electrolito | F14: mg | G14: Sí | H14: Sí | I14: No establecido | J14: VERIFICADO_SECUNDARIO | K14: 46237
A15: MIN-MG | B15: Magnesio | C15: Mg | D15: Mineral | E15: Macromineral | F15: mg | G15: Sí | H15: Sí | I15: Sí | J15: VERIFICADO_SECUNDARIO | K15: 46237
A16: MIN-NA | B16: Sodio | C16: Na | D16: Mineral | E16: Electrolito | F16: mg | G16: Sí | H16: Sí | I16: Según sistema | J16: VERIFICADO_SECUNDARIO | K16: 46237
A17: MIN-CL | B17: Cloruro | C17: Cl⁻ | D17: Mineral | E17: Electrolito | F17: mg | G17: No | H17: Sí | I17: Sí | J17: VERIFICADO_SECUNDARIO | K17: 46237
A18: VIT-A | B18: Vitamina A | C18: RAE | D18: Vitamina liposoluble | E18: Liposoluble | F18: µg RAE | G18: Sí | H18: Sí | I18: Sí | J18: VERIFICADO_SECUNDARIO | K18: 46237
A19: VIT-D | B19: Vitamina D | C19: D | D19: Vitamina liposoluble | E19: Liposoluble | F19: µg | G19: Sí | H19: Sí | I19: Sí | J19: VERIFICADO_SECUNDARIO | K19: 46237
... A30: VIT-B12 | B30: Cobalamina | C30: B12 | D30: Vitamina hidrosoluble | E30: Complejo B | F30: µg | G30: Sí | H30: Sí | I30: No establecido | J30: VERIFICADO_SECUNDARIO | K30: 46237

Sheet FICHA_NUTRIENTE
A1: NUTRIMETRÍA · NMX-43 | FICHA DE NUTRIENTE
A3: Ficha automatizada de consulta rápida para 23 vitaminas y minerales.
A5: =HYPERLINK("#'INICIO'!A1","INICIO") -> INICIO | B5: =HYPERLINK("#'DATOS'!A1","DATOS") -> DATOS | C5: =HYPERLINK("#'ENERGÍA'!A1","ENERGÍA") -> ENERGÍA | D5: =HYPERLINK("#'MACRONUTRIENTES'!A1","MACRONUTRIENTES") -> MACRONUTRIENTES | E5: =HYPERLINK("#'AGUA_FIBRA'!A1","AGUA/FIBRA") -> AGUA/FIBRA | F5: =HYPERLINK("#'FICHA_NUTRIENTE'!A1","FICHA/NUTRIENTE") -> FICHA/NUTRIENTE | G5: =HYPERLINK("#'RESULTADOS'!A1","RESULTADOS") -> RESULTADOS | H5: =HYPERLINK("#'DOCUMENTACIÓN'!A1","DOCUMENTACIÓN") -> DOCUMENTACIÓN | I5: =HYPERLINK("#'COBERTURA'!A1","COBERTURA") -> COBERTURA | J5: =HYPERLINK("#'AUDITORÍA_FINAL'!A1","AUDITORÍA") -> AUDITORÍA
A7: NUTRIENTE | C7: Zinc | E7: ID | G7: =IFERROR(INDEX(NUTRIENTES!$A$8:$A$30,MATCH($C$7,NUTRIENTES!$B$8:$B$30,0)),"") -> MIN-ZN | I7: CLASE | K7: =IFERROR(INDEX(NUTRIENTES!$D$8:$D$30,MATCH($C$7,NUTRIENTES!$B$8:$B$30,0)),"") -> Mineral | M7: UNIDAD | N7: =IFERROR(INDEX(NUTRIENTES!$F$8:$F$30,MATCH($C$7,NUTRIENTES!$B$8:$B$30,0)),"") -> mg
A8: Use la flecha de la celda amarilla para seleccionar el nutriente. | C8: =IFERROR(INDEX(NUTRIENTES!$A$8:$A$30,MATCH($C$7,NUTRIENTES!$B$8:$B$30,0)),"") -> MIN-ZN
A10: 1. IDENTIFICACIÓN | E10: 2. FUNCIONES FISIOLÓGICAS | J10: 3. IMPORTANCIA CLÍNICA
A11: =IFERROR(INDEX(FICHAS_BASE!$D$2:$D$461,MATCH($C$8&"|IDENTIFICACION",FICHAS_BASE!$H$2:$H$461,0)),"") -> Zinc (Zn). Mineral traza presente en proteínas y enzimas; no posee un depósito corporal especializado de gran tamaño. | E11: =IFERROR(INDEX(FICHAS_BASE!$D$2:$D$461,MATCH($C$8&"|FUNCIONES",FICHAS_BASE!$H$2:$H$461,0)),"") -> • Actividad catalítica de numerosas enzimas. • Síntesis de ADN y proteínas. • Crecimiento, desarrollo y cicatrización. • Función inmunitaria y percepción del gusto. | J11: =IFERROR(INDEX(FICHAS_BASE!$D$2:$D$461,MATCH($C$8&"|ORGANOS_TEJIDOS",FICHAS_BASE!$H$2:$H$461,0)),"")&CHAR(10)&CHAR(10)&IFERROR(INDEX(FICHAS_BASE!$D$2:$D$461,MATCH($C$8&"|IMPORTANCIA_CLINICA",FICHAS_BASE!$H$2:$H$461,0)),"") -> Intestino, hígado, páncreas, piel, sistema inmunitario, músculo y hueso. La homeostasis depende de absorción intestinal y pérdidas. La deficiencia afecta crecimiento, inmunidad y cicatrización.
A17: 4. METABOLISMO RESUMIDO
A18: =IFERROR(INDEX(FICHAS_BASE!$D$2:$D$461,MATCH($C$8&"|METABOLISMO",FICHAS_BASE!$H$2:$H$461,0)),"") -> Ingesta → absorción en intestino delgado → transporte unido principalmente a albúmina → distribución tisular → intercambio rápido con reservas celulares → excreción sobre todo fecal.
A23: 5. ABSORCIÓN | E23: 6. TRANSPORTE Y ALMACENAMIENTO | J23: 7. EXCRECIÓN
A24: =IFERROR(INDEX(FICHAS_BASE!$D$2:$D$461,MATCH($C$8&"|ABSORCION",FICHAS_BASE!$H$2:$H$461,0)),"") -> La absorción ocurre en intestino delgado mediante transportadores regulados por el estado de zinc y la composición de la dieta. | E24: ="Transporte: "&IFERROR(INDEX(FICHAS_BASE!$D$2:$D$461,MATCH($C$8&"|TRANSPORTE",FICHAS_BASE!$H$2:$H$461,0)),"")&CHAR(10)&CHAR(10)&"Almacenamiento: "&IFERROR(INDEX(FICHAS_BASE!$D$2:$D$461,MATCH($C$8&"|ALMACENAMIENTO",FICHAS_BASE!$H$2:$H$461,0)),"") -> Transporte: Circula unido sobre todo a albúmina y otras proteínas; entra y sale de células mediante familias de transportadores ZIP y ZnT. Almacenamiento: No hay un órgano de depósito específico; músculo y hueso contienen gran parte del zinc corporal por su masa. | J24: =IFERROR(INDEX(FICHAS_BASE!$D$2:$D$461,MATCH($C$8&"|EXCRECION",FICHAS_BASE!$H$2:$H$461,0)),"") -> Principalmente por heces; también orina, sudor, semen, menstruación y descamación.
A30: 8. BIODISPONIBILIDAD | H30: 9. FUENTES ALIMENTARIAS
A31: ="Favorece: "&IFERROR(INDEX(FICHAS_BASE!$D$2:$D$461,MATCH($C$8&"|BIODISPONIBILIDAD_MEJORA",FICHAS_BASE!$H$2:$H$461,0)),"")&CHAR(10)&CHAR(10)&"Reduce: "&IFERROR(INDEX(FICHAS_BASE!$D$2:$D$461,MATCH($C$8&"|BIODISPONIBILIDAD_REDUCE",FICHAS_BASE!$H$2:$H$461,0)),"") -> Favorece: Proteínas animales y fermentación/germinación que reduzcan fitatos pueden mejorar la biodisponibilidad. Reduce: Fitatos reducen la absorción; dietas vegetales no planificadas pueden requerir atención a la biodisponibilidad. | H31: =IFERROR(INDEX(FICHAS_BASE!$D$2:$D$461,MATCH($C$8&"|FUENTES_ALIMENTARIAS",FICHAS_BASE!$H$2:$H$461,0)),"") -> Ostras y otros mariscos; carne bovina; aves; lácteos; legumbres, semillas y frutos secos.
A37: 10. DÉFICIT Y EXCESO | H37: 11. APLICACIÓN CLÍNICA
A38: ="Déficit: "&IFERROR(INDEX(FICHAS_BASE!$D$2:$D$461,MATCH($C$8&"|DEFICIT",FICHAS_BASE!$H$2:$H$461,0)),"")&CHAR(10)&CHAR(10)&"Exceso: "&IFERROR(INDEX(FICHAS_BASE!$D$2:$D$461,MATCH($C$8&"|EXCESO",FICHAS_BASE!$H$2:$H$461,0)),"") -> Déficit: Retraso del crecimiento, alopecia, dermatitis, diarrea, alteración del gusto, mala cicatrización e inmunidad deteriorada. Riesgo en malabsorción, cirugía bariátrica, alcoholismo y dietas muy altas en fitatos. Exceso: Dosis elevadas sostenidas pueden causar náuseas, reducir cobre, alterar perfil lipídico y deteriorar función inmunitaria. | H38: =IFERROR(INDEX(FICHAS_BASE!$D$2:$D$461,MATCH($C$8&"|APLICACION_CLINICA",FICHAS_BASE!$H$2:$H$461,0)),"") -> En diarrea crónica, malabsorción o cicatrización deficiente, revisar ingesta, pérdidas y contexto clínico antes de atribuir los síntomas al zinc.
A44: 12. INTERACCIONES DESTACADAS
A45: =IFERROR(INDEX(FICHAS_BASE!$D$2:$D$461,MATCH($C$8&"|INTERACCIONES_RESUMEN",FICHAS_BASE!$H$2:$H$461,0)),"") -> Cobre | Nutriente–nutriente | Dosis altas de zinc reducen cobre Vigilar suplementos crónicos de zinc. Quinolonas y tetraciclinas | Medicamento–nutriente | Reduce absorción de ambos Separación horaria solo según indicación farmacéutica/médica.
A51: 13. BIOMARCADORES | H51: 14. PERLAS CLÍNICAS
A52: =IFERROR(INDEX(FICHAS_BASE!$D$2:$D$461,MATCH($C$8&"|BIOMARCADORES_RESUMEN",FICHAS_BASE!$H$2:$H$461,0)),"") -> Zinc plasmático/sérico | Estado circulante de zinc Limitación: Sensibilidad limitada; cambia con ayuno, hora, inflamación y embarazo. | H52: =IFERROR(INDEX(FICHAS_BASE!$D$2:$D$461,MATCH($C$8&"|PERLAS",FICHAS_BASE!$H$2:$H$461,0)),"") -> • Zinc alto en suplementos puede inducir deficiencia de cobre. • El zinc plasmático cambia con inflamación y hora del día. • Fitatos importan tanto como la cantidad ingerida. • No usar zinc para todas las infecciones sin indicación.
A59: 15. REFERENCIAS Y ADVERTENCIA
A60: =IFERROR(INDEX(FICHAS_BASE!$D$2:$D$461,MATCH($C$8&"|REFERENCIAS",FICHAS_BASE!$H$2:$H$461,0)),"")&CHAR(10)&CHAR(10)&IFERROR(INDEX(FICHAS_BASE!$D$2:$D$461,MATCH($C$8&"|ADVERTENCIA",FICHAS_BASE!$H$2:$H$461,0)),"") -> 1) SRC-ODS-ZINC: fuente institucional principal para funciones, metabolismo, déficit, exceso e interacciones. 2) SRC-DRI-SUMMARY: referencia normativa o clínica complementaria para requerimientos e interpretación. Material educativo. No sustituye evaluación clínica, diagnóstico, tratamiento ni indicaciones farmacológicas.
A66: =HYPERLINK("#'FUENTES'!A1","VER FUENTES") -> VER FUENTES | E66: =HYPERLINK("#'INTERACCIONES'!A1","VER INTERACCIONES") -> VER INTERACCIONES | I66: =HYPERLINK("#'BIOMARCADORES'!A1","VER BIOMARCADORES") -> VER BIOMARCADORES | M66: =HYPERLINK("#'CASOS_CLÍNICOS'!A1","VER CASO") -> VER CASO

Sheet FUENTES_ALIMENTARIAS
A1: NUTRIMETRÍA · NMX-43 | FUENTES_ALIMENTARIAS
A3: Selección de alimentos INTA, cálculo por gramaje, porcentaje de referencia y ranking por 100 g.
A5: =HYPERLINK("#'INICIO'!A1","INICIO") -> INICIO | B5: =HYPERLINK("#'DATOS'!A1","DATOS") -> DATOS | C5: =HYPERLINK("#'ENERGÍA'!A1","ENERGÍA") -> ENERGÍA | D5: =HYPERLINK("#'MACRONUTRIENTES'!A1","MACRONUTRIENTES") -> MACRONUTRIENTES | E5: =HYPERLINK("#'AGUA_FIBRA'!A1","AGUA/FIBRA") -> AGUA/FIBRA | F5: =HYPERLINK("#'FICHA_NUTRIENTE'!A1","FICHA/NUTRIENTE") -> FICHA/NUTRIENTE | G5: =HYPERLINK("#'RESULTADOS'!A1","RESULTADOS") -> RESULTADOS | H5: =HYPERLINK("#'DOCUMENTACIÓN'!A1","DOCUMENTACIÓN") -> DOCUMENTACIÓN | I5: =HYPERLINK("#'COBERTURA'!A1","COBERTURA") -> COBERTURA | J5: =HYPERLINK("#'AUDITORÍA_FINAL'!A1","AUDITORÍA") -> AUDITORÍA
A7: NUTRIENTE | C7: Zinc | E7: ID | G7: =IFERROR(IFERROR(INDEX(NUTRIENTES!$A$8:$A$30,MATCH($C$7,NUTRIENTES!$B$8:$B$30,0)),""),"") -> MIN-ZN | I7: ENCABEZADO INTA | K7: =IFERROR(IFERROR(INDEX(LISTAS!$AH$2:$AH$24,MATCH($G$7,LISTAS!$AF$2:$AF$24,0)),""),"") -> Zinc (mg) | M7: UNIDAD | N7: =IFERROR(IFERROR(INDEX(LISTAS!$AI$2:$AI$24,MATCH($G$7,LISTAS!$AF$2:$AF$24,0)),""),"") -> mg
A8: Use la flecha de la celda amarilla para seleccionar el nutriente.
A9: OBJETIVO | E9: TIPO | I9: LÍMITE | M9: DISPONIBLE INTA
A10: =IFERROR(IFERROR(INDEX(DRI_BASE!$T$2:$T$469,MATCH(1,INDEX((DRI_BASE!$B$2:$B$469=$G$7)*(DRI_BASE!$D$2:$D$469<=DATOS!$F$9)*(DRI_BASE!$E$2:$E$469>DATOS!$F$9)*(((DRI_BASE!$C$2:$C$469=DATOS!$B$13)+(DRI_BASE!$C$2:$C$469="Ambos"))>0)*(DRI_BASE!$G$2:$G$469=DATOS!$B$16),0),0)),"ND"),"ND") -> 8 | E10: =IFERROR(IFERROR(INDEX(DRI_BASE!$R$2:$R$469,MATCH(1,INDEX((DRI_BASE!$B$2:$B$469=$G$7)*(DRI_BASE!$D$2:$D$469<=DATOS!$F$9)*(DRI_BASE!$E$2:$E$469>DATOS!$F$9)*(((DRI_BASE!$C$2:$C$469=DATOS!$B$13)+(DRI_BASE!$C$2:$C$469="Ambos"))>0)*(DRI_BASE!$G$2:$G$469=DATOS!$B$16),0),0)),"ND"),"ND") -> RDA | I10: =IFERROR(IFERROR(INDEX(DRI_BASE!$U$2:$U$469,MATCH(1,INDEX((DRI_BASE!$B$2:$B$469=$G$7)*(DRI_BASE!$D$2:$D$469<=DATOS!$F$9)*(DRI_BASE!$E$2:$E$469>DATOS!$F$9)*(((DRI_BASE!$C$2:$C$469=DATOS!$B$13)+(DRI_BASE!$C$2:$C$469="Ambos"))>0)*(DRI_BASE!$G$2:$G$469=DATOS!$B$16),0),0)),"ND"),"ND") -> 40 | M10: =IFERROR(IFERROR(INDEX(LISTAS!$AJ$2:$AJ$24,MATCH($G$7,LISTAS!$AF$2:$AF$24,0)),"No"),"No") -> Sí
A12: # | B12: Alimento | C12: Grupo | D12: Estado | E12: Porción doméstica | F12: Gramaje | G12: Valor/100 g | H12: Aporte | I12: Unidad | J12: % referencia | K12: ND | L12: Estado dato | M12: Fuente | N12: Observación
A13: 1 | B13: Mango | C13: =IF($B13="","",IFERROR(IFERROR(INDEX(ALIMENTOS_INTA!$F$8:$F$625,MATCH($B13,ALIMENTOS_INTA!$E$8:$E$625,0)),""),"")) -> Frutas | D13: =IF($B13="","",IFERROR(IFERROR(INDEX(ALIMENTOS_INTA!$G$8:$G$625,MATCH($B13,ALIMENTOS_INTA!$E$8:$E$625,0)),""),"")) -> sin documentar | E13: 1 taza aprox. | F13: 150 | G13: =IF($B13="","",IF($K$7="","ND",IF(ISNUMBER((INDEX(ALIMENTOS_INTA!$D$8:$AO$625,(MATCH($B13,ALIMENTOS_INTA!$E$8:$E$625,0)),(MATCH($K$7,ALIMENTOS_INTA!$D$7:$AO$7,0))))),(INDEX(ALIMENTOS_INTA!$D$8:$AO$625,(MATCH($B13,ALIMENTOS_INTA!$E$8:$E$625,0)),(MATCH($K$7,ALIMENTOS_INTA!$D$7:$AO$7,0)))),"ND"))) -> 0.1 | H13: =IF(AND(ISNUMBER($G13),ISNUMBER($F13),$F13>=0),$G13*$F13/100,IF($B13="","",IF($G13="ND","ND",""))) -> 0.15 | I13: =$N$7 -> mg | J13: =IF(AND(ISNUMBER($H13),ISNUMBER($A$10),$A$10>0),$H13/$A$10*100,"ND") -> 1.875 | K13: =IF($B13="","",IF($G13="ND",1,0)) -> 0 | L13: =IF($B13="","SIN ALIMENTO",IF($G13="ND","ND FUENTE",IF(NOT(ISNUMBER($F13)),"FALTA GRAMAJE","DISPONIBLE"))) -> DISPONIBLE | M13: =IF($B13="","","SRC-NMX21") -> SRC-NMX21 | N13: =IF($B13="","",IF($G13="ND","El nutriente no está informado para este alimento.","Aporte = valor por 100 g × gramaje / 100.")) -> Aporte = valor por 100 g × gramaje / 100.
A14: 2 | B14: Higado de vacuno cocido | C14: =IF($B14="","",IFERROR(IFERROR(INDEX(ALIMENTOS_INTA!$F$8:$F$625,MATCH($B14,ALIMENTOS_INTA!$E$8:$E$625,0)),""),"")) -> Carnes y Vísceras | D14: =IF($B14="","",IFERROR(IFERROR(INDEX(ALIMENTOS_INTA!$G$8:$G$625,MATCH($B14,ALIMENTOS_INTA!$E$8:$E$625,0)),""),"")) -> sin documentar | E14: 1 porción | F14: 100 | G14: =IF($B14="","",IF($K$7="","ND",IF(ISNUMBER((INDEX(ALIMENTOS_INTA!$D$8:$AO$625,(MATCH($B14,ALIMENTOS_INTA!$E$8:$E$625,0)),(MATCH($K$7,ALIMENTOS_INTA!$D$7:$AO$7,0))))),(INDEX(ALIMENTOS_INTA!$D$8:$AO$625,(MATCH($B14,ALIMENTOS_INTA!$E$8:$E$625,0)),(MATCH($K$7,ALIMENTOS_INTA!$D$7:$AO$7,0)))),"ND"))) -> 5.3 | H14: =IF(AND(ISNUMBER($G14),ISNUMBER($F14),$F14>=0),$G14*$F14/100,IF($B14="","",IF($G14="ND","ND",""))) -> 5.3 | I14: =$N$7 -> mg | J14: =IF(AND(ISNUMBER($H14),ISNUMBER($A$10),$A$10>0),$H14/$A$10*100,"ND") -> 66.25 | K14: =IF($B14="","",IF($G14="ND",1,0)) -> 0 | L14: =IF($B14="","SIN ALIMENTO",IF($G14="ND","ND FUENTE",IF(NOT(ISNUMBER($F14)),"FALTA GRAMAJE","DISPONIBLE"))) -> DISPONIBLE | M14: =IF($B14="","","SRC-NMX21") -> SRC-NMX21 | N14: =IF($B14="","",IF($G14="ND","El nutriente no está informado para este alimento.","Aporte = valor por 100 g × gramaje / 100.")) -> Aporte = valor por 100 g × gramaje / 100.
A15: 3 | B15: Espinaca cocida | C15: =IF($B15="","",IFERROR(IFERROR(INDEX(ALIMENTOS_INTA!$F$8:$F$625,MATCH($B15,ALIMENTOS_INTA!$E$8:$E$625,0)),""),"")) -> Verduras y hortalizas | D15: =IF($B15="","",IFERROR(IFERROR(INDEX(ALIMENTOS_INTA!$G$8:$G$625,MATCH($B15,ALIMENTOS_INTA!$E$8:$E$625,0)),""),"")) -> sin documentar | E15: 1 porción | F15: 100 | G15: =IF($B15="","",IF($K$7="","ND",IF(ISNUMBER((INDEX(ALIMENTOS_INTA!$D$8:$AO$625,(MATCH($B15,ALIMENTOS_INTA!$E$8:$E$625,0)),(MATCH($K$7,ALIMENTOS_INTA!$D$7:$AO$7,0))))),(INDEX(ALIMENTOS_INTA!$D$8:$AO$625,(MATCH($B15,ALIMENTOS_INTA!$E$8:$E$625,0)),(MATCH($K$7,ALIMENTOS_INTA!$D$7:$AO$7,0)))),"ND"))) -> 0.8 | H15: =IF(AND(ISNUMBER($G15),ISNUMBER($F15),$F15>=0),$G15*$F15/100,IF($B15="","",IF($G15="ND","ND",""))) -> 0.8 | I15: =$N$7 -> mg | J15: =IF(AND(ISNUMBER($H15),ISNUMBER($A$10),$A$10>0),$H15/$A$10*100,"ND") -> 10 | K15: =IF($B15="","",IF($G15="ND",1,0)) -> 0 | L15: =IF($B15="","SIN ALIMENTO",IF($G15="ND","ND FUENTE",IF(NOT(ISNUMBER($F15)),"FALTA GRAMAJE","DISPONIBLE"))) -> DISPONIBLE | M15: =IF($B15="","","SRC-NMX21") -> SRC-NMX21 | N15: =IF($B15="","",IF($G15="ND","El nutriente no está informado para este alimento.","Aporte = valor por 100 g × gramaje / 100.")) -> Aporte = valor por 100 g × gramaje / 100.
A16: 4 | B16: Huevo entero cocido | C16: =IF($B16="","",IFERROR(IFERROR(INDEX(ALIMENTOS_INTA!$F$8:$F$625,MATCH($B16,ALIMENTOS_INTA!$E$8:$E$625,0)),""),"")) -> HUEVOS | D16: =IF($B16="","",IFERROR(IFERROR(INDEX(ALIMENTOS_INTA!$G$8:$G$625,MATCH($B16,ALIMENTOS_INTA!$E$8:$E$625,0)),""),"")) -> sin documentar | E16: 1 unidad mediana | F16: 50 | G16: =IF($B16="","",IF($K$7="","ND",IF(ISNUMBER((INDEX(ALIMENTOS_INTA!$D$8:$AO$625,(MATCH($B16,ALIMENTOS_INTA!$E$8:$E$625,0)),(MATCH($K$7,ALIMENTOS_INTA!$D$7:$AO$7,0))))),(INDEX(ALIMENTOS_INTA!$D$8:$AO$625,(MATCH($B16,ALIMENTOS_INTA!$E$8:$E$625,0)),(MATCH($K$7,ALIMENTOS_INTA!$D$7:$AO$7,0)))),"ND"))) -> ND | H16: =IF(AND(ISNUMBER($G16),ISNUMBER($F16),$F16>=0),$G16*$F16/100,IF($B16="","",IF($G16="ND","ND",""))) -> ND | I16: =$N$7 -> mg | J16: =IF(AND(ISNUMBER($H16),ISNUMBER($A$10),$A$10>0),$H16/$A$10*100,"ND") -> ND | K16: =IF($B16="","",IF($G16="ND",1,0)) -> 1 | L16: =IF($B16="","SIN ALIMENTO",IF($G16="ND","ND FUENTE",IF(NOT(ISNUMBER($F16)),"FALTA GRAMAJE","DISPONIBLE"))) -> ND FUENTE | M16: =IF($B16="","","SRC-NMX21") -> SRC-NMX21 | N16: =IF($B16="","",IF($G16="ND","El nutriente no está informado para este alimento.","Aporte = valor por 100 g × gramaje / 100.")) -> El nutriente no está informado para este alimento.
A17: 5 | B17: Yogurt natural | C17: =IF($B17="","",IFERROR(IFERROR(INDEX(ALIMENTOS_INTA!$F$8:$F$625,MATCH($B17,ALIMENTOS_INTA!$E$8:$E$625,0)),""),"")) -> Leche y derivados | D17: =IF($B17="","",IFERROR(IFERROR(INDEX(ALIMENTOS_INTA!$G$8:$G$625,MATCH($B17,ALIMENTOS_INTA!$E$8:$E$625,0)),""),"")) -> sin documentar | E17: 1 envase | F17: 170 | G17: =IF($B17="","",IF($K$7="","ND",IF(ISNUMBER((INDEX(ALIMENTOS_INTA!$D$8:$AO$625,(MATCH($B17,ALIMENTOS_INTA!$E$8:$E$625,0)),(MATCH($K$7,ALIMENTOS_INTA!$D$7:$AO$7,0))))),(INDEX(ALIMENTOS_INTA!$D$8:$AO$625,(MATCH($B17,ALIMENTOS_INTA!$E$8:$E$625,0)),(MATCH($K$7,ALIMENTOS_INTA!$D$7:$AO$7,0)))),"ND"))) -> 0.6 | H17: =IF(AND(ISNUMBER($G17),ISNUMBER($F17),$F17>=0),$G17*$F17/100,IF($B17="","",IF($G17="ND","ND",""))) -> 1.02 | I17: =$N$7 -> mg | J17: =IF(AND(ISNUMBER($H17),ISNUMBER($A$10),$A$10>0),$H17/$A$10*100,"ND") -> 12.75 | K17: =IF($B17="","",IF($G17="ND",1,0)) -> 0 | L17: =IF($B17="","SIN ALIMENTO",IF($G17="ND","ND FUENTE",IF(NOT(ISNUMBER($F17)),"FALTA GRAMAJE","DISPONIBLE"))) -> DISPONIBLE | M17: =IF($B17="","","SRC-NMX21") -> SRC-NMX21 | N17: =IF($B17="","",IF($G17="ND","El nutriente no está informado para este alimento.","Aporte = valor por 100 g × gramaje / 100.")) -> Aporte = valor por 100 g × gramaje / 100.
A18: 6 | B18: Leche fluida entera | C18: =IF($B18="","",IFERROR(IFERROR(INDEX(ALIMENTOS_INTA!$F$8:$F$625,MATCH($B18,ALIMENTOS_INTA!$E$8:$E$625,0)),""),"")) -> Leche y derivados | D18: =IF($B18="","",IFERROR(IFERROR(INDEX(ALIMENTOS_INTA!$G$8:$G$625,MATCH($B18,ALIMENTOS_INTA!$E$8:$E$625,0)),""),"")) -> sin documentar | F18: 100 | G18: =IF($B18="","",IF($K$7="","ND",IF(ISNUMBER((INDEX(ALIMENTOS_INTA!$D$8:$AO$625,(MATCH($B18,ALIMENTOS_INTA!$E$8:$E$625,0)),(MATCH($K$7,ALIMENTOS_INTA!$D$7:$AO$7,0))))),(INDEX(ALIMENTOS_INTA!$D$8:$AO$625,(MATCH($B18,ALIMENTOS_INTA!$E$8:$E$625,0)),(MATCH($K$7,ALIMENTOS_INTA!$D$7:$AO$7,0)))),"ND"))) -> 0.4 | H18: =IF(AND(ISNUMBER($G18),ISNUMBER($F18),$F18>=0),$G18*$F18/100,IF($B18="","",IF($G18="ND","ND",""))) -> 0.4 | I18: =$N$7 -> mg | J18: =IF(AND(ISNUMBER($H18),ISNUMBER($A$10),$A$10>0),$H18/$A$10*100,"ND") -> 5 | K18: =IF($B18="","",IF($G18="ND",1,0)) -> 0 | L18: =IF($B18="","SIN ALIMENTO",IF($G18="ND","ND FUENTE",IF(NOT(ISNUMBER($F18)),"FALTA GRAMAJE","DISPONIBLE"))) -> DISPONIBLE | M18: =IF($B18="","","SRC-NMX21") -> SRC-NMX21 | N18: =IF($B18="","",IF($G18="ND","El nutriente no está informado para este alimento.","Aporte = valor por 100 g × gramaje / 100.")) -> Aporte = valor por 100 g × gramaje / 100.
A19: 7 | B19: Leche de Burra | C19: =IF($B19="","",IFERROR(IFERROR(INDEX(ALIMENTOS_INTA!$F$8:$F$625,MATCH($B19,ALIMENTOS_INTA!$E$8:$E$625,0)),""),"")) -> Leche y derivados | D19: =IF($B19="","",IFERROR(IFERROR(INDEX(ALIMENTOS_INTA!$G$8:$G$625,MATCH($B19,ALIMENTOS_INTA!$E$8:$E$625,0)),""),"")) -> sin documentar | F19: 100 | G19: =IF($B19="","",IF($K$7="","ND",IF(ISNUMBER((INDEX(ALIMENTOS_INTA!$D$8:$AO$625,(MATCH($B19,ALIMENTOS_INTA!$E$8:$E$625,0)),(MATCH($K$7,ALIMENTOS_INTA!$D$7:$AO$7,0))))),(INDEX(ALIMENTOS_INTA!$D$8:$AO$625,(MATCH($B19,ALIMENTOS_INTA!$E$8:$E$625,0)),(MATCH($K$7,ALIMENTOS_INTA!$D$7:$AO$7,0)))),"ND"))) -> ND | H19: =IF(AND(ISNUMBER($G19),ISNUMBER($F19),$F19>=0),$G19*$F19/100,IF($B19="","",IF($G19="ND","ND",""))) -> ND | I19: =$N$7 -> mg | J19: =IF(AND(ISNUMBER($H19),ISNUMBER($A$10),$A$10>0),$H19/$A$10*100,"ND") -> ND | K19: =IF($B19="","",IF($G19="ND",1,0)) -> 1 | L19: =IF($B19="","SIN ALIMENTO",IF($G19="ND","ND FUENTE",IF(NOT(ISNUMBER($F19)),"FALTA GRAMAJE","DISPONIBLE"))) -> ND FUENTE | M19: =IF($B19="","","SRC-NMX21") -> SRC-NMX21 | N19: =IF($B19="","",IF($G19="ND","El nutriente no está informado para este alimento.","Aporte = valor por 100 g × gramaje / 100.")) -> El nutriente no está informado para este alimento.
A20: 8 | B20: Semillas de hinojo | C20: =IF($B20="","",IFERROR(IFERROR(INDEX(ALIMENTOS_INTA!$F$8:$F$625,MATCH($B20,ALIMENTOS_INTA!$E$8:$E$625,0)),""),"")) -> Especias | D20: =IF($B20="","",IFERROR(IFERROR(INDEX(ALIMENTOS_INTA!$G$8:$G$625,MATCH($B20,ALIMENTOS_INTA!$E$8:$E$625,0)),""),"")) -> sin documentar | F20: 100 | G20: =IF($B20="","",IF($K$7="","ND",IF(ISNUMBER((INDEX(ALIMENTOS_INTA!$D$8:$AO$625,(MATCH($B20,ALIMENTOS_INTA!$E$8:$E$625,0)),(MATCH($K$7,ALIMENTOS_INTA!$D$7:$AO$7,0))))),(INDEX(ALIMENTOS_INTA!$D$8:$AO$625,(MATCH($B20,ALIMENTOS_INTA!$E$8:$E$625,0)),(MATCH($K$7,ALIMENTOS_INTA!$D$7:$AO$7,0)))),"ND"))) -> 3.7 | H20: =IF(AND(ISNUMBER($G20),ISNUMBER($F20),$F20>=0),$G20*$F20/100,IF($B20="","",IF($G20="ND","ND",""))) -> 3.7 | I20: =$N$7 -> mg | J20: =IF(AND(ISNUMBER($H20),ISNUMBER($A$10),$A$10>0),$H20/$A$10*100,"ND") -> 46.25 | K20: =IF($B20="","",IF($G20="ND",1,0)) -> 0 | L20: =IF($B20="","SIN ALIMENTO",IF($G20="ND","ND FUENTE",IF(NOT(ISNUMBER($F20)),"FALTA GRAMAJE","DISPONIBLE"))) -> DISPONIBLE | M20: =IF($B20="","","SRC-NMX21") -> SRC-NMX21 | N20: =IF($B20="","",IF($G20="ND","El nutriente no está informado para este alimento.","Aporte = valor por 100 g × gramaje / 100.")) -> Aporte = valor por 100 g × gramaje / 100.
A21: 9 | B21: Leche evaporada | C21: =IF($B21="","",IFERROR(IFERROR(INDEX(ALIMENTOS_INTA!$F$8:$F$625,MATCH($B21,ALIMENTOS_INTA!$E$8:$E$625,0)),""),"")) -> Leche y derivados | D21: =IF($B21="","",IFERROR(IFERROR(INDEX(ALIMENTOS_INTA!$G$8:$G$625,MATCH($B21,ALIMENTOS_INTA!$E$8:$E$625,0)),""),"")) -> sin documentar | F21: 100 | G21: =IF($B21="","",IF($K$7="","ND",IF(ISNUMBER((INDEX(ALIMENTOS_INTA!$D$8:$AO$625,(MATCH($B21,ALIMENTOS_INTA!$E$8:$E$625,0)),(MATCH($K$7,ALIMENTOS_INTA!$D$7:$AO$7,0))))),(INDEX(ALIMENTOS_INTA!$D$8:$AO$625,(MATCH($B21,ALIMENTOS_INTA!$E$8:$E$625,0)),(MATCH($K$7,ALIMENTOS_INTA!$D$7:$AO$7,0)))),"ND"))) -> 0.8 | H21: =IF(AND(ISNUMBER($G21),ISNUMBER($F21),$F21>=0),$G21*$F21/100,IF($B21="","",IF($G21="ND","ND",""))) -> 0.8 | I21: =$N$7 -> mg | J21: =IF(AND(ISNUMBER($H21),ISNUMBER($A$10),$A$10>0),$H21/$A$10*100,"ND") -> 10 | K21: =IF($B21="","",IF($G21="ND",1,0)) -> 0 | L21: =IF($B21="","SIN ALIMENTO",IF($G21="ND","ND FUENTE",IF(NOT(ISNUMBER($F21)),"FALTA GRAMAJE","DISPONIBLE"))) -> DISPONIBLE | M21: =IF($B21="","","SRC-NMX21") -> SRC-NMX21 | N21: =IF($B21="","",IF($G21="ND","El nutriente no está informado para este alimento.","Aporte = valor por 100 g × gramaje / 100.")) -> Aporte = valor por 100 g × gramaje / 100.
A22: 10 | B22: Pan trigo | C22: =IF($B22="","",IFERROR(IFERROR(INDEX(ALIMENTOS_INTA!$F$8:$F$625,MATCH($B22,ALIMENTOS_INTA!$E$8:$E$625,0)),""),"")) -> cereales y derivados | D22: =IF($B22="","",IFERROR(IFERROR(INDEX(ALIMENTOS_INTA!$G$8:$G$625,MATCH($B22,ALIMENTOS_INTA!$E$8:$E$625,0)),""),"")) -> sin documentar | F22: 100 | G22: =IF($B22="","",IF($K$7="","ND",IF(ISNUMBER((INDEX(ALIMENTOS_INTA!$D$8:$AO$625,(MATCH($B22,ALIMENTOS_INTA!$E$8:$E$625,0)),(MATCH($K$7,ALIMENTOS_INTA!$D$7:$AO$7,0))))),(INDEX(ALIMENTOS_INTA!$D$8:$AO$625,(MATCH($B22,ALIMENTOS_INTA!$E$8:$E$625,0)),(MATCH($K$7,ALIMENTOS_INTA!$D$7:$AO$7,0)))),"ND"))) -> 1.2 | H22: =IF(AND(ISNUMBER($G22),ISNUMBER($F22),$F22>=0),$G22*$F22/100,IF($B22="","",IF($G22="ND","ND",""))) -> 1.2 | I22: =$N$7 -> mg | J22: =IF(AND(ISNUMBER($H22),ISNUMBER($A$10),$A$10>0),$H22/$A$10*100,"ND") -> 15 | K22: =IF($B22="","",IF($G22="ND",1,0)) -> 0 | L22: =IF($B22="","SIN ALIMENTO",IF($G22="ND","ND FUENTE",IF(NOT(ISNUMBER($F22)),"FALTA GRAMAJE","DISPONIBLE"))) -> DISPONIBLE | M22: =IF($B22="","","SRC-NMX21") -> SRC-NMX21 | N22: =IF($B22="","",IF($G22="ND","El nutriente no está informado para este alimento.","Aporte = valor por 100 g × gramaje / 100.")) -> Aporte = valor por 100 g × gramaje / 100.
A23: TOTAL | H23: =IF(COUNTA($B$13:$B$22)=0,"",SUM(H13:H22)) -> 13.37 | I23: =$N$7 -> mg | J23: =IF(AND(ISNUMBER(H23),ISNUMBER(A10),A10>0),H23/A10*100,"ND") -> 167.125 | K23: =SUM(K13:K22) -> 2 | L23: =IF(COUNTA($B$13:$B$22)=0,"SIN ALIMENTOS",IF(K23>0,"PARCIAL · "&K23&" ND","COMPLETO")) -> PARCIAL · 2 ND | M23: SRC-NMX21 | N23: El total conocido no convierte los datos s/i en cero.
A26: Rango | B26: Alimento | C26: Grupo | D26: Estado | E26: Valor/100 g | F26: Unidad
A27: 1 | B27: =IFERROR(IFERROR(INDEX(CALCULOS_NUTRIENTES!$AL$2:$AL$211,MATCH(1,INDEX((CALCULOS_NUTRIENTES!$AJ$2:$AJ$211=$G$7)*(CALCULOS_NUTRIENTES!$AK$2:$AK$211=$A27),0),0)),""),"") -> Tyrex 1 | C27: =IFERROR(IFERROR(INDEX(CALCULOS_NUTRIENTES!$AM$2:$AM$211,MATCH(1,INDEX((CALCULOS_NUTRIENTES!$AJ$2:$AJ$211=$G$7)*(CALCULOS_NUTRIENTES!$AK$2:$AK$211=$A27),0),0)),""),"") -> Alimentos con formulaciones Especiales | D27: =IFERROR(IFERROR(INDEX(CALCULOS_NUTRIENTES!$AN$2:$AN$211,MATCH(1,INDEX((CALCULOS_NUTRIENTES!$AJ$2:$AJ$211=$G$7)*(CALCULOS_NUTRIENTES!$AK$2:$AK$211=$A27),0),0)),""),"") -> sin documentar | E27: =IFERROR(IFERROR(INDEX(CALCULOS_NUTRIENTES!$AO$2:$AO$211,MATCH(1,INDEX((CALCULOS_NUTRIENTES!$AJ$2:$AJ$211=$G$7)*(CALCULOS_NUTRIENTES!$AK$2:$AK$211=$A27),0),0)),""),"") -> 85.4 | F27: =IFERROR(IFERROR(INDEX(CALCULOS_NUTRIENTES!$AP$2:$AP$211,MATCH(1,INDEX((CALCULOS_NUTRIENTES!$AJ$2:$AJ$211=$G$7)*(CALCULOS_NUTRIENTES!$AK$2:$AK$211=$A27),0),0)),""),"") -> mg
A28: 2 | B28: =IFERROR(IFERROR(INDEX(CALCULOS_NUTRIENTES!$AL$2:$AL$211,MATCH(1,INDEX((CALCULOS_NUTRIENTES!$AJ$2:$AJ$211=$G$7)*(CALCULOS_NUTRIENTES!$AK$2:$AK$211=$A28),0),0)),""),"") -> PKU2 Nutri Concentrated | C28: =IFERROR(IFERROR(INDEX(CALCULOS_NUTRIENTES!$AM$2:$AM$211,MATCH(1,INDEX((CALCULOS_NUTRIENTES!$AJ$2:$AJ$211=$G$7)*(CALCULOS_NUTRIENTES!$AK$2:$AK$211=$A28),0),0)),""),"") -> Alimentos con formulaciones Especiales | D28: =IFERROR(IFERROR(INDEX(CALCULOS_NUTRIENTES!$AN$2:$AN$211,MATCH(1,INDEX((CALCULOS_NUTRIENTES!$AJ$2:$AJ$211=$G$7)*(CALCULOS_NUTRIENTES!$AK$2:$AK$211=$A28),0),0)),""),"") -> sin documentar | E28: =IFERROR(IFERROR(INDEX(CALCULOS_NUTRIENTES!$AO$2:$AO$211,MATCH(1,INDEX((CALCULOS_NUTRIENTES!$AJ$2:$AJ$211=$G$7)*(CALCULOS_NUTRIENTES!$AK$2:$AK$211=$A28),0),0)),""),"") -> 30 | F28: =IFERROR(IFERROR(INDEX(CALCULOS_NUTRIENTES!$AP$2:$AP$211,MATCH(1,INDEX((CALCULOS_NUTRIENTES!$AJ$2:$AJ$211=$G$7)*(CALCULOS_NUTRIENTES!$AK$2:$AK$211=$A28),0),0)),""),"") -> mg
A29: 3 | B29: =IFERROR(IFERROR(INDEX(CALCULOS_NUTRIENTES!$AL$2:$AL$211,MATCH(1,INDEX((CALCULOS_NUTRIENTES!$AJ$2:$AJ$211=$G$7)*(CALCULOS_NUTRIENTES!$AK$2:$AK$211=$A29),0),0)),""),"") -> MSUD Med A Plus | C29: =IFERROR(IFERROR(INDEX(CALCULOS_NUTRIENTES!$AM$2:$AM$211,MATCH(1,INDEX((CALCULOS_NUTRIENTES!$AJ$2:$AJ$211=$G$7)*(CALCULOS_NUTRIENTES!$AK$2:$AK$211=$A29),0),0)),""),"") -> Alimentos con formulaciones Especiales | D29: =IFERROR(IFERROR(INDEX(CALCULOS_NUTRIENTES!$AN$2:$AN$211,MATCH(1,INDEX((CALCULOS_NUTRIENTES!$AJ$2:$AJ$211=$G$7)*(CALCULOS_NUTRIENTES!$AK$2:$AK$211=$A29),0),0)),""),"") -> sin documentar | E29: =IFERROR(IFERROR(INDEX(CALCULOS_NUTRIENTES!$AO$2:$AO$211,MATCH(1,INDEX((CALCULOS_NUTRIENTES!$AJ$2:$AJ$211=$G$7)*(CALCULOS_NUTRIENTES!$AK$2:$AK$211=$A29),0),0)),""),"") -> 25 | F29: =IFERROR(IFERROR(INDEX(CALCULOS_NUTRIENTES!$AP$2:$AP$211,MATCH(1,INDEX((CALCULOS_NUTRIENTES!$AJ$2:$AJ$211=$G$7)*(CALCULOS_NUTRIENTES!$AK$2:$AK$211=$A29),0),0)),""),"") -> mg
A30: 4 | B30: =IFERROR(IFERROR(INDEX(CALCULOS_NUTRIENTES!$AL$2:$AL$211,MATCH(1,INDEX((CALCULOS_NUTRIENTES!$AJ$2:$AJ$211=$G$7)*(CALCULOS_NUTRIENTES!$AK$2:$AK$211=$A30),0),0)),""),"") -> Ketonex 2 | C30: =IFERROR(IFERROR(INDEX(CALCULOS_NUTRIENTES!$AM$2:$AM$211,MATCH(1,INDEX((CALCULOS_NUTRIENTES!$AJ$2:$AJ$211=$G$7)*(CALCULOS_NUTRIENTES!$AK$2:$AK$211=$A30),0),0)),""),"") -> Alimentos con formulaciones Especiales | D30: =IFERROR(IFERROR(INDEX(CALCULOS_NUTRIENTES!$AN$2:$AN$211,MATCH(1,INDEX((CALCULOS_NUTRIENTES!$AJ$2:$AJ$211=$G$7)*(CALCULOS_NUTRIENTES!$AK$2:$AK$211=$A30),0),0)),""),"") -> sin documentar | E30: =IFERROR(IFERROR(INDEX(CALCULOS_NUTRIENTES!$AO$2:$AO$211,MATCH(1,INDEX((CALCULOS_NUTRIENTES!$AJ$2:$AJ$211=$G$7)*(CALCULOS_NUTRIENTES!$AK$2:$AK$211=$A30),0),0)),""),"") -> 23 | F30: =IFERROR(IFERROR(INDEX(CALCULOS_NUTRIENTES!$AP$2:$AP$211,MATCH(1,INDEX((CALCULOS_NUTRIENTES!$AJ$2:$AJ$211=$G$7)*(CALCULOS_NUTRIENTES!$AK$2:$AK$211=$A30),0),0)),""),"") -> mg
A31: 5 | B31: =IFERROR(IFERROR(INDEX(CALCULOS_NUTRIENTES!$AL$2:$AL$211,MATCH(1,INDEX((CALCULOS_NUTRIENTES!$AJ$2:$AJ$211=$G$7)*(CALCULOS_NUTRIENTES!$AK$2:$AK$211=$A31),0),0)),""),"") -> P-AM2 | C31: =IFERROR(IFERROR(INDEX(CALCULOS_NUTRIENTES!$AM$2:$AM$211,MATCH(1,INDEX((CALCULOS_NUTRIENTES!$AJ$2:$AJ$211=$G$7)*(CALCULOS_NUTRIENTES!$AK$2:$AK$211=$A31),0),0)),""),"") -> Alimentos con formulaciones Especiales | D31: =IFERROR(IFERROR(INDEX(CALCULOS_NUTRIENTES!$AN$2:$AN$211,MATCH(1,INDEX((CALCULOS_NUTRIENTES!$AJ$2:$AJ$211=$G$7)*(CALCULOS_NUTRIENTES!$AK$2:$AK$211=$A31),0),0)),""),"") -> sin documentar | E31: =IFERROR(IFERROR(INDEX(CALCULOS_NUTRIENTES!$AO$2:$AO$211,MATCH(1,INDEX((CALCULOS_NUTRIENTES!$AJ$2:$AJ$211=$G$7)*(CALCULOS_NUTRIENTES!$AK$2:$AK$211=$A31),0),0)),""),"") -> 21 | F31: =IFERROR(IFERROR(INDEX(CALCULOS_NUTRIENTES!$AP$2:$AP$211,MATCH(1,INDEX((CALCULOS_NUTRIENTES!$AJ$2:$AJ$211=$G$7)*(CALCULOS_NUTRIENTES!$AK$2:$AK$211=$A31),0),0)),""),"") -> mg
A32: 6 | B32: =IFERROR(IFERROR(INDEX(CALCULOS_NUTRIENTES!$AL$2:$AL$211,MATCH(1,INDEX((CALCULOS_NUTRIENTES!$AJ$2:$AJ$211=$G$7)*(CALCULOS_NUTRIENTES!$AK$2:$AK$211=$A32),0),0)),""),"") -> MSUD Med B Plus | C32: =IFERROR(IFERROR(INDEX(CALCULOS_NUTRIENTES!$AM$2:$AM$211,MATCH(1,INDEX((CALCULOS_NUTRIENTES!$AJ$2:$AJ$211=$G$7)*(CALCULOS_NUTRIENTES!$AK$2:$AK$211=$A32),0),0)),""),"") -> Alimentos con formulaciones Especiales | D32: =IFERROR(IFERROR(INDEX(CALCULOS_NUTRIENTES!$AN$2:$AN$211,MATCH(1,INDEX((CALCULOS_NUTRIENTES!$AJ$2:$AJ$211=$G$7)*(CALCULOS_NUTRIENTES!$AK$2:$AK$211=$A32),0),0)),""),"") -> sin documentar | E32: =IFERROR(IFERROR(INDEX(CALCULOS_NUTRIENTES!$AO$2:$AO$211,MATCH(1,INDEX((CALCULOS_NUTRIENTES!$AJ$2:$AJ$211=$G$7)*(CALCULOS_NUTRIENTES!$AK$2:$AK$211=$A32),0),0)),""),"") -> 19 | F32: =IFERROR(IFERROR(INDEX(CALCULOS_NUTRIENTES!$AP$2:$AP$211,MATCH(1,INDEX((CALCULOS_NUTRIENTES!$AJ$2:$AJ$211=$G$7)*(CALCULOS_NUTRIENTES!$AK$2:$AK$211=$A32),0),0)),""),"") -> mg
A33: 7 | B33: =IFERROR(IFERROR(INDEX(CALCULOS_NUTRIENTES!$AL$2:$AL$211,MATCH(1,INDEX((CALCULOS_NUTRIENTES!$AJ$2:$AJ$211=$G$7)*(CALCULOS_NUTRIENTES!$AK$2:$AK$211=$A33),0),0)),""),"") -> MSUD OAcMedB Plus | C33: =IFERROR(IFERROR(INDEX(CALCULOS_NUTRIENTES!$AM$2:$AM$211,MATCH(1,INDEX((CALCULOS_NUTRIENTES!$AJ$2:$AJ$211=$G$7)*(CALCULOS_NUTRIENTES!$AK$2:$AK$211=$A33),0),0)),""),"") -> Alimentos con formulaciones Especiales | D33: =IFERROR(IFERROR(INDEX(CALCULOS_NUTRIENTES!$AN$2:$AN$211,MATCH(1,INDEX((CALCULOS_NUTRIENTES!$AJ$2:$AJ$211=$G$7)*(CALCULOS_NUTRIENTES!$AK$2:$AK$211=$A33),0),0)),""),"") -> sin documentar | E33: =IFERROR(IFERROR(INDEX(CALCULOS_NUTRIENTES!$AO$2:$AO$211,MATCH(1,INDEX((CALCULOS_NUTRIENTES!$AJ$2:$AJ$211=$G$7)*(CALCULOS_NUTRIENTES!$AK$2:$AK$211=$A33),0),0)),""),"") -> 19 | F33: =IFERROR(IFERROR(INDEX(CALCULOS_NUTRIENTES!$AP$2:$AP$211,MATCH(1,INDEX((CALCULOS_NUTRIENTES!$AJ$2:$AJ$211=$G$7)*(CALCULOS_NUTRIENTES!$AK$2:$AK$211=$A33),0),0)),""),"") -> mg
A34: 8 | B34: =IFERROR(IFERROR(INDEX(CALCULOS_NUTRIENTES!$AL$2:$AL$211,MATCH(1,INDEX((CALCULOS_NUTRIENTES!$AJ$2:$AJ$211=$G$7)*(CALCULOS_NUTRIENTES!$AK$2:$AK$211=$A34),0),0)),""),"") -> Phenex 2 | C34: =IFERROR(IFERROR(INDEX(CALCULOS_NUTRIENTES!$AM$2:$AM$211,MATCH(1,INDEX((CALCULOS_NUTRIENTES!$AJ$2:$AJ$211=$G$7)*(CALCULOS_NUTRIENTES!$AK$2:$AK$211=$A34),0),0)),""),"") -> Alimentos con formulaciones Especiales | D34: =IFERROR(IFERROR(INDEX(CALCULOS_NUTRIENTES!$AN$2:$AN$211,MATCH(1,INDEX((CALCULOS_NUTRIENTES!$AJ$2:$AJ$211=$G$7)*(CALCULOS_NUTRIENTES!$AK$2:$AK$211=$A34),0),0)),""),"") -> sin documentar | E34: =IFERROR(IFERROR(INDEX(CALCULOS_NUTRIENTES!$AO$2:$AO$211,MATCH(1,INDEX((CALCULOS_NUTRIENTES!$AJ$2:$AJ$211=$G$7)*(CALCULOS_NUTRIENTES!$AK$2:$AK$211=$A34),0),0)),""),"") -> 19 | F34: =IFERROR(IFERROR(INDEX(CALCULOS_NUTRIENTES!$AP$2:$AP$211,MATCH(1,INDEX((CALCULOS_NUTRIENTES!$AJ$2:$AJ$211=$G$7)*(CALCULOS_NUTRIENTES!$AK$2:$AK$211=$A34),0),0)),""),"") -> mg
A35: 9 | B35: =IFERROR(IFERROR(INDEX(CALCULOS_NUTRIENTES!$AL$2:$AL$211,MATCH(1,INDEX((CALCULOS_NUTRIENTES!$AJ$2:$AJ$211=$G$7)*(CALCULOS_NUTRIENTES!$AK$2:$AK$211=$A35),0),0)),""),"") -> PKU Med B Plus | C35: =IFERROR(IFERROR(INDEX(CALCULOS_NUTRIENTES!$AM$2:$AM$211,MATCH(1,INDEX((CALCULOS_NUTRIENTES!$AJ$2:$AJ$211=$G$7)*(CALCULOS_NUTRIENTES!$AK$2:$AK$211=$A35),0),0)),""),"") -> Alimentos con formulaciones Especiales | D35: =IFERROR(IFERROR(INDEX(CALCULOS_NUTRIENTES!$AN$2:$AN$211,MATCH(1,INDEX((CALCULOS_NUTRIENTES!$AJ$2:$AJ$211=$G$7)*(CALCULOS_NUTRIENTES!$AK$2:$AK$211=$A35),0),0)),""),"") -> sin documentar | E35: =IFERROR(IFERROR(INDEX(CALCULOS_NUTRIENTES!$AO$2:$AO$211,MATCH(1,INDEX((CALCULOS_NUTRIENTES!$AJ$2:$AJ$211=$G$7)*(CALCULOS_NUTRIENTES!$AK$2:$AK$211=$A35),0),0)),""),"") -> 19 | F35: =IFERROR(IFERROR(INDEX(CALCULOS_NUTRIENTES!$AP$2:$AP$211,MATCH(1,INDEX((CALCULOS_NUTRIENTES!$AJ$2:$AJ$211=$G$7)*(CALCULOS_NUTRIENTES!$AK$2:$AK$211=$A35),0),0)),""),"") -> mg
A36: 10 | B36: =IFERROR(IFERROR(INDEX(CALCULOS_NUTRIENTES!$AL$2:$AL$211,MATCH(1,INDEX((CALCULOS_NUTRIENTES!$AJ$2:$AJ$211=$G$7)*(CALCULOS_NUTRIENTES!$AK$2:$AK$211=$A36),0),0)),""),"") -> Propimex 2 | C36: =IFERROR(IFERROR(INDEX(CALCULOS_NUTRIENTES!$AM$2:$AM$211,MATCH(1,INDEX((CALCULOS_NUTRIENTES!$AJ$2:$AJ$211=$G$7)*(CALCULOS_NUTRIENTES!$AK$2:$AK$211=$A36),0),0)),""),"") -> Alimentos con formulaciones Especiales | D36: =IFERROR(IFERROR(INDEX(CALCULOS_NUTRIENTES!$AN$2:$AN$211,MATCH(1,INDEX((CALCULOS_NUTRIENTES!$AJ$2:$AJ$211=$G$7)*(CALCULOS_NUTRIENTES!$AK$2:$AK$211=$A36),0),0)),""),"") -> sin documentar | E36: =IFERROR(IFERROR(INDEX(CALCULOS_NUTRIENTES!$AO$2:$AO$211,MATCH(1,INDEX((CALCULOS_NUTRIENTES!$AJ$2:$AJ$211=$G$7)*(CALCULOS_NUTRIENTES!$AK$2:$AK$211=$A36),0),0)),""),"") -> 18 | F36: =IFERROR(IFERROR(INDEX(CALCULOS_NUTRIENTES!$AP$2:$AP$211,MATCH(1,INDEX((CALCULOS_NUTRIENTES!$AJ$2:$AJ$211=$G$7)*(CALCULOS_NUTRIENTES!$AK$2:$AK$211=$A36),0),0)),""),"") -> mg
A39: El ranking se expresa por 100 g de porción comestible y no representa una porción recomendada. Las medidas domésticas son textos editables y no provienen de la tabla INTA. Cloruro y biotina permanecen como ND porque no están disponibles en la base alimentaria incorporada.

Sheet REQUERIMIENTOS
A1: NUTRIMETRÍA · NMX-43 | REQUERIMIENTOS
A3: Consulta automática de RDA/AI y UL/CDRR por edad, sexo y estado fisiológico.
A5: =HYPERLINK("#'INICIO'!A1","INICIO") -> INICIO | B5: =HYPERLINK("#'DATOS'!A1","DATOS") -> DATOS | C5: =HYPERLINK("#'ENERGÍA'!A1","ENERGÍA") -> ENERGÍA | D5: =HYPERLINK("#'MACRONUTRIENTES'!A1","MACRONUTRIENTES") -> MACRONUTRIENTES | E5: =HYPERLINK("#'AGUA_FIBRA'!A1","AGUA/FIBRA") -> AGUA/FIBRA | F5: =HYPERLINK("#'FICHA_NUTRIENTE'!A1","FICHA/NUTRIENTE") -> FICHA/NUTRIENTE | G5: =HYPERLINK("#'RESULTADOS'!A1","RESULTADOS") -> RESULTADOS | H5: =HYPERLINK("#'DOCUMENTACIÓN'!A1","DOCUMENTACIÓN") -> DOCUMENTACIÓN | I5: =HYPERLINK("#'COBERTURA'!A1","COBERTURA") -> COBERTURA | J5: =HYPERLINK("#'AUDITORÍA_FINAL'!A1","AUDITORÍA") -> AUDITORÍA
A7: NUTRIENTE | C7: Zinc | E7: ID | G7: =IFERROR(IFERROR(INDEX(NUTRIENTES!$A$8:$A$30,MATCH($C$7,NUTRIENTES!$B$8:$B$30,0)),""),"") -> MIN-ZN
A8: Use la flecha de la celda amarilla para seleccionar el nutriente.
A9: EDAD | C9: SEXO | E9: ESTADO | G9: GRUPO RESUELTO
A10: =DATOS!F9 -> 25 | C10: =DATOS!B13 -> Femenino | E10: =DATOS!B16 -> Ninguno | G10: =IFERROR(IFERROR(INDEX(DRI_BASE!$C$2:$C$469&" · "&DRI_BASE!$D$2:$D$469&"–"&DRI_BASE!$E$2:$E$469&" años",MATCH(1,INDEX((DRI_BASE!$B$2:$B$469=$G$7)*(DRI_BASE!$D$2:$D$469<=DATOS!$F$9)*(DRI_BASE!$E$2:$E$469>DATOS!$F$9)*(((DRI_BASE!$C$2:$C$469=DATOS!$B$13)+(DRI_BASE!$C$2:$C$469="Ambos"))>0)*(DRI_BASE!$G$2:$G$469=DATOS!$B$16),0),0)),"ND"),"ND") -> Femenino · 19–31 años
A12: OBJETIVO | C12: TIPO | E12: LÍMITE | G12: TIPO LÍMITE | I12: UNIDAD | K12: FUENTE
A13: =IFERROR(IFERROR(INDEX(DRI_BASE!$T$2:$T$469,MATCH(1,INDEX((DRI_BASE!$B$2:$B$469=$G$7)*(DRI_BASE!$D$2:$D$469<=DATOS!$F$9)*(DRI_BASE!$E$2:$E$469>DATOS!$F$9)*(((DRI_BASE!$C$2:$C$469=DATOS!$B$13)+(DRI_BASE!$C$2:$C$469="Ambos"))>0)*(DRI_BASE!$G$2:$G$469=DATOS!$B$16),0),0)),"ND"),"ND") -> 8 | C13: =IFERROR(IFERROR(INDEX(DRI_BASE!$R$2:$R$469,MATCH(1,INDEX((DRI_BASE!$B$2:$B$469=$G$7)*(DRI_BASE!$D$2:$D$469<=DATOS!$F$9)*(DRI_BASE!$E$2:$E$469>DATOS!$F$9)*(((DRI_BASE!$C$2:$C$469=DATOS!$B$13)+(DRI_BASE!$C$2:$C$469="Ambos"))>0)*(DRI_BASE!$G$2:$G$469=DATOS!$B$16),0),0)),"ND"),"ND") -> RDA | E13: =IFERROR(IFERROR(INDEX(DRI_BASE!$U$2:$U$469,MATCH(1,INDEX((DRI_BASE!$B$2:$B$469=$G$7)*(DRI_BASE!$D$2:$D$469<=DATOS!$F$9)*(DRI_BASE!$E$2:$E$469>DATOS!$F$9)*(((DRI_BASE!$C$2:$C$469=DATOS!$B$13)+(DRI_BASE!$C$2:$C$469="Ambos"))>0)*(DRI_BASE!$G$2:$G$469=DATOS!$B$16),0),0)),"ND"),"ND") -> 40 | G13: =IFERROR(IFERROR(INDEX(DRI_BASE!$S$2:$S$469,MATCH(1,INDEX((DRI_BASE!$B$2:$B$469=$G$7)*(DRI_BASE!$D$2:$D$469<=DATOS!$F$9)*(DRI_BASE!$E$2:$E$469>DATOS!$F$9)*(((DRI_BASE!$C$2:$C$469=DATOS!$B$13)+(DRI_BASE!$C$2:$C$469="Ambos"))>0)*(DRI_BASE!$G$2:$G$469=DATOS!$B$16),0),0)),"ND"),"ND") -> UL | I13: =IFERROR(IFERROR(INDEX(DRI_BASE!$L$2:$L$469,MATCH(1,INDEX((DRI_BASE!$B$2:$B$469=$G$7)*(DRI_BASE!$D$2:$D$469<=DATOS!$F$9)*(DRI_BASE!$E$2:$E$469>DATOS!$F$9)*(((DRI_BASE!$C$2:$C$469=DATOS!$B$13)+(DRI_BASE!$C$2:$C$469="Ambos"))>0)*(DRI_BASE!$G$2:$G$469=DATOS!$B$16),0),0)),""),"") -> mg | K13: =IFERROR(IFERROR(INDEX(DRI_BASE!$M$2:$M$469,MATCH(1,INDEX((DRI_BASE!$B$2:$B$469=$G$7)*(DRI_BASE!$D$2:$D$469<=DATOS!$F$9)*(DRI_BASE!$E$2:$E$469>DATOS!$F$9)*(((DRI_BASE!$C$2:$C$469=DATOS!$B$13)+(DRI_BASE!$C$2:$C$469="Ambos"))>0)*(DRI_BASE!$G$2:$G$469=DATOS!$B$16),0),0)),"ND"),"ND") -> SRC-DRI-SUMMARY
A17: Grupo | B17: Sexo | C17: Estado | D17: Edad | E17: EAR | F17: RDA | G17: AI | H17: Objetivo | I17: Tipo | J17: UL | K17: CDRR | L17: Límite | M17: Tipo límite | N17: Unidad | O17: Fuente
A18: 0–6 m | B18: Ambos | C18: Ninguno | D18: 0–0.5 | E18: =IFERROR(IFERROR(INDEX(DRI_BASE!$H$2:$H$469,MATCH(1,INDEX((DRI_BASE!$B$2:$B$469=$G$7)*(DRI_BASE!$C$2:$C$469="Ambos")*(DRI_BASE!$D$2:$D$469=0)*(DRI_BASE!$G$2:$G$469="Ninguno"),0),0)),"ND"),"ND") -> 0 | F18: =IFERROR(IFERROR(INDEX(DRI_BASE!$I$2:$I$469,MATCH(1,INDEX((DRI_BASE!$B$2:$B$469=$G$7)*(DRI_BASE!$C$2:$C$469="Ambos")*(DRI_BASE!$D$2:$D$469=0)*(DRI_BASE!$G$2:$G$469="Ninguno"),0),0)),"ND"),"ND") -> 0 | G18: =IFERROR(IFERROR(INDEX(DRI_BASE!$J$2:$J$469,MATCH(1,INDEX((DRI_BASE!$B$2:$B$469=$G$7)*(DRI_BASE!$C$2:$C$469="Ambos")*(DRI_BASE!$D$2:$D$469=0)*(DRI_BASE!$G$2:$G$469="Ninguno"),0),0)),"ND"),"ND") -> 2 | H18: =IFERROR(IFERROR(INDEX(DRI_BASE!$T$2:$T$469,MATCH(1,INDEX((DRI_BASE!$B$2:$B$469=$G$7)*(DRI_BASE!$C$2:$C$469="Ambos")*(DRI_BASE!$D$2:$D$469=0)*(DRI_BASE!$G$2:$G$469="Ninguno"),0),0)),"ND"),"ND") -> 2 | I18: =IFERROR(IFERROR(INDEX(DRI_BASE!$R$2:$R$469,MATCH(1,INDEX((DRI_BASE!$B$2:$B$469=$G$7)*(DRI_BASE!$C$2:$C$469="Ambos")*(DRI_BASE!$D$2:$D$469=0)*(DRI_BASE!$G$2:$G$469="Ninguno"),0),0)),"ND"),"ND") -> AI | J18: =IFERROR(IFERROR(INDEX(DRI_BASE!$K$2:$K$469,MATCH(1,INDEX((DRI_BASE!$B$2:$B$469=$G$7)*(DRI_BASE!$C$2:$C$469="Ambos")*(DRI_BASE!$D$2:$D$469=0)*(DRI_BASE!$G$2:$G$469="Ninguno"),0),0)),"ND"),"ND") -> 4 | K18: =IFERROR(IFERROR(INDEX(DRI_BASE!$Q$2:$Q$469,MATCH(1,INDEX((DRI_BASE!$B$2:$B$469=$G$7)*(DRI_BASE!$C$2:$C$469="Ambos")*(DRI_BASE!$D$2:$D$469=0)*(DRI_BASE!$G$2:$G$469="Ninguno"),0),0)),"ND"),"ND") -> 0 | L18: =IFERROR(IFERROR(INDEX(DRI_BASE!$U$2:$U$469,MATCH(1,INDEX((DRI_BASE!$B$2:$B$469=$G$7)*(DRI_BASE!$C$2:$C$469="Ambos")*(DRI_BASE!$D$2:$D$469=0)*(DRI_BASE!$G$2:$G$469="Ninguno"),0),0)),"ND"),"ND") -> 4 | M18: =IFERROR(IFERROR(INDEX(DRI_BASE!$S$2:$S$469,MATCH(1,INDEX((DRI_BASE!$B$2:$B$469=$G$7)*(DRI_BASE!$C$2:$C$469="Ambos")*(DRI_BASE!$D$2:$D$469=0)*(DRI_BASE!$G$2:$G$469="Ninguno"),0),0)),""),"") -> UL | N18: =IFERROR(IFERROR(INDEX(DRI_BASE!$L$2:$L$469,MATCH(1,INDEX((DRI_BASE!$B$2:$B$469=$G$7)*(DRI_BASE!$C$2:$C$469="Ambos")*(DRI_BASE!$D$2:$D$469=0)*(DRI_BASE!$G$2:$G$469="Ninguno"),0),0)),""),"") -> mg | O18: =IFERROR(IFERROR(INDEX(DRI_BASE!$M$2:$M$469,MATCH(1,INDEX((DRI_BASE!$B$2:$B$469=$G$7)*(DRI_BASE!$C$2:$C$469="Ambos")*(DRI_BASE!$D$2:$D$469=0)*(DRI_BASE!$G$2:$G$469="Ninguno"),0),0)),"ND"),"ND") -> SRC-DRI-SUMMARY
A19: 7–12 m | B19: Ambos | C19: Ninguno | D19: 0.5–1 | E19: =IFERROR(IFERROR(INDEX(DRI_BASE!$H$2:$H$469,MATCH(1,INDEX((DRI_BASE!$B$2:$B$469=$G$7)*(DRI_BASE!$C$2:$C$469="Ambos")*(DRI_BASE!$D$2:$D$469=0.5)*(DRI_BASE!$G$2:$G$469="Ninguno"),0),0)),"ND"),"ND") -> 0 | F19: =IFERROR(IFERROR(INDEX(DRI_BASE!$I$2:$I$469,MATCH(1,INDEX((DRI_BASE!$B$2:$B$469=$G$7)*(DRI_BASE!$C$2:$C$469="Ambos")*(DRI_BASE!$D$2:$D$469=0.5)*(DRI_BASE!$G$2:$G$469="Ninguno"),0),0)),"ND"),"ND") -> 0 | G19: =IFERROR(IFERROR(INDEX(DRI_BASE!$J$2:$J$469,MATCH(1,INDEX((DRI_BASE!$B$2:$B$469=$G$7)*(DRI_BASE!$C$2:$C$469="Ambos")*(DRI_BASE!$D$2:$D$469=0.5)*(DRI_BASE!$G$2:$G$469="Ninguno"),0),0)),"ND"),"ND") -> 3 | H19: =IFERROR(IFERROR(INDEX(DRI_BASE!$T$2:$T$469,MATCH(1,INDEX((DRI_BASE!$B$2:$B$469=$G$7)*(DRI_BASE!$C$2:$C$469="Ambos")*(DRI_BASE!$D$2:$D$469=0.5)*(DRI_BASE!$G$2:$G$469="Ninguno"),0),0)),"ND"),"ND") -> 3 | I19: =IFERROR(IFERROR(INDEX(DRI_BASE!$R$2:$R$469,MATCH(1,INDEX((DRI_BASE!$B$2:$B$469=$G$7)*(DRI_BASE!$C$2:$C$469="Ambos")*(DRI_BASE!$D$2:$D$469=0.5)*(DRI_BASE!$G$2:$G$469="Ninguno"),0),0)),"ND"),"ND") -> AI | J19: =IFERROR(IFERROR(INDEX(DRI_BASE!$K$2:$K$469,MATCH(1,INDEX((DRI_BASE!$B$2:$B$469=$G$7)*(DRI_BASE!$C$2:$C$469="Ambos")*(DRI_BASE!$D$2:$D$469=0.5)*(DRI_BASE!$G$2:$G$469="Ninguno"),0),0)),"ND"),"ND") -> 5 | K19: =IFERROR(IFERROR(INDEX(DRI_BASE!$Q$2:$Q$469,MATCH(1,INDEX((DRI_BASE!$B$2:$B$469=$G$7)*(DRI_BASE!$C$2:$C$469="Ambos")*(DRI_BASE!$D$2:$D$469=0.5)*(DRI_BASE!$G$2:$G$469="Ninguno"),0),0)),"ND"),"ND") -> 0 | L19: =IFERROR(IFERROR(INDEX(DRI_BASE!$U$2:$U$469,MATCH(1,INDEX((DRI_BASE!$B$2:$B$469=$G$7)*(DRI_BASE!$C$2:$C$469="Ambos")*(DRI_BASE!$D$2:$D$469=0.5)*(DRI_BASE!$G$2:$G$469="Ninguno"),0),0)),"ND"),"ND") -> 5 | M19: =IFERROR(IFERROR(INDEX(DRI_BASE!$S$2:$S$469,MATCH(1,INDEX((DRI_BASE!$B$2:$B$469=$G$7)*(DRI_BASE!$C$2:$C$469="Ambos")*(DRI_BASE!$D$2:$D$469=0.5)*(DRI_BASE!$G$2:$G$469="Ninguno"),0),0)),""),"") -> UL | N19: =IFERROR(IFERROR(INDEX(DRI_BASE!$L$2:$L$469,MATCH(1,INDEX((DRI_BASE!$B$2:$B$469=$G$7)*(DRI_BASE!$C$2:$C$469="Ambos")*(DRI_BASE!$D$2:$D$469=0.5)*(DRI_BASE!$G$2:$G$469="Ninguno"),0),0)),""),"") -> mg | O19: =IFERROR(IFERROR(INDEX(DRI_BASE!$M$2:$M$469,MATCH(1,INDEX((DRI_BASE!$B$2:$B$469=$G$7)*(DRI_BASE!$C$2:$C$469="Ambos")*(DRI_BASE!$D$2:$D$469=0.5)*(DRI_BASE!$G$2:$G$469="Ninguno"),0),0)),"ND"),"ND") -> SRC-DRI-SUMMARY
A20: 1–3 a | B20: Ambos | C20: Ninguno | D20: 1–4 | E20: =IFERROR(IFERROR(INDEX(DRI_BASE!$H$2:$H$469,MATCH(1,INDEX((DRI_BASE!$B$2:$B$469=$G$7)*(DRI_BASE!$C$2:$C$469="Ambos")*(DRI_BASE!$D$2:$D$469=1)*(DRI_BASE!$G$2:$G$469="Ninguno"),0),0)),"ND"),"ND") -> 0 | F20: =IFERROR(IFERROR(INDEX(DRI_BASE!$I$2:$I$469,MATCH(1,INDEX((DRI_BASE!$B$2:$B$469=$G$7)*(DRI_BASE!$C$2:$C$469="Ambos")*(DRI_BASE!$D$2:$D$469=1)*(DRI_BASE!$G$2:$G$469="Ninguno"),0),0)),"ND"),"ND") -> 3 | G20: =IFERROR(IFERROR(INDEX(DRI_BASE!$J$2:$J$469,MATCH(1,INDEX((DRI_BASE!$B$2:$B$469=$G$7)*(DRI_BASE!$C$2:$C$469="Ambos")*(DRI_BASE!$D$2:$D$469=1)*(DRI_BASE!$G$2:$G$469="Ninguno"),0),0)),"ND"),"ND") -> 0 | H20: =IFERROR(IFERROR(INDEX(DRI_BASE!$T$2:$T$469,MATCH(1,INDEX((DRI_BASE!$B$2:$B$469=$G$7)*(DRI_BASE!$C$2:$C$469="Ambos")*(DRI_BASE!$D$2:$D$469=1)*(DRI_BASE!$G$2:$G$469="Ninguno"),0),0)),"ND"),"ND") -> 3 | I20: =IFERROR(IFERROR(INDEX(DRI_BASE!$R$2:$R$469,MATCH(1,INDEX((DRI_BASE!$B$2:$B$469=$G$7)*(DRI_BASE!$C$2:$C$469="Ambos")*(DRI_BASE!$D$2:$D$469=1)*(DRI_BASE!$G$2:$G$469="Ninguno"),0),0)),"ND"),"ND") -> RDA | J20: =IFERROR(IFERROR(INDEX(DRI_BASE!$K$2:$K$469,MATCH(1,INDEX((DRI_BASE!$B$2:$B$469=$G$7)*(DRI_BASE!$C$2:$C$469="Ambos")*(DRI_BASE!$D$2:$D$469=1)*(DRI_BASE!$G$2:$G$469="Ninguno"),0),0)),"ND"),"ND") -> 7 | K20: =IFERROR(IFERROR(INDEX(DRI_BASE!$Q$2:$Q$469,MATCH(1,INDEX((DRI_BASE!$B$2:$B$469=$G$7)*(DRI_BASE!$C$2:$C$469="Ambos")*(DRI_BASE!$D$2:$D$469=1)*(DRI_BASE!$G$2:$G$469="Ninguno"),0),0)),"ND"),"ND") -> 0 | L20: =IFERROR(IFERROR(INDEX(DRI_BASE!$U$2:$U$469,MATCH(1,INDEX((DRI_BASE!$B$2:$B$469=$G$7)*(DRI_BASE!$C$2:$C$469="Ambos")*(DRI_BASE!$D$2:$D$469=1)*(DRI_BASE!$G$2:$G$469="Ninguno"),0),0)),"ND"),"ND") -> 7 | M20: =IFERROR(IFERROR(INDEX(DRI_BASE!$S$2:$S$469,MATCH(1,INDEX((DRI_BASE!$B$2:$B$469=$G$7)*(DRI_BASE!$C$2:$C$469="Ambos")*(DRI_BASE!$D$2:$D$469=1)*(DRI_BASE!$G$2:$G$469="Ninguno"),0),0)),""),"") -> UL | N20: =IFERROR(IFERROR(INDEX(DRI_BASE!$L$2:$L$469,MATCH(1,INDEX((DRI_BASE!$B$2:$B$469=$G$7)*(DRI_BASE!$C$2:$C$469="Ambos")*(DRI_BASE!$D$2:$D$469=1)*(DRI_BASE!$G$2:$G$469="Ninguno"),0),0)),""),"") -> mg | O20: =IFERROR(IFERROR(INDEX(DRI_BASE!$M$2:$M$469,MATCH(1,INDEX((DRI_BASE!$B$2:$B$469=$G$7)*(DRI_BASE!$C$2:$C$469="Ambos")*(DRI_BASE!$D$2:$D$469=1)*(DRI_BASE!$G$2:$G$469="Ninguno"),0),0)),"ND"),"ND") -> SRC-DRI-SUMMARY
A21: 4–8 a | B21: Ambos | C21: Ninguno | D21: 4–9 | E21: =IFERROR(IFERROR(INDEX(DRI_BASE!$H$2:$H$469,MATCH(1,INDEX((DRI_BASE!$B$2:$B$469=$G$7)*(DRI_BASE!$C$2:$C$469="Ambos")*(DRI_BASE!$D$2:$D$469=4)*(DRI_BASE!$G$2:$G$469="Ninguno"),0),0)),"ND"),"ND") -> 0 | F21: =IFERROR(IFERROR(INDEX(DRI_BASE!$I$2:$I$469,MATCH(1,INDEX((DRI_BASE!$B$2:$B$469=$G$7)*(DRI_BASE!$C$2:$C$469="Ambos")*(DRI_BASE!$D$2:$D$469=4)*(DRI_BASE!$G$2:$G$469="Ninguno"),0),0)),"ND"),"ND") -> 5 | G21: =IFERROR(IFERROR(INDEX(DRI_BASE!$J$2:$J$469,MATCH(1,INDEX((DRI_BASE!$B$2:$B$469=$G$7)*(DRI_BASE!$C$2:$C$469="Ambos")*(DRI_BASE!$D$2:$D$469=4)*(DRI_BASE!$G$2:$G$469="Ninguno"),0),0)),"ND"),"ND") -> 0 | H21: =IFERROR(IFERROR(INDEX(DRI_BASE!$T$2:$T$469,MATCH(1,INDEX((DRI_BASE!$B$2:$B$469=$G$7)*(DRI_BASE!$C$2:$C$469="Ambos")*(DRI_BASE!$D$2:$D$469=4)*(DRI_BASE!$G$2:$G$469="Ninguno"),0),0)),"ND"),"ND") -> 5 | I21: =IFERROR(IFERROR(INDEX(DRI_BASE!$R$2:$R$469,MATCH(1,INDEX((DRI_BASE!$B$2:$B$469=$G$7)*(DRI_BASE!$C$2:$C$469="Ambos")*(DRI_BASE!$D$2:$D$469=4)*(DRI_BASE!$G$2:$G$469="Ninguno"),0),0)),"ND"),"ND") -> RDA | J21: =IFERROR(IFERROR(INDEX(DRI_BASE!$K$2:$K$469,MATCH(1,INDEX((DRI_BASE!$B$2:$B$469=$G$7)*(DRI_BASE!$C$2:$C$469="Ambos")*(DRI_BASE!$D$2:$D$469=4)*(DRI_BASE!$G$2:$G$469="Ninguno"),0),0)),"ND"),"ND") -> 12 | K21: =IFERROR(IFERROR(INDEX(DRI_BASE!$Q$2:$Q$469,MATCH(1,INDEX((DRI_BASE!$B$2:$B$469=$G$7)*(DRI_BASE!$C$2:$C$469="Ambos")*(DRI_BASE!$D$2:$D$469=4)*(DRI_BASE!$G$2:$G$469="Ninguno"),0),0)),"ND"),"ND") -> 0 | L21: =IFERROR(IFERROR(INDEX(DRI_BASE!$U$2:$U$469,MATCH(1,INDEX((DRI_BASE!$B$2:$B$469=$G$7)*(DRI_BASE!$C$2:$C$469="Ambos")*(DRI_BASE!$D$2:$D$469=4)*(DRI_BASE!$G$2:$G$469="Ninguno"),0),0)),"ND"),"ND") -> 12 | M21: =IFERROR(IFERROR(INDEX(DRI_BASE!$S$2:$S$469,MATCH(1,INDEX((DRI_BASE!$B$2:$B$469=$G$7)*(DRI_BASE!$C$2:$C$469="Ambos")*(DRI_BASE!$D$2:$D$469=4)*(DRI_BASE!$G$2:$G$469="Ninguno"),0),0)),""),"") -> UL | N21: =IFERROR(IFERROR(INDEX(DRI_BASE!$L$2:$L$469,MATCH(1,INDEX((DRI_BASE!$B$2:$B$469=$G$7)*(DRI_BASE!$C$2:$C$469="Ambos")*(DRI_BASE!$D$2:$D$469=4)*(DRI_BASE!$G$2:$G$469="Ninguno"),0),0)),""),"") -> mg | O21: =IFERROR(IFERROR(INDEX(DRI_BASE!$M$2:$M$469,MATCH(1,INDEX((DRI_BASE!$B$2:$B$469=$G$7)*(DRI_BASE!$C$2:$C$469="Ambos")*(DRI_BASE!$D$2:$D$469=4)*(DRI_BASE!$G$2:$G$469="Ninguno"),0),0)),"ND"),"ND") -> SRC-DRI-SUMMARY
A22: M 9–13 | B22: Masculino | C22: Ninguno | D22: 9–14 | E22: =IFERROR(IFERROR(INDEX(DRI_BASE!$H$2:$H$469,MATCH(1,INDEX((DRI_BASE!$B$2:$B$469=$G$7)*(DRI_BASE!$C$2:$C$469="Masculino")*(DRI_BASE!$D$2:$D$469=9)*(DRI_BASE!$G$2:$G$469="Ninguno"),0),0)),"ND"),"ND") -> 0 | F22: =IFERROR(IFERROR(INDEX(DRI_BASE!$I$2:$I$469,MATCH(1,INDEX((DRI_BASE!$B$2:$B$469=$G$7)*(DRI_BASE!$C$2:$C$469="Masculino")*(DRI_BASE!$D$2:$D$469=9)*(DRI_BASE!$G$2:$G$469="Ninguno"),0),0)),"ND"),"ND") -> 8 | G22: =IFERROR(IFERROR(INDEX(DRI_BASE!$J$2:$J$469,MATCH(1,INDEX((DRI_BASE!$B$2:$B$469=$G$7)*(DRI_BASE!$C$2:$C$469="Masculino")*(DRI_BASE!$D$2:$D$469=9)*(DRI_BASE!$G$2:$G$469="Ninguno"),0),0)),"ND"),"ND") -> 0 | H22: =IFERROR(IFERROR(INDEX(DRI_BASE!$T$2:$T$469,MATCH(1,INDEX((DRI_BASE!$B$2:$B$469=$G$7)*(DRI_BASE!$C$2:$C$469="Masculino")*(DRI_BASE!$D$2:$D$469=9)*(DRI_BASE!$G$2:$G$469="Ninguno"),0),0)),"ND"),"ND") -> 8 | I22: =IFERROR(IFERROR(INDEX(DRI_BASE!$R$2:$R$469,MATCH(1,INDEX((DRI_BASE!$B$2:$B$469=$G$7)*(DRI_BASE!$C$2:$C$469="Masculino")*(DRI_BASE!$D$2:$D$469=9)*(DRI_BASE!$G$2:$G$469="Ninguno"),0),0)),"ND"),"ND") -> RDA | J22: =IFERROR(IFERROR(INDEX(DRI_BASE!$K$2:$K$469,MATCH(1,INDEX((DRI_BASE!$B$2:$B$469=$G$7)*(DRI_BASE!$C$2:$C$469="Masculino")*(DRI_BASE!$D$2:$D$469=9)*(DRI_BASE!$G$2:$G$469="Ninguno"),0),0)),"ND"),"ND") -> 23 | K22: =IFERROR(IFERROR(INDEX(DRI_BASE!$Q$2:$Q$469,MATCH(1,INDEX((DRI_BASE!$B$2:$B$469=$G$7)*(DRI_BASE!$C$2:$C$469="Masculino")*(DRI_BASE!$D$2:$D$469=9)*(DRI_BASE!$G$2:$G$469="Ninguno"),0),0)),"ND"),"ND") -> 0 | L22: =IFERROR(IFERROR(INDEX(DRI_BASE!$U$2:$U$469,MATCH(1,INDEX((DRI_BASE!$B$2:$B$469=$G$7)*(DRI_BASE!$C$2:$C$469="Masculino")*(DRI_BASE!$D$2:$D$469=9)*(DRI_BASE!$G$2:$G$469="Ninguno"),0),0)),"ND"),"ND") -> 23 | M22: =IFERROR(IFERROR(INDEX(DRI_BASE!$S$2:$S$469,MATCH(1,INDEX((DRI_BASE!$B$2:$B$469=$G$7)*(DRI_BASE!$C$2:$C$469="Masculino")*(DRI_BASE!$D$2:$D$469=9)*(DRI_BASE!$G$2:$G$469="Ninguno"),0),0)),""),"") -> UL | N22: =IFERROR(IFERROR(INDEX(DRI_BASE!$L$2:$L$469,MATCH(1,INDEX((DRI_BASE!$B$2:$B$469=$G$7)*(DRI_BASE!$C$2:$C$469="Masculino")*(DRI_BASE!$D$2:$D$469=9)*(DRI_BASE!$G$2:$G$469="Ninguno"),0),0)),""),"") -> mg | O22: =IFERROR(IFERROR(INDEX(DRI_BASE!$M$2:$M$469,MATCH(1,INDEX((DRI_BASE!$B$2:$B$469=$G$7)*(DRI_BASE!$C$2:$C$469="Masculino")*(DRI_BASE!$D$2:$D$469=9)*(DRI_BASE!$G$2:$G$469="Ninguno"),0),0)),"ND"),"ND") -> SRC-DRI-SUMMARY
A23: F 9–13 | B23: Femenino | C23: Ninguno | D23: 9–14 | E23: =IFERROR(IFERROR(INDEX(DRI_BASE!$H$2:$H$469,MATCH(1,INDEX((DRI_BASE!$B$2:$B$469=$G$7)*(DRI_BASE!$C$2:$C$469="Femenino")*(DRI_BASE!$D$2:$D$469=9)*(DRI_BASE!$G$2:$G$469="Ninguno"),0),0)),"ND"),"ND") -> 0 | F23: =IFERROR(IFERROR(INDEX(DRI_BASE!$I$2:$I$469,MATCH(1,INDEX((DRI_BASE!$B$2:$B$469=$G$7)*(DRI_BASE!$C$2:$C$469="Femenino")*(DRI_BASE!$D$2:$D$469=9)*(DRI_BASE!$G$2:$G$469="Ninguno"),0),0)),"ND"),"ND") -> 8 | G23: =IFERROR(IFERROR(INDEX(DRI_BASE!$J$2:$J$469,MATCH(1,INDEX((DRI_BASE!$B$2:$B$469=$G$7)*(DRI_BASE!$C$2:$C$469="Femenino")*(DRI_BASE!$D$2:$D$469=9)*(DRI_BASE!$G$2:$G$469="Ninguno"),0),0)),"ND"),"ND") -> 0 | H23: =IFERROR(IFERROR(INDEX(DRI_BASE!$T$2:$T$469,MATCH(1,INDEX((DRI_BASE!$B$2:$B$469=$G$7)*(DRI_BASE!$C$2:$C$469="Femenino")*(DRI_BASE!$D$2:$D$469=9)*(DRI_BASE!$G$2:$G$469="Ninguno"),0),0)),"ND"),"ND") -> 8 | I23: =IFERROR(IFERROR(INDEX(DRI_BASE!$R$2:$R$469,MATCH(1,INDEX((DRI_BASE!$B$2:$B$469=$G$7)*(DRI_BASE!$C$2:$C$469="Femenino")*(DRI_BASE!$D$2:$D$469=9)*(DRI_BASE!$G$2:$G$469="Ninguno"),0),0)),"ND"),"ND") -> RDA | J23: =IFERROR(IFERROR(INDEX(DRI_BASE!$K$2:$K$469,MATCH(1,INDEX((DRI_BASE!$B$2:$B$469=$G$7)*(DRI_BASE!$C$2:$C$469="Femenino")*(DRI_BASE!$D$2:$D$469=9)*(DRI_BASE!$G$2:$G$469="Ninguno"),0),0)),"ND"),"ND") -> 23 | K23: =IFERROR(IFERROR(INDEX(DRI_BASE!$Q$2:$Q$469,MATCH(1,INDEX((DRI_BASE!$B$2:$B$469=$G$7)*(DRI_BASE!$C$2:$C$469="Femenino")*(DRI_BASE!$D$2:$D$469=9)*(DRI_BASE!$G$2:$G$469="Ninguno"),0),0)),"ND"),"ND") -> 0 | L23: =IFERROR(IFERROR(INDEX(DRI_BASE!$U$2:$U$469,MATCH(1,INDEX((DRI_BASE!$B$2:$B$469=$G$7)*(DRI_BASE!$C$2:$C$469="Femenino")*(DRI_BASE!$D$2:$D$469=9)*(DRI_BASE!$G$2:$G$469="Ninguno"),0),0)),"ND"),"ND") -> 23 | M23: =IFERROR(IFERROR(INDEX(DRI_BASE!$S$2:$S$469,MATCH(1,INDEX((DRI_BASE!$B$2:$B$469=$G$7)*(DRI_BASE!$C$2:$C$469="Femenino")*(DRI_BASE!$D$2:$D$469=9)*(DRI_BASE!$G$2:$G$469="Ninguno"),0),0)),""),"") -> UL | N23: =IFERROR(IFERROR(INDEX(DRI_BASE!$L$2:$L$469,MATCH(1,INDEX((DRI_BASE!$B$2:$B$469=$G$7)*(DRI_BASE!$C$2:$C$469="Femenino")*(DRI_BASE!$D$2:$D$469=9)*(DRI_BASE!$G$2:$G$469="Ninguno"),0),0)),""),"") -> mg | O23: =IFERROR(IFERROR(INDEX(DRI_BASE!$M$2:$M$469,MATCH(1,INDEX((DRI_BASE!$B$2:$B$469=$G$7)*(DRI_BASE!$C$2:$C$469="Femenino")*(DRI_BASE!$D$2:$D$469=9)*(DRI_BASE!$G$2:$G$469="Ninguno"),0),0)),"ND"),"ND") -> SRC-DRI-SUMMARY
A24: M 14–18 | B24: Masculino | C24: Ninguno | D24: 14–19 | E24: =IFERROR(IFERROR(INDEX(DRI_BASE!$H$2:$H$469,MATCH(1,INDEX((DRI_BASE!$B$2:$B$469=$G$7)*(DRI_BASE!$C$2:$C$469="Masculino")*(DRI_BASE!$D$2:$D$469=14)*(DRI_BASE!$G$2:$G$469="Ninguno"),0),0)),"ND"),"ND") -> 0 | F24: =IFERROR(IFERROR(INDEX(DRI_BASE!$I$2:$I$469,MATCH(1,INDEX((DRI_BASE!$B$2:$B$469=$G$7)*(DRI_BASE!$C$2:$C$469="Masculino")*(DRI_BASE!$D$2:$D$469=14)*(DRI_BASE!$G$2:$G$469="Ninguno"),0),0)),"ND"),"ND") -> 11 | G24: =IFERROR(IFERROR(INDEX(DRI_BASE!$J$2:$J$469,MATCH(1,INDEX((DRI_BASE!$B$2:$B$469=$G$7)*(DRI_BASE!$C$2:$C$469="Masculino")*(DRI_BASE!$D$2:$D$469=14)*(DRI_BASE!$G$2:$G$469="Ninguno"),0),0)),"ND"),"ND") -> 0 | H24: =IFERROR(IFERROR(INDEX(DRI_BASE!$T$2:$T$469,MATCH(1,INDEX((DRI_BASE!$B$2:$B$469=$G$7)*(DRI_BASE!$C$2:$C$469="Masculino")*(DRI_BASE!$D$2:$D$469=14)*(DRI_BASE!$G$2:$G$469="Ninguno"),0),0)),"ND"),"ND") -> 11 | I24: =IFERROR(IFERROR(INDEX(DRI_BASE!$R$2:$R$469,MATCH(1,INDEX((DRI_BASE!$B$2:$B$469=$G$7)*(DRI_BASE!$C$2:$C$469="Masculino")*(DRI_BASE!$D$2:$D$469=14)*(DRI_BASE!$G$2:$G$469="Ninguno"),0),0)),"ND"),"ND") -> RDA | J24: =IFERROR(IFERROR(INDEX(DRI_BASE!$K$2:$K$469,MATCH(1,INDEX((DRI_BASE!$B$2:$B$469=$G$7)*(DRI_BASE!$C$2:$C$469="Masculino")*(DRI_BASE!$D$2:$D$469=14)*(DRI_BASE!$G$2:$G$469="Ninguno"),0),0)),"ND"),"ND") -> 34 | K24: =IFERROR(IFERROR(INDEX(DRI_BASE!$Q$2:$Q$469,MATCH(1,INDEX((DRI_BASE!$B$2:$B$469=$G$7)*(DRI_BASE!$C$2:$C$469="Masculino")*(DRI_BASE!$D$2:$D$469=14)*(DRI_BASE!$G$2:$G$469="Ninguno"),0),0)),"ND"),"ND") -> 0 | L24: =IFERROR(IFERROR(INDEX(DRI_BASE!$U$2:$U$469,MATCH(1,INDEX((DRI_BASE!$B$2:$B$469=$G$7)*(DRI_BASE!$C$2:$C$469="Masculino")*(DRI_BASE!$D$2:$D$469=14)*(DRI_BASE!$G$2:$G$469="Ninguno"),0),0)),"ND"),"ND") -> 34 | M24: =IFERROR(IFERROR(INDEX(DRI_BASE!$S$2:$S$469,MATCH(1,INDEX((DRI_BASE!$B$2:$B$469=$G$7)*(DRI_BASE!$C$2:$C$469="Masculino")*(DRI_BASE!$D$2:$D$469=14)*(DRI_BASE!$G$2:$G$469="Ninguno"),0),0)),""),"") -> UL | N24: =IFERROR(IFERROR(INDEX(DRI_BASE!$L$2:$L$469,MATCH(1,INDEX((DRI_BASE!$B$2:$B$469=$G$7)*(DRI_BASE!$C$2:$C$469="Masculino")*(DRI_BASE!$D$2:$D$469=14)*(DRI_BASE!$G$2:$G$469="Ninguno"),0),0)),""),"") -> mg | O24: =IFERROR(IFERROR(INDEX(DRI_BASE!$M$2:$M$469,MATCH(1,INDEX((DRI_BASE!$B$2:$B$469=$G$7)*(DRI_BASE!$C$2:$C$469="Masculino")*(DRI_BASE!$D$2:$D$469=14)*(DRI_BASE!$G$2:$G$469="Ninguno"),0),0)),"ND"),"ND") -> SRC-DRI-SUMMARY
A25: F 14–18 | B25: Femenino | C25: Ninguno | D25: 14–19 | E25: =IFERROR(IFERROR(INDEX(DRI_BASE!$H$2:$H$469,MATCH(1,INDEX((DRI_BASE!$B$2:$B$469=$G$7)*(DRI_BASE!$C$2:$C$469="Femenino")*(DRI_BASE!$D$2:$D$469=14)*(DRI_BASE!$G$2:$G$469="Ninguno"),0),0)),"ND"),"ND") -> 0 | F25: =IFERROR(IFERROR(INDEX(DRI_BASE!$I$2:$I$469,MATCH(1,INDEX((DRI_BASE!$B$2:$B$469=$G$7)*(DRI_BASE!$C$2:$C$469="Femenino")*(DRI_BASE!$D$2:$D$469=14)*(DRI_BASE!$G$2:$G$469="Ninguno"),0),0)),"ND"),"ND") -> 9 | G25: =IFERROR(IFERROR(INDEX(DRI_BASE!$J$2:$J$469,MATCH(1,INDEX((DRI_BASE!$B$2:$B$469=$G$7)*(DRI_BASE!$C$2:$C$469="Femenino")*(DRI_BASE!$D$2:$D$469=14)*(DRI_BASE!$G$2:$G$469="Ninguno"),0),0)),"ND"),"ND") -> 0 | H25: =IFERROR(IFERROR(INDEX(DRI_BASE!$T$2:$T$469,MATCH(1,INDEX((DRI_BASE!$B$2:$B$469=$G$7)*(DRI_BASE!$C$2:$C$469="Femenino")*(DRI_BASE!$D$2:$D$469=14)*(DRI_BASE!$G$2:$G$469="Ninguno"),0),0)),"ND"),"ND") -> 9 | I25: =IFERROR(IFERROR(INDEX(DRI_BASE!$R$2:$R$469,MATCH(1,INDEX((DRI_BASE!$B$2:$B$469=$G$7)*(DRI_BASE!$C$2:$C$469="Femenino")*(DRI_BASE!$D$2:$D$469=14)*(DRI_BASE!$G$2:$G$469="Ninguno"),0),0)),"ND"),"ND") -> RDA | J25: =IFERROR(IFERROR(INDEX(DRI_BASE!$K$2:$K$469,MATCH(1,INDEX((DRI_BASE!$B$2:$B$469=$G$7)*(DRI_BASE!$C$2:$C$469="Femenino")*(DRI_BASE!$D$2:$D$469=14)*(DRI_BASE!$G$2:$G$469="Ninguno"),0),0)),"ND"),"ND") -> 34 | K25: =IFERROR(IFERROR(INDEX(DRI_BASE!$Q$2:$Q$469,MATCH(1,INDEX((DRI_BASE!$B$2:$B$469=$G$7)*(DRI_BASE!$C$2:$C$469="Femenino")*(DRI_BASE!$D$2:$D$469=14)*(DRI_BASE!$G$2:$G$469="Ninguno"),0),0)),"ND"),"ND") -> 0 | L25: =IFERROR(IFERROR(INDEX(DRI_BASE!$U$2:$U$469,MATCH(1,INDEX((DRI_BASE!$B$2:$B$469=$G$7)*(DRI_BASE!$C$2:$C$469="Femenino")*(DRI_BASE!$D$2:$D$469=14)*(DRI_BASE!$G$2:$G$469="Ninguno"),0),0)),"ND"),"ND") -> 34 | M25: =IFERROR(IFERROR(INDEX(DRI_BASE!$S$2:$S$469,MATCH(1,INDEX((DRI_BASE!$B$2:$B$469=$G$7)*(DRI_BASE!$C$2:$C$469="Femenino")*(DRI_BASE!$D$2:$D$469=14)*(DRI_BASE!$G$2:$G$469="Ninguno"),0),0)),""),"") -> UL | N25: =IFERROR(IFERROR(INDEX(DRI_BASE!$L$2:$L$469,MATCH(1,INDEX((DRI_BASE!$B$2:$B$469=$G$7)*(DRI_BASE!$C$2:$C$469="Femenino")*(DRI_BASE!$D$2:$D$469=14)*(DRI_BASE!$G$2:$G$469="Ninguno"),0),0)),""),"") -> mg | O25: =IFERROR(IFERROR(INDEX(DRI_BASE!$M$2:$M$469,MATCH(1,INDEX((DRI_BASE!$B$2:$B$469=$G$7)*(DRI_BASE!$C$2:$C$469="Femenino")*(DRI_BASE!$D$2:$D$469=14)*(DRI_BASE!$G$2:$G$469="Ninguno"),0),0)),"ND"),"ND") -> SRC-DRI-SUMMARY
A26: M 19–30 | B26: Masculino | C26: Ninguno | D26: 19–31 | E26: =IFERROR(IFERROR(INDEX(DRI_BASE!$H$2:$H$469,MATCH(1,INDEX((DRI_BASE!$B$2:$B$469=$G$7)*(DRI_BASE!$C$2:$C$469="Masculino")*(DRI_BASE!$D$2:$D$469=19)*(DRI_BASE!$G$2:$G$469="Ninguno"),0),0)),"ND"),"ND") -> 0 | F26: =IFERROR(IFERROR(INDEX(DRI_BASE!$I$2:$I$469,MATCH(1,INDEX((DRI_BASE!$B$2:$B$469=$G$7)*(DRI_BASE!$C$2:$C$469="Masculino")*(DRI_BASE!$D$2:$D$469=19)*(DRI_BASE!$G$2:$G$469="Ninguno"),0),0)),"ND"),"ND") -> 11 | G26: =IFERROR(IFERROR(INDEX(DRI_BASE!$J$2:$J$469,MATCH(1,INDEX((DRI_BASE!$B$2:$B$469=$G$7)*(DRI_BASE!$C$2:$C$469="Masculino")*(DRI_BASE!$D$2:$D$469=19)*(DRI_BASE!$G$2:$G$469="Ninguno"),0),0)),"ND"),"ND") -> 0 | H26: =IFERROR(IFERROR(INDEX(DRI_BASE!$T$2:$T$469,MATCH(1,INDEX((DRI_BASE!$B$2:$B$469=$G$7)*(DRI_BASE!$C$2:$C$469="Masculino")*(DRI_BASE!$D$2:$D$469=19)*(DRI_BASE!$G$2:$G$469="Ninguno"),0),0)),"ND"),"ND") -> 11 | I26: =IFERROR(IFERROR(INDEX(DRI_BASE!$R$2:$R$469,MATCH(1,INDEX((DRI_BASE!$B$2:$B$469=$G$7)*(DRI_BASE!$C$2:$C$469="Masculino")*(DRI_BASE!$D$2:$D$469=19)*(DRI_BASE!$G$2:$G$469="Ninguno"),0),0)),"ND"),"ND") -> RDA | J26: =IFERROR(IFERROR(INDEX(DRI_BASE!$K$2:$K$469,MATCH(1,INDEX((DRI_BASE!$B$2:$B$469=$G$7)*(DRI_BASE!$C$2:$C$469="Masculino")*(DRI_BASE!$D$2:$D$469=19)*(DRI_BASE!$G$2:$G$469="Ninguno"),0),0)),"ND"),"ND") -> 40 | K26: =IFERROR(IFERROR(INDEX(DRI_BASE!$Q$2:$Q$469,MATCH(1,INDEX((DRI_BASE!$B$2:$B$469=$G$7)*(DRI_BASE!$C$2:$C$469="Masculino")*(DRI_BASE!$D$2:$D$469=19)*(DRI_BASE!$G$2:$G$469="Ninguno"),0),0)),"ND"),"ND") -> 0 | L26: =IFERROR(IFERROR(INDEX(DRI_BASE!$U$2:$U$469,MATCH(1,INDEX((DRI_BASE!$B$2:$B$469=$G$7)*(DRI_BASE!$C$2:$C$469="Masculino")*(DRI_BASE!$D$2:$D$469=19)*(DRI_BASE!$G$2:$G$469="Ninguno"),0),0)),"ND"),"ND") -> 40 | M26: =IFERROR(IFERROR(INDEX(DRI_BASE!$S$2:$S$469,MATCH(1,INDEX((DRI_BASE!$B$2:$B$469=$G$7)*(DRI_BASE!$C$2:$C$469="Masculino")*(DRI_BASE!$D$2:$D$469=19)*(DRI_BASE!$G$2:$G$469="Ninguno"),0),0)),""),"") -> UL | N26: =IFERROR(IFERROR(INDEX(DRI_BASE!$L$2:$L$469,MATCH(1,INDEX((DRI_BASE!$B$2:$B$469=$G$7)*(DRI_BASE!$C$2:$C$469="Masculino")*(DRI_BASE!$D$2:$D$469=19)*(DRI_BASE!$G$2:$G$469="Ninguno"),0),0)),""),"") -> mg | O26: =IFERROR(IFERROR(INDEX(DRI_BASE!$M$2:$M$469,MATCH(1,INDEX((DRI_BASE!$B$2:$B$469=$G$7)*(DRI_BASE!$C$2:$C$469="Masculino")*(DRI_BASE!$D$2:$D$469=19)*(DRI_BASE!$G$2:$G$469="Ninguno"),0),0)),"ND"),"ND") -> SRC-DRI-SUMMARY
A27: F 19–30 | B27: Femenino | C27: Ninguno | D27: 19–31 | E27: =IFERROR(IFERROR(INDEX(DRI_BASE!$H$2:$H$469,MATCH(1,INDEX((DRI_BASE!$B$2:$B$469=$G$7)*(DRI_BASE!$C$2:$C$469="Femenino")*(DRI_BASE!$D$2:$D$469=19)*(DRI_BASE!$G$2:$G$469="Ninguno"),0),0)),"ND"),"ND") -> 0 | F27: =IFERROR(IFERROR(INDEX(DRI_BASE!$I$2:$I$469,MATCH(1,INDEX((DRI_BASE!$B$2:$B$469=$G$7)*(DRI_BASE!$C$2:$C$469="Femenino")*(DRI_BASE!$D$2:$D$469=19)*(DRI_BASE!$G$2:$G$469="Ninguno"),0),0)),"ND"),"ND") -> 8 | G27: =IFERROR(IFERROR(INDEX(DRI_BASE!$J$2:$J$469,MATCH(1,INDEX((DRI_BASE!$B$2:$B$469=$G$7)*(DRI_BASE!$C$2:$C$469="Femenino")*(DRI_BASE!$D$2:$D$469=19)*(DRI_BASE!$G$2:$G$469="Ninguno"),0),0)),"ND"),"ND") -> 0 | H27: =IFERROR(IFERROR(INDEX(DRI_BASE!$T$2:$T$469,MATCH(1,INDEX((DRI_BASE!$B$2:$B$469=$G$7)*(DRI_BASE!$C$2:$C$469="Femenino")*(DRI_BASE!$D$2:$D$469=19)*(DRI_BASE!$G$2:$G$469="Ninguno"),0),0)),"ND"),"ND") -> 8 | I27: =IFERROR(IFERROR(INDEX(DRI_BASE!$R$2:$R$469,MATCH(1,INDEX((DRI_BASE!$B$2:$B$469=$G$7)*(DRI_BASE!$C$2:$C$469="Femenino")*(DRI_BASE!$D$2:$D$469=19)*(DRI_BASE!$G$2:$G$469="Ninguno"),0),0)),"ND"),"ND") -> RDA | J27: =IFERROR(IFERROR(INDEX(DRI_BASE!$K$2:$K$469,MATCH(1,INDEX((DRI_BASE!$B$2:$B$469=$G$7)*(DRI_BASE!$C$2:$C$469="Femenino")*(DRI_BASE!$D$2:$D$469=19)*(DRI_BASE!$G$2:$G$469="Ninguno"),0),0)),"ND"),"ND") -> 40 | K27: =IFERROR(IFERROR(INDEX(DRI_BASE!$Q$2:$Q$469,MATCH(1,INDEX((DRI_BASE!$B$2:$B$469=$G$7)*(DRI_BASE!$C$2:$C$469="Femenino")*(DRI_BASE!$D$2:$D$469=19)*(DRI_BASE!$G$2:$G$469="Ninguno"),0),0)),"ND"),"ND") -> 0 | L27: =IFERROR(IFERROR(INDEX(DRI_BASE!$U$2:$U$469,MATCH(1,INDEX((DRI_BASE!$B$2:$B$469=$G$7)*(DRI_BASE!$C$2:$C$469="Femenino")*(DRI_BASE!$D$2:$D$469=19)*(DRI_BASE!$G$2:$G$469="Ninguno"),0),0)),"ND"),"ND") -> 40 | M27: =IFERROR(IFERROR(INDEX(DRI_BASE!$S$2:$S$469,MATCH(1,INDEX((DRI_BASE!$B$2:$B$469=$G$7)*(DRI_BASE!$C$2:$C$469="Femenino")*(DRI_BASE!$D$2:$D$469=19)*(DRI_BASE!$G$2:$G$469="Ninguno"),0),0)),""),"") -> UL | N27: =IFERROR(IFERROR(INDEX(DRI_BASE!$L$2:$L$469,MATCH(1,INDEX((DRI_BASE!$B$2:$B$469=$G$7)*(DRI_BASE!$C$2:$C$469="Femenino")*(DRI_BASE!$D$2:$D$469=19)*(DRI_BASE!$G$2:$G$469="Ninguno"),0),0)),""),"") -> mg | O27: =IFERROR(IFERROR(INDEX(DRI_BASE!$M$2:$M$469,MATCH(1,INDEX((DRI_BASE!$B$2:$B$469=$G$7)*(DRI_BASE!$C$2:$C$469="Femenino")*(DRI_BASE!$D$2:$D$469=19)*(DRI_BASE!$G$2:$G$469="Ninguno"),0),0)),"ND"),"ND") -> SRC-DRI-SUMMARY
A28: M 31–50 | B28: Masculino | C28: Ninguno | D28: 31–51 | E28: =IFERROR(IFERROR(INDEX(DRI_BASE!$H$2:$H$469,MATCH(1,INDEX((DRI_BASE!$B$2:$B$469=$G$7)*(DRI_BASE!$C$2:$C$469="Masculino")*(DRI_BASE!$D$2:$D$469=31)*(DRI_BASE!$G$2:$G$469="Ninguno"),0),0)),"ND"),"ND") -> 0 | F28: =IFERROR(IFERROR(INDEX(DRI_BASE!$I$2:$I$469,MATCH(1,INDEX((DRI_BASE!$B$2:$B$469=$G$7)*(DRI_BASE!$C$2:$C$469="Masculino")*(DRI_BASE!$D$2:$D$469=31)*(DRI_BASE!$G$2:$G$469="Ninguno"),0),0)),"ND"),"ND") -> 11 | G28: =IFERROR(IFERROR(INDEX(DRI_BASE!$J$2:$J$469,MATCH(1,INDEX((DRI_BASE!$B$2:$B$469=$G$7)*(DRI_BASE!$C$2:$C$469="Masculino")*(DRI_BASE!$D$2:$D$469=31)*(DRI_BASE!$G$2:$G$469="Ninguno"),0),0)),"ND"),"ND") -> 0 | H28: =IFERROR(IFERROR(INDEX(DRI_BASE!$T$2:$T$469,MATCH(1,INDEX((DRI_BASE!$B$2:$B$469=$G$7)*(DRI_BASE!$C$2:$C$469="Masculino")*(DRI_BASE!$D$2:$D$469=31)*(DRI_BASE!$G$2:$G$469="Ninguno"),0),0)),"ND"),"ND") -> 11 | I28: =IFERROR(IFERROR(INDEX(DRI_BASE!$R$2:$R$469,MATCH(1,INDEX((DRI_BASE!$B$2:$B$469=$G$7)*(DRI_BASE!$C$2:$C$469="Masculino")*(DRI_BASE!$D$2:$D$469=31)*(DRI_BASE!$G$2:$G$469="Ninguno"),0),0)),"ND"),"ND") -> RDA | J28: =IFERROR(IFERROR(INDEX(DRI_BASE!$K$2:$K$469,MATCH(1,INDEX((DRI_BASE!$B$2:$B$469=$G$7)*(DRI_BASE!$C$2:$C$469="Masculino")*(DRI_BASE!$D$2:$D$469=31)*(DRI_BASE!$G$2:$G$469="Ninguno"),0),0)),"ND"),"ND") -> 40 | K28: =IFERROR(IFERROR(INDEX(DRI_BASE!$Q$2:$Q$469,MATCH(1,INDEX((DRI_BASE!$B$2:$B$469=$G$7)*(DRI_BASE!$C$2:$C$469="Masculino")*(DRI_BASE!$D$2:$D$469=31)*(DRI_BASE!$G$2:$G$469="Ninguno"),0),0)),"ND"),"ND") -> 0 | L28: =IFERROR(IFERROR(INDEX(DRI_BASE!$U$2:$U$469,MATCH(1,INDEX((DRI_BASE!$B$2:$B$469=$G$7)*(DRI_BASE!$C$2:$C$469="Masculino")*(DRI_BASE!$D$2:$D$469=31)*(DRI_BASE!$G$2:$G$469="Ninguno"),0),0)),"ND"),"ND") -> 40 | M28: =IFERROR(IFERROR(INDEX(DRI_BASE!$S$2:$S$469,MATCH(1,INDEX((DRI_BASE!$B$2:$B$469=$G$7)*(DRI_BASE!$C$2:$C$469="Masculino")*(DRI_BASE!$D$2:$D$469=31)*(DRI_BASE!$G$2:$G$469="Ninguno"),0),0)),""),"") -> UL | N28: =IFERROR(IFERROR(INDEX(DRI_BASE!$L$2:$L$469,MATCH(1,INDEX((DRI_BASE!$B$2:$B$469=$G$7)*(DRI_BASE!$C$2:$C$469="Masculino")*(DRI_BASE!$D$2:$D$469=31)*(DRI_BASE!$G$2:$G$469="Ninguno"),0),0)),""),"") -> mg | O28: =IFERROR(IFERROR(INDEX(DRI_BASE!$M$2:$M$469,MATCH(1,INDEX((DRI_BASE!$B$2:$B$469=$G$7)*(DRI_BASE!$C$2:$C$469="Masculino")*(DRI_BASE!$D$2:$D$469=31)*(DRI_BASE!$G$2:$G$469="Ninguno"),0),0)),"ND"),"ND") -> SRC-DRI-SUMMARY
A29: F 31–50 | B29: Femenino | C29: Ninguno | D29: 31–51 | E29: =IFERROR(IFERROR(INDEX(DRI_BASE!$H$2:$H$469,MATCH(1,INDEX((DRI_BASE!$B$2:$B$469=$G$7)*(DRI_BASE!$C$2:$C$469="Femenino")*(DRI_BASE!$D$2:$D$469=31)*(DRI_BASE!$G$2:$G$469="Ninguno"),0),0)),"ND"),"ND") -> 0 | F29: =IFERROR(IFERROR(INDEX(DRI_BASE!$I$2:$I$469,MATCH(1,INDEX((DRI_BASE!$B$2:$B$469=$G$7)*(DRI_BASE!$C$2:$C$469="Femenino")*(DRI_BASE!$D$2:$D$469=31)*(DRI_BASE!$G$2:$G$469="Ninguno"),0),0)),"ND"),"ND") -> 8 | G29: =IFERROR(IFERROR(INDEX(DRI_BASE!$J$2:$J$469,MATCH(1,INDEX((DRI_BASE!$B$2:$B$469=$G$7)*(DRI_BASE!$C$2:$C$469="Femenino")*(DRI_BASE!$D$2:$D$469=31)*(DRI_BASE!$G$2:$G$469="Ninguno"),0),0)),"ND"),"ND") -> 0 | H29: =IFERROR(IFERROR(INDEX(DRI_BASE!$T$2:$T$469,MATCH(1,INDEX((DRI_BASE!$B$2:$B$469=$G$7)*(DRI_BASE!$C$2:$C$469="Femenino")*(DRI_BASE!$D$2:$D$469=31)*(DRI_BASE!$G$2:$G$469="Ninguno"),0),0)),"ND"),"ND") -> 8 | I29: =IFERROR(IFERROR(INDEX(DRI_BASE!$R$2:$R$469,MATCH(1,INDEX((DRI_BASE!$B$2:$B$469=$G$7)*(DRI_BASE!$C$2:$C$469="Femenino")*(DRI_BASE!$D$2:$D$469=31)*(DRI_BASE!$G$2:$G$469="Ninguno"),0),0)),"ND"),"ND") -> RDA | J29: =IFERROR(IFERROR(INDEX(DRI_BASE!$K$2:$K$469,MATCH(1,INDEX((DRI_BASE!$B$2:$B$469=$G$7)*(DRI_BASE!$C$2:$C$469="Femenino")*(DRI_BASE!$D$2:$D$469=31)*(DRI_BASE!$G$2:$G$469="Ninguno"),0),0)),"ND"),"ND") -> 40 | K29: =IFERROR(IFERROR(INDEX(DRI_BASE!$Q$2:$Q$469,MATCH(1,INDEX((DRI_BASE!$B$2:$B$469=$G$7)*(DRI_BASE!$C$2:$C$469="Femenino")*(DRI_BASE!$D$2:$D$469=31)*(DRI_BASE!$G$2:$G$469="Ninguno"),0),0)),"ND"),"ND") -> 0 | L29: =IFERROR(IFERROR(INDEX(DRI_BASE!$U$2:$U$469,MATCH(1,INDEX((DRI_BASE!$B$2:$B$469=$G$7)*(DRI_BASE!$C$2:$C$469="Femenino")*(DRI_BASE!$D$2:$D$469=31)*(DRI_BASE!$G$2:$G$469="Ninguno"),0),0)),"ND"),"ND") -> 40 | M29: =IFERROR(IFERROR(INDEX(DRI_BASE!$S$2:$S$469,MATCH(1,INDEX((DRI_BASE!$B$2:$B$469=$G$7)*(DRI_BASE!$C$2:$C$469="Femenino")*(DRI_BASE!$D$2:$D$469=31)*(DRI_BASE!$G$2:$G$469="Ninguno"),0),0)),""),"") -> UL | N29: =IFERROR(IFERROR(INDEX(DRI_BASE!$L$2:$L$469,MATCH(1,INDEX((DRI_BASE!$B$2:$B$469=$G$7)*(DRI_BASE!$C$2:$C$469="Femenino")*(DRI_BASE!$D$2:$D$469=31)*(DRI_BASE!$G$2:$G$469="Ninguno"),0),0)),""),"") -> mg | O29: =IFERROR(IFERROR(INDEX(DRI_BASE!$M$2:$M$469,MATCH(1,INDEX((DRI_BASE!$B$2:$B$469=$G$7)*(DRI_BASE!$C$2:$C$469="Femenino")*(DRI_BASE!$D$2:$D$469=31)*(DRI_BASE!$G$2:$G$469="Ninguno"),0),0)),"ND"),"ND") -> SRC-DRI-SUMMARY
A30: M 51–70 | B30: Masculino | C30: Ninguno | D30: 51–71 | E30: =IFERROR(IFERROR(INDEX(DRI_BASE!$H$2:$H$469,MATCH(1,INDEX((DRI_BASE!$B$2:$B$469=$G$7)*(DRI_BASE!$C$2:$C$469="Masculino")*(DRI_BASE!$D$2:$D$469=51)*(DRI_BASE!$G$2:$G$469="Ninguno"),0),0)),"ND"),"ND") -> 0 | F30: =IFERROR(IFERROR(INDEX(DRI_BASE!$I$2:$I$469,MATCH(1,INDEX((DRI_BASE!$B$2:$B$469=$G$7)*(DRI_BASE!$C$2:$C$469="Masculino")*(DRI_BASE!$D$2:$D$469=51)*(DRI_BASE!$G$2:$G$469="Ninguno"),0),0)),"ND"),"ND") -> 11 | G30: =IFERROR(IFERROR(INDEX(DRI_BASE!$J$2:$J$469,MATCH(1,INDEX((DRI_BASE!$B$2:$B$469=$G$7)*(DRI_BASE!$C$2:$C$469="Masculino")*(DRI_BASE!$D$2:$D$469=51)*(DRI_BASE!$G$2:$G$469="Ninguno"),0),0)),"ND"),"ND") -> 0 | H30: =IFERROR(IFERROR(INDEX(DRI_BASE!$T$2:$T$469,MATCH(1,INDEX((DRI_BASE!$B$2:$B$469=$G$7)*(DRI_BASE!$C$2:$C$469="Masculino")*(DRI_BASE!$D$2:$D$469=51)*(DRI_BASE!$G$2:$G$469="Ninguno"),0),0)),"ND"),"ND") -> 11 | I30: =IFERROR(IFERROR(INDEX(DRI_BASE!$R$2:$R$469,MATCH(1,INDEX((DRI_BASE!$B$2:$B$469=$G$7)*(DRI_BASE!$C$2:$C$469="Masculino")*(DRI_BASE!$D$2:$D$469=51)*(DRI_BASE!$G$2:$G$469="Ninguno"),0),0)),"ND"),"ND") -> RDA | J30: =IFERROR(IFERROR(INDEX(DRI_BASE!$K$2:$K$469,MATCH(1,INDEX((DRI_BASE!$B$2:$B$469=$G$7)*(DRI_BASE!$C$2:$C$469="Masculino")*(DRI_BASE!$D$2:$D$469=51)*(DRI_BASE!$G$2:$G$469="Ninguno"),0),0)),"ND"),"ND") -> 40 | K30: =IFERROR(IFERROR(INDEX(DRI_BASE!$Q$2:$Q$469,MATCH(1,INDEX((DRI_BASE!$B$2:$B$469=$G$7)*(DRI_BASE!$C$2:$C$469="Masculino")*(DRI_BASE!$D$2:$D$469=51)*(DRI_BASE!$G$2:$G$469="Ninguno"),0),0)),"ND"),"ND") -> 0 | L30: =IFERROR(IFERROR(INDEX(DRI_BASE!$U$2:$U$469,MATCH(1,INDEX((DRI_BASE!$B$2:$B$469=$G$7)*(DRI_BASE!$C$2:$C$469="Masculino")*(DRI_BASE!$D$2:$D$469=51)*(DRI_BASE!$G$2:$G$469="Ninguno"),0),0)),"ND"),"ND") -> 40 | M30: =IFERROR(IFERROR(INDEX(DRI_BASE!$S$2:$S$469,MATCH(1,INDEX((DRI_BASE!$B$2:$B$469=$G$7)*(DRI_BASE!$C$2:$C$469="Masculino")*(DRI_BASE!$D$2:$D$469=51)*(DRI_BASE!$G$2:$G$469="Ninguno"),0),0)),""),"") -> UL | N30: =IFERROR(IFERROR(INDEX(DRI_BASE!$L$2:$L$469,MATCH(1,INDEX((DRI_BASE!$B$2:$B$469=$G$7)*(DRI_BASE!$C$2:$C$469="Masculino")*(DRI_BASE!$D$2:$D$469=51)*(DRI_BASE!$G$2:$G$469="Ninguno"),0),0)),""),"") -> mg | O30: =IFERROR(IFERROR(INDEX(DRI_BASE!$M$2:$M$469,MATCH(1,INDEX((DRI_BASE!$B$2:$B$469=$G$7)*(DRI_BASE!$C$2:$C$469="Masculino")*(DRI_BASE!$D$2:$D$469=51)*(DRI_BASE!$G$2:$G$469="Ninguno"),0),0)),"ND"),"ND") -> SRC-DRI-SUMMARY
A31: F 51–70 | B31: Femenino | C31: Ninguno | D31: 51–71 | E31: =IFERROR(IFERROR(INDEX(DRI_BASE!$H$2:$H$469,MATCH(1,INDEX((DRI_BASE!$B$2:$B$469=$G$7)*(DRI_BASE!$C$2:$C$469="Femenino")*(DRI_BASE!$D$2:$D$469=51)*(DRI_BASE!$G$2:$G$469="Ninguno"),0),0)),"ND"),"ND") -> 0 | F31: =IFERROR(IFERROR(INDEX(DRI_BASE!$I$2:$I$469,MATCH(1,INDEX((DRI_BASE!$B$2:$B$469=$G$7)*(DRI_BASE!$C$2:$C$469="Femenino")*(DRI_BASE!$D$2:$D$469=51)*(DRI_BASE!$G$2:$G$469="Ninguno"),0),0)),"ND"),"ND") -> 8 | G31: =IFERROR(IFERROR(INDEX(DRI_BASE!$J$2:$J$469,MATCH(1,INDEX((DRI_BASE!$B$2:$B$469=$G$7)*(DRI_BASE!$C$2:$C$469="Femenino")*(DRI_BASE!$D$2:$D$469=51)*(DRI_BASE!$G$2:$G$469="Ninguno"),0),0)),"ND"),"ND") -> 0 | H31: =IFERROR(IFERROR(INDEX(DRI_BASE!$T$2:$T$469,MATCH(1,INDEX((DRI_BASE!$B$2:$B$469=$G$7)*(DRI_BASE!$C$2:$C$469="Femenino")*(DRI_BASE!$D$2:$D$469=51)*(DRI_BASE!$G$2:$G$469="Ninguno"),0),0)),"ND"),"ND") -> 8 | I31: =IFERROR(IFERROR(INDEX(DRI_BASE!$R$2:$R$469,MATCH(1,INDEX((DRI_BASE!$B$2:$B$469=$G$7)*(DRI_BASE!$C$2:$C$469="Femenino")*(DRI_BASE!$D$2:$D$469=51)*(DRI_BASE!$G$2:$G$469="Ninguno"),0),0)),"ND"),"ND") -> RDA | J31: =IFERROR(IFERROR(INDEX(DRI_BASE!$K$2:$K$469,MATCH(1,INDEX((DRI_BASE!$B$2:$B$469=$G$7)*(DRI_BASE!$C$2:$C$469="Femenino")*(DRI_BASE!$D$2:$D$469=51)*(DRI_BASE!$G$2:$G$469="Ninguno"),0),0)),"ND"),"ND") -> 40 | K31: =IFERROR(IFERROR(INDEX(DRI_BASE!$Q$2:$Q$469,MATCH(1,INDEX((DRI_BASE!$B$2:$B$469=$G$7)*(DRI_BASE!$C$2:$C$469="Femenino")*(DRI_BASE!$D$2:$D$469=51)*(DRI_BASE!$G$2:$G$469="Ninguno"),0),0)),"ND"),"ND") -> 0 | L31: =IFERROR(IFERROR(INDEX(DRI_BASE!$U$2:$U$469,MATCH(1,INDEX((DRI_BASE!$B$2:$B$469=$G$7)*(DRI_BASE!$C$2:$C$469="Femenino")*(DRI_BASE!$D$2:$D$469=51)*(DRI_BASE!$G$2:$G$469="Ninguno"),0),0)),"ND"),"ND") -> 40 | M31: =IFERROR(IFERROR(INDEX(DRI_BASE!$S$2:$S$469,MATCH(1,INDEX((DRI_BASE!$B$2:$B$469=$G$7)*(DRI_BASE!$C$2:$C$469="Femenino")*(DRI_BASE!$D$2:$D$469=51)*(DRI_BASE!$G$2:$G$469="Ninguno"),0),0)),""),"") -> UL | N31: =IFERROR(IFERROR(INDEX(DRI_BASE!$L$2:$L$469,MATCH(1,INDEX((DRI_BASE!$B$2:$B$469=$G$7)*(DRI_BASE!$C$2:$C$469="Femenino")*(DRI_BASE!$D$2:$D$469=51)*(DRI_BASE!$G$2:$G$469="Ninguno"),0),0)),""),"") -> mg | O31: =IFERROR(IFERROR(INDEX(DRI_BASE!$M$2:$M$469,MATCH(1,INDEX((DRI_BASE!$B$2:$B$469=$G$7)*(DRI_BASE!$C$2:$C$469="Femenino")*(DRI_BASE!$D$2:$D$469=51)*(DRI_BASE!$G$2:$G$469="Ninguno"),0),0)),"ND"),"ND") -> SRC-DRI-SUMMARY
A32: M >70 | B32: Masculino | C32: Ninguno | D32: 71–999 | E32: =IFERROR(IFERROR(INDEX(DRI_BASE!$H$2:$H$469,MATCH(1,INDEX((DRI_BASE!$B$2:$B$469=$G$7)*(DRI_BASE!$C$2:$C$469="Masculino")*(DRI_BASE!$D$2:$D$469=71)*(DRI_BASE!$G$2:$G$469="Ninguno"),0),0)),"ND"),"ND") -> 0 | F32: =IFERROR(IFERROR(INDEX(DRI_BASE!$I$2:$I$469,MATCH(1,INDEX((DRI_BASE!$B$2:$B$469=$G$7)*(DRI_BASE!$C$2:$C$469="Masculino")*(DRI_BASE!$D$2:$D$469=71)*(DRI_BASE!$G$2:$G$469="Ninguno"),0),0)),"ND"),"ND") -> 11 | G32: =IFERROR(IFERROR(INDEX(DRI_BASE!$J$2:$J$469,MATCH(1,INDEX((DRI_BASE!$B$2:$B$469=$G$7)*(DRI_BASE!$C$2:$C$469="Masculino")*(DRI_BASE!$D$2:$D$469=71)*(DRI_BASE!$G$2:$G$469="Ninguno"),0),0)),"ND"),"ND") -> 0 | H32: =IFERROR(IFERROR(INDEX(DRI_BASE!$T$2:$T$469,MATCH(1,INDEX((DRI_BASE!$B$2:$B$469=$G$7)*(DRI_BASE!$C$2:$C$469="Masculino")*(DRI_BASE!$D$2:$D$469=71)*(DRI_BASE!$G$2:$G$469="Ninguno"),0),0)),"ND"),"ND") -> 11 | I32: =IFERROR(IFERROR(INDEX(DRI_BASE!$R$2:$R$469,MATCH(1,INDEX((DRI_BASE!$B$2:$B$469=$G$7)*(DRI_BASE!$C$2:$C$469="Masculino")*(DRI_BASE!$D$2:$D$469=71)*(DRI_BASE!$G$2:$G$469="Ninguno"),0),0)),"ND"),"ND") -> RDA | J32: =IFERROR(IFERROR(INDEX(DRI_BASE!$K$2:$K$469,MATCH(1,INDEX((DRI_BASE!$B$2:$B$469=$G$7)*(DRI_BASE!$C$2:$C$469="Masculino")*(DRI_BASE!$D$2:$D$469=71)*(DRI_BASE!$G$2:$G$469="Ninguno"),0),0)),"ND"),"ND") -> 40 | K32: =IFERROR(IFERROR(INDEX(DRI_BASE!$Q$2:$Q$469,MATCH(1,INDEX((DRI_BASE!$B$2:$B$469=$G$7)*(DRI_BASE!$C$2:$C$469="Masculino")*(DRI_BASE!$D$2:$D$469=71)*(DRI_BASE!$G$2:$G$469="Ninguno"),0),0)),"ND"),"ND") -> 0 | L32: =IFERROR(IFERROR(INDEX(DRI_BASE!$U$2:$U$469,MATCH(1,INDEX((DRI_BASE!$B$2:$B$469=$G$7)*(DRI_BASE!$C$2:$C$469="Masculino")*(DRI_BASE!$D$2:$D$469=71)*(DRI_BASE!$G$2:$G$469="Ninguno"),0),0)),"ND"),"ND") -> 40 | M32: =IFERROR(IFERROR(INDEX(DRI_BASE!$S$2:$S$469,MATCH(1,INDEX((DRI_BASE!$B$2:$B$469=$G$7)*(DRI_BASE!$C$2:$C$469="Masculino")*(DRI_BASE!$D$2:$D$469=71)*(DRI_BASE!$G$2:$G$469="Ninguno"),0),0)),""),"") -> UL | N32: =IFERROR(IFERROR(INDEX(DRI_BASE!$L$2:$L$469,MATCH(1,INDEX((DRI_BASE!$B$2:$B$469=$G$7)*(DRI_BASE!$C$2:$C$469="Masculino")*(DRI_BASE!$D$2:$D$469=71)*(DRI_BASE!$G$2:$G$469="Ninguno"),0),0)),""),"") -> mg | O32: =IFERROR(IFERROR(INDEX(DRI_BASE!$M$2:$M$469,MATCH(1,INDEX((DRI_BASE!$B$2:$B$469=$G$7)*(DRI_BASE!$C$2:$C$469="Masculino")*(DRI_BASE!$D$2:$D$469=71)*(DRI_BASE!$G$2:$G$469="Ninguno"),0),0)),"ND"),"ND") -> SRC-DRI-SUMMARY
A33: F >70 | B33: Femenino | C33: Ninguno | D33: 71–999 | E33: =IFERROR(IFERROR(INDEX(DRI_BASE!$H$2:$H$469,MATCH(1,INDEX((DRI_BASE!$B$2:$B$469=$G$7)*(DRI_BASE!$C$2:$C$469="Femenino")*(DRI_BASE!$D$2:$D$469=71)*(DRI_BASE!$G$2:$G$469="Ninguno"),0),0)),"ND"),"ND") -> 0 | F33: =IFERROR(IFERROR(INDEX(DRI_BASE!$I$2:$I$469,MATCH(1,INDEX((DRI_BASE!$B$2:$B$469=$G$7)*(DRI_BASE!$C$2:$C$469="Femenino")*(DRI_BASE!$D$2:$D$469=71)*(DRI_BASE!$G$2:$G$469="Ninguno"),0),0)),"ND"),"ND") -> 8 | G33: =IFERROR(IFERROR(INDEX(DRI_BASE!$J$2:$J$469,MATCH(1,INDEX((DRI_BASE!$B$2:$B$469=$G$7)*(DRI_BASE!$C$2:$C$469="Femenino")*(DRI_BASE!$D$2:$D$469=71)*(DRI_BASE!$G$2:$G$469="Ninguno"),0),0)),"ND"),"ND") -> 0 | H33: =IFERROR(IFERROR(INDEX(DRI_BASE!$T$2:$T$469,MATCH(1,INDEX((DRI_BASE!$B$2:$B$469=$G$7)*(DRI_BASE!$C$2:$C$469="Femenino")*(DRI_BASE!$D$2:$D$469=71)*(DRI_BASE!$G$2:$G$469="Ninguno"),0),0)),"ND"),"ND") -> 8 | I33: =IFERROR(IFERROR(INDEX(DRI_BASE!$R$2:$R$469,MATCH(1,INDEX((DRI_BASE!$B$2:$B$469=$G$7)*(DRI_BASE!$C$2:$C$469="Femenino")*(DRI_BASE!$D$2:$D$469=71)*(DRI_BASE!$G$2:$G$469="Ninguno"),0),0)),"ND"),"ND") -> RDA | J33: =IFERROR(IFERROR(INDEX(DRI_BASE!$K$2:$K$469,MATCH(1,INDEX((DRI_BASE!$B$2:$B$469=$G$7)*(DRI_BASE!$C$2:$C$469="Femenino")*(DRI_BASE!$D$2:$D$469=71)*(DRI_BASE!$G$2:$G$469="Ninguno"),0),0)),"ND"),"ND") -> 40 | K33: =IFERROR(IFERROR(INDEX(DRI_BASE!$Q$2:$Q$469,MATCH(1,INDEX((DRI_BASE!$B$2:$B$469=$G$7)*(DRI_BASE!$C$2:$C$469="Femenino")*(DRI_BASE!$D$2:$D$469=71)*(DRI_BASE!$G$2:$G$469="Ninguno"),0),0)),"ND"),"ND") -> 0 | L33: =IFERROR(IFERROR(INDEX(DRI_BASE!$U$2:$U$469,MATCH(1,INDEX((DRI_BASE!$B$2:$B$469=$G$7)*(DRI_BASE!$C$2:$C$469="Femenino")*(DRI_BASE!$D$2:$D$469=71)*(DRI_BASE!$G$2:$G$469="Ninguno"),0),0)),"ND"),"ND") -> 40 | M33: =IFERROR(IFERROR(INDEX(DRI_BASE!$S$2:$S$469,MATCH(1,INDEX((DRI_BASE!$B$2:$B$469=$G$7)*(DRI_BASE!$C$2:$C$469="Femenino")*(DRI_BASE!$D$2:$D$469=71)*(DRI_BASE!$G$2:$G$469="Ninguno"),0),0)),""),"") -> UL | N33: =IFERROR(IFERROR(INDEX(DRI_BASE!$L$2:$L$469,MATCH(1,INDEX((DRI_BASE!$B$2:$B$469=$G$7)*(DRI_BASE!$C$2:$C$469="Femenino")*(DRI_BASE!$D$2:$D$469=71)*(DRI_BASE!$G$2:$G$469="Ninguno"),0),0)),""),"") -> mg | O33: =IFERROR(IFERROR(INDEX(DRI_BASE!$M$2:$M$469,MATCH(1,INDEX((DRI_BASE!$B$2:$B$469=$G$7)*(DRI_BASE!$C$2:$C$469="Femenino")*(DRI_BASE!$D$2:$D$469=71)*(DRI_BASE!$G$2:$G$469="Ninguno"),0),0)),"ND"),"ND") -> SRC-DRI-SUMMARY
A34: Embarazo | B34: Femenino | C34: Embarazo | D34: 14–51 | E34: =IFERROR(IFERROR(INDEX(DRI_BASE!$H$2:$H$469,MATCH(1,INDEX((DRI_BASE!$B$2:$B$469=$G$7)*(DRI_BASE!$C$2:$C$469="Femenino")*(DRI_BASE!$D$2:$D$469=14)*(DRI_BASE!$G$2:$G$469="Embarazo"),0),0)),"ND"),"ND") -> 0 | F34: =IFERROR(IFERROR(INDEX(DRI_BASE!$I$2:$I$469,MATCH(1,INDEX((DRI_BASE!$B$2:$B$469=$G$7)*(DRI_BASE!$C$2:$C$469="Femenino")*(DRI_BASE!$D$2:$D$469=14)*(DRI_BASE!$G$2:$G$469="Embarazo"),0),0)),"ND"),"ND") -> 11 | G34: =IFERROR(IFERROR(INDEX(DRI_BASE!$J$2:$J$469,MATCH(1,INDEX((DRI_BASE!$B$2:$B$469=$G$7)*(DRI_BASE!$C$2:$C$469="Femenino")*(DRI_BASE!$D$2:$D$469=14)*(DRI_BASE!$G$2:$G$469="Embarazo"),0),0)),"ND"),"ND") -> 0 | H34: =IFERROR(IFERROR(INDEX(DRI_BASE!$T$2:$T$469,MATCH(1,INDEX((DRI_BASE!$B$2:$B$469=$G$7)*(DRI_BASE!$C$2:$C$469="Femenino")*(DRI_BASE!$D$2:$D$469=14)*(DRI_BASE!$G$2:$G$469="Embarazo"),0),0)),"ND"),"ND") -> 11 | I34: =IFERROR(IFERROR(INDEX(DRI_BASE!$R$2:$R$469,MATCH(1,INDEX((DRI_BASE!$B$2:$B$469=$G$7)*(DRI_BASE!$C$2:$C$469="Femenino")*(DRI_BASE!$D$2:$D$469=14)*(DRI_BASE!$G$2:$G$469="Embarazo"),0),0)),"ND"),"ND") -> RDA | J34: =IFERROR(IFERROR(INDEX(DRI_BASE!$K$2:$K$469,MATCH(1,INDEX((DRI_BASE!$B$2:$B$469=$G$7)*(DRI_BASE!$C$2:$C$469="Femenino")*(DRI_BASE!$D$2:$D$469=14)*(DRI_BASE!$G$2:$G$469="Embarazo"),0),0)),"ND"),"ND") -> 40 | K34: =IFERROR(IFERROR(INDEX(DRI_BASE!$Q$2:$Q$469,MATCH(1,INDEX((DRI_BASE!$B$2:$B$469=$G$7)*(DRI_BASE!$C$2:$C$469="Femenino")*(DRI_BASE!$D$2:$D$469=14)*(DRI_BASE!$G$2:$G$469="Embarazo"),0),0)),"ND"),"ND") -> 0 | L34: =IFERROR(IFERROR(INDEX(DRI_BASE!$U$2:$U$469,MATCH(1,INDEX((DRI_BASE!$B$2:$B$469=$G$7)*(DRI_BASE!$C$2:$C$469="Femenino")*(DRI_BASE!$D$2:$D$469=14)*(DRI_BASE!$G$2:$G$469="Embarazo"),0),0)),"ND"),"ND") -> 40 | M34: =IFERROR(IFERROR(INDEX(DRI_BASE!$S$2:$S$469,MATCH(1,INDEX((DRI_BASE!$B$2:$B$469=$G$7)*(DRI_BASE!$C$2:$C$469="Femenino")*(DRI_BASE!$D$2:$D$469=14)*(DRI_BASE!$G$2:$G$469="Embarazo"),0),0)),""),"") -> UL | N34: =IFERROR(IFERROR(INDEX(DRI_BASE!$L$2:$L$469,MATCH(1,INDEX((DRI_BASE!$B$2:$B$469=$G$7)*(DRI_BASE!$C$2:$C$469="Femenino")*(DRI_BASE!$D$2:$D$469=14)*(DRI_BASE!$G$2:$G$469="Embarazo"),0),0)),""),"") -> mg | O34: =IFERROR(IFERROR(INDEX(DRI_BASE!$M$2:$M$469,MATCH(1,INDEX((DRI_BASE!$B$2:$B$469=$G$7)*(DRI_BASE!$C$2:$C$469="Femenino")*(DRI_BASE!$D$2:$D$469=14)*(DRI_BASE!$G$2:$G$469="Embarazo"),0),0)),"ND"),"ND") -> SRC-DRI-SUMMARY
A35: Lactancia | B35: Femenino | C35: Lactancia | D35: 14–51 | E35: =IFERROR(IFERROR(INDEX(DRI_BASE!$H$2:$H$469,MATCH(1,INDEX((DRI_BASE!$B$2:$B$469=$G$7)*(DRI_BASE!$C$2:$C$469="Femenino")*(DRI_BASE!$D$2:$D$469=14)*(DRI_BASE!$G$2:$G$469="Lactancia"),0),0)),"ND"),"ND") -> 0 | F35: =IFERROR(IFERROR(INDEX(DRI_BASE!$I$2:$I$469,MATCH(1,INDEX((DRI_BASE!$B$2:$B$469=$G$7)*(DRI_BASE!$C$2:$C$469="Femenino")*(DRI_BASE!$D$2:$D$469=14)*(DRI_BASE!$G$2:$G$469="Lactancia"),0),0)),"ND"),"ND") -> 12 | G35: =IFERROR(IFERROR(INDEX(DRI_BASE!$J$2:$J$469,MATCH(1,INDEX((DRI_BASE!$B$2:$B$469=$G$7)*(DRI_BASE!$C$2:$C$469="Femenino")*(DRI_BASE!$D$2:$D$469=14)*(DRI_BASE!$G$2:$G$469="Lactancia"),0),0)),"ND"),"ND") -> 0 | H35: =IFERROR(IFERROR(INDEX(DRI_BASE!$T$2:$T$469,MATCH(1,INDEX((DRI_BASE!$B$2:$B$469=$G$7)*(DRI_BASE!$C$2:$C$469="Femenino")*(DRI_BASE!$D$2:$D$469=14)*(DRI_BASE!$G$2:$G$469="Lactancia"),0),0)),"ND"),"ND") -> 12 | I35: =IFERROR(IFERROR(INDEX(DRI_BASE!$R$2:$R$469,MATCH(1,INDEX((DRI_BASE!$B$2:$B$469=$G$7)*(DRI_BASE!$C$2:$C$469="Femenino")*(DRI_BASE!$D$2:$D$469=14)*(DRI_BASE!$G$2:$G$469="Lactancia"),0),0)),"ND"),"ND") -> RDA | J35: =IFERROR(IFERROR(INDEX(DRI_BASE!$K$2:$K$469,MATCH(1,INDEX((DRI_BASE!$B$2:$B$469=$G$7)*(DRI_BASE!$C$2:$C$469="Femenino")*(DRI_BASE!$D$2:$D$469=14)*(DRI_BASE!$G$2:$G$469="Lactancia"),0),0)),"ND"),"ND") -> 40 | K35: =IFERROR(IFERROR(INDEX(DRI_BASE!$Q$2:$Q$469,MATCH(1,INDEX((DRI_BASE!$B$2:$B$469=$G$7)*(DRI_BASE!$C$2:$C$469="Femenino")*(DRI_BASE!$D$2:$D$469=14)*(DRI_BASE!$G$2:$G$469="Lactancia"),0),0)),"ND"),"ND") -> 0 | L35: =IFERROR(IFERROR(INDEX(DRI_BASE!$U$2:$U$469,MATCH(1,INDEX((DRI_BASE!$B$2:$B$469=$G$7)*(DRI_BASE!$C$2:$C$469="Femenino")*(DRI_BASE!$D$2:$D$469=14)*(DRI_BASE!$G$2:$G$469="Lactancia"),0),0)),"ND"),"ND") -> 40 | M35: =IFERROR(IFERROR(INDEX(DRI_BASE!$S$2:$S$469,MATCH(1,INDEX((DRI_BASE!$B$2:$B$469=$G$7)*(DRI_BASE!$C$2:$C$469="Femenino")*(DRI_BASE!$D$2:$D$469=14)*(DRI_BASE!$G$2:$G$469="Lactancia"),0),0)),""),"") -> UL | N35: =IFERROR(IFERROR(INDEX(DRI_BASE!$L$2:$L$469,MATCH(1,INDEX((DRI_BASE!$B$2:$B$469=$G$7)*(DRI_BASE!$C$2:$C$469="Femenino")*(DRI_BASE!$D$2:$D$469=14)*(DRI_BASE!$G$2:$G$469="Lactancia"),0),0)),""),"") -> mg | O35: =IFERROR(IFERROR(INDEX(DRI_BASE!$M$2:$M$469,MATCH(1,INDEX((DRI_BASE!$B$2:$B$469=$G$7)*(DRI_BASE!$C$2:$C$469="Femenino")*(DRI_BASE!$D$2:$D$469=14)*(DRI_BASE!$G$2:$G$469="Lactancia"),0),0)),"ND"),"ND") -> SRC-DRI-SUMMARY
A37: Nota: la Fase 6 normaliza RDA/AI y UL/CDRR. Las EAR completas no se incorporaron porque la tabla adjunta no las contiene de forma íntegra. Un UL o CDRR no es una meta de consumo.

Sheet INTERACCIONES
A1: NUTRIMETRÍA · NMX-43 | INTERACCIONES
A3: Consulta filtrable de interacciones nutriente–nutriente y medicamento–nutriente.
A5: =HYPERLINK("#'INICIO'!A1","INICIO") -> INICIO | B5: =HYPERLINK("#'DATOS'!A1","DATOS") -> DATOS | C5: =HYPERLINK("#'ENERGÍA'!A1","ENERGÍA") -> ENERGÍA | D5: =HYPERLINK("#'MACRONUTRIENTES'!A1","MACRONUTRIENTES") -> MACRONUTRIENTES | E5: =HYPERLINK("#'AGUA_FIBRA'!A1","AGUA/FIBRA") -> AGUA/FIBRA | F5: =HYPERLINK("#'FICHA_NUTRIENTE'!A1","FICHA/NUTRIENTE") -> FICHA/NUTRIENTE | G5: =HYPERLINK("#'RESULTADOS'!A1","RESULTADOS") -> RESULTADOS | H5: =HYPERLINK("#'DOCUMENTACIÓN'!A1","DOCUMENTACIÓN") -> DOCUMENTACIÓN | I5: =HYPERLINK("#'COBERTURA'!A1","COBERTURA") -> COBERTURA | J5: =HYPERLINK("#'AUDITORÍA_FINAL'!A1","AUDITORÍA") -> AUDITORÍA
A7: NUTRIENTE | C7: Vitamina A | E7: ID | G7: =IFERROR(IFERROR(INDEX(NUTRIENTES!$A$8:$A$30,MATCH($C$7,NUTRIENTES!$B$8:$B$30,0)),""),"") -> VIT-A
A8: Use la flecha de la celda amarilla para seleccionar el nutriente.
A9: Las interacciones describen mecanismos y riesgos educativos. No indican suspender, iniciar ni separar medicamentos sin revisar su ficha y al equipo tratante.
A11: Agente | B11: Tipo | C11: Dirección | D11: Mecanismo | E11: Relevancia práctica | F11: Evidencia | G11: Fuente_ID | H11: Estado
A12: =IFERROR(INDEX(INTERACCIONES_BASE!C$2:C$36,MATCH(ROWS($A$12:$A12),INTERACCIONES_BASE!$K$2:$K$36,0)),"") -> Zinc | B12: =IFERROR(INDEX(INTERACCIONES_BASE!D$2:D$36,MATCH(ROWS($A$12:$A12),INTERACCIONES_BASE!$K$2:$K$36,0)),"") -> Nutriente–nutriente | C12: =IFERROR(INDEX(INTERACCIONES_BASE!E$2:E$36,MATCH(ROWS($A$12:$A12),INTERACCIONES_BASE!$K$2:$K$36,0)),"") -> Relación funcional | D12: =IFERROR(INDEX(INTERACCIONES_BASE!F$2:F$36,MATCH(ROWS($A$12:$A12),INTERACCIONES_BASE!$K$2:$K$36,0)),"") -> El zinc participa en síntesis y transporte de proteína fijadora de retinol. | E12: =IFERROR(INDEX(INTERACCIONES_BASE!G$2:G$36,MATCH(ROWS($A$12:$A12),INTERACCIONES_BASE!$K$2:$K$36,0)),"") -> Deficiencias múltiples pueden coexistir. | F12: =IFERROR(INDEX(INTERACCIONES_BASE!H$2:H$36,MATCH(ROWS($A$12:$A12),INTERACCIONES_BASE!$K$2:$K$36,0)),"") -> Contextual | G12: =IFERROR(INDEX(INTERACCIONES_BASE!I$2:I$36,MATCH(ROWS($A$12:$A12),INTERACCIONES_BASE!$K$2:$K$36,0)),"") -> SRC-ODS-VITA | H12: =IFERROR(INDEX(INTERACCIONES_BASE!J$2:J$36,MATCH(ROWS($A$12:$A12),INTERACCIONES_BASE!$K$2:$K$36,0)),"") -> VERIFICADO
A13: =IFERROR(INDEX(INTERACCIONES_BASE!C$2:C$36,MATCH(ROWS($A$12:$A13),INTERACCIONES_BASE!$K$2:$K$36,0)),"") -> Orlistat/colestiramina | B13: =IFERROR(INDEX(INTERACCIONES_BASE!D$2:D$36,MATCH(ROWS($A$12:$A13),INTERACCIONES_BASE!$K$2:$K$36,0)),"") -> Medicamento–nutriente | C13: =IFERROR(INDEX(INTERACCIONES_BASE!E$2:E$36,MATCH(ROWS($A$12:$A13),INTERACCIONES_BASE!$K$2:$K$36,0)),"") -> Reduce absorción | D13: =IFERROR(INDEX(INTERACCIONES_BASE!F$2:F$36,MATCH(ROWS($A$12:$A13),INTERACCIONES_BASE!$K$2:$K$36,0)),"") -> Disminuyen absorción de grasas o ácidos biliares. | E13: =IFERROR(INDEX(INTERACCIONES_BASE!G$2:G$36,MATCH(ROWS($A$12:$A13),INTERACCIONES_BASE!$K$2:$K$36,0)),"") -> Vigilar vitaminas liposolubles según indicación clínica. | F13: =IFERROR(INDEX(INTERACCIONES_BASE!H$2:H$36,MATCH(ROWS($A$12:$A13),INTERACCIONES_BASE!$K$2:$K$36,0)),"") -> Alta | G13: =IFERROR(INDEX(INTERACCIONES_BASE!I$2:I$36,MATCH(ROWS($A$12:$A13),INTERACCIONES_BASE!$K$2:$K$36,0)),"") -> SRC-ODS-VITA | H13: =IFERROR(INDEX(INTERACCIONES_BASE!J$2:J$36,MATCH(ROWS($A$12:$A13),INTERACCIONES_BASE!$K$2:$K$36,0)),"") -> VERIFICADO
A14: =IFERROR(INDEX(INTERACCIONES_BASE!C$2:C$36,MATCH(ROWS($A$12:$A14),INTERACCIONES_BASE!$K$2:$K$36,0)),"") | B14: =IFERROR(INDEX(INTERACCIONES_BASE!D$2:D$36,MATCH(ROWS($A$12:$A14),INTERACCIONES_BASE!$K$2:$K$36,0)),"") | C14: =IFERROR(INDEX(INTERACCIONES_BASE!E$2:E$36,MATCH(ROWS($A$12:$A14),INTERACCIONES_BASE!$K$2:$K$36,0)),"") | D14: =IFERROR(INDEX(INTERACCIONES_BASE!F$2:F$36,MATCH(ROWS($A$12:$A14),INTERACCIONES_BASE!$K$2:$K$36,0)),"") | E14: =IFERROR(INDEX(INTERACCIONES_BASE!G$2:G$36,MATCH(ROWS($A$12:$A14),INTERACCIONES_BASE!$K$2:$K$36,0)),"") | F14: =IFERROR(INDEX(INTERACCIONES_BASE!H$2:H$36,MATCH(ROWS($A$12:$A14),INTERACCIONES_BASE!$K$2:$K$36,0)),"") | G14: =IFERROR(INDEX(INTERACCIONES_BASE!I$2:I$36,MATCH(ROWS($A$12:$A14),INTERACCIONES_BASE!$K$2:$K$36,0)),"") | H14: =IFERROR(INDEX(INTERACCIONES_BASE!J$2:J$36,MATCH(ROWS($A$12:$A14),INTERACCIONES_BASE!$K$2:$K$36,0)),"")

Sheet BIOMARCADORES
A1: NUTRIMETRÍA · NMX-43 | BIOMARCADORES
A3: Biomarcadores seleccionados, utilidad, criterios y limitaciones de interpretación.
A5: =HYPERLINK("#'INICIO'!A1","INICIO") -> INICIO | B5: =HYPERLINK("#'DATOS'!A1","DATOS") -> DATOS | C5: =HYPERLINK("#'ENERGÍA'!A1","ENERGÍA") -> ENERGÍA | D5: =HYPERLINK("#'MACRONUTRIENTES'!A1","MACRONUTRIENTES") -> MACRONUTRIENTES | E5: =HYPERLINK("#'AGUA_FIBRA'!A1","AGUA/FIBRA") -> AGUA/FIBRA | F5: =HYPERLINK("#'FICHA_NUTRIENTE'!A1","FICHA/NUTRIENTE") -> FICHA/NUTRIENTE | G5: =HYPERLINK("#'RESULTADOS'!A1","RESULTADOS") -> RESULTADOS | H5: =HYPERLINK("#'DOCUMENTACIÓN'!A1","DOCUMENTACIÓN") -> DOCUMENTACIÓN | I5: =HYPERLINK("#'COBERTURA'!A1","COBERTURA") -> COBERTURA | J5: =HYPERLINK("#'AUDITORÍA_FINAL'!A1","AUDITORÍA") -> AUDITORÍA
A7: NUTRIENTE | C7: Hierro | E7: ID | G7: =IFERROR(IFERROR(INDEX(NUTRIENTES!$A$8:$A$30,MATCH($C$7,NUTRIENTES!$B$8:$B$30,0)),""),"") -> MIN-FE
A8: Use la flecha de la celda amarilla para seleccionar el nutriente.
A9: No se cargan rangos universales. Cada resultado debe interpretarse con método, población, laboratorio, función renal, inflamación y contexto clínico.
A11: Examen | B11: Muestra | C11: Qué evalúa | D11: Unidad | E11: Criterio general | F11: Limitaciones | G11: Fuente_ID | H11: Estado
A12: =IFERROR(INDEX(BIOMARCADORES_BASE!C$2:C$27,MATCH(ROWS($A$12:$A12),BIOMARCADORES_BASE!$K$2:$K$27,0)),"") -> Ferritina | B12: =IFERROR(INDEX(BIOMARCADORES_BASE!D$2:D$27,MATCH(ROWS($A$12:$A12),BIOMARCADORES_BASE!$K$2:$K$27,0)),"") -> Suero | C12: =IFERROR(INDEX(BIOMARCADORES_BASE!E$2:E$27,MATCH(ROWS($A$12:$A12),BIOMARCADORES_BASE!$K$2:$K$27,0)),"") -> Depósitos de hierro | D12: =IFERROR(INDEX(BIOMARCADORES_BASE!F$2:F$27,MATCH(ROWS($A$12:$A12),BIOMARCADORES_BASE!$K$2:$K$27,0)),"") -> µg/L o ng/mL | E12: =IFERROR(INDEX(BIOMARCADORES_BASE!G$2:G$27,MATCH(ROWS($A$12:$A12),BIOMARCADORES_BASE!$K$2:$K$27,0)),"") -> Valor bajo apoya depleción; usar criterio del laboratorio y población. | F12: =IFERROR(INDEX(BIOMARCADORES_BASE!H$2:H$27,MATCH(ROWS($A$12:$A12),BIOMARCADORES_BASE!$K$2:$K$27,0)),"") -> Reactante de fase aguda; aumenta con inflamación, infección, hígado y obesidad. | G12: =IFERROR(INDEX(BIOMARCADORES_BASE!I$2:I$27,MATCH(ROWS($A$12:$A12),BIOMARCADORES_BASE!$K$2:$K$27,0)),"") -> SRC-ODS-IRON | H12: =IFERROR(INDEX(BIOMARCADORES_BASE!J$2:J$27,MATCH(ROWS($A$12:$A12),BIOMARCADORES_BASE!$K$2:$K$27,0)),"") -> VERIFICADO
A13: =IFERROR(INDEX(BIOMARCADORES_BASE!C$2:C$27,MATCH(ROWS($A$12:$A13),BIOMARCADORES_BASE!$K$2:$K$27,0)),"") -> Saturación de transferrina | B13: =IFERROR(INDEX(BIOMARCADORES_BASE!D$2:D$27,MATCH(ROWS($A$12:$A13),BIOMARCADORES_BASE!$K$2:$K$27,0)),"") -> Suero | C13: =IFERROR(INDEX(BIOMARCADORES_BASE!E$2:E$27,MATCH(ROWS($A$12:$A13),BIOMARCADORES_BASE!$K$2:$K$27,0)),"") -> Hierro disponible para eritropoyesis | D13: =IFERROR(INDEX(BIOMARCADORES_BASE!F$2:F$27,MATCH(ROWS($A$12:$A13),BIOMARCADORES_BASE!$K$2:$K$27,0)),"") -> % | E13: =IFERROR(INDEX(BIOMARCADORES_BASE!G$2:G$27,MATCH(ROWS($A$12:$A13),BIOMARCADORES_BASE!$K$2:$K$27,0)),"") -> Interpretar con ferritina, hemograma y contexto. | F13: =IFERROR(INDEX(BIOMARCADORES_BASE!H$2:H$27,MATCH(ROWS($A$12:$A13),BIOMARCADORES_BASE!$K$2:$K$27,0)),"") -> Varía con hierro sérico, hora y transferrina. | G13: =IFERROR(INDEX(BIOMARCADORES_BASE!I$2:I$27,MATCH(ROWS($A$12:$A13),BIOMARCADORES_BASE!$K$2:$K$27,0)),"") -> SRC-ODS-IRON | H13: =IFERROR(INDEX(BIOMARCADORES_BASE!J$2:J$27,MATCH(ROWS($A$12:$A13),BIOMARCADORES_BASE!$K$2:$K$27,0)),"") -> VERIFICADO
A14: =IFERROR(INDEX(BIOMARCADORES_BASE!C$2:C$27,MATCH(ROWS($A$12:$A14),BIOMARCADORES_BASE!$K$2:$K$27,0)),"") | B14: =IFERROR(INDEX(BIOMARCADORES_BASE!D$2:D$27,MATCH(ROWS($A$12:$A14),BIOMARCADORES_BASE!$K$2:$K$27,0)),"") | C14: =IFERROR(INDEX(BIOMARCADORES_BASE!E$2:E$27,MATCH(ROWS($A$12:$A14),BIOMARCADORES_BASE!$K$2:$K$27,0)),"") | D14: =IFERROR(INDEX(BIOMARCADORES_BASE!F$2:F$27,MATCH(ROWS($A$12:$A14),BIOMARCADORES_BASE!$K$2:$K$27,0)),"") | E14: =IFERROR(INDEX(BIOMARCADORES_BASE!G$2:G$27,MATCH(ROWS($A$12:$A14),BIOMARCADORES_BASE!$K$2:$K$27,0)),"") | F14: =IFERROR(INDEX(BIOMARCADORES_BASE!H$2:H$27,MATCH(ROWS($A$12:$A14),BIOMARCADORES_BASE!$K$2:$K$27,0)),"") | G14: =IFERROR(INDEX(BIOMARCADORES_BASE!I$2:I$27,MATCH(ROWS($A$12:$A14),BIOMARCADORES_BASE!$K$2:$K$27,0)),"") | H14: =IFERROR(INDEX(BIOMARCADORES_BASE!J$2:J$27,MATCH(ROWS($A$12:$A14),BIOMARCADORES_BASE!$K$2:$K$27,0)),"")

Sheet CASOS_CLÍNICOS
A1: NUTRIMETRÍA · NMX-43 | CASOS_CLÍNICOS
A3: Banco interactivo con 69 casos clínico-formativos: un caso básico, uno intermedio y uno avanzado para cada uno de los 23 micronutrientes.
A5: =HYPERLINK("#'INICIO'!A1","INICIO") -> INICIO | B5: =HYPERLINK("#'DATOS'!A1","DATOS") -> DATOS | C5: =HYPERLINK("#'ENERGÍA'!A1","ENERGÍA") -> ENERGÍA | D5: =HYPERLINK("#'MACRONUTRIENTES'!A1","MACRONUTRIENTES") -> MACRONUTRIENTES | E5: =HYPERLINK("#'AGUA_FIBRA'!A1","AGUA/FIBRA") -> AGUA/FIBRA | F5: =HYPERLINK("#'FICHA_NUTRIENTE'!A1","FICHA/NUTRIENTE") -> FICHA/NUTRIENTE | G5: =HYPERLINK("#'RESULTADOS'!A1","RESULTADOS") -> RESULTADOS | H5: =HYPERLINK("#'DOCUMENTACIÓN'!A1","DOCUMENTACIÓN") -> DOCUMENTACIÓN | I5: =HYPERLINK("#'COBERTURA'!A1","COBERTURA") -> COBERTURA | J5: =HYPERLINK("#'AUDITORÍA_FINAL'!A1","AUDITORÍA") -> AUDITORÍA | K5: =HYPERLINK("#'EJEMPLOS_CASOS'!A1","EJEMPLOS B / I / A") -> EJEMPLOS B / I / A
A7: NUTRIENTE | C7: Selenio | E7: ID NUT. | G7: =IFERROR(IFERROR(INDEX(NUTRIENTES!$A$8:$A$30,MATCH($C$7,NUTRIENTES!$B$8:$B$30,0)),""),"") -> MIN-SE | I7: NIVEL | K7: Básico
A8: =IF(OR($C$7="",$K$7=""),"Seleccione un nutriente y un nivel desde las listas desplegables.",IF(IFERROR(INDEX(CASOS_BASE!$P$2:$R$24,MATCH($G$7,CASOS_BASE!$O$2:$O$24,0),MATCH($K$7,CASOS_BASE!$P$1:$R$1,0)),"")="","No existe un caso "&LOWER($K$7)&" para "&$C$7&".","Caso cargado correctamente: "&IFERROR(INDEX(CASOS_BASE!$P$2:$R$24,MATCH($G$7,CASOS_BASE!$O$2:$O$24,0),MATCH($K$7,CASOS_BASE!$P$1:$R$1,0)),""))) -> Caso cargado correctamente: CASO-SE-BAS
A10: PACIENTE | H10: ANTECEDENTES
A11: =IFERROR(INDEX(CASOS_BASE!$D$2:$D$70,MATCH(IFERROR(INDEX(CASOS_BASE!$P$2:$R$24,MATCH($G$7,CASOS_BASE!$O$2:$O$24,0),MATCH($K$7,CASOS_BASE!$P$1:$R$1,0)),""),CASOS_BASE!$A$2:$A$70,0)),"") -> Adulto que consume nueces de Brasil todos los días junto con un suplemento de selenio. | H11: =IFERROR(INDEX(CASOS_BASE!$E$2:$E$70,MATCH(IFERROR(INDEX(CASOS_BASE!$P$2:$R$24,MATCH($G$7,CASOS_BASE!$O$2:$O$24,0),MATCH($K$7,CASOS_BASE!$P$1:$R$1,0)),""),CASOS_BASE!$A$2:$A$70,0)),"") -> Busca mejorar la función tiroidea sin diagnóstico.
A16: INGESTA | H16: SIGNOS Y SÍNTOMAS
A17: =IFERROR(INDEX(CASOS_BASE!$F$2:$F$70,MATCH(IFERROR(INDEX(CASOS_BASE!$P$2:$R$24,MATCH($G$7,CASOS_BASE!$O$2:$O$24,0),MATCH($K$7,CASOS_BASE!$P$1:$R$1,0)),""),CASOS_BASE!$A$2:$A$70,0)),"") -> Aporte muy concentrado y variable de selenio. | H17: =IFERROR(INDEX(CASOS_BASE!$G$2:$G$70,MATCH(IFERROR(INDEX(CASOS_BASE!$P$2:$R$24,MATCH($G$7,CASOS_BASE!$O$2:$O$24,0),MATCH($K$7,CASOS_BASE!$P$1:$R$1,0)),""),CASOS_BASE!$A$2:$A$70,0)),"") -> Caída de cabello y fragilidad ungueal.
A22: LABORATORIO | H22: PREGUNTAS
A23: =IFERROR(INDEX(CASOS_BASE!$H$2:$H$70,MATCH(IFERROR(INDEX(CASOS_BASE!$P$2:$R$24,MATCH($G$7,CASOS_BASE!$O$2:$O$24,0),MATCH($K$7,CASOS_BASE!$P$1:$R$1,0)),""),CASOS_BASE!$A$2:$A$70,0)),"") -> Selenio elevado según laboratorio. | H23: =IFERROR(INDEX(CASOS_BASE!$I$2:$I$70,MATCH(IFERROR(INDEX(CASOS_BASE!$P$2:$R$24,MATCH($G$7,CASOS_BASE!$O$2:$O$24,0),MATCH($K$7,CASOS_BASE!$P$1:$R$1,0)),""),CASOS_BASE!$A$2:$A$70,0)),"") -> 1) ¿Qué cuadro debe considerarse? 2) ¿Por qué varía el contenido de las nueces? 3) ¿Qué suplementos deben revisarse?
A28: INTERPRETACIÓN ESPERADA
A29: =IFERROR(INDEX(CASOS_BASE!$J$2:$J$70,MATCH(IFERROR(INDEX(CASOS_BASE!$P$2:$R$24,MATCH($G$7,CASOS_BASE!$O$2:$O$24,0),MATCH($K$7,CASOS_BASE!$P$1:$R$1,0)),""),CASOS_BASE!$A$2:$A$70,0)),"") -> El exceso acumulado puede causar selenosis. El contenido de los alimentos varía según el suelo y la duplicación de suplementos aumenta el riesgo.
A36: CASO EDUCATIVO: no representa diagnóstico ni tratamiento de una persona real. La orientación final depende de evaluación clínica, laboratorio, medicamentos y protocolos locales.
A38: =HYPERLINK("#'EJEMPLOS_CASOS'!A1","ABRIR TRES EJEMPLOS DESARROLLADOS: BÁSICO · INTERMEDIO · AVANZADO") -> ABRIR TRES EJEMPLOS DESARROLLADOS: BÁSICO · INTERMEDIO · AVANZADO
A40: INTEGRACIÓN CON LOS ALIMENTOS SELECCIONADOS
A42: ="APORTE"&CHAR(10)&IFERROR(INDEX(CALCULOS_ADECUACIÓN!$H$3:$H$25,MATCH($G$7,CALCULOS_ADECUACIÓN!$F$3:$F$25,0)),"ND") -> APORTE 279,94 | D42: ="OBJETIVO"&CHAR(10)&IFERROR(INDEX(CALCULOS_ADECUACIÓN!$J$3:$J$25,MATCH($G$7,CALCULOS_ADECUACIÓN!$F$3:$F$25,0)),"ND") -> OBJETIVO 55 | G42: ="ADECUACIÓN %"&CHAR(10)&IFERROR(INDEX(CALCULOS_ADECUACIÓN!$L$3:$L$25,MATCH($G$7,CALCULOS_ADECUACIÓN!$F$3:$F$25,0)),"ND") -> ADECUACIÓN % 508,981818181818 | J42: ="ESTADO"&CHAR(10)&IFERROR(INDEX(CALCULOS_ADECUACIÓN!$Q$3:$Q$25,MATCH($G$7,CALCULOS_ADECUACIÓN!$F$3:$F$25,0)),"ND") -> ESTADO PARCIAL · 2 ND
A47: Este bloque usa solo los alimentos del módulo FUENTES_ALIMENTARIAS. No sustituye el análisis de la dieta completa ni la evaluación clínica del caso.
A49: ÍNDICE DE CASOS DISPONIBLES · 23 MICRONUTRIENTES × 3 NIVELES
A50: MICRONUTRIENTE | D50: BÁSICO | G50: INTERMEDIO | J50: AVANZADO
A51: Hierro | D51: CASO-FE-BAS | G51: CASO-FE-INT | J51: CASO-FE-ADV
A52: Zinc | D52: CASO-ZN-BAS | G52: CASO-ZN-INT | J52: CASO-ZN-ADV
A53: Cobre | D53: CASO-CU-BAS | G53: CASO-CU-INT | J53: CASO-CU-ADV
A54: Calcio | D54: CASO-CA-BAS | G54: CASO-CA-INT | J54: CASO-CA-ADV
A55: Fósforo | D55: CASO-P-BAS | G55: CASO-P-INT | J55: CASO-P-ADV
A56: Selenio | D56: CASO-SE-BAS | G56: CASO-SE-INT | J56: CASO-SE-ADV
A57: Potasio | D57: CASO-K-BAS | G57: CASO-K-INT | J57: CASO-K-ADV
A58: Magnesio | D58: CASO-MG-BAS | G58: CASO-MG-INT | J58: CASO-MG-ADV
A59: Sodio | D59: CASO-NA-BAS | G59: CASO-NA-INT | J59: CASO-NA-ADV
A60: Cloruro | D60: CASO-CL-BAS | G60: CASO-CL-INT | J60: CASO-CL-ADV
A61: Vitamina A | D61: CASO-A-BAS | G61: CASO-A-INT | J61: CASO-A-ADV
... A73: Cobalamina | D73: CASO-B12-BAS | G73: CASO-B12-INT | J73: CASO-B12-ADV
A75: COBERTURA COMPLETA: 69 DE 69 COMBINACIONES DISPONIBLES. Seleccione el micronutriente en C7 y el nivel en K7.

Sheet RESULTADOS
A1: NUTRIMETRÍA · NMX-43 | RESULTADOS
A3: Panel integrado de energía, macronutrientes, agua, fibra e índice/carga glicémica.
A5: =HYPERLINK("#'INICIO'!A1","INICIO") -> INICIO | B5: =HYPERLINK("#'DATOS'!A1","DATOS") -> DATOS | C5: =HYPERLINK("#'ENERGÍA'!A1","ENERGÍA") -> ENERGÍA | D5: =HYPERLINK("#'MACRONUTRIENTES'!A1","MACRONUTRIENTES") -> MACRONUTRIENTES | E5: =HYPERLINK("#'AGUA_FIBRA'!A1","AGUA/FIBRA") -> AGUA/FIBRA | F5: =HYPERLINK("#'FICHA_NUTRIENTE'!A1","FICHA/NUTRIENTE") -> FICHA/NUTRIENTE | G5: =HYPERLINK("#'RESULTADOS'!A1","RESULTADOS") -> RESULTADOS | H5: =HYPERLINK("#'DOCUMENTACIÓN'!A1","DOCUMENTACIÓN") -> DOCUMENTACIÓN | I5: =HYPERLINK("#'COBERTURA'!A1","COBERTURA") -> COBERTURA | J5: =HYPERLINK("#'AUDITORÍA_FINAL'!A1","AUDITORÍA") -> AUDITORÍA
A7: RESULTADOS INTEGRADOS · FASE 4
A9: ="ENERGÍA SELECCIONADA"&CHAR(10)&TEXT(CALCULOS_ENERGÍA!B23,"0.0")&" kcal/d" -> ENERGÍA SELECCIONADA 2.106 kcal/d | E9: ="MÉTODO"&CHAR(10)&CALCULOS_ENERGÍA!B22 -> MÉTODO Schofield × PAL | I9: ="CIERRE DE MACROS"&CHAR(10)&CALCULOS_NUTRIENTES!B28 -> CIERRE DE MACROS CIERRE CORRECTO | M9: ="DATOS ND"&CHAR(10)&COUNTIF(F17:F23,"NO EVALUABLE") -> DATOS ND 0
A16: Indicador | B16: Aporte/resultado | C16: Unidad | D16: Referencia | E16: Adecuación | F16: Estado | G16: Fuente/nota
A17: Energía | B17: =CALCULOS_ENERGÍA!B23 -> 2106.2528 | C17: kcal/d | D17: =CALCULOS_ENERGÍA!B22 -> Schofield × PAL | F17: =CALCULOS_ENERGÍA!B26 -> OK CON LIMITACIONES | G17: Método energético seleccionado
A18: Proteína | B18: =CALCULOS_NUTRIENTES!B12 -> 78.98448 | C18: g/d | D18: =CALCULOS_NUTRIENTES!B21 -> 46 | E18: =CALCULOS_NUTRIENTES!B23 -> 171.70539 | F18: =IF(NOT(ISNUMBER(E18)),"NO EVALUABLE",IF(E18<CONFIG!$B$17,"BAJO",IF(E18<=CONFIG!$B$18,"DENTRO DEL RANGO","SOBRE EL RANGO"))) -> SOBRE EL RANGO | G18: DRI + distribución
A19: Lípidos | B19: =CALCULOS_NUTRIENTES!B14 -> 70.208427 | C19: g/d | D19: =CALCULOS_NUTRIENTES!B26 -> 20–35 | E19: =CALCULOS_NUTRIENTES!B10 -> 30 | F19: =IF(CALCULOS_NUTRIENTES!B3<1,"NO EVALUABLE",IF(AND(E19>=INDEX(LISTAS!$AA$2:$AA$4,MATCH(CALCULOS_NUTRIENTES!B3,LISTAS!$W$2:$W$4,1)),E19<=INDEX(LISTAS!$AB$2:$AB$4,MATCH(CALCULOS_NUTRIENTES!B3,LISTAS!$W$2:$W$4,1))),"DENTRO DEL AMDR","FUERA DEL AMDR")) -> DENTRO DEL AMDR | G19: AMDR según edad
A20: Carbohidratos | B20: =CALCULOS_NUTRIENTES!B16 -> 289.60976 | C20: g/d | D20: =CALCULOS_NUTRIENTES!B22 -> 130 | E20: =CALCULOS_NUTRIENTES!B24 -> 222.77674 | F20: =IF(NOT(ISNUMBER(E20)),"NO EVALUABLE",IF(E20<CONFIG!$B$17,"BAJO",IF(E20<=CONFIG!$B$18,"DENTRO DEL RANGO","SOBRE EL RANGO"))) -> SOBRE EL RANGO | G20: DRI + distribución
A21: Agua total | B21: =CALCULOS_ADECUACIÓN!B5 -> 2.5 | C21: L/d | D21: =CALCULOS_ADECUACIÓN!B7 -> 2.7 | E21: =CALCULOS_ADECUACIÓN!B9 -> 92.592593 | F21: =CALCULOS_ADECUACIÓN!B11 -> DENTRO DEL RANGO | G21: AI incluye bebidas y alimentos
A22: Fibra dietaria | B22: =CALCULOS_ADECUACIÓN!B6 -> 25 | C22: g/d | D22: =CALCULOS_ADECUACIÓN!B8 -> 25 | E22: =CALCULOS_ADECUACIÓN!B10 -> 100 | F22: =CALCULOS_ADECUACIÓN!B12 -> DENTRO DEL RANGO | G22: AI
A23: Carga glicémica | B23: =ÍNDICE_CARGA_GLICÉMICA!G11 -> 10.5 | D23: =ÍNDICE_CARGA_GLICÉMICA!G10 -> 35 | F23: =ÍNDICE_CARGA_GLICÉMICA!I11 -> MEDIA | G23: Según IG y CHO de la porción
A27: RESUMEN INTERPRETATIVO
A28: ="Caso: "&DATOS!B8&". Energía seleccionada: "&TEXT(CALCULOS_ENERGÍA!B23,"0")&" kcal/d mediante "&CALCULOS_ENERGÍA!B22&". Distribución: proteína "&TEXT(CALCULOS_NUTRIENTES!B9,"0")&" %, lípidos "&TEXT(CALCULOS_NUTRIENTES!B10,"0")&" % y carbohidratos "&TEXT(CALCULOS_NUTRIENTES!B11,"0")&" %. "&"Agua: "&TEXT(CALCULOS_ADECUACIÓN!B9,"0.0")&" % de la AI; fibra: "&IF(ISNUMBER(CALCULOS_ADECUACIÓN!B10),TEXT(CALCULOS_ADECUACIÓN!B10,"0.0")&" % de la AI","no evaluable")&". La carga glicémica del ejemplo seleccionado es "&TEXT(ÍNDICE_CARGA_GLICÉMICA!G11,"0.0")&" ("&ÍNDICE_CARGA_GLICÉMICA!I11&"). Resultados educativos: revisar aplicabilidad, fuente y contexto individual." -> Caso: CASO-DEMO-01. Energía seleccionada: 2106 kcal/d mediante Schofield × PAL. Distribución: proteína 15 %, lípidos 30 % y carbohidratos 55 %. Agua: 93 % de la AI; fibra: 100 % de la AI. La carga glicémica del ejemplo seleccionado es 11 (MEDIA). Resultados educativos: revisar aplicabilidad, fuente y contexto individual.
A37: ALERTAS DE USO
A38: Los resultados estiman requerimientos para fines de aprendizaje. Las ecuaciones no miden el gasto energético individual y las DRI se aplican principalmente a poblaciones sanas. AI, RDA y AMDR no son conceptos equivalentes. Un porcentaje superior a 100 % no implica por sí solo beneficio ni toxicidad. La carga glicémica depende de una porción definida y de un IG publicado compatible con el alimento y su preparación.
A41: MICRONUTRIENTES · APORTE CONOCIDO DE LOS ALIMENTOS SELECCIONADOS
A43: Nutriente | B43: Aporte | C43: Unidad | D43: Objetivo | E43: Tipo | F43: Adecuación % | G43: ND | H43: Estado | I43: ="ALIMENTOS"&CHAR(10)&COUNTA(FUENTES_ALIMENTARIAS!$B$13:$B$22) -> ALIMENTOS 10 | K43: ="CON DATOS"&CHAR(10)&(ROWS($H$44:$H$66)-COUNTIF($H$44:$H$66,"ND EN INTA")) -> CON DATOS 21 | M43: ="PARCIALES/ND"&CHAR(10)&COUNTIF($G$44:$G$66,">0") -> PARCIALES/ND 23
A44: =CALCULOS_ADECUACIÓN!G3 -> Hierro | B44: =CALCULOS_ADECUACIÓN!H3 -> 32.17 | C44: =CALCULOS_ADECUACIÓN!I3 -> mg | D44: =CALCULOS_ADECUACIÓN!J3 -> 18 | E44: =CALCULOS_ADECUACIÓN!K3 -> RDA | F44: =CALCULOS_ADECUACIÓN!L3 -> 178.72222 | G44: =CALCULOS_ADECUACIÓN!P3 -> 2 | H44: =CALCULOS_ADECUACIÓN!Q3 -> PARCIAL · 2 ND
A45: =CALCULOS_ADECUACIÓN!G4 -> Zinc | B45: =CALCULOS_ADECUACIÓN!H4 -> 13.37 | C45: =CALCULOS_ADECUACIÓN!I4 -> mg | D45: =CALCULOS_ADECUACIÓN!J4 -> 8 | E45: =CALCULOS_ADECUACIÓN!K4 -> RDA | F45: =CALCULOS_ADECUACIÓN!L4 -> 167.125 | G45: =CALCULOS_ADECUACIÓN!P4 -> 2 | H45: =CALCULOS_ADECUACIÓN!Q4 -> PARCIAL · 2 ND
A46: =CALCULOS_ADECUACIÓN!G5 -> Cobre | B46: =CALCULOS_ADECUACIÓN!H5 -> 15.95 | C46: =CALCULOS_ADECUACIÓN!I5 -> mg | D46: =CALCULOS_ADECUACIÓN!J5 -> 0.9 | E46: =CALCULOS_ADECUACIÓN!K5 -> RDA | F46: =CALCULOS_ADECUACIÓN!L5 -> 1772.2222 | G46: =CALCULOS_ADECUACIÓN!P5 -> 2 | H46: =CALCULOS_ADECUACIÓN!Q5 -> SOBRE UL · PARCIAL
A47: =CALCULOS_ADECUACIÓN!G6 -> Calcio | B47: =CALCULOS_ADECUACIÓN!H6 -> 2121.2 | C47: =CALCULOS_ADECUACIÓN!I6 -> mg | D47: =CALCULOS_ADECUACIÓN!J6 -> 1000 | E47: =CALCULOS_ADECUACIÓN!K6 -> RDA | F47: =CALCULOS_ADECUACIÓN!L6 -> 212.12 | G47: =CALCULOS_ADECUACIÓN!P6 -> 1 | H47: =CALCULOS_ADECUACIÓN!Q6 -> PARCIAL · 1 ND
A48: =CALCULOS_ADECUACIÓN!G7 -> Fósforo | B48: =CALCULOS_ADECUACIÓN!H7 -> 1731.5 | C48: =CALCULOS_ADECUACIÓN!I7 -> mg | D48: =CALCULOS_ADECUACIÓN!J7 -> 700 | E48: =CALCULOS_ADECUACIÓN!K7 -> RDA | F48: =CALCULOS_ADECUACIÓN!L7 -> 247.35714 | G48: =CALCULOS_ADECUACIÓN!P7 -> 1 | H48: =CALCULOS_ADECUACIÓN!Q7 -> PARCIAL · 1 ND | I48: ="El módulo cuantifica "&COUNTA(FUENTES_ALIMENTARIAS!$B$13:$B$22)&" alimentos. Los aportes representan solo esos alimentos y gramajes, no la dieta completa. Los porcentajes comparan el aporte conocido con la RDA o AI del perfil. Cuando existe s/i, el resultado se marca PARCIAL y no se reemplaza por cero." -> El módulo cuantifica 10 alimentos. Los aportes representan solo esos alimentos y gramajes, no la dieta completa. Los porcentajes comparan el aporte conocido con la RDA o AI del perfil. Cuando existe s/i, el resultado se marca PARCIAL y no se reemplaza por cero.
A49: =CALCULOS_ADECUACIÓN!G8 -> Selenio | B49: =CALCULOS_ADECUACIÓN!H8 -> 279.94 | C49: =CALCULOS_ADECUACIÓN!I8 -> µg | D49: =CALCULOS_ADECUACIÓN!J8 -> 55 | E49: =CALCULOS_ADECUACIÓN!K8 -> RDA | F49: =CALCULOS_ADECUACIÓN!L8 -> 508.98182 | G49: =CALCULOS_ADECUACIÓN!P8 -> 2 | H49: =CALCULOS_ADECUACIÓN!Q8 -> PARCIAL · 2 ND
A50: =CALCULOS_ADECUACIÓN!G9 -> Potasio | B50: =CALCULOS_ADECUACIÓN!H9 -> 3658.5 | C50: =CALCULOS_ADECUACIÓN!I9 -> mg | D50: =CALCULOS_ADECUACIÓN!J9 -> 2600 | E50: =CALCULOS_ADECUACIÓN!K9 -> AI | F50: =CALCULOS_ADECUACIÓN!L9 -> 140.71154 | G50: =CALCULOS_ADECUACIÓN!P9 -> 2 | H50: =CALCULOS_ADECUACIÓN!Q9 -> PARCIAL · 2 ND
A51: =CALCULOS_ADECUACIÓN!G10 -> Magnesio | B51: =CALCULOS_ADECUACIÓN!H10 -> 617.4 | C51: =CALCULOS_ADECUACIÓN!I10 -> mg | D51: =CALCULOS_ADECUACIÓN!J10 -> 310 | E51: =CALCULOS_ADECUACIÓN!K10 -> RDA | F51: =CALCULOS_ADECUACIÓN!L10 -> 199.16129 | G51: =CALCULOS_ADECUACIÓN!P10 -> 2 | H51: =CALCULOS_ADECUACIÓN!Q10 -> SOBRE UL · PARCIAL
A52: =CALCULOS_ADECUACIÓN!G11 -> Sodio | B52: =CALCULOS_ADECUACIÓN!H11 -> 1078.2 | C52: =CALCULOS_ADECUACIÓN!I11 -> mg | D52: =CALCULOS_ADECUACIÓN!J11 -> 1500 | E52: =CALCULOS_ADECUACIÓN!K11 -> AI | F52: =CALCULOS_ADECUACIÓN!L11 -> 71.88 | G52: =CALCULOS_ADECUACIÓN!P11 -> 1 | H52: =CALCULOS_ADECUACIÓN!Q11 -> PARCIAL · 1 ND
A53: =CALCULOS_ADECUACIÓN!G12 -> Cloruro | B53: =CALCULOS_ADECUACIÓN!H12 -> ND | C53: =CALCULOS_ADECUACIÓN!I12 -> mg | D53: =CALCULOS_ADECUACIÓN!J12 -> 2300 | E53: =CALCULOS_ADECUACIÓN!K12 -> AI | F53: =CALCULOS_ADECUACIÓN!L12 -> ND | G53: =CALCULOS_ADECUACIÓN!P12 -> 10 | H53: =CALCULOS_ADECUACIÓN!Q12 -> ND EN INTA
A54: =CALCULOS_ADECUACIÓN!G13 -> Vitamina A | B54: =CALCULOS_ADECUACIÓN!H13 -> 10197.9 | C54: =CALCULOS_ADECUACIÓN!I13 -> µg RAE | D54: =CALCULOS_ADECUACIÓN!J13 -> 700 | E54: =CALCULOS_ADECUACIÓN!K13 -> RDA | F54: =CALCULOS_ADECUACIÓN!L13 -> 1456.8429 | G54: =CALCULOS_ADECUACIÓN!P13 -> 2 | H54: =CALCULOS_ADECUACIÓN!Q13 -> SOBRE UL · PARCIAL
A55: =CALCULOS_ADECUACIÓN!G14 -> Vitamina D | B55: =CALCULOS_ADECUACIÓN!H14 -> 3.37 | C55: =CALCULOS_ADECUACIÓN!I14 -> µg | D55: =CALCULOS_ADECUACIÓN!J14 -> 15 | E55: =CALCULOS_ADECUACIÓN!K14 -> RDA | F55: =CALCULOS_ADECUACIÓN!L14 -> 22.466667 | G55: =CALCULOS_ADECUACIÓN!P14 -> 4 | H55: =CALCULOS_ADECUACIÓN!Q14 -> PARCIAL · 4 ND
A56: =CALCULOS_ADECUACIÓN!G15 -> Vitamina E | B56: =CALCULOS_ADECUACIÓN!H15 -> 4.22 | C56: =CALCULOS_ADECUACIÓN!I15 -> mg | D56: =CALCULOS_ADECUACIÓN!J15 -> 15 | E56: =CALCULOS_ADECUACIÓN!K15 -> RDA | F56: =CALCULOS_ADECUACIÓN!L15 -> 28.133333 | G56: =CALCULOS_ADECUACIÓN!P15 -> 5 | H56: =CALCULOS_ADECUACIÓN!Q15 -> PARCIAL · 5 ND
A57: =CALCULOS_ADECUACIÓN!G16 -> Vitamina K | B57: =CALCULOS_ADECUACIÓN!H16 -> 504.04 | C57: =CALCULOS_ADECUACIÓN!I16 -> µg | D57: =CALCULOS_ADECUACIÓN!J16 -> 90 | E57: =CALCULOS_ADECUACIÓN!K16 -> AI | F57: =CALCULOS_ADECUACIÓN!L16 -> 560.04444 | G57: =CALCULOS_ADECUACIÓN!P16 -> 5 | H57: =CALCULOS_ADECUACIÓN!Q16 -> PARCIAL · 5 ND
A58: =CALCULOS_ADECUACIÓN!G17 -> Vitamina C | B58: =CALCULOS_ADECUACIÓN!H17 -> 79.35 | C58: =CALCULOS_ADECUACIÓN!I17 -> mg | D58: =CALCULOS_ADECUACIÓN!J17 -> 75 | E58: =CALCULOS_ADECUACIÓN!K17 -> RDA | F58: =CALCULOS_ADECUACIÓN!L17 -> 105.8 | G58: =CALCULOS_ADECUACIÓN!P17 -> 1 | H58: =CALCULOS_ADECUACIÓN!Q17 -> PARCIAL · 1 ND | I58: Interpretación educativa: superar 100% de una RDA/AI no significa toxicidad. La comparación con UL o CDRR se mantiene separada. Las DRI se aplican principalmente a personas aparentemente sanas.
A59: =CALCULOS_ADECUACIÓN!G18 -> Tiamina | B59: =CALCULOS_ADECUACIÓN!H18 -> 1.95 | C59: =CALCULOS_ADECUACIÓN!I18 -> mg | D59: =CALCULOS_ADECUACIÓN!J18 -> 1.1 | E59: =CALCULOS_ADECUACIÓN!K18 -> RDA | F59: =CALCULOS_ADECUACIÓN!L18 -> 177.27273 | G59: =CALCULOS_ADECUACIÓN!P18 -> 1 | H59: =CALCULOS_ADECUACIÓN!Q18 -> PARCIAL · 1 ND
A60: =CALCULOS_ADECUACIÓN!G19 -> Riboflavina | B60: =CALCULOS_ADECUACIÓN!H19 -> 5.07 | C60: =CALCULOS_ADECUACIÓN!I19 -> mg | D60: =CALCULOS_ADECUACIÓN!J19 -> 1.1 | E60: =CALCULOS_ADECUACIÓN!K19 -> RDA | F60: =CALCULOS_ADECUACIÓN!L19 -> 460.90909 | G60: =CALCULOS_ADECUACIÓN!P19 -> 1 | H60: =CALCULOS_ADECUACIÓN!Q19 -> PARCIAL · 1 ND
A61: =CALCULOS_ADECUACIÓN!G20 -> Niacina | B61: =CALCULOS_ADECUACIÓN!H20 -> 29.42 | C61: =CALCULOS_ADECUACIÓN!I20 -> mg NE | D61: =CALCULOS_ADECUACIÓN!J20 -> 14 | E61: =CALCULOS_ADECUACIÓN!K20 -> RDA | F61: =CALCULOS_ADECUACIÓN!L20 -> 210.14286 | G61: =CALCULOS_ADECUACIÓN!P20 -> 1 | H61: =CALCULOS_ADECUACIÓN!Q20 -> PARCIAL · 1 ND
A62: =CALCULOS_ADECUACIÓN!G21 -> Ácido pantoténico | B62: =CALCULOS_ADECUACIÓN!H21 -> 9.58 | C62: =CALCULOS_ADECUACIÓN!I21 -> mg | D62: =CALCULOS_ADECUACIÓN!J21 -> 5 | E62: =CALCULOS_ADECUACIÓN!K21 -> AI | F62: =CALCULOS_ADECUACIÓN!L21 -> 191.6 | G62: =CALCULOS_ADECUACIÓN!P21 -> 3 | H62: =CALCULOS_ADECUACIÓN!Q21 -> PARCIAL · 3 ND
A63: =CALCULOS_ADECUACIÓN!G22 -> Vitamina B6 | B63: =CALCULOS_ADECUACIÓN!H22 -> 2.25 | C63: =CALCULOS_ADECUACIÓN!I22 -> mg | D63: =CALCULOS_ADECUACIÓN!J22 -> 1.3 | E63: =CALCULOS_ADECUACIÓN!K22 -> RDA | F63: =CALCULOS_ADECUACIÓN!L22 -> 173.07692 | G63: =CALCULOS_ADECUACIÓN!P22 -> 2 | H63: =CALCULOS_ADECUACIÓN!Q22 -> PARCIAL · 2 ND
A64: =CALCULOS_ADECUACIÓN!G23 -> Biotina | B64: =CALCULOS_ADECUACIÓN!H23 -> ND | C64: =CALCULOS_ADECUACIÓN!I23 -> µg | D64: =CALCULOS_ADECUACIÓN!J23 -> 30 | E64: =CALCULOS_ADECUACIÓN!K23 -> AI | F64: =CALCULOS_ADECUACIÓN!L23 -> ND | G64: =CALCULOS_ADECUACIÓN!P23 -> 10 | H64: =CALCULOS_ADECUACIÓN!Q23 -> ND EN INTA
A65: =CALCULOS_ADECUACIÓN!G24 -> Folato | B65: =CALCULOS_ADECUACIÓN!H24 -> 549.4 | C65: =CALCULOS_ADECUACIÓN!I24 -> µg DFE | D65: =CALCULOS_ADECUACIÓN!J24 -> 400 | E65: =CALCULOS_ADECUACIÓN!K24 -> RDA | F65: =CALCULOS_ADECUACIÓN!L24 -> 137.35 | G65: =CALCULOS_ADECUACIÓN!P24 -> 3 | H65: =CALCULOS_ADECUACIÓN!Q24 -> PARCIAL · 3 ND
A66: =CALCULOS_ADECUACIÓN!G25 -> Cobalamina | B66: =CALCULOS_ADECUACIÓN!H25 -> 71.88 | C66: =CALCULOS_ADECUACIÓN!I25 -> µg | D66: =CALCULOS_ADECUACIÓN!J25 -> 2.4 | E66: =CALCULOS_ADECUACIÓN!K25 -> RDA | F66: =CALCULOS_ADECUACIÓN!L25 -> 2995 | G66: =CALCULOS_ADECUACIÓN!P25 -> 2 | H66: =CALCULOS_ADECUACIÓN!Q25 -> PARCIAL · 2 ND

Sheet RESUMEN_ESTUDIO
A1: NUTRIMETRÍA · NMX-43 | RESUMEN_ESTUDIO
A3: Matriz de repaso rápido de los 23 micronutrientes incluidos.
A5: =HYPERLINK("#'INICIO'!A1","INICIO") -> INICIO | B5: =HYPERLINK("#'DATOS'!A1","DATOS") -> DATOS | C5: =HYPERLINK("#'ENERGÍA'!A1","ENERGÍA") -> ENERGÍA | D5: =HYPERLINK("#'MACRONUTRIENTES'!A1","MACRONUTRIENTES") -> MACRONUTRIENTES | E5: =HYPERLINK("#'AGUA_FIBRA'!A1","AGUA/FIBRA") -> AGUA/FIBRA | F5: =HYPERLINK("#'FICHA_NUTRIENTE'!A1","FICHA/NUTRIENTE") -> FICHA/NUTRIENTE | G5: =HYPERLINK("#'RESULTADOS'!A1","RESULTADOS") -> RESULTADOS | H5: =HYPERLINK("#'DOCUMENTACIÓN'!A1","DOCUMENTACIÓN") -> DOCUMENTACIÓN | I5: =HYPERLINK("#'COBERTURA'!A1","COBERTURA") -> COBERTURA | J5: =HYPERLINK("#'AUDITORÍA_FINAL'!A1","AUDITORÍA") -> AUDITORÍA
A7: ID | B7: Nutriente | C7: Categoría | D7: Función principal | E7: Fuente alimentaria destacada | F7: Déficit | G7: Exceso | H7: Interacción | I7: Biomarcador | J7: Perla clínica | K7: Fuente_ID | L7: Estado | M7: Disponible INTA | N7: Aporte demo | O7: % referencia
A8: MIN-FE | B8: Hierro | C8: Mineral | D8: Transporte y almacenamiento de oxígeno mediante hemoglobina y mioglobina. | E8: Hígado y carnes rojas | F8: Fatiga, palidez, menor rendimiento, alteración cognitiva y anemia microcítica/hipocrómica. | G8: La sobrecarga puede dañar hígado, corazón y otros tejidos. | H8: Vitamina C: Aumenta absorción | I8: Ferritina | J8: Ferritina baja apoya depósitos disminuidos, pero ferritina normal/alta no excluye deficiencia con inflamación. | K8: SRC-ODS-IRON | L8: VERIFICADO_SECUNDARIO | M8: =IFERROR(IFERROR(INDEX(LISTAS!$AJ$2:$AJ$24,MATCH($A8,LISTAS!$AF$2:$AF$24,0)),"No"),"No") -> Sí | N8: =IFERROR(IFERROR(INDEX(CALCULOS_ADECUACIÓN!$H$3:$H$25,MATCH($A8,CALCULOS_ADECUACIÓN!$F$3:$F$25,0)),"ND"),"ND") -> 32.17 | O8: =IFERROR(IFERROR(INDEX(CALCULOS_ADECUACIÓN!$L$3:$L$25,MATCH($A8,CALCULOS_ADECUACIÓN!$F$3:$F$25,0)),"ND"),"ND") -> 178.72222
A9: MIN-ZN | B9: Zinc | C9: Mineral | D9: Actividad catalítica de numerosas enzimas. | E9: Ostras y otros mariscos | F9: Retraso del crecimiento, alopecia, dermatitis, diarrea, alteración del gusto, mala cicatrización e inmunidad deteriorada. | G9: Dosis elevadas sostenidas pueden causar náuseas, reducir cobre, alterar perfil lipídico y deteriorar función inmunitaria. | H9: Cobre: Dosis altas de zinc reducen cobre | I9: Zinc plasmático/sérico | J9: Zinc alto en suplementos puede inducir deficiencia de cobre. | K9: SRC-ODS-ZINC | L9: VERIFICADO_SECUNDARIO | M9: =IFERROR(IFERROR(INDEX(LISTAS!$AJ$2:$AJ$24,MATCH($A9,LISTAS!$AF$2:$AF$24,0)),"No"),"No") -> Sí | N9: =IFERROR(IFERROR(INDEX(CALCULOS_ADECUACIÓN!$H$3:$H$25,MATCH($A9,CALCULOS_ADECUACIÓN!$F$3:$F$25,0)),"ND"),"ND") -> 13.37 | O9: =IFERROR(IFERROR(INDEX(CALCULOS_ADECUACIÓN!$L$3:$L$25,MATCH($A9,CALCULOS_ADECUACIÓN!$F$3:$F$25,0)),"ND"),"ND") -> 167.125
A10: MIN-CU | B10: Cobre | C10: Mineral | D10: Metabolismo del hierro y formación de tejido conectivo. | E10: Hígado | F10: Anemia, neutropenia, alteraciones óseas, despigmentación y neuropatía/mielopatía. | G10: Náuseas, dolor abdominal y daño hepático; el riesgo es mayor en trastornos hereditarios del metabolismo del cobre. | H10: Zinc suplementario: Disminuye absorción de cobre | I10: Cobre sérico y ceruloplasmina | J10: Zinc y cobre compiten de forma clínicamente relevante en suplementos. | K10: SRC-ODS-COPPER | L10: VERIFICADO_SECUNDARIO | M10: =IFERROR(IFERROR(INDEX(LISTAS!$AJ$2:$AJ$24,MATCH($A10,LISTAS!$AF$2:$AF$24,0)),"No"),"No") -> Sí | N10: =IFERROR(IFERROR(INDEX(CALCULOS_ADECUACIÓN!$H$3:$H$25,MATCH($A10,CALCULOS_ADECUACIÓN!$F$3:$F$25,0)),"ND"),"ND") -> 15.95 | O10: =IFERROR(IFERROR(INDEX(CALCULOS_ADECUACIÓN!$L$3:$L$25,MATCH($A10,CALCULOS_ADECUACIÓN!$F$3:$F$25,0)),"ND"),"ND") -> 1772.2222
A11: MIN-CA | B11: Calcio | C11: Mineral | D11: Estructura ósea y dental. | E11: Leche, yogur y queso | F11: La ingesta insuficiente crónica contribuye a baja masa ósea y osteoporosis; hipocalcemia clínica suele reflejar alteraciones hormonales, renales o vitamínicas más que dieta aislada. | G11: Hipercalcemia/hipercalciuria, estreñimiento y riesgo de cálculos en contextos susceptibles; suplementos excesivos pueden interferir con medicamentos. | H11: Vitamina D: Aumenta absorción de calcio | I11: Calcio ionizado/total | J11: Calcio sérico normal no descarta ingesta baja. | K11: SRC-ODS-CALCIUM | L11: VERIFICADO_SECUNDARIO | M11: =IFERROR(IFERROR(INDEX(LISTAS!$AJ$2:$AJ$24,MATCH($A11,LISTAS!$AF$2:$AF$24,0)),"No"),"No") -> Sí | N11: =IFERROR(IFERROR(INDEX(CALCULOS_ADECUACIÓN!$H$3:$H$25,MATCH($A11,CALCULOS_ADECUACIÓN!$F$3:$F$25,0)),"ND"),"ND") -> 2121.2 | O11: =IFERROR(IFERROR(INDEX(CALCULOS_ADECUACIÓN!$L$3:$L$25,MATCH($A11,CALCULOS_ADECUACIÓN!$F$3:$F$25,0)),"ND"),"ND") -> 212.12
A12: MIN-P | B12: Fósforo | C12: Mineral | D12: Estructura ósea y dental. | E12: Lácteos | F12: Rara por dieta aislada; puede causar debilidad, dolor óseo, alteraciones hematológicas y osteomalacia en casos graves. | G12: Hiperfosfatemia, especialmente con enfermedad renal, altera metabolismo mineral y puede favorecer calcificación vascular y trastorno óseo. | H12: Antiácidos con aluminio: Disminuye absorción de fósforo | I12: Fósforo sérico | J12: Los aditivos fosfatados pueden aportar fósforo altamente absorbible. | K12: SRC-ODS-PHOSPHORUS | L12: VERIFICADO_SECUNDARIO | M12: =IFERROR(IFERROR(INDEX(LISTAS!$AJ$2:$AJ$24,MATCH($A12,LISTAS!$AF$2:$AF$24,0)),"No"),"No") -> Sí | N12: =IFERROR(IFERROR(INDEX(CALCULOS_ADECUACIÓN!$H$3:$H$25,MATCH($A12,CALCULOS_ADECUACIÓN!$F$3:$F$25,0)),"ND"),"ND") -> 1731.5 | O12: =IFERROR(IFERROR(INDEX(CALCULOS_ADECUACIÓN!$L$3:$L$25,MATCH($A12,CALCULOS_ADECUACIÓN!$F$3:$F$25,0)),"ND"),"ND") -> 247.35714
A13: MIN-SE | B13: Selenio | C13: Mineral | D13: Defensa antioxidante mediante glutatión peroxidasas. | E13: Pescados y mariscos | F13: Puede deteriorar función de selenoproteínas; se ha asociado a cardiomiopatía en contextos endémicos y puede agravar alteraciones tiroideas. | G13: Selenosis: caída de cabello, uñas frágiles, aliento a ajo, náuseas, alteraciones neurológicas y cutáneas. | H13: Yodo/función tiroidea: Relación funcional | I13: Selenio sérico/plasmático | J13: El contenido de selenio de un alimento puede variar por suelo. | K13: SRC-ODS-SELENIUM | L13: VERIFICADO_SECUNDARIO | M13: =IFERROR(IFERROR(INDEX(LISTAS!$AJ$2:$AJ$24,MATCH($A13,LISTAS!$AF$2:$AF$24,0)),"No"),"No") -> Sí | N13: =IFERROR(IFERROR(INDEX(CALCULOS_ADECUACIÓN!$H$3:$H$25,MATCH($A13,CALCULOS_ADECUACIÓN!$F$3:$F$25,0)),"ND"),"ND") -> 279.94 | O13: =IFERROR(IFERROR(INDEX(CALCULOS_ADECUACIÓN!$L$3:$L$25,MATCH($A13,CALCULOS_ADECUACIÓN!$F$3:$F$25,0)),"ND"),"ND") -> 508.98182
A14: MIN-K | B14: Potasio | C14: Mineral | D14: Potencial de membrana y transmisión nerviosa. | E14: Papas | F14: Hipopotasemia: debilidad, calambres, estreñimiento y arritmias; suele deberse a pérdidas o redistribución más que a dieta aislada. | G14: Hiperpotasemia puede causar debilidad y arritmias; riesgo con insuficiencia renal, ciertos fármacos y suplementos/sustitutos de sal. | H14: IECA/ARA-II: Puede aumentar potasio sérico | I14: Potasio sérico | J14: Potasio sérico no mide consumo dietario. | K14: SRC-ODS-POTASSIUM | L14: VERIFICADO_SECUNDARIO | M14: =IFERROR(IFERROR(INDEX(LISTAS!$AJ$2:$AJ$24,MATCH($A14,LISTAS!$AF$2:$AF$24,0)),"No"),"No") -> Sí | N14: =IFERROR(IFERROR(INDEX(CALCULOS_ADECUACIÓN!$H$3:$H$25,MATCH($A14,CALCULOS_ADECUACIÓN!$F$3:$F$25,0)),"ND"),"ND") -> 3658.5 | O14: =IFERROR(IFERROR(INDEX(CALCULOS_ADECUACIÓN!$L$3:$L$25,MATCH($A14,CALCULOS_ADECUACIÓN!$F$3:$F$25,0)),"ND"),"ND") -> 140.71154
A15: MIN-MG | B15: Magnesio | C15: Mineral | D15: Síntesis de proteínas y ácidos nucleicos. | E15: Semillas y frutos secos | F15: Pérdida de apetito, náuseas, debilidad; casos más graves con calambres, alteraciones neuromusculares, hipocalcemia, hipopotasemia y arritmias. | G15: El alimento rara vez causa toxicidad en personas sanas; suplementos o fármacos con magnesio pueden causar diarrea y, con insuficiencia renal, toxicidad sistémica. | H15: Inhibidores de bomba de protones: Puede disminuir magnesio | I15: Magnesio sérico | J15: El UL se aplica al magnesio de suplementos/medicamentos, no al de alimentos. | K15: SRC-ODS-MAGNESIUM | L15: VERIFICADO_SECUNDARIO | M15: =IFERROR(IFERROR(INDEX(LISTAS!$AJ$2:$AJ$24,MATCH($A15,LISTAS!$AF$2:$AF$24,0)),"No"),"No") -> Sí | N15: =IFERROR(IFERROR(INDEX(CALCULOS_ADECUACIÓN!$H$3:$H$25,MATCH($A15,CALCULOS_ADECUACIÓN!$F$3:$F$25,0)),"ND"),"ND") -> 617.4 | O15: =IFERROR(IFERROR(INDEX(CALCULOS_ADECUACIÓN!$L$3:$L$25,MATCH($A15,CALCULOS_ADECUACIÓN!$F$3:$F$25,0)),"ND"),"ND") -> 199.16129
A16: MIN-NA | B16: Sodio | C16: Mineral | D16: Volumen extracelular y balance hídrico. | E16: Sal de mesa | F16: Hiponatremia produce cefalea, confusión, náuseas, convulsiones o coma; suele ser un trastorno de agua y regulación, no simple baja ingesta. | G16: Una ingesta elevada favorece presión arterial y riesgo cardiovascular en la población; hiper­natremia suele reflejar déficit de agua. | H16: Potasio y patrón DASH: Modula efecto sobre presión arterial | I16: Sodio sérico | J16: Sodio sérico no equivale a consumo de sal. | K16: SRC-NASEM-SODIUM-2019 | L16: VERIFICADO_SECUNDARIO | M16: =IFERROR(IFERROR(INDEX(LISTAS!$AJ$2:$AJ$24,MATCH($A16,LISTAS!$AF$2:$AF$24,0)),"No"),"No") -> Sí | N16: =IFERROR(IFERROR(INDEX(CALCULOS_ADECUACIÓN!$H$3:$H$25,MATCH($A16,CALCULOS_ADECUACIÓN!$F$3:$F$25,0)),"ND"),"ND") -> 1078.2 | O16: =IFERROR(IFERROR(INDEX(CALCULOS_ADECUACIÓN!$L$3:$L$25,MATCH($A16,CALCULOS_ADECUACIÓN!$F$3:$F$25,0)),"ND"),"ND") -> 71.88
A17: MIN-CL | B17: Cloruro | C17: Mineral | D17: Equilibrio osmótico y electroneutralidad. | E17: Sal de mesa | F17: Hipocloremia puede acompañar alcalosis metabólica, vómitos y depleción de volumen; los síntomas dependen del trastorno subyacente. | G17: Hipercloremia puede acompañar deshidratación, acidosis metabólica o cargas elevadas de cloruro en contextos clínicos. | H17: Vómitos/aspiración gástrica: Aumenta pérdida de cloruro | I17: Cloruro sérico | J17: Debe llamarse cloruro, no cloro elemental. | K17: SRC-DRI-CHLORIDE-2005 | L17: VERIFICADO_SECUNDARIO | M17: =IFERROR(IFERROR(INDEX(LISTAS!$AJ$2:$AJ$24,MATCH($A17,LISTAS!$AF$2:$AF$24,0)),"No"),"No") -> No | N17: =IFERROR(IFERROR(INDEX(CALCULOS_ADECUACIÓN!$H$3:$H$25,MATCH($A17,CALCULOS_ADECUACIÓN!$F$3:$F$25,0)),"ND"),"ND") -> ND | O17: =IFERROR(IFERROR(INDEX(CALCULOS_ADECUACIÓN!$L$3:$L$25,MATCH($A17,CALCULOS_ADECUACIÓN!$F$3:$F$25,0)),"ND"),"ND") -> ND
A18: VIT-A | B18: Vitamina A | C18: Vitamina liposoluble | D18: Visión, especialmente adaptación a oscuridad. | E18: Hígado | F18: Ceguera nocturna, xeroftalmía, queratinización epitelial, mayor susceptibilidad a infecciones y alteración del crecimiento. | G18: Toxicidad aguda o crónica por retinol: cefalea, alteraciones hepáticas, óseas y cutáneas; riesgo teratogénico en embarazo. | H18: Zinc: Relación funcional | I18: Retinol sérico | J18: Retinol y beta-caroteno no tienen la misma toxicidad. | K18: SRC-ODS-VITA | L18: VERIFICADO_SECUNDARIO | M18: =IFERROR(IFERROR(INDEX(LISTAS!$AJ$2:$AJ$24,MATCH($A18,LISTAS!$AF$2:$AF$24,0)),"No"),"No") -> Sí | N18: =IFERROR(IFERROR(INDEX(CALCULOS_ADECUACIÓN!$H$3:$H$25,MATCH($A18,CALCULOS_ADECUACIÓN!$F$3:$F$25,0)),"ND"),"ND") -> 10197.9 | O18: =IFERROR(IFERROR(INDEX(CALCULOS_ADECUACIÓN!$L$3:$L$25,MATCH($A18,CALCULOS_ADECUACIÓN!$F$3:$F$25,0)),"ND"),"ND") -> 1456.8429
A19: VIT-D | B19: Vitamina D | C19: Vitamina liposoluble | D19: Favorece absorción de calcio y fósforo. | E19: Pescados grasos | F19: Raquitismo en niños, osteomalacia en adultos, debilidad muscular y contribución a baja salud ósea. | G19: Toxicidad por suplementos: hipercalcemia, hipercalciuria, náuseas, debilidad, cálculos y daño renal; no suele deberse al sol. | H19: Orlistat/colestiramina: Reduce absorción | I19: 25-hidroxivitamina D | J19: 25(OH)D evalúa estado; 1,25(OH)₂D no refleja reservas habituales. | K19: SRC-ODS-VITD | L19: VERIFICADO_SECUNDARIO | M19: =IFERROR(IFERROR(INDEX(LISTAS!$AJ$2:$AJ$24,MATCH($A19,LISTAS!$AF$2:$AF$24,0)),"No"),"No") -> Sí | N19: =IFERROR(IFERROR(INDEX(CALCULOS_ADECUACIÓN!$H$3:$H$25,MATCH($A19,CALCULOS_ADECUACIÓN!$F$3:$F$25,0)),"ND"),"ND") -> 3.37 | O19: =IFERROR(IFERROR(INDEX(CALCULOS_ADECUACIÓN!$L$3:$L$25,MATCH($A19,CALCULOS_ADECUACIÓN!$F$3:$F$25,0)),"ND"),"ND") -> 22.466667
... A30: VIT-B12 | B30: Cobalamina | C30: Vitamina hidrosoluble | D30: Síntesis de ADN y formación eritrocitaria. | E30: Almejas y otros mariscos | F30: Anemia megaloblástica, glositis, parestesias, pérdida de vibración, alteración de marcha, cognición y ánimo; MMA y homocisteína pueden aumentar. | G30: No se ha establecido UL; toxicidad oral es baja, aunque los suplementos no deben sustituir diagnóstico. | H30: Metformina: Disminuye estado/absorción | I30: Vitamina B12 sérica | J30: Puede existir daño neurológico sin anemia. | K30: SRC-ODS-B12 | L30: VERIFICADO_SECUNDARIO | M30: =IFERROR(IFERROR(INDEX(LISTAS!$AJ$2:$AJ$24,MATCH($A30,LISTAS!$AF$2:$AF$24,0)),"No"),"No") -> Sí | N30: =IFERROR(IFERROR(INDEX(CALCULOS_ADECUACIÓN!$H$3:$H$25,MATCH($A30,CALCULOS_ADECUACIÓN!$F$3:$F$25,0)),"ND"),"ND") -> 71.88 | O30: =IFERROR(IFERROR(INDEX(CALCULOS_ADECUACIÓN!$L$3:$L$25,MATCH($A30,CALCULOS_ADECUACIÓN!$F$3:$F$25,0)),"ND"),"ND") -> 2995

Sheet FUENTES
A1: NUTRIMETRÍA · NMX-43 | FUENTES
A3: Trazabilidad documental y estado de verificación.
A5: =HYPERLINK("#'INICIO'!A1","INICIO") -> INICIO | B5: =HYPERLINK("#'DATOS'!A1","DATOS") -> DATOS | C5: =HYPERLINK("#'ENERGÍA'!A1","ENERGÍA") -> ENERGÍA | D5: =HYPERLINK("#'MACRONUTRIENTES'!A1","MACRONUTRIENTES") -> MACRONUTRIENTES | E5: =HYPERLINK("#'AGUA_FIBRA'!A1","AGUA/FIBRA") -> AGUA/FIBRA | F5: =HYPERLINK("#'FICHA_NUTRIENTE'!A1","FICHA/NUTRIENTE") -> FICHA/NUTRIENTE | G5: =HYPERLINK("#'RESULTADOS'!A1","RESULTADOS") -> RESULTADOS | H5: =HYPERLINK("#'DOCUMENTACIÓN'!A1","DOCUMENTACIÓN") -> DOCUMENTACIÓN | I5: =HYPERLINK("#'COBERTURA'!A1","COBERTURA") -> COBERTURA | J5: =HYPERLINK("#'AUDITORÍA_FINAL'!A1","AUDITORÍA") -> AUDITORÍA
A7: Fuente_ID | B7: Tema | C7: Institución/autor | D7: Título | E7: Año | F7: Tipo | G7: Nivel | H7: URL | I7: Fecha consulta | J7: Módulo | K7: Estado | L7: Observaciones
A8: PORTAFOLIO-2026 | B8: Pauta académica | C8: Universidad Autónoma de Chile / Mg. Javier Arriagada Gacitúa | D8: Portafolios Bases de la Nutrición II | E8: 2026 | F8: Documento docente | G8: A | H8: Archivo adjunto | I8: 46236 | J8: Todos | K8: VERIFICADO | L8: Base obligatoria de requisitos académicos.
A9: NMX21 | B9: Diseño y base alimentaria | C9: Nutrimetría / INTA 2018 según el archivo de referencia | D9: NMX-21 Distribución Alimentaria INTA2018 aprobado | E9: 2026 | F9: Excel de referencia | G9: A | H9: Archivo adjunto | I9: 46236 | J9: Diseño, alimentos y normalización Fase 6 | K9: VERIFICADO | L9: Base INTA y tabla DRI reutilizadas sin modificar el original; licencia comercial pendiente.
A10: SRC-FAO-ENER-2004 | B10: Energía y método factorial | C10: FAO/WHO/UNU | D10: Human Energy Requirements | E10: 2004 | F10: Informe técnico | G10: A | H10: https://www.fao.org/4/y5686e/y5686e00.htm | I10: 46236 | J10: ENERGÍA | K10: VERIFICADO | L10: Ecuaciones pediátricas, Schofield reproducido, PAL/PAR y crecimiento.
A11: SRC-SCHOFIELD-1985 | B11: Metabolismo basal | C11: W. N. Schofield | D11: Predicting basal metabolic rate, new standards and review of previous work | E11: 1985 | F11: Artículo original | G11: A | H11: https://pubmed.ncbi.nlm.nih.gov/4044297/ | I11: 46236 | J11: ENERGÍA | K11: VERIFICADO | L11: Ecuaciones por edad y sexo basadas en peso.
A12: SRC-NASEM-ENER-2023 | B12: Energía | C12: National Academies of Sciences, Engineering, and Medicine | D12: Dietary Reference Intakes for Energy | E12: 2023 | F12: Informe normativo | G12: A | H12: https://www.ncbi.nlm.nih.gov/books/NBK591034/ | I12: 46236 | J12: ENERGÍA | K12: VERIFICADO | L12: EER por edad, sexo, actividad y etapa fisiológica.
A13: SRC-DRI-SUMMARY | B13: DRI de macro y micronutrientes | C13: Institute of Medicine / National Academies | D13: Dietary Reference Intakes: Reference Tables | E13: 2005 | F13: Tablas normativas | G13: A | H13: https://www.ncbi.nlm.nih.gov/books/NBK208874/ | I13: 46237 | J13: MACRONUTRIENTES; AGUA_FIBRA; REQUERIMIENTOS; FASE 6 | K13: VERIFICADO | L13: RDA/AI y tablas de referencia; los informes específicos tienen años distintos.
A14: SRC-ATWATER | B14: Conversión energética | C14: FAO | D14: Food energy – methods of analysis and conversion factors | E14: 2003 | F14: Informe técnico | G14: A | H14: https://www.fao.org/4/y5022e/y5022e04.htm | I14: 46236 | J14: MACRONUTRIENTES; CONFIG | K14: VERIFICADO | L14: Factores generales 4 kcal/g proteína, 9 grasa y 4 CHO.
A15: SRC-GI-2021 | B15: Índice glicémico | C15: Atkinson, Brand-Miller, Foster-Powell, Buyken y Goletzke | D15: International tables of glycemic index and glycemic load values 2021: a systematic review | E15: 2021 | F15: Revisión sistemática | G15: A | H15: https://pubmed.ncbi.nlm.nih.gov/34258626/ | I15: 46236 | J15: ÍNDICE_CARGA_GLICÉMICA | K15: VERIFICADO | L15: Más de 4.000 alimentos; el prototipo usa promedios de categorías con advertencia.
A16: SRC-GI-CUTOFFS | B16: Clasificación IG/CG | C16: University of Sydney Glycemic Index Research Service | D16: GI FAQs and glycemic-load cut-offs | E16: — | F16: Fuente académica secundaria | G16: B | H16: https://glycemicindex.com/faqs/ | I16: 46236 | J16: ÍNDICE_CARGA_GLICÉMICA; CONFIG | K16: VERIFICADO_SECUNDARIO | L16: IG ≤55 bajo, 56–69 medio, ≥70 alto; GL según guías del grupo.
A17: SRC-NIH-ODS | B17: Fichas de nutrientes | C17: NIH Office of Dietary Supplements | D17: Vitamin and Mineral Supplement Fact Sheets | E17: — | F17: Institucional | G17: A | H17: https://ods.od.nih.gov/factsheets/list-VitaminsMinerals/ | I17: 46236 | J17: FASE 5 | K17: VERIFICADO | L17: Fuente auxiliar para fichas; revisar referencias primarias específicas.
A18: SRC-ODS-IRON | B18: Hierro | C18: NIH Office of Dietary Supplements | D18: Iron — Fact Sheet for Health Professionals | E18: Actualización continua | F18: Institucional | G18: A | H18: https://ods.od.nih.gov/factsheets/Iron-HealthProfessional/ | I18: 46237 | J18: FASE 5 | K18: VERIFICADO | L18: Funciones, absorción, deficiencia, exceso, fuentes e interacciones.
A19: SRC-ODS-ZINC | B19: Zinc | C19: NIH Office of Dietary Supplements | D19: Zinc — Fact Sheet for Health Professionals | E19: Actualización continua | F19: Institucional | G19: A | H19: https://ods.od.nih.gov/factsheets/Zinc-HealthProfessional/ | I19: 46237 | J19: FASE 5 | K19: VERIFICADO | L19: Funciones, biodisponibilidad, déficit, exceso e interacciones.
A20: SRC-ODS-COPPER | B20: Cobre | C20: NIH Office of Dietary Supplements | D20: Copper — Fact Sheet for Health Professionals | E20: Actualización continua | F20: Institucional | G20: A | H20: https://ods.od.nih.gov/factsheets/Copper-HealthProfessional/ | I20: 46237 | J20: FASE 5 | K20: VERIFICADO | L20: Metabolismo, déficit, toxicidad e interacción con zinc.
A21: SRC-ODS-CALCIUM | B21: Calcio | C21: NIH Office of Dietary Supplements | D21: Calcium — Fact Sheet for Health Professionals | E21: Actualización continua | F21: Institucional | G21: A | H21: https://ods.od.nih.gov/factsheets/Calcium-HealthProfessional/ | I21: 46237 | J21: FASE 5 | K21: VERIFICADO | L21: Absorción, funciones, exceso e interacciones.
A22: SRC-ODS-PHOSPHORUS | B22: Fósforo | C22: NIH Office of Dietary Supplements | D22: Phosphorus — Fact Sheet for Health Professionals | E22: Actualización continua | F22: Institucional | G22: A | H22: https://ods.od.nih.gov/factsheets/Phosphorus-HealthProfessional/ | I22: 46237 | J22: FASE 5 | K22: VERIFICADO | L22: Funciones, balance, déficit y exceso.
A23: SRC-ODS-SELENIUM | B23: Selenio | C23: NIH Office of Dietary Supplements | D23: Selenium — Fact Sheet for Health Professionals | E23: Actualización continua | F23: Institucional | G23: A | H23: https://ods.od.nih.gov/factsheets/Selenium-HealthProfessional/ | I23: 46237 | J23: FASE 5 | K23: VERIFICADO | L23: Selenoproteínas, deficiencia y toxicidad.
A24: SRC-ODS-POTASSIUM | B24: Potasio | C24: NIH Office of Dietary Supplements | D24: Potassium — Fact Sheet for Health Professionals | E24: Actualización continua | F24: Institucional | G24: A | H24: https://ods.od.nih.gov/factsheets/Potassium-HealthProfessional/ | I24: 46237 | J24: FASE 5 | K24: VERIFICADO | L24: Funciones, hipopotasemia, hiperpotasemia e interacciones farmacológicas.
A25: SRC-ODS-MAGNESIUM | B25: Magnesio | C25: NIH Office of Dietary Supplements | D25: Magnesium — Fact Sheet for Health Professionals | E25: Actualización continua | F25: Institucional | G25: A | H25: https://ods.od.nih.gov/factsheets/Magnesium-HealthProfessional/ | I25: 46237 | J25: FASE 5 | K25: VERIFICADO | L25: Funciones enzimáticas, déficit, exceso e interacciones.
A26: SRC-NASEM-SODIUM-2019 | B26: Sodio | C26: National Academies / NCBI Bookshelf | D26: Dietary Reference Intakes for Sodium and Potassium | E26: 2019 | F26: Informe normativo | G26: A | H26: https://www.ncbi.nlm.nih.gov/books/NBK538102/ | I26: 46237 | J26: FASE 5 | K26: VERIFICADO | L26: AI, CDRR, fisiología y ausencia de EAR/RDA/UL.
A27: SRC-NCBI-CHLORIDE | B27: Cloruro | C27: National Library of Medicine / NCBI Bookshelf | D27: Serum Chloride — Clinical Methods | E27: 1990 | F27: Libro clínico de referencia | G27: B | H27: https://www.ncbi.nlm.nih.gov/books/NBK309/ | I27: 46237 | J27: FASE 5 | K27: VERIFICADO_SECUNDARIO | L27: Fisiología clínica, pérdidas y limitaciones del cloruro sérico.
A28: SRC-DRI-CHLORIDE-2005 | B28: Cloruro | C28: Institute of Medicine / NCBI | D28: Dietary Reference Intakes for Water, Potassium, Sodium, Chloride, and Sulfate | E28: 2005 | F28: Informe normativo | G28: A | H28: https://www.ncbi.nlm.nih.gov/nlmcatalog/101209392 | I28: 46237 | J28: FASE 5 | K28: VERIFICADO | L28: Requerimientos y marco de referencia para cloruro.
A29: SRC-ODS-VITA | B29: Vitamina A | C29: NIH Office of Dietary Supplements | D29: Vitamin A and Carotenoids — Fact Sheet for Health Professionals | E29: Actualización continua | F29: Institucional | G29: A | H29: https://ods.od.nih.gov/factsheets/VitaminA-HealthProfessional/ | I29: 46237 | J29: FASE 5 | K29: VERIFICADO | L29: Retinoides, carotenoides, deficiencia, toxicidad e interacciones.
A30: SRC-ODS-VITD | B30: Vitamina D | C30: NIH Office of Dietary Supplements | D30: Vitamin D — Fact Sheet for Health Professionals | E30: Actualización continua | F30: Institucional | G30: A | H30: https://ods.od.nih.gov/factsheets/VitaminD-HealthProfessional/ | I30: 46237 | J30: FASE 5 | K30: VERIFICADO | L30: Metabolismo, 25(OH)D, deficiencia, exceso e interacciones.
A31: SRC-ODS-VITE | B31: Vitamina E | C31: NIH Office of Dietary Supplements | D31: Vitamin E — Fact Sheet for Health Professionals | E31: Actualización continua | F31: Institucional | G31: A | H31: https://ods.od.nih.gov/factsheets/VitaminE-HealthProfessional/ | I31: 46237 | J31: FASE 5 | K31: VERIFICADO | L31: α-tocoferol, antioxidación, déficit y seguridad.
A32: SRC-ODS-VITK | B32: Vitamina K | C32: NIH Office of Dietary Supplements | D32: Vitamin K — Fact Sheet for Health Professionals | E32: Actualización continua | F32: Institucional | G32: A | H32: https://ods.od.nih.gov/factsheets/VitaminK-HealthProfessional/ | I32: 46237 | J32: FASE 5 | K32: VERIFICADO | L32: Coagulación, hueso, deficiencia e interacción con warfarina.
A33: SRC-ODS-VITC | B33: Vitamina C | C33: NIH Office of Dietary Supplements | D33: Vitamin C — Fact Sheet for Health Professionals | E33: Actualización continua | F33: Institucional | G33: A | H33: https://ods.od.nih.gov/factsheets/VitaminC-HealthProfessional/ | I33: 46237 | J33: FASE 5 | K33: VERIFICADO | L33: Colágeno, antioxidación, hierro no hemo y toxicidad.
A34: SRC-ODS-B1 | B34: Tiamina | C34: NIH Office of Dietary Supplements | D34: Thiamin — Fact Sheet for Health Professionals | E34: Actualización continua | F34: Institucional | G34: A | H34: https://ods.od.nih.gov/factsheets/Thiamin-HealthProfessional/ | I34: 46237 | J34: FASE 5 | K34: VERIFICADO | L34: Metabolismo energético, déficit y riesgo por alcohol.
A35: SRC-ODS-B2 | B35: Riboflavina | C35: NIH Office of Dietary Supplements | D35: Riboflavin — Fact Sheet for Health Professionals | E35: Actualización continua | F35: Institucional | G35: A | H35: https://ods.od.nih.gov/factsheets/Riboflavin-HealthProfessional/ | I35: 46237 | J35: FASE 5 | K35: VERIFICADO | L35: FMN/FAD, deficiencia y estado nutricional.
A36: SRC-ODS-B3 | B36: Niacina | C36: NIH Office of Dietary Supplements | D36: Niacin — Fact Sheet for Health Professionals | E36: Actualización continua | F36: Institucional | G36: A | H36: https://ods.od.nih.gov/factsheets/Niacin-HealthProfessional/ | I36: 46237 | J36: FASE 5 | K36: VERIFICADO | L36: NAD/NADP, pelagra y toxicidad farmacológica.
A37: SRC-ODS-B5 | B37: Ácido pantoténico | C37: NIH Office of Dietary Supplements | D37: Pantothenic Acid — Fact Sheet for Health Professionals | E37: Actualización continua | F37: Institucional | G37: A | H37: https://ods.od.nih.gov/factsheets/PantothenicAcid-HealthProfessional/ | I37: 46237 | J37: FASE 5 | K37: VERIFICADO | L37: Coenzima A, déficit raro y seguridad.
A38: SRC-ODS-B6 | B38: Vitamina B6 | C38: NIH Office of Dietary Supplements | D38: Vitamin B6 — Fact Sheet for Health Professionals | E38: Actualización continua | F38: Institucional | G38: A | H38: https://ods.od.nih.gov/factsheets/VitaminB6-HealthProfessional/ | I38: 46237 | J38: FASE 5 | K38: VERIFICADO | L38: PLP, metabolismo aminoacídico, déficit, toxicidad e interacciones.
A39: SRC-ODS-B7 | B39: Biotina | C39: NIH Office of Dietary Supplements | D39: Biotin — Fact Sheet for Health Professionals | E39: Actualización continua | F39: Institucional | G39: A | H39: https://ods.od.nih.gov/factsheets/Biotin-HealthProfessional/ | I39: 46237 | J39: FASE 5 | K39: VERIFICADO | L39: Carboxilasas, déficit raro e interferencia analítica.
A40: SRC-ODS-B9 | B40: Folato | C40: NIH Office of Dietary Supplements | D40: Folate — Fact Sheet for Health Professionals | E40: Actualización continua | F40: Institucional | G40: A | H40: https://ods.od.nih.gov/factsheets/Folate-HealthProfessional/ | I40: 46237 | J40: FASE 5 | K40: VERIFICADO | L40: Unidades DFE, síntesis de ADN, déficit e interacciones.
A41: SRC-ODS-B12 | B41: Vitamina B12 | C41: NIH Office of Dietary Supplements | D41: Vitamin B12 — Fact Sheet for Health Professionals | E41: Actualización continua | F41: Institucional | G41: A | H41: https://ods.od.nih.gov/factsheets/VitaminB12-HealthProfessional/ | I41: 46237 | J41: FASE 5 | K41: VERIFICADO | L41: Absorción con factor intrínseco, biomarcadores e interacciones.
A42: SRC-NMX43-F6-NORM | B42: Normalización técnica | C42: Nutrimetría Excel Lab | D42: Normalización de DRI y cálculo por gramaje para NMX-43 | E42: 2026 | F42: Transformación documentada | G42: B | H42: Archivo interno | I42: 46237 | J42: REQUERIMIENTOS; FUENTES_ALIMENTARIAS; RESULTADOS | K42: VERIFICADO_SECUNDARIO | L42: Transformación de tablas adjuntas; no reemplaza documentos primarios.
A43: SRC-USUARIO | B43: Entrada manual | C43: Usuario del libro | D43: Valor publicado ingresado manualmente | E43: Variable | F43: Fuente aportada por el usuario | G43: C | H43: Debe registrarse en la hoja correspondiente | I43: 46237 | J43: ÍNDICE_CARGA_GLICÉMICA | K43: PENDIENTE_PRIMARIA | L43: No se considera verificada hasta registrar y revisar la fuente exacta.
A44: SRC-NMX43-F7-QA | B44: Gobernanza y control de calidad | C44: Nutrimetría Excel Lab | D44: Documentación, cobertura y auditoría estructural de NMX-43 | E44: 2026 | F44: Documentación interna | G44: B | H44: Archivo interno | I44: 46237 | J44: DOCUMENTACIÓN; COBERTURA; PRUEBAS | K44: VERIFICADO_SECUNDARIO | L44: Resume decisiones, limitaciones y controles; no sustituye fuentes científicas primarias.

Sheet PRUEBAS
A1: NUTRIMETRÍA · NMX-43 | PRUEBAS
A3: 70 controles registrados: 67 aprobados y 3 verificaciones manuales pendientes.
A5: =HYPERLINK("#'INICIO'!A1","INICIO") -> INICIO | B5: =HYPERLINK("#'DATOS'!A1","DATOS") -> DATOS | C5: =HYPERLINK("#'ENERGÍA'!A1","ENERGÍA") -> ENERGÍA | D5: =HYPERLINK("#'MACRONUTRIENTES'!A1","MACRONUTRIENTES") -> MACRONUTRIENTES | E5: =HYPERLINK("#'AGUA_FIBRA'!A1","AGUA/FIBRA") -> AGUA/FIBRA | F5: =HYPERLINK("#'FICHA_NUTRIENTE'!A1","FICHA/NUTRIENTE") -> FICHA/NUTRIENTE | G5: =HYPERLINK("#'RESULTADOS'!A1","RESULTADOS") -> RESULTADOS | H5: =HYPERLINK("#'DOCUMENTACIÓN'!A1","DOCUMENTACIÓN") -> DOCUMENTACIÓN | I5: =HYPERLINK("#'COBERTURA'!A1","COBERTURA") -> COBERTURA | J5: =HYPERLINK("#'AUDITORÍA_FINAL'!A1","AUDITORÍA") -> AUDITORÍA
A7: ID | B7: Módulo | C7: Descripción | D7: Entrada | E7: Resultado obtenido | F7: Resultado esperado | G7: Tolerancia | H7: Estado | I7: Observación | J7: Fecha
A8: T-01 | B8: ENERGÍA | C8: NASEM 2023, mujer adulta poco activa | D8: 25 a; 65 kg; 165 cm | E8: 2278.62 | F8: 2278.62 | G8: 0.1 | H8: APROBADA | I8: Comparación con ecuación independiente. | J8: 46236
A9: T-02 | B9: ENERGÍA | C9: NASEM 2023, hombre adulto inactivo | D9: 25 a; 70 kg; 175 cm | E9: 2606.82 | F9: 2606.82 | G9: 0.1 | H9: APROBADA | I9: Comparación con ecuación independiente. | J9: 46236
A10: T-03 | B10: ENERGÍA | C10: Schofield hombre 18–30 años | D10: 25 a; 70 kg | E10: 1746.19 | F10: 1746.19 | G10: 0.1 | H10: APROBADA | I10: Ecuación basada en peso. | J10: 46236
A11: T-04 | B11: ENERGÍA | C11: Schofield mujer 30–60 años | D11: 35 a; 60 kg | E11: 1333.16 | F11: 1333.16 | G11: 0.1 | H11: APROBADA | I11: Ecuación basada en peso. | J11: 46236
A12: T-05 | B12: ENERGÍA | C12: GET por Schofield × PAL manual | D12: BMR × 1,50 | E12: 1999.74 | F12: 1999.74 | G12: 0.1 | H12: APROBADA | I12: PAL manual. | J12: 46236
A13: T-06 | B13: ENERGÍA | C13: PAL factorial 24 horas | D13: Σ horas×PAR=36; 24 h | E13: 1.5 | F13: 1.5 | G13: 0.001 | H13: APROBADA | I13: Tabla de actividades visible. | J13: 46236
A14: T-07 | B14: ENERGÍA | C14: GET método factorial | D14: BMR × PAL factorial | E14: 1999.74 | F14: 1999.74 | G14: 0.1 | H14: APROBADA | I14: Usa el BMR de Schofield. | J14: 46236
A15: T-08 | B15: ENERGÍA | C15: FAO niño de 10 años, actividad moderada | D15: 10 a; 30 kg | E15: 1993.9 | F15: 1993.9 | G15: 0.1 | H15: APROBADA | I15: Incluye costo energético del crecimiento. | J15: 46236
A16: T-09 | B16: MACRONUTRIENTES | C16: Proteína desde porcentaje | D16: 2000 kcal; 15/30/55 % | E16: 75 | F16: 75 | G16: 0.1 | H16: APROBADA | I16: Factores 4-9-4. | J16: 46236
A17: T-10 | B17: MACRONUTRIENTES | C17: Lípidos desde porcentaje | D17: 2000 kcal; 15/30/55 % | E17: 66.666667 | F17: 66.666667 | G17: 0.1 | H17: APROBADA | I17: Factores 4-9-4. | J17: 46236
A18: T-11 | B18: MACRONUTRIENTES | C18: CHO desde porcentaje | D18: 2000 kcal; 15/30/55 % | E18: 275 | F18: 275 | G18: 0.1 | H18: APROBADA | I18: Factores 4-9-4. | J18: 46236
A19: T-12 | B19: MACRONUTRIENTES | C19: Cierre porcentual | D19: 2000 kcal; 15/30/55 % | E19: 100 | F19: 100 | G19: 0.1 | H19: APROBADA | I19: Factores 4-9-4. | J19: 46236
... A28: T-21 | B28: MACRONUTRIENTES | C28: RDA CHO en lactancia | D28: 25 a; lactancia | E28: 210 | F28: 210 | G28: 0.01 | H28: APROBADA | I28: Matriz DRI. | J28: 46236
A29: T-22 | B29: AGUA_FIBRA | C29: Fibra en lactante sin AI cargada | D29: 6 meses; femenino | E29: ND | F29: ND | G29: 0 | H29: APROBADA | I29: ND no se convierte en cero. | J29: 46236
A30: T-23 | B30: ÍNDICE_CARGA_GLICÉMICA | C30: Carga glicémica | D30: IG 73; CHO 30 g | E30: 21.9 | F30: 21.9 | G30: 0.01 | H30: APROBADA | I30: IG×CHO/100. | J30: 46236
A31: T-24 | B31: ÍNDICE_CARGA_GLICÉMICA | C31: Clasificación IG alto | D31: IG 73 | E31: ALTO | F31: ALTO | G31: 0 | H31: APROBADA | I31: Límites CONFIG. | J31: 46236
A32: T-25 | B32: ÍNDICE_CARGA_GLICÉMICA | C32: Clasificación carga alta | D32: CG 21,9 | E32: ALTA | F32: ALTA | G32: 0 | H32: APROBADA | I32: Límites CONFIG. | J32: 46236
A33: T-26 | B33: CONTROL GENERAL | C33: Escaneo de errores de fórmula | D33: Libro completo | E33: 0 | F33: 0 | G33: 0 | H33: APROBADA | I33: Búsqueda de #REF!, #DIV/0!, #VALUE!, #NAME?, #N/A y #NUM! sin coincidencias. | J33: 46236
A34: T-27 | B34: PROTECCIÓN | C34: Protección y desbloqueo selectivo de celdas | D34: Hojas de interfaz | E34: Pendiente | F34: Revisión en Microsoft Excel | G34: — | H34: APROBADA | I34: Programada para la Fase 7; no se declara aprobada. | J34: 46236
A35: T-28 | B35: FASE 5 | C35: Cobertura de nutrientes | D35: Catálogo y FICHAS_BASE | E35: 23 | F35: 23 | G35: 0 | H35: APROBADA | I35: Los 23 nutrientes tienen ficha. | J35: 46237
A36: T-29 | B36: FASE 5 | C36: Campos obligatorios por nutriente | D36: 18 campos por ficha | E36: 18 | F36: 18 | G36: 0 | H36: APROBADA | I36: Estructura uniforme. | J36: 46237
A37: T-30 | B37: FASE 5 | C37: Contenido no vacío | D37: 414 registros | E37: 414 | F37: 414 | G37: 0 | H37: APROBADA | I37: No se detectó contenido obligatorio vacío. | J37: 46237
A38: T-31 | B38: CASOS | C38: Un caso por nutriente | D38: CASOS_BASE | E38: 23 | F38: 23 | G38: 0 | H38: APROBADA | I38: Cobertura completa. | J38: 46237
A39: T-32 | B39: INTERACCIONES | C39: Trazabilidad de interacciones | D39: 35 registros | E39: 35 | F39: 35 | G39: 0 | H39: APROBADA | I39: Cada interacción tiene fuente y estado. | J39: 46237
A40: T-33 | B40: BIOMARCADORES | C40: Limitaciones documentadas | D40: 26 registros | E40: 26 | F40: 26 | G40: 0 | H40: APROBADA | I40: No se cargaron rangos universales. | J40: 46237
A41: T-34 | B41: FUENTES | C41: Fuentes institucionales Fase 5 | D41: Filas añadidas | E41: 24 | F41: 24 | G41: 0 | H41: APROBADA | I41: Todas las fuentes añadidas tienen URL institucional. | J41: 46237
A42: T-35 | B42: NOMENCLATURA | C42: Biotina B7/B8 | D42: Catálogo y observación | E42: Biotina | F42: Biotina | G42: 0 | H42: APROBADA | I42: La discrepancia B8 queda documentada. | J42: 46237
A43: T-36 | B43: RESUMEN | C43: Cobertura del resumen de estudio | D43: TablaResumenEstudio | E43: 23 | F43: 23 | G43: 0 | H43: APROBADA | I43: Una fila por nutriente. | J43: 46237
A44: T-37 | B44: FUENTES | C44: URLs válidas en fuentes añadidas | D44: 24 URLs | E44: 24 | F44: 24 | G44: 0 | H44: APROBADA | I44: Todas las fuentes añadidas tienen URL institucional. | J44: 46237
A45: T-38 | B45: SELECTORES | C45: Cambio dinámico a cobalamina | D45: 4 hojas vinculadas | E45: VIT-B12 | Metformina | Vitamina B12 sérica | Caso adulto mayor | F45: Contenido B12 en las cuatro vistas | G45: 0 | H45: APROBADA | I45: Se verificó ficha, interacción, biomarcador y caso. | J45: 46237
A46: T-39 | B46: CONTROL GENERAL | C46: Escaneo de errores tras Fase 5 | D46: Libro completo | E46: 0 | F46: 0 | G46: 0 | H46: APROBADA | I46: Se excluyeron menciones textuales de códigos de error en hojas de documentación. | J46: 46237
A47: T-40 | B47: BIBLIOGRAFÍA | C47: Mínimo dos referencias por ficha | D47: 23 fichas | E47: 23 | F47: 23 | G47: 0 | H47: APROBADA | I47: Cada ficha identifica una fuente principal y una referencia normativa/clínica complementaria. | J47: 46237
A48: T-41 | B48: FASE 6 | C48: Mapeo de nutrientes a INTA | D48: 23 nutrientes | E48: 21 | F48: 21 | G48: 0 | H48: APROBADA | I48: Cloruro y biotina no están disponibles. | J48: 46237
A49: T-42 | B49: DRI_BASE | C49: Filas micronutrientes normalizadas | D49: 23 × 18 grupos | E49: 414 | F49: 414 | G49: 0 | H49: APROBADA | I49: RDA/AI y UL/CDRR con fuente. | J49: 46237
A50: T-43 | B50: REQUERIMIENTOS | C50: Hierro mujer 25 años | D50: Femenino; 25 a | E50: 18 | F50: 18 | G50: 0 | H50: APROBADA | I50: RDA adulta. | J50: 46237
A51: T-44 | B51: REQUERIMIENTOS | C51: Biotina adulta | D51: Femenino; 25 a | E51: 30 | F51: 30 | G51: 0 | H51: APROBADA | I51: AI; sin RDA/UL. | J51: 46237
A52: T-45 | B52: REQUERIMIENTOS | C52: Cloruro adulto | D52: Femenino; 25 a | E52: 2300 | F52: 2300 | G52: 0 | H52: APROBADA | I52: AI en mg/d. | J52: 46237
A53: T-46 | B53: PORCIÓN | C53: Lenteja cocida: hierro por 150 g | D53: Valor/100 g × 1,5 | E53: 4.95 | F53: 4.95 | G53: 0.001 | H53: APROBADA | I53: Cálculo proporcional. | J53: 46237
A54: T-47 | B54: TOTAL | C54: Hierro de cinco alimentos demostrativos | D54: Suma conocida | E54: 15.22 | F54: 15.22 | G54: 0.001 | H54: APROBADA | I54: ND aparte. | J54: 46237
A55: T-48 | B55: REFERENCIA | C55: Objetivo de hierro enlazado | D55: Mujer 25 a | E55: 18 | F55: 18 | G55: 0 | H55: APROBADA | I55: Selector y DRI_BASE. | J55: 46237
A56: T-49 | B56: RESULTADOS | C56: Cobertura de micronutrientes | D56: Tabla resultados | E56: 23 | F56: 23 | G56: 0 | H56: APROBADA | I56: Una fila por nutriente. | J56: 46237
A57: T-50 | B57: ND INTA | C57: Cloruro y biotina sin composición | D57: Estados | E57: ND EN INTA | ND EN INTA | F57: ND EN INTA | ND EN INTA | G57: 0 | H57: APROBADA | I57: No se inventan aportes. | J57: 46237
A58: T-51 | B58: RANKING | C58: Primer alimento por hierro/100 g | D58: Ranking | E58: Bebida lactea años dorados | F58: Bebida lactea años dorados | G58: 0 | H58: APROBADA | I58: Orden descendente. | J58: 46237
A59: T-52 | B59: SODIO | C59: Límite adulto identificado | D59: Mujer 25 a | E59: 2300.0 CDRR | F59: 2300 CDRR | G59: 0 | H59: APROBADA | I59: CDRR no es UL. | J59: 46237
A60: T-53 | B60: CONTROL GENERAL | C60: Escaneo de errores tras Fase 6 | D60: Libro completo | E60: 0 | F60: 0 | G60: 0 | H60: APROBADA | I60: Se excluyen menciones textuales de códigos de error. | J60: 46237
A61: T-54 | B61: LÍMITES | C61: Prioridad de alerta sobre UL | D61: Cobre demo | E61: SOBRE UL · PARCIAL | F61: SOBRE UL · PARCIAL | G61: 0 | H61: APROBADA | I61: La alerta de límite prevalece sobre el estado parcial. | J61: 46237
A62: T-55 | B62: FUENTES | C62: Identificadores de fuente únicos | D62: 37 registros | E62: 37 | F62: 37 | G62: 0 | H62: APROBADA | I62: No existen Source_ID duplicados. | J62: 46237
A63: T-56 | B63: FUENTES | C63: Referencias internas resueltas | D63: 1011 referencias | E63: 0 | F63: 0 | G63: 0 | H63: APROBADA | I63: No existen Source_ID faltantes. | J63: 46237
A64: T-57 | B64: FUENTES | C64: Campos obligatorios completos | D64: 37 fuentes | E64: 0 | F64: 0 | G64: 0 | H64: APROBADA | I64: ID, tema, autor/institución, título, tipo, nivel, módulo y estado. | J64: 46237
A65: T-58 | B65: CONTROL GENERAL | C65: Escaneo de errores de fórmula | D65: Libro completo | E65: 0 | F65: 0 | G65: 0 | H65: APROBADA | I65: Se excluyeron menciones textuales en documentación. | J65: 46237
A66: T-59 | B66: DOCUMENTACIÓN | C66: Hojas visibles documentadas | D66: Guía de hojas | E66: 23 | F66: 23 | G66: 0 | H66: APROBADA | I66: Cobertura de interfaz y gobernanza. | J66: 46237
A67: T-60 | B67: DOCUMENTACIÓN | C67: Hojas técnicas documentadas | D67: Guía de hojas | E67: 11 | F67: 11 | G67: 0 | H67: APROBADA | I67: Señaladas como no editables. | J67: 46237
A68: T-61 | B68: COBERTURA | C68: Requisitos registrados | D68: Matriz COBERTURA | E68: 48 | F68: 48 | G68: 0 | H68: APROBADA | I68: Inventario del portafolio y gobernanza. | J68: 46237
A69: T-62 | B69: COBERTURA | C69: Estados de cobertura completos | D69: 48 requisitos | E69: 48 | F69: 48 | G69: 0 | H69: APROBADA | I69: Sin estados vacíos. | J69: 46237
A70: T-63 | B70: VALIDACIONES | C70: Validaciones en DATOS | D70: Hoja DATOS | E70: 9 | F70: 9 | G70: 0 | H70: APROBADA | I70: Listas y restricciones del perfil. | J70: 46237
A71: T-64 | B71: VALIDACIONES | C71: Validaciones de selectores y alimentos | D71: 8 hojas de interfaz | E71: 11 | F71: 11 | G71: 0 | H71: APROBADA | I71: Nutrientes, IG, actividades y alimentos. | J71: 46237
A72: T-65 | B72: TABLAS | C72: Nombres de tabla únicos | D72: 15 tablas | E72: 15 | F72: 15 | G72: 0 | H72: APROBADA | I72: Evita conflictos estructurales. | J72: 46237
A73: T-66 | B73: NAVEGACIÓN | C73: Enlaces a documentación y cobertura | D73: 23 hojas | E73: 23 | F73: 23 | G73: 0 | H73: APROBADA | I73: Botones H5 e I5. | J73: 46237
A74: T-67 | B74: PAQUETE | C74: Ausencia de macros VBA | D74: Archivo XLSX | E74: Sin macros | F74: Sin macros | G74: 0 | H74: APROBADA | I74: No existe vbaProject.bin. | J74: 46237
A75: T-68 | B75: PAQUETE | C75: Ausencia de vínculos externos de libro | D75: Archivo XLSX | E75: Sin externalLinks | F75: Sin externalLinks | G75: 0 | H75: APROBADA | I75: No se detectan relaciones xl/externalLinks. | J75: 46237
A76: T-69 | B76: PROTECCIÓN | C76: Protección y desbloqueo selectivo | D76: Microsoft Excel | E76: Pendiente | F76: Revisión manual | G76: — | H76: NO EJECUTADA | I76: El editor actual no expone protección de hoja; seguir DOCUMENTACIÓN. | J76: 46237
A77: T-70 | B77: IMPRESIÓN | C77: Áreas de impresión y escalado | D77: Microsoft Excel | E77: Pendiente | F77: Revisión manual | G77: — | H77: NO EJECUTADA | I77: Objetivos por hoja documentados en DOCUMENTACIÓN. | J77: 46237
A78: T-71 | B78: INVENTARIO | C78: Cantidad de hojas finales | D78: 35 hojas | E78: 35 | F78: 35 | G78: 0 | H78: APROBADA | I78: Incluye AUDITORÍA_FINAL. | J78: 46237
A79: T-72 | B79: ARQUITECTURA | C79: Hojas obligatorias presentes | D79: Conjunto requerido | E79: 35 | F79: 35 | G79: 0 | H79: APROBADA | I79: No faltan módulos obligatorios. | J79: 46237
A80: T-73 | B80: FUENTES | C80: Identificadores de fuente únicos | D80: FUENTES | E80: 37 | F80: 37 | G80: 0 | H80: APROBADA | I80: Sin duplicados. | J80: 46237
A81: T-74 | B81: TRAZABILIDAD | C81: Source_ID internos resueltos | D81: Bases y CONFIG | E81: 0 | F81: 0 | G81: 0 | H81: APROBADA | I81: No quedan alias sin registro. | J81: 46237
A82: T-75 | B82: FUENTES | C82: Campos esenciales completos | D82: Registro de fuentes | E82: 0 | F82: 0 | G82: 0 | H82: APROBADA | I82: ID, institución, título, nivel, módulo y estado. | J82: 46237
A83: T-76 | B83: TABLAS | C83: Nombres de tabla únicos | D83: Libro completo | E83: 15 | F83: 15 | G83: 0 | H83: APROBADA | I83: Evita conflictos estructurales. | J83: 46237
A84: T-77 | B84: VALIDACIONES | C84: Validaciones de datos activas | D84: Libro completo | E84: 20 | F84: 20 | G84: 0 | H84: APROBADA | I84: Incluye DATOS y selectores. | J84: 46237
A85: T-78 | B85: COBERTURA | C85: Requisitos documentados | D85: COBERTURA | E85: 49 | F85: 49 | G85: 0 | H85: APROBADA | I85: Todos tienen estado. | J85: 46237
A86: T-79 | B86: REGISTRO PREVIO | C86: Consistencia de pruebas F1–F7 | D86: 70 totales | E86: 67 aprobadas / 3 pendientes | F86: 67 aprobadas / 3 pendientes | G86: 0 | H86: APROBADA | I86: No se modificaron resultados previos. | J86: 46237
A87: T-80 | B87: CONTROL GENERAL | C87: Escaneo de errores de fórmula | D87: Libro completo | E87: 0 | F87: 0 | G87: 0 | H87: APROBADA | I87: Se excluyen menciones textuales. | J87: 46237
A88: T-81 | B88: PAQUETE XLSX | C88: Estructura ZIP/Open XML | D88: Archivo temporal | E88: 1 | F88: 1 | G88: 0 | H88: APROBADA | I88: Contiene workbook.xml y Content_Types. | J88: 46237
A89: T-82 | B89: SEGURIDAD | C89: Ausencia de VBA y vínculos externos | D89: Paquete XLSX | E89: VBA=False; externos=False | F89: VBA=False; externos=False | G89: 0 | H89: APROBADA | I89: El libro permanece .xlsx sin macros. | J89: 46237
A90: T-83 | B90: REAPERTURA | C90: Reimportación del archivo exportado | D90: Artifact Tool | E90: 35 | F90: 35 | G90: 0 | H90: APROBADA | I90: La hoja AUDITORÍA_FINAL permanece disponible. | J90: 46237
A91: T-84 | B91: INSPECCIÓN FINAL | C91: Rangos clave legibles y calculados | D91: INICIO; RESULTADOS; AUDITORÍA_FINAL | E91: 3 | F91: 3 | G91: 0 | H91: APROBADA | I91: Inspección dirigida de valores y fórmulas. | J91: 46237

Sheet CONFIG
A1: NUTRIMETRÍA · NMX-43 | CONFIG
A3: Constantes, límites y políticas del motor.
A5: =HYPERLINK("#'INICIO'!A1","INICIO") -> INICIO | B5: =HYPERLINK("#'DATOS'!A1","DATOS") -> DATOS | C5: =HYPERLINK("#'ENERGÍA'!A1","ENERGÍA") -> ENERGÍA | D5: =HYPERLINK("#'MACRONUTRIENTES'!A1","MACRONUTRIENTES") -> MACRONUTRIENTES | E5: =HYPERLINK("#'AGUA_FIBRA'!A1","AGUA/FIBRA") -> AGUA/FIBRA | F5: =HYPERLINK("#'FICHA_NUTRIENTE'!A1","FICHA/NUTRIENTE") -> FICHA/NUTRIENTE | G5: =HYPERLINK("#'RESULTADOS'!A1","RESULTADOS") -> RESULTADOS | H5: =HYPERLINK("#'DOCUMENTACIÓN'!A1","DOCUMENTACIÓN") -> DOCUMENTACIÓN | I5: =HYPERLINK("#'COBERTURA'!A1","COBERTURA") -> COBERTURA | J5: =HYPERLINK("#'AUDITORÍA_FINAL'!A1","AUDITORÍA") -> AUDITORÍA
A7: Clave | B7: Valor | C7: Unidad | D7: Categoría | E7: Fuente_ID | F7: Estado | G7: Observación
A8: FACTOR_KCAL_PROTEINA | B8: 4 | C8: kcal/g | D8: Conversión | E8: SRC-ATWATER | F8: VERIFICADO | G8: Factor general de Atwater.
A9: FACTOR_KCAL_CHO | B9: 4 | C9: kcal/g | D9: Conversión | E9: SRC-ATWATER | F9: VERIFICADO | G9: Carbohidratos disponibles.
A10: FACTOR_KCAL_LIPIDOS | B10: 9 | C10: kcal/g | D10: Conversión | E10: SRC-ATWATER | F10: VERIFICADO | G10: Factor general de Atwater.
A11: TOLERANCIA_CIERRE_ENERGETICO | B11: 2 | C11: % | D11: Control | E11: INTERNA | F11: VERIFICADO | G11: Tolerancia técnica; no criterio clínico.
A12: TEXTO_ND | B12: ND | D12: Política | E12: INTERNA | F12: VERIFICADO | G12: Dato no disponible/no establecido.
A13: IG_BAJO_MAX | B13: 55 | C13: índice | D13: Clasificación | E13: SRC-GI-2021 | F13: VERIFICADO | G13: Escala glucosa=100.
A14: IG_MEDIO_MAX | B14: 69 | C14: índice | D14: Clasificación | E14: SRC-GI-2021 | F14: VERIFICADO | G14: Desde 56 hasta 69.
A15: GL_BAJO_MAX | B15: 10 | C15: carga | D15: Clasificación | E15: SRC-GI-CUTOFFS | F15: VERIFICADO | G15: Por porción.
A16: GL_MEDIO_MAX | B16: 19 | C16: carga | D16: Clasificación | E16: SRC-GI-CUTOFFS | F16: VERIFICADO | G16: Desde 11 hasta 19.
A17: ADECUACION_BAJO | B17: 90 | C17: % | D17: Semáforo | E17: INTERNA | F17: VERIFICADO | G17: Umbral didáctico configurable.
A18: ADECUACION_ALTO | B18: 110 | C18: % | D18: Semáforo | E18: INTERNA | F18: VERIFICADO | G18: No equivale a UL ni toxicidad.
A19: PAL_SEDENTARIO_CENTRO | B19: 1.55 | C19: múltiplo BMR | D19: Energía | E19: SRC-FAO-ENER-2004 | F19: VERIFICADO | G19: Centro aproximado dentro de 1,40–1,69.
A20: PAL_MODERADO_CENTRO | B20: 1.85 | C20: múltiplo BMR | D20: Energía | E20: SRC-FAO-ENER-2004 | F20: VERIFICADO | G20: Centro aproximado dentro de 1,70–1,99.
A21: PAL_VIGOROSO_CENTRO | B21: 2.2 | C21: múltiplo BMR | D21: Energía | E21: SRC-FAO-ENER-2004 | F21: VERIFICADO | G21: Centro aproximado dentro de 2,00–2,40.
A22: AJUSTE_FAO_LIGERA | B22: 0.85 | C22: factor | D22: Energía pediátrica | E22: SRC-FAO-ENER-2004 | F22: VERIFICADO | G22: 15% bajo actividad moderada desde 6 años.
A23: AJUSTE_FAO_MODERADA | B23: 1 | C23: factor | D23: Energía pediátrica | E23: SRC-FAO-ENER-2004 | F23: VERIFICADO | G23: Referencia promedio/moderada.
A24: AJUSTE_FAO_INTENSA | B24: 1.15 | C24: factor | D24: Energía pediátrica | E24: SRC-FAO-ENER-2004 | F24: VERIFICADO | G24: 15% sobre actividad moderada desde 6 años.
... A30: LACTANCIA_7_12 | B30: 380 | C30: kcal/d | D30: NASEM 2023 | E30: SRC-NASEM-ENER-2023 | F30: VERIFICADO | G30: Lactancia parcial.
A31: SISTEMA_DRI_ACTIVO | B31: DRI EE.UU./Canadá | D31: Gobernanza | E31: SRC-DRI-SUMMARY | F31: VERIFICADO | G31: No mezclar con EFSA.
A32: FUENTE_ENERGIA_PRINCIPAL | B32: FAO/WHO/UNU 2004 | D32: Gobernanza | E32: SRC-FAO-ENER-2004 | F32: VERIFICADO | G32: NASEM 2023 queda como comparador moderno.
A33: VERSION_MINIMA_EXCEL | B33: Microsoft 365 / Excel 2021 | D33: Compatibilidad | E33: INTERNA | F33: VERIFICADO | G33: Sin macros.
A34: USO_AUTORIZADO | B34: Académico privado | D34: Licencia | E34: INTERNA | F34: VERIFICADO | G34: Comercialización bloqueada hasta revisar licencia INTA.
A35: FASE_ACTUAL | B35: 8 | C35: fase | D35: Gobernanza | E35: INTERNA | F35: VERIFICADO | G35: Fase 8: auditoría automatizada completada; tres controles manuales permanecen pendientes.
A36: FICHAS_CARGADAS | B36: 23 | C36: nutrientes | D36: Fase 5 | E36: INTERNA | F36: VERIFICADO | G36: 18 campos uniformes por nutriente.
A37: INTERACCIONES_CARGADAS | B37: 35 | C37: registros | D37: Fase 5 | E37: INTERNA | F37: VERIFICADO | G37: Con fuente y estado.
A38: BIOMARCADORES_CARGADOS | B38: 26 | C38: registros | D38: Fase 5 | E38: INTERNA | F38: VERIFICADO | G38: Sin rangos universales.
A39: CASOS_CARGADOS | B39: 23 | C39: casos | D39: Fase 5 | E39: INTERNA | F39: VERIFICADO | G39: Un caso por nutriente.
A40: ALIMENTOS_SELECCIONABLES | B40: 618 | C40: alimentos | D40: Fase 6 | E40: SRC-NMX21 | F40: VERIFICADO | G40: Base para validación de datos.
A41: NUTRIENTES_CUANTIFICABLES | B41: 21 | C41: nutrientes | D41: Fase 6 | E41: SRC-NMX21 | F41: VERIFICADO | G41: Cloruro y biotina no están en la base.
A42: FILAS_DRI_NORMALIZADAS | B42: 468 | C42: filas | D42: Fase 6 | E42: SRC-NMX43-F6-NORM | F42: VERIFICADO_SECUNDARIO | G42: Incluye macro, agua, fibra y micronutrientes.
A43: ALIMENTOS_POR_CASO | B43: 10 | C43: filas | D43: Fase 6 | E43: INTERNA | F43: VERIFICADO | G43: Entradas editables.
A44: TOP_FUENTES | B44: 10 | C44: alimentos | D44: Fase 6 | E44: INTERNA | F44: VERIFICADO | G44: Ranking por 100 g.
A45: POLITICA_TOTAL_PARCIAL | B45: Sumar conocido + contar ND | D45: Fase 6 | E45: INTERNA | F45: VERIFICADO | G45: ND nunca se transforma en cero.
A46: HOJAS_TOTALES | B46: 34 | C46: hojas | D46: Fase 7 | E46: SRC-NMX43-F7-QA | F46: VERIFICADO | G46: 23 visibles/documentales y 11 técnicas.
A47: FUENTES_REGISTRADAS | B47: 37 | C47: fuentes | D47: Fase 7 | E47: FUENTES | F47: VERIFICADO | G47: Incluye fuentes científicas, internas y entrada del usuario.
A48: REQUISITOS_COBERTURA | B48: 48 | C48: requisitos | D48: Fase 7 | E48: SRC-NMX43-F7-QA | F48: VERIFICADO | G48: Matriz COBERTURA.
A49: PRUEBAS_APROBADAS | B49: 67 | C49: pruebas | D49: Fase 7 | E49: PRUEBAS | F49: VERIFICADO | G49: De 70 controles registrados.
A50: PRUEBAS_PENDIENTES | B50: 3 | C50: pruebas | D50: Fase 7 | E50: PRUEBAS | F50: VERIFICADO | G50: T-27, T-69 y T-70.
A51: PROTECCION_HOJAS | B51: Pendiente manual | D51: Fase 7 | E51: INTERNA | F51: PENDIENTE | G51: Configurar en Microsoft Excel.
A52: AREAS_IMPRESION | B52: Pendiente manual | D52: Fase 7 | E52: INTERNA | F52: PENDIENTE | G52: Objetivos documentados en DOCUMENTACIÓN.
A53: FASE_ACTUAL | B53: 8 | C53: fase | D53: Fase 8 | E53: SRC-NMX43-F7-QA | F53: VERIFICADO | G53: Auditoría automatizada completada.
A54: HOJAS_FINALES | B54: 35 | C54: hojas | D54: Fase 8 | E54: SRC-NMX43-F7-QA | F54: VERIFICADO | G54: Incluye AUDITORÍA_FINAL.
A55: PRUEBAS_TOTALES | B55: 84 | C55: pruebas | D55: Fase 8 | E55: PRUEBAS | F55: VERIFICADO | G55: Registro acumulado.
A56: PRUEBAS_APROBADAS_FINAL | B56: 81 | C56: pruebas | D56: Fase 8 | E56: PRUEBAS | F56: VERIFICADO | G56: Controles aprobados.
A57: PRUEBAS_PENDIENTES_FINAL | B57: 3 | C57: pruebas | D57: Fase 8 | E57: PRUEBAS | F57: VERIFICADO | G57: Protección, impresión y comprobación manual.
A58: ESTADO_ENTREGA | B58: Final académica | D58: Fase 8 | E58: INTERNA | F58: VERIFICADO | G58: No validada clínicamente ni autorizada para comercialización.

Sheet DICCIONARIO
A1: NUTRIMETRÍA · NMX-43 | DICCIONARIO
A3: Estructura de DICCIONARIO preparada para el desarrollo por fases.
A5: =HYPERLINK("#'INICIO'!A1","INICIO") -> INICIO | B5: =HYPERLINK("#'DATOS'!A1","DATOS") -> DATOS | C5: =HYPERLINK("#'ENERGÍA'!A1","ENERGÍA") -> ENERGÍA | D5: =HYPERLINK("#'MACRONUTRIENTES'!A1","MACRONUTRIENTES") -> MACRONUTRIENTES | E5: =HYPERLINK("#'AGUA_FIBRA'!A1","AGUA/FIBRA") -> AGUA/FIBRA | F5: =HYPERLINK("#'FICHA_NUTRIENTE'!A1","FICHA/NUTRIENTE") -> FICHA/NUTRIENTE | G5: =HYPERLINK("#'RESULTADOS'!A1","RESULTADOS") -> RESULTADOS | H5: =HYPERLINK("#'DOCUMENTACIÓN'!A1","DOCUMENTACIÓN") -> DOCUMENTACIÓN | I5: =HYPERLINK("#'COBERTURA'!A1","COBERTURA") -> COBERTURA | J5: =HYPERLINK("#'AUDITORÍA_FINAL'!A1","AUDITORÍA") -> AUDITORÍA
A7: Término | B7: Definición operativa | C7: Nota
A8: EAR | B8: Requerimiento promedio estimado. | C8: No es una meta individual.
A9: RDA | B9: Ingesta dietaria recomendada. | C9: Se deriva del EAR cuando existe evidencia suficiente.
A10: AI | B10: Ingesta adecuada. | C10: Se usa cuando no puede establecerse EAR/RDA.
A11: UL | B11: Nivel máximo tolerable de ingesta. | C11: No es una meta de consumo.
A12: ND | B12: Dato no disponible/no informado. | C12: No equivale a cero.
A13: CHO disponibles | B13: Carbohidratos digeribles usados para cálculo energético/carga glicémica. | C13: Distinguir de carbohidratos totales.
A14: Biotina | B14: Vitamina B7. | C14: La pauta la menciona como B8; discrepancia registrada.
A15: Cloruro | B15: Anión cloruro, no cloro elemental. | C15: Definir unidad y fuente.
A16: CDRR | B16: Ingesta de reducción del riesgo de enfermedad crónica. | C16: Para sodio; no es un UL.
A17: Aporte conocido | B17: Suma de datos numéricos disponibles para los alimentos seleccionados. | C17: No incluye componentes s/i.
A18: Resultado parcial | B18: Existe al menos un alimento con dato ND para el nutriente. | C18: No interpretar como ingesta total completa.
... A23: Hoja técnica | B23: Hoja auxiliar para motores o bases. | C23: No debe editarse durante el uso normal.

Sheet OBSERVACIONES
A1: NUTRIMETRÍA · NMX-43 | OBSERVACIONES
A3: Discrepancias académicas, legales y técnicas.
A5: =HYPERLINK("#'INICIO'!A1","INICIO") -> INICIO | B5: =HYPERLINK("#'DATOS'!A1","DATOS") -> DATOS | C5: =HYPERLINK("#'ENERGÍA'!A1","ENERGÍA") -> ENERGÍA | D5: =HYPERLINK("#'MACRONUTRIENTES'!A1","MACRONUTRIENTES") -> MACRONUTRIENTES | E5: =HYPERLINK("#'AGUA_FIBRA'!A1","AGUA/FIBRA") -> AGUA/FIBRA | F5: =HYPERLINK("#'FICHA_NUTRIENTE'!A1","FICHA/NUTRIENTE") -> FICHA/NUTRIENTE | G5: =HYPERLINK("#'RESULTADOS'!A1","RESULTADOS") -> RESULTADOS | H5: =HYPERLINK("#'DOCUMENTACIÓN'!A1","DOCUMENTACIÓN") -> DOCUMENTACIÓN | I5: =HYPERLINK("#'COBERTURA'!A1","COBERTURA") -> COBERTURA | J5: =HYPERLINK("#'AUDITORÍA_FINAL'!A1","AUDITORÍA") -> AUDITORÍA
A7: ID | B7: Tema | C7: Observación | D7: Impacto | E7: Estado
A8: OBS-001 | B8: Biotina B7/B8 | C8: La pauta docente escribe B8; el catálogo usa B7 y conserva la discrepancia. | D8: Académico | E8: ABIERTO
A9: OBS-002 | B9: Cloro/cloruro | C9: El motor deberá trabajar con cloruro y documentar la unidad. | D9: Académico | E9: ABIERTO
A10: OBS-003 | B10: Licencia INTA | C10: No se autoriza comercialización hasta verificar redistribución y atribución. | D10: Legal | E10: BLOQUEANTE
A11: OBS-004 | B11: DRI | C11: No mezclar EAR/RDA/AI/UL ni sistemas DRI y EFSA. | D11: Metodológico | E11: CONTROLADO
A12: OBS-005 | B12: Valores ausentes | C12: s/i y ND no se transforman en cero. | D12: Técnico | E12: CONTROLADO
A13: OBS-006 | B13: Fase 4 | C13: Motores energéticos y de macronutrientes implementados con fuentes rastreables. | D13: Alcance | E13: COMPLETADO
A14: OBS-007 | B14: Índice glicémico | C14: Los valores precargados son promedios de categoría; para aplicación individual debe registrarse un valor específico compatible. | D14: Metodológico | E14: CONTROLADO
A15: OBS-008 | B15: Adecuación | C15: Los umbrales 90–110 % son técnicos y configurables; no son diagnóstico ni criterio universal de suficiencia/toxicidad. | D15: Académico | E15: CONTROLADO
A16: OBS-009 | B16: Protección | C16: La protección final y las celdas desbloqueadas se verificarán en Microsoft Excel durante Fase 7. | D16: Técnico | E16: COMPLETO
A17: OBS-010 | B17: NASEM/FAO | C17: Los sistemas energéticos se muestran por separado y no se promedian automáticamente. | D17: Metodológico | E17: CONTROLADO
A18: OBS-011 | B18: Fichas Fase 5 | C18: Las 23 fichas son resúmenes académicos concisos basados principalmente en fuentes institucionales; el estado es VERIFICADO_SECUNDARIO. | D18: Metodológico | E18: CONTROLADO
... A39: OBS-032 | B39: Cierre | C39: La fase 8 no convierte controles manuales no realizados en aprobados. | D39: Honestidad | E39: CONTROLADO

Sheet CHANGELOG
A1: NUTRIMETRÍA · NMX-43 | CHANGELOG
A3: Historial de versiones.
A5: =HYPERLINK("#'INICIO'!A1","INICIO") -> INICIO | B5: =HYPERLINK("#'DATOS'!A1","DATOS") -> DATOS | C5: =HYPERLINK("#'ENERGÍA'!A1","ENERGÍA") -> ENERGÍA | D5: =HYPERLINK("#'MACRONUTRIENTES'!A1","MACRONUTRIENTES") -> MACRONUTRIENTES | E5: =HYPERLINK("#'AGUA_FIBRA'!A1","AGUA/FIBRA") -> AGUA/FIBRA | F5: =HYPERLINK("#'FICHA_NUTRIENTE'!A1","FICHA/NUTRIENTE") -> FICHA/NUTRIENTE | G5: =HYPERLINK("#'RESULTADOS'!A1","RESULTADOS") -> RESULTADOS | H5: =HYPERLINK("#'DOCUMENTACIÓN'!A1","DOCUMENTACIÓN") -> DOCUMENTACIÓN | I5: =HYPERLINK("#'COBERTURA'!A1","COBERTURA") -> COBERTURA | J5: =HYPERLINK("#'AUDITORÍA_FINAL'!A1","AUDITORÍA") -> AUDITORÍA
A7: Versión | B7: Fecha | C7: Fase | D7: Cambio | E7: Estado | F7: Autoría
A8: 1.0-F3 | B8: 46236 | C8: Fase 3 | D8: Contenedor, hojas, CONFIG, LISTAS, catálogo, bases, fuentes y copia de ALIMENTOS. | E8: COMPLETADA | F8: Nutrimetría
A9: 1.0-F4 | B9: 46236 | C9: Fase 4 | D9: Motores de energía, método factorial, macronutrientes, agua, fibra, IG/CG, resultados integrados, fuentes y 26 pruebas aprobadas. | E9: COMPLETADA | F9: Nutrimetría
A10: 1.0-F5 | B10: 46237 | C10: Fase 5 | D10: 23 fichas automatizadas, 414 registros de contenido, 35 interacciones, 26 biomarcadores, 23 casos, resumen de estudio, 24 fuentes y 13 pruebas estructurales/dinámicas. | E10: COMPLETADA | F10: Nutrimetría
A11: 1.0-F6 | B11: 46237 | C11: Fase 6 | D11: DRI de 23 micronutrientes, selección de 10 alimentos, cálculo por gramaje, matriz de 23 nutrientes, ranking top 10, integración con resultados/resumen/casos y 14 pruebas. | E11: COMPLETADA | F11: Nutrimetría
A12: 1.0-F7 | B12: 46237 | C12: Fase 7 | D12: Documentación completa, matriz de cobertura, auditoría de fuentes, navegación ampliada, estilo de entradas, 16 controles y checklist manual de protección/impresión. | E12: COMPLETADA CON 2 CONTROLES MANUALES | F12: Nutrimetría
A13: 1.0-F8 | B13: 46237 | C13: Fase 8 | D13: Auditoría final, hoja AUDITORÍA_FINAL, 49 requisitos, 84 pruebas, verificación de paquete, reapertura e inspección dirigida. | E13: COMPLETADA CON 3 CONTROLES MANUALES | F13: Nutrimetría
A14: 1.1-UDD | B14: 46240 | C14: Fase 9 | D14: Biblioteca UDD integrada: 9 hojas, cobertura de 238 elementos, derechos controlados y motores sin cambios. | E14: COMPLETADA CON 3 CONTROLES MANUALES HEREDADOS | F14: Nutrimetría
A15: 1.1-UDD | B15: 46240 | C15: Fase 9 | D15: Biblioteca UDD integrada: 9 hojas, cobertura de 238 elementos, derechos controlados y motores sin cambios. | E15: COMPLETADA CON 3 CONTROLES MANUALES HEREDADOS | F15: Nutrimetría
A16: 1.1-UDD | B16: 46240 | C16: Fase 9 | D16: Biblioteca UDD integrada: 9 hojas, cobertura de 238 elementos, derechos controlados y motores sin cambios. | E16: COMPLETADA CON 3 CONTROLES MANUALES HEREDADOS | F16: Nutrimetría
A17: 1.1-UDD | B17: 46240 | C17: Fase 9 | D17: Biblioteca UDD integrada: 9 hojas, cobertura de 238 elementos, derechos controlados y motores sin cambios. | E17: COMPLETADA CON 3 CONTROLES MANUALES HEREDADOS | F17: Nutrimetría
A18: 1.1-UDD | B18: 46240 | C18: Fase 9 | D18: Biblioteca UDD integrada: 9 hojas, cobertura de 238 elementos, derechos controlados y motores sin cambios. | E18: COMPLETADA CON 3 CONTROLES MANUALES HEREDADOS | F18: Nutrimetría
A19: 1.1-UDD | B19: 46240 | C19: Fase 9 | D19: Biblioteca UDD integrada: 9 hojas, cobertura de 238 elementos, derechos controlados y motores sin cambios. | E19: COMPLETADA CON 3 CONTROLES MANUALES HEREDADOS | F19: Nutrimetría
... A21: 1.1-UDD | B21: 46240 | C21: Fase 9 | D21: Biblioteca UDD integrada: 9 hojas, cobertura de 238 elementos, derechos controlados y motores sin cambios. | E21: COMPLETADA CON 3 CONTROLES MANUALES HEREDADOS | F21: Nutrimetría

Sheet ALIMENTOS_INTA
A1: NMX43_ID | B1: ESTADO_DATO | C1: FUENTE_ID | D1: NUTRIMETRÍA · NMX-21 | E1: Columna1 | F1: Columna2 | G1: Columna3 | H1: Columna4 | I1: Columna5 | J1: Columna6 | K1: Columna7 | L1: Columna8 | M1: Columna9 | N1: Columna10 | O1: Columna11 | P1: Columna12 | Q1: Columna13 | R1: Columna14 | S1: Columna15 | T1: Columna16 | U1: Columna17 | V1: Columna18 | W1: Columna19 | X1: Columna20 | Y1: Columna21 | Z1: Columna22 | AA1: Columna23 | AB1: Columna24 | AC1: Columna25 | AD1: Columna26 | AE1: Columna27 | AF1: Columna28 | AG1: Columna29 | AH1: Columna30 | AI1: Columna31 | AJ1: Columna32 | AK1: Columna33 | AL1: Columna34 | AM1: Columna35 | AN1: Columna36 | AO1: Columna37
A2: INTA-0001 | B2: SEGÚN_CELDA | C2: SRC-NMX21 | D2: Composición por 100 g de porción comestible. Celdas 's/i' = sin información en la fuente (NO es cero).
A3: INTA-0002 | B3: SEGÚN_CELDA | C3: SRC-NMX21 | D3: ▶ INICIO | E3: ▶ DATOS | F3: ● ALIMENTOS | G3: ▶ CALCULOS | H3: ▶ RESULTADOS | I3: ▶ REQUERIMIENTOS | J3: ▶ FUENTES | K3: ▶ PRUEBAS | L3: ▶ CONFIG | M3: ▶ CHANGELOG
A4: INTA-0003 | B4: SEGÚN_CELDA | C4: SRC-NMX21
A5: INTA-0004 | B5: SEGÚN_CELDA | C5: SRC-NMX21 | D5: REGISTROS (618 alimentos · 34 nutrientes)
A6: INTA-0005 | B6: SEGÚN_CELDA | C6: SRC-NMX21 | D6: No modifique esta hoja: es la base de datos. Los valores 's/i' deben permanecer como texto.
A7: INTA-0006 | B7: SEGÚN_CELDA | C7: SRC-NMX21 | D7: ID | E7: Alimento | F7: Grupo | G7: Estado | H7: Energía (kcal) | I7: Humedad (g) | J7: Cenizas (g) | K7: Proteínas (g) | L7: H de C disp. (g) | M7: Azúcares tot. (g) | N7: Fibra (g) | O7: Lípidos (g) | P7: AG saturados (g) | Q7: AG monoinsat. (g) | R7: AG poliinsat. (g) | S7: AG trans (g) | T7: Colesterol (mg) | U7: Vitamina A (µg) | V7: Vitamina C (mg) | W7: Vitamina D (µg) | X7: Vitamina E (mg) | Y7: Vitamina K (µg) | Z7: Vit. B1 (mg) | AA7: Vit. B2 (mg) | AB7: Niacina (mg) | AC7: Vit. B6 (mg) | AD7: Ác. pantoténico (mg) | AE7: Vit. B12 (µg) | AF7: Folatos (µg) | AG7: Sodio (mg) | AH7: Potasio (mg) | AI7: Calcio (mg) | AJ7: Fósforo (mg) | AK7: Magnesio (mg) | AL7: Hierro (mg) | AM7: Zinc (mg) | AN7: Cobre (mg) | AO7: Selenio (µg)
A8: INTA-0007 | B8: SEGÚN_CELDA | C8: SRC-NMX21 | D8: INTA-0001 | E8: Leche materna | F8: Leche y derivados | G8: sin documentar | H8: 70 | I8: 87.5 | J8: 0.2 | K8: 1 | L8: 6.9 | M8: 6.9 | N8: 0 | O8: 4.4 | P8: 2.01 | Q8: 1.66 | R8: 0.5 | S8: s/i | T8: 14 | U8: 61 | V8: 5 | W8: 0.1 | X8: 0.1 | Y8: 0.3 | Z8: 0 | AA8: 0 | AB8: 0.2 | AC8: 0 | AD8: 0.2 | AE8: 0.1 | AF8: 5 | AG8: 17 | AH8: 51 | AI8: 32 | AJ8: 14 | AK8: 3 | AL8: 0 | AM8: 0.2 | AN8: 0.1 | AO8: 1.8
A9: INTA-0008 | B9: SEGÚN_CELDA | C9: SRC-NMX21 | D9: INTA-0002 | E9: Leche de Burra | F9: Leche y derivados | G9: sin documentar | H9: 41 | I9: 90.4 | J9: 0.4 | K9: 1.6 | L9: 6.7 | M9: s/i | N9: 0 | O9: 0.9 | P9: s/i | Q9: s/i | R9: s/i | S9: s/i | T9: s/i | U9: s/i | V9: 1.7 | W9: s/i | X9: s/i | Y9: s/i | Z9: 0 | AA9: 0.1 | AB9: 0.1 | AC9: s/i | AD9: s/i | AE9: s/i | AF9: s/i | AG9: s/i | AH9: s/i | AI9: 138 | AJ9: 60 | AK9: s/i | AL9: s/i | AM9: s/i | AN9: s/i | AO9: s/i
A10: INTA-0009 | B10: SEGÚN_CELDA | C10: SRC-NMX21 | D10: INTA-0003 | E10: Leche de cabra con Vit. D | F10: Leche y derivados | G10: sin documentar | H10: 69 | I10: 87 | J10: 0.8 | K10: 3.6 | L10: 4.5 | M10: 4.5 | N10: 0 | O10: 4.1 | P10: 2.67 | Q10: 1.11 | R10: 0.15 | S10: s/i | T10: 11 | U10: 57 | V10: 1.3 | W10: s/i | X10: 0.1 | Y10: 0.3 | Z10: 0.1 | AA10: 0.1 | AB10: 0.3 | AC10: 0.1 | AD10: 0.3 | AE10: 0.1 | AF10: 1 | AG10: 50 | AH10: 204 | AI10: 134 | AJ10: 111 | AK10: 14 | AL10: 0.1 | AM10: 0.3 | AN10: 0.1 | AO10: 1.4
A11: INTA-0010 | B11: SEGÚN_CELDA | C11: SRC-NMX21 | D11: INTA-0004 | E11: Leche fluida entera | F11: Leche y derivados | G11: sin documentar | H11: 64 | I11: 87.7 | J11: 0.7 | K11: 3.3 | L11: 4.7 | M11: s/i | N11: 0 | O11: 3.7 | P11: 2.28 | Q11: 1.06 | R11: 0.14 | S11: s/i | T11: 14 | U11: 33 | V11: 1.5 | W11: s/i | X11: s/i | Y11: s/i | Z11: 0 | AA11: 0.2 | AB11: 0.1 | AC11: 0 | AD11: 0.3 | AE11: 0.4 | AF11: 5 | AG11: 49 | AH11: 151 | AI11: 119 | AJ11: 93 | AK11: 13 | AL11: 0.1 | AM11: 0.4 | AN11: 0 | AO11: 2
A12: INTA-0011 | B12: SEGÚN_CELDA | C12: SRC-NMX21 | D12: INTA-0005 | E12: Leche fluida entera 2 | F12: Leche y derivados | G12: sin documentar | H12: 58 | I12: 88.1 | J12: 0.6 | K12: 3.2 | L12: 5.6 | M12: s/i | N12: 0 | O12: 2.5 | P12: 2.09 | Q12: 0.96 | R12: 0.12 | S12: s/i | T12: 13.5 | U12: 31.1 | V12: 1 | W12: s/i | X12: s/i | Y12: s/i | Z12: 0.1 | AA12: 0.1 | AB12: 0.1 | AC12: 0 | AD12: 0.3 | AE12: 0.4 | AF12: 4.9 | AG12: 59.7 | AH12: 141.8 | AI12: 123 | AJ12: 95 | AK12: 13.5 | AL12: 0.1 | AM12: 0.4 | AN12: 0 | AO12: s/i
A13: INTA-0012 | B13: SEGÚN_CELDA | C13: SRC-NMX21 | D13: INTA-0006 | E13: Leche entera con sabor | F13: Leche y derivados | G13: sin documentar | H13: 80 | I13: 82.9 | J13: 0.8 | K13: 2.4 | L13: 10.5 | M13: s/i | N13: 0.5 | O13: 2.9 | P13: 1.84 | Q13: 0.87 | R13: 0.15 | S13: s/i | T13: 6.4 | U13: 29 | V13: 0.9 | W13: s/i | X13: 0.1 | Y13: s/i | Z13: 0 | AA13: 0.2 | AB13: 0.1 | AC13: 0 | AD13: 0.3 | AE13: 0.3 | AF13: 4.7 | AG13: 59.6 | AH13: 167 | AI13: 112 | AJ13: 100 | AK13: 13 | AL13: 0.2 | AM13: 0.4 | AN13: 0.1 | AO13: 1.2
A14: INTA-0013 | B14: SEGÚN_CELDA | C14: SRC-NMX21 | D14: INTA-0007 | E14: Leche semidescremada | F14: Leche y derivados | G14: sin documentar | H14: 42 | I14: 90.2 | J14: 0.8 | K14: 2.6 | L14: 5.1 | M14: 3.2 | N14: 0 | O14: 1.3 | P14: s/i | Q14: s/i | R14: s/i | S14: s/i | T14: s/i | U14: s/i | V14: s/i | W14: s/i | X14: s/i | Y14: s/i | Z14: s/i | AA14: s/i | AB14: s/i | AC14: s/i | AD14: s/i | AE14: s/i | AF14: s/i | AG14: s/i | AH14: s/i | AI14: s/i | AJ14: s/i | AK14: s/i | AL14: s/i | AM14: s/i | AN14: s/i | AO14: s/i
A15: INTA-0014 | B15: SEGÚN_CELDA | C15: SRC-NMX21 | D15: INTA-0008 | E15: Leche semidescremada con sabor | F15: Leche y derivados | G15: sin documentar | H15: 76 | I15: 82.2 | J15: 0.8 | K15: 3 | L15: 11.4 | M15: 9.6 | N15: 0.7 | O15: 1.9 | P15: 1.18 | Q15: 0.46 | R15: 0.09 | S15: s/i | T15: 8 | U15: 64 | V15: 0 | W15: 1.2 | X15: 0 | Y15: 0.2 | Z15: 0.1 | AA15: 0.2 | AB15: 0.2 | AC15: 0 | AD15: 0.5 | AE15: 0.3 | AF15: 2 | AG15: 66 | AH15: 169 | AI15: 109 | AJ15: 102 | AK15: 14 | AL15: 0.2 | AM15: 0.4 | AN15: 0.1 | AO15: 3.4
A16: INTA-0015 | B16: SEGÚN_CELDA | C16: SRC-NMX21 | D16: INTA-0009 | E16: Leche semidescremada con sabor chocolate | F16: Leche y derivados | G16: sin documentar | H16: 52 | I16: s/i | J16: s/i | K16: 3.2 | L16: 5.6 | M16: 5 | N16: s/i | O16: 1.8 | P16: 1.15 | Q16: 0.52 | R16: 0.05 | S16: 0.1 | T16: 6 | U16: 40 | V16: s/i | W16: 0.3 | X16: 1 | Y16: s/i | Z16: s/i | AA16: s/i | AB16: s/i | AC16: s/i | AD16: s/i | AE16: s/i | AF16: s/i | AG16: 70 | AH16: s/i | AI16: 93 | AJ16: 84 | AK16: s/i | AL16: s/i | AM16: s/i | AN16: s/i | AO16: s/i
A17: INTA-0016 | B17: SEGÚN_CELDA | C17: SRC-NMX21 | D17: INTA-0010 | E17: Leche semidescremada con sabor frutilla | F17: Leche y derivados | G17: sin documentar | H17: 54 | I17: s/i | J17: s/i | K17: 3.1 | L17: 6 | M17: 5.5 | N17: s/i | O17: 1.9 | P17: 1.22 | Q17: 0.55 | R17: 0.05 | S17: 0.1 | T17: 6 | U17: 40 | V17: s/i | W17: 0.3 | X17: 1 | Y17: s/i | Z17: s/i | AA17: s/i | AB17: s/i | AC17: s/i | AD17: s/i | AE17: s/i | AF17: s/i | AG17: 60 | AH17: s/i | AI17: 104 | AJ17: 84 | AK17: s/i | AL17: s/i | AM17: s/i | AN17: s/i | AO17: s/i
A18: INTA-0017 | B18: SEGÚN_CELDA | C18: SRC-NMX21 | D18: INTA-0011 | E18: Leche semidescremada sin lactosa | F18: Leche y derivados | G18: sin documentar | H18: 44 | I18: s/i | J18: s/i | K18: 3.1 | L18: 4.6 | M18: 4.6 | N18: s/i | O18: 1.3 | P18: 1 | Q18: 0.35 | R18: 0.05 | S18: 0.1 | T18: 6 | U18: 50 | V18: s/i | W18: 0.4 | X18: s/i | Y18: s/i | Z18: s/i | AA18: s/i | AB18: s/i | AC18: s/i | AD18: s/i | AE18: s/i | AF18: s/i | AG18: 60 | AH18: s/i | AI18: 101 | AJ18: s/i | AK18: s/i | AL18: s/i | AM18: s/i | AN18: s/i | AO18: s/i
