Workbook
Name a_Horas: ACTIVIDADES!$B$20
Name a_IndiceMET: ACTIVIDADES!$B$22
Name a_PAL: ACTIVIDADES!$B$27
Name a_SumaMETh: ACTIVIDADES!$B$21
Name a_TEE: ACTIVIDADES!$B$25
Name AJUSTE_MAX: CONFIG!$B$22
Name AMPL_MAX: CONFIG!$B$34
Name c_Energia: CALCULOS!$B$48
Name c_ETA: CALCULOS!$B$40
Name c_FA: CALCULOS!$B$13
Name c_GAF: CALCULOS!$B$38
Name c_Gate: CALCULOS!$B$33
Name c_GEB: CALCULOS!$B$37
Name c_GET: CALCULOS!$B$41
Name c_IMC: CALCULOS!$B$8
Name c_MLG: CALCULOS!$B$10
Name c_TallaM: CALCULOS!$B$7
Name COD_ACT: CONFIG!$A$131:$A$144
Name e_Ampl: ECUACIONES!$B$23
Name e_GEBsel: ECUACIONES!$B$28
Name EDAD_MAX: CONFIG!$B$12
Name EDAD_MIN: CONFIG!$B$11
Name EST_MAX: CONFIG!$B$16
Name EST_MIN: CONFIG!$B$15
Name EST_RA: CONFIG!$B$29
Name EST_RB: CONFIG!$B$28
Name ETA_DEF: CONFIG!$B$25
Name ETA_MAX: CONFIG!$B$21
Name FA_MAX: CONFIG!$B$20
Name FA_MIN: CONFIG!$B$19
Name FA_VAL: CONFIG!$B$51:$B$57
Name GRA_MIN: CONFIG!$B$33
Name GRASA_MAX: CONFIG!$B$18
Name GRASA_MIN: CONFIG!$B$17
Name HORAS_DIA: CONFIG!$B$23
Name IMC_RA: CONFIG!$B$31
Name IMC_RB: CONFIG!$B$30
Name in_Ajuste: DATOS!$B$16
Name in_Ecu: DATOS!$B$22
Name in_Edad: DATOS!$B$10
Name in_Est: DATOS!$B$12
Name in_FAcat: DATOS!$B$18
Name in_FAman: DATOS!$B$19
Name in_Fecha: DATOS!$B$7
Name in_Grasa: DATOS!$B$13
Name in_ID: DATOS!$B$6
Name in_Metodo: DATOS!$B$17
Name in_MLG: DATOS!$B$14
Name in_ModoETA: DATOS!$B$20
Name in_ModoGra: DATOS!$B$26
Name in_ModoPro: DATOS!$B$24
Name in_Motivo: DATOS!$B$23
Name in_Obj: DATOS!$B$15
Name in_Obs: DATOS!$B$28
Name in_Pac: DATOS!$B$8
Name in_Peso: DATOS!$B$11
Name in_pETA: DATOS!$B$21
Name in_Sexo: DATOS!$B$9
Name in_ValGra: DATOS!$B$27
Name in_ValPro: DATOS!$B$25

Sheet INICIO
A1: NUTRIMETRÍA · NMX-01
A2: Calculadora Energética · DEFINITIVO 2026 · NMX-PAL-2026-08-v1 · NMX-ACT-2024-v1
A4: Navegación — use las pestañas inferiores del libro
A5: =HYPERLINK("#DATOS!A1","▶ DATOS") -> ▶ DATOS | B5: =HYPERLINK("#ECUACIONES!A1","▶ ECUACIONES") -> ▶ ECUACIONES | D5: =HYPERLINK("#CALCULOS!A1","▶ CALCULOS") -> ▶ CALCULOS | F5: =HYPERLINK("#RESULTADOS!A1","▶ RESULTADOS") -> ▶ RESULTADOS | H5: =HYPERLINK("#ACTIVIDADES!A1","▶ ACTIVIDADES") -> ▶ ACTIVIDADES | J5: =HYPERLINK("#FUENTES!A1","▶ FUENTES") -> ▶ FUENTES | L5: =HYPERLINK("#PRUEBAS!A1","▶ PRUEBAS") -> ▶ PRUEBAS | N5: =HYPERLINK("#CONFIG!A1","▶ CONFIG") -> ▶ CONFIG | P5: =HYPERLINK("#CHANGELOG!A1","▶ CHANGELOG") -> ▶ CHANGELOG
A6: Ingresar datos | B6: Revisar motores | D6: Auditar operaciones | F6: Ver resumen | H6: Revisar PAL | J6: Consultar evidencia | L6: Ver QA | N6: Ajustes y límites | P6: Registro de versiones y cambios
A7: Código del producto | B7: NMX-01
A8: Versión | B8: DEFINITIVO 2026 · NMX-PAL-2026-08-v1 · NMX-ACT-2024-v1
A9: Fecha | B9: 46242
A10: Base | B10: v1.0 (2026-07-12), auditada contra el 'Dossier de verificación bibliográfica y metodológica'
A11: Formato | B11: .xlsx sin macros · Microsoft 365 (Windows) y Excel 2021
A12: Responsable | B12: Equipo Nutrimetría (completar por el titular)
A13: AVISO DE ALCANCE — LÉALO ANTES DE USAR EL LIBRO
A14: EXACTITUD MATEMÁTICA ≠ VALIDACIÓN CLÍNICA. Este libro cotejó sus coeficientes contra las fuentes documentadas en
A15: la hoja FUENTES. Eso NO significa que las ecuaciones estén validadas para su paciente concreto ni para población chilena.
A16: ESTE ARCHIVO NO ESTÁ VALIDADO CLÍNICAMENTE. La calorimetría indirecta sigue siendo la referencia de medición.
A17: APLICA A: personas ADULTAS (≥18 años) en condición estable. Módulo Compendium de actividad: desde 19 años.
A18: NO APLICA A: embarazo · lactancia · menores de edad · pacientes críticos o clínicamente inestables.
A19: PROPÓSITO Y ALCANCE
A20: Propósito | B20: Estimar gasto energético basal/de reposo y requerimiento energético diario mediante siete ecuaciones predictivas y un nivel de actividad física (PAL).
A21: Población | B21: Adultos ≥18 años en condición estable. Actividad física: 18 años = sin módulo Compendium; 19–59 = Adult Compendium 2024 (MET); ≥60 ambulante = Older Adult Compendium 2024 (MET60+); adultos usuarios de silla de ruedas = Wheelchair Compendium 2024 (METWC), con precaución etaria en ≥60.
A22: Uso | B22: Apoyo educativo y profesional. No sustituye calorimetría indirecta, evaluación clínica ni juicio del nutricionista.
A23: Compatibilidad | B23: Microsoft 365 y Excel 2021 para Windows. No utiliza VBA, complementos ni conexiones permanentes.
A24: Privacidad | B24: Los datos permanecen en el archivo local. El libro no transmite información.
A25: CÓMO SE MODELA EL GASTO (sin doble conteo) — confirmado por el dossier
A26: GEB = gasto energético basal, según la ecuación seleccionada.
A27: GAF = GEB × (Factor de actividad − 1). Se resta 1 para NO volver a contar el basal ya incluido en el PAL.
A28: ETA = 0 por defecto. FAO define PAL = gasto total 24 h / metabolismo basal 24 h: el efecto térmico YA está dentro.
A29: Si usted activa un ETA explícito sobre un PAL, el libro se lo permite pero ADVIERTE del doble conteo.
A30: GET = GEB + GAF + ETA ( = GEB × PAL cuando ETA = 0 ).
A31: Energía objetivo = GET × (1 + % de ajuste). Carbohidratos = por diferencia.
A32: Flujo de uso
A33: 1 | B33: Abra DATOS e ingrese sexo, edad, peso, estatura, porcentaje de grasa opcional, PAL y ecuación principal.
A34: 2 | B34: Revise RESULTADOS para la estimación principal y la comparación entre ecuaciones.
A35: 3 | B35: Use ECUACIONES y FUENTES para auditar fórmulas, poblaciones y limitaciones.
A36: 4 | B36: Consulte PRUEBAS para verificar casos sintéticos y controles manuales.
A37: 5 | B37: Interprete diferencias como incertidumbre predictiva; no como diagnóstico.
A38: MET → PAL: la conversión que la v1.1 hace explícita
A39: Un MET es un múltiplo del metabolismo en reposo ESTÁNDAR (≈1 kcal/kg/h), no del GEB de esta persona.
A40: Por eso Σ(MET×h)/24 es un ÍNDICE MET-h/día, y NO el PAL. La v1.0 los confundía. La v1.1 hace:
A41: 1) Σ(MET × horas) → índice MET-h/día (se muestra, pero no se usa como PAL)
A42: 2) TEE = Σ(MET × horas) × Peso × 1 kcal/kg/h → energía total estimada del día
A43: 3) PAL = TEE / GEB → este SÍ es el factor de actividad que usa el motor
A44: Consecuencia: dos personas del mismo peso con el mismo día de actividades, pero distinto GEB, reciben PAL distinto.
A45: Sigue siendo una APROXIMACIÓN: el MET estándar no se ajusta al metabolismo individual. Ver hoja ACTIVIDADES.

Sheet DATOS
A1: DATOS · Variables ingresadas por el usuario
A2: =HYPERLINK("#INICIO!A1","◀ INICIO") -> ◀ INICIO | C2: =HYPERLINK("#RESULTADOS!A1","▶ RESULTADOS") -> ▶ RESULTADOS | E2: =HYPERLINK("#ACTIVIDADES!A1","▶ ACTIVIDADES") -> ▶ ACTIVIDADES
A3: LEYENDA · Celdas ARENA con texto AZUL = editables. Celdas grises = calculadas y protegidas. (opcional) = puede quedar vacía.
A4: ► Viene cargado un CASO DE EJEMPLO realista. Reemplace los valores por los de su paciente.
A5: Campo | B5: Valor | C5: Unidad | D5: Validación | E5: Ayuda | G5: MÓDULO ACTIVIDAD FÍSICA · NMX-ACT-2024-v1
A6: Identificador de la evaluación | B6: NMX-2026-0001 | C6: — | D6: Texto libre | E6: Código interno de la evaluación. | G6: Condición clínica | H6: Estable | I6: Debe estar estable; NMX-01 no aplica a pacientes críticos/inestables.
A7: Fecha | B7: 46215 | C7: fecha | D7: Fecha | E7: dd/mm/aaaa. | G7: Movilidad | H7: Usuario de silla de ruedas | I7: Seleccione silla de ruedas solo si corresponde al modo habitual de movilidad.
A8: Nombre o código del paciente | B8: PAC-0042 | C8: — | D8: Texto libre | E8: Prefiera un CÓDIGO si va a compartir el archivo. | G8: Estado del módulo | H8: =IF($H$10="BLOQUEADO_INESTABLE","BLOQUEADO · condición no estable",IF($H$10="FUERA_ALCANCE","FUERA DE ALCANCE",IF($H$10="COMPENDIUM_NO_DISPONIBLE_18","NMX-01 aplica; Compendium no disponible",IF(AND($H$10="WHEELCHAIR2024_METWC",in_Edad>=CONFIG!$B$154),"PRECAUCIÓN · METWC con evidencia etaria limitada","ACTIVO")))) -> ACTIVO | I8: Se determina por edad, condición clínica y movilidad.
A9: Sexo biológico | B9: Hombre | C9: — | D9: Lista: Hombre / Mujer | E9: LIMITACIÓN DEL MODELO: las 7 ecuaciones se derivaron por sexo biológico. Si no aplica, documéntelo en Observaciones. | G9: Fuente activa | H9: =IF($H$10="ADULT2024_MET","2024 Adult Compendium",IF($H$10="OLDER2024_MET60","2024 Older Adult Compendium",IF($H$10="WHEELCHAIR2024_METWC","2024 Wheelchair Compendium",IF($H$10="COMPENDIUM_NO_DISPONIBLE_18","No disponible para edad 18",IF($H$10="BLOQUEADO_INESTABLE","Bloqueado","Fuera de alcance"))))) -> 2024 Wheelchair Compendium | I9: Cambia automáticamente con la edad/movilidad.
A10: Edad | B10: 20 | C10: años | D10: ≥18 y ≤120 (IMPOSIBLE fuera de rango) | E10: Solo adultos. | G10: Motor actividad | H10: =IF($H$6<>"Estable","BLOQUEADO_INESTABLE",IF(NOT(ISNUMBER(in_Edad)),"FUERA_ALCANCE",IF(in_Edad<EDAD_MIN,"FUERA_ALCANCE",IF(in_Edad<CONFIG!$B$152,"COMPENDIUM_NO_DISPONIBLE_18",IF($H$7="Usuario de silla de ruedas","WHEELCHAIR2024_METWC",IF(in_Edad>=CONFIG!$B$154,"OLDER2024_MET60","ADULT2024_MET")))))) -> WHEELCHAIR2024_METWC | I10: Identificador auditable del motor activo.
A11: Peso | B11: 78 | C11: kg | D11: >0, entre PESO_MIN y PESO_MAX | E11: Balanza calibrada, ropa ligera, sin calzado.
A12: Estatura | B12: 180 | C12: cm | D12: >0, entre EST_MIN y EST_MAX | E12: Estadiómetro, plano de Frankfort.
A13: % de grasa corporal (opcional) | B13: 0.05 | C13: % | D13: Entre GRASA_MIN y GRASA_MAX | E13: Deje VACÍA si no la tiene.
A14: MLG medida (opcional) | B14: 62 | C14: kg | D14: Numérica y menor que el peso | E14: Si la ingresa, TIENE PRIORIDAD sobre el % de grasa. Sin % de grasa ni MLG, Cunningham 1980 y 1991 NO se calculan.
A15: Objetivo | B15: Aumento de peso | C15: — | D15: Lista (CONFIG C5) | E15: Descriptivo. El % real lo fija el campo siguiente.
A16: % de ajuste energético | B16: 0.05 | C16: % | D16: |%| ≤ AJUSTE_MAX | E16: NEGATIVO = déficit. POSITIVO = superávit. 0 = mantenimiento. Se aplica sobre el GET.
A17: Método de actividad | B17: Factor de actividad global | C17: — | D17: Lista (CONFIG C3) | E17: NMX-ACT-2024-v1: 'Cálculo por actividades' selecciona MET / MET60+ / METWC según edad y movilidad. El PAL se deriva solo cuando la conversión energética es aplicable.
A18: Factor de actividad global (catálogo) | B18: Moderado · PAL 1,80 | C18: — | D18: Lista (CONFIG C4) | E18: Seleccione según el patrón habitual global (trabajo/estudio, transporte, actividad física y descanso); no por una sola sesión ni solo por pasos.
A19: Factor de actividad manual (opcional) | C19: — | D19: Entre FA_MIN y FA_MAX | E19: Si lo escribe, SOBREESCRIBE al catálogo. Deje VACÍO para usar el catálogo.
A20: Tratamiento del efecto térmico (ETA) | B20: Incluido en el factor de actividad (recomendado) | C20: — | D20: Lista (CONFIG C6) | E20: Por defecto el ETA vale 0 porque el PAL ya lo contiene. Activarlo aparte lo duplicaría.
A21: % de efecto térmico | B21: 0.1 | C21: % | D21: Entre 0 y ETA_MAX | E21: Solo se usa si el modo de ETA es explícito.
A22: Ecuación seleccionada | B22: Cunningham (1991) · alias secundario: Katch–McArdle | C22: — | D22: Lista (CONFIG C11) · 7 opciones | E22: Las 7 ecuaciones se calculan igualmente. Esta define el GEB que alimenta el resto del libro.
A23: Motivo de selección | B23: Adulto sano sin composición corporal medida; Mifflin–St Jeor es la de mejor desempeño documentado en este perfil. | C23: — | D23: Texto OBLIGATORIO | E23: El libro advierte si lo deja vacío: una selección sin justificación no es auditable.
A24: Modo de distribución · PROTEÍNA | B24: g/kg de peso | C24: — | D24: Lista (CONFIG C7) | E24: '% de la energía' o 'g/kg de peso'.
A25: Valor de PROTEÍNA | B25: 1.5 | C25: % o g/kg | D25: ≥0 | E25: Se interpreta según el modo elegido arriba.
A26: Modo de distribución · GRASA | B26: % de la energía | C26: — | D26: Lista (CONFIG C7) | E26: '% de la energía' o 'g/kg de peso'.
A27: Valor de GRASA | B27: 0.2 | C27: % o g/kg | D27: ≥0 | E27: Se interpreta según el modo elegido arriba.
A28: Observaciones | C28: — | D28: Texto libre | E28: Contexto clínico, criterios adoptados, fuente de un MET personalizado, etc.
A30: ► Los CARBOHIDRATOS no se ingresan: se calculan POR DIFERENCIA, una vez fijadas la proteína y la grasa.
A31: ► % de ajuste sugerido para el objetivo elegido: | C31: =IF(COUNTIF(LISTA_OBJ,in_Obj)=1,INDEX(OBJ_PCT,MATCH(in_Obj,LISTA_OBJ,0)),"—") -> 0.1 | D31: (referencial; usted decide el % real en la fila 16)

Sheet ECUACIONES
A1: ECUACIONES · Gasto energético basal (7 ecuaciones)
A2: =HYPERLINK("#INICIO!A1","◀ INICIO") -> ◀ INICIO
A3: Cada ecuación se calcula si y solo si están presentes sus variables indispensables; si falta alguna, devuelve ND y explica por qué. La columna 'Fórmula publicada' es documental: el cálculo usa siempre los coeficientes de CONFIG (C8, C9 y C10), visibles en las columnas L a P. Esta hoja NO depende de la compuerta de CALCULOS: se resuelve antes, porque el PAL estimado de ACTIVIDADES necesita el GEB. GUARDAS ESPECÍFICAS POR ECUACIÓN (v1.1.1): la estatura solo se exige a Mifflin y a Harris–Benedict revisada, las únicas que la usan. La edad se exige a todas porque el alcance del producto es solo adultos. Ver CONFIG C11.
A5: COMPARACIÓN DE LAS 7 ECUACIONES
A6: ID | B6: Ecuación | C6: Fórmula publicada (hombre | mujer) | D6: Variables indispensables | E6: ¿Datos disponibles? | F6: GEB (kcal/día) | G6: Aplicabilidad por edad | H6: Dif. vs promedio (kcal) | I6: Dif. vs promedio (%) | J6: Dif. vs seleccionada (kcal) | K6: Dif. vs seleccionada (%) | L6: a | M6: b_peso | N6: b_estatura | O6: b_edad | P6: b_MLG
A7: =CONFIG!$A$120 -> E1 | B7: =CONFIG!$B$120 -> Mifflin–St Jeor (1990) | C7: 10·P + 6,25·T − 5·E + 5 | 10·P + 6,25·T − 5·E − 161 | D7: =CONFIG!$G$120 -> sexo, peso, estatura, edad | E7: =IF(OR(COUNTIF(SEXOS,in_Sexo)<>1,ISBLANK(in_Edad),NOT(ISNUMBER(in_Edad)),ISBLANK(in_Peso),NOT(ISNUMBER(in_Peso))),"NO: faltan sexo, edad o peso válidos",IF(OR(in_Edad<EDAD_MIN,in_Edad>EDAD_MAX),"NO: edad fuera del alcance adulto",IF(OR(in_Peso<=0,in_Peso<PESO_MIN,in_Peso>PESO_MAX),"NO: peso no válido",IF(AND(CONFIG!$F$120="SÍ",OR(ISBLANK(in_Est),NOT(ISNUMBER(in_Est)),in_Est<=0,in_Est<EST_MIN,in_Est>EST_MAX)),"NO: esta ecuación necesita la estatura",IF(AND(CONFIG!$E$120="SÍ",NOT(ISNUMBER(CALCULOS!$B$10))),"NO: falta la masa libre de grasa","SÍ"))))) -> SÍ | F7: =IF($E7<>"SÍ","ND",$L7+$M7*in_Peso+$N7*IF(CONFIG!$F$120="SÍ",in_Est,0)+$O7*in_Edad+$P7*IF(ISNUMBER(CALCULOS!$B$10),CALCULOS!$B$10,0)) -> 1810 | G7: =IF(OR(ISBLANK(in_Edad),NOT(ISNUMBER(in_Edad))),"",IF(OR(in_Edad<CONFIG!$C$120,in_Edad>CONFIG!$D$120),"⚠ Fuera del rango de derivación","Dentro del rango de derivación")) -> Dentro del rango de derivación | H7: =IF(OR(NOT(ISNUMBER($F7)),NOT(ISNUMBER($B$18))),"ND",$F7-$B$18) -> 9.8494286 | I7: =IF(OR(NOT(ISNUMBER($F7)),NOT(ISNUMBER($B$18)),$B$18=0),"ND",($F7-$B$18)/$B$18) -> 0.0054714471 | J7: =IF(OR(NOT(ISNUMBER($F7)),NOT(ISNUMBER($B$28))),"ND",$F7-$B$28) -> 100.8 | K7: =IF(OR(NOT(ISNUMBER($F7)),NOT(ISNUMBER($B$28)),$B$28=0),"ND",($F7-$B$28)/$B$28) -> 0.058974959 | L7: =IF($E7<>"SÍ",0,SUMIFS(CONFIG!$D$79:$D$88,CONFIG!$A$79:$A$88,$A7,CONFIG!$C$79:$C$88,in_Sexo)) -> 5 | M7: =IF($E7<>"SÍ",0,SUMIFS(CONFIG!$E$79:$E$88,CONFIG!$A$79:$A$88,$A7,CONFIG!$C$79:$C$88,in_Sexo)) -> 10 | N7: =IF($E7<>"SÍ",0,SUMIFS(CONFIG!$F$79:$F$88,CONFIG!$A$79:$A$88,$A7,CONFIG!$C$79:$C$88,in_Sexo)) -> 6.25 | O7: =IF($E7<>"SÍ",0,SUMIFS(CONFIG!$G$79:$G$88,CONFIG!$A$79:$A$88,$A7,CONFIG!$C$79:$C$88,in_Sexo)) -> -5 | P7: =IF($E7<>"SÍ",0,SUMIFS(CONFIG!$H$79:$H$88,CONFIG!$A$79:$A$88,$A7,CONFIG!$C$79:$C$88,in_Sexo)) -> 0
A8: =CONFIG!$A$121 -> E2 | B8: =CONFIG!$B$121 -> Harris–Benedict revisada · Roza & Shizgal (1984) | C8: 88,362 + 13,397·P + 4,799·T − 5,677·E | 447,593 + 9,247·P + 3,098·T − 4,330·E | D8: =CONFIG!$G$121 -> sexo, peso, estatura, edad | E8: =IF(OR(COUNTIF(SEXOS,in_Sexo)<>1,ISBLANK(in_Edad),NOT(ISNUMBER(in_Edad)),ISBLANK(in_Peso),NOT(ISNUMBER(in_Peso))),"NO: faltan sexo, edad o peso válidos",IF(OR(in_Edad<EDAD_MIN,in_Edad>EDAD_MAX),"NO: edad fuera del alcance adulto",IF(OR(in_Peso<=0,in_Peso<PESO_MIN,in_Peso>PESO_MAX),"NO: peso no válido",IF(AND(CONFIG!$F$121="SÍ",OR(ISBLANK(in_Est),NOT(ISNUMBER(in_Est)),in_Est<=0,in_Est<EST_MIN,in_Est>EST_MAX)),"NO: esta ecuación necesita la estatura",IF(AND(CONFIG!$E$121="SÍ",NOT(ISNUMBER(CALCULOS!$B$10))),"NO: falta la masa libre de grasa","SÍ"))))) -> SÍ | F8: =IF($E8<>"SÍ","ND",$L8+$M8*in_Peso+$N8*IF(CONFIG!$F$121="SÍ",in_Est,0)+$O8*in_Edad+$P8*IF(ISNUMBER(CALCULOS!$B$10),CALCULOS!$B$10,0)) -> 1883.608 | G8: =IF(OR(ISBLANK(in_Edad),NOT(ISNUMBER(in_Edad))),"",IF(OR(in_Edad<CONFIG!$C$121,in_Edad>CONFIG!$D$121),"⚠ Fuera del rango de derivación","Dentro del rango de derivación")) -> Dentro del rango de derivación | H8: =IF(OR(NOT(ISNUMBER($F8)),NOT(ISNUMBER($B$18))),"ND",$F8-$B$18) -> 83.457429 | I8: =IF(OR(NOT(ISNUMBER($F8)),NOT(ISNUMBER($B$18)),$B$18=0),"ND",($F8-$B$18)/$B$18) -> 0.04636136 | J8: =IF(OR(NOT(ISNUMBER($F8)),NOT(ISNUMBER($B$28))),"ND",$F8-$B$28) -> 174.408 | K8: =IF(OR(NOT(ISNUMBER($F8)),NOT(ISNUMBER($B$28)),$B$28=0),"ND",($F8-$B$28)/$B$28) -> 0.10204072 | L8: =IF($E8<>"SÍ",0,SUMIFS(CONFIG!$D$79:$D$88,CONFIG!$A$79:$A$88,$A8,CONFIG!$C$79:$C$88,in_Sexo)) -> 88.362 | M8: =IF($E8<>"SÍ",0,SUMIFS(CONFIG!$E$79:$E$88,CONFIG!$A$79:$A$88,$A8,CONFIG!$C$79:$C$88,in_Sexo)) -> 13.397 | N8: =IF($E8<>"SÍ",0,SUMIFS(CONFIG!$F$79:$F$88,CONFIG!$A$79:$A$88,$A8,CONFIG!$C$79:$C$88,in_Sexo)) -> 4.799 | O8: =IF($E8<>"SÍ",0,SUMIFS(CONFIG!$G$79:$G$88,CONFIG!$A$79:$A$88,$A8,CONFIG!$C$79:$C$88,in_Sexo)) -> -5.677 | P8: =IF($E8<>"SÍ",0,SUMIFS(CONFIG!$H$79:$H$88,CONFIG!$A$79:$A$88,$A8,CONFIG!$C$79:$C$88,in_Sexo)) -> 0
A9: =CONFIG!$A$122 -> E3 | B9: =CONFIG!$B$122 -> Owen (1986/1987) | C9: 879 + 10,2·P | 795 + 7,18·P | D9: =CONFIG!$G$122 -> sexo, peso | E9: =IF(OR(COUNTIF(SEXOS,in_Sexo)<>1,ISBLANK(in_Edad),NOT(ISNUMBER(in_Edad)),ISBLANK(in_Peso),NOT(ISNUMBER(in_Peso))),"NO: faltan sexo, edad o peso válidos",IF(OR(in_Edad<EDAD_MIN,in_Edad>EDAD_MAX),"NO: edad fuera del alcance adulto",IF(OR(in_Peso<=0,in_Peso<PESO_MIN,in_Peso>PESO_MAX),"NO: peso no válido",IF(AND(CONFIG!$F$122="SÍ",OR(ISBLANK(in_Est),NOT(ISNUMBER(in_Est)),in_Est<=0,in_Est<EST_MIN,in_Est>EST_MAX)),"NO: esta ecuación necesita la estatura",IF(AND(CONFIG!$E$122="SÍ",NOT(ISNUMBER(CALCULOS!$B$10))),"NO: falta la masa libre de grasa","SÍ"))))) -> SÍ | F9: =IF($E9<>"SÍ","ND",$L9+$M9*in_Peso+$N9*IF(CONFIG!$F$122="SÍ",in_Est,0)+$O9*in_Edad+$P9*IF(ISNUMBER(CALCULOS!$B$10),CALCULOS!$B$10,0)) -> 1674.6 | G9: =IF(OR(ISBLANK(in_Edad),NOT(ISNUMBER(in_Edad))),"",IF(OR(in_Edad<CONFIG!$C$122,in_Edad>CONFIG!$D$122),"⚠ Fuera del rango de derivación","Dentro del rango de derivación")) -> Dentro del rango de derivación | H9: =IF(OR(NOT(ISNUMBER($F9)),NOT(ISNUMBER($B$18))),"ND",$F9-$B$18) -> -125.55057 | I9: =IF(OR(NOT(ISNUMBER($F9)),NOT(ISNUMBER($B$18)),$B$18=0),"ND",($F9-$B$18)/$B$18) -> -0.069744483 | J9: =IF(OR(NOT(ISNUMBER($F9)),NOT(ISNUMBER($B$28))),"ND",$F9-$B$28) -> -34.6 | K9: =IF(OR(NOT(ISNUMBER($F9)),NOT(ISNUMBER($B$28)),$B$28=0),"ND",($F9-$B$28)/$B$28) -> -0.020243389 | L9: =IF($E9<>"SÍ",0,SUMIFS(CONFIG!$D$79:$D$88,CONFIG!$A$79:$A$88,$A9,CONFIG!$C$79:$C$88,in_Sexo)) -> 879 | M9: =IF($E9<>"SÍ",0,SUMIFS(CONFIG!$E$79:$E$88,CONFIG!$A$79:$A$88,$A9,CONFIG!$C$79:$C$88,in_Sexo)) -> 10.2 | N9: =IF($E9<>"SÍ",0,SUMIFS(CONFIG!$F$79:$F$88,CONFIG!$A$79:$A$88,$A9,CONFIG!$C$79:$C$88,in_Sexo)) -> 0 | O9: =IF($E9<>"SÍ",0,SUMIFS(CONFIG!$G$79:$G$88,CONFIG!$A$79:$A$88,$A9,CONFIG!$C$79:$C$88,in_Sexo)) -> 0 | P9: =IF($E9<>"SÍ",0,SUMIFS(CONFIG!$H$79:$H$88,CONFIG!$A$79:$A$88,$A9,CONFIG!$C$79:$C$88,in_Sexo)) -> 0
A10: =CONFIG!$A$123 -> E4 | B10: =CONFIG!$B$123 -> Cunningham (1980) | C10: 500 + 22·MLG (idéntica en ambos sexos) | D10: =CONFIG!$G$123 -> MLG | E10: =IF(OR(COUNTIF(SEXOS,in_Sexo)<>1,ISBLANK(in_Edad),NOT(ISNUMBER(in_Edad)),ISBLANK(in_Peso),NOT(ISNUMBER(in_Peso))),"NO: faltan sexo, edad o peso válidos",IF(OR(in_Edad<EDAD_MIN,in_Edad>EDAD_MAX),"NO: edad fuera del alcance adulto",IF(OR(in_Peso<=0,in_Peso<PESO_MIN,in_Peso>PESO_MAX),"NO: peso no válido",IF(AND(CONFIG!$F$123="SÍ",OR(ISBLANK(in_Est),NOT(ISNUMBER(in_Est)),in_Est<=0,in_Est<EST_MIN,in_Est>EST_MAX)),"NO: esta ecuación necesita la estatura",IF(AND(CONFIG!$E$123="SÍ",NOT(ISNUMBER(CALCULOS!$B$10))),"NO: falta la masa libre de grasa","SÍ"))))) -> SÍ | F10: =IF($E10<>"SÍ","ND",$L10+$M10*in_Peso+$N10*IF(CONFIG!$F$123="SÍ",in_Est,0)+$O10*in_Edad+$P10*IF(ISNUMBER(CALCULOS!$B$10),CALCULOS!$B$10,0)) -> 1864 | G10: =IF(OR(ISBLANK(in_Edad),NOT(ISNUMBER(in_Edad))),"",IF(OR(in_Edad<CONFIG!$C$123,in_Edad>CONFIG!$D$123),"⚠ Fuera del rango de derivación","Dentro del rango de derivación")) -> Dentro del rango de derivación | H10: =IF(OR(NOT(ISNUMBER($F10)),NOT(ISNUMBER($B$18))),"ND",$F10-$B$18) -> 63.849429 | I10: =IF(OR(NOT(ISNUMBER($F10)),NOT(ISNUMBER($B$18)),$B$18=0),"ND",($F10-$B$18)/$B$18) -> 0.035468938 | J10: =IF(OR(NOT(ISNUMBER($F10)),NOT(ISNUMBER($B$28))),"ND",$F10-$B$28) -> 154.8 | K10: =IF(OR(NOT(ISNUMBER($F10)),NOT(ISNUMBER($B$28)),$B$28=0),"ND",($F10-$B$28)/$B$28) -> 0.090568687 | L10: =IF($E10<>"SÍ",0,SUMIFS(CONFIG!$D$79:$D$88,CONFIG!$A$79:$A$88,$A10,CONFIG!$C$79:$C$88,in_Sexo)) -> 500 | M10: =IF($E10<>"SÍ",0,SUMIFS(CONFIG!$E$79:$E$88,CONFIG!$A$79:$A$88,$A10,CONFIG!$C$79:$C$88,in_Sexo)) -> 0 | N10: =IF($E10<>"SÍ",0,SUMIFS(CONFIG!$F$79:$F$88,CONFIG!$A$79:$A$88,$A10,CONFIG!$C$79:$C$88,in_Sexo)) -> 0 | O10: =IF($E10<>"SÍ",0,SUMIFS(CONFIG!$G$79:$G$88,CONFIG!$A$79:$A$88,$A10,CONFIG!$C$79:$C$88,in_Sexo)) -> 0 | P10: =IF($E10<>"SÍ",0,SUMIFS(CONFIG!$H$79:$H$88,CONFIG!$A$79:$A$88,$A10,CONFIG!$C$79:$C$88,in_Sexo)) -> 22
A11: =CONFIG!$A$124 -> E5 | B11: =CONFIG!$B$124 -> Cunningham (1991) · alias secundario: Katch–McArdle | C11: 370 + 21,6·FFM (idéntica en ambos sexos) · fuente primaria: Cunningham 1991 | D11: =CONFIG!$G$124 -> MLG (FFM) | E11: =IF(OR(COUNTIF(SEXOS,in_Sexo)<>1,ISBLANK(in_Edad),NOT(ISNUMBER(in_Edad)),ISBLANK(in_Peso),NOT(ISNUMBER(in_Peso))),"NO: faltan sexo, edad o peso válidos",IF(OR(in_Edad<EDAD_MIN,in_Edad>EDAD_MAX),"NO: edad fuera del alcance adulto",IF(OR(in_Peso<=0,in_Peso<PESO_MIN,in_Peso>PESO_MAX),"NO: peso no válido",IF(AND(CONFIG!$F$124="SÍ",OR(ISBLANK(in_Est),NOT(ISNUMBER(in_Est)),in_Est<=0,in_Est<EST_MIN,in_Est>EST_MAX)),"NO: esta ecuación necesita la estatura",IF(AND(CONFIG!$E$124="SÍ",NOT(ISNUMBER(CALCULOS!$B$10))),"NO: falta la masa libre de grasa","SÍ"))))) -> SÍ | F11: =IF($E11<>"SÍ","ND",$L11+$M11*in_Peso+$N11*IF(CONFIG!$F$124="SÍ",in_Est,0)+$O11*in_Edad+$P11*IF(ISNUMBER(CALCULOS!$B$10),CALCULOS!$B$10,0)) -> 1709.2 | G11: =IF(OR(ISBLANK(in_Edad),NOT(ISNUMBER(in_Edad))),"",IF(OR(in_Edad<CONFIG!$C$124,in_Edad>CONFIG!$D$124),"⚠ Fuera del rango de derivación","Dentro del rango de derivación")) -> Dentro del rango de derivación | H11: =IF(OR(NOT(ISNUMBER($F11)),NOT(ISNUMBER($B$18))),"ND",$F11-$B$18) -> -90.950571 | I11: =IF(OR(NOT(ISNUMBER($F11)),NOT(ISNUMBER($B$18)),$B$18=0),"ND",($F11-$B$18)/$B$18) -> -0.050523869 | J11: =IF(OR(NOT(ISNUMBER($F11)),NOT(ISNUMBER($B$28))),"ND",$F11-$B$28) -> 0 | K11: =IF(OR(NOT(ISNUMBER($F11)),NOT(ISNUMBER($B$28)),$B$28=0),"ND",($F11-$B$28)/$B$28) -> 0 | L11: =IF($E11<>"SÍ",0,SUMIFS(CONFIG!$D$79:$D$88,CONFIG!$A$79:$A$88,$A11,CONFIG!$C$79:$C$88,in_Sexo)) -> 370 | M11: =IF($E11<>"SÍ",0,SUMIFS(CONFIG!$E$79:$E$88,CONFIG!$A$79:$A$88,$A11,CONFIG!$C$79:$C$88,in_Sexo)) -> 0 | N11: =IF($E11<>"SÍ",0,SUMIFS(CONFIG!$F$79:$F$88,CONFIG!$A$79:$A$88,$A11,CONFIG!$C$79:$C$88,in_Sexo)) -> 0 | O11: =IF($E11<>"SÍ",0,SUMIFS(CONFIG!$G$79:$G$88,CONFIG!$A$79:$A$88,$A11,CONFIG!$C$79:$C$88,in_Sexo)) -> 0 | P11: =IF($E11<>"SÍ",0,SUMIFS(CONFIG!$H$79:$H$88,CONFIG!$A$79:$A$88,$A11,CONFIG!$C$79:$C$88,in_Sexo)) -> 21.6
A12: =CONFIG!$A$125 -> E6 | B12: =CONFIG!$B$125 -> Schofield (1985) adultos · tabla canónica | C12: Bandas 18–30 / 30–60 / ≥60 · GEB = a + b·P (tabla canónica, CONFIG C9) | D12: =CONFIG!$G$125 -> sexo, peso, banda etaria | E12: =IF(OR(COUNTIF(SEXOS,in_Sexo)<>1,ISBLANK(in_Edad),NOT(ISNUMBER(in_Edad)),ISBLANK(in_Peso),NOT(ISNUMBER(in_Peso))),"NO: faltan sexo, edad o peso válidos",IF(OR(in_Edad<EDAD_MIN,in_Edad>EDAD_MAX),"NO: edad fuera del alcance adulto",IF(OR(in_Peso<=0,in_Peso<PESO_MIN,in_Peso>PESO_MAX),"NO: peso no válido",IF(AND(CONFIG!$F$125="SÍ",OR(ISBLANK(in_Est),NOT(ISNUMBER(in_Est)),in_Est<=0,in_Est<EST_MIN,in_Est>EST_MAX)),"NO: esta ecuación necesita la estatura",IF(AND(CONFIG!$E$125="SÍ",NOT(ISNUMBER(CALCULOS!$B$10))),"NO: falta la masa libre de grasa","SÍ"))))) -> SÍ | F12: =IF($E12<>"SÍ","ND",$L12+$M12*in_Peso+$N12*IF(CONFIG!$F$125="SÍ",in_Est,0)+$O12*in_Edad+$P12*IF(ISNUMBER(CALCULOS!$B$10),CALCULOS!$B$10,0)) -> 1866.646 | G12: =IF(OR(ISBLANK(in_Edad),NOT(ISNUMBER(in_Edad))),"",IF(OR(in_Edad<CONFIG!$C$125,in_Edad>CONFIG!$D$125),"⚠ Fuera del rango de derivación","Dentro del rango de derivación")) -> Dentro del rango de derivación | H12: =IF(OR(NOT(ISNUMBER($F12)),NOT(ISNUMBER($B$18))),"ND",$F12-$B$18) -> 66.495429 | I12: =IF(OR(NOT(ISNUMBER($F12)),NOT(ISNUMBER($B$18)),$B$18=0),"ND",($F12-$B$18)/$B$18) -> 0.036938815 | J12: =IF(OR(NOT(ISNUMBER($F12)),NOT(ISNUMBER($B$28))),"ND",$F12-$B$28) -> 157.446 | K12: =IF(OR(NOT(ISNUMBER($F12)),NOT(ISNUMBER($B$28)),$B$28=0),"ND",($F12-$B$28)/$B$28) -> 0.09211678 | L12: =IF($E12<>"SÍ",0,SUMPRODUCT((CONFIG!$A$92:$A$97=in_Sexo)*(CONFIG!$B$92:$B$97<=in_Edad)*(CONFIG!$C$92:$C$97>in_Edad)*CONFIG!$E$92:$E$97)) -> 692.2 | M12: =IF($E12<>"SÍ",0,SUMPRODUCT((CONFIG!$A$92:$A$97=in_Sexo)*(CONFIG!$B$92:$B$97<=in_Edad)*(CONFIG!$C$92:$C$97>in_Edad)*CONFIG!$D$92:$D$97)) -> 15.057 | N12: 0 | O12: 0 | P12: 0
A13: =CONFIG!$A$126 -> E7 | B13: =CONFIG!$B$126 -> Henry / Oxford (2005) adultos · solo peso | C13: Bandas 18–30 / 30–60 / ≥60 · GEB = a + b·P (CONFIG C10) · NUEVO en v1.1 | D13: =CONFIG!$G$126 -> sexo, peso, banda etaria | E13: =IF(OR(COUNTIF(SEXOS,in_Sexo)<>1,ISBLANK(in_Edad),NOT(ISNUMBER(in_Edad)),ISBLANK(in_Peso),NOT(ISNUMBER(in_Peso))),"NO: faltan sexo, edad o peso válidos",IF(OR(in_Edad<EDAD_MIN,in_Edad>EDAD_MAX),"NO: edad fuera del alcance adulto",IF(OR(in_Peso<=0,in_Peso<PESO_MIN,in_Peso>PESO_MAX),"NO: peso no válido",IF(AND(CONFIG!$F$126="SÍ",OR(ISBLANK(in_Est),NOT(ISNUMBER(in_Est)),in_Est<=0,in_Est<EST_MIN,in_Est>EST_MAX)),"NO: esta ecuación necesita la estatura",IF(AND(CONFIG!$E$126="SÍ",NOT(ISNUMBER(CALCULOS!$B$10))),"NO: falta la masa libre de grasa","SÍ"))))) -> SÍ | F13: =IF($E13<>"SÍ","ND",$L13+$M13*in_Peso+$N13*IF(CONFIG!$F$126="SÍ",in_Est,0)+$O13*in_Edad+$P13*IF(ISNUMBER(CALCULOS!$B$10),CALCULOS!$B$10,0)) -> 1793 | G13: =IF(OR(ISBLANK(in_Edad),NOT(ISNUMBER(in_Edad))),"",IF(OR(in_Edad<CONFIG!$C$126,in_Edad>CONFIG!$D$126),"⚠ Fuera del rango de derivación","Dentro del rango de derivación")) -> Dentro del rango de derivación | H13: =IF(OR(NOT(ISNUMBER($F13)),NOT(ISNUMBER($B$18))),"ND",$F13-$B$18) -> -7.1505714 | I13: =IF(OR(NOT(ISNUMBER($F13)),NOT(ISNUMBER($B$18)),$B$18=0),"ND",($F13-$B$18)/$B$18) -> -0.0039722074 | J13: =IF(OR(NOT(ISNUMBER($F13)),NOT(ISNUMBER($B$28))),"ND",$F13-$B$28) -> 83.8 | K13: =IF(OR(NOT(ISNUMBER($F13)),NOT(ISNUMBER($B$28)),$B$28=0),"ND",($F13-$B$28)/$B$28) -> 0.049028785 | L13: =IF($E13<>"SÍ",0,SUMPRODUCT((CONFIG!$A$110:$A$115=in_Sexo)*(CONFIG!$B$110:$B$115<=in_Edad)*(CONFIG!$C$110:$C$115>in_Edad)*CONFIG!$E$110:$E$115)) -> 545 | M13: =IF($E13<>"SÍ",0,SUMPRODUCT((CONFIG!$A$110:$A$115=in_Sexo)*(CONFIG!$B$110:$B$115<=in_Edad)*(CONFIG!$C$110:$C$115>in_Edad)*CONFIG!$D$110:$D$115)) -> 16 | N13: 0 | O13: 0 | P13: 0
A15: ESTADÍSTICOS (las ecuaciones que devuelven ND quedan EXCLUIDAS)
A16: Estadístico | B16: Valor | C16: Unidad | D16: Nota
A17: Ecuaciones efectivamente calculadas (n) | B17: =COUNT($F$7:$F$13) -> 7 | C17: — | D17: COUNT ignora los ND: las no calculables quedan fuera de TODOS los estadísticos.
A18: Promedio | B18: =IF($B$17=0,"ND",AVERAGE($F$7:$F$13)) -> 1800.1506 | C18: kcal/día | D18: Media de las calculadas.
A19: Mediana | B19: =IF($B$17=0,"ND",MEDIAN($F$7:$F$13)) -> 1810 | C19: kcal/día | D19: Menos sensible a un valor extremo.
A20: Mínimo | B20: =IF($B$17=0,"ND",MIN($F$7:$F$13)) -> 1674.6 | C20: kcal/día
A21: Máximo | B21: =IF($B$17=0,"ND",MAX($F$7:$F$13)) -> 1883.608 | C21: kcal/día
A22: Rango (máximo − mínimo) | B22: =IF($B$17=0,"ND",$B$21-$B$20) -> 209.008 | C22: kcal/día | D22: Discrepancia entre ecuaciones.
A23: Amplitud relativa (rango / promedio) | B23: =IF(OR($B$17=0,$B$18=0),"ND",$B$22/$B$18) -> 0.11610584 | C23: % | D23: Si supera AMPL_MAX (CONFIG C1), el libro advierte de la dispersión.
A24: Estado de la dispersión | B24: =IF(NOT(ISNUMBER($B$23)),"ND",IF($B$23>AMPL_MAX,"⚠ Dispersión alta: la elección de la ecuación pesa mucho en el resultado.","OK: las ecuaciones concuerdan dentro del umbral configurado.")) -> OK: las ecuaciones concuerdan dentro del umbral configurado. | C24: —
A26: SELECCIÓN DE LA ECUACIÓN
A27: Elemento | B27: Valor | C27: Estado
A28: GEB de la ecuación seleccionada | B28: =IF(COUNTIF(LISTA_ECU,in_Ecu)<>1,"ND",INDEX($F$7:$F$13,MATCH(in_Ecu,$B$7:$B$13,0))) -> 1709.2 | C28: =in_Ecu -> Cunningham (1991) · alias secundario: Katch–McArdle
A29: Motivo de selección registrado | B29: =in_Motivo -> Adulto sano sin composición corporal medida; Mifflin–St Jeor es la de mejor desempeño documentado en este perfil. | C29: =IF(TRIM(in_Motivo)="","⚠ FALTA: registre el motivo en DATOS (fila 23). Una selección sin justificación no es auditable.","OK: motivo registrado") -> OK: motivo registrado
A30: Sugerencia automática del libro | B30: =IF(ISNUMBER(CALCULOS!$B$10),"Hay masa libre de grasa: Cunningham 1980 o Cunningham 1991 (alias Katch–McArdle) son defendibles, sobre todo con masa muscular alta. Mifflin–St Jeor y Henry siguen siendo opciones válidas.","Sin composición corporal: Mifflin–St Jeor (1990) y Henry/Oxford (2005) son las de mejor respaldo en adultos sanos.") -> Hay masa libre de grasa: Cunningham 1980 o Cunningham 1991 (alias Katch–McArdle) son defendibles, sobre todo con masa muscular alta. Mifflin–St Jeor y Henry siguen siendo opciones válidas. | C30: Sugerencia, NO imposición: la decisión y su motivo son suyos.
A31: Nivel de verificación de la ecuación seleccionada | B31: =IF(COUNTIF(LISTA_ECU,in_Ecu)<>1,"ND","Nivel "&INDEX(CONFIG!$H$120:$H$126,MATCH(in_Ecu,LISTA_ECU,0))&" · "&INDEX(CONFIG!$I$120:$I$126,MATCH(in_Ecu,LISTA_ECU,0))) -> Nivel B · Fuente primaria de 370+21,6·FFM: Cunningham 1991, DOI 10.1093/ajcn/54.6.963. El nombre 'Katch–McArdle' es un alias de nivel C | C31: A = fuente primaria cotejada · B = resumen primario o corroboración por pares · C = fuente secundaria

Sheet CALCULOS
A1: CÁLCULOS · Cadena auditable · DEFINITIVO 2026
A2: Sin constantes dentro de las fórmulas: todas provienen de CONFIG. Sin IFERROR: cada guarda es explícita y devuelve la causa. DATO IMPOSIBLE (bloquea) y DATO POCO FRECUENTE (solo advierte) son categorías separadas.
A3: =HYPERLINK("#INICIO!A1","◀ INICIO") -> ◀ INICIO
A5: 0 · CAPA BASE — se resuelve ANTES de la compuerta (el PAL por METs necesita el GEB)
A6: Variable | B6: Valor | C6: Unidad | D6: Fórmula / nota
A7: Estatura | B7: =IF(OR(ISBLANK(in_Est),NOT(ISNUMBER(in_Est)),in_Est<=0),"",in_Est/100) -> 1.8 | C7: m | D7: Estatura (cm) / 100
A8: IMC | B8: =IF(OR(NOT(ISNUMBER($B$7)),$B$7<=0,NOT(ISNUMBER(in_Peso)),in_Peso<=0),"",in_Peso/$B$7^2) -> 24.074074 | C8: kg/m² | D8: Peso / estatura². Guarda explícita contra la división por cero.
A9: % de grasa utilizado | B9: =IF(OR(NOT(ISNUMBER(in_Peso)),in_Peso<=0),"",IF(AND(NOT(ISBLANK(in_Grasa)),ISNUMBER(in_Grasa),in_Grasa>=GRASA_MIN,in_Grasa<=GRASA_MAX),in_Grasa,IF(AND(NOT(ISBLANK(in_MLG)),ISNUMBER(in_MLG),in_MLG>0,in_MLG<in_Peso),(in_Peso-in_MLG)/in_Peso,""))) -> 0.05 | C9: % | D9: Prioriza el % ingresado; si no, lo deriva de la MLG.
A10: Masa libre de grasa utilizada | B10: =IF(OR(NOT(ISNUMBER(in_Peso)),in_Peso<=0),"",IF(AND(NOT(ISBLANK(in_MLG)),ISNUMBER(in_MLG),in_MLG>0,in_MLG<in_Peso),in_MLG,IF(AND(NOT(ISBLANK(in_Grasa)),ISNUMBER(in_Grasa),in_Grasa>=GRASA_MIN,in_Grasa<=GRASA_MAX),in_Peso*(1-in_Grasa),""))) -> 62 | C10: kg | D10: La MLG MEDIDA tiene prioridad sobre la derivada del % de grasa. Alimenta a Cunningham 1980 y 1991.
A11: Masa grasa | B11: =IF(NOT(ISNUMBER($B$10)),"",in_Peso-$B$10) -> 16 | C11: kg | D11: Peso − MLG
A12: Origen de la MLG | B12: =IF(NOT(ISNUMBER($B$10)),"No disponible (Cunningham 1980 y 1991 no se calculan)",IF(AND(NOT(ISBLANK(in_MLG)),ISNUMBER(in_MLG),in_MLG>0,in_MLG<in_Peso),"Medida directamente","Derivada del % de grasa")) -> Medida directamente | C12: — | D12: Trazabilidad del dato.
A13: Factor de actividad efectivo (FA) | B13: =IF(in_Metodo=INDEX(LISTA_METODO,2),IF(ISNUMBER(ACTIVIDADES!$B$27),ACTIVIDADES!$B$27,""),IF(AND(NOT(ISBLANK(in_FAman)),ISNUMBER(in_FAman)),in_FAman,IF(COUNTIF(LISTA_FA,in_FAcat)=1,INDEX(FA_VAL,MATCH(in_FAcat,LISTA_FA,0)),""))) -> 1.8 | C13: — | D13: Prioridad: PAL derivado de ACTIVIDADES › factor manual › catálogo.
A14: Origen del factor | B14: =IF(in_Metodo=INDEX(LISTA_METODO,2),"PAL estimado desde ACTIVIDADES (TEE/GEB)",IF(AND(NOT(ISBLANK(in_FAman)),ISNUMBER(in_FAman)),"Factor manual de DATOS (sobreescribe el catálogo)","Catálogo CONFIG C4")) -> Catálogo CONFIG C4 | C14: — | D14: Trazabilidad de dónde salió el número.
A15: Horas registradas en ACTIVIDADES | B15: =ACTIVIDADES!$B$20 -> 24 | C15: h | D15: Debe ser 24 con el método por actividades.
A16: PAL estimado en ACTIVIDADES (TEE/GEB) | B16: =ACTIVIDADES!$B$27 -> NO CALCULADO | C16: — | D16: v1.1: ya NO es el promedio de METs. Ver hoja ACTIVIDADES.
A18: 1 · VALIDACIÓN — DATOS IMPOSIBLES (bloquean el cálculo)
A19: Verificación | B19: Estado | C19: Regla aplicada
A20: Sexo biológico | B20: =IF(COUNTIF(SEXOS,in_Sexo)=1,"OK","ERROR: seleccione Hombre o Mujer") -> OK | C20: Debe existir en el catálogo CONFIG C2.
A21: Edad adulta | B21: =IF(ISBLANK(in_Edad),"ERROR: vacío",IF(NOT(ISNUMBER(in_Edad)),"ERROR: no es numérico",IF(OR(in_Edad<EDAD_MIN,in_Edad>EDAD_MAX),"ERROR: edad fuera del alcance (solo adultos)","OK"))) -> OK | C21: Vacío → texto → rango [EDAD_MIN, EDAD_MAX].
A22: Peso mayor que cero | B22: =IF(ISBLANK(in_Peso),"ERROR: vacío",IF(NOT(ISNUMBER(in_Peso)),"ERROR: no es numérico",IF(in_Peso<=0,"ERROR: el peso debe ser mayor que cero",IF(OR(in_Peso<PESO_MIN,in_Peso>PESO_MAX),"ERROR: peso imposible en un adulto","OK")))) -> OK | C22: Bloquea vacíos, texto, cero y negativos.
A23: Estatura mayor que cero | B23: =IF(ISBLANK(in_Est),"ERROR: vacío",IF(NOT(ISNUMBER(in_Est)),"ERROR: no es numérico",IF(in_Est<=0,"ERROR: la estatura debe ser mayor que cero",IF(OR(in_Est<EST_MIN,in_Est>EST_MAX),"ERROR: estatura imposible","OK")))) -> OK | C23: Bloquea vacíos, texto, cero y negativos. Evita la división por cero del IMC.
A24: % de grasa (opcional) | B24: =IF(ISBLANK(in_Grasa),"NO INGRESADO (opcional)",IF(NOT(ISNUMBER(in_Grasa)),"ERROR: no es numérico",IF(OR(in_Grasa<GRASA_MIN,in_Grasa>GRASA_MAX),"ERROR: % de grasa imposible","OK"))) -> OK | C24: Opcional. Rango configurable.
A25: MLG menor que el peso (opcional) | B25: =IF(ISBLANK(in_MLG),"NO INGRESADA (opcional)",IF(NOT(ISNUMBER(in_MLG)),"ERROR: no es numérico",IF(NOT(ISNUMBER(in_Peso)),"NO APLICA",IF(in_MLG>=in_Peso,"ERROR: la MLG es mayor o igual al peso","OK")))) -> OK | C25: Imposibilidad fisiológica.
A26: Factor de actividad efectivo | B26: =IF(NOT(ISNUMBER($B$13)),IF(in_Metodo=INDEX(LISTA_METODO,2),"ERROR: el PAL por actividades exige 24 h registradas y un GEB calculable","ERROR: no se pudo determinar el factor de actividad"),IF(OR($B$13<FA_MIN,$B$13>FA_MAX),"ERROR: factor de actividad fuera de límites","OK")) -> OK | C26: Se valida el factor EFECTIVO, venga del catálogo, del campo manual o del PAL derivado.
A27: % de efecto térmico | B27: =IF(ISBLANK(in_pETA),"ERROR: vacío",IF(NOT(ISNUMBER(in_pETA)),"ERROR: no es numérico",IF(OR(in_pETA<0,in_pETA>ETA_MAX),"ERROR: % de efecto térmico fuera de rango","OK"))) -> OK | C27: Rango [0, ETA_MAX].
A28: % de ajuste energético | B28: =IF(ISBLANK(in_Ajuste),"ERROR: vacío",IF(NOT(ISNUMBER(in_Ajuste)),"ERROR: no es numérico",IF(ABS(in_Ajuste)>AJUSTE_MAX,"ERROR: ajuste fuera de rango","OK"))) -> OK | C28: |ajuste| ≤ AJUSTE_MAX.
A29: Registro de ACTIVIDADES = 24 h | B29: =IF(in_Metodo<>"Registro de actividades 24 h","NO APLICA · método global",IF(ABS(ACTIVIDADES!$B$20-HORAS_DIA)>0.001,"ERROR · registro de actividades ≠24 h",IF(COUNTIF(ACTIVIDADES!$H$7:$H$18,"REQUIERE REVALIDACIÓN")>0,"ERROR · hay actividades que requieren revalidación","OK"))) -> NO APLICA · método global | C29: Solo se exige con el método por actividades.
A30: Proteína no negativa | B30: =IF(ISBLANK(in_ValPro),"ERROR: vacío",IF(NOT(ISNUMBER(in_ValPro)),"ERROR: no es numérico",IF(in_ValPro<0,"ERROR: la proteína no puede ser negativa","OK"))) -> OK | C30: Se aplica en ambos modos.
A31: Grasa no negativa | B31: =IF(ISBLANK(in_ValGra),"ERROR: vacío",IF(NOT(ISNUMBER(in_ValGra)),"ERROR: no es numérico",IF(in_ValGra<0,"ERROR: la grasa no puede ser negativa","OK"))) -> OK | C31: Se aplica en ambos modos.
A32: % de proteína + % de grasa ≤ 100 % | B32: =IF(AND(in_ModoPro=INDEX(LISTA_MODO,1),in_ModoGra=INDEX(LISTA_MODO,1)),IF(ISNUMBER(in_ValPro)*ISNUMBER(in_ValGra)=0,"ERROR: valores no numéricos",IF(in_ValPro+in_ValGra>1,"ERROR: los % de proteína y grasa superan el 100 %","OK")),"NO APLICA (algún macro está en g/kg)") -> NO APLICA (algún macro está en g/kg) | C32: Con g/kg, el control equivalente es que los carbohidratos por diferencia no sean negativos (bloque 4).
A33: ¿CÁLCULO HABILITADO? | B33: =IF(SUMPRODUCT(--(LEFT($B$20:$B$32,5)="ERROR"))=0,"SÍ","NO") -> SÍ | C33: Compuerta única. Si es NO, todo lo que sigue devuelve vacío o 'ND', nunca un error de Excel.
A35: 2 · COMPONENTES DEL GASTO — GET = GEB + GAF + ETA
A36: Variable | B36: Valor | C36: Unidad | D36: Fórmula / nota
A37: GEB · gasto energético basal | B37: =IF($B$33<>"SÍ","",IF(ISNUMBER(ECUACIONES!$B$28),ECUACIONES!$B$28,"ND: la ecuación seleccionada no es calculable con los datos disponibles")) -> 1709.2 | C37: kcal/día | D37: Ecuación seleccionada en DATOS (hoja ECUACIONES).
A38: GAF · gasto por actividad física | B38: =IF(NOT(ISNUMBER($B$37)),"ND",$B$37*($B$13-1)) -> 1367.36 | C38: kcal/día | D38: GEB × (FA − 1). Se resta 1 para NO volver a contar el basal ya incluido en el factor.
A39: Modo de efecto térmico | B39: =in_ModoETA -> Incluido en el factor de actividad (recomendado) | C39: — | D39: Elegido en DATOS.
A40: ETA · efecto térmico de los alimentos | B40: =IF(NOT(ISNUMBER($B$38)),"ND",IF(in_ModoETA=INDEX(LISTA_ETA,1),0,IF(in_ModoETA=INDEX(LISTA_ETA,2),($B$37+$B$38)*in_pETA,IF(in_ModoETA=INDEX(LISTA_ETA,3),($B$37+$B$38)*in_pETA/(1-in_pETA),"ND")))) -> 0 | C40: kcal/día | D40: Modo 1: 0 (el PAL ya lo incluye). Modo 2: % de (GEB+GAF). Modo 3: se resuelve como % del GET.
A41: GET · gasto energético total | B41: =IF(OR(NOT(ISNUMBER($B$37)),NOT(ISNUMBER($B$38)),NOT(ISNUMBER($B$40))),"ND",$B$37+$B$38+$B$40) -> 3076.56 | C41: kcal/día | D41: Con ETA = 0 esto equivale exactamente a GEB × FA.
A42: Control de doble conteo | B42: =IF(in_ModoETA=INDEX(LISTA_ETA,1),"OK: el ETA está incluido en el factor de actividad; el libro lo fija en 0 y no lo suma dos veces.","⚠ ETA EXPLÍCITO SOBRE UN PAL: por definición de FAO, el PAL ya contiene el efecto térmico. Si su factor de actividad es un PAL, está contando el ETA DOS VECES. Actívelo solo si puede documentar que su factor lo EXCLUYE.") -> OK: el ETA está incluido en el factor de actividad; el libro lo fija en 0 y no lo suma dos veces.
A44: 3 · AJUSTE POR OBJETIVO Y ENERGÍA OBJETIVO
A45: Objetivo | B45: =in_Obj -> Aumento de peso | C45: — | D45: Elegido en DATOS.
A46: % de ajuste aplicado | B46: =in_Ajuste -> 0.05 | C46: % | D46: Negativo = déficit; positivo = superávit.
A47: Ajuste energético | B47: =IF(NOT(ISNUMBER($B$41)),"ND",$B$41*$B$46) -> 153.828 | C47: kcal/día | D47: GET × % de ajuste. Se aplica sobre el GET, nunca sobre el GEB.
A48: ENERGÍA OBJETIVO | B48: =IF(OR(NOT(ISNUMBER($B$41)),NOT(ISNUMBER($B$47))),"ND",$B$41+$B$47) -> 3230.388 | C48: kcal/día | D48: GET + ajuste. Es la energía que se reparte entre los macronutrientes.
A49: Energía objetivo por kg de peso | B49: =IF(NOT(ISNUMBER($B$48)),"ND",$B$48/in_Peso) -> 41.415231 | C49: kcal/kg/día
A51: 4 · MACRONUTRIENTES · los CARBOHIDRATOS se obtienen POR DIFERENCIA
A52: Macronutriente | B52: Modo | C52: Valor ingresado | D52: g/día | E52: g/kg/día | F52: kcal/día | G52: % de la energía
A53: Proteína | B53: =in_ModoPro -> g/kg de peso | C53: =in_ValPro -> 1.5 | D53: =IF(NOT(ISNUMBER($B$48)),"ND",ROUND(IF($B53=INDEX(LISTA_MODO,2),$C53*in_Peso,$B$48*$C53/KPRO),0)) -> 117 | E53: =IF(NOT(ISNUMBER($D53)),"ND",$D53/in_Peso) -> 1.5 | F53: =IF(NOT(ISNUMBER($D53)),"ND",$D53*KPRO) -> 468 | G53: =IF(OR(NOT(ISNUMBER($F53)),NOT(ISNUMBER($B$48))),"ND",$F53/$B$48) -> 0.14487424
A54: Grasa | B54: =in_ModoGra -> % de la energía | C54: =in_ValGra -> 0.2 | D54: =IF(NOT(ISNUMBER($B$48)),"ND",ROUND(IF($B54=INDEX(LISTA_MODO,2),$C54*in_Peso,$B$48*$C54/KGRA),0)) -> 72 | E54: =IF(NOT(ISNUMBER($D54)),"ND",$D54/in_Peso) -> 0.92307692 | F54: =IF(NOT(ISNUMBER($D54)),"ND",$D54*KGRA) -> 648 | G54: =IF(OR(NOT(ISNUMBER($F54)),NOT(ISNUMBER($B$48))),"ND",$F54/$B$48) -> 0.2005951
A55: Carbohidratos (por diferencia) | B55: ="por diferencia" -> por diferencia | C55: ="—" -> — | D55: =IF(OR(NOT(ISNUMBER($B$48)),NOT(ISNUMBER($F$53)),NOT(ISNUMBER($F$54))),"ND",IF(($B$48-$F$53-$F$54)<0,"ERROR: la proteína y la grasa exceden la energía objetivo",ROUND(($B$48-$F$53-$F$54)/KCHO,0))) -> 529 | E55: =IF(NOT(ISNUMBER($D55)),"ND",$D55/in_Peso) -> 6.7820513 | F55: =IF(NOT(ISNUMBER($D55)),"ND",$D55*KCHO) -> 2116 | G55: =IF(OR(NOT(ISNUMBER($F55)),NOT(ISNUMBER($B$48))),"ND",$F55/$B$48) -> 0.65502967
A56: TOTAL | B56: ="" | C56: ="" | D56: =IF(COUNT($D$53:$D$55)=3,SUM($D$53:$D$55),"ND") -> 718 | E56: =IF(COUNT($E$53:$E$55)=3,SUM($E$53:$E$55),"ND") -> 9.2051282 | F56: =IF(COUNT($F$53:$F$55)=3,SUM($F$53:$F$55),"ND") -> 3232 | G56: =IF(COUNT($G$53:$G$55)=3,SUM($G$53:$G$55),"ND") -> 1.000499
A57: Los gramos se redondean a enteros (así se prescribe). Las kcal se reconstruyen DESDE el gramo redondeado, de modo que el cuadre de abajo mide una diferencia real, no una ficticia.
A59: 5 · CUADRE ENERGÉTICO
A60: Suma de kcal de los macronutrientes | B60: =IF(COUNT($F$53:$F$55)=3,SUM($F$53:$F$55),"ND") -> 3232 | C60: kcal/día
A61: Energía objetivo | B61: =$B$48 -> 3230.388 | C61: kcal/día
A62: Diferencia (macros − objetivo) | B62: =IF(OR(NOT(ISNUMBER($B$60)),NOT(ISNUMBER($B$61))),"ND",$B$60-$B$61) -> 1.612 | C62: kcal/día
A63: Tolerancia configurada | B63: =TOL_KCAL -> 5 | C63: kcal/día
A64: ESTADO DEL CUADRE | B64: =IF(NOT(ISNUMBER($B$62)),"ND",IF(ABS($B$62)<=$B$63,"OK: las kcal de los macronutrientes cuadran con la energía objetivo dentro de la tolerancia.","⚠ FUERA DE TOLERANCIA: la diferencia supera el umbral de CONFIG C1. Revise la distribución.")) -> OK: las kcal de los macronutrientes cuadran con la energía objetivo dentro de la tolerancia.
A66: 6 · ADVERTENCIAS (no bloquean: separan lo POCO FRECUENTE de lo IMPOSIBLE)
A67: Chequeo | B67: Resultado
A68: Cálculo bloqueado | B68: =IF($B$33="SÍ","—","⚠ Hay DATOS IMPOSIBLES en el bloque 1. Nada se calcula hasta corregirlos.") -> —
A69: Motivo de selección no registrado | B69: =IF(TRIM(in_Motivo)="","⚠ No registró el motivo de selección de la ecuación (DATOS). La decisión no es auditable.","—") -> —
A70: Ecuación fuera de su rango de derivación | B70: =IF($B$33<>"SÍ","—",IF(COUNTIF(LISTA_ECU,in_Ecu)<>1,"—",IF(OR(in_Edad<INDEX(CONFIG!$C$120:$C$126,MATCH(in_Ecu,LISTA_ECU,0)),in_Edad>INDEX(CONFIG!$D$120:$D$126,MATCH(in_Ecu,LISTA_ECU,0))),"⚠ La edad del paciente queda fuera del rango en que se derivó la ecuación seleccionada.","—"))) -> —
A71: Dispersión entre ecuaciones | B71: =IF(NOT(ISNUMBER(ECUACIONES!$B$23)),"—",IF(ECUACIONES!$B$23>AMPL_MAX,"⚠ Las ecuaciones discrepan más que el umbral configurado: la elección pesa mucho en el resultado.","—")) -> —
A72: Doble conteo del efecto térmico | B72: =IF(in_ModoETA=INDEX(LISTA_ETA,1),"—","⚠ ETA explícito sobre un PAL: el efecto térmico se está contando dos veces (ver CALCULOS, control de doble conteo).") -> —
A73: Peso poco frecuente | B73: =IF(NOT(ISNUMBER(in_Peso)),"—",IF(OR(in_Peso<PESO_RB,in_Peso>PESO_RA),"⚠ POCO FRECUENTE (no imposible): verifique la medición del peso.","—")) -> —
A74: Estatura poco frecuente | B74: =IF(NOT(ISNUMBER(in_Est)),"—",IF(OR(in_Est<EST_RB,in_Est>EST_RA),"⚠ POCO FRECUENTE (no imposible): verifique la medición de la estatura.","—")) -> —
A75: IMC poco frecuente | B75: =IF(NOT(ISNUMBER($B$8)),"—",IF(OR($B$8<IMC_RB,$B$8>IMC_RA),"⚠ POCO FRECUENTE (no imposible): en IMC extremos las ecuaciones basadas en peso pierden precisión.","—")) -> —
A76: Proteína por encima de lo plausible | B76: =IF(NOT(ISNUMBER($E$53)),"—",IF($E$53>PRO_MAX,"⚠ Proteína sobre el máximo plausible de CONFIG (g/kg). Verifique la indicación.","—")) -> —
A77: Grasa por debajo de lo plausible | B77: =IF(NOT(ISNUMBER($G$54)),"—",IF($G$54<GRA_MIN,"⚠ Grasa bajo el mínimo plausible de CONFIG (% de la energía).","—")) -> —
A78: Carbohidratos negativos | B78: =IF($B$33<>"SÍ","—",IF(ISNUMBER($D$55),"—","⚠ Los carbohidratos por diferencia no son calculables: la proteína y la grasa exceden la energía objetivo.")) -> —
A79: Coherencia entre objetivo y signo del ajuste | B79: =IF(NOT(ISNUMBER(in_Ajuste)),"—",IF(AND(in_Obj=INDEX(LISTA_OBJ,2),in_Ajuste>=0),"⚠ El objetivo es reducción, pero el ajuste no es negativo.",IF(AND(in_Obj=INDEX(LISTA_OBJ,3),in_Ajuste<=0),"⚠ El objetivo es aumento, pero el ajuste no es positivo.",IF(AND(in_Obj=INDEX(LISTA_OBJ,1),in_Ajuste<>0),"⚠ El objetivo es mantenimiento, pero el ajuste no es cero.","—")))) -> —
A80: Factor de actividad elevado | B80: =IF(NOT(ISNUMBER($B$13)),"—",IF($B$13>PAL_VIGOROSO_MIN,"⚠ Factor de actividad muy alto: propio de patrones de actividad vigorosos. Verifique que represente la actividad habitual global.","—")) -> —
A81: Método por actividades: MET no es PAL | B81: =IF(in_Metodo<>INDEX(LISTA_METODO,2),"—","⚠ El PAL se derivó como TEE(METs)/GEB. Un MET es múltiplo del reposo ESTÁNDAR (1 kcal/kg/h), no del GEB individual: la conversión es una APROXIMACIÓN documentada en la hoja ACTIVIDADES.") -> —
A82: Nivel de verificación de la ecuación elegida | B82: =IF(COUNTIF(LISTA_ECU,in_Ecu)<>1,"ND","Nivel "&INDEX(CONFIG!$H$120:$H$126,MATCH(in_Ecu,LISTA_ECU,0))&" · A = fuente primaria cotejada; B = resumen primario o corroboración por pares; C = fuente secundaria") -> Nivel B · A = fuente primaria cotejada; B = resumen primario o corroboración por pares; C = fuente secundaria

Sheet RESULTADOS
A1: RESULTADOS · Informe de la evaluación energética · DEFINITIVO 2026
A2: =HYPERLINK("#DATOS!A1","◀ DATOS") -> ◀ DATOS | C2: =HYPERLINK("#ECUACIONES!A1","▶ ECUACIONES") -> ▶ ECUACIONES
A4: IDENTIFICACIÓN
A5: Identificador de la evaluación | B5: =in_ID -> NMX-2026-0001
A6: Fecha | B6: =in_Fecha -> 46215
A7: Paciente | B7: =in_Pac -> PAC-0042
A8: Sexo · edad | B8: =IF(CALCULOS!$B$33<>"SÍ","ND",in_Sexo&" · "&ROUND(in_Edad,0)&" años") -> Hombre · 20 años
A9: Peso · estatura | B9: =IF(CALCULOS!$B$33<>"SÍ","ND",ROUND(in_Peso,1)&" kg · "&ROUND(in_Est,0)&" cm") -> 78 kg · 180 cm
A10: IMC | B10: =CALCULOS!$B$8 -> 24.074074 | C10: kg/m² | G10: kg/m²
A11: MLG utilizada · origen | B11: =IF(NOT(ISNUMBER(CALCULOS!$B$10)),"No disponible",ROUND(CALCULOS!$B$10,1)&" kg · "&CALCULOS!$B$12) -> 62 kg · Medida directamente
A12: Método de actividad · factor | B12: =in_Metodo&" · FA = "&IF(ISNUMBER(CALCULOS!$B$13),ROUND(CALCULOS!$B$13,3),"ND")&" ("&CALCULOS!$B$14&")" -> Factor de actividad global · FA = 1,8 (Catálogo CONFIG C4)
A13: Observaciones | B13: =IF(DATOS!$B$28="","—",DATOS!$B$28) -> —
A14: Nota técnica (QA v1.1.1): este bloque NO usa la función TEXT() con códigos de formato que contengan un punto decimal. En Excel en español el punto se interpreta como separador de millares y un factor de 1,55 se presentaría como 0,002. Se usa ROUND(), que respeta la configuración regional del usuario.
A15: DESGLOSE DEL GASTO Y ENERGÍA OBJETIVO
A16: Componente | B16: kcal/día | C16: % del GET | D16: Cómo se obtiene
A17: GEB · gasto energético basal | B17: =CALCULOS!$B$37 -> 1709.2 | C17: =IF(OR(NOT(ISNUMBER($B17)),NOT(ISNUMBER($B$20)),$B$20=0),"ND",$B17/$B$20) -> 0.55555556 | D17: Ecuación seleccionada
A18: GAF · gasto por actividad física | B18: =CALCULOS!$B$38 -> 1367.36 | C18: =IF(OR(NOT(ISNUMBER($B18)),NOT(ISNUMBER($B$20)),$B$20=0),"ND",$B18/$B$20) -> 0.44444444 | D18: GEB × (FA − 1)
A19: ETA · efecto térmico de los alimentos | B19: =CALCULOS!$B$40 -> 0 | C19: =IF(OR(NOT(ISNUMBER($B19)),NOT(ISNUMBER($B$20)),$B$20=0),"ND",$B19/$B$20) -> 0 | D19: 0 si el PAL ya lo incluye
A20: GET · gasto energético total | B20: =CALCULOS!$B$41 -> 3076.56 | C20: =IF(ISNUMBER($B$20),1,"ND") -> 1 | D20: GEB + GAF + ETA
A21: Ajuste por objetivo | B21: =CALCULOS!$B$47 -> 153.828 | C21: =in_Ajuste -> 0.05 | D21: GET × % de ajuste
A22: ENERGÍA OBJETIVO | B22: =CALCULOS!$B$48 -> 3230.388 | C22: ="—" -> — | D22: GET + ajuste
A23: Energía objetivo por kg | B23: =CALCULOS!$B$49 -> 41.415231 | C23: ="—" -> — | D23: Energía objetivo / peso
A24: =CALCULOS!$B$42 -> OK: el ETA está incluido en el factor de actividad; el libro lo fija en 0 y no lo suma dos veces.
A26: DISTRIBUCIÓN DE MACRONUTRIENTES
A27: Macronutriente | B27: g/día | C27: g/kg/día | D27: kcal/día | E27: % de la energía
A28: Proteína | B28: =CALCULOS!$D$53 -> 117 | C28: =CALCULOS!$E$53 -> 1.5 | D28: =CALCULOS!$F$53 -> 468 | E28: =CALCULOS!$G$53 -> 0.14487424
A29: Grasa | B29: =CALCULOS!$D$54 -> 72 | C29: =CALCULOS!$E$54 -> 0.92307692 | D29: =CALCULOS!$F$54 -> 648 | E29: =CALCULOS!$G$54 -> 0.2005951
A30: Carbohidratos (por diferencia) | B30: =CALCULOS!$D$55 -> 529 | C30: =CALCULOS!$E$55 -> 6.7820513 | D30: =CALCULOS!$F$55 -> 2116 | E30: =CALCULOS!$G$55 -> 0.65502967
A31: TOTAL | B31: =CALCULOS!$D$56 -> 718 | C31: =CALCULOS!$E$56 -> 9.2051282 | D31: =CALCULOS!$F$56 -> 3232 | E31: =CALCULOS!$G$56 -> 1.000499
A32: Comprobación · kcal de los macros − energía objetivo | B32: =CALCULOS!$B$62 -> 1.612 | C32: ="tolerancia: "&TEXT(TOL_KCAL,"0")&" kcal" -> tolerancia: 5 kcal | D32: =CALCULOS!$B$64 -> OK: las kcal de los macronutrientes cuadran con la energía objetivo dentro de la tolerancia.
A34: COMPARACIÓN DE LAS 7 ECUACIONES
A35: Ecuación | B35: GEB (kcal/día) | C35: Dif. vs promedio (kcal) | D35: Dif. vs promedio (%) | E35: Dif. vs seleccionada (kcal) | F35: Dif. vs seleccionada (%) | G35: ¿Datos disponibles?
A36: =ECUACIONES!$B$7 -> Mifflin–St Jeor (1990) | B36: =ECUACIONES!$F$7 -> 1810 | C36: =ECUACIONES!$H$7 -> 9.8494286 | D36: =ECUACIONES!$I$7 -> 0.0054714471 | E36: =ECUACIONES!$J$7 -> 100.8 | F36: =ECUACIONES!$K$7 -> 0.058974959 | G36: =ECUACIONES!$E$7 -> SÍ
A37: =ECUACIONES!$B$8 -> Harris–Benedict revisada · Roza & Shizgal (1984) | B37: =ECUACIONES!$F$8 -> 1883.608 | C37: =ECUACIONES!$H$8 -> 83.457429 | D37: =ECUACIONES!$I$8 -> 0.04636136 | E37: =ECUACIONES!$J$8 -> 174.408 | F37: =ECUACIONES!$K$8 -> 0.10204072 | G37: =ECUACIONES!$E$8 -> SÍ
A38: =ECUACIONES!$B$9 -> Owen (1986/1987) | B38: =ECUACIONES!$F$9 -> 1674.6 | C38: =ECUACIONES!$H$9 -> -125.55057 | D38: =ECUACIONES!$I$9 -> -0.069744483 | E38: =ECUACIONES!$J$9 -> -34.6 | F38: =ECUACIONES!$K$9 -> -0.020243389 | G38: =ECUACIONES!$E$9 -> SÍ
A39: =ECUACIONES!$B$10 -> Cunningham (1980) | B39: =ECUACIONES!$F$10 -> 1864 | C39: =ECUACIONES!$H$10 -> 63.849429 | D39: =ECUACIONES!$I$10 -> 0.035468938 | E39: =ECUACIONES!$J$10 -> 154.8 | F39: =ECUACIONES!$K$10 -> 0.090568687 | G39: =ECUACIONES!$E$10 -> SÍ
A40: =ECUACIONES!$B$11 -> Cunningham (1991) · alias secundario: Katch–McArdle | B40: =ECUACIONES!$F$11 -> 1709.2 | C40: =ECUACIONES!$H$11 -> -90.950571 | D40: =ECUACIONES!$I$11 -> -0.050523869 | E40: =ECUACIONES!$J$11 -> 0 | F40: =ECUACIONES!$K$11 -> 0 | G40: =ECUACIONES!$E$11 -> SÍ
A41: =ECUACIONES!$B$12 -> Schofield (1985) adultos · tabla canónica | B41: =ECUACIONES!$F$12 -> 1866.646 | C41: =ECUACIONES!$H$12 -> 66.495429 | D41: =ECUACIONES!$I$12 -> 0.036938815 | E41: =ECUACIONES!$J$12 -> 157.446 | F41: =ECUACIONES!$K$12 -> 0.09211678 | G41: =ECUACIONES!$E$12 -> SÍ
A42: =ECUACIONES!$B$13 -> Henry / Oxford (2005) adultos · solo peso | B42: =ECUACIONES!$F$13 -> 1793 | C42: =ECUACIONES!$H$13 -> -7.1505714 | D42: =ECUACIONES!$I$13 -> -0.0039722074 | E42: =ECUACIONES!$J$13 -> 83.8 | F42: =ECUACIONES!$K$13 -> 0.049028785 | G42: =ECUACIONES!$E$13 -> SÍ
A43: Ecuaciones calculadas (n) | B43: =ECUACIONES!$B$17 -> 7
A44: Promedio | B44: =ECUACIONES!$B$18 -> 1800.1506
A45: Mediana | B45: =ECUACIONES!$B$19 -> 1810
A46: Mínimo | B46: =ECUACIONES!$B$20 -> 1674.6
A47: Máximo | B47: =ECUACIONES!$B$21 -> 1883.608
A48: Rango (máx − mín) | B48: =ECUACIONES!$B$22 -> 209.008
A49: Amplitud relativa | B49: =ECUACIONES!$B$23 -> 0.11610584 | C49: =ECUACIONES!$B$24 -> OK: las ecuaciones concuerdan dentro del umbral configurado.
A51: DATOS DE APOYO PARA LOS GRÁFICOS
A52: Componente del gasto | B52: kcal/día
A53: GEB (basal) | B53: =IF(ISNUMBER(CALCULOS!$B$37),CALCULOS!$B$37,0) -> 1709.2
A54: Actividad (GAF) | B54: =IF(ISNUMBER(CALCULOS!$B$38),CALCULOS!$B$38,0) -> 1367.36
A55: Efecto térmico (ETA) | B55: =IF(ISNUMBER(CALCULOS!$B$40),CALCULOS!$B$40,0) -> 0
A56: Ajuste por objetivo | B56: =IF(ISNUMBER(CALCULOS!$B$47),CALCULOS!$B$47,0) -> 153.828
A58: Macronutriente | B58: kcal/día
A59: Proteína | B59: =IF(ISNUMBER(CALCULOS!$F$53),CALCULOS!$F$53,0) -> 468
A60: Grasa | B60: =IF(ISNUMBER(CALCULOS!$F$54),CALCULOS!$F$54,0) -> 648
A61: Carbohidratos | B61: =IF(ISNUMBER(CALCULOS!$F$55),CALCULOS!$F$55,0) -> 2116
A63: ADVERTENCIAS
A64: Cálculo bloqueado | B64: =CALCULOS!$B$68 -> —
A65: Motivo de selección no registrado | B65: =CALCULOS!$B$69 -> —
A66: Ecuación fuera de rango de derivación | B66: =CALCULOS!$B$70 -> —
A67: Dispersión entre ecuaciones | B67: =CALCULOS!$B$71 -> —
A68: Doble conteo del efecto térmico | B68: =CALCULOS!$B$72 -> —
A69: Peso poco frecuente | B69: =CALCULOS!$B$73 -> —
A70: Estatura poco frecuente | B70: =CALCULOS!$B$74 -> —
A71: IMC poco frecuente | B71: =CALCULOS!$B$75 -> —
A72: Proteína sobre lo plausible | B72: =CALCULOS!$B$76 -> —
A73: Grasa bajo lo plausible | B73: =CALCULOS!$B$77 -> —
A74: Carbohidratos negativos | B74: =CALCULOS!$B$78 -> —
A75: Objetivo vs signo del ajuste | B75: =CALCULOS!$B$79 -> —
A76: Factor de actividad elevado | B76: =CALCULOS!$B$80 -> —
A77: Método por actividades: MET no es PAL | B77: =CALCULOS!$B$81 -> —
A78: Nivel de verificación de la ecuación elegida | B78: =CALCULOS!$B$82 -> Nivel B · A = fuente primaria cotejada; B = resumen primario o corroboración por pares; C = fuente secundaria
A80: EXACTITUD MATEMÁTICA ≠ VALIDACIÓN CLÍNICA. Los coeficientes fueron cotejados contra las fuentes de la hoja FUENTES, pero este archivo NO está validado clínicamente. Son estimaciones poblacionales, no mediciones. No constituyen diagnóstico ni prescripción, y no reemplazan la calorimetría indirecta ni la evaluación profesional.

Sheet ACTIVIDADES
A1: =IF(DATOS!$H$10="ADULT2024_MET","ACTIVIDADES · Adulto 19–59 años · MET · 2024 Adult Compendium",IF(DATOS!$H$10="OLDER2024_MET60","ACTIVIDADES · Adulto ≥60 años · MET60+ · 2024 Older Adult Compendium",IF(DATOS!$H$10="WHEELCHAIR2024_METWC","ACTIVIDADES · Usuario adulto de silla de ruedas · METWC · 2024 Wheelchair Compendium",IF(DATOS!$H$10="COMPENDIUM_NO_DISPONIBLE_18","ACTIVIDADES · Módulo Compendium no disponible para edad 18",IF(DATOS!$H$10="BLOQUEADO_INESTABLE","ACTIVIDADES · Módulo bloqueado · condición no estable","ACTIVIDADES · Fuera del alcance NMX-01"))))) -> ACTIVIDADES · Usuario adulto de silla de ruedas · METWC · 2024 Wheelchair Compendium
A2: =HYPERLINK("#DATOS!A1","◀ DATOS") -> ◀ DATOS
A3: =IF(DATOS!$H$10="BLOQUEADO_INESTABLE","MÓDULO BLOQUEADO: NMX-01 no aplica a pacientes críticos o clínicamente inestables.",IF(DATOS!$H$10="FUERA_ALCANCE","FUERA DEL ALCANCE DE NMX-01.",IF(DATOS!$H$10="COMPENDIUM_NO_DISPONIBLE_18","Edad 18: NMX-01 general aplica, pero este módulo no extrapola el Adult Compendium 2024. No se calcula PAL derivado del Compendium.",IF(COUNTIF($H$7:$H$18,"REQUIERE REVALIDACIÓN")>0,"CAMBIO DE POBLACIÓN O CATÁLOGO: revise las actividades marcadas REQUIERE REVALIDACIÓN antes de calcular TEE/PAL.",IF(AND(DATOS!$H$10="WHEELCHAIR2024_METWC",in_Edad>=CONFIG!$B$154),"PRECAUCIÓN: METWC es la referencia disponible para silla de ruedas; en ≥60 años la evidencia etaria es limitada y NMX-01 bloquea TEE/PAL automático.","Fuente 2024 activa y registro listo. MET/MET60+/METWC NO son intercambiables; el índice medio NO es el PAL."))))) -> CAMBIO DE POBLACIÓN O CATÁLOGO: revise las actividades marcadas REQUIERE REVALIDACIÓN antes de calcular TEE/PAL.
A4: Edad | B4: =in_Edad -> 20 | C4: Movilidad | D4: =DATOS!$H$7 -> Usuario de silla de ruedas | E4: Unidad activa | F4: =IF(DATOS!$H$10="ADULT2024_MET","MET",IF(DATOS!$H$10="OLDER2024_MET60","MET60+",IF(DATOS!$H$10="WHEELCHAIR2024_METWC","METWC","—"))) -> METWC | G4: =IF(DATOS!$H$10="ADULT2024_MET","✓ APLICABLE",IF(DATOS!$H$10="OLDER2024_MET60","✓ APLICABLE",IF(DATOS!$H$10="WHEELCHAIR2024_METWC",IF(in_Edad>=CONFIG!$B$154,"⚠ EVIDENCIA ETARIA LIMITADA","✓ APLICABLE"),IF(DATOS!$H$10="COMPENDIUM_NO_DISPONIBLE_18","⚠ NO DISPONIBLE","✕ BLOQUEADO")))) -> ✓ APLICABLE
A5: Fuente activa | B5: =IF(DATOS!$H$10="ADULT2024_MET","2024 Adult Compendium",IF(DATOS!$H$10="OLDER2024_MET60","2024 Older Adult Compendium",IF(DATOS!$H$10="WHEELCHAIR2024_METWC","2024 Wheelchair Compendium","—"))) -> 2024 Wheelchair Compendium | E5: Equiv. energético | F5: =IF(DATOS!$H$10="ADULT2024_MET",CONFIG!$B$149,IF(DATOS!$H$10="OLDER2024_MET60",CONFIG!$B$150,IF(DATOS!$H$10="WHEELCHAIR2024_METWC",CONFIG!$B$151,""))) -> 0.992 | G5: =IF(DATOS!$H$10="ADULT2024_MET","BASE_MET_ADULT_2024",IF(DATOS!$H$10="OLDER2024_MET60","BASE_MET_OLDER_2024",IF(DATOS!$H$10="WHEELCHAIR2024_METWC","BASE_MET_WHEELCHAIR_2024","—"))) -> BASE_MET_WHEELCHAIR_2024
A6: Nº | B6: Actividad (catálogo dinámico 2024) | C6: Código | D6: =$F$4 -> METWC | E6: Horas/día | F6: =IF($F$4="—","Unidad × h",$F$4&" × h") -> METWC × h | G6: Nota / justificación | H6: Estado
A7: 1 | B7: Dormir · [MET] | C7: 7030 | D7: 1 | E7: 8 | F7: =IF(AND(ISNUMBER($D7),ISNUMBER($E7)),$D7*$E7,0) -> 8 | H7: =IF(OR(DATOS!$H$10="FUERA_ALCANCE",DATOS!$H$10="BLOQUEADO_INESTABLE"),"FUERA DE ALCANCE",IF(DATOS!$H$10="COMPENDIUM_NO_DISPONIBLE_18","NO DISPONIBLE",IF(B7="","SIN ACTIVIDAD",IF(LEFT(B7,15)="(sin actividad)","SIN ACTIVIDAD",IF(OR(AND(DATOS!$H$10="ADULT2024_MET",NOT(ISNUMBER(FIND("[MET]",B7)))),AND(DATOS!$H$10="OLDER2024_MET60",NOT(ISNUMBER(FIND("[MET60+]",B7)))),AND(DATOS!$H$10="WHEELCHAIR2024_METWC",NOT(ISNUMBER(FIND("[METWC]",B7))))),"REQUIERE REVALIDACIÓN",IF(C7="","REQUIERE REVALIDACIÓN","OK")))))) -> REQUIERE REVALIDACIÓN
A8: 2 | B8: Trabajo sentado ligero · oficina / laboratorio / escritorio · [MET] | C8: 11580 | D8: 1.5 | E8: 7 | F8: =IF(AND(ISNUMBER($D8),ISNUMBER($E8)),$D8*$E8,0) -> 10.5 | H8: =IF(OR(DATOS!$H$10="FUERA_ALCANCE",DATOS!$H$10="BLOQUEADO_INESTABLE"),"FUERA DE ALCANCE",IF(DATOS!$H$10="COMPENDIUM_NO_DISPONIBLE_18","NO DISPONIBLE",IF(B8="","SIN ACTIVIDAD",IF(LEFT(B8,15)="(sin actividad)","SIN ACTIVIDAD",IF(OR(AND(DATOS!$H$10="ADULT2024_MET",NOT(ISNUMBER(FIND("[MET]",B8)))),AND(DATOS!$H$10="OLDER2024_MET60",NOT(ISNUMBER(FIND("[MET60+]",B8)))),AND(DATOS!$H$10="WHEELCHAIR2024_METWC",NOT(ISNUMBER(FIND("[METWC]",B8))))),"REQUIERE REVALIDACIÓN",IF(C8="","REQUIERE REVALIDACIÓN","OK")))))) -> REQUIERE REVALIDACIÓN
A9: 3 | B9: Estudiar sentado · lectura o escritura · esfuerzo ligero · [MET] | C9: 9060 | D9: 1.5 | E9: 3 | F9: =IF(AND(ISNUMBER($D9),ISNUMBER($E9)),$D9*$E9,0) -> 4.5 | H9: =IF(OR(DATOS!$H$10="FUERA_ALCANCE",DATOS!$H$10="BLOQUEADO_INESTABLE"),"FUERA DE ALCANCE",IF(DATOS!$H$10="COMPENDIUM_NO_DISPONIBLE_18","NO DISPONIBLE",IF(B9="","SIN ACTIVIDAD",IF(LEFT(B9,15)="(sin actividad)","SIN ACTIVIDAD",IF(OR(AND(DATOS!$H$10="ADULT2024_MET",NOT(ISNUMBER(FIND("[MET]",B9)))),AND(DATOS!$H$10="OLDER2024_MET60",NOT(ISNUMBER(FIND("[MET60+]",B9)))),AND(DATOS!$H$10="WHEELCHAIR2024_METWC",NOT(ISNUMBER(FIND("[METWC]",B9))))),"REQUIERE REVALIDACIÓN",IF(C9="","REQUIERE REVALIDACIÓN","OK")))))) -> REQUIERE REVALIDACIÓN
A10: 4 | B10: Caminar 4,5–5,5 km/h · moderado · [MET] | C10: 17190 | D10: 3.8 | E10: 2 | F10: =IF(AND(ISNUMBER($D10),ISNUMBER($E10)),$D10*$E10,0) -> 7.6 | H10: =IF(OR(DATOS!$H$10="FUERA_ALCANCE",DATOS!$H$10="BLOQUEADO_INESTABLE"),"FUERA DE ALCANCE",IF(DATOS!$H$10="COMPENDIUM_NO_DISPONIBLE_18","NO DISPONIBLE",IF(B10="","SIN ACTIVIDAD",IF(LEFT(B10,15)="(sin actividad)","SIN ACTIVIDAD",IF(OR(AND(DATOS!$H$10="ADULT2024_MET",NOT(ISNUMBER(FIND("[MET]",B10)))),AND(DATOS!$H$10="OLDER2024_MET60",NOT(ISNUMBER(FIND("[MET60+]",B10)))),AND(DATOS!$H$10="WHEELCHAIR2024_METWC",NOT(ISNUMBER(FIND("[METWC]",B10))))),"REQUIERE REVALIDACIÓN",IF(C10="","REQUIERE REVALIDACIÓN","OK")))))) -> REQUIERE REVALIDACIÓN
A11: 5 | B11: Cocina general · platos y limpieza · esfuerzo moderado · [MET] | C11: 5035 | D11: 3.3 | E11: 1.5 | F11: =IF(AND(ISNUMBER($D11),ISNUMBER($E11)),$D11*$E11,0) -> 4.95 | H11: =IF(OR(DATOS!$H$10="FUERA_ALCANCE",DATOS!$H$10="BLOQUEADO_INESTABLE"),"FUERA DE ALCANCE",IF(DATOS!$H$10="COMPENDIUM_NO_DISPONIBLE_18","NO DISPONIBLE",IF(B11="","SIN ACTIVIDAD",IF(LEFT(B11,15)="(sin actividad)","SIN ACTIVIDAD",IF(OR(AND(DATOS!$H$10="ADULT2024_MET",NOT(ISNUMBER(FIND("[MET]",B11)))),AND(DATOS!$H$10="OLDER2024_MET60",NOT(ISNUMBER(FIND("[MET60+]",B11)))),AND(DATOS!$H$10="WHEELCHAIR2024_METWC",NOT(ISNUMBER(FIND("[METWC]",B11))))),"REQUIERE REVALIDACIÓN",IF(C11="","REQUIERE REVALIDACIÓN","OK")))))) -> REQUIERE REVALIDACIÓN
A12: 6 | B12: Subir escaleras · ritmo lento · [MET] | C12: 17133 | D12: 4.5 | E12: 0.5 | F12: =IF(AND(ISNUMBER($D12),ISNUMBER($E12)),$D12*$E12,0) -> 2.25 | H12: =IF(OR(DATOS!$H$10="FUERA_ALCANCE",DATOS!$H$10="BLOQUEADO_INESTABLE"),"FUERA DE ALCANCE",IF(DATOS!$H$10="COMPENDIUM_NO_DISPONIBLE_18","NO DISPONIBLE",IF(B12="","SIN ACTIVIDAD",IF(LEFT(B12,15)="(sin actividad)","SIN ACTIVIDAD",IF(OR(AND(DATOS!$H$10="ADULT2024_MET",NOT(ISNUMBER(FIND("[MET]",B12)))),AND(DATOS!$H$10="OLDER2024_MET60",NOT(ISNUMBER(FIND("[MET60+]",B12)))),AND(DATOS!$H$10="WHEELCHAIR2024_METWC",NOT(ISNUMBER(FIND("[METWC]",B12))))),"REQUIERE REVALIDACIÓN",IF(C12="","REQUIERE REVALIDACIÓN","OK")))))) -> REQUIERE REVALIDACIÓN
A13: 7 | B13: Barrer garaje, acera o exterior de la casa · [MET] | C13: 5140 | D13: 3 | E13: 0.5 | F13: =IF(AND(ISNUMBER($D13),ISNUMBER($E13)),$D13*$E13,0) -> 1.5 | H13: =IF(OR(DATOS!$H$10="FUERA_ALCANCE",DATOS!$H$10="BLOQUEADO_INESTABLE"),"FUERA DE ALCANCE",IF(DATOS!$H$10="COMPENDIUM_NO_DISPONIBLE_18","NO DISPONIBLE",IF(B13="","SIN ACTIVIDAD",IF(LEFT(B13,15)="(sin actividad)","SIN ACTIVIDAD",IF(OR(AND(DATOS!$H$10="ADULT2024_MET",NOT(ISNUMBER(FIND("[MET]",B13)))),AND(DATOS!$H$10="OLDER2024_MET60",NOT(ISNUMBER(FIND("[MET60+]",B13)))),AND(DATOS!$H$10="WHEELCHAIR2024_METWC",NOT(ISNUMBER(FIND("[METWC]",B13))))),"REQUIERE REVALIDACIÓN",IF(C13="","REQUIERE REVALIDACIÓN","OK")))))) -> REQUIERE REVALIDACIÓN
A14: 8 | B14: Pesas · varios ejercicios · 8–15 repeticiones · [MET] | C14: 2054 | D14: 3.5 | E14: 1 | F14: =IF(AND(ISNUMBER($D14),ISNUMBER($E14)),$D14*$E14,0) -> 3.5 | H14: =IF(OR(DATOS!$H$10="FUERA_ALCANCE",DATOS!$H$10="BLOQUEADO_INESTABLE"),"FUERA DE ALCANCE",IF(DATOS!$H$10="COMPENDIUM_NO_DISPONIBLE_18","NO DISPONIBLE",IF(B14="","SIN ACTIVIDAD",IF(LEFT(B14,15)="(sin actividad)","SIN ACTIVIDAD",IF(OR(AND(DATOS!$H$10="ADULT2024_MET",NOT(ISNUMBER(FIND("[MET]",B14)))),AND(DATOS!$H$10="OLDER2024_MET60",NOT(ISNUMBER(FIND("[MET60+]",B14)))),AND(DATOS!$H$10="WHEELCHAIR2024_METWC",NOT(ISNUMBER(FIND("[METWC]",B14))))),"REQUIERE REVALIDACIÓN",IF(C14="","REQUIERE REVALIDACIÓN","OK")))))) -> REQUIERE REVALIDACIÓN
A15: 9 | B15: Ver televisión sentado · [MET] | C15: 7020 | D15: 1 | E15: 0.5 | F15: =IF(AND(ISNUMBER($D15),ISNUMBER($E15)),$D15*$E15,0) -> 0.5 | H15: =IF(OR(DATOS!$H$10="FUERA_ALCANCE",DATOS!$H$10="BLOQUEADO_INESTABLE"),"FUERA DE ALCANCE",IF(DATOS!$H$10="COMPENDIUM_NO_DISPONIBLE_18","NO DISPONIBLE",IF(B15="","SIN ACTIVIDAD",IF(LEFT(B15,15)="(sin actividad)","SIN ACTIVIDAD",IF(OR(AND(DATOS!$H$10="ADULT2024_MET",NOT(ISNUMBER(FIND("[MET]",B15)))),AND(DATOS!$H$10="OLDER2024_MET60",NOT(ISNUMBER(FIND("[MET60+]",B15)))),AND(DATOS!$H$10="WHEELCHAIR2024_METWC",NOT(ISNUMBER(FIND("[METWC]",B15))))),"REQUIERE REVALIDACIÓN",IF(C15="","REQUIERE REVALIDACIÓN","OK")))))) -> REQUIERE REVALIDACIÓN
A16: 10 | B16: (sin actividad) · [MET] | C16: 0 | D16: 0 | E16: 0 | F16: =IF(AND(ISNUMBER($D16),ISNUMBER($E16)),$D16*$E16,0) -> 0 | H16: =IF(OR(DATOS!$H$10="FUERA_ALCANCE",DATOS!$H$10="BLOQUEADO_INESTABLE"),"FUERA DE ALCANCE",IF(DATOS!$H$10="COMPENDIUM_NO_DISPONIBLE_18","NO DISPONIBLE",IF(B16="","SIN ACTIVIDAD",IF(LEFT(B16,15)="(sin actividad)","SIN ACTIVIDAD",IF(OR(AND(DATOS!$H$10="ADULT2024_MET",NOT(ISNUMBER(FIND("[MET]",B16)))),AND(DATOS!$H$10="OLDER2024_MET60",NOT(ISNUMBER(FIND("[MET60+]",B16)))),AND(DATOS!$H$10="WHEELCHAIR2024_METWC",NOT(ISNUMBER(FIND("[METWC]",B16))))),"REQUIERE REVALIDACIÓN",IF(C16="","REQUIERE REVALIDACIÓN","OK")))))) -> SIN ACTIVIDAD
A17: 11 | B17: (sin actividad) · [MET] | C17: 0 | D17: 0 | E17: 0 | F17: =IF(AND(ISNUMBER($D17),ISNUMBER($E17)),$D17*$E17,0) -> 0 | H17: =IF(OR(DATOS!$H$10="FUERA_ALCANCE",DATOS!$H$10="BLOQUEADO_INESTABLE"),"FUERA DE ALCANCE",IF(DATOS!$H$10="COMPENDIUM_NO_DISPONIBLE_18","NO DISPONIBLE",IF(B17="","SIN ACTIVIDAD",IF(LEFT(B17,15)="(sin actividad)","SIN ACTIVIDAD",IF(OR(AND(DATOS!$H$10="ADULT2024_MET",NOT(ISNUMBER(FIND("[MET]",B17)))),AND(DATOS!$H$10="OLDER2024_MET60",NOT(ISNUMBER(FIND("[MET60+]",B17)))),AND(DATOS!$H$10="WHEELCHAIR2024_METWC",NOT(ISNUMBER(FIND("[METWC]",B17))))),"REQUIERE REVALIDACIÓN",IF(C17="","REQUIERE REVALIDACIÓN","OK")))))) -> SIN ACTIVIDAD
A18: 12 | B18: (sin actividad) · [MET] | C18: 0 | D18: 0 | E18: 0 | F18: =IF(AND(ISNUMBER($D18),ISNUMBER($E18)),$D18*$E18,0) -> 0 | H18: =IF(OR(DATOS!$H$10="FUERA_ALCANCE",DATOS!$H$10="BLOQUEADO_INESTABLE"),"FUERA DE ALCANCE",IF(DATOS!$H$10="COMPENDIUM_NO_DISPONIBLE_18","NO DISPONIBLE",IF(B18="","SIN ACTIVIDAD",IF(LEFT(B18,15)="(sin actividad)","SIN ACTIVIDAD",IF(OR(AND(DATOS!$H$10="ADULT2024_MET",NOT(ISNUMBER(FIND("[MET]",B18)))),AND(DATOS!$H$10="OLDER2024_MET60",NOT(ISNUMBER(FIND("[MET60+]",B18)))),AND(DATOS!$H$10="WHEELCHAIR2024_METWC",NOT(ISNUMBER(FIND("[METWC]",B18))))),"REQUIERE REVALIDACIÓN",IF(C18="","REQUIERE REVALIDACIÓN","OK")))))) -> SIN ACTIVIDAD
A19: CONVERSIÓN 24 H · UNIDAD × H → ENERGÍA → PAL ESTIMADO
A20: 1 · Total de horas registradas | B20: =SUM($E$7:$E$18) -> 24 | C20: h | D20: =IF(ABS($B$20-HORAS_DIA)<0.001,"OK · Registro de 24 h completo",IF($B$20<HORAS_DIA,"INCOMPLETO · faltan "&TEXT(HORAS_DIA-$B$20,"0.00")&" h","ERROR · sobran "&TEXT($B$20-HORAS_DIA,"0.00")&" h")) -> OK · Registro de 24 h completo
A21: ="2 · Σ ("&$F$4&" × horas)" -> 2 · Σ (METWC × horas) | B21: =SUM($F$7:$F$18) -> 43.3 | C21: =IF($F$4="—","—",$F$4&"·h/día") -> METWC·h/día | D21: Suma bruta del registro activo.
A22: ="3 · Índice "&$F$4&" medio = Σ / 24 ◄ NO ES EL PAL" -> 3 · Índice METWC medio = Σ / 24 ◄ NO ES EL PAL | B22: =IF($B$20=0,"ND",$B$21/HORAS_DIA) -> 1.8041667 | C22: — | D22: Referencia descriptiva del costo relativo medio; NO se usa como PAL.
A23: 4 · Peso del paciente | B23: =IF(OR(ISBLANK(in_Peso),NOT(ISNUMBER(in_Peso)),in_Peso<=0),"ND",in_Peso) -> 78 | C23: kg | D23: Desde DATOS.
A24: ="5 · Equivalente energético de 1 "&$F$4 -> 5 · Equivalente energético de 1 METWC | B24: =$F$5 -> 0.992 | C24: kcal/kg/h | D24: =IF($F$4="MET","Adult Compendium 2024: 1,000 kcal/kg/h.",IF($F$4="MET60+","Older Adult 2024: 0,810 kcal/kg/h (basal 2,7 mL O2/kg/min).",IF($F$4="METWC","Wheelchair 2024: 0,992 kcal/kg/h.","No aplicable."))) -> Wheelchair 2024: 0,992 kcal/kg/h.
A25: 6 · TEE estimado = Σ(unidad×h) × Peso × equivalente | B25: =IF(ABS($B$20-HORAS_DIA)>0.001,"NO CALCULADO · registro ≠ 24 h",IF(COUNTIF($H$7:$H$18,"REQUIERE REVALIDACIÓN")>0,"NO CALCULADO · revalidar actividades",IF(OR(DATOS!$H$10="FUERA_ALCANCE",DATOS!$H$10="BLOQUEADO_INESTABLE",DATOS!$H$10="COMPENDIUM_NO_DISPONIBLE_18"),"NO CALCULADO · módulo no aplicable",IF(AND(DATOS!$H$10="WHEELCHAIR2024_METWC",in_Edad>=CONFIG!$B$154),"NO CALCULADO · METWC ≥60 con evidencia etaria limitada",IF(OR(NOT(ISNUMBER(in_Peso)),in_Peso<=0,NOT(ISNUMBER($F$5)),$F$5<=0),"NO CALCULADO · datos insuficientes",SUM($F$7:$F$18)*in_Peso*$F$5))))) -> NO CALCULADO · revalidar actividades | C25: kcal/día | D25: Estimación Compendium; no equivale a calorimetría indirecta. En silla de ruedas ≥60 se bloquea por evidencia etaria limitada.
A26: 7 · GEB de la ecuación seleccionada | B26: =IF(ISNUMBER(ECUACIONES!$B$28),ECUACIONES!$B$28,"ND") -> 1709.2 | C26: kcal/día | D26: Desde ECUACIONES.
A27: 8 · PAL ESTIMADO DERIVADO DE COMPENDIUM = TEE / GEB | B27: =IF(NOT(ISNUMBER($B$25)),"NO CALCULADO",IF(OR(NOT(ISNUMBER($B$26)),$B$26<=0),"NO CALCULADO",$B$25/$B$26)) -> NO CALCULADO | C27: — | D27: APROXIMACIÓN · NO MEDICIÓN. No presentar como PAL exacto ni clínicamente validado.
A29: Advertencia metodológica: MET, MET60+ y METWC tienen referencias de reposo diferentes y NO son intercambiables. El promedio de unidad×h NO es PAL. Si cambia la edad 59→60 o la movilidad, vuelva a seleccionar las actividades; las etiquetas incluyen la unidad para impedir una migración silenciosa.
A30: Fuentes 2024: Herrmann et al. Adult Compendium (19–59); Willis et al. Older Adult Compendium (≥60; MET60+); Conger et al. Wheelchair Compendium (METWC). Ver FUENTES y las hojas BASE_MET_* para códigos, valores y URLs oficiales.

Sheet FUENTES
A1: FUENTES · Trazabilidad y nivel de verificación · DEFINITIVO 2026 · NMX-ACT-2024-v1
A2: Fecha de cotejo: 2026-07-12, contra el 'Dossier de verificación bibliográfica y metodológica NMX-01 v1.1'. NIVEL A = publicación primaria con texto completo o documento institucional oficial · NIVEL B = resumen primario exacto y/o corroboración consistente en literatura revisada por pares · NIVEL C = depende de fuentes secundarias. EXACTITUD BIBLIOGRÁFICA ≠ VALIDACIÓN CLÍNICA.
A4: =HYPERLINK("#INICIO!A1","◀ INICIO") -> ◀ INICIO
A5: Ecuación o dato | B5: Autor u organización | C5: Año | D5: Población de derivación | E5: Fórmula / valor | F5: Unidades | G5: Limitaciones | H5: DOI o URL | I5: Fecha de cotejo | J5: Licencia / condiciones | K5: Nivel | L5: Estado de verificación · cambios en v1.1
A6: Mifflin–St Jeor (E1) | B6: Mifflin MD, St Jeor ST, Hill LA, Scott BJ, Daugherty SA, Koh YO — Am J Clin Nutr 51:241-247 | C6: 1990 | D6: 498 adultos sanos de EE. UU. (247 mujeres, 251 hombres), 19–78 años, de IMC normal a obesidad | E6: H: 10·P + 6,25·T − 5·E + 5 · M: 10·P + 6,25·T − 5·E − 161 | F6: P kg; T cm; E años; kcal/día | G6: Derivada en población estadounidense. Menor precisión en deportistas y obesidad extrema. | H6: 10.1093/ajcn/51.2.241 | I6: 2026-07-12 | J6: Artículo con derechos de autor. Solo se usa la ECUACIÓN (hecho no protegible). | K6: B | L6: SIN CAMBIO NUMÉRICO. El resumen primario contiene la fórmula exacta; texto completo no inspeccionado.
A7: Harris–Benedict revisada (E2) | B7: Roza AM, Shizgal HM — Am J Clin Nutr 40:168-182 | C7: 1984 | D7: 337 adultos (168 hombres, 169 mujeres); reanálisis de la base de Harris y Benedict | E7: H: 88,362 + 13,397·P + 4,799·T − 5,677·E · M: 447,593 + 9,247·P + 3,098·T − 4,330·E | F7: P kg; T cm; E años; kcal/día | G7: El rango exacto de edad de la muestra no se especifica con precisión. | H7: 10.1093/ajcn/40.1.168 | I7: 2026-07-12 | J7: Artículo con derechos de autor. Solo se usa la ecuación. | K7: A | L7: SIN CAMBIO NUMÉRICO. SUBE de nivel: el dossier confirma el cotejo contra el PDF primario (tabla 3).
A8: Owen (E3) | B8: Owen OE, Kavle E, Owen RS et al. (mujeres 1986) · Owen OE, Holup JL, D'Alessio DA et al. (hombres 1987) — Am J Clin Nutr | C8: 1986/1987 | D8: 44 mujeres (8 atletas) y 60 hombres, 18–82 años, 43–171 kg; calorimetría indirecta | E8: H: 879 + 10,2·P · M: 795 + 7,18·P | F8: P kg; kcal/día | G8: Solo usa el peso. Owen publicó una recta APARTE para mujeres atletas (50,4 + 21,1·P) que NO se incluye aquí. | H8: 10.1093/ajcn/44.1.1 · 10.1093/ajcn/46.6.875 | I8: 2026-07-12 | J8: Artículo con derechos de autor. Solo se usa la ecuación. | K8: B | L8: SIN CAMBIO NUMÉRICO. Corroborada en literatura revisada por pares; texto completo tras acceso editorial.
A9: Cunningham 1980 (E4) | B9: Cunningham JJ — Am J Clin Nutr 33:2372-2374 | C9: 1980 | D9: Reanálisis de la base de Harris–Benedict; la MLG resultó el único predictor relevante | E9: TMB = 500 + 22 · MLG | F9: MLG kg; kcal/día | G9: Exige una MLG fiable: el resultado hereda por completo el error del método de composición corporal. | H9: 10.1093/ajcn/33.11.2372 | I9: 2026-07-12 | J9: Artículo con derechos de autor. Solo se usa la ecuación. | K9: A | L9: SIN CAMBIO NUMÉRICO. SUBE de nivel: PDF primario accesible. Es una ecuación DISTINTA de Cunningham 1991.
A10: Cunningham 1991 (E5) · alias secundario: Katch–McArdle | B10: Cunningham JJ. Body composition as a determinant of energy expenditure — Am J Clin Nutr 54:963-969 | C10: 1991 | D10: Revisión sintética con ecuación general propuesta a partir de la masa libre de grasa | E10: REE = 370 + 21,6 · FFM | F10: FFM (MLG) kg; kcal/día | G10: El alias 'Katch–McArdle' proviene de libros de texto (nivel C) y NO de una publicación primaria de esos autores. La fórmula es la misma; la atribución cambia. | H10: 10.1093/ajcn/54.6.963 | I10: 2026-07-12 | J10: Artículo con derechos de autor. Solo se usa la ecuación. El alias es de uso didáctico. | K10: B | L10: ⚑ CORRECCIÓN P0 EN v1.1. La v1.0 atribuía esta fórmula a McArdle/Katch/Katch (libro) y la declaraba NO VERIFICADA. Fuente primaria correcta: Cunningham 1991. SIN CAMBIO NUMÉRICO: los coeficientes 370 y 21,6 se mantienen.
A11: Schofield adultos (E6) · tabla canónica | B11: Schofield WN — Hum Nutr Clin Nutr 39 Suppl 1:5-41 | C11: 1985 | D11: Metaanálisis de ~11.000 mediciones de TMB. Este libro usa solo las bandas adultas 18–30 / 30–60 / ≥60 | E11: H: 15,057·P+692,2 | 11,472·P+873,1 | 11,711·P+587,7 · M: 14,818·P+486,6 | 8,126·P+845,6 | 9,082·P+658,5 | F11: P kg; kcal/día (convertidos desde MJ/día × 239,0057) | G11: Sobrerrepresentación de sujetos italianos; sobrestima la TMB en poblaciones tropicales. Henry (2005) propuso su reemplazo. | H11: Hum Nutr Clin Nutr 1985;39 Suppl 1:5-41 | I11: 2026-07-12 | J11: Publicación con derechos de autor. Solo se usan los coeficientes. | K11: B | L11: ⚑ CAMBIO NUMÉRICO EN v1.1. La v1.0 usaba la tabla FAO/WHO/UNU REDONDEADA en kcal (15,3·P+679 …), que NO es la misma. Se congela una tabla canónica única derivada de MJ/día. La tabla antigua queda documentada en CONFIG C9b, desconectada del motor.
A12: Henry / Oxford (E7) | B12: Henry CJK — Public Health Nutr 8(7A):1133-1152 | C12: 2005 | D12: 10.552 valores de TMB; excluye la sobrerrepresentación italiana de Schofield e incorpora más datos de zonas tropicales | E12: H: 16,0·P+545 | 14,2·P+593 | 13,5·P+514 · M: 13,1·P+558 | 9,74·P+694 | 10,1·P+569 | F12: P kg; kcal/día (el artículo publica también la tabla en MJ/día) | G12: Solo peso: el propio análisis informó que añadir la talla no mejora significativamente la predicción media. No aplicar las bandas adultas a menores de 18 años. | H12: 10.1079/PHN2005801 | I12: 2026-07-12 | J12: Artículo con derechos de autor. Solo se usan los coeficientes. | K12: A | L12: ⚑ NUEVA EN v1.1. La v1.0 la omitió por no poder verificar los coeficientes. El dossier los aporta (tabla 12). La tabla en kcal es una conversión REDONDEADA de la tabla en MJ: difieren hasta ~4,64 kcal (0,315 %) en el rango de pesos probado. PRUEBAS lo contrasta con una tolerancia RELATIVA del 1 %.
A13: PAL · clasificación canónica · GAF · ETA | B13: FAO/WHO/UNU — Human Energy Requirements, FAO Food and Nutrition Technical Report Series No. 1 | C13: 2004 | D13: Consulta de expertos; §5.1, §5.3.1 (Tabla 5.3) y §5.3.2 | E13: PAL = TEE/BMR; GET = GEB × PAL. Rangos adultos: 1,40–1,69 · 1,70–1,99 · 2,00–2,40 | F13: PAL adimensional; kcal/día | G13: FAO usa rangos, no un factor único por categoría. El PAL representa el patrón habitual global y no debe asignarse solo por ocupación. Con GET = GEB×PAL, sumar ETA otra vez implica doble conteo. | H13: https://www.fao.org/4/y5686e/y5686e07.htm | I13: 2026-08-08 | J13: Documento oficial FAO de acceso público. | K13: A | L13: ACTUALIZADO NMX-PAL-2026-08-v1: se separan los rangos canónicos FAO de los factores puntuales del selector práctico.
A14: Compendium 2011 · antecedente histórico | B14: Ainsworth BE, Haskell WL, Herrmann SD et al. — Med Sci Sports Exerc 43:1575-1581 | C14: 2011 | D14: Adultos; versión previa del Compendium | E14: Valores/códigos 2011 conservados solo para trazabilidad histórica | F14: MET | G14: NO es la fuente maestra del motor NMX-ACT-2024-v1. Los códigos/valores activos se cotejan contra 2024. | H14: 10.1249/MSS.0b013e31821ece12 · https://pacompendium.com/ | I14: 2026-08-08 | J14: Uso sujeto a condiciones del Compendium; citar y no alterar valores. | K14: A | L14: HISTÓRICO. Reemplazado como fuente maestra por las tres ramas 2024.
A15: Efecto térmico de los alimentos | B15: Westerterp KR — Nutr Metab (Lond) 1:5 | C15: 2004 | D15: Revisión sobre termogénesis inducida por la dieta en adultos | E15: TID ≈ 5–15 % del gasto diario en dieta mixta y equilibrio energético | F15: % de la energía | G15: El rango sirve para EXPLICAR la magnitud, no para justificar sumarla aparte cuando ya se usa un PAL. | H15: 10.1186/1743-7075-1-5 | I15: 2026-07-12 | J15: Acceso abierto (BioMed Central). | K15: A | L15: ⚑ CORREGIDO EN v1.1: la v1.0 decía '≈10 %'. El rango correcto es 5–15 %.
A16: Factores generales de Atwater | B16: Merrill AL, Watt BK — Energy Value of Foods: Basis and Derivation. USDA Agriculture Handbook 74 | C16: 1973 | D16: Documento institucional del USDA sobre factores generales y específicos | E16: Proteína 4 kcal/g · Carbohidratos 4 kcal/g · Grasa 9 kcal/g | F16: kcal/g | G16: Son factores GENERALES. Existen factores específicos por alimento que este libro NO aplica: se declara explícitamente. | H16: USDA Agriculture Handbook No. 74 (1973) | I16: 2026-07-12 | J16: Documento institucional de dominio público (obra del gobierno de EE. UU.). | K16: A | L16: SIN CAMBIO NUMÉRICO. Se sustituye la cita a FAO FNP 77 por la fuente institucional primaria indicada en el dossier.
A17: Selector PAL práctico · NMX-PAL-2026-08-v1 | B17: FoodWorks.online Learning and Support — Physical Activity Levels (PAL) explained | C17: 2026 | D17: Escala operacional para comparar el patrón medio de actividad diaria con descripciones y ocupaciones de ejemplo | E17: PAL 1,2 · 1,4 · 1,5 · 1,6 · 1,7 · 1,8 · 2,0 · 2,2 | F17: PAL adimensional | G17: FUENTE SECUNDARIA OPERACIONAL. Los factores puntuales facilitan la selección, pero no reemplazan la clasificación/rangos de FAO. PAL 1,20 queda fuera del selector general. | H17: https://support.foodworks.online/hc/en-au/articles/360004401336-Physical-Activity-Levels-PAL-explained | I17: 2026-08-08 | J17: Página web de soporte; actualización indicada por la fuente: 20-07-2026. Verificar cambios futuros. | K17: C | L17: NUEVO NMX-PAL-2026-08-v1. Se usa solo como selector práctico y para ejemplos de ocupación/estilo de vida; fuente canónica de categorías y rangos: FAO/WHO/UNU 2004.
A18: PENDIENTES DE VERIFICACIÓN PRIMARIA (nivel B): Mifflin–St Jeor, Owen, Cunningham 1991 y Schofield. Para estos se conserva el estado documental previo del libro. Los códigos Compendium 17190 y 11210 fueron revalidados contra la edición oficial 2024 en NMX-ACT-2024-v1; 11210 corresponde a ordeño manual / limpieza de baldes, esfuerzo moderado, no a carga pesada.
A19: Valores MET · adultos 19–59 | B19: Herrmann SD, Willis EA, Ainsworth BE, Barreira TV, Hastert M, Kracht CL, Schuna JM Jr, Cai Z, Quan M, Tudor-Locke C, Whitt-Glover MC, Jacobs DR Jr. | C19: 2024 | D19: Adultos 19–59 años; no discapacitados y sin condiciones significativas que alteren EE/metabolismo | E19: 2024 Adult Compendium · 1114 actividades; MET estándar. 1 MET = 1,000 kcal/kg/h ≈ 3,5 mL O₂/kg/min. | F19: MET; kcal/kg/h | G19: Valores poblacionales/estandarizados; no equivalen a medición individual. Embarazo y condiciones que alteran EE quedan fuera del alcance. | H19: 10.1016/j.jshs.2023.10.010 · https://pacompendium.com/adult-compendium/ | I19: 2026-08-08 | J19: Compendium: uso educacional/comercial permitido; no alterar MET ni combinar actividades de distinta intensidad; citar. | K19: A | L19: FUENTE MAESTRA NMX-ACT-2024-v1 para 19–59 años.
A20: Valores MET60+ · adultos mayores | B20: Willis EA, Herrmann SD, Hastert M, Kracht CL, Barreira TV, Schuna JM Jr, Cai Z, Quan M, Conger SA, Brown WJ, Ainsworth BE. | C20: 2024 | D20: Adultos ≥60 años | E20: Older Adult Compendium · MET60+ con baseline 2,7 mL O₂/kg/min; conversión documentada 0,810 kcal/kg/h. | F20: MET60+; kcal/kg/h | G20: No tratar MET60+ como MET estándar. Usar catálogo y códigos específicos de Older Adult Compendium. | H20: 10.1016/j.jshs.2023.10.007 · https://pacompendium.com/older-adult-compendium/ | I20: 2026-08-08 | J20: Compendium: uso educacional/comercial permitido; citar y no alterar valores. | K20: A | L20: FUENTE MAESTRA NMX-ACT-2024-v1 para ≥60 años ambulantes.
A21: Valores METWC · usuarios de silla de ruedas | B21: Conger SA, Herrmann SD, Willis EA, Nightingale TE, Sherman JR, Ainsworth BE. | C21: 2024 | D21: Adultos usuarios de silla de ruedas; evidencia publicada predominantemente en adultos jóvenes/mediana edad | E21: Wheelchair Compendium · METWC; baseline 0,992 kcal/kg/h. | F21: METWC; kcal/kg/h | G21: No mezclar METWC con MET o MET60+. La publicación advierte cautela al extrapolar a adultos mayores; NMX-01 bloquea PAL automático en silla de ruedas ≥60. | H21: 10.1016/j.jshs.2023.11.003 · https://pacompendium.com/adult-wheelchair-users-compendium/ | I21: 2026-08-08 | J21: Compendium: uso educacional/comercial permitido; citar y no alterar valores. | K21: A | L21: FUENTE MAESTRA NMX-ACT-2024-v1 para adultos usuarios de silla de ruedas; ≥60 con advertencia/limitación.
A22: Conversión energética 2024 · comparación de Compendia | B22: Herrmann SD, Conger SA, Willis EA, Ainsworth BE — Journal of Sport and Health Science | C22: 2024 | D22: Adultos, adultos mayores y usuarios de silla de ruedas | E22: Adult MET→kcal: MET×kg×h; METWC→kcal: METWC×0,992×kg×h; MET60+→kcal: MET60+×0,810×kg×h. | F22: kcal | G22: Ejemplos de conversión; siguen siendo estimaciones del Compendium, no calorimetría. | H22: 10.1016/j.jshs.2024.05.013 · https://pacompendium.com/compendium-calculator/ | I22: 2026-08-08 | J22: Artículo académico + calculadora oficial del Compendium. | K22: A | L22: SOPORTE DE CONVERSIÓN para parámetros EQUIV_MET_*.

Sheet PRUEBAS
A1: PRUEBAS · Banco de verificación · DEFINITIVO 2026
A2: REGLA DEL DOSSIER: el valor ESPERADO nunca lee la tabla CONFIG que usa el motor. O bien está fijado a partir del cálculo literal de la fuente primaria, o bien se reconstruye con una fórmula que escribe los coeficientes publicados de forma explícita. Así, si alguien corrompe un coeficiente de CONFIG, estas pruebas FALLAN.
A4: =HYPERLINK("#INICIO!A1","◀ INICIO") -> ◀ INICIO
A6: BLOQUE A · EXACTITUD DE LAS 7 ECUACIONES (tolerancia ±0,5 kcal)
A7: ID | B7: Descripción | C7: Sexo | D7: Ec. | E7: Edad | F7: Peso (kg) | G7: Estatura (cm) | H7: % grasa | I7: MLG (kg) | J7: a | K7: b_peso | L7: b_est | M7: b_edad | N7: b_MLG | O7: Obtenido (kcal) | P7: Esperado (kcal) | Q7: Diferencia | R7: Estado
A8: A01 | B8: Adulto normal 1 · Mifflin–St Jeor | C8: Hombre | D8: E1 | E8: 30 | F8: 70 | G8: 175 | I8: =IF(ISBLANK($H8),0,$F8*(1-$H8)) -> 0 | J8: =IF($D8="E6",SUMPRODUCT((CONFIG!$A$92:$A$97=$C8)*(CONFIG!$B$92:$B$97<=$E8)*(CONFIG!$C$92:$C$97>$E8)*CONFIG!$E$92:$E$97),SUMIFS(CONFIG!$D$79:$D$88,CONFIG!$A$79:$A$88,$D8,CONFIG!$C$79:$C$88,$C8)) -> 5 | K8: =IF($D8="E6",SUMPRODUCT((CONFIG!$A$92:$A$97=$C8)*(CONFIG!$B$92:$B$97<=$E8)*(CONFIG!$C$92:$C$97>$E8)*CONFIG!$D$92:$D$97),SUMIFS(CONFIG!$E$79:$E$88,CONFIG!$A$79:$A$88,$D8,CONFIG!$C$79:$C$88,$C8)) -> 10 | L8: =IF($D8="E6",0,SUMIFS(CONFIG!$F$79:$F$88,CONFIG!$A$79:$A$88,$D8,CONFIG!$C$79:$C$88,$C8)) -> 6.25 | M8: =IF($D8="E6",0,SUMIFS(CONFIG!$G$79:$G$88,CONFIG!$A$79:$A$88,$D8,CONFIG!$C$79:$C$88,$C8)) -> -5 | N8: =IF($D8="E6",0,SUMIFS(CONFIG!$H$79:$H$88,CONFIG!$A$79:$A$88,$D8,CONFIG!$C$79:$C$88,$C8)) -> 0 | O8: =$J8+$K8*IF(ISNUMBER($F8),$F8,0)+$L8*IF(ISNUMBER($G8),$G8,0)+$M8*IF(ISNUMBER($E8),$E8,0)+$N8*IF(ISNUMBER($I8),$I8,0) -> 1648.75 | P8: 1648.75 | Q8: =$O8-$P8 -> 0 | R8: =IF(ABS($Q8)<=0.5,"APROBADO","FALLIDO") -> APROBADO
A9: A02 | B9: Adulto normal 2 · Mifflin–St Jeor | C9: Mujer | D9: E1 | E9: 45 | F9: 62 | G9: 162 | I9: =IF(ISBLANK($H9),0,$F9*(1-$H9)) -> 0 | J9: =IF($D9="E6",SUMPRODUCT((CONFIG!$A$92:$A$97=$C9)*(CONFIG!$B$92:$B$97<=$E9)*(CONFIG!$C$92:$C$97>$E9)*CONFIG!$E$92:$E$97),SUMIFS(CONFIG!$D$79:$D$88,CONFIG!$A$79:$A$88,$D9,CONFIG!$C$79:$C$88,$C9)) -> -161 | K9: =IF($D9="E6",SUMPRODUCT((CONFIG!$A$92:$A$97=$C9)*(CONFIG!$B$92:$B$97<=$E9)*(CONFIG!$C$92:$C$97>$E9)*CONFIG!$D$92:$D$97),SUMIFS(CONFIG!$E$79:$E$88,CONFIG!$A$79:$A$88,$D9,CONFIG!$C$79:$C$88,$C9)) -> 10 | L9: =IF($D9="E6",0,SUMIFS(CONFIG!$F$79:$F$88,CONFIG!$A$79:$A$88,$D9,CONFIG!$C$79:$C$88,$C9)) -> 6.25 | M9: =IF($D9="E6",0,SUMIFS(CONFIG!$G$79:$G$88,CONFIG!$A$79:$A$88,$D9,CONFIG!$C$79:$C$88,$C9)) -> -5 | N9: =IF($D9="E6",0,SUMIFS(CONFIG!$H$79:$H$88,CONFIG!$A$79:$A$88,$D9,CONFIG!$C$79:$C$88,$C9)) -> 0 | O9: =$J9+$K9*IF(ISNUMBER($F9),$F9,0)+$L9*IF(ISNUMBER($G9),$G9,0)+$M9*IF(ISNUMBER($E9),$E9,0)+$N9*IF(ISNUMBER($I9),$I9,0) -> 1246.5 | P9: 1246.5 | Q9: =$O9-$P9 -> 0 | R9: =IF(ABS($Q9)<=0.5,"APROBADO","FALLIDO") -> APROBADO
A10: A03 | B10: Adulto normal 3 · Harris–Benedict revisada | C10: Hombre | D10: E2 | E10: 55 | F10: 85 | G10: 180 | I10: =IF(ISBLANK($H10),0,$F10*(1-$H10)) -> 0 | J10: =IF($D10="E6",SUMPRODUCT((CONFIG!$A$92:$A$97=$C10)*(CONFIG!$B$92:$B$97<=$E10)*(CONFIG!$C$92:$C$97>$E10)*CONFIG!$E$92:$E$97),SUMIFS(CONFIG!$D$79:$D$88,CONFIG!$A$79:$A$88,$D10,CONFIG!$C$79:$C$88,$C10)) -> 88.362 | K10: =IF($D10="E6",SUMPRODUCT((CONFIG!$A$92:$A$97=$C10)*(CONFIG!$B$92:$B$97<=$E10)*(CONFIG!$C$92:$C$97>$E10)*CONFIG!$D$92:$D$97),SUMIFS(CONFIG!$E$79:$E$88,CONFIG!$A$79:$A$88,$D10,CONFIG!$C$79:$C$88,$C10)) -> 13.397 | L10: =IF($D10="E6",0,SUMIFS(CONFIG!$F$79:$F$88,CONFIG!$A$79:$A$88,$D10,CONFIG!$C$79:$C$88,$C10)) -> 4.799 | M10: =IF($D10="E6",0,SUMIFS(CONFIG!$G$79:$G$88,CONFIG!$A$79:$A$88,$D10,CONFIG!$C$79:$C$88,$C10)) -> -5.677 | N10: =IF($D10="E6",0,SUMIFS(CONFIG!$H$79:$H$88,CONFIG!$A$79:$A$88,$D10,CONFIG!$C$79:$C$88,$C10)) -> 0 | O10: =$J10+$K10*IF(ISNUMBER($F10),$F10,0)+$L10*IF(ISNUMBER($G10),$G10,0)+$M10*IF(ISNUMBER($E10),$E10,0)+$N10*IF(ISNUMBER($I10),$I10,0) -> 1778.692 | P10: 1778.692 | Q10: =$O10-$P10 -> 0 | R10: =IF(ABS($Q10)<=0.5,"APROBADO","FALLIDO") -> APROBADO
A11: A04 | B11: Harris–Benedict revisada · mujer | C11: Mujer | D11: E2 | E11: 38 | F11: 58 | G11: 160 | I11: =IF(ISBLANK($H11),0,$F11*(1-$H11)) -> 0 | J11: =IF($D11="E6",SUMPRODUCT((CONFIG!$A$92:$A$97=$C11)*(CONFIG!$B$92:$B$97<=$E11)*(CONFIG!$C$92:$C$97>$E11)*CONFIG!$E$92:$E$97),SUMIFS(CONFIG!$D$79:$D$88,CONFIG!$A$79:$A$88,$D11,CONFIG!$C$79:$C$88,$C11)) -> 447.593 | K11: =IF($D11="E6",SUMPRODUCT((CONFIG!$A$92:$A$97=$C11)*(CONFIG!$B$92:$B$97<=$E11)*(CONFIG!$C$92:$C$97>$E11)*CONFIG!$D$92:$D$97),SUMIFS(CONFIG!$E$79:$E$88,CONFIG!$A$79:$A$88,$D11,CONFIG!$C$79:$C$88,$C11)) -> 9.247 | L11: =IF($D11="E6",0,SUMIFS(CONFIG!$F$79:$F$88,CONFIG!$A$79:$A$88,$D11,CONFIG!$C$79:$C$88,$C11)) -> 3.098 | M11: =IF($D11="E6",0,SUMIFS(CONFIG!$G$79:$G$88,CONFIG!$A$79:$A$88,$D11,CONFIG!$C$79:$C$88,$C11)) -> -4.33 | N11: =IF($D11="E6",0,SUMIFS(CONFIG!$H$79:$H$88,CONFIG!$A$79:$A$88,$D11,CONFIG!$C$79:$C$88,$C11)) -> 0 | O11: =$J11+$K11*IF(ISNUMBER($F11),$F11,0)+$L11*IF(ISNUMBER($G11),$G11,0)+$M11*IF(ISNUMBER($E11),$E11,0)+$N11*IF(ISNUMBER($I11),$I11,0) -> 1315.059 | P11: 1315.059 | Q11: =$O11-$P11 -> 0 | R11: =IF(ABS($Q11)<=0.5,"APROBADO","FALLIDO") -> APROBADO
A12: A05 | B12: Owen · hombre con obesidad | C12: Hombre | D12: E3 | E12: 50 | F12: 105 | G12: 172 | I12: =IF(ISBLANK($H12),0,$F12*(1-$H12)) -> 0 | J12: =IF($D12="E6",SUMPRODUCT((CONFIG!$A$92:$A$97=$C12)*(CONFIG!$B$92:$B$97<=$E12)*(CONFIG!$C$92:$C$97>$E12)*CONFIG!$E$92:$E$97),SUMIFS(CONFIG!$D$79:$D$88,CONFIG!$A$79:$A$88,$D12,CONFIG!$C$79:$C$88,$C12)) -> 879 | K12: =IF($D12="E6",SUMPRODUCT((CONFIG!$A$92:$A$97=$C12)*(CONFIG!$B$92:$B$97<=$E12)*(CONFIG!$C$92:$C$97>$E12)*CONFIG!$D$92:$D$97),SUMIFS(CONFIG!$E$79:$E$88,CONFIG!$A$79:$A$88,$D12,CONFIG!$C$79:$C$88,$C12)) -> 10.2 | L12: =IF($D12="E6",0,SUMIFS(CONFIG!$F$79:$F$88,CONFIG!$A$79:$A$88,$D12,CONFIG!$C$79:$C$88,$C12)) -> 0 | M12: =IF($D12="E6",0,SUMIFS(CONFIG!$G$79:$G$88,CONFIG!$A$79:$A$88,$D12,CONFIG!$C$79:$C$88,$C12)) -> 0 | N12: =IF($D12="E6",0,SUMIFS(CONFIG!$H$79:$H$88,CONFIG!$A$79:$A$88,$D12,CONFIG!$C$79:$C$88,$C12)) -> 0 | O12: =$J12+$K12*IF(ISNUMBER($F12),$F12,0)+$L12*IF(ISNUMBER($G12),$G12,0)+$M12*IF(ISNUMBER($E12),$E12,0)+$N12*IF(ISNUMBER($I12),$I12,0) -> 1950 | P12: 1950 | Q12: =$O12-$P12 -> 0 | R12: =IF(ABS($Q12)<=0.5,"APROBADO","FALLIDO") -> APROBADO
A13: A06 | B13: Owen · mujer mayor | C13: Mujer | D13: E3 | E13: 68 | F13: 70 | G13: 156 | I13: =IF(ISBLANK($H13),0,$F13*(1-$H13)) -> 0 | J13: =IF($D13="E6",SUMPRODUCT((CONFIG!$A$92:$A$97=$C13)*(CONFIG!$B$92:$B$97<=$E13)*(CONFIG!$C$92:$C$97>$E13)*CONFIG!$E$92:$E$97),SUMIFS(CONFIG!$D$79:$D$88,CONFIG!$A$79:$A$88,$D13,CONFIG!$C$79:$C$88,$C13)) -> 795 | K13: =IF($D13="E6",SUMPRODUCT((CONFIG!$A$92:$A$97=$C13)*(CONFIG!$B$92:$B$97<=$E13)*(CONFIG!$C$92:$C$97>$E13)*CONFIG!$D$92:$D$97),SUMIFS(CONFIG!$E$79:$E$88,CONFIG!$A$79:$A$88,$D13,CONFIG!$C$79:$C$88,$C13)) -> 7.18 | L13: =IF($D13="E6",0,SUMIFS(CONFIG!$F$79:$F$88,CONFIG!$A$79:$A$88,$D13,CONFIG!$C$79:$C$88,$C13)) -> 0 | M13: =IF($D13="E6",0,SUMIFS(CONFIG!$G$79:$G$88,CONFIG!$A$79:$A$88,$D13,CONFIG!$C$79:$C$88,$C13)) -> 0 | N13: =IF($D13="E6",0,SUMIFS(CONFIG!$H$79:$H$88,CONFIG!$A$79:$A$88,$D13,CONFIG!$C$79:$C$88,$C13)) -> 0 | O13: =$J13+$K13*IF(ISNUMBER($F13),$F13,0)+$L13*IF(ISNUMBER($G13),$G13,0)+$M13*IF(ISNUMBER($E13),$E13,0)+$N13*IF(ISNUMBER($I13),$I13,0) -> 1297.6 | P13: 1297.6 | Q13: =$O13-$P13 -> 0 | R13: =IF(ABS($Q13)<=0.5,"APROBADO","FALLIDO") -> APROBADO
A14: A07 | B14: CON % de grasa · Cunningham 1980 | C14: Hombre | D14: E4 | E14: 28 | F14: 80 | G14: 178 | H14: 0.15 | I14: =IF(ISBLANK($H14),0,$F14*(1-$H14)) -> 68 | J14: =IF($D14="E6",SUMPRODUCT((CONFIG!$A$92:$A$97=$C14)*(CONFIG!$B$92:$B$97<=$E14)*(CONFIG!$C$92:$C$97>$E14)*CONFIG!$E$92:$E$97),SUMIFS(CONFIG!$D$79:$D$88,CONFIG!$A$79:$A$88,$D14,CONFIG!$C$79:$C$88,$C14)) -> 500 | K14: =IF($D14="E6",SUMPRODUCT((CONFIG!$A$92:$A$97=$C14)*(CONFIG!$B$92:$B$97<=$E14)*(CONFIG!$C$92:$C$97>$E14)*CONFIG!$D$92:$D$97),SUMIFS(CONFIG!$E$79:$E$88,CONFIG!$A$79:$A$88,$D14,CONFIG!$C$79:$C$88,$C14)) -> 0 | L14: =IF($D14="E6",0,SUMIFS(CONFIG!$F$79:$F$88,CONFIG!$A$79:$A$88,$D14,CONFIG!$C$79:$C$88,$C14)) -> 0 | M14: =IF($D14="E6",0,SUMIFS(CONFIG!$G$79:$G$88,CONFIG!$A$79:$A$88,$D14,CONFIG!$C$79:$C$88,$C14)) -> 0 | N14: =IF($D14="E6",0,SUMIFS(CONFIG!$H$79:$H$88,CONFIG!$A$79:$A$88,$D14,CONFIG!$C$79:$C$88,$C14)) -> 22 | O14: =$J14+$K14*IF(ISNUMBER($F14),$F14,0)+$L14*IF(ISNUMBER($G14),$G14,0)+$M14*IF(ISNUMBER($E14),$E14,0)+$N14*IF(ISNUMBER($I14),$I14,0) -> 1996 | P14: 1996 | Q14: =$O14-$P14 -> 0 | R14: =IF(ABS($Q14)<=0.5,"APROBADO","FALLIDO") -> APROBADO
A15: A08 | B15: CON % de grasa · Cunningham 1991 (alias Katch–McArdle) | C15: Mujer | D15: E5 | E15: 32 | F15: 62 | G15: 165 | H15: 0.26 | I15: =IF(ISBLANK($H15),0,$F15*(1-$H15)) -> 45.88 | J15: =IF($D15="E6",SUMPRODUCT((CONFIG!$A$92:$A$97=$C15)*(CONFIG!$B$92:$B$97<=$E15)*(CONFIG!$C$92:$C$97>$E15)*CONFIG!$E$92:$E$97),SUMIFS(CONFIG!$D$79:$D$88,CONFIG!$A$79:$A$88,$D15,CONFIG!$C$79:$C$88,$C15)) -> 370 | K15: =IF($D15="E6",SUMPRODUCT((CONFIG!$A$92:$A$97=$C15)*(CONFIG!$B$92:$B$97<=$E15)*(CONFIG!$C$92:$C$97>$E15)*CONFIG!$D$92:$D$97),SUMIFS(CONFIG!$E$79:$E$88,CONFIG!$A$79:$A$88,$D15,CONFIG!$C$79:$C$88,$C15)) -> 0 | L15: =IF($D15="E6",0,SUMIFS(CONFIG!$F$79:$F$88,CONFIG!$A$79:$A$88,$D15,CONFIG!$C$79:$C$88,$C15)) -> 0 | M15: =IF($D15="E6",0,SUMIFS(CONFIG!$G$79:$G$88,CONFIG!$A$79:$A$88,$D15,CONFIG!$C$79:$C$88,$C15)) -> 0 | N15: =IF($D15="E6",0,SUMIFS(CONFIG!$H$79:$H$88,CONFIG!$A$79:$A$88,$D15,CONFIG!$C$79:$C$88,$C15)) -> 21.6 | O15: =$J15+$K15*IF(ISNUMBER($F15),$F15,0)+$L15*IF(ISNUMBER($G15),$G15,0)+$M15*IF(ISNUMBER($E15),$E15,0)+$N15*IF(ISNUMBER($I15),$I15,0) -> 1361.008 | P15: 1361.008 | Q15: =$O15-$P15 -> 0 | R15: =IF(ABS($Q15)<=0.5,"APROBADO","FALLIDO") -> APROBADO
A16: A09 | B16: SIN % de grasa · Schofield canónica, banda 30–60 | C16: Hombre | D16: E6 | E16: 40 | F16: 90 | G16: 175 | I16: =IF(ISBLANK($H16),0,$F16*(1-$H16)) -> 0 | J16: =IF($D16="E6",SUMPRODUCT((CONFIG!$A$92:$A$97=$C16)*(CONFIG!$B$92:$B$97<=$E16)*(CONFIG!$C$92:$C$97>$E16)*CONFIG!$E$92:$E$97),SUMIFS(CONFIG!$D$79:$D$88,CONFIG!$A$79:$A$88,$D16,CONFIG!$C$79:$C$88,$C16)) -> 873.1 | K16: =IF($D16="E6",SUMPRODUCT((CONFIG!$A$92:$A$97=$C16)*(CONFIG!$B$92:$B$97<=$E16)*(CONFIG!$C$92:$C$97>$E16)*CONFIG!$D$92:$D$97),SUMIFS(CONFIG!$E$79:$E$88,CONFIG!$A$79:$A$88,$D16,CONFIG!$C$79:$C$88,$C16)) -> 11.472 | L16: =IF($D16="E6",0,SUMIFS(CONFIG!$F$79:$F$88,CONFIG!$A$79:$A$88,$D16,CONFIG!$C$79:$C$88,$C16)) -> 0 | M16: =IF($D16="E6",0,SUMIFS(CONFIG!$G$79:$G$88,CONFIG!$A$79:$A$88,$D16,CONFIG!$C$79:$C$88,$C16)) -> 0 | N16: =IF($D16="E6",0,SUMIFS(CONFIG!$H$79:$H$88,CONFIG!$A$79:$A$88,$D16,CONFIG!$C$79:$C$88,$C16)) -> 0 | O16: =$J16+$K16*IF(ISNUMBER($F16),$F16,0)+$L16*IF(ISNUMBER($G16),$G16,0)+$M16*IF(ISNUMBER($E16),$E16,0)+$N16*IF(ISNUMBER($I16),$I16,0) -> 1905.58 | P16: 1905.58 | Q16: =$O16-$P16 -> 0 | R16: =IF(ABS($Q16)<=0.5,"APROBADO","FALLIDO") -> APROBADO
A17: A10 | B17: SIN % de grasa · Schofield canónica, banda ≥60 | C17: Mujer | D17: E6 | E17: 65 | F17: 68 | G17: 158 | I17: =IF(ISBLANK($H17),0,$F17*(1-$H17)) -> 0 | J17: =IF($D17="E6",SUMPRODUCT((CONFIG!$A$92:$A$97=$C17)*(CONFIG!$B$92:$B$97<=$E17)*(CONFIG!$C$92:$C$97>$E17)*CONFIG!$E$92:$E$97),SUMIFS(CONFIG!$D$79:$D$88,CONFIG!$A$79:$A$88,$D17,CONFIG!$C$79:$C$88,$C17)) -> 658.5 | K17: =IF($D17="E6",SUMPRODUCT((CONFIG!$A$92:$A$97=$C17)*(CONFIG!$B$92:$B$97<=$E17)*(CONFIG!$C$92:$C$97>$E17)*CONFIG!$D$92:$D$97),SUMIFS(CONFIG!$E$79:$E$88,CONFIG!$A$79:$A$88,$D17,CONFIG!$C$79:$C$88,$C17)) -> 9.082 | L17: =IF($D17="E6",0,SUMIFS(CONFIG!$F$79:$F$88,CONFIG!$A$79:$A$88,$D17,CONFIG!$C$79:$C$88,$C17)) -> 0 | M17: =IF($D17="E6",0,SUMIFS(CONFIG!$G$79:$G$88,CONFIG!$A$79:$A$88,$D17,CONFIG!$C$79:$C$88,$C17)) -> 0 | N17: =IF($D17="E6",0,SUMIFS(CONFIG!$H$79:$H$88,CONFIG!$A$79:$A$88,$D17,CONFIG!$C$79:$C$88,$C17)) -> 0 | O17: =$J17+$K17*IF(ISNUMBER($F17),$F17,0)+$L17*IF(ISNUMBER($G17),$G17,0)+$M17*IF(ISNUMBER($E17),$E17,0)+$N17*IF(ISNUMBER($I17),$I17,0) -> 1276.076 | P17: 1276.076 | Q17: =$O17-$P17 -> 0 | R17: =IF(ABS($Q17)<=0.5,"APROBADO","FALLIDO") -> APROBADO
A19: BLOQUE H · HENRY / OXFORD 2005 — NUEVO · fronteras exactas de edad · tolerancia ±0,1 kcal (dossier §3)
A20: ID | B20: Descripción | C20: Sexo | D20: Edad | E20: Peso (kg) | F20: a (motor) | G20: b (motor) | H20: Obtenido (kcal) | I20: Esperado kcal (tabla primaria) | J20: Dif. kcal | K20: Estado kcal | L20: Esperado desde la tabla MJ (kcal) | M20: Dif. kcal ↔ MJ | N20: Estado MJ | O20: ESTADO DEL CASO
A21: H01 | B21: Hombre · banda 18–30 · frontera inferior exacta | C21: Hombre | D21: 18 | E21: 60 | F21: =IF(OR($D21<EDAD_MIN,$D21>EDAD_MAX),0,SUMPRODUCT((CONFIG!$A$110:$A$115=$C21)*(CONFIG!$B$110:$B$115<=$D21)*(CONFIG!$C$110:$C$115>$D21)*CONFIG!$E$110:$E$115)) -> 545 | G21: =IF(OR($D21<EDAD_MIN,$D21>EDAD_MAX),0,SUMPRODUCT((CONFIG!$A$110:$A$115=$C21)*(CONFIG!$B$110:$B$115<=$D21)*(CONFIG!$C$110:$C$115>$D21)*CONFIG!$D$110:$D$115)) -> 16 | H21: =IF(OR($D21<EDAD_MIN,$D21>EDAD_MAX),"ND: fuera del alcance adulto",$F21+$G21*$E21) -> 1505 | I21: 1505 | J21: =IF(OR(NOT(ISNUMBER($H21)),NOT(ISNUMBER($I21))),"",$H21-$I21) -> 0 | K21: =IF(AND(NOT(ISNUMBER($H21)),NOT(ISNUMBER($I21))),IF($H21=$I21,"APROBADO","FALLIDO"),IF(NOT(ISNUMBER($J21)),"FALLIDO",IF(ABS($J21)<=0.1,"APROBADO","FALLIDO"))) -> APROBADO | L21: 1504.3019 | M21: =IF(OR(NOT(ISNUMBER($H21)),NOT(ISNUMBER($L21))),"",$H21-$L21) -> 0.6981 | N21: =IF(OR(NOT(ISNUMBER($M21)),NOT(ISNUMBER($L21)),$L21=0),"N/A",IF(ABS($M21/$L21)<=TOL_MJ,"APROBADO","FALLIDO")) -> APROBADO | O21: =IF(AND($K21="APROBADO",OR($N21="APROBADO",$N21="N/A")),"APROBADO","FALLIDO") -> APROBADO
A22: H02 | B22: Hombre · banda 18–30 · frontera superior (29,99) | C22: Hombre | D22: 29.99 | E22: 80 | F22: =IF(OR($D22<EDAD_MIN,$D22>EDAD_MAX),0,SUMPRODUCT((CONFIG!$A$110:$A$115=$C22)*(CONFIG!$B$110:$B$115<=$D22)*(CONFIG!$C$110:$C$115>$D22)*CONFIG!$E$110:$E$115)) -> 545 | G22: =IF(OR($D22<EDAD_MIN,$D22>EDAD_MAX),0,SUMPRODUCT((CONFIG!$A$110:$A$115=$C22)*(CONFIG!$B$110:$B$115<=$D22)*(CONFIG!$C$110:$C$115>$D22)*CONFIG!$D$110:$D$115)) -> 16 | H22: =IF(OR($D22<EDAD_MIN,$D22>EDAD_MAX),"ND: fuera del alcance adulto",$F22+$G22*$E22) -> 1825 | I22: 1825 | J22: =IF(OR(NOT(ISNUMBER($H22)),NOT(ISNUMBER($I22))),"",$H22-$I22) -> 0 | K22: =IF(AND(NOT(ISNUMBER($H22)),NOT(ISNUMBER($I22))),IF($H22=$I22,"APROBADO","FALLIDO"),IF(NOT(ISNUMBER($J22)),"FALLIDO",IF(ABS($J22)<=0.1,"APROBADO","FALLIDO"))) -> APROBADO | L22: 1824.0915 | M22: =IF(OR(NOT(ISNUMBER($H22)),NOT(ISNUMBER($L22))),"",$H22-$L22) -> 0.9085 | N22: =IF(OR(NOT(ISNUMBER($M22)),NOT(ISNUMBER($L22)),$L22=0),"N/A",IF(ABS($M22/$L22)<=TOL_MJ,"APROBADO","FALLIDO")) -> APROBADO | O22: =IF(AND($K22="APROBADO",OR($N22="APROBADO",$N22="N/A")),"APROBADO","FALLIDO") -> APROBADO
A23: H03 | B23: Hombre · banda 30–60 · frontera inferior exacta | C23: Hombre | D23: 30 | E23: 60 | F23: =IF(OR($D23<EDAD_MIN,$D23>EDAD_MAX),0,SUMPRODUCT((CONFIG!$A$110:$A$115=$C23)*(CONFIG!$B$110:$B$115<=$D23)*(CONFIG!$C$110:$C$115>$D23)*CONFIG!$E$110:$E$115)) -> 593 | G23: =IF(OR($D23<EDAD_MIN,$D23>EDAD_MAX),0,SUMPRODUCT((CONFIG!$A$110:$A$115=$C23)*(CONFIG!$B$110:$B$115<=$D23)*(CONFIG!$C$110:$C$115>$D23)*CONFIG!$D$110:$D$115)) -> 14.2 | H23: =IF(OR($D23<EDAD_MIN,$D23>EDAD_MAX),"ND: fuera del alcance adulto",$F23+$G23*$E23) -> 1445 | I23: 1445 | J23: =IF(OR(NOT(ISNUMBER($H23)),NOT(ISNUMBER($I23))),"",$H23-$I23) -> 0 | K23: =IF(AND(NOT(ISNUMBER($H23)),NOT(ISNUMBER($I23))),IF($H23=$I23,"APROBADO","FALLIDO"),IF(NOT(ISNUMBER($J23)),"FALLIDO",IF(ABS($J23)<=0.1,"APROBADO","FALLIDO"))) -> APROBADO | L23: 1441.6824 | M23: =IF(OR(NOT(ISNUMBER($H23)),NOT(ISNUMBER($L23))),"",$H23-$L23) -> 3.3176 | N23: =IF(OR(NOT(ISNUMBER($M23)),NOT(ISNUMBER($L23)),$L23=0),"N/A",IF(ABS($M23/$L23)<=TOL_MJ,"APROBADO","FALLIDO")) -> APROBADO | O23: =IF(AND($K23="APROBADO",OR($N23="APROBADO",$N23="N/A")),"APROBADO","FALLIDO") -> APROBADO
A24: H04 | B24: Hombre · banda 30–60 · frontera superior (59,99) | C24: Hombre | D24: 59.99 | E24: 80 | F24: =IF(OR($D24<EDAD_MIN,$D24>EDAD_MAX),0,SUMPRODUCT((CONFIG!$A$110:$A$115=$C24)*(CONFIG!$B$110:$B$115<=$D24)*(CONFIG!$C$110:$C$115>$D24)*CONFIG!$E$110:$E$115)) -> 593 | G24: =IF(OR($D24<EDAD_MIN,$D24>EDAD_MAX),0,SUMPRODUCT((CONFIG!$A$110:$A$115=$C24)*(CONFIG!$B$110:$B$115<=$D24)*(CONFIG!$C$110:$C$115>$D24)*CONFIG!$D$110:$D$115)) -> 14.2 | H24: =IF(OR($D24<EDAD_MIN,$D24>EDAD_MAX),"ND: fuera del alcance adulto",$F24+$G24*$E24) -> 1729 | I24: 1729 | J24: =IF(OR(NOT(ISNUMBER($H24)),NOT(ISNUMBER($I24))),"",$H24-$I24) -> 0 | K24: =IF(AND(NOT(ISNUMBER($H24)),NOT(ISNUMBER($I24))),IF($H24=$I24,"APROBADO","FALLIDO"),IF(NOT(ISNUMBER($J24)),"FALLIDO",IF(ABS($J24)<=0.1,"APROBADO","FALLIDO"))) -> APROBADO | L24: 1724.6651 | M24: =IF(OR(NOT(ISNUMBER($H24)),NOT(ISNUMBER($L24))),"",$H24-$L24) -> 4.3349 | N24: =IF(OR(NOT(ISNUMBER($M24)),NOT(ISNUMBER($L24)),$L24=0),"N/A",IF(ABS($M24/$L24)<=TOL_MJ,"APROBADO","FALLIDO")) -> APROBADO | O24: =IF(AND($K24="APROBADO",OR($N24="APROBADO",$N24="N/A")),"APROBADO","FALLIDO") -> APROBADO
A25: H05 | B25: Hombre · banda ≥60 · frontera inferior exacta | C25: Hombre | D25: 60 | E25: 60 | F25: =IF(OR($D25<EDAD_MIN,$D25>EDAD_MAX),0,SUMPRODUCT((CONFIG!$A$110:$A$115=$C25)*(CONFIG!$B$110:$B$115<=$D25)*(CONFIG!$C$110:$C$115>$D25)*CONFIG!$E$110:$E$115)) -> 514 | G25: =IF(OR($D25<EDAD_MIN,$D25>EDAD_MAX),0,SUMPRODUCT((CONFIG!$A$110:$A$115=$C25)*(CONFIG!$B$110:$B$115<=$D25)*(CONFIG!$C$110:$C$115>$D25)*CONFIG!$D$110:$D$115)) -> 13.5 | H25: =IF(OR($D25<EDAD_MIN,$D25>EDAD_MAX),"ND: fuera del alcance adulto",$F25+$G25*$E25) -> 1324 | I25: 1324 | J25: =IF(OR(NOT(ISNUMBER($H25)),NOT(ISNUMBER($I25))),"",$H25-$I25) -> 0 | K25: =IF(AND(NOT(ISNUMBER($H25)),NOT(ISNUMBER($I25))),IF($H25=$I25,"APROBADO","FALLIDO"),IF(NOT(ISNUMBER($J25)),"FALLIDO",IF(ABS($J25)<=0.1,"APROBADO","FALLIDO"))) -> APROBADO | L25: 1321.2235 | M25: =IF(OR(NOT(ISNUMBER($H25)),NOT(ISNUMBER($L25))),"",$H25-$L25) -> 2.7765 | N25: =IF(OR(NOT(ISNUMBER($M25)),NOT(ISNUMBER($L25)),$L25=0),"N/A",IF(ABS($M25/$L25)<=TOL_MJ,"APROBADO","FALLIDO")) -> APROBADO | O25: =IF(AND($K25="APROBADO",OR($N25="APROBADO",$N25="N/A")),"APROBADO","FALLIDO") -> APROBADO
A26: H06 | B26: Hombre · banda ≥60 · adulto mayor | C26: Hombre | D26: 75 | E26: 80 | F26: =IF(OR($D26<EDAD_MIN,$D26>EDAD_MAX),0,SUMPRODUCT((CONFIG!$A$110:$A$115=$C26)*(CONFIG!$B$110:$B$115<=$D26)*(CONFIG!$C$110:$C$115>$D26)*CONFIG!$E$110:$E$115)) -> 514 | G26: =IF(OR($D26<EDAD_MIN,$D26>EDAD_MAX),0,SUMPRODUCT((CONFIG!$A$110:$A$115=$C26)*(CONFIG!$B$110:$B$115<=$D26)*(CONFIG!$C$110:$C$115>$D26)*CONFIG!$D$110:$D$115)) -> 13.5 | H26: =IF(OR($D26<EDAD_MIN,$D26>EDAD_MAX),"ND: fuera del alcance adulto",$F26+$G26*$E26) -> 1594 | I26: 1594 | J26: =IF(OR(NOT(ISNUMBER($H26)),NOT(ISNUMBER($I26))),"",$H26-$I26) -> 0 | K26: =IF(AND(NOT(ISNUMBER($H26)),NOT(ISNUMBER($I26))),IF($H26=$I26,"APROBADO","FALLIDO"),IF(NOT(ISNUMBER($J26)),"FALLIDO",IF(ABS($J26)<=0.1,"APROBADO","FALLIDO"))) -> APROBADO | L26: 1590.3439 | M26: =IF(OR(NOT(ISNUMBER($H26)),NOT(ISNUMBER($L26))),"",$H26-$L26) -> 3.6561 | N26: =IF(OR(NOT(ISNUMBER($M26)),NOT(ISNUMBER($L26)),$L26=0),"N/A",IF(ABS($M26/$L26)<=TOL_MJ,"APROBADO","FALLIDO")) -> APROBADO | O26: =IF(AND($K26="APROBADO",OR($N26="APROBADO",$N26="N/A")),"APROBADO","FALLIDO") -> APROBADO
A27: H07 | B27: Mujer · banda 18–30 · frontera inferior exacta | C27: Mujer | D27: 18 | E27: 55 | F27: =IF(OR($D27<EDAD_MIN,$D27>EDAD_MAX),0,SUMPRODUCT((CONFIG!$A$110:$A$115=$C27)*(CONFIG!$B$110:$B$115<=$D27)*(CONFIG!$C$110:$C$115>$D27)*CONFIG!$E$110:$E$115)) -> 558 | G27: =IF(OR($D27<EDAD_MIN,$D27>EDAD_MAX),0,SUMPRODUCT((CONFIG!$A$110:$A$115=$C27)*(CONFIG!$B$110:$B$115<=$D27)*(CONFIG!$C$110:$C$115>$D27)*CONFIG!$D$110:$D$115)) -> 13.1 | H27: =IF(OR($D27<EDAD_MIN,$D27>EDAD_MAX),"ND: fuera del alcance adulto",$F27+$G27*$E27) -> 1278.5 | I27: 1278.5 | J27: =IF(OR(NOT(ISNUMBER($H27)),NOT(ISNUMBER($I27))),"",$H27-$I27) -> 0 | K27: =IF(AND(NOT(ISNUMBER($H27)),NOT(ISNUMBER($I27))),IF($H27=$I27,"APROBADO","FALLIDO"),IF(NOT(ISNUMBER($J27)),"FALLIDO",IF(ABS($J27)<=0.1,"APROBADO","FALLIDO"))) -> APROBADO | L27: 1274.6174 | M27: =IF(OR(NOT(ISNUMBER($H27)),NOT(ISNUMBER($L27))),"",$H27-$L27) -> 3.8826 | N27: =IF(OR(NOT(ISNUMBER($M27)),NOT(ISNUMBER($L27)),$L27=0),"N/A",IF(ABS($M27/$L27)<=TOL_MJ,"APROBADO","FALLIDO")) -> APROBADO | O27: =IF(AND($K27="APROBADO",OR($N27="APROBADO",$N27="N/A")),"APROBADO","FALLIDO") -> APROBADO
A28: H08 | B28: Mujer · banda 18–30 · frontera superior (29,99) | C28: Mujer | D28: 29.99 | E28: 70 | F28: =IF(OR($D28<EDAD_MIN,$D28>EDAD_MAX),0,SUMPRODUCT((CONFIG!$A$110:$A$115=$C28)*(CONFIG!$B$110:$B$115<=$D28)*(CONFIG!$C$110:$C$115>$D28)*CONFIG!$E$110:$E$115)) -> 558 | G28: =IF(OR($D28<EDAD_MIN,$D28>EDAD_MAX),0,SUMPRODUCT((CONFIG!$A$110:$A$115=$C28)*(CONFIG!$B$110:$B$115<=$D28)*(CONFIG!$C$110:$C$115>$D28)*CONFIG!$D$110:$D$115)) -> 13.1 | H28: =IF(OR($D28<EDAD_MIN,$D28>EDAD_MAX),"ND: fuera del alcance adulto",$F28+$G28*$E28) -> 1475 | I28: 1475 | J28: =IF(OR(NOT(ISNUMBER($H28)),NOT(ISNUMBER($I28))),"",$H28-$I28) -> 0 | K28: =IF(AND(NOT(ISNUMBER($H28)),NOT(ISNUMBER($I28))),IF($H28=$I28,"APROBADO","FALLIDO"),IF(NOT(ISNUMBER($J28)),"FALLIDO",IF(ABS($J28)<=0.1,"APROBADO","FALLIDO"))) -> APROBADO | L28: 1470.3631 | M28: =IF(OR(NOT(ISNUMBER($H28)),NOT(ISNUMBER($L28))),"",$H28-$L28) -> 4.6369 | N28: =IF(OR(NOT(ISNUMBER($M28)),NOT(ISNUMBER($L28)),$L28=0),"N/A",IF(ABS($M28/$L28)<=TOL_MJ,"APROBADO","FALLIDO")) -> APROBADO | O28: =IF(AND($K28="APROBADO",OR($N28="APROBADO",$N28="N/A")),"APROBADO","FALLIDO") -> APROBADO
A29: H09 | B29: Mujer · banda 30–60 · frontera inferior exacta | C29: Mujer | D29: 30 | E29: 55 | F29: =IF(OR($D29<EDAD_MIN,$D29>EDAD_MAX),0,SUMPRODUCT((CONFIG!$A$110:$A$115=$C29)*(CONFIG!$B$110:$B$115<=$D29)*(CONFIG!$C$110:$C$115>$D29)*CONFIG!$E$110:$E$115)) -> 694 | G29: =IF(OR($D29<EDAD_MIN,$D29>EDAD_MAX),0,SUMPRODUCT((CONFIG!$A$110:$A$115=$C29)*(CONFIG!$B$110:$B$115<=$D29)*(CONFIG!$C$110:$C$115>$D29)*CONFIG!$D$110:$D$115)) -> 9.74 | H29: =IF(OR($D29<EDAD_MIN,$D29>EDAD_MAX),"ND: fuera del alcance adulto",$F29+$G29*$E29) -> 1229.7 | I29: 1229.7 | J29: =IF(OR(NOT(ISNUMBER($H29)),NOT(ISNUMBER($I29))),"",$H29-$I29) -> 0 | K29: =IF(AND(NOT(ISNUMBER($H29)),NOT(ISNUMBER($I29))),IF($H29=$I29,"APROBADO","FALLIDO"),IF(NOT(ISNUMBER($J29)),"FALLIDO",IF(ABS($J29)<=0.1,"APROBADO","FALLIDO"))) -> APROBADO | L29: 1228.1308 | M29: =IF(OR(NOT(ISNUMBER($H29)),NOT(ISNUMBER($L29))),"",$H29-$L29) -> 1.5692 | N29: =IF(OR(NOT(ISNUMBER($M29)),NOT(ISNUMBER($L29)),$L29=0),"N/A",IF(ABS($M29/$L29)<=TOL_MJ,"APROBADO","FALLIDO")) -> APROBADO | O29: =IF(AND($K29="APROBADO",OR($N29="APROBADO",$N29="N/A")),"APROBADO","FALLIDO") -> APROBADO
A30: H10 | B30: Mujer · banda 30–60 · frontera superior (59,99) | C30: Mujer | D30: 59.99 | E30: 70 | F30: =IF(OR($D30<EDAD_MIN,$D30>EDAD_MAX),0,SUMPRODUCT((CONFIG!$A$110:$A$115=$C30)*(CONFIG!$B$110:$B$115<=$D30)*(CONFIG!$C$110:$C$115>$D30)*CONFIG!$E$110:$E$115)) -> 694 | G30: =IF(OR($D30<EDAD_MIN,$D30>EDAD_MAX),0,SUMPRODUCT((CONFIG!$A$110:$A$115=$C30)*(CONFIG!$B$110:$B$115<=$D30)*(CONFIG!$C$110:$C$115>$D30)*CONFIG!$D$110:$D$115)) -> 9.74 | H30: =IF(OR($D30<EDAD_MIN,$D30>EDAD_MAX),"ND: fuera del alcance adulto",$F30+$G30*$E30) -> 1375.8 | I30: 1375.8 | J30: =IF(OR(NOT(ISNUMBER($H30)),NOT(ISNUMBER($I30))),"",$H30-$I30) -> 2.2737368e-13 | K30: =IF(AND(NOT(ISNUMBER($H30)),NOT(ISNUMBER($I30))),IF($H30=$I30,"APROBADO","FALLIDO"),IF(NOT(ISNUMBER($J30)),"FALLIDO",IF(ABS($J30)<=0.1,"APROBADO","FALLIDO"))) -> APROBADO | L30: 1374.0438 | M30: =IF(OR(NOT(ISNUMBER($H30)),NOT(ISNUMBER($L30))),"",$H30-$L30) -> 1.7562 | N30: =IF(OR(NOT(ISNUMBER($M30)),NOT(ISNUMBER($L30)),$L30=0),"N/A",IF(ABS($M30/$L30)<=TOL_MJ,"APROBADO","FALLIDO")) -> APROBADO | O30: =IF(AND($K30="APROBADO",OR($N30="APROBADO",$N30="N/A")),"APROBADO","FALLIDO") -> APROBADO
A31: H11 | B31: Mujer · banda ≥60 · frontera inferior exacta | C31: Mujer | D31: 60 | E31: 55 | F31: =IF(OR($D31<EDAD_MIN,$D31>EDAD_MAX),0,SUMPRODUCT((CONFIG!$A$110:$A$115=$C31)*(CONFIG!$B$110:$B$115<=$D31)*(CONFIG!$C$110:$C$115>$D31)*CONFIG!$E$110:$E$115)) -> 569 | G31: =IF(OR($D31<EDAD_MIN,$D31>EDAD_MAX),0,SUMPRODUCT((CONFIG!$A$110:$A$115=$C31)*(CONFIG!$B$110:$B$115<=$D31)*(CONFIG!$C$110:$C$115>$D31)*CONFIG!$D$110:$D$115)) -> 10.1 | H31: =IF(OR($D31<EDAD_MIN,$D31>EDAD_MAX),"ND: fuera del alcance adulto",$F31+$G31*$E31) -> 1124.5 | I31: 1124.5 | J31: =IF(OR(NOT(ISNUMBER($H31)),NOT(ISNUMBER($I31))),"",$H31-$I31) -> 0 | K31: =IF(AND(NOT(ISNUMBER($H31)),NOT(ISNUMBER($I31))),IF($H31=$I31,"APROBADO","FALLIDO"),IF(NOT(ISNUMBER($J31)),"FALLIDO",IF(ABS($J31)<=0.1,"APROBADO","FALLIDO"))) -> APROBADO | L31: 1126.1949 | M31: =IF(OR(NOT(ISNUMBER($H31)),NOT(ISNUMBER($L31))),"",$H31-$L31) -> -1.6949 | N31: =IF(OR(NOT(ISNUMBER($M31)),NOT(ISNUMBER($L31)),$L31=0),"N/A",IF(ABS($M31/$L31)<=TOL_MJ,"APROBADO","FALLIDO")) -> APROBADO | O31: =IF(AND($K31="APROBADO",OR($N31="APROBADO",$N31="N/A")),"APROBADO","FALLIDO") -> APROBADO
A32: H12 | B32: Mujer · banda ≥60 · adulta mayor | C32: Mujer | D32: 75 | E32: 70 | F32: =IF(OR($D32<EDAD_MIN,$D32>EDAD_MAX),0,SUMPRODUCT((CONFIG!$A$110:$A$115=$C32)*(CONFIG!$B$110:$B$115<=$D32)*(CONFIG!$C$110:$C$115>$D32)*CONFIG!$E$110:$E$115)) -> 569 | G32: =IF(OR($D32<EDAD_MIN,$D32>EDAD_MAX),0,SUMPRODUCT((CONFIG!$A$110:$A$115=$C32)*(CONFIG!$B$110:$B$115<=$D32)*(CONFIG!$C$110:$C$115>$D32)*CONFIG!$D$110:$D$115)) -> 10.1 | H32: =IF(OR($D32<EDAD_MIN,$D32>EDAD_MAX),"ND: fuera del alcance adulto",$F32+$G32*$E32) -> 1276 | I32: 1276 | J32: =IF(OR(NOT(ISNUMBER($H32)),NOT(ISNUMBER($I32))),"",$H32-$I32) -> 0 | K32: =IF(AND(NOT(ISNUMBER($H32)),NOT(ISNUMBER($I32))),IF($H32=$I32,"APROBADO","FALLIDO"),IF(NOT(ISNUMBER($J32)),"FALLIDO",IF(ABS($J32)<=0.1,"APROBADO","FALLIDO"))) -> APROBADO | L32: 1278.2025 | M32: =IF(OR(NOT(ISNUMBER($H32)),NOT(ISNUMBER($L32))),"",$H32-$L32) -> -2.2025 | N32: =IF(OR(NOT(ISNUMBER($M32)),NOT(ISNUMBER($L32)),$L32=0),"N/A",IF(ABS($M32/$L32)<=TOL_MJ,"APROBADO","FALLIDO")) -> APROBADO | O32: =IF(AND($K32="APROBADO",OR($N32="APROBADO",$N32="N/A")),"APROBADO","FALLIDO") -> APROBADO
A33: H13 | B33: FUERA DE ALCANCE · edad 17,99 (menor de edad) | C33: Hombre | D33: 17.99 | E33: 60 | F33: =IF(OR($D33<EDAD_MIN,$D33>EDAD_MAX),0,SUMPRODUCT((CONFIG!$A$110:$A$115=$C33)*(CONFIG!$B$110:$B$115<=$D33)*(CONFIG!$C$110:$C$115>$D33)*CONFIG!$E$110:$E$115)) -> 0 | G33: =IF(OR($D33<EDAD_MIN,$D33>EDAD_MAX),0,SUMPRODUCT((CONFIG!$A$110:$A$115=$C33)*(CONFIG!$B$110:$B$115<=$D33)*(CONFIG!$C$110:$C$115>$D33)*CONFIG!$D$110:$D$115)) -> 0 | H33: =IF(OR($D33<EDAD_MIN,$D33>EDAD_MAX),"ND: fuera del alcance adulto",$F33+$G33*$E33) -> ND: fuera del alcance adulto | I33: ND: fuera del alcance adulto | J33: =IF(OR(NOT(ISNUMBER($H33)),NOT(ISNUMBER($I33))),"",$H33-$I33) | K33: =IF(AND(NOT(ISNUMBER($H33)),NOT(ISNUMBER($I33))),IF($H33=$I33,"APROBADO","FALLIDO"),IF(NOT(ISNUMBER($J33)),"FALLIDO",IF(ABS($J33)<=0.1,"APROBADO","FALLIDO"))) -> APROBADO | M33: =IF(OR(NOT(ISNUMBER($H33)),NOT(ISNUMBER($L33))),"",$H33-$L33) | N33: =IF(OR(NOT(ISNUMBER($M33)),NOT(ISNUMBER($L33)),$L33=0),"N/A",IF(ABS($M33/$L33)<=TOL_MJ,"APROBADO","FALLIDO")) -> N/A | O33: =IF(AND($K33="APROBADO",OR($N33="APROBADO",$N33="N/A")),"APROBADO","FALLIDO") -> APROBADO
A34: La columna 'Esperado desde la tabla MJ' contrasta las DOS tablas publicadas por Henry. Difieren hasta ~4,6 kcal (≈0,3 %) porque la tabla en kcal del artículo está REDONDEADA a 3 cifras significativas. NO es un error del libro. El contraste existe para detectar una conversión DUPLICADA u OMITIDA, que produciría cientos de kcal de error: por eso el umbral es RELATIVO (TOL_MJ = 1 %) y no absoluto. H13 comprueba que a los 17,99 años el motor devuelve ND.
A36: BLOQUE B · CADENA DEL GASTO: actividad, efecto térmico, GET y energía objetivo (±0,5 kcal)
A37: ID | B37: Escenario | C37: GEB | D37: FA | E37: Modo ETA (1/2/3) | F37: % ETA | G37: % ajuste | H37: GAF obt. | I37: ETA obt. | J37: GET obt. | K37: Energía obt. | L37: GET esp. | M37: Energía esp. | N37: Dif. GET | O37: Dif. energía | P37: Estado
A38: B01 | B38: PAL global (1,50) · ETA incluido en el FA (modo 1) · déficit 15 % | C38: 1720 | D38: 1.5 | E38: 1 | F38: 0.1 | G38: -0.15 | H38: =$C38*($D38-1) -> 860 | I38: =IF($E38=1,0,IF($E38=2,($C38+$H38)*$F38,($C38+$H38)*$F38/(1-$F38))) -> 0 | J38: =$C38+$H38+$I38 -> 2580 | K38: =$J38*(1+$G38) -> 2193 | L38: 2580 | M38: 2193 | N38: =$J38-$L38 -> 0 | O38: =$K38-$M38 -> 0 | P38: =IF(AND(ABS($N38)<=0.5,ABS($O38)<=0.5),"APROBADO","FALLIDO") -> APROBADO
A39: B02 | B39: PAL derivado de actividades (1,85) · ETA explícito como % del GET · mantenimiento | C39: 1720 | D39: 1.85 | E39: 3 | F39: 0.1 | G39: 0 | H39: =$C39*($D39-1) -> 1462 | I39: =IF($E39=1,0,IF($E39=2,($C39+$H39)*$F39,($C39+$H39)*$F39/(1-$F39))) -> 353.55556 | J39: =$C39+$H39+$I39 -> 3535.5556 | K39: =$J39*(1+$G39) -> 3535.5556 | L39: 3535.5556 | M39: 3535.5556 | N39: =$J39-$L39 -> -4.4444444e-05 | O39: =$K39-$M39 -> -4.4444444e-05 | P39: =IF(AND(ABS($N39)<=0.5,ABS($O39)<=0.5),"APROBADO","FALLIDO") -> APROBADO
A40: B03 | B40: PAL global (1,80) · ETA explícito como % de (GEB+GAF) · superávit 10 % | C40: 1600 | D40: 1.8 | E40: 2 | F40: 0.1 | G40: 0.1 | H40: =$C40*($D40-1) -> 1280 | I40: =IF($E40=1,0,IF($E40=2,($C40+$H40)*$F40,($C40+$H40)*$F40/(1-$F40))) -> 288 | J40: =$C40+$H40+$I40 -> 3168 | K40: =$J40*(1+$G40) -> 3484.8 | L40: 3168 | M40: 3484.8 | N40: =$J40-$L40 -> 0 | O40: =$K40-$M40 -> 0 | P40: =IF(AND(ABS($N40)<=0.5,ABS($O40)<=0.5),"APROBADO","FALLIDO") -> APROBADO
A41: B01 es la PRUEBA DE NO DOBLE CONTEO: con el modo por defecto el ETA vale exactamente 0 y GET = GEB × PAL. B02 y B03 ejercitan los dos modos explícitos de ETA (que el libro permite, pero advirtiendo).
A43: BLOQUE C · VALIDACIONES: imposibles, vacíos, ceros, negativos, extremos y macros
A44: ID | B44: Escenario probado | C44: Entrada 1 | D44: Entrada 2 | E44: Comportamiento esperado | F44: Comportamiento obtenido | G44: Estado
A45: C01 | B45: Edad inválida (menor de edad: 15 años) | C45: 15 | E45: ERROR: edad fuera del alcance (solo adultos) | F45: =IF(ISBLANK($C45),"ERROR: vacío",IF(NOT(ISNUMBER($C45)),"ERROR: no es numérico",IF(OR($C45<EDAD_MIN,$C45>EDAD_MAX),"ERROR: edad fuera del alcance (solo adultos)","OK"))) -> ERROR: edad fuera del alcance (solo adultos) | G45: =IF($E45=$F45,"APROBADO","FALLIDO") -> APROBADO
A46: C02 | B46: Edad inválida (texto) | C46: treinta | E46: ERROR: no es numérico | F46: =IF(ISBLANK($C46),"ERROR: vacío",IF(NOT(ISNUMBER($C46)),"ERROR: no es numérico",IF(OR($C46<EDAD_MIN,$C46>EDAD_MAX),"ERROR: edad fuera del alcance (solo adultos)","OK"))) -> ERROR: no es numérico | G46: =IF($E46=$F46,"APROBADO","FALLIDO") -> APROBADO
A47: C03 | B47: Peso negativo (−70 kg) | C47: -70 | E47: ERROR: el peso debe ser mayor que cero | F47: =IF(ISBLANK($C47),"ERROR: vacío",IF(NOT(ISNUMBER($C47)),"ERROR: no es numérico",IF($C47<=0,"ERROR: el peso debe ser mayor que cero",IF(OR($C47<PESO_MIN,$C47>PESO_MAX),"ERROR: peso imposible en un adulto","OK")))) -> ERROR: el peso debe ser mayor que cero | G47: =IF($E47=$F47,"APROBADO","FALLIDO") -> APROBADO
A48: C04 | B48: Peso CERO | C48: 0 | E48: ERROR: el peso debe ser mayor que cero | F48: =IF(ISBLANK($C48),"ERROR: vacío",IF(NOT(ISNUMBER($C48)),"ERROR: no es numérico",IF($C48<=0,"ERROR: el peso debe ser mayor que cero",IF(OR($C48<PESO_MIN,$C48>PESO_MAX),"ERROR: peso imposible en un adulto","OK")))) -> ERROR: el peso debe ser mayor que cero | G48: =IF($E48=$F48,"APROBADO","FALLIDO") -> APROBADO
A49: C05 | B49: Estatura VACÍA | E49: ERROR: vacío | F49: =IF(ISBLANK($C49),"ERROR: vacío",IF(NOT(ISNUMBER($C49)),"ERROR: no es numérico",IF($C49<=0,"ERROR: la estatura debe ser mayor que cero",IF(OR($C49<EST_MIN,$C49>EST_MAX),"ERROR: estatura imposible","OK")))) -> ERROR: vacío | G49: =IF($E49=$F49,"APROBADO","FALLIDO") -> APROBADO
A50: C06 | B50: Estatura imposible (400 cm) | C50: 400 | E50: ERROR: estatura imposible | F50: =IF(ISBLANK($C50),"ERROR: vacío",IF(NOT(ISNUMBER($C50)),"ERROR: no es numérico",IF($C50<=0,"ERROR: la estatura debe ser mayor que cero",IF(OR($C50<EST_MIN,$C50>EST_MAX),"ERROR: estatura imposible","OK")))) -> ERROR: estatura imposible | G50: =IF($E50=$F50,"APROBADO","FALLIDO") -> APROBADO
A51: C07 | B51: % de grasa fuera de rango (90 %) | C51: 0.9 | E51: ERROR: % de grasa imposible | F51: =IF(ISBLANK($C51),"NO INGRESADO (opcional)",IF(NOT(ISNUMBER($C51)),"ERROR: no es numérico",IF(OR($C51<GRASA_MIN,$C51>GRASA_MAX),"ERROR: % de grasa imposible","OK"))) -> ERROR: % de grasa imposible | G51: =IF($E51=$F51,"APROBADO","FALLIDO") -> APROBADO
A52: C08 | B52: % de grasa ausente (uso legítimo: es opcional) | E52: NO INGRESADO (opcional) | F52: =IF(ISBLANK($C52),"NO INGRESADO (opcional)",IF(NOT(ISNUMBER($C52)),"ERROR: no es numérico",IF(OR($C52<GRASA_MIN,$C52>GRASA_MAX),"ERROR: % de grasa imposible","OK"))) -> NO INGRESADO (opcional) | G52: =IF($E52=$F52,"APROBADO","FALLIDO") -> APROBADO
A53: C09 | B53: MLG (80 kg) ≥ peso (75 kg) | C53: 80 | D53: 75 | E53: ERROR: la MLG es mayor o igual al peso | F53: =IF(ISBLANK($C53),"NO INGRESADA (opcional)",IF(NOT(ISNUMBER($C53)),"ERROR: no es numérico",IF(NOT(ISNUMBER($D53)),"NO APLICA",IF($C53>=$D53,"ERROR: la MLG es mayor o igual al peso","OK")))) -> ERROR: la MLG es mayor o igual al peso | G53: =IF($E53=$F53,"APROBADO","FALLIDO") -> APROBADO
A54: C10 | B54: Macros > 100 % (60 % + 50 %) | C54: 0.6 | D54: 0.5 | E54: ERROR: los % de proteína y grasa superan el 100 % | F54: =IF(ISNUMBER($C54)*ISNUMBER($D54)=0,"ERROR: valores no numéricos",IF($C54+$D54>1,"ERROR: los % de proteína y grasa superan el 100 %","OK")) -> ERROR: los % de proteína y grasa superan el 100 % | G54: =IF($E54=$F54,"APROBADO","FALLIDO") -> APROBADO
A55: C11 | B55: Proteína negativa (−1,2 g/kg) | C55: -1.2 | E55: ERROR: la proteína no puede ser negativa | F55: =IF(ISBLANK($C55),"ERROR: vacío",IF(NOT(ISNUMBER($C55)),"ERROR: no es numérico",IF($C55<0,"ERROR: la proteína no puede ser negativa","OK"))) -> ERROR: la proteína no puede ser negativa | G55: =IF($E55=$F55,"APROBADO","FALLIDO") -> APROBADO
A56: C12 | B56: Registro de actividades de 23 h | C56: 23 | E56: ERROR: el registro de ACTIVIDADES no suma 24 h | F56: =IF(ABS($C56-HORAS_DIA)>0.001,"ERROR: el registro de ACTIVIDADES no suma 24 h","OK") -> ERROR: el registro de ACTIVIDADES no suma 24 h | G56: =IF($E56=$F56,"APROBADO","FALLIDO") -> APROBADO
A57: C13 | B57: Factor de actividad imposible (3,5) | C57: 3.5 | E57: ERROR: factor de actividad fuera de límites | F57: =IF(NOT(ISNUMBER($C57)),"ERROR: no se pudo determinar el factor de actividad",IF(OR($C57<FA_MIN,$C57>FA_MAX),"ERROR: factor de actividad fuera de límites","OK")) -> ERROR: factor de actividad fuera de límites | G57: =IF($E57=$F57,"APROBADO","FALLIDO") -> APROBADO
A58: C14 | B58: Macros suman EXACTAMENTE 100 % (30 % + 70 %) | C58: 0.3 | D58: 0.7 | E58: OK | F58: =IF(ISNUMBER($C58)*ISNUMBER($D58)=0,"ERROR: valores no numéricos",IF($C58+$D58>1,"ERROR: los % de proteína y grasa superan el 100 %","OK")) -> OK | G58: =IF($E58=$F58,"APROBADO","FALLIDO") -> APROBADO
A59: C15 | B59: Macros suman 99,9 % (30 % + 69,9 %) | C59: 0.3 | D59: 0.699 | E59: OK | F59: =IF(ISNUMBER($C59)*ISNUMBER($D59)=0,"ERROR: valores no numéricos",IF($C59+$D59>1,"ERROR: los % de proteína y grasa superan el 100 %","OK")) -> OK | G59: =IF($E59=$F59,"APROBADO","FALLIDO") -> APROBADO
A60: C16 | B60: Macros suman 100,1 % (30 % + 70,1 %) | C60: 0.3 | D60: 0.701 | E60: ERROR: los % de proteína y grasa superan el 100 % | F60: =IF(ISNUMBER($C60)*ISNUMBER($D60)=0,"ERROR: valores no numéricos",IF($C60+$D60>1,"ERROR: los % de proteína y grasa superan el 100 %","OK")) -> ERROR: los % de proteína y grasa superan el 100 % | G60: =IF($E60=$F60,"APROBADO","FALLIDO") -> APROBADO
A62: BLOQUE D · COMPARACIÓN MANUAL CON LAS PUBLICACIONES (sobre el caso vivo de DATOS)
A63: El 'Esperado' reproduce LITERALMENTE la ecuación publicada usando las celdas de DATOS, SIN pasar por CONFIG. El 'Obtenido' se lee de la hoja ECUACIONES. Verifica la cadena DATOS → CONFIG → ECUACIONES y sigue siendo válido aunque usted cambie el caso. Desde la v1.1.1 cubre LAS SIETE ecuaciones (D01–D07), no solo cuatro.
A64: ID | B64: Ecuación | C64: Fórmula publicada aplicada literalmente | D64: Obtenido por el libro (kcal) | E64: Esperado · cálculo literal (kcal) | F64: Diferencia | G64: Estado | H64: MLG reconstruida desde DATOS (sin leer el motor)
A65: D01 | B65: Mifflin–St Jeor (1990) | C65: H: 10P+6,25T−5E+5 | M: 10P+6,25T−5E−161 | D65: =ECUACIONES!$F$7 -> 1810 | E65: =IF(ECUACIONES!$E$7<>"SÍ","ND",IF(in_Sexo="Hombre",10*in_Peso+6.25*in_Est-5*in_Edad+5,10*in_Peso+6.25*in_Est-5*in_Edad-161)) -> 1810 | F65: =IF(OR(NOT(ISNUMBER($D65)),NOT(ISNUMBER($E65))),"ND",$D65-$E65) -> 0 | G65: =IF(AND(NOT(ISNUMBER($D65)),NOT(ISNUMBER($E65))),IF($D65=$E65,"APROBADO","FALLIDO"),IF(NOT(ISNUMBER($F65)),"FALLIDO",IF(ABS($F65)<=0.5,"APROBADO","FALLIDO"))) -> APROBADO
A66: D02 | B66: Harris–Benedict revisada (1984) | C66: H: 88,362+13,397P+4,799T−5,677E | M: 447,593+9,247P+3,098T−4,330E | D66: =ECUACIONES!$F$8 -> 1883.608 | E66: =IF(ECUACIONES!$E$8<>"SÍ","ND",IF(in_Sexo="Hombre",88.362+13.397*in_Peso+4.799*in_Est-5.677*in_Edad,447.593+9.247*in_Peso+3.098*in_Est-4.33*in_Edad)) -> 1883.608 | F66: =IF(OR(NOT(ISNUMBER($D66)),NOT(ISNUMBER($E66))),"ND",$D66-$E66) -> 0 | G66: =IF(AND(NOT(ISNUMBER($D66)),NOT(ISNUMBER($E66))),IF($D66=$E66,"APROBADO","FALLIDO"),IF(NOT(ISNUMBER($F66)),"FALLIDO",IF(ABS($F66)<=0.5,"APROBADO","FALLIDO"))) -> APROBADO
A67: D03 | B67: Schofield (1985) · TABLA CANÓNICA v1.1 | C67: H: 15,057/11,472/11,711 · M: 14,818/8,126/9,082 | D67: =ECUACIONES!$F$12 -> 1866.646 | E67: =IF(ECUACIONES!$E$12<>"SÍ","ND",IF(in_Sexo="Hombre",IF(in_Edad<30,15.057*in_Peso+692.2,IF(in_Edad<60,11.472*in_Peso+873.1,11.711*in_Peso+587.7)),IF(in_Edad<30,14.818*in_Peso+486.6,IF(in_Edad<60,8.126*in_Peso+845.6,9.082*in_Peso+658.5)))) -> 1866.646 | F67: =IF(OR(NOT(ISNUMBER($D67)),NOT(ISNUMBER($E67))),"ND",$D67-$E67) -> 0 | G67: =IF(AND(NOT(ISNUMBER($D67)),NOT(ISNUMBER($E67))),IF($D67=$E67,"APROBADO","FALLIDO"),IF(NOT(ISNUMBER($F67)),"FALLIDO",IF(ABS($F67)<=0.5,"APROBADO","FALLIDO"))) -> APROBADO
A68: D04 | B68: Henry / Oxford (2005) · NUEVA en v1.1 | C68: H: 16,0/14,2/13,5 · M: 13,1/9,74/10,1 | D68: =ECUACIONES!$F$13 -> 1793 | E68: =IF(ECUACIONES!$E$13<>"SÍ","ND",IF(in_Sexo="Hombre",IF(in_Edad<30,16*in_Peso+545,IF(in_Edad<60,14.2*in_Peso+593,13.5*in_Peso+514)),IF(in_Edad<30,13.1*in_Peso+558,IF(in_Edad<60,9.74*in_Peso+694,10.1*in_Peso+569)))) -> 1793 | F68: =IF(OR(NOT(ISNUMBER($D68)),NOT(ISNUMBER($E68))),"ND",$D68-$E68) -> 0 | G68: =IF(AND(NOT(ISNUMBER($D68)),NOT(ISNUMBER($E68))),IF($D68=$E68,"APROBADO","FALLIDO"),IF(NOT(ISNUMBER($F68)),"FALLIDO",IF(ABS($F68)<=0.5,"APROBADO","FALLIDO"))) -> APROBADO
A69: D05 | B69: Owen (1986/1987) · AÑADIDA en v1.1.1 | C69: H: 879+10,2·P | M: 795+7,18·P | D69: =ECUACIONES!$F$9 -> 1674.6 | E69: =IF(ECUACIONES!$E$9<>"SÍ","ND",IF(in_Sexo="Hombre",879+10.2*in_Peso,795+7.18*in_Peso)) -> 1674.6 | F69: =IF(OR(NOT(ISNUMBER($D69)),NOT(ISNUMBER($E69))),"ND",$D69-$E69) -> 0 | G69: =IF(AND(NOT(ISNUMBER($D69)),NOT(ISNUMBER($E69))),IF($D69=$E69,"APROBADO","FALLIDO"),IF(NOT(ISNUMBER($F69)),"FALLIDO",IF(ABS($F69)<=0.5,"APROBADO","FALLIDO"))) -> APROBADO
A70: D06 | B70: Cunningham (1980) · MLG reconstruida desde DATOS (v1.1.2) | C70: 500 + 22 · MLG | D70: =ECUACIONES!$F$10 -> 1864 | E70: =IF(ECUACIONES!$E$10<>"SÍ","ND",IF(NOT(ISNUMBER($H70)),"ND",500+22*$H70)) -> 1864 | F70: =IF(OR(NOT(ISNUMBER($D70)),NOT(ISNUMBER($E70))),"ND",$D70-$E70) -> 0 | G70: =IF(AND(NOT(ISNUMBER($D70)),NOT(ISNUMBER($E70))),IF($D70=$E70,"APROBADO","FALLIDO"),IF(NOT(ISNUMBER($F70)),"FALLIDO",IF(ABS($F70)<=0.5,"APROBADO","FALLIDO"))) -> APROBADO | H70: =IF(OR(NOT(ISNUMBER(in_Peso)),in_Peso<=0),"ND",IF(AND(NOT(ISBLANK(in_MLG)),ISNUMBER(in_MLG),in_MLG>0,in_MLG<in_Peso),in_MLG,IF(AND(NOT(ISBLANK(in_Grasa)),ISNUMBER(in_Grasa),in_Grasa>=GRASA_MIN,in_Grasa<=GRASA_MAX),in_Peso*(1-in_Grasa),"ND"))) -> 62 | I70: v1.1.2 · Antes, el valor ESPERADO de D06/D07 leía CALCULOS!B10, la MLG que produce el propio motor. Una derivación incorrecta de la MLG habría afectado por igual al obtenido y al esperado, y el caso habría seguido aprobando. Ahora la MLG del lado esperado se reconstruye SOLO desde DATOS (MLG medida válida, o si no derivada del % de grasa válido). Los coeficientes 500/22 y 370/21,6 siguen escritos literalmente.
A71: D07 | B71: Cunningham (1991) · alias Katch–McArdle · MLG reconstruida desde DATOS (v1.1.2) | C71: 370 + 21,6 · FFM | D71: =ECUACIONES!$F$11 -> 1709.2 | E71: =IF(ECUACIONES!$E$11<>"SÍ","ND",IF(NOT(ISNUMBER($H71)),"ND",370+21.6*$H71)) -> 1709.2 | F71: =IF(OR(NOT(ISNUMBER($D71)),NOT(ISNUMBER($E71))),"ND",$D71-$E71) -> 0 | G71: =IF(AND(NOT(ISNUMBER($D71)),NOT(ISNUMBER($E71))),IF($D71=$E71,"APROBADO","FALLIDO"),IF(NOT(ISNUMBER($F71)),"FALLIDO",IF(ABS($F71)<=0.5,"APROBADO","FALLIDO"))) -> APROBADO | H71: =IF(OR(NOT(ISNUMBER(in_Peso)),in_Peso<=0),"ND",IF(AND(NOT(ISBLANK(in_MLG)),ISNUMBER(in_MLG),in_MLG>0,in_MLG<in_Peso),in_MLG,IF(AND(NOT(ISBLANK(in_Grasa)),ISNUMBER(in_Grasa),in_Grasa>=GRASA_MIN,in_Grasa<=GRASA_MAX),in_Peso*(1-in_Grasa),"ND"))) -> 62
A73: BLOQUE E · CONVERSIÓN MET → ENERGÍA → PAL (auditoría P0 del dossier §5)
A74: ID | B74: Verificación | C74: Entrada 1 | D74: Entrada 2 | E74: Obtenido | F74: Esperado | G74: Diferencia | H74: Estado
A75: E01 | B75: Las horas registradas en ACTIVIDADES suman exactamente 24 | E75: =ACTIVIDADES!$B$20 -> 24 | F75: =HORAS_DIA -> 24 | G75: =$E75-$F75 -> 0 | H75: =IF(ABS($G75)<=0.001,"APROBADO","FALLIDO") -> APROBADO
A76: E02 | B76: Σ(MET × h) recalculado fila a fila, sin usar la columna F de ACTIVIDADES | E76: =ACTIVIDADES!$B$21 -> 43.3 | F76: =IF(COUNT(ACTIVIDADES!$D$7:$D$18)<>12,"ND: hay filas sin actividad válida",SUMPRODUCT(ACTIVIDADES!$D$7:$D$18,ACTIVIDADES!$E$7:$E$18)) -> 43.3 | G76: =IF(NOT(ISNUMBER($F76)),"ND",$E76-$F76) -> 0 | H76: =IF(NOT(ISNUMBER($G76)),"FALLIDO",IF(ABS($G76)<=0.0001,"APROBADO","FALLIDO")) -> APROBADO
A77: E03 | B77: TEE = Σ(MET×h) × Peso × 1 kcal/kg/h ◄ conversión NUEVA en v1.1 | E77: =ACTIVIDADES!$B$25 -> NO CALCULADO · revalidar actividades | F77: =IF(OR(NOT(ISNUMBER(in_Peso)),in_Peso<=0),"ND",ACTIVIDADES!$B$21*in_Peso*MET_KCAL) -> 3377.4 | G77: =IF(OR(NOT(ISNUMBER($E77)),NOT(ISNUMBER($F77))),"ND",$E77-$F77) -> ND | H77: =IF(NOT(ISNUMBER($G77)),"FALLIDO",IF(ABS($G77)<=0.0001,"APROBADO","FALLIDO")) -> FALLIDO
A78: E04 | B78: PAL ESTIMADO = TEE / GEB (NO es el promedio de METs) | E78: =ACTIVIDADES!$B$27 -> NO CALCULADO | F78: =IF(OR(NOT(ISNUMBER(ACTIVIDADES!$B$25)),NOT(ISNUMBER(ACTIVIDADES!$B$26)),ACTIVIDADES!$B$26<=0),"ND",ACTIVIDADES!$B$25/ACTIVIDADES!$B$26) -> ND | G78: =IF(OR(NOT(ISNUMBER($E78)),NOT(ISNUMBER($F78))),"ND",$E78-$F78) -> ND | H78: =IF(NOT(ISNUMBER($G78)),"FALLIDO",IF(ABS($G78)<=0.000001,"APROBADO","FALLIDO")) -> FALLIDO
A79: E05 | B79: Dos personas de IGUAL peso (80 kg) y el MISMO día de actividades, pero con distinto GEB, deben recibir un PAL ESTIMADO DISTINTO. Si el libro devolviera el mismo, seguiría equiparando el índice MET con el PAL. | C79: 1600 | D79: 1900 | E79: =IF(OR(NOT(ISNUMBER(ACTIVIDADES!$B$21)),NOT(ISNUMBER($C79)),NOT(ISNUMBER($D79)),$C79<=0,$D79<=0),"ND",ACTIVIDADES!$B$21*80*MET_KCAL/$C79-ACTIVIDADES!$B$21*80*MET_KCAL/$D79) -> 0.34184211 | F79: distinto de 0 | G79: =IF(NOT(ISNUMBER($E79)),"ND","—") -> — | H79: =IF(NOT(ISNUMBER($E79)),"FALLIDO",IF(ABS($E79)>0.001,"APROBADO","FALLIDO")) -> APROBADO
A81: BLOQUE F · INTEGRIDAD: cero errores de Excel (VALUE, DIV/0, REF, N/A, NAME, NUM) en las hojas de cálculo
A82: ID | B82: Rango verificado | C82: Nº de celdas con error | D82: Esperado | E82: Estado
A83: F01 | B83: CALCULOS!B7:B82 (toda la cadena de cálculo) | C83: =SUMPRODUCT(--ISERROR(CALCULOS!$B$7:$B$82)) -> 0 | D83: 0 | E83: =IF($C83=$D83,"APROBADO","FALLIDO") -> APROBADO
A84: F02 | B84: ECUACIONES!F7:F13 (las 7 ecuaciones) | C84: =SUMPRODUCT(--ISERROR(ECUACIONES!$F$7:$F$13)) -> 0 | D84: 0 | E84: =IF($C84=$D84,"APROBADO","FALLIDO") -> APROBADO
A85: F03 | B85: RESULTADOS!B5:B78 (informe completo) | C85: =SUMPRODUCT(--ISERROR(RESULTADOS!$B$5:$B$78)) -> 0 | D85: 0 | E85: =IF($C85=$D85,"APROBADO","FALLIDO") -> APROBADO
A87: BLOQUE G · PRESENTACIÓN Y LOCALIZACIÓN REGIONAL (corrección QA NMX-QA-01)
A88: ID | B88: Verificación | C88: Entrada | D88: Obtenido | E88: Esperado | F88: Estado
A89: G01 | B89: RESULTADOS!B9 presenta el MISMO peso que usa el motor | D89: =IF(NOT(ISNUMBER(in_Peso)),"ND",IF(ISNUMBER(FIND(""&ROUND(in_Peso,1),RESULTADOS!$B$9)),"EL VALOR PRESENTADO COINCIDE","EL VALOR PRESENTADO NO COINCIDE")) -> EL VALOR PRESENTADO COINCIDE | E89: EL VALOR PRESENTADO COINCIDE | F89: =IF($D89=$E89,"APROBADO","FALLIDO") -> APROBADO
A90: G02 | B90: RESULTADOS!B9 presenta la MISMA estatura que usa el motor | D90: =IF(NOT(ISNUMBER(in_Est)),"ND",IF(ISNUMBER(FIND(""&ROUND(in_Est,0),RESULTADOS!$B$9)),"EL VALOR PRESENTADO COINCIDE","EL VALOR PRESENTADO NO COINCIDE")) -> EL VALOR PRESENTADO COINCIDE | E90: EL VALOR PRESENTADO COINCIDE | F90: =IF($D90=$E90,"APROBADO","FALLIDO") -> APROBADO
A91: G03 | B91: RESULTADOS!B11 presenta la MISMA MLG que usa el motor | D91: =IF(NOT(ISNUMBER(CALCULOS!$B$10)),"ND",IF(ISNUMBER(FIND(""&ROUND(CALCULOS!$B$10,1),RESULTADOS!$B$11)),"EL VALOR PRESENTADO COINCIDE","EL VALOR PRESENTADO NO COINCIDE")) -> EL VALOR PRESENTADO COINCIDE | E91: EL VALOR PRESENTADO COINCIDE | F91: =IF($D91=$E91,"APROBADO","FALLIDO") -> APROBADO
A92: G04 | B92: RESULTADOS!B12 presenta el MISMO factor de actividad que usa el motor ◄ DEFECTO NMX-QA-01 | D92: =IF(NOT(ISNUMBER(CALCULOS!$B$13)),"ND",IF(ISNUMBER(FIND(""&ROUND(CALCULOS!$B$13,3),RESULTADOS!$B$12)),"EL VALOR PRESENTADO COINCIDE","EL VALOR PRESENTADO NO COINCIDE")) -> EL VALOR PRESENTADO COINCIDE | E92: EL VALOR PRESENTADO COINCIDE | F92: =IF($D92=$E92,"APROBADO","FALLIDO") -> APROBADO
A93: G05 | B93: Un FA de 1,55 no se corrompe a 0,002 al presentarse | C93: 1.55 | D93: =ROUND($C93,3) -> 1.55 | E93: 1.55 | F93: =IF(AND(ISNUMBER($D93),ABS($D93-$E93)<=0.0005),"APROBADO","FALLIDO") -> APROBADO
A94: G06 | B94: GEB 1340,25 × (FA 1,55 − 1) → GAF exacto | C94: 1340.25 | D94: =$C94*(1.55-1) -> 737.1375 | E94: 737.1375 | F94: =IF(AND(ISNUMBER($D94),ABS($D94-$E94)<=0.0005),"APROBADO","FALLIDO") -> APROBADO
A95: G07 | B95: GAF presentado con 2 decimales | C95: 1340.25 | D95: =ROUND($C95*(1.55-1),2) -> 737.14 | E95: 737.14 | F95: =IF(AND(ISNUMBER($D95),ABS($D95-$E95)<=0.0005),"APROBADO","FALLIDO") -> APROBADO
A96: G08 | B96: Un peso de 68,5 conserva su decimal al presentarse | C96: 68.5 | D96: =ROUND($C96,1) -> 68.5 | E96: 68.5 | F96: =IF(AND(ISNUMBER($D96),ABS($D96-$E96)<=0.0005),"APROBADO","FALLIDO") -> APROBADO
A97: G09 | B97: Una MLG de 52,4 conserva su decimal al presentarse | C97: 52.4 | D97: =ROUND($C97,1) -> 52.4 | E97: 52.4 | F97: =IF(AND(ISNUMBER($D97),ABS($D97-$E97)<=0.0005),"APROBADO","FALLIDO") -> APROBADO
A98: G10 | B98: Observaciones VACÍAS → se presenta un guion, no un cero | D98: =IF($C98="","—",$C98) -> — | E98: — | F98: =IF($D98=$E98,"APROBADO","FALLIDO") -> APROBADO
A99: G11 | B99: Observaciones CON TEXTO → se reproduce el texto íntegro | C99: Paciente con hipotiroidismo controlado. | D99: =IF($C99="","—",$C99) -> Paciente con hipotiroidismo controlado. | E99: Paciente con hipotiroidismo controlado. | F99: =IF($D99=$E99,"APROBADO","FALLIDO") -> APROBADO
A100: G12 | B100: RESULTADOS!B13 coincide con la guarda aplicada al valor real de DATOS | D100: =RESULTADOS!$B$13 -> — | E100: =IF(DATOS!$B$28="","—",DATOS!$B$28) -> — | F100: =IF($D100=$E100,"APROBADO","FALLIDO") -> APROBADO
A101: G01–G04 son pruebas DE COMPORTAMIENTO, no de inspección: comprueban que el número que aparece escrito en el informe sea literalmente el mismo que usa el motor. Con el defecto NMX-QA-01, en un Excel en español RESULTADOS!B12 contenía '0,002' mientras el motor usaba 1,55 y la búsqueda fallaba. Al no depender de FORMULATEXT ni de la configuración regional, estas pruebas detectan la reaparición del defecto en cualquier instalación de Excel.
A103: BLOQUE I · DERIVACIÓN DE LA MASA LIBRE DE GRASA (independiente del motor) · NUEVO en v1.1.2
A104: ID | B104: Escenario | C104: MLG ingresada (kg) | D104: % de grasa | E104: Peso (kg) | F104: MLG obtenida (regla replicada) | G104: MLG esperada (a mano) | H104: Estado
A105: I01 | B105: MLG medida válida | C105: 60 | E105: 80 | F105: =IF(OR(NOT(ISNUMBER($E105)),$E105<=0),"ND",IF(AND(NOT(ISBLANK($C105)),ISNUMBER($C105),$C105>0,$C105<$E105),$C105,IF(AND(NOT(ISBLANK($D105)),ISNUMBER($D105),$D105>=GRASA_MIN,$D105<=GRASA_MAX),$E105*(1-$D105),"ND"))) -> 60 | G105: 60 | H105: =IF(AND(ISNUMBER($F105),ISNUMBER($G105)),IF(ABS($F105-$G105)<=0.0001,"APROBADO","FALLIDO"),IF(AND(NOT(ISNUMBER($F105)),NOT(ISNUMBER($G105))),IF($F105=$G105,"APROBADO","FALLIDO"),"FALLIDO")) -> APROBADO
A106: I02 | B106: MLG derivada del % de grasa (20 %) | D106: 0.2 | E106: 80 | F106: =IF(OR(NOT(ISNUMBER($E106)),$E106<=0),"ND",IF(AND(NOT(ISBLANK($C106)),ISNUMBER($C106),$C106>0,$C106<$E106),$C106,IF(AND(NOT(ISBLANK($D106)),ISNUMBER($D106),$D106>=GRASA_MIN,$D106<=GRASA_MAX),$E106*(1-$D106),"ND"))) -> 64 | G106: 64 | H106: =IF(AND(ISNUMBER($F106),ISNUMBER($G106)),IF(ABS($F106-$G106)<=0.0001,"APROBADO","FALLIDO"),IF(AND(NOT(ISNUMBER($F106)),NOT(ISNUMBER($G106))),IF($F106=$G106,"APROBADO","FALLIDO"),"FALLIDO")) -> APROBADO
A107: I03 | B107: MLG AUSENTE: ni MLG medida ni % de grasa | E107: 80 | F107: =IF(OR(NOT(ISNUMBER($E107)),$E107<=0),"ND",IF(AND(NOT(ISBLANK($C107)),ISNUMBER($C107),$C107>0,$C107<$E107),$C107,IF(AND(NOT(ISBLANK($D107)),ISNUMBER($D107),$D107>=GRASA_MIN,$D107<=GRASA_MAX),$E107*(1-$D107),"ND"))) -> ND | G107: ND | H107: =IF(AND(ISNUMBER($F107),ISNUMBER($G107)),IF(ABS($F107-$G107)<=0.0001,"APROBADO","FALLIDO"),IF(AND(NOT(ISNUMBER($F107)),NOT(ISNUMBER($G107))),IF($F107=$G107,"APROBADO","FALLIDO"),"FALLIDO")) -> APROBADO
A108: I04 | B108: MLG IGUAL al peso (imposible) | C108: 80 | E108: 80 | F108: =IF(OR(NOT(ISNUMBER($E108)),$E108<=0),"ND",IF(AND(NOT(ISBLANK($C108)),ISNUMBER($C108),$C108>0,$C108<$E108),$C108,IF(AND(NOT(ISBLANK($D108)),ISNUMBER($D108),$D108>=GRASA_MIN,$D108<=GRASA_MAX),$E108*(1-$D108),"ND"))) -> ND | G108: ND | H108: =IF(AND(ISNUMBER($F108),ISNUMBER($G108)),IF(ABS($F108-$G108)<=0.0001,"APROBADO","FALLIDO"),IF(AND(NOT(ISNUMBER($F108)),NOT(ISNUMBER($G108))),IF($F108=$G108,"APROBADO","FALLIDO"),"FALLIDO")) -> APROBADO
A109: I05 | B109: MLG SUPERIOR al peso (imposible) | C109: 90 | E109: 80 | F109: =IF(OR(NOT(ISNUMBER($E109)),$E109<=0),"ND",IF(AND(NOT(ISBLANK($C109)),ISNUMBER($C109),$C109>0,$C109<$E109),$C109,IF(AND(NOT(ISBLANK($D109)),ISNUMBER($D109),$D109>=GRASA_MIN,$D109<=GRASA_MAX),$E109*(1-$D109),"ND"))) -> ND | G109: ND | H109: =IF(AND(ISNUMBER($F109),ISNUMBER($G109)),IF(ABS($F109-$G109)<=0.0001,"APROBADO","FALLIDO"),IF(AND(NOT(ISNUMBER($F109)),NOT(ISNUMBER($G109))),IF($F109=$G109,"APROBADO","FALLIDO"),"FALLIDO")) -> APROBADO
A110: I06 | B110: MLG inválida (>peso) pero % de grasa válido → cae a la derivación | C110: 90 | D110: 0.25 | E110: 80 | F110: =IF(OR(NOT(ISNUMBER($E110)),$E110<=0),"ND",IF(AND(NOT(ISBLANK($C110)),ISNUMBER($C110),$C110>0,$C110<$E110),$C110,IF(AND(NOT(ISBLANK($D110)),ISNUMBER($D110),$D110>=GRASA_MIN,$D110<=GRASA_MAX),$E110*(1-$D110),"ND"))) -> 60 | G110: 60 | H110: =IF(AND(ISNUMBER($F110),ISNUMBER($G110)),IF(ABS($F110-$G110)<=0.0001,"APROBADO","FALLIDO"),IF(AND(NOT(ISNUMBER($F110)),NOT(ISNUMBER($G110))),IF($F110=$G110,"APROBADO","FALLIDO"),"FALLIDO")) -> APROBADO
...

Sheet CONFIG
A1: CONFIGURACIÓN · Parámetros, coeficientes y catálogos · DEFINITIVO 2026 · NMX-ACT-2024-v1
A2: Toda constante del modelo vive aquí; ninguna fórmula contiene un coeficiente escrito a mano. Las celdas arena son editables. Las tablas con fondo lila son NUEVAS o MODIFICADAS en la v1.1.
A3: =HYPERLINK("#INICIO!A1","◀ INICIO") -> ◀ INICIO
A4: C1 · PARÁMETROS · LÍMITES DE 'DATO IMPOSIBLE' Y UMBRALES DE 'DATO POCO FRECUENTE'
A5: Parámetro | B5: Valor | C5: Unidad | D5: Tipo | E5: Nota / fuente
A6: Idioma | B6: Español (es-CL) | C6: — | D6: — | E6: Interfaz
A7: Versión de las fuentes | B7: 2026-08 · DEFINITIVO 2026 · NMX-PAL-2026-08-v1 · NMX-ACT-2024-v1 | C7: — | D7: — | E7: Ver hoja FUENTES
A8: Factor energético · proteína | B8: 4 | C8: kcal/g | D8: Constante | E8: Sistema general de Atwater (Merrill & Watt, USDA AH-74, 1973)
A9: Factor energético · grasa | B9: 9 | C9: kcal/g | D9: Constante | E9: Sistema general de Atwater (Merrill & Watt, USDA AH-74, 1973)
A10: Factor energético · carbohidratos | B10: 4 | C10: kcal/g | D10: Constante | E10: Sistema general de Atwater (Merrill & Watt, USDA AH-74, 1973)
A11: Edad mínima (adulto) | B11: 18 | C11: años | D11: IMPOSIBLE | E11: Alcance v1.0/v1.1: solo adultos
A12: Edad máxima plausible | B12: 120 | C12: años | D12: IMPOSIBLE | E12: Límite operativo
A13: Peso mínimo posible | B13: 25 | C13: kg | D13: IMPOSIBLE | E13: Bajo este valor se considera imposible en un adulto
A14: Peso máximo posible | B14: 350 | C14: kg | D14: IMPOSIBLE | E14: Límite operativo
A15: Estatura mínima posible | B15: 120 | C15: cm | D15: IMPOSIBLE | E15: Límite operativo
A16: Estatura máxima posible | B16: 230 | C16: cm | D16: IMPOSIBLE | E16: Límite operativo
A17: % de grasa mínimo | B17: 0.03 | C17: % | D17: IMPOSIBLE | E17: Grasa esencial
A18: % de grasa máximo | B18: 0.75 | C18: % | D18: IMPOSIBLE | E18: Límite operativo
A19: Factor de actividad mínimo | B19: 1 | C19: — | D19: IMPOSIBLE | E19: Un FA < 1 implicaría gastar menos que el basal
... A37: Tolerancia RELATIVA del contraste MJ ↔ kcal (Henry) | B37: 0.01 | C37: % | D37: Umbral · NUEVO v1.1 | E37: La tabla en kcal de Henry está REDONDEADA a 3 cifras significativas: difiere de su propia tabla en MJ hasta ~4,6 kcal (≈0,3 %). El contraste sirve para detectar una conversión DUPLICADA u OMITIDA, que daría cientos de kcal de error, no unidades. Por eso el umbral es relativo (1 %) y no absoluto
A39: C2 · SEXO BIOLÓGICO
A40: Valor | B40: Nota
A41: Hombre | B41: Coeficientes derivados en varones
A42: Mujer | B42: Coeficientes derivados en mujeres
A44: C3 · MÉTODO DE ACTIVIDAD
A45: Método | B45: Descripción
A46: Factor de actividad global | B46: Factor único del catálogo C4, o el factor manual de DATOS.
A47: Cálculo por actividades | B47: NMX-ACT-2024-v1: el registro de 24 h selecciona Adult MET (19–59), Older Adult MET60+ (≥60) o Wheelchair METWC según edad y movilidad.
A49: C4 · SELECTOR PAL PRÁCTICO · NMX-PAL-2026-08-v1
A50: Etiqueta | B50: Factor | C50: Rango FAO | D50: Fuente puntual / rango | E50: Categoría FAO | F50: PAL mín. | G50: PAL máx. | H50: Fuente canónica
A51: Muy sedentario · PAL 1,40 | B51: 1.4 | C51: 1,40–1,69 | D51: FoodWorks 2026 · FAO 2004 | E51: Sedentario o actividad ligera | F51: 1.4 | G51: 1.69 | H51: FAO/WHO/UNU 2004 · Tabla 5.3
A52: Sedentario · PAL 1,50 | B52: 1.5 | C52: 1,40–1,69 | D52: FoodWorks 2026 · FAO 2004 | E52: Activo o moderadamente activo | F52: 1.7 | G52: 1.99 | H52: FAO/WHO/UNU 2004 · Tabla 5.3
A53: Ligero · PAL 1,60 | B53: 1.6 | C53: 1,40–1,69 | D53: FoodWorks 2026 · FAO 2004 | E53: Vigoroso o vigorosamente activo | F53: 2 | G53: 2.4 | H53: FAO/WHO/UNU 2004 · Tabla 5.3
A54: Ligero-moderado · PAL 1,70 | B54: 1.7 | C54: 1,70–1,99 | D54: FoodWorks 2026 · FAO 2004
A55: Moderado · PAL 1,80 | B55: 1.8 | C55: 1,70–1,99 | D55: FoodWorks 2026 · FAO 2004 | E55: Reposo / inmovilidad excepcional | F55: 1.2 | G55: Uso especial | H55: No selector general · FoodWorks 2026 · FAO §5.3.2
A56: Pesado / vigoroso · PAL 2,00 | B56: 2 | C56: 2,00–2,40 | D56: FoodWorks 2026 · FAO 2004
A57: Muy pesado / muy vigoroso · PAL 2,20 | B57: 2.2 | C57: 2,00–2,40 | D57: FoodWorks 2026 · FAO 2004
A58: FoodWorks 2026 = selector práctico. FAO/WHO/UNU 2004 = rangos 1,40–1,69 · 1,70–1,99 · 2,00–2,40. PAL 1,20: solo reposo/inmovilidad excepcional.
A59: C5 · OBJETIVOS
A60: Objetivo | B60: % de ajuste sugerido | C60: Nota
A61: Mantenimiento | B61: 0 | C61: Sin ajuste: la energía objetivo es igual al GET.
A62: Reducción de peso | B62: -0.15 | C62: Sugerencia referencial. El % real lo escribe usted en DATOS.
A63: Aumento de peso | B63: 0.1 | C63: Sugerencia referencial. El % real lo escribe usted en DATOS.
A64: Ajuste personalizado | B64: 0 | C64: El % lo define íntegramente el profesional.
A66: C6 · TRATAMIENTO DEL EFECTO TÉRMICO DE LOS ALIMENTOS (ETA)
A67: Modo | B67: Qué hace | C67: Riesgo de doble conteo
A68: Incluido en el factor de actividad (recomendado) | B68: ETA = 0. Por definición, el PAL ya contiene el ETA. | C68: Ninguno.
A69: Explícito · % del gasto basal + actividad | B69: ETA = %ETA × (GEB + GAF). | C69: ALTO si el FA es un PAL: el ETA se contaría dos veces.
A70: Explícito · % de la energía total | B70: ETA = (GEB + GAF) × %ETA / (1 − %ETA). | C70: ALTO si el FA es un PAL. Solo válido si su factor EXCLUYE el ETA y puede documentarlo.
A72: C7 · MODO DE DISTRIBUCIÓN DE PROTEÍNA Y GRASA
A73: Modo | B73: Interpretación del valor ingresado en DATOS
A74: % de la energía | B74: Fracción de la energía objetivo (0,25 = 25 %).
A75: g/kg de peso | B75: Gramos por kg de peso corporal (1,6 = 1,6 g/kg).
A76: Prioridad explícita: el modo elegido para cada macro se aplica de forma EXCLUYENTE. Nunca se aplican simultáneamente la regla de % y la de g/kg sobre el mismo macronutriente.
A77: C8 · COEFICIENTES LINEALES · GEB = a + b_peso·P + b_estatura·T + b_edad·E + b_MLG·MLG
A78: ID | B78: Ecuación | C78: Sexo | D78: a | E78: b_peso (kg) | F78: b_estatura (cm) | G78: b_edad (años) | H78: b_MLG (kg)
A79: E1 | B79: Mifflin–St Jeor (1990) | C79: Hombre | D79: 5 | E79: 10 | F79: 6.25 | G79: -5 | H79: 0
A80: E1 | B80: Mifflin–St Jeor (1990) | C80: Mujer | D80: -161 | E80: 10 | F80: 6.25 | G80: -5 | H80: 0
A81: E2 | B81: Harris–Benedict revisada · Roza & Shizgal (1984) | C81: Hombre | D81: 88.362 | E81: 13.397 | F81: 4.799 | G81: -5.677 | H81: 0
A82: E2 | B82: Harris–Benedict revisada · Roza & Shizgal (1984) | C82: Mujer | D82: 447.593 | E82: 9.247 | F82: 3.098 | G82: -4.33 | H82: 0
A83: E3 | B83: Owen (1986/1987) | C83: Hombre | D83: 879 | E83: 10.2 | F83: 0 | G83: 0 | H83: 0
A84: E3 | B84: Owen (1986/1987) | C84: Mujer | D84: 795 | E84: 7.18 | F84: 0 | G84: 0 | H84: 0
A85: E4 | B85: Cunningham (1980) | C85: Hombre | D85: 500 | E85: 0 | F85: 0 | G85: 0 | H85: 22
A86: E4 | B86: Cunningham (1980) | C86: Mujer | D86: 500 | E86: 0 | F86: 0 | G86: 0 | H86: 22
A87: E5 | B87: Cunningham (1991) · alias secundario: Katch–McArdle | C87: Hombre | D87: 370 | E87: 0 | F87: 0 | G87: 0 | H87: 21.6
A88: E5 | B88: Cunningham (1991) · alias secundario: Katch–McArdle | C88: Mujer | D88: 370 | E88: 0 | F88: 0 | G88: 0 | H88: 21.6
A90: C9 · SCHOFIELD (1985) — TABLA CANÓNICA ADULTA · MODIFICADA EN v1.1 · GEB = a + b·P
A91: Sexo | B91: Edad desde (≥) | C91: Edad hasta (<) | D91: b_peso (kcal/kg) | E91: a (kcal) | F91: Ecuación original (MJ/día) | G91: Nota de unidades
A92: Hombre | B92: 18 | C92: 30 | D92: 15.057 | E92: 692.2 | F92: 0,063·P + 2,896 MJ/día | G92: kcal = MJ × 239,0057
A93: Hombre | B93: 30 | C93: 60 | D93: 11.472 | E93: 873.1 | F93: 0,048·P + 3,653 MJ/día | G93: kcal = MJ × 239,0057
A94: Hombre | B94: 60 | C94: 200 | D94: 11.711 | E94: 587.7 | F94: 0,049·P + 2,459 MJ/día | G94: kcal = MJ × 239,0057
A95: Mujer | B95: 18 | C95: 30 | D95: 14.818 | E95: 486.6 | F95: 0,062·P + 2,036 MJ/día | G95: kcal = MJ × 239,0057
A96: Mujer | B96: 30 | C96: 60 | D96: 8.126 | E96: 845.6 | F96: 0,034·P + 3,538 MJ/día | G96: kcal = MJ × 239,0057
A97: Mujer | B97: 60 | C97: 200 | D97: 9.082 | E97: 658.5 | F97: 0,038·P + 2,755 MJ/día | G97: kcal = MJ × 239,0057
A98: TABLA CANÓNICA ÚNICA. La v1.0 usaba la tabla FAO/WHO/UNU redondeada en kcal (15,3P+679 …), que NO es la misma. Se conserva abajo SOLO como documentación histórica y NO está conectada al motor.
A99: C9b · TABLA FAO/WHO/UNU 1985 (kcal redondeadas) — DOCUMENTACIÓN HISTÓRICA · NO CONECTADA AL MOTOR
A100: Sexo | B100: Edad desde | C100: Edad hasta | D100: b_peso (kcal/kg) | E100: a (kcal) | F100: Uso
A101: Hombre | B101: 18 | C101: 30 | D101: 15.3 | E101: 679 | F101: Usada por NMX-01 v1.0. Ya NO se usa.
A102: Hombre | B102: 30 | C102: 60 | D102: 11.6 | E102: 879 | F102: Usada por NMX-01 v1.0. Ya NO se usa.
A103: Hombre | B103: 60 | C103: 200 | D103: 13.5 | E103: 487 | F103: Usada por NMX-01 v1.0. Ya NO se usa.
A104: Mujer | B104: 18 | C104: 30 | D104: 14.7 | E104: 496 | F104: Usada por NMX-01 v1.0. Ya NO se usa.
A105: Mujer | B105: 30 | C105: 60 | D105: 8.7 | E105: 829 | F105: Usada por NMX-01 v1.0. Ya NO se usa.
A106: Mujer | B106: 60 | C106: 200 | D106: 10.5 | E106: 596 | F106: Usada por NMX-01 v1.0. Ya NO se usa.
A108: C10 · HENRY / OXFORD (2005) — SOLO PESO · NUEVO EN v1.1 · GEB = a + b·P
A109: Sexo | B109: Edad desde (≥) | C109: Edad hasta (<) | D109: b_peso (kcal/kg) | E109: a (kcal) | F109: b_peso (MJ/kg) | G109: a (MJ)
A110: Hombre | B110: 18 | C110: 30 | D110: 16 | E110: 545 | F110: 0.0669 | G110: 2.28
A111: Hombre | B111: 30 | C111: 60 | D111: 14.2 | E111: 593 | F111: 0.0592 | G111: 2.48
A112: Hombre | B112: 60 | C112: 200 | D112: 13.5 | E112: 514 | F112: 0.0563 | G112: 2.15
A113: Mujer | B113: 18 | C113: 30 | D113: 13.1 | E113: 558 | F113: 0.0546 | G113: 2.33
A114: Mujer | B114: 30 | C114: 60 | D114: 9.74 | E114: 694 | F114: 0.0407 | G114: 2.9
A115: Mujer | B115: 60 | C115: 200 | D115: 10.1 | E115: 569 | F115: 0.0424 | G115: 2.38
A116: El motor usa la columna en kcal. Las columnas en MJ están para el contraste de unidades de la hoja PRUEBAS: la tabla en kcal de Henry es una conversión REDONDEADA (3 cifras significativas) de la tabla en MJ, así que no coinciden al decimal. La discrepancia medida por PRUEBAS llega hasta 4,64 kcal (0,315 %) en el rango de pesos probado. Eso NO es un error de doble conversión: una conversión duplicada u omitida daría CIENTOS de kcal. Por eso la tolerancia del contraste es RELATIVA (1 %) y no absoluta.
A118: C11 · CATÁLOGO DE ECUACIONES · niveles de verificación A / B / C
A119: ID | B119: Nombre (lista desplegable) | C119: Edad mín. | D119: Edad máx. | E119: Requiere MLG | F119: Requiere estatura | G119: Variables indispensables de la ECUACIÓN | H119: Nivel | I119: Justificación del nivel
A120: E1 | B120: Mifflin–St Jeor (1990) | C120: 19 | D120: 78 | E120: NO | F120: SÍ | G120: sexo, peso, estatura, edad | H120: B | I120: Resumen primario exacto; corroboración consistente. DOI 10.1093/ajcn/51.2.241
A121: E2 | B121: Harris–Benedict revisada · Roza & Shizgal (1984) | C121: 18 | D121: 99 | E121: NO | F121: SÍ | G121: sexo, peso, estatura, edad | H121: A | I121: Cotejada contra PDF primario (tabla 3). DOI 10.1093/ajcn/40.1.168
A122: E3 | B122: Owen (1986/1987) | C122: 18 | D122: 82 | E122: NO | F122: NO | G122: sexo, peso | H122: B | I122: Corroborada en literatura revisada por pares; texto completo tras acceso editorial
A123: E4 | B123: Cunningham (1980) | C123: 18 | D123: 99 | E123: SÍ | F123: NO | G123: MLG | H123: A | I123: PDF primario accesible. DOI 10.1093/ajcn/33.11.2372
A124: E5 | B124: Cunningham (1991) · alias secundario: Katch–McArdle | C124: 18 | D124: 99 | E124: SÍ | F124: NO | G124: MLG (FFM) | H124: B | I124: Fuente primaria de 370+21,6·FFM: Cunningham 1991, DOI 10.1093/ajcn/54.6.963. El nombre 'Katch–McArdle' es un alias de nivel C
A125: E6 | B125: Schofield (1985) adultos · tabla canónica | C125: 18 | D125: 110 | E125: NO | F125: NO | G125: sexo, peso, banda etaria | H125: B | I125: Referencia primaria; tabla canónica derivada de MJ/día. NO mezclar con la tabla FAO redondeada en kcal
...

Sheet CHANGELOG
A1: CHANGELOG
A2: =HYPERLINK("#INICIO!A1","◀ INICIO") -> ◀ INICIO
A4: Versión | B4: Fecha | C4: Prio | D4: Cambio | E4: Motivo / fuente | F4: Impacto numérico | G4: Responsable
A5: 1.0 | B5: 2026-07-12 | C5: — | D5: Versión inicial. 10 hojas, 6 ecuaciones, 31 casos de prueba. | E5: Primera entrega de NMX-01. | F5: — | G5: Equipo Nutrimetría
A6: 1.1 | B6: 2026-07-12 | C6: P0 | D6: REATRIBUCIÓN: la fórmula 370 + 21,6 × MLG deja de atribuirse a 'Katch–McArdle' (libro de texto) y pasa a 'Cunningham (1991) · alias secundario: Katch–McArdle'. Sube de nivel C a nivel B. | E6: Dossier §2 y §7. Fuente primaria: Cunningham JJ, Am J Clin Nutr 1991;54:963-969, DOI 10.1093/ajcn/54.6.963. Cunningham 1980 (500+22·MLG) y Cunningham 1991 (370+21,6·FFM) son ecuaciones DISTINTAS y se mantienen separadas. | F6: NINGUNO. Los coeficientes 370 y 21,6 no cambian. | G6: Equipo Nutrimetría
A7: 1.1 | B7: 2026-07-12 | C7: P0 | D7: MET → PAL: el promedio de METs deja de usarse como factor de actividad. Ahora ACTIVIDADES calcula TEE = Σ(MET×h) × Peso × 1 kcal/kg/h y luego PAL = TEE / GEB. | E7: Dossier §5: un MET es múltiplo del reposo ESTÁNDAR (≈1 kcal/kg/h), no del GEB individual. FAO define PAL = TEE/BMR. Promediar MET×h produce un índice MET-h/día, NO el PAL. | F7: SÍ. Con el día de ejemplo, el factor pasa de 1,669 (índice MET, v1.0) a 1,853 (PAL ESTIMADO como TEE/GEB, v1.1) para un GEB de 1720. Sigue siendo una APROXIMACIÓN: el MET parte de un reposo estándar, no del metabolismo individual. Dos personas de igual peso y distinto GEB ahora reciben PAL distinto. | G7: Equipo Nutrimetría
A8: 1.1 | B8: 2026-07-12 | C8: P0 | D8: El MET de 'Dormir' (código 07030) se corrige de 0,95 a 1,0. | E8: Dossier §5, tabla de códigos verificados del Compendium 2011. | F8: SÍ. Σ(MET×h) del día de ejemplo aumenta en 0,4 MET·h. | G8: Equipo Nutrimetría
A9: 1.1 | B9: 2026-07-12 | C9: P1 | D9: SE AÑADE Henry / Oxford (2005), solo peso, con bandas adultas 18≤E<30, 30≤E<60 y E≥60 (ecuación E7). Se guardan también las columnas en MJ/día para el contraste de unidades. | E9: Dossier §3, tabla 12. Henry CJK, Public Health Nutr 2005;8(7A):1133-52, DOI 10.1079/PHN2005801. NIVEL A. La v1.0 la omitió por no poder verificar los coeficientes. | F9: SÍ. Hay una séptima ecuación: cambian el promedio, la mediana, el mínimo, el máximo y el rango. | G9: Equipo Nutrimetría
A10: 1.1 | B10: 2026-07-12 | C10: P1 | D10: SCHOFIELD: se congela una TABLA CANÓNICA ÚNICA (H: 15,057/11,472/11,711 · M: 14,818/8,126/9,082), derivada de la publicación en MJ/día. La tabla anterior queda en CONFIG C9b, documentada y DESCONECTADA del motor. | E10: Dossier §2: 'fijar una sola tabla canónica; no mezclar versiones redondeadas en kJ/MJ'. La v1.0 usaba la tabla FAO/WHO/UNU redondeada en kcal (15,3·P+679 …), que NO es la misma tabla. | F10: SÍ, Y ES EL CAMBIO CON MÁS IMPACTO EN EL GEB. Ejemplos: hombre 40 a / 90 kg: 1923 → 1905,6 kcal (−17,4). Mujer 65 a / 68 kg: 1310 → 1276,1 kcal (−33,9). Los casos A09 y A10 de PRUEBAS actualizan su valor esperado. | G10: Equipo Nutrimetría
A11: 1.1 | B11: 2026-07-12 | C11: P1 | D11: Los códigos MET 17190 (caminar) y 11210 (cargar objetos pesados) se DEGRADAN a nivel C. Salen del día de ejemplo. | E11: No figuran entre los ocho códigos verificados del dossier. La v1.0 marcaba uno de ellos como 'verificado': era una afirmación que no podíamos sostener. | F11: Ninguno mientras no se usen. El día de ejemplo se reconstruyó solo con códigos de nivel A. | G11: Equipo Nutrimetría
A12: 1.1 | B12: 2026-07-12 | C12: P1 | D12: SIN CAMBIO (confirmación): GAF = GEB × (FA − 1); ETA = 0 por defecto; GET = GEB + GAF + ETA. Se conservan las advertencias visibles de doble conteo en CALCULOS y en RESULTADOS cuando se activa un ETA explícito sobre un PAL. | E12: Dossier §4: la arquitectura es algebraicamente correcta cuando el FA es un PAL completo. | F12: Ninguno. | G12: Equipo Nutrimetría
A13: 1.1 | B13: 2026-07-12 | C13: P2 | D13: Los códigos MET se guardan como TEXTO de cinco dígitos (07030, 05035, 05140…). | E13: Dossier §5 y §7: conservar los ceros iniciales. | F13: Ninguno (formato). | G13: Equipo Nutrimetría
A14: 1.1 | B14: 2026-07-12 | C14: P2 | D14: Documentación: se añade el nivel de verificación A/B/C a cada fuente y a cada ecuación; el efecto térmico pasa de '≈10 %' a '5–15 %' (Westerterp 2004); los factores de Atwater se atribuyen a Merrill & Watt (USDA AH-74, 1973); se repite en INICIO, RESULTADOS, FUENTES y CHANGELOG que exactitud matemática ≠ validación clínica. | E14: Dossier §6, §7 y §9. | F14: Ninguno. | G14: Equipo Nutrimetría
A15: 1.1 | B15: 2026-07-12 | C15: — | D15: PRUEBAS: de 31 casos (v1.0) a 54 (v1.1). Nuevos bloques H (13 casos de Henry, con fronteras de edad exactas y contraste MJ↔kcal), E (5 casos de MET→PAL, incluida la prueba de dos personas con igual peso y distinto GEB) y F (3 casos de integridad de Excel). Bloque C ampliado con macros al 100 %, 99,9 % y 100,1 %. | E15: Pruebas obligatorias solicitadas + criterios de aceptación del dossier. | F15: A09 y A10 cambian su valor ESPERADO por la nueva tabla de Schofield (cambio esperado, no un fallo). | G15: Equipo Nutrimetría
... A27: DEFINITIVO 2026 | B27: 2026-08-08 | C27: FINAL/P0 | D27: Cierre NMX-01: motor auditable por edad/movilidad, revalidación dinámica y bloqueo TEE/PAL ante cambio de catálogo. | E27: FAO/WHO/UNU 2004 + Adult/Older Adult/Wheelchair Compendia 2024. | F27: Evita resultados espurios en 59→60 o Ambulante→Silla de ruedas; no altera ecuaciones GEB válidas. | G27: Equipo Nutrimetría

Sheet AUDITORIA
A1: AUDITORIA · Registro de verificación · DEFINITIVO 2026
A2: Hoja AÑADIDA en la v1.1.1 al final del libro, sin alterar el orden de las diez hojas originales. Contiene los entregables de verificación que antes solo existían fuera del archivo: los recálculos manuales, los escenarios adversariales y la lista PRINCIPAL de celdas modificadas. AVISO: esa lista NO es exhaustiva — recoge los cambios de fondo, no cada celda de texto o formato. El registro completo de cambios está en el CHANGELOG. Es un REGISTRO ESTÁTICO; las pruebas VIVAS y reejecutables están en la hoja PRUEBAS.
A4: =HYPERLINK("#INICIO!A1","◀ INICIO") -> ◀ INICIO
A6: 1 · TRES RECÁLCULOS MANUALES COMPLETOS (cálculo a mano, independiente del libro, contra las celdas reales)
A7: Caso | B7: Configuración | C7: Variable | D7: Cálculo MANUAL | E7: Valor del LIBRO | F7: Diferencia | G7: Estado
A8: M1 | B8: Hombre 34 a · 78,5 kg · 176 cm · 18 % grasa · Mifflin · PAL 1,85 (catálogo) · ETA modo 1 · ajuste −15 % · proteína 1,6 g/kg · grasa 30 % | C8: GEB | D8: 10×78,5 + 6,25×176 − 5×34 + 5 = 1720 | E8: 1720 | F8: 0 | G8: COINCIDE
C9: GAF | D9: 1720 × (1,85 − 1) = 1462 | E9: 1462 | F9: 0 | G9: COINCIDE
C10: ETA | D10: modo 1 → 0 | E10: 0 | F10: 0 | G10: COINCIDE
C11: GET | D11: 1720 + 1462 + 0 = 3182 | E11: 3182 | F11: 0 | G11: COINCIDE
C12: Energía objetivo | D12: 3182 × (1 − 0,15) = 2704,7 | E12: 2704,7 | F12: 0 | G12: COINCIDE
C13: Macros (g) | D13: PRO 126 · GRA 90 · CHO 348 | E13: 126 / 90 / 348 | F13: 0 | G13: COINCIDE
C14: Cuadre | D14: 2706 − 2704,7 = +1,3 | E14: +1,3 | F14: 0 | G14: COINCIDE
A15: M2 | B15: Mujer 62 a · 68 kg · 160 cm · MLG medida 44 kg · HENRY · método POR ACTIVIDADES · ETA modo 1 · mantenimiento · proteína 20 % · grasa 30 % | C15: GEB (Henry ≥60) | D15: 10,1×68 + 569 = 1255,8 | E15: 1255,8 | F15: 0 | G15: COINCIDE
C16: TEE (METs) | D16: 40,6 × 68 × 1 = 2760,8 | E16: 2760,8 | F16: 0 | G16: COINCIDE
C17: PAL estimado | D17: 2760,8 / 1255,8 = 2,198439 | E17: 2,198439 | F17: 0 | G17: COINCIDE
C18: GAF | D18: 1255,8 × (2,198439 − 1) = 1505,0 | E18: 1505,0 | F18: 0 | G18: COINCIDE
C19: GET | D19: 1255,8 + 1505,0 + 0 = 2760,8 ( = TEE ) | E19: 2760,8 | F19: 0 | G19: COINCIDE
C20: Energía objetivo | D20: 2760,8 × 1,00 = 2760,8 | E20: 2760,8 | F20: 0 | G20: COINCIDE
C21: Macros (g) | D21: PRO 138 · GRA 92 · CHO 345 | E21: 138 / 92 / 345 | F21: 0 | G21: COINCIDE
C22: Cuadre | D22: 2760 − 2760,8 = −0,8 | E22: −0,8 | F22: 0 | G22: COINCIDE
A23: M3 | B23: Hombre 25 a · 92 kg · 182 cm · 22 % grasa · CUNNINGHAM 1991 · FA manual 1,60 · ETA modo 2 (10 %) · ajuste +10 % · proteína 2,0 g/kg · grasa 25 % | C23: MLG | D23: 92 × (1 − 0,22) = 71,76 | E23: 71,76 | F23: 0 | G23: COINCIDE
C24: GEB (Cunn. 1991) | D24: 370 + 21,6×71,76 = 1920,016 | E24: 1920,016 | F24: 0 | G24: COINCIDE
C25: GAF | D25: 1920,016 × 0,60 = 1152,0096 | E25: 1152,0096 | F25: 0 | G25: COINCIDE
C26: ETA (modo 2) | D26: (1920,016 + 1152,0096) × 0,10 = 307,2026 | E26: 307,2026 | F26: 0 | G26: COINCIDE
C27: GET | D27: 1920,016 + 1152,0096 + 307,2026 = 3379,2282 | E27: 3379,2282 | F27: 0 | G27: COINCIDE
C28: Energía objetivo | D28: 3379,2282 × 1,10 = 3717,151 | E28: 3717,151 | F28: 0 | G28: COINCIDE
C29: Macros (g) | D29: PRO 184 · GRA 103 · CHO 514 | E29: 184 / 103 / 514 | F29: 0 | G29: COINCIDE
C30: Cuadre | D30: 3719 − 3717,151 = +1,849 | E30: +1,849 | F30: 0 | G30: COINCIDE
C31: Cunningham 1980 (contraste) | D31: 500 + 22×71,76 = 2078,72 ← ECUACIÓN DISTINTA | E31: 2078,72 | F31: 0 | G31: COINCIDE
A32: Resultado: los tres recálculos coinciden con el libro hasta el último decimal. M2 verifica además la identidad GEB × PAL = TEE, que es la prueba algebraica de que no hay doble conteo.
A34: 2 · SEIS ESCENARIOS ADVERSARIALES EJECUTADOS SOBRE LA HOJA VIVA
A35: Nº | B35: Escenario | C35: Comportamiento esperado | D35: Comportamiento observado | E35: Errores de Excel | F35: Estado
A36: AD1 | B36: Cunningham 1991 SIN masa libre de grasa + método por actividades | C36: Ambos Cunningham → ND; sin GEB no se puede derivar el PAL → bloqueo con causa explícita | D36: Cunningham 1980 y 1991 → 'NO: falta la masa libre de grasa'; n baja de 7 a 5; validación: 'ERROR: el PAL por actividades exige 24 h registradas y un GEB calculable'; compuerta = NO | E36: 0 | F36: CORRECTO
A37: AD2 | B37: Peso 205 kg · estatura 138 cm · proteína 3,5 g/kg · grasa 2,5 g/kg · déficit 35 % | C37: NO debe bloquear (poco frecuente ≠ imposible), pero sí advertir; los carbohidratos por diferencia salen negativos | D37: Compuerta = SÍ; 4 advertencias de dato POCO FRECUENTE; carbohidratos → 'ERROR: la proteína y la grasa exceden la energía objetivo' | E37: 0 | F37: CORRECTO
A38: AD3 | B38: Edad 17 años (fuera del alcance adulto) | C38: Bloqueo total; las 7 ecuaciones deben devolver ND | D38: Compuerta = NO; las 7 ecuaciones → 'NO: edad fuera del alcance adulto'; n = 0; estadísticos = ND | E38: 0 | F38: CORRECTO
A39: AD4 | B39: ETA explícito al 30 % (máximo) aplicado SOBRE un PAL | C39: Debe calcular, pero advertir del doble conteo en CALCULOS y en RESULTADOS; sin división por cero | D39: GET = 4513,21; advertencia de doble conteo visible en ambas hojas; sin división por cero (el % de ETA está acotado por ETA_MAX = 30 %) | E39: 0 | F39: CORRECTO
A40: AD5 | B40: Registro de ACTIVIDADES con 0 horas (todas las filas vacías) | C40: FA no determinable → bloqueo con causa | D40: FA = 0 → dos validaciones distintas fallan ('factor fuera de límites' y 'el registro no suma 24 h'); compuerta = NO | E40: 0 | F40: CORRECTO
A41: AD6 | B41: Texto ('noventa') en el campo Peso | C41: Bloqueo; ninguna ecuación calculable; ningún error de Excel | D41: Validación: 'ERROR: no es numérico'; las 7 ecuaciones → 'NO: faltan sexo, edad o peso válidos'; compuerta = NO | E41: 0 | F41: CORRECTO
A42: Resultado: cero errores de Excel en los seis escenarios. La distinción entre DATO IMPOSIBLE (bloquea) y DATO POCO FRECUENTE (solo advierte) se comporta como está especificada.
A44: 3 · LISTA PRINCIPAL DE CAMBIOS (no exhaustiva: ver CHANGELOG para el registro completo)
A45: Versión | B45: Elemento | C45: Ubicación exacta | D45: Antes | E45: Después | F45: Impacto numérico
A46: 1.1 | B46: Coeficientes de Cunningham 1991 (reatribución) | C46: CONFIG!A87:H88 · CONFIG!B124 | D46: 'Katch–McArdle' (libro de texto), nivel C | E46: 'Cunningham (1991) · alias secundario: Katch–McArdle', nivel B | F46: Ninguno
A47: 1.1 | B47: Tabla canónica de Schofield | C47: CONFIG!A92:G97 (C9) | D47: 15,3/11,6/13,5 · 14,7/8,7/10,5 (tabla FAO redondeada en kcal) | E47: 15,057/11,472/11,711 · 14,818/8,126/9,082 (canónica desde MJ) | F47: SÍ · p. ej. H 40 a/90 kg: 1923 → 1905,58
A48: 1.1 | B48: Tabla FAO histórica (desconectada) | C48: CONFIG!A101:F106 (C9b) | D48: — | E48: Documentación; 0 referencias desde fórmulas | F48: Ninguno
A49: 1.1 | B49: Henry / Oxford 2005 (NUEVA) | C49: CONFIG!A110:G115 (C10) · ECUACIONES fila 13 | D49: No existía | E49: E7, kcal + MJ, bandas 18–30 / 30–60 / ≥60 | F49: SÍ · séptima ecuación; cambian promedio, mediana y rango
A50: 1.1 | B50: Cadena MET → TEE → PAL | C50: ACTIVIDADES!B21:B27 · CALCULOS!B13:B16 | D50: FA = Σ(MET×h)/24 (índice MET usado como PAL) | E50: TEE = Σ(MET×h)×Peso×1 kcal/kg/h ; PAL estimado = TEE/GEB | F50: SÍ · día de ejemplo: 1,669 → 1,853 (con GEB 1720)
A51: 1.1 | B51: MET de 'Dormir' | C51: CONFIG!C131 | D51: 0,95 | E51: 1,0 | F51: SÍ · Σ MET·h sube 0,4
A52: 1.1 | B52: Códigos MET como texto | C52: CONFIG!A131:A144 · ACTIVIDADES!C7:C18 | D52: 7030 (numérico) | E52: '07030' (texto) | F52: Ninguno
A53: 1.1 | B53: MET 17190 y 11210 | C53: CONFIG!D139:D140 | D53: Nivel A ('verificado') | E53: Nivel C (NO verificado) | F53: Ninguno
A54: 1.1.1 | B54: Formato regional del informe | C54: RESULTADOS!B8, B9, B11, B12 | D54: TEXT(x;"0.0") y TEXT(x;"0.000") | E54: ROUND(x;n) concatenado | F54: Ninguno en el cálculo. En Excel español, un FA de 1,55 se PRESENTABA como 0,002
A55: 1.1.1 | B55: Guarda de observaciones vacías | C55: RESULTADOS!B13 | D55: in_Obs (referencia directa: mostraba 0) | E55: IF(in_Obs="";"—";in_Obs) | F55: Ninguno
A56: 1.1.1 | B56: Guardas específicas por ecuación | C56: CONFIG!F120:F126 (columna nueva) · ECUACIONES!E7:E13 | D56: Todas las ecuaciones exigían estatura | E56: La estatura solo se exige a Mifflin y a Harris–Benedict revisada | F56: Solo en casos degradados: sin estatura, Owen/Cunningham/Schofield/Henry ahora devuelven GEB en vez de ND
... A67: 1.1.1 | B67: Nombres definidos | C67: Libro completo | D67: 82 nombres (v1.1) | E67: 82 nombres; ninguno eliminado ni roto. LISTA_ECU y las columnas de nivel se reapuntan por la nueva columna F de C11 | F67: Ninguno
A69: 4 · ANTES / DESPUÉS
A70: Indicador | B70: v1.0 | C70: v1.1 | D70: v1.1.1 | E70: v1.1.2
A71: Ecuaciones de GEB | B71: 6 | C71: 7 (+ Henry) | D71: 7 | E71: 7
A72: Casos de prueba | B72: 31 | C72: 54 | D72: 69 | E72: 81 (el RESUMEN lo calcula solo)
A73: Ecuaciones verificadas de extremo a extremo (bloque D) | B73: — | C73: 4 | D73: 7 | E73: 7
A74: Pruebas independientes del motor (sin leer sus salidas) | B74: — | C74: parcial | D74: parcial (D06/D07 no lo eran) | E74: SÍ
A75: Errores de Excel con estatura TEXTUAL | B75: n/d | C75: 0 | D75: 15 (error VALUE) | E75: 0
A76: Fuentes de nivel A / nivel B | B76: — | C76: 7 / 4 | D76: 7 / 4 | E76: 7 / 4
A77: Errores de Excel (caso normal) | B77: 0 | C77: 0 | D77: 0 | E77: 0
A78: Ocurrencias de IFERROR | B78: 0 | C78: 0 | D78: 0 | E78: 0
A79: ¿Validado clínicamente? | B79: NO | C79: NO | D79: NO | E79: NO
A81: EXACTITUD MATEMÁTICA Y BIBLIOGRÁFICA ≠ VALIDACIÓN CLÍNICA. Ni la v1.0, ni la v1.1, ni la v1.1.1 están validadas clínicamente. Requieren revisión por un nutricionista antes de cualquier uso asistencial.
A84: Recuento real de fórmulas del libro (contado por el generador): | E84: 742
A85: Recuento real de casos de prueba: lo calcula la propia hoja PRUEBAS (RESUMEN, fila 120). No se fija a mano para que no pueda desincronizarse.
A87: 5 · DICTAMEN FINAL · NMX-01 DEFINITIVO 2026
A88: Dimensión | B88: Resultado | C88: Estado | D88: Evidencia / criterio
A89: Separación MET / MET60+ / METWC | B89: 3 motores independientes | C89: CONFORME | D89: Adult 19–59 · Older ≥60 · Wheelchair
A90: Cambio 59→60 | B90: Revalidación dinámica | C90: CONFORME | D90: No reutiliza silenciosamente MET como MET60+
A91: Cambio de movilidad | B91: Revalidación dinámica | C91: CONFORME | D91: No convierte MET/MET60+ a METWC
A92: Registro 24 h | B92: Compuerta exacta | C92: CONFORME | D92: TEE/PAL bloqueado si registro ≠24 h
A93: PAL habitual vs PAL 24 h | B93: Separados | C93: CONFORME | D93: PAL derivado se etiqueta como estimado
A94: Wheelchair ≥60 | B94: TEE/PAL automático bloqueado | C94: CONFORME | D94: No se inventa METWC60+
A95: Validación clínica | B95: NO | C95: LIMITACIÓN DOCUMENTADA | D95: Herramienta académica
A96: Estado de cierre | B96: Auditoría post-export requerida | C96: CANDIDATO DEFINITIVO | D96: P0 debe quedar en 0

Sheet BASE_MET_ADULT_2024
A1: NUTRIMETRÍA · BASE_MET_ADULT_2024 · catálogo verificado | S1: LISTA_ACT_NONE
A2: Código | B2: Actividad_lista | C2: Categoría | D2: Actividad_original | E2: Actividad_ES | F2: Valor | G2: Unidad | H2: Población | I2: Edad_min | J2: Edad_max | K2: Estado_valor | L2: Fuente_corta | M2: Año | N2: DOI | O2: URL | P2: Nota_metodológica | Q2: Estado_verificación | S2: (no disponible para esta edad/condición)
A3: 07030 | B3: Dormir · [MET] | C3: Inactividad | D3: Sleeping | E3: Dormir | F3: 1 | G3: MET | H3: Adultos 19–59 años, no discapacitados y sin condiciones que alteren EE/metabolismo | I3: 19 | J3: 59 | K3: VERIFICADO EN TABLA OFICIAL 2024; estatus medido/estimado no transcrito por el extractor web | L3: Herrmann SD et al. 2024 Adult Compendium of Physical Activities | M3: 2024 | N3: 10.1016/j.jshs.2023.10.010 | O3: https://pacompendium.com/inactivity/ | P3: MET estándar: 1 MET = 1,000 kcal/kg/h = 3,5 mL O2/kg/min. Estimación poblacional; no es calorimetría individual. | Q3: A · FUENTE OFICIAL/PRIMARIA
A4: 07011 | B4: Acostado despierto, tranquilo · [MET] | C4: Inactividad | D4: Lying quietly, doing nothing, lying in bed awake, listening to music | E4: Acostado despierto, tranquilo | F4: 1 | G4: MET | H4: Adultos 19–59 años, no discapacitados y sin condiciones que alteren EE/metabolismo | I4: 19 | J4: 59 | K4: VERIFICADO EN TABLA OFICIAL 2024; estatus medido/estimado no transcrito por el extractor web | L4: Herrmann SD et al. 2024 Adult Compendium of Physical Activities | M4: 2024 | N4: 10.1016/j.jshs.2023.10.010 | O4: https://pacompendium.com/inactivity/ | P4: MET estándar: 1 MET = 1,000 kcal/kg/h = 3,5 mL O2/kg/min. Estimación poblacional; no es calorimetría individual. | Q4: A · FUENTE OFICIAL/PRIMARIA
A5: 07020 | B5: Ver televisión sentado · [MET] | C5: Inactividad | D5: Sit, watch television | E5: Ver televisión sentado | F5: 1 | G5: MET | H5: Adultos 19–59 años, no discapacitados y sin condiciones que alteren EE/metabolismo | I5: 19 | J5: 59 | K5: VERIFICADO EN TABLA OFICIAL 2024; estatus medido/estimado no transcrito por el extractor web | L5: Herrmann SD et al. 2024 Adult Compendium of Physical Activities | M5: 2024 | N5: 10.1016/j.jshs.2023.10.010 | O5: https://pacompendium.com/inactivity/ | P5: MET estándar: 1 MET = 1,000 kcal/kg/h = 3,5 mL O2/kg/min. Estimación poblacional; no es calorimetría individual. | Q5: A · FUENTE OFICIAL/PRIMARIA
A6: 07021 | B6: Sentado tranquilamente, general · [MET] | C6: Inactividad | D6: Sitting quietly, general | E6: Sentado tranquilamente, general | F6: 1 | G6: MET | H6: Adultos 19–59 años, no discapacitados y sin condiciones que alteren EE/metabolismo | I6: 19 | J6: 59 | K6: VERIFICADO EN TABLA OFICIAL 2024; estatus medido/estimado no transcrito por el extractor web | L6: Herrmann SD et al. 2024 Adult Compendium of Physical Activities | M6: 2024 | N6: 10.1016/j.jshs.2023.10.010 | O6: https://pacompendium.com/inactivity/ | P6: MET estándar: 1 MET = 1,000 kcal/kg/h = 3,5 mL O2/kg/min. Estimación poblacional; no es calorimetría individual. | Q6: A · FUENTE OFICIAL/PRIMARIA
A7: 07040 | B7: De pie quieto / esperando · [MET] | C7: Inactividad | D7: Standing quietly (standing in a line) | E7: De pie quieto / esperando | F7: 1.3 | G7: MET | H7: Adultos 19–59 años, no discapacitados y sin condiciones que alteren EE/metabolismo | I7: 19 | J7: 59 | K7: VERIFICADO EN TABLA OFICIAL 2024; estatus medido/estimado no transcrito por el extractor web | L7: Herrmann SD et al. 2024 Adult Compendium of Physical Activities | M7: 2024 | N7: 10.1016/j.jshs.2023.10.010 | O7: https://pacompendium.com/inactivity/ | P7: MET estándar: 1 MET = 1,000 kcal/kg/h = 3,5 mL O2/kg/min. Estimación poblacional; no es calorimetría individual. | Q7: A · FUENTE OFICIAL/PRIMARIA
A8: 09030 | B8: Leer sentado · [MET] | C8: Estudio / misceláneas | D8: Sitting: reading, book, newspaper, magazine | E8: Leer sentado | F8: 1 | G8: MET | H8: Adultos 19–59 años, no discapacitados y sin condiciones que alteren EE/metabolismo | I8: 19 | J8: 59 | K8: VERIFICADO EN TABLA OFICIAL 2024; estatus medido/estimado no transcrito por el extractor web | L8: Herrmann SD et al. 2024 Adult Compendium of Physical Activities | M8: 2024 | N8: 10.1016/j.jshs.2023.10.010 | O8: https://pacompendium.com/miscellaneous/ | P8: MET estándar: 1 MET = 1,000 kcal/kg/h = 3,5 mL O2/kg/min. Estimación poblacional; no es calorimetría individual. | Q8: A · FUENTE OFICIAL/PRIMARIA
A9: 09040 | B9: Escribir o trabajo de escritorio sentado · [MET] | C9: Estudio / misceláneas | D9: Sitting: writing, desk work, typing | E9: Escribir o trabajo de escritorio sentado | F9: 1.3 | G9: MET | H9: Adultos 19–59 años, no discapacitados y sin condiciones que alteren EE/metabolismo | I9: 19 | J9: 59 | K9: VERIFICADO EN TABLA OFICIAL 2024; estatus medido/estimado no transcrito por el extractor web | L9: Herrmann SD et al. 2024 Adult Compendium of Physical Activities | M9: 2024 | N9: 10.1016/j.jshs.2023.10.010 | O9: https://pacompendium.com/miscellaneous/ | P9: MET estándar: 1 MET = 1,000 kcal/kg/h = 3,5 mL O2/kg/min. Estimación poblacional; no es calorimetría individual. | Q9: A · FUENTE OFICIAL/PRIMARIA
A10: 09060 | B10: Estudiar sentado · lectura o escritura · esfuerzo ligero · [MET] | C10: Estudio / misceláneas | D10: Sitting – studying, general, including reading and/or writing, light effort | E10: Estudiar sentado · lectura o escritura · esfuerzo ligero | F10: 1.5 | G10: MET | H10: Adultos 19–59 años, no discapacitados y sin condiciones que alteren EE/metabolismo | I10: 19 | J10: 59 | K10: VERIFICADO EN TABLA OFICIAL 2024; estatus medido/estimado no transcrito por el extractor web | L10: Herrmann SD et al. 2024 Adult Compendium of Physical Activities | M10: 2024 | N10: 10.1016/j.jshs.2023.10.010 | O10: https://pacompendium.com/miscellaneous/ | P10: MET estándar: 1 MET = 1,000 kcal/kg/h = 3,5 mL O2/kg/min. Estimación poblacional; no es calorimetría individual. | Q10: A · FUENTE OFICIAL/PRIMARIA
A11: 09065 | B11: Estar en clases · tomar apuntes / discusión · [MET] | C11: Estudio / misceláneas | D11: Sitting – in class, general, including note-taking or class discussion | E11: Estar en clases · tomar apuntes / discusión | F11: 1.8 | G11: MET | H11: Adultos 19–59 años, no discapacitados y sin condiciones que alteren EE/metabolismo | I11: 19 | J11: 59 | K11: VERIFICADO EN TABLA OFICIAL 2024; estatus medido/estimado no transcrito por el extractor web | L11: Herrmann SD et al. 2024 Adult Compendium of Physical Activities | M11: 2024 | N11: 10.1016/j.jshs.2023.10.010 | O11: https://pacompendium.com/miscellaneous/ | P11: MET estándar: 1 MET = 1,000 kcal/kg/h = 3,5 mL O2/kg/min. Estimación poblacional; no es calorimetría individual. | Q11: A · FUENTE OFICIAL/PRIMARIA
A12: 09050 | B12: De pie · conversar / teléfono / computador / escribir · [MET] | C12: Estudio / misceláneas | D12: Standing: talking in person, on the phone, computer, text messaging, writing | E12: De pie · conversar / teléfono / computador / escribir | F12: 1.3 | G12: MET | H12: Adultos 19–59 años, no discapacitados y sin condiciones que alteren EE/metabolismo | I12: 19 | J12: 59 | K12: VERIFICADO EN TABLA OFICIAL 2024; estatus medido/estimado no transcrito por el extractor web | L12: Herrmann SD et al. 2024 Adult Compendium of Physical Activities | M12: 2024 | N12: 10.1016/j.jshs.2023.10.010 | O12: https://pacompendium.com/miscellaneous/ | P12: MET estándar: 1 MET = 1,000 kcal/kg/h = 3,5 mL O2/kg/min. Estimación poblacional; no es calorimetría individual. | Q12: A · FUENTE OFICIAL/PRIMARIA
A13: 09055 | B13: Sentado · conversar / teléfono / computador · ligero · [MET] | C13: Estudio / misceláneas | D13: Sitting: talking in person, on the phone, computer, or text messaging, light effort | E13: Sentado · conversar / teléfono / computador · ligero | F13: 1.3 | G13: MET | H13: Adultos 19–59 años, no discapacitados y sin condiciones que alteren EE/metabolismo | I13: 19 | J13: 59 | K13: VERIFICADO EN TABLA OFICIAL 2024; estatus medido/estimado no transcrito por el extractor web | L13: Herrmann SD et al. 2024 Adult Compendium of Physical Activities | M13: 2024 | N13: 10.1016/j.jshs.2023.10.010 | O13: https://pacompendium.com/miscellaneous/ | P13: MET estándar: 1 MET = 1,000 kcal/kg/h = 3,5 mL O2/kg/min. Estimación poblacional; no es calorimetría individual. | Q13: A · FUENTE OFICIAL/PRIMARIA
A14: 11580 | B14: Trabajo sentado ligero · oficina / laboratorio / escritorio · [MET] | C14: Trabajo | D14: Sitting tasks, light effort (e.g., office work, chemistry lab work, light assembly repair, watch repair, reading, desk work) | E14: Trabajo sentado ligero · oficina / laboratorio / escritorio | F14: 1.5 | G14: MET | H14: Adultos 19–59 años, no discapacitados y sin condiciones que alteren EE/metabolismo | I14: 19 | J14: 59 | K14: VERIFICADO EN TABLA OFICIAL 2024; estatus medido/estimado no transcrito por el extractor web | L14: Herrmann SD et al. 2024 Adult Compendium of Physical Activities | M14: 2024 | N14: 10.1016/j.jshs.2023.10.010 | O14: https://pacompendium.com/occupation/ | P14: MET estándar: 1 MET = 1,000 kcal/kg/h = 3,5 mL O2/kg/min. Estimación poblacional; no es calorimetría individual. | Q14: A · FUENTE OFICIAL/PRIMARIA
... A94: 00000 | B94: (sin actividad) · [MET] | C94: Sin actividad | D94: No activity selected | E94: (sin actividad) | F94: 0 | G94: MET | H94: Adultos 19–59 años, no discapacitados y sin condiciones que alteren EE/metabolismo | I94: 19 | J94: 59 | K94: VERIFICADO EN TABLA OFICIAL 2024; estatus medido/estimado no transcrito por el extractor web | L94: Herrmann SD et al. 2024 Adult Compendium of Physical Activities | M94: 2024 | N94: 10.1016/j.jshs.2023.10.010 | O94: https://pacompendium.com/adult-compendium/ | P94: MET estándar: 1 MET = 1,000 kcal/kg/h = 3,5 mL O2/kg/min. Estimación poblacional; no es calorimetría individual. | Q94: A · FUENTE OFICIAL/PRIMARIA

Sheet BASE_MET_OLDER_2024
A1: NUTRIMETRÍA · BASE_MET_OLDER_2024 · catálogo verificado | S1: LISTA_ACT_NONE
A2: Código | B2: Actividad_lista | C2: Categoría | D2: Actividad_original | E2: Actividad_ES | F2: Valor | G2: Unidad | H2: Población | I2: Edad_min | J2: Edad_max | K2: Estado_valor | L2: Fuente_corta | M2: Año | N2: DOI | O2: URL | P2: Nota_metodológica | Q2: Estado_verificación | S2: (no disponible para esta edad/condición)
A3: 0101060 | B3: Bicicleta estática · general · moderado · [MET60+] | C3: Bicicleta | D3: Bicycling, stationary, general, moderate effort | E3: Bicicleta estática · general · moderado | F3: 5.3 | G3: MET60+ | H3: Adultos ≥60 años | I3: 60 | K3: VERIFICADO EN TABLA OFICIAL 2024; estatus medido/estimado no transcrito por el extractor web | L3: Willis EA et al. Older Adult Compendium of Physical Activities (2024) | M3: 2024 | N3: 10.1016/j.jshs.2023.10.007 | O3: https://pacompendium.com/older-adult-compendium/ | P3: MET60+ usa una referencia de 2,7 mL O2/kg/min; conversión documentada: 0,810 kcal/kg/h. | Q3: A · FUENTE OFICIAL/PRIMARIA
A4: 0101160 | B4: Bicicleta estática 30–50 W · moderado · [MET60+] | C4: Bicicleta | D4: Bicycling, stationary, 30-50 watts, moderate effort | E4: Bicicleta estática 30–50 W · moderado | F4: 4.3 | G4: MET60+ | H4: Adultos ≥60 años | I4: 60 | K4: VERIFICADO EN TABLA OFICIAL 2024; estatus medido/estimado no transcrito por el extractor web | L4: Willis EA et al. Older Adult Compendium of Physical Activities (2024) | M4: 2024 | N4: 10.1016/j.jshs.2023.10.007 | O4: https://pacompendium.com/older-adult-compendium/ | P4: MET60+ usa una referencia de 2,7 mL O2/kg/min; conversión documentada: 0,810 kcal/kg/h. | Q4: A · FUENTE OFICIAL/PRIMARIA
A5: 0101760 | B5: Bicicleta estática 51–89 W · moderado-vigoroso · [MET60+] | C5: Bicicleta | D5: Bicycling, stationary, 51-89 watts, moderate-to-vigorous effort | E5: Bicicleta estática 51–89 W · moderado-vigoroso | F5: 4.5 | G5: MET60+ | H5: Adultos ≥60 años | I5: 60 | K5: VERIFICADO EN TABLA OFICIAL 2024; estatus medido/estimado no transcrito por el extractor web | L5: Willis EA et al. Older Adult Compendium of Physical Activities (2024) | M5: 2024 | N5: 10.1016/j.jshs.2023.10.007 | O5: https://pacompendium.com/older-adult-compendium/ | P5: MET60+ usa una referencia de 2,7 mL O2/kg/min; conversión documentada: 0,810 kcal/kg/h. | Q5: A · FUENTE OFICIAL/PRIMARIA
A6: 0202260 | B6: Calistenia · moderado · [MET60+] | C6: Ejercicio | D6: Calisthenics, moderate effort | E6: Calistenia · moderado | F6: 3.5 | G6: MET60+ | H6: Adultos ≥60 años | I6: 60 | K6: VERIFICADO EN TABLA OFICIAL 2024; estatus medido/estimado no transcrito por el extractor web | L6: Willis EA et al. Older Adult Compendium of Physical Activities (2024) | M6: 2024 | N6: 10.1016/j.jshs.2023.10.007 | O6: https://pacompendium.com/older-adult-compendium/ | P6: MET60+ usa una referencia de 2,7 mL O2/kg/min; conversión documentada: 0,810 kcal/kg/h. | Q6: A · FUENTE OFICIAL/PRIMARIA
A7: 0203560 | B7: Circuito · tipo Parcour · moderado · [MET60+] | C7: Ejercicio | D7: Circuit training, Parcour-type, moderate effort | E7: Circuito · tipo Parcour · moderado | F7: 4.5 | G7: MET60+ | H7: Adultos ≥60 años | I7: 60 | K7: VERIFICADO EN TABLA OFICIAL 2024; estatus medido/estimado no transcrito por el extractor web | L7: Willis EA et al. Older Adult Compendium of Physical Activities (2024) | M7: 2024 | N7: 10.1016/j.jshs.2023.10.007 | O7: https://pacompendium.com/older-adult-compendium/ | P7: MET60+ usa una referencia de 2,7 mL O2/kg/min; conversión documentada: 0,810 kcal/kg/h. | Q7: A · FUENTE OFICIAL/PRIMARIA
A8: 0204760 | B8: Elíptica · ligero · [MET60+] | C8: Ejercicio | D8: Elliptical trainer, light effort | E8: Elíptica · ligero | F8: 3 | G8: MET60+ | H8: Adultos ≥60 años | I8: 60 | K8: VERIFICADO EN TABLA OFICIAL 2024; estatus medido/estimado no transcrito por el extractor web | L8: Willis EA et al. Older Adult Compendium of Physical Activities (2024) | M8: 2024 | N8: 10.1016/j.jshs.2023.10.007 | O8: https://pacompendium.com/older-adult-compendium/ | P8: MET60+ usa una referencia de 2,7 mL O2/kg/min; conversión documentada: 0,810 kcal/kg/h. | Q8: A · FUENTE OFICIAL/PRIMARIA
A9: 0205160 | B9: Pesas · sentadillas · ligero · [MET60+] | C9: Ejercicio | D9: Resistance training, squats, light effort | E9: Pesas · sentadillas · ligero | F9: 3 | G9: MET60+ | H9: Adultos ≥60 años | I9: 60 | K9: VERIFICADO EN TABLA OFICIAL 2024; estatus medido/estimado no transcrito por el extractor web | L9: Willis EA et al. Older Adult Compendium of Physical Activities (2024) | M9: 2024 | N9: 10.1016/j.jshs.2023.10.007 | O9: https://pacompendium.com/older-adult-compendium/ | P9: MET60+ usa una referencia de 2,7 mL O2/kg/min; conversión documentada: 0,810 kcal/kg/h. | Q9: A · FUENTE OFICIAL/PRIMARIA
A10: 0205360 | B10: Entrenamiento de resistencia general · ligero · [MET60+] | C10: Ejercicio | D10: Resistance Training, general, light effort | E10: Entrenamiento de resistencia general · ligero | F10: 2.3 | G10: MET60+ | H10: Adultos ≥60 años | I10: 60 | K10: VERIFICADO EN TABLA OFICIAL 2024; estatus medido/estimado no transcrito por el extractor web | L10: Willis EA et al. Older Adult Compendium of Physical Activities (2024) | M10: 2024 | N10: 10.1016/j.jshs.2023.10.007 | O10: https://pacompendium.com/older-adult-compendium/ | P10: MET60+ usa una referencia de 2,7 mL O2/kg/min; conversión documentada: 0,810 kcal/kg/h. | Q10: A · FUENTE OFICIAL/PRIMARIA
A11: 0205460 | B11: Pesas · varios ejercicios · 8–15 repeticiones · [MET60+] | C11: Ejercicio | D11: Resistance training, multiple exercises, 8-15 repetitions at varied resistance | E11: Pesas · varios ejercicios · 8–15 repeticiones | F11: 4.3 | G11: MET60+ | H11: Adultos ≥60 años | I11: 60 | K11: VERIFICADO EN TABLA OFICIAL 2024; estatus medido/estimado no transcrito por el extractor web | L11: Willis EA et al. Older Adult Compendium of Physical Activities (2024) | M11: 2024 | N11: 10.1016/j.jshs.2023.10.007 | O11: https://pacompendium.com/older-adult-compendium/ | P11: MET60+ usa una referencia de 2,7 mL O2/kg/min; conversión documentada: 0,810 kcal/kg/h. | Q11: A · FUENTE OFICIAL/PRIMARIA
A12: 0206260 | B12: Clases de acondicionamiento / gimnasio · [MET60+] | C12: Ejercicio | D12: Health club exercise, conditioning classes | E12: Clases de acondicionamiento / gimnasio | F12: 5 | G12: MET60+ | H12: Adultos ≥60 años | I12: 60 | K12: VERIFICADO EN TABLA OFICIAL 2024; estatus medido/estimado no transcrito por el extractor web | L12: Willis EA et al. Older Adult Compendium of Physical Activities (2024) | M12: 2024 | N12: 10.1016/j.jshs.2023.10.007 | O12: https://pacompendium.com/older-adult-compendium/ | P12: MET60+ usa una referencia de 2,7 mL O2/kg/min; conversión documentada: 0,810 kcal/kg/h. | Q12: A · FUENTE OFICIAL/PRIMARIA
A13: 0206360 | B13: Clases de acondicionamiento en silla · [MET60+] | C13: Ejercicio | D13: Health club exercise, conditioning classes, chair-based | E13: Clases de acondicionamiento en silla | F13: 3.8 | G13: MET60+ | H13: Adultos ≥60 años | I13: 60 | K13: VERIFICADO EN TABLA OFICIAL 2024; estatus medido/estimado no transcrito por el extractor web | L13: Willis EA et al. Older Adult Compendium of Physical Activities (2024) | M13: 2024 | N13: 10.1016/j.jshs.2023.10.007 | O13: https://pacompendium.com/older-adult-compendium/ | P13: MET60+ usa una referencia de 2,7 mL O2/kg/min; conversión documentada: 0,810 kcal/kg/h. | Q13: A · FUENTE OFICIAL/PRIMARIA
A14: 0211360 | B14: Fitball / ejercicio terapéutico / silla · [MET60+] | C14: Ejercicio | D14: Therapeutic exercise ball, Fitball exercise, chair exercise | E14: Fitball / ejercicio terapéutico / silla | F14: 3.5 | G14: MET60+ | H14: Adultos ≥60 años | I14: 60 | K14: VERIFICADO EN TABLA OFICIAL 2024; estatus medido/estimado no transcrito por el extractor web | L14: Willis EA et al. Older Adult Compendium of Physical Activities (2024) | M14: 2024 | N14: 10.1016/j.jshs.2023.10.007 | O14: https://pacompendium.com/older-adult-compendium/ | P14: MET60+ usa una referencia de 2,7 mL O2/kg/min; conversión documentada: 0,810 kcal/kg/h. | Q14: A · FUENTE OFICIAL/PRIMARIA
... A87: 0000000 | B87: (sin actividad) · [MET60+] | C87: Sin actividad | D87: No activity selected | E87: (sin actividad) | F87: 0 | G87: MET60+ | H87: Adultos ≥60 años | I87: 60 | K87: VERIFICADO EN TABLA OFICIAL 2024; estatus medido/estimado no transcrito por el extractor web | L87: Willis EA et al. Older Adult Compendium of Physical Activities (2024) | M87: 2024 | N87: 10.1016/j.jshs.2023.10.007 | O87: https://pacompendium.com/older-adult-compendium/ | P87: MET60+ usa una referencia de 2,7 mL O2/kg/min; conversión documentada: 0,810 kcal/kg/h. | Q87: A · FUENTE OFICIAL/PRIMARIA

Sheet BASE_MET_WHEELCHAIR_2024
A1: NUTRIMETRÍA · BASE_MET_WHEELCHAIR_2024 · catálogo verificado | S1: LISTA_ACT_NONE
A2: Código | B2: Actividad_lista | C2: Categoría | D2: Actividad_original | E2: Actividad_ES | F2: Valor | G2: Unidad | H2: Población | I2: Edad_min | J2: Edad_max | K2: Estado_valor | L2: Fuente_corta | M2: Año | N2: DOI | O2: URL | P2: Nota_metodológica | Q2: Estado_verificación | S2: (no disponible para esta edad/condición)
A3: 90101 | B3: Aeróbicos · [METWC] | C3: Ejercicio | D3: Aerobics | E3: Aeróbicos | F3: 1.7 | G3: METWC | H3: Adultos usuarios de silla de ruedas; evidencia predominante en adultos jóvenes/mediana edad | I3: 19 | K3: VERIFICADO EN TABLA OFICIAL 2024; estatus medido/estimado no transcrito por el extractor web | L3: Conger SA et al. 2024 Wheelchair Compendium of Physical Activities | M3: 2024 | N3: 10.1016/j.jshs.2023.11.003 | O3: https://pacompendium.com/adult-wheelchair-users-compendium/ | P3: METWC usa una referencia de 0,992 kcal/kg/h. Para ≥60 años la evidencia etaria es limitada; NMX-01 no deriva PAL automáticamente. | Q3: A · FUENTE OFICIAL/PRIMARIA
A4: 90102 | B4: Ergometría de brazos 16 W · [METWC] | C4: Ejercicio | D4: Arm Ergometry 16W | E4: Ergometría de brazos 16 W | F4: 2.2 | G4: METWC | H4: Adultos usuarios de silla de ruedas; evidencia predominante en adultos jóvenes/mediana edad | I4: 19 | K4: VERIFICADO EN TABLA OFICIAL 2024; estatus medido/estimado no transcrito por el extractor web | L4: Conger SA et al. 2024 Wheelchair Compendium of Physical Activities | M4: 2024 | N4: 10.1016/j.jshs.2023.11.003 | O4: https://pacompendium.com/adult-wheelchair-users-compendium/ | P4: METWC usa una referencia de 0,992 kcal/kg/h. Para ≥60 años la evidencia etaria es limitada; NMX-01 no deriva PAL automáticamente. | Q4: A · FUENTE OFICIAL/PRIMARIA
A5: 90104 | B5: Ergometría de brazos 30–32 W · [METWC] | C5: Ejercicio | D5: Arm Ergometry 30-32W | E5: Ergometría de brazos 30–32 W | F5: 2.7 | G5: METWC | H5: Adultos usuarios de silla de ruedas; evidencia predominante en adultos jóvenes/mediana edad | I5: 19 | K5: VERIFICADO EN TABLA OFICIAL 2024; estatus medido/estimado no transcrito por el extractor web | L5: Conger SA et al. 2024 Wheelchair Compendium of Physical Activities | M5: 2024 | N5: 10.1016/j.jshs.2023.11.003 | O5: https://pacompendium.com/adult-wheelchair-users-compendium/ | P5: METWC usa una referencia de 0,992 kcal/kg/h. Para ≥60 años la evidencia etaria es limitada; NMX-01 no deriva PAL automáticamente. | Q5: A · FUENTE OFICIAL/PRIMARIA
A6: 90105 | B6: Ergometría de brazos 40–48 W · [METWC] | C6: Ejercicio | D6: Arm Ergometry 40-48W | E6: Ergometría de brazos 40–48 W | F6: 3.5 | G6: METWC | H6: Adultos usuarios de silla de ruedas; evidencia predominante en adultos jóvenes/mediana edad | I6: 19 | K6: VERIFICADO EN TABLA OFICIAL 2024; estatus medido/estimado no transcrito por el extractor web | L6: Conger SA et al. 2024 Wheelchair Compendium of Physical Activities | M6: 2024 | N6: 10.1016/j.jshs.2023.11.003 | O6: https://pacompendium.com/adult-wheelchair-users-compendium/ | P6: METWC usa una referencia de 0,992 kcal/kg/h. Para ≥60 años la evidencia etaria es limitada; NMX-01 no deriva PAL automáticamente. | Q6: A · FUENTE OFICIAL/PRIMARIA
A7: 90106 | B7: Ergometría de brazos 60–64 W · [METWC] | C7: Ejercicio | D7: Arm Ergometry 60-64W | E7: Ergometría de brazos 60–64 W | F7: 4.6 | G7: METWC | H7: Adultos usuarios de silla de ruedas; evidencia predominante en adultos jóvenes/mediana edad | I7: 19 | K7: VERIFICADO EN TABLA OFICIAL 2024; estatus medido/estimado no transcrito por el extractor web | L7: Conger SA et al. 2024 Wheelchair Compendium of Physical Activities | M7: 2024 | N7: 10.1016/j.jshs.2023.11.003 | O7: https://pacompendium.com/adult-wheelchair-users-compendium/ | P7: METWC usa una referencia de 0,992 kcal/kg/h. Para ≥60 años la evidencia etaria es limitada; NMX-01 no deriva PAL automáticamente. | Q7: A · FUENTE OFICIAL/PRIMARIA
A8: 90109 | B8: Ergometría de brazos · intensidad autoelegida moderada · [METWC] | C8: Ejercicio | D8: Arm Ergometry (self-selected intensity, moderate) | E8: Ergometría de brazos · intensidad autoelegida moderada | F8: 2.3 | G8: METWC | H8: Adultos usuarios de silla de ruedas; evidencia predominante en adultos jóvenes/mediana edad | I8: 19 | K8: VERIFICADO EN TABLA OFICIAL 2024; estatus medido/estimado no transcrito por el extractor web | L8: Conger SA et al. 2024 Wheelchair Compendium of Physical Activities | M8: 2024 | N8: 10.1016/j.jshs.2023.11.003 | O8: https://pacompendium.com/adult-wheelchair-users-compendium/ | P8: METWC usa una referencia de 0,992 kcal/kg/h. Para ≥60 años la evidencia etaria es limitada; NMX-01 no deriva PAL automáticamente. | Q8: A · FUENTE OFICIAL/PRIMARIA
A9: 90110 | B9: Ergometría de brazos · intensidad autoelegida vigorosa · [METWC] | C9: Ejercicio | D9: Arm Ergometry exercise (self-selected intensity, vigorous) | E9: Ergometría de brazos · intensidad autoelegida vigorosa | F9: 4.3 | G9: METWC | H9: Adultos usuarios de silla de ruedas; evidencia predominante en adultos jóvenes/mediana edad | I9: 19 | K9: VERIFICADO EN TABLA OFICIAL 2024; estatus medido/estimado no transcrito por el extractor web | L9: Conger SA et al. 2024 Wheelchair Compendium of Physical Activities | M9: 2024 | N9: 10.1016/j.jshs.2023.11.003 | O9: https://pacompendium.com/adult-wheelchair-users-compendium/ | P9: METWC usa una referencia de 0,992 kcal/kg/h. Para ≥60 años la evidencia etaria es limitada; NMX-01 no deriva PAL automáticamente. | Q9: A · FUENTE OFICIAL/PRIMARIA
A10: 90120 | B10: Handcycle · 8 km/h · [METWC] | C10: Ejercicio | D10: Handcycle – 8 km/h | E10: Handcycle · 8 km/h | F10: 3 | G10: METWC | H10: Adultos usuarios de silla de ruedas; evidencia predominante en adultos jóvenes/mediana edad | I10: 19 | K10: VERIFICADO EN TABLA OFICIAL 2024; estatus medido/estimado no transcrito por el extractor web | L10: Conger SA et al. 2024 Wheelchair Compendium of Physical Activities | M10: 2024 | N10: 10.1016/j.jshs.2023.11.003 | O10: https://pacompendium.com/adult-wheelchair-users-compendium/ | P10: METWC usa una referencia de 0,992 kcal/kg/h. Para ≥60 años la evidencia etaria es limitada; NMX-01 no deriva PAL automáticamente. | Q10: A · FUENTE OFICIAL/PRIMARIA
A11: 90121 | B11: Handcycle · 16 km/h · [METWC] | C11: Ejercicio | D11: Handcycle – 16 km/h | E11: Handcycle · 16 km/h | F11: 7.5 | G11: METWC | H11: Adultos usuarios de silla de ruedas; evidencia predominante en adultos jóvenes/mediana edad | I11: 19 | K11: VERIFICADO EN TABLA OFICIAL 2024; estatus medido/estimado no transcrito por el extractor web | L11: Conger SA et al. 2024 Wheelchair Compendium of Physical Activities | M11: 2024 | N11: 10.1016/j.jshs.2023.11.003 | O11: https://pacompendium.com/adult-wheelchair-users-compendium/ | P11: METWC usa una referencia de 0,992 kcal/kg/h. Para ≥60 años la evidencia etaria es limitada; NMX-01 no deriva PAL automáticamente. | Q11: A · FUENTE OFICIAL/PRIMARIA
A12: 90122 | B12: Ergómetro handcycle · general · [METWC] | C12: Ejercicio | D12: Handcycle ergometer (general) | E12: Ergómetro handcycle · general | F12: 3.6 | G12: METWC | H12: Adultos usuarios de silla de ruedas; evidencia predominante en adultos jóvenes/mediana edad | I12: 19 | K12: VERIFICADO EN TABLA OFICIAL 2024; estatus medido/estimado no transcrito por el extractor web | L12: Conger SA et al. 2024 Wheelchair Compendium of Physical Activities | M12: 2024 | N12: 10.1016/j.jshs.2023.11.003 | O12: https://pacompendium.com/adult-wheelchair-users-compendium/ | P12: METWC usa una referencia de 0,992 kcal/kg/h. Para ≥60 años la evidencia etaria es limitada; NMX-01 no deriva PAL automáticamente. | Q12: A · FUENTE OFICIAL/PRIMARIA
A13: 90125 | B13: Entrenamiento de resistencia / pesas · [METWC] | C13: Ejercicio | D13: Resistance (weight) Training | E13: Entrenamiento de resistencia / pesas | F13: 2.1 | G13: METWC | H13: Adultos usuarios de silla de ruedas; evidencia predominante en adultos jóvenes/mediana edad | I13: 19 | K13: VERIFICADO EN TABLA OFICIAL 2024; estatus medido/estimado no transcrito por el extractor web | L13: Conger SA et al. 2024 Wheelchair Compendium of Physical Activities | M13: 2024 | N13: 10.1016/j.jshs.2023.11.003 | O13: https://pacompendium.com/adult-wheelchair-users-compendium/ | P13: METWC usa una referencia de 0,992 kcal/kg/h. Para ≥60 años la evidencia etaria es limitada; NMX-01 no deriva PAL automáticamente. | Q13: A · FUENTE OFICIAL/PRIMARIA
A14: 90126 | B14: Entrenamiento en circuito · [METWC] | C14: Ejercicio | D14: Circuit Training | E14: Entrenamiento en circuito | F14: 2.3 | G14: METWC | H14: Adultos usuarios de silla de ruedas; evidencia predominante en adultos jóvenes/mediana edad | I14: 19 | K14: VERIFICADO EN TABLA OFICIAL 2024; estatus medido/estimado no transcrito por el extractor web | L14: Conger SA et al. 2024 Wheelchair Compendium of Physical Activities | M14: 2024 | N14: 10.1016/j.jshs.2023.11.003 | O14: https://pacompendium.com/adult-wheelchair-users-compendium/ | P14: METWC usa una referencia de 0,992 kcal/kg/h. Para ≥60 años la evidencia etaria es limitada; NMX-01 no deriva PAL automáticamente. | Q14: A · FUENTE OFICIAL/PRIMARIA
... A84: 00000 | B84: (sin actividad) · [METWC] | C84: Sin actividad | D84: No activity selected | E84: (sin actividad) | F84: 0 | G84: METWC | H84: Adultos usuarios de silla de ruedas; evidencia predominante en adultos jóvenes/mediana edad | I84: 19 | K84: VERIFICADO EN TABLA OFICIAL 2024; estatus medido/estimado no transcrito por el extractor web | L84: Conger SA et al. 2024 Wheelchair Compendium of Physical Activities | M84: 2024 | N84: 10.1016/j.jshs.2023.11.003 | O84: https://pacompendium.com/adult-wheelchair-users-compendium/ | P84: METWC usa una referencia de 0,992 kcal/kg/h. Para ≥60 años la evidencia etaria es limitada; NMX-01 no deriva PAL automáticamente. | Q84: A · FUENTE OFICIAL/PRIMARIA
