Workbook
Name CFG_ActivarActividad: CONFIG!$B$25
Name CFG_ActivarBioquimica: CONFIG!$B$23
Name CFG_ActivarComposicion: CONFIG!$B$28
Name CFG_ActivarFarmacos: CONFIG!$B$26
Name CFG_ActivarGraficos: CONFIG!$B$29
Name CFG_ActivarIdentificacionDirecta: CONFIG!$B$30
Name CFG_ActivarR24H: CONFIG!$B$24
Name CFG_ActivarSuplementos: CONFIG!$B$27
Name CFG_CaderaMax: CONFIG!$B$45
Name CFG_CaderaMin: CONFIG!$B$44
Name CFG_CinturaMax: CONFIG!$B$43
Name CFG_CinturaMin: CONFIG!$B$42
Name CFG_EdadMax: CONFIG!$B$37
Name CFG_EdadMin: CONFIG!$B$36
Name CFG_EstaturaMax: CONFIG!$B$41
Name CFG_EstaturaMin: CONFIG!$B$40
Name CFG_GrasaMax: CONFIG!$B$47
Name CFG_GrasaMin: CONFIG!$B$46
Name CFG_MaxGrafico: CONFIG!$B$49
Name CFG_PermitirFechasFuturas: CONFIG!$B$31
Name CFG_PesoMax: CONFIG!$B$39
Name CFG_PesoMin: CONFIG!$B$38
Name CFG_Tolerancia: CONFIG!$B$48
Name Lista_CategoriaAntecedente: CATALOGOS!$D$7:$D$27
Name Lista_CategoriaIntervencion: CATALOGOS!$K$7:$K$16
Name Lista_Confiabilidad: CATALOGOS!$P$7:$P$10
Name Lista_Consentimiento: CATALOGOS!$N$7:$N$10
Name Lista_EstadoBio: CATALOGOS!$T$7:$T$10
Name Lista_EstadoDiagnostico: CATALOGOS!$H$7:$H$11
Name Lista_EstadoObjetivo: CATALOGOS!$J$7:$J$11
Name Lista_EstadoPaciente: CATALOGOS!$A$7:$A$11
Name Lista_EstadoRegistro: CATALOGOS!$O$7:$O$12
Name Lista_EvaluationID: EVALUACION!$A$7:$A$36
Name Lista_FuenteDato: CATALOGOS!$M$7:$M$12
Name Lista_Intensidad: CATALOGOS!$Q$7:$Q$10
Name Lista_Modalidad: CATALOGOS!$C$7:$C$9
Name Lista_PatientID: PACIENTES!$A$7:$A$26
Name Lista_Presencia: CATALOGOS!$R$7:$R$10
Name Lista_Prioridad: CATALOGOS!$I$7:$I$10
Name Lista_SiNoNA: CATALOGOS!$U$7:$U$9
Name Lista_SistemaClinico: CATALOGOS!$E$7:$E$26
Name Lista_TiempoComida: CATALOGOS!$F$7:$F$14
Name Lista_TipoActividad: CATALOGOS!$G$7:$G$12
Name Lista_TipoDia: CATALOGOS!$S$7:$S$12
Name Lista_TipoEvaluacion: CATALOGOS!$B$7:$B$10
Name Lista_Unidad: CATALOGOS!$L$7:$L$24

Sheet INICIO
A1: Nutrimetría Excel Lab — NMX-03 · Historia Clínica Nutricional Completa
A2: ◀ INICIO | B2: RESUMEN | C2: CONFIG | D2: PRUEBAS
A3: PACIENTE FICTICIO PARA PRUEBA — NO UTILIZAR COMO REFERENCIA CLÍNICA · Elimine o reemplace todos los casos antes de uso real.
A5: Estado e inventario
A6: Código | B6: NMX-03 | F6: Información técnica y trazable.
A7: Versión | B7: 1.0.1-RC | F7: Información técnica y trazable.
A8: Estado | B8: CANDIDATO A PUBLICACIÓN — revisión clínica profesional declarada; requiere protocolo final en Excel 2021 y Microsoft 365 | F8: Información técnica y trazable.
A9: Pacientes | B9: =CALCULOS!B10 -> 5 | F9: Información técnica y trazable.
A10: Evaluaciones | B10: =CALCULOS!B11 -> 6 | F10: Información técnica y trazable.
A11: Última fecha | B11: =CALCULOS!B12 -> 46208 | F11: Información técnica y trazable.
A12: Pruebas | B12: =PRUEBAS!B99&" totales · "&PRUEBAS!B100&" aprobadas · "&PRUEBAS!B102&" pendientes" -> 90 totales · 88 aprobadas · 2 pendientes | F12: Información técnica y trazable.
A13: Compatibilidad | B13: Objetivo Excel 365 / Excel 2021 para Windows | F13: Información técnica y trazable.
A15: Objetivo, alcance y privacidad
A16: Registrar múltiples pacientes y evaluaciones longitudinales mediante PatientID y EvaluationID.
A17: Orientado a adultos en consulta nutricional ambulatoria; no pediatría, embarazo, UCI, nutrición enteral/parenteral, enfermedad renal avanzada, TCA ni deporte especializado.
A18: ▲ No emite diagnósticos médicos, no prescribe medicamentos ni decide tratamientos automáticamente.
A19: ▲ Use minimización de datos, identificadores internos, equipo protegido, copias de seguridad y medios de transferencia seguros.
A20: ▲ La protección de hojas evita cambios accidentales; no cifra datos ni impide accesos no autorizados.
A21: ▲ No use almacenamiento público ni envíe el archivo sin medidas de seguridad y autorización aplicables.
A23: Flujo de trabajo
A24: 1 · Registrar paciente en PACIENTES.
A25: 2 · Crear evaluación en EVALUACION.
A26: 3 · Completar ANTECEDENTES, ANTROPOMETRIA, BIOQUIMICA y CLINICA.
A27: 4 · Completar ALIMENTACION y ACTIVIDAD.
... A35: Navegación interna
A36: PACIENTES | D36: EVALUACION | G36: ANTECEDENTES | J36: ANTROPOMETRIA
A37: BIOQUIMICA | D37: CLINICA | G37: ALIMENTACION | J37: ACTIVIDAD
A38: FARMACOS | D38: DIAGNOSTICO | G38: OBJETIVOS | J38: INTERVENCION
A39: SEGUIMIENTO | D39: RESUMEN | G39: CALCULOS | J39: CATALOGOS
A40: PRUEBAS | D40: CONFIG | G40: FUENTES | J40: CHANGELOG
A41: AUDITORIA_COMERCIAL | D41: COMPATIBILIDAD
A42: Leyenda, respaldo y accesibilidad
A43: Tipo | B43: Muestra | C43: Significado
A44: Entrada editable | C44: Fondo ámbar
A45: Cálculo | C45: Fondo gris
A46: Dato ficticio | C46: Fondo lavanda
A47: Advertencia | C47: Texto ▲ + fondo amarillo
A48: Error | C48: Texto ✖ + fondo rojo
A50: Estado v1.0.1-RC: fórmulas ampliadas, navegación compatible, fechas y gráficos corregidos, validaciones reforzadas y barreras antiedición aplicadas. La protección nativa y la prueba física de Excel deben cerrarse antes de etiquetar la versión como definitiva.

Sheet PACIENTES
A1: PACIENTES · Maestro de identificación mínima y consentimiento
A2: ◀ INICIO | B2: RESUMEN | C2: CONFIG | D2: PRUEBAS
A3: PACIENTE FICTICIO PARA PRUEBA — NO UTILIZAR COMO REFERENCIA CLÍNICA · Todos los datos son sintéticos.
A5: T_PACIENTES
A6: PatientID | B6: Estado | C6: FechaRegistro | D6: Iniciales | E6: Nombre opcional | F6: Apellido opcional | G6: FechaNacimiento opcional | H6: Edad calculada | I6: Sexo registrado al nacer | J6: Género opcional | K6: Pronombres opcionales | L6: Teléfono opcional | M6: Correo opcional | N6: Ciudad o región opcional | O6: Ocupación | P6: Sistema previsión opcional | Q6: Contacto emergencia opcional | R6: Consentimiento datos | S6: Fecha consentimiento | T6: Versión consentimiento | U6: Profesional responsable | V6: FechaModificacion | W6: FuenteDato | X6: Observaciones | Y6: Control
A7: P-FICT-A | B7: Activo | C7: 46174 | D7: AFA | G7: 32975 | H7: =IF(ISNUMBER(G7),YEAR(TODAY())-YEAR(G7)-IF(DATE(YEAR(TODAY()),MONTH(G7),DAY(G7))>TODAY(),1,0),"") -> 36 | I7: Femenino | N7: Región ficticia | O7: Ocupación ficticia | R7: Sí | S7: 46174 | T7: CONS-1 | U7: PROF-DEMO | V7: 46216 | W7: Documentado | X7: PACIENTE FICTICIO PARA PRUEBA — NO UTILIZAR COMO REFERENCIA CLÍNICA | Y7: =IF(A7="","",IF(COUNTIF($A$7:$A$1006,A7)>1,"✖ PatientID duplicado",IF(AND(ISNUMBER(G7),G7>TODAY()),"✖ Fecha nacimiento futura",IF(AND(M7<>"",COUNTIF(M7,"?*@?*.?*")=0),"▲ Correo básico inválido",IF(COUNTIF(CATALOGOS!$A$7:$A$11,B7)=0,"✖ Estado no permitido",IF(AND(R7="Sí",NOT(ISNUMBER(S7))),"✖ Consentimiento Sí sin fecha",IF(AND(ISNUMBER(H7),OR(H7<CONFIG!$B$36,H7>CONFIG!$B$37)),"▲ Fuera de alcance adulto","✔ Correcto"))))))) -> ✔ Correcto
A8: P-FICT-B | B8: Activo | C8: 46143 | D8: BFB | G8: 31310 | H8: =IF(ISNUMBER(G8),YEAR(TODAY())-YEAR(G8)-IF(DATE(YEAR(TODAY()),MONTH(G8),DAY(G8))>TODAY(),1,0),"") -> 40 | I8: Masculino | N8: Región ficticia | O8: Ocupación ficticia | R8: Sí | S8: 46143 | T8: CONS-1 | U8: PROF-DEMO | V8: 46216 | W8: Documentado | X8: PACIENTE FICTICIO PARA PRUEBA — NO UTILIZAR COMO REFERENCIA CLÍNICA | Y8: =IF(A8="","",IF(COUNTIF($A$7:$A$1006,A8)>1,"✖ PatientID duplicado",IF(AND(ISNUMBER(G8),G8>TODAY()),"✖ Fecha nacimiento futura",IF(AND(M8<>"",COUNTIF(M8,"?*@?*.?*")=0),"▲ Correo básico inválido",IF(COUNTIF(CATALOGOS!$A$7:$A$11,B8)=0,"✖ Estado no permitido",IF(AND(R8="Sí",NOT(ISNUMBER(S8))),"✖ Consentimiento Sí sin fecha",IF(AND(ISNUMBER(H8),OR(H8<CONFIG!$B$36,H8>CONFIG!$B$37)),"▲ Fuera de alcance adulto","✔ Correcto"))))))) -> ✔ Correcto
A9: P-FICT-C | B9: Activo | C9: 46204 | D9: CFC | G9: 36535 | H9: =IF(ISNUMBER(G9),YEAR(TODAY())-YEAR(G9)-IF(DATE(YEAR(TODAY()),MONTH(G9),DAY(G9))>TODAY(),1,0),"") -> 26 | I9: No informado | N9: Región ficticia | O9: Ocupación ficticia | R9: Pendiente | T9: CONS-1 | U9: PROF-DEMO | V9: 46216 | W9: Informado por paciente | X9: PACIENTE FICTICIO PARA PRUEBA — NO UTILIZAR COMO REFERENCIA CLÍNICA | Y9: =IF(A9="","",IF(COUNTIF($A$7:$A$1006,A9)>1,"✖ PatientID duplicado",IF(AND(ISNUMBER(G9),G9>TODAY()),"✖ Fecha nacimiento futura",IF(AND(M9<>"",COUNTIF(M9,"?*@?*.?*")=0),"▲ Correo básico inválido",IF(COUNTIF(CATALOGOS!$A$7:$A$11,B9)=0,"✖ Estado no permitido",IF(AND(R9="Sí",NOT(ISNUMBER(S9))),"✖ Consentimiento Sí sin fecha",IF(AND(ISNUMBER(H9),OR(H9<CONFIG!$B$36,H9>CONFIG!$B$37)),"▲ Fuera de alcance adulto","✔ Correcto"))))))) -> ✔ Correcto
A10: P-FICT-D | B10: Activo | C10: 46183 | D10: DFD | G10: 28829 | H10: =IF(ISNUMBER(G10),YEAR(TODAY())-YEAR(G10)-IF(DATE(YEAR(TODAY()),MONTH(G10),DAY(G10))>TODAY(),1,0),"") -> 47 | I10: Femenino | N10: Región ficticia | O10: Ocupación ficticia | R10: Sí | S10: 46183 | T10: CONS-1 | U10: PROF-DEMO | V10: 46216 | W10: Documentado | X10: PACIENTE FICTICIO PARA PRUEBA — NO UTILIZAR COMO REFERENCIA CLÍNICA | Y10: =IF(A10="","",IF(COUNTIF($A$7:$A$1006,A10)>1,"✖ PatientID duplicado",IF(AND(ISNUMBER(G10),G10>TODAY()),"✖ Fecha nacimiento futura",IF(AND(M10<>"",COUNTIF(M10,"?*@?*.?*")=0),"▲ Correo básico inválido",IF(COUNTIF(CATALOGOS!$A$7:$A$11,B10)=0,"✖ Estado no permitido",IF(AND(R10="Sí",NOT(ISNUMBER(S10))),"✖ Consentimiento Sí sin fecha",IF(AND(ISNUMBER(H10),OR(H10<CONFIG!$B$36,H10>CONFIG!$B$37)),"▲ Fuera de alcance adulto","✔ Correcto"))))))) -> ✔ Correcto
A11: P-FICT-E | B11: Activo | C11: 46208 | D11: EFE | G11: 34887 | H11: =IF(ISNUMBER(G11),YEAR(TODAY())-YEAR(G11)-IF(DATE(YEAR(TODAY()),MONTH(G11),DAY(G11))>TODAY(),1,0),"") -> 31 | I11: Masculino | N11: Región ficticia | O11: Ocupación ficticia | R11: Revocado | S11: 46215 | T11: CONS-1 | U11: PROF-DEMO | V11: 46216 | W11: Documentado | X11: PACIENTE FICTICIO PARA PRUEBA — NO UTILIZAR COMO REFERENCIA CLÍNICA · Escenarios inválidos solo en PRUEBAS. | Y11: =IF(A11="","",IF(COUNTIF($A$7:$A$1006,A11)>1,"✖ PatientID duplicado",IF(AND(ISNUMBER(G11),G11>TODAY()),"✖ Fecha nacimiento futura",IF(AND(M11<>"",COUNTIF(M11,"?*@?*.?*")=0),"▲ Correo básico inválido",IF(COUNTIF(CATALOGOS!$A$7:$A$11,B11)=0,"✖ Estado no permitido",IF(AND(R11="Sí",NOT(ISNUMBER(S11))),"✖ Consentimiento Sí sin fecha",IF(AND(ISNUMBER(H11),OR(H11<CONFIG!$B$36,H11>CONFIG!$B$37)),"▲ Fuera de alcance adulto","✔ Correcto"))))))) -> ✔ Correcto
H12: =IF(ISNUMBER(G12),YEAR(TODAY())-YEAR(G12)-IF(DATE(YEAR(TODAY()),MONTH(G12),DAY(G12))>TODAY(),1,0),"") | Y12: =IF(A12="","",IF(COUNTIF($A$7:$A$26,A12)>1,"✖ PatientID duplicado",IF(AND(ISNUMBER(G12),G12>TODAY()),"✖ Fecha nacimiento futura",IF(AND(M12<>"",COUNTIF(M12,"?*@?*.?*")=0),"▲ Correo básico inválido",IF(COUNTIF(CATALOGOS!$A$7:$A$11,B12)=0,"✖ Estado no permitido",IF(AND(R12="Sí",NOT(ISNUMBER(S12))),"✖ Consentimiento Sí sin fecha",IF(AND(ISNUMBER(H12),OR(H12<CONFIG!$B$36,H12>CONFIG!$B$37)),"▲ Fuera de alcance adulto","✔ Correcto")))))))
H13: =IF(ISNUMBER(G13),YEAR(TODAY())-YEAR(G13)-IF(DATE(YEAR(TODAY()),MONTH(G13),DAY(G13))>TODAY(),1,0),"") | Y13: =IF(A13="","",IF(COUNTIF($A$7:$A$26,A13)>1,"✖ PatientID duplicado",IF(AND(ISNUMBER(G13),G13>TODAY()),"✖ Fecha nacimiento futura",IF(AND(M13<>"",COUNTIF(M13,"?*@?*.?*")=0),"▲ Correo básico inválido",IF(COUNTIF(CATALOGOS!$A$7:$A$11,B13)=0,"✖ Estado no permitido",IF(AND(R13="Sí",NOT(ISNUMBER(S13))),"✖ Consentimiento Sí sin fecha",IF(AND(ISNUMBER(H13),OR(H13<CONFIG!$B$36,H13>CONFIG!$B$37)),"▲ Fuera de alcance adulto","✔ Correcto")))))))
H14: =IF(ISNUMBER(G14),YEAR(TODAY())-YEAR(G14)-IF(DATE(YEAR(TODAY()),MONTH(G14),DAY(G14))>TODAY(),1,0),"") | Y14: =IF(A14="","",IF(COUNTIF($A$7:$A$26,A14)>1,"✖ PatientID duplicado",IF(AND(ISNUMBER(G14),G14>TODAY()),"✖ Fecha nacimiento futura",IF(AND(M14<>"",COUNTIF(M14,"?*@?*.?*")=0),"▲ Correo básico inválido",IF(COUNTIF(CATALOGOS!$A$7:$A$11,B14)=0,"✖ Estado no permitido",IF(AND(R14="Sí",NOT(ISNUMBER(S14))),"✖ Consentimiento Sí sin fecha",IF(AND(ISNUMBER(H14),OR(H14<CONFIG!$B$36,H14>CONFIG!$B$37)),"▲ Fuera de alcance adulto","✔ Correcto")))))))
H15: =IF(ISNUMBER(G15),YEAR(TODAY())-YEAR(G15)-IF(DATE(YEAR(TODAY()),MONTH(G15),DAY(G15))>TODAY(),1,0),"") | Y15: =IF(A15="","",IF(COUNTIF($A$7:$A$26,A15)>1,"✖ PatientID duplicado",IF(AND(ISNUMBER(G15),G15>TODAY()),"✖ Fecha nacimiento futura",IF(AND(M15<>"",COUNTIF(M15,"?*@?*.?*")=0),"▲ Correo básico inválido",IF(COUNTIF(CATALOGOS!$A$7:$A$11,B15)=0,"✖ Estado no permitido",IF(AND(R15="Sí",NOT(ISNUMBER(S15))),"✖ Consentimiento Sí sin fecha",IF(AND(ISNUMBER(H15),OR(H15<CONFIG!$B$36,H15>CONFIG!$B$37)),"▲ Fuera de alcance adulto","✔ Correcto")))))))
H16: =IF(ISNUMBER(G16),YEAR(TODAY())-YEAR(G16)-IF(DATE(YEAR(TODAY()),MONTH(G16),DAY(G16))>TODAY(),1,0),"") | Y16: =IF(A16="","",IF(COUNTIF($A$7:$A$26,A16)>1,"✖ PatientID duplicado",IF(AND(ISNUMBER(G16),G16>TODAY()),"✖ Fecha nacimiento futura",IF(AND(M16<>"",COUNTIF(M16,"?*@?*.?*")=0),"▲ Correo básico inválido",IF(COUNTIF(CATALOGOS!$A$7:$A$11,B16)=0,"✖ Estado no permitido",IF(AND(R16="Sí",NOT(ISNUMBER(S16))),"✖ Consentimiento Sí sin fecha",IF(AND(ISNUMBER(H16),OR(H16<CONFIG!$B$36,H16>CONFIG!$B$37)),"▲ Fuera de alcance adulto","✔ Correcto")))))))
H17: =IF(ISNUMBER(G17),YEAR(TODAY())-YEAR(G17)-IF(DATE(YEAR(TODAY()),MONTH(G17),DAY(G17))>TODAY(),1,0),"") | Y17: =IF(A17="","",IF(COUNTIF($A$7:$A$26,A17)>1,"✖ PatientID duplicado",IF(AND(ISNUMBER(G17),G17>TODAY()),"✖ Fecha nacimiento futura",IF(AND(M17<>"",COUNTIF(M17,"?*@?*.?*")=0),"▲ Correo básico inválido",IF(COUNTIF(CATALOGOS!$A$7:$A$11,B17)=0,"✖ Estado no permitido",IF(AND(R17="Sí",NOT(ISNUMBER(S17))),"✖ Consentimiento Sí sin fecha",IF(AND(ISNUMBER(H17),OR(H17<CONFIG!$B$36,H17>CONFIG!$B$37)),"▲ Fuera de alcance adulto","✔ Correcto")))))))
H18: =IF(ISNUMBER(G18),YEAR(TODAY())-YEAR(G18)-IF(DATE(YEAR(TODAY()),MONTH(G18),DAY(G18))>TODAY(),1,0),"") | Y18: =IF(A18="","",IF(COUNTIF($A$7:$A$26,A18)>1,"✖ PatientID duplicado",IF(AND(ISNUMBER(G18),G18>TODAY()),"✖ Fecha nacimiento futura",IF(AND(M18<>"",COUNTIF(M18,"?*@?*.?*")=0),"▲ Correo básico inválido",IF(COUNTIF(CATALOGOS!$A$7:$A$11,B18)=0,"✖ Estado no permitido",IF(AND(R18="Sí",NOT(ISNUMBER(S18))),"✖ Consentimiento Sí sin fecha",IF(AND(ISNUMBER(H18),OR(H18<CONFIG!$B$36,H18>CONFIG!$B$37)),"▲ Fuera de alcance adulto","✔ Correcto")))))))
H19: =IF(ISNUMBER(G19),YEAR(TODAY())-YEAR(G19)-IF(DATE(YEAR(TODAY()),MONTH(G19),DAY(G19))>TODAY(),1,0),"") | Y19: =IF(A19="","",IF(COUNTIF($A$7:$A$26,A19)>1,"✖ PatientID duplicado",IF(AND(ISNUMBER(G19),G19>TODAY()),"✖ Fecha nacimiento futura",IF(AND(M19<>"",COUNTIF(M19,"?*@?*.?*")=0),"▲ Correo básico inválido",IF(COUNTIF(CATALOGOS!$A$7:$A$11,B19)=0,"✖ Estado no permitido",IF(AND(R19="Sí",NOT(ISNUMBER(S19))),"✖ Consentimiento Sí sin fecha",IF(AND(ISNUMBER(H19),OR(H19<CONFIG!$B$36,H19>CONFIG!$B$37)),"▲ Fuera de alcance adulto","✔ Correcto")))))))
H20: =IF(ISNUMBER(G20),YEAR(TODAY())-YEAR(G20)-IF(DATE(YEAR(TODAY()),MONTH(G20),DAY(G20))>TODAY(),1,0),"") | Y20: =IF(A20="","",IF(COUNTIF($A$7:$A$26,A20)>1,"✖ PatientID duplicado",IF(AND(ISNUMBER(G20),G20>TODAY()),"✖ Fecha nacimiento futura",IF(AND(M20<>"",COUNTIF(M20,"?*@?*.?*")=0),"▲ Correo básico inválido",IF(COUNTIF(CATALOGOS!$A$7:$A$11,B20)=0,"✖ Estado no permitido",IF(AND(R20="Sí",NOT(ISNUMBER(S20))),"✖ Consentimiento Sí sin fecha",IF(AND(ISNUMBER(H20),OR(H20<CONFIG!$B$36,H20>CONFIG!$B$37)),"▲ Fuera de alcance adulto","✔ Correcto")))))))
H21: =IF(ISNUMBER(G21),YEAR(TODAY())-YEAR(G21)-IF(DATE(YEAR(TODAY()),MONTH(G21),DAY(G21))>TODAY(),1,0),"") | Y21: =IF(A21="","",IF(COUNTIF($A$7:$A$26,A21)>1,"✖ PatientID duplicado",IF(AND(ISNUMBER(G21),G21>TODAY()),"✖ Fecha nacimiento futura",IF(AND(M21<>"",COUNTIF(M21,"?*@?*.?*")=0),"▲ Correo básico inválido",IF(COUNTIF(CATALOGOS!$A$7:$A$11,B21)=0,"✖ Estado no permitido",IF(AND(R21="Sí",NOT(ISNUMBER(S21))),"✖ Consentimiento Sí sin fecha",IF(AND(ISNUMBER(H21),OR(H21<CONFIG!$B$36,H21>CONFIG!$B$37)),"▲ Fuera de alcance adulto","✔ Correcto")))))))
H22: =IF(ISNUMBER(G22),YEAR(TODAY())-YEAR(G22)-IF(DATE(YEAR(TODAY()),MONTH(G22),DAY(G22))>TODAY(),1,0),"") | Y22: =IF(A22="","",IF(COUNTIF($A$7:$A$26,A22)>1,"✖ PatientID duplicado",IF(AND(ISNUMBER(G22),G22>TODAY()),"✖ Fecha nacimiento futura",IF(AND(M22<>"",COUNTIF(M22,"?*@?*.?*")=0),"▲ Correo básico inválido",IF(COUNTIF(CATALOGOS!$A$7:$A$11,B22)=0,"✖ Estado no permitido",IF(AND(R22="Sí",NOT(ISNUMBER(S22))),"✖ Consentimiento Sí sin fecha",IF(AND(ISNUMBER(H22),OR(H22<CONFIG!$B$36,H22>CONFIG!$B$37)),"▲ Fuera de alcance adulto","✔ Correcto")))))))
H23: =IF(ISNUMBER(G23),YEAR(TODAY())-YEAR(G23)-IF(DATE(YEAR(TODAY()),MONTH(G23),DAY(G23))>TODAY(),1,0),"") | Y23: =IF(A23="","",IF(COUNTIF($A$7:$A$26,A23)>1,"✖ PatientID duplicado",IF(AND(ISNUMBER(G23),G23>TODAY()),"✖ Fecha nacimiento futura",IF(AND(M23<>"",COUNTIF(M23,"?*@?*.?*")=0),"▲ Correo básico inválido",IF(COUNTIF(CATALOGOS!$A$7:$A$11,B23)=0,"✖ Estado no permitido",IF(AND(R23="Sí",NOT(ISNUMBER(S23))),"✖ Consentimiento Sí sin fecha",IF(AND(ISNUMBER(H23),OR(H23<CONFIG!$B$36,H23>CONFIG!$B$37)),"▲ Fuera de alcance adulto","✔ Correcto")))))))
... H26: =IF(ISNUMBER(G26),YEAR(TODAY())-YEAR(G26)-IF(DATE(YEAR(TODAY()),MONTH(G26),DAY(G26))>TODAY(),1,0),"") | Y26: =IF(A26="","",IF(COUNTIF($A$7:$A$26,A26)>1,"✖ PatientID duplicado",IF(AND(ISNUMBER(G26),G26>TODAY()),"✖ Fecha nacimiento futura",IF(AND(M26<>"",COUNTIF(M26,"?*@?*.?*")=0),"▲ Correo básico inválido",IF(COUNTIF(CATALOGOS!$A$7:$A$11,B26)=0,"✖ Estado no permitido",IF(AND(R26="Sí",NOT(ISNUMBER(S26))),"✖ Consentimiento Sí sin fecha",IF(AND(ISNUMBER(H26),OR(H26<CONFIG!$B$36,H26>CONFIG!$B$37)),"▲ Fuera de alcance adulto","✔ Correcto")))))))

Sheet EVALUACION
A1: EVALUACIÓN · Maestro de atenciones y trazabilidad
A2: ◀ INICIO | B2: RESUMEN | C2: CONFIG | D2: PRUEBAS
A3: PACIENTE FICTICIO PARA PRUEBA — NO UTILIZAR COMO REFERENCIA CLÍNICA · Una evaluación corresponde a un único PatientID.
A5: T_EVALUACIONES
A6: EvaluationID | B6: PatientID | C6: Fecha | D6: Hora opcional | E6: Tipo evaluación | F6: Modalidad | G6: Motivo consulta | H6: Derivación | I6: Profesional | J6: Estado | K6: Duración aproximada min | L6: Prioridad clínica manual | M6: Fuente información | N6: Confiabilidad relato | O6: Acompañante opcional | P6: Observaciones | Q6: FechaRegistro | R6: FechaModificacion | S6: RangoPaciente | T6: ClavePacienteRango | U6: Control
A7: E-A-01 | B7: P-FICT-A | C7: 46174 | D7: 09:00 | E7: Inicial | F7: Presencial | G7: Evaluación inicial ficticia | H7: Sin derivación | I7: PROF-DEMO | J7: Revisado | K7: 60 | L7: Media | M7: Informado por paciente | N7: Alta | P7: PACIENTE FICTICIO PARA PRUEBA — NO UTILIZAR COMO REFERENCIA CLÍNICA | Q7: 46174 | R7: 46216 | S7: =IF(A7="","",COUNTIF($B$7:B7,B7)) -> 1 | T7: =IF(A7="","",B7&"|"&S7) -> P-FICT-A|1 | U7: =IF(A7="","",IF(COUNTIF($A$7:$A$3006,A7)>1,"✖ EvaluationID duplicado",IF(COUNTIF(PACIENTES!$A$7:$A$1006,B7)=0,"✖ PatientID inexistente",IF(AND(ISNUMBER(C7),C7>TODAY(),CONFIG!$B$31="No"),"✖ Fecha futura",IF(COUNTIF(CATALOGOS!$O$7:$O$12,J7)=0,"✖ Estado no permitido",IF(I7="","▲ Evaluación sin profesional","✔ Correcto")))))) -> ✔ Correcto
A8: E-B-01 | B8: P-FICT-B | C8: 46143 | D8: 10:00 | E8: Inicial | F8: Presencial | G8: Evaluación inicial ficticia | H8: Sin derivación | I8: PROF-DEMO | J8: Revisado | K8: 60 | L8: Media | M8: Informado por paciente | N8: Alta | P8: PACIENTE FICTICIO PARA PRUEBA — NO UTILIZAR COMO REFERENCIA CLÍNICA | Q8: 46143 | R8: 46216 | S8: =IF(A8="","",COUNTIF($B$7:B8,B8)) -> 1 | T8: =IF(A8="","",B8&"|"&S8) -> P-FICT-B|1 | U8: =IF(A8="","",IF(COUNTIF($A$7:$A$3006,A8)>1,"✖ EvaluationID duplicado",IF(COUNTIF(PACIENTES!$A$7:$A$1006,B8)=0,"✖ PatientID inexistente",IF(AND(ISNUMBER(C8),C8>TODAY(),CONFIG!$B$31="No"),"✖ Fecha futura",IF(COUNTIF(CATALOGOS!$O$7:$O$12,J8)=0,"✖ Estado no permitido",IF(I8="","▲ Evaluación sin profesional","✔ Correcto")))))) -> ✔ Correcto
A9: E-B-02 | B9: P-FICT-B | C9: 46204 | D9: 10:30 | E9: Control | F9: Remota | G9: Control longitudinal ficticio | H9: Sin derivación | I9: PROF-DEMO | J9: Completo | K9: 45 | L9: Media | M9: Informado por paciente | N9: Alta | P9: PACIENTE FICTICIO PARA PRUEBA — NO UTILIZAR COMO REFERENCIA CLÍNICA | Q9: 46204 | R9: 46216 | S9: =IF(A9="","",COUNTIF($B$7:B9,B9)) -> 2 | T9: =IF(A9="","",B9&"|"&S9) -> P-FICT-B|2 | U9: =IF(A9="","",IF(COUNTIF($A$7:$A$3006,A9)>1,"✖ EvaluationID duplicado",IF(COUNTIF(PACIENTES!$A$7:$A$1006,B9)=0,"✖ PatientID inexistente",IF(AND(ISNUMBER(C9),C9>TODAY(),CONFIG!$B$31="No"),"✖ Fecha futura",IF(COUNTIF(CATALOGOS!$O$7:$O$12,J9)=0,"✖ Estado no permitido",IF(I9="","▲ Evaluación sin profesional","✔ Correcto")))))) -> ✔ Correcto
A10: E-C-01 | B10: P-FICT-C | C10: 46205 | D10: 11:00 | E10: Inicial | F10: Presencial | G10: Evaluación incompleta ficticia | H10: Sin derivación | I10: PROF-DEMO | J10: Borrador | K10: 30 | L10: Baja | M10: Informado por paciente | N10: No evaluada | P10: PACIENTE FICTICIO PARA PRUEBA — NO UTILIZAR COMO REFERENCIA CLÍNICA | Q10: 46205 | R10: 46216 | S10: =IF(A10="","",COUNTIF($B$7:B10,B10)) -> 1 | T10: =IF(A10="","",B10&"|"&S10) -> P-FICT-C|1 | U10: =IF(A10="","",IF(COUNTIF($A$7:$A$3006,A10)>1,"✖ EvaluationID duplicado",IF(COUNTIF(PACIENTES!$A$7:$A$1006,B10)=0,"✖ PatientID inexistente",IF(AND(ISNUMBER(C10),C10>TODAY(),CONFIG!$B$31="No"),"✖ Fecha futura",IF(COUNTIF(CATALOGOS!$O$7:$O$12,J10)=0,"✖ Estado no permitido",IF(I10="","▲ Evaluación sin profesional","✔ Correcto")))))) -> ✔ Correcto
A11: E-D-01 | B11: P-FICT-D | C11: 46183 | D11: 12:00 | E11: Inicial | F11: Mixta | G11: Caso de advertencias ficticio | H11: Sin derivación | I11: PROF-DEMO | J11: Completo | K11: 60 | L11: Alta | M11: Documentado | N11: Media | P11: PACIENTE FICTICIO PARA PRUEBA — NO UTILIZAR COMO REFERENCIA CLÍNICA | Q11: 46183 | R11: 46216 | S11: =IF(A11="","",COUNTIF($B$7:B11,B11)) -> 1 | T11: =IF(A11="","",B11&"|"&S11) -> P-FICT-D|1 | U11: =IF(A11="","",IF(COUNTIF($A$7:$A$3006,A11)>1,"✖ EvaluationID duplicado",IF(COUNTIF(PACIENTES!$A$7:$A$1006,B11)=0,"✖ PatientID inexistente",IF(AND(ISNUMBER(C11),C11>TODAY(),CONFIG!$B$31="No"),"✖ Fecha futura",IF(COUNTIF(CATALOGOS!$O$7:$O$12,J11)=0,"✖ Estado no permitido",IF(I11="","▲ Evaluación sin profesional","✔ Correcto")))))) -> ✔ Correcto
A12: E-E-01 | B12: P-FICT-E | C12: 46208 | D12: 13:00 | E12: Inicial | F12: Presencial | G12: Caso de integridad ficticio | H12: Sin derivación | I12: PROF-DEMO | J12: Borrador | K12: 30 | L12: Media | M12: Documentado | N12: Media | P12: PACIENTE FICTICIO PARA PRUEBA — NO UTILIZAR COMO REFERENCIA CLÍNICA · Cruces inválidos solo en PRUEBAS. | Q12: 46208 | R12: 46216 | S12: =IF(A12="","",COUNTIF($B$7:B12,B12)) -> 1 | T12: =IF(A12="","",B12&"|"&S12) -> P-FICT-E|1 | U12: =IF(A12="","",IF(COUNTIF($A$7:$A$3006,A12)>1,"✖ EvaluationID duplicado",IF(COUNTIF(PACIENTES!$A$7:$A$1006,B12)=0,"✖ PatientID inexistente",IF(AND(ISNUMBER(C12),C12>TODAY(),CONFIG!$B$31="No"),"✖ Fecha futura",IF(COUNTIF(CATALOGOS!$O$7:$O$12,J12)=0,"✖ Estado no permitido",IF(I12="","▲ Evaluación sin profesional","✔ Correcto")))))) -> ✔ Correcto
S13: =IF(A13="","",COUNTIF($B$7:B13,B13)) | T13: =IF(A13="","",B13&"|"&S13) | U13: =IF(A13="","",IF(COUNTIF($A$7:$A$36,A13)>1,"✖ EvaluationID duplicado",IF(COUNTIF(PACIENTES!$A$7:$A$26,B13)=0,"✖ PatientID inexistente",IF(AND(ISNUMBER(C13),C13>TODAY(),CONFIG!$B$31="No"),"✖ Fecha futura",IF(COUNTIF(CATALOGOS!$O$7:$O$12,J13)=0,"✖ Estado no permitido",IF(I13="","▲ Evaluación sin profesional","✔ Correcto"))))))
S14: =IF(A14="","",COUNTIF($B$7:B14,B14)) | T14: =IF(A14="","",B14&"|"&S14) | U14: =IF(A14="","",IF(COUNTIF($A$7:$A$36,A14)>1,"✖ EvaluationID duplicado",IF(COUNTIF(PACIENTES!$A$7:$A$26,B14)=0,"✖ PatientID inexistente",IF(AND(ISNUMBER(C14),C14>TODAY(),CONFIG!$B$31="No"),"✖ Fecha futura",IF(COUNTIF(CATALOGOS!$O$7:$O$12,J14)=0,"✖ Estado no permitido",IF(I14="","▲ Evaluación sin profesional","✔ Correcto"))))))
S15: =IF(A15="","",COUNTIF($B$7:B15,B15)) | T15: =IF(A15="","",B15&"|"&S15) | U15: =IF(A15="","",IF(COUNTIF($A$7:$A$36,A15)>1,"✖ EvaluationID duplicado",IF(COUNTIF(PACIENTES!$A$7:$A$26,B15)=0,"✖ PatientID inexistente",IF(AND(ISNUMBER(C15),C15>TODAY(),CONFIG!$B$31="No"),"✖ Fecha futura",IF(COUNTIF(CATALOGOS!$O$7:$O$12,J15)=0,"✖ Estado no permitido",IF(I15="","▲ Evaluación sin profesional","✔ Correcto"))))))
S16: =IF(A16="","",COUNTIF($B$7:B16,B16)) | T16: =IF(A16="","",B16&"|"&S16) | U16: =IF(A16="","",IF(COUNTIF($A$7:$A$36,A16)>1,"✖ EvaluationID duplicado",IF(COUNTIF(PACIENTES!$A$7:$A$26,B16)=0,"✖ PatientID inexistente",IF(AND(ISNUMBER(C16),C16>TODAY(),CONFIG!$B$31="No"),"✖ Fecha futura",IF(COUNTIF(CATALOGOS!$O$7:$O$12,J16)=0,"✖ Estado no permitido",IF(I16="","▲ Evaluación sin profesional","✔ Correcto"))))))
S17: =IF(A17="","",COUNTIF($B$7:B17,B17)) | T17: =IF(A17="","",B17&"|"&S17) | U17: =IF(A17="","",IF(COUNTIF($A$7:$A$36,A17)>1,"✖ EvaluationID duplicado",IF(COUNTIF(PACIENTES!$A$7:$A$26,B17)=0,"✖ PatientID inexistente",IF(AND(ISNUMBER(C17),C17>TODAY(),CONFIG!$B$31="No"),"✖ Fecha futura",IF(COUNTIF(CATALOGOS!$O$7:$O$12,J17)=0,"✖ Estado no permitido",IF(I17="","▲ Evaluación sin profesional","✔ Correcto"))))))
S18: =IF(A18="","",COUNTIF($B$7:B18,B18)) | T18: =IF(A18="","",B18&"|"&S18) | U18: =IF(A18="","",IF(COUNTIF($A$7:$A$36,A18)>1,"✖ EvaluationID duplicado",IF(COUNTIF(PACIENTES!$A$7:$A$26,B18)=0,"✖ PatientID inexistente",IF(AND(ISNUMBER(C18),C18>TODAY(),CONFIG!$B$31="No"),"✖ Fecha futura",IF(COUNTIF(CATALOGOS!$O$7:$O$12,J18)=0,"✖ Estado no permitido",IF(I18="","▲ Evaluación sin profesional","✔ Correcto"))))))
S19: =IF(A19="","",COUNTIF($B$7:B19,B19)) | T19: =IF(A19="","",B19&"|"&S19) | U19: =IF(A19="","",IF(COUNTIF($A$7:$A$36,A19)>1,"✖ EvaluationID duplicado",IF(COUNTIF(PACIENTES!$A$7:$A$26,B19)=0,"✖ PatientID inexistente",IF(AND(ISNUMBER(C19),C19>TODAY(),CONFIG!$B$31="No"),"✖ Fecha futura",IF(COUNTIF(CATALOGOS!$O$7:$O$12,J19)=0,"✖ Estado no permitido",IF(I19="","▲ Evaluación sin profesional","✔ Correcto"))))))
S20: =IF(A20="","",COUNTIF($B$7:B20,B20)) | T20: =IF(A20="","",B20&"|"&S20) | U20: =IF(A20="","",IF(COUNTIF($A$7:$A$36,A20)>1,"✖ EvaluationID duplicado",IF(COUNTIF(PACIENTES!$A$7:$A$26,B20)=0,"✖ PatientID inexistente",IF(AND(ISNUMBER(C20),C20>TODAY(),CONFIG!$B$31="No"),"✖ Fecha futura",IF(COUNTIF(CATALOGOS!$O$7:$O$12,J20)=0,"✖ Estado no permitido",IF(I20="","▲ Evaluación sin profesional","✔ Correcto"))))))
S21: =IF(A21="","",COUNTIF($B$7:B21,B21)) | T21: =IF(A21="","",B21&"|"&S21) | U21: =IF(A21="","",IF(COUNTIF($A$7:$A$36,A21)>1,"✖ EvaluationID duplicado",IF(COUNTIF(PACIENTES!$A$7:$A$26,B21)=0,"✖ PatientID inexistente",IF(AND(ISNUMBER(C21),C21>TODAY(),CONFIG!$B$31="No"),"✖ Fecha futura",IF(COUNTIF(CATALOGOS!$O$7:$O$12,J21)=0,"✖ Estado no permitido",IF(I21="","▲ Evaluación sin profesional","✔ Correcto"))))))
S22: =IF(A22="","",COUNTIF($B$7:B22,B22)) | T22: =IF(A22="","",B22&"|"&S22) | U22: =IF(A22="","",IF(COUNTIF($A$7:$A$36,A22)>1,"✖ EvaluationID duplicado",IF(COUNTIF(PACIENTES!$A$7:$A$26,B22)=0,"✖ PatientID inexistente",IF(AND(ISNUMBER(C22),C22>TODAY(),CONFIG!$B$31="No"),"✖ Fecha futura",IF(COUNTIF(CATALOGOS!$O$7:$O$12,J22)=0,"✖ Estado no permitido",IF(I22="","▲ Evaluación sin profesional","✔ Correcto"))))))
S23: =IF(A23="","",COUNTIF($B$7:B23,B23)) | T23: =IF(A23="","",B23&"|"&S23) | U23: =IF(A23="","",IF(COUNTIF($A$7:$A$36,A23)>1,"✖ EvaluationID duplicado",IF(COUNTIF(PACIENTES!$A$7:$A$26,B23)=0,"✖ PatientID inexistente",IF(AND(ISNUMBER(C23),C23>TODAY(),CONFIG!$B$31="No"),"✖ Fecha futura",IF(COUNTIF(CATALOGOS!$O$7:$O$12,J23)=0,"✖ Estado no permitido",IF(I23="","▲ Evaluación sin profesional","✔ Correcto"))))))
S24: =IF(A24="","",COUNTIF($B$7:B24,B24)) | T24: =IF(A24="","",B24&"|"&S24) | U24: =IF(A24="","",IF(COUNTIF($A$7:$A$36,A24)>1,"✖ EvaluationID duplicado",IF(COUNTIF(PACIENTES!$A$7:$A$26,B24)=0,"✖ PatientID inexistente",IF(AND(ISNUMBER(C24),C24>TODAY(),CONFIG!$B$31="No"),"✖ Fecha futura",IF(COUNTIF(CATALOGOS!$O$7:$O$12,J24)=0,"✖ Estado no permitido",IF(I24="","▲ Evaluación sin profesional","✔ Correcto"))))))
... S36: =IF(A36="","",COUNTIF($B$7:B36,B36)) | T36: =IF(A36="","",B36&"|"&S36) | U36: =IF(A36="","",IF(COUNTIF($A$7:$A$36,A36)>1,"✖ EvaluationID duplicado",IF(COUNTIF(PACIENTES!$A$7:$A$26,B36)=0,"✖ PatientID inexistente",IF(AND(ISNUMBER(C36),C36>TODAY(),CONFIG!$B$31="No"),"✖ Fecha futura",IF(COUNTIF(CATALOGOS!$O$7:$O$12,J36)=0,"✖ Estado no permitido",IF(I36="","▲ Evaluación sin profesional","✔ Correcto"))))))

Sheet ANTECEDENTES
A1: ANTECEDENTES · Registros múltiples por evaluación
A2: ◀ INICIO | B2: RESUMEN | C2: CONFIG | D2: PRUEBAS
A3: PACIENTE FICTICIO PARA PRUEBA — NO UTILIZAR COMO REFERENCIA CLÍNICA · No convertir automáticamente un antecedente en diagnóstico.
A5: T_ANTECEDENTES
A6: EvaluationID | B6: PatientID | C6: Categoría | D6: Antecedente | E6: Estado | F6: Fecha inicio | G6: Fecha término | H6: Profesional diagnóstico opcional | I6: Tratamiento relacionado | J6: Relevancia nutricional manual | K6: FuenteDato | L6: FechaRegistro | M6: FechaModificacion | N6: Profesional | O6: Observaciones | P6: Control
A7: E-A-01 | B7: P-FICT-A | C7: Personales | D7: Antecedente ficticio A | E7: Activo | F7: 45292 | J7: Relevancia manual | K7: Documentado | L7: 46174 | M7: 46216 | N7: PROF-DEMO | O7: PACIENTE FICTICIO PARA PRUEBA — NO UTILIZAR COMO REFERENCIA CLÍNICA | P7: =IF(A7="","",IF(COUNTIF(EVALUACION!$A$7:$A$3006,A7)=0,"✖ EvaluationID inexistente",IF(COUNTIFS(EVALUACION!$A$7:$A$3006,A7,EVALUACION!$B$7:$B$3006,B7)=0,"✖ EvaluationID de otro paciente",IF(AND(ISNUMBER(F7),ISNUMBER(G7),G7<F7),"✖ Fecha término anterior","✔ Correcto")))) -> ✔ Correcto
A8: E-B-01 | B8: P-FICT-B | C8: Familiares | D8: Antecedente familiar ficticio | E8: Informado | J8: Relevancia manual | K8: Informado por paciente | L8: 46143 | M8: 46216 | N8: PROF-DEMO | O8: PACIENTE FICTICIO PARA PRUEBA — NO UTILIZAR COMO REFERENCIA CLÍNICA | P8: =IF(A8="","",IF(COUNTIF(EVALUACION!$A$7:$A$3006,A8)=0,"✖ EvaluationID inexistente",IF(COUNTIFS(EVALUACION!$A$7:$A$3006,A8,EVALUACION!$B$7:$B$3006,B8)=0,"✖ EvaluationID de otro paciente",IF(AND(ISNUMBER(F8),ISNUMBER(G8),G8<F8),"✖ Fecha término anterior","✔ Correcto")))) -> ✔ Correcto
A9: E-D-01 | B9: P-FICT-D | C9: Alergias | D9: Alergia ficticia no especificada | E9: Pendiente | J9: Revisar | K9: Informado por paciente | L9: 46183 | M9: 46216 | N9: PROF-DEMO | O9: PACIENTE FICTICIO PARA PRUEBA — NO UTILIZAR COMO REFERENCIA CLÍNICA | P9: =IF(A9="","",IF(COUNTIF(EVALUACION!$A$7:$A$3006,A9)=0,"✖ EvaluationID inexistente",IF(COUNTIFS(EVALUACION!$A$7:$A$3006,A9,EVALUACION!$B$7:$B$3006,B9)=0,"✖ EvaluationID de otro paciente",IF(AND(ISNUMBER(F9),ISNUMBER(G9),G9<F9),"✖ Fecha término anterior","✔ Correcto")))) -> ✔ Correcto
P10: =IF(A10="","",IF(COUNTIF(EVALUACION!$A$7:$A$36,A10)=0,"✖ EvaluationID inexistente",IF(COUNTIFS(EVALUACION!$A$7:$A$36,A10,EVALUACION!$B$7:$B$36,B10)=0,"✖ EvaluationID de otro paciente",IF(AND(ISNUMBER(F10),ISNUMBER(G10),G10<F10),"✖ Fecha término anterior","✔ Correcto"))))
P11: =IF(A11="","",IF(COUNTIF(EVALUACION!$A$7:$A$36,A11)=0,"✖ EvaluationID inexistente",IF(COUNTIFS(EVALUACION!$A$7:$A$36,A11,EVALUACION!$B$7:$B$36,B11)=0,"✖ EvaluationID de otro paciente",IF(AND(ISNUMBER(F11),ISNUMBER(G11),G11<F11),"✖ Fecha término anterior","✔ Correcto"))))
P12: =IF(A12="","",IF(COUNTIF(EVALUACION!$A$7:$A$36,A12)=0,"✖ EvaluationID inexistente",IF(COUNTIFS(EVALUACION!$A$7:$A$36,A12,EVALUACION!$B$7:$B$36,B12)=0,"✖ EvaluationID de otro paciente",IF(AND(ISNUMBER(F12),ISNUMBER(G12),G12<F12),"✖ Fecha término anterior","✔ Correcto"))))
P13: =IF(A13="","",IF(COUNTIF(EVALUACION!$A$7:$A$36,A13)=0,"✖ EvaluationID inexistente",IF(COUNTIFS(EVALUACION!$A$7:$A$36,A13,EVALUACION!$B$7:$B$36,B13)=0,"✖ EvaluationID de otro paciente",IF(AND(ISNUMBER(F13),ISNUMBER(G13),G13<F13),"✖ Fecha término anterior","✔ Correcto"))))
P14: =IF(A14="","",IF(COUNTIF(EVALUACION!$A$7:$A$36,A14)=0,"✖ EvaluationID inexistente",IF(COUNTIFS(EVALUACION!$A$7:$A$36,A14,EVALUACION!$B$7:$B$36,B14)=0,"✖ EvaluationID de otro paciente",IF(AND(ISNUMBER(F14),ISNUMBER(G14),G14<F14),"✖ Fecha término anterior","✔ Correcto"))))
P15: =IF(A15="","",IF(COUNTIF(EVALUACION!$A$7:$A$36,A15)=0,"✖ EvaluationID inexistente",IF(COUNTIFS(EVALUACION!$A$7:$A$36,A15,EVALUACION!$B$7:$B$36,B15)=0,"✖ EvaluationID de otro paciente",IF(AND(ISNUMBER(F15),ISNUMBER(G15),G15<F15),"✖ Fecha término anterior","✔ Correcto"))))
P16: =IF(A16="","",IF(COUNTIF(EVALUACION!$A$7:$A$36,A16)=0,"✖ EvaluationID inexistente",IF(COUNTIFS(EVALUACION!$A$7:$A$36,A16,EVALUACION!$B$7:$B$36,B16)=0,"✖ EvaluationID de otro paciente",IF(AND(ISNUMBER(F16),ISNUMBER(G16),G16<F16),"✖ Fecha término anterior","✔ Correcto"))))
P17: =IF(A17="","",IF(COUNTIF(EVALUACION!$A$7:$A$36,A17)=0,"✖ EvaluationID inexistente",IF(COUNTIFS(EVALUACION!$A$7:$A$36,A17,EVALUACION!$B$7:$B$36,B17)=0,"✖ EvaluationID de otro paciente",IF(AND(ISNUMBER(F17),ISNUMBER(G17),G17<F17),"✖ Fecha término anterior","✔ Correcto"))))
P18: =IF(A18="","",IF(COUNTIF(EVALUACION!$A$7:$A$36,A18)=0,"✖ EvaluationID inexistente",IF(COUNTIFS(EVALUACION!$A$7:$A$36,A18,EVALUACION!$B$7:$B$36,B18)=0,"✖ EvaluationID de otro paciente",IF(AND(ISNUMBER(F18),ISNUMBER(G18),G18<F18),"✖ Fecha término anterior","✔ Correcto"))))
P19: =IF(A19="","",IF(COUNTIF(EVALUACION!$A$7:$A$36,A19)=0,"✖ EvaluationID inexistente",IF(COUNTIFS(EVALUACION!$A$7:$A$36,A19,EVALUACION!$B$7:$B$36,B19)=0,"✖ EvaluationID de otro paciente",IF(AND(ISNUMBER(F19),ISNUMBER(G19),G19<F19),"✖ Fecha término anterior","✔ Correcto"))))
P20: =IF(A20="","",IF(COUNTIF(EVALUACION!$A$7:$A$36,A20)=0,"✖ EvaluationID inexistente",IF(COUNTIFS(EVALUACION!$A$7:$A$36,A20,EVALUACION!$B$7:$B$36,B20)=0,"✖ EvaluationID de otro paciente",IF(AND(ISNUMBER(F20),ISNUMBER(G20),G20<F20),"✖ Fecha término anterior","✔ Correcto"))))
P21: =IF(A21="","",IF(COUNTIF(EVALUACION!$A$7:$A$36,A21)=0,"✖ EvaluationID inexistente",IF(COUNTIFS(EVALUACION!$A$7:$A$36,A21,EVALUACION!$B$7:$B$36,B21)=0,"✖ EvaluationID de otro paciente",IF(AND(ISNUMBER(F21),ISNUMBER(G21),G21<F21),"✖ Fecha término anterior","✔ Correcto"))))
... P46: =IF(A46="","",IF(COUNTIF(EVALUACION!$A$7:$A$36,A46)=0,"✖ EvaluationID inexistente",IF(COUNTIFS(EVALUACION!$A$7:$A$36,A46,EVALUACION!$B$7:$B$36,B46)=0,"✖ EvaluationID de otro paciente",IF(AND(ISNUMBER(F46),ISNUMBER(G46),G46<F46),"✖ Fecha término anterior","✔ Correcto"))))

Sheet ANTROPOMETRIA
A1: ANTROPOMETRÍA · Mediciones, condiciones y cálculos auditables
A2: ◀ INICIO | B2: RESUMEN | C2: CONFIG | D2: PRUEBAS
A3: PACIENTE FICTICIO PARA PRUEBA — NO UTILIZAR COMO REFERENCIA CLÍNICA · IMC y composición corporal no constituyen evaluación completa.
A5: T_ANTROPOMETRIA
A6: EvaluationID | B6: PatientID | C6: Fecha | D6: Peso kg | E6: Estatura cm | F6: IMC | G6: Peso habitual kg | H6: Peso mínimo reciente kg | I6: Peso máximo reciente kg | J6: Cambio peso kg | K6: Cambio peso % | L6: Periodo cambio | M6: Intencionalidad cambio | N6: Cintura cm | O6: Cadera cm | P6: Brazo cm | Q6: Pantorrilla cm | R6: % grasa | S6: Masa grasa kg | T6: Masa libre grasa kg | U6: Fuente % grasa | V6: Cintura/estatura | W6: Cintura/cadera | X6: Calidad medición | Y6: Ayuno | Z6: Horario | AA6: Ropa | AB6: Retención líquidos | AC6: Edema | AD6: Dispositivo | AE6: Condiciones medición | AF6: Instrumento | AG6: Profesional | AH6: FuenteDato | AI6: Observaciones | AJ6: RangoPaciente | AK6: ClavePacienteRango | AL6: Control
A7: E-A-01 | B7: P-FICT-A | C7: 46174 | D7: 70 | E7: 165 | F7: =IF(AND(ISNUMBER(D7),ISNUMBER(E7),D7>0,E7>0),D7/((E7/100)^2),"") -> 25.711662 | G7: 72 | H7: 68 | I7: 75 | J7: =IF(AND(ISNUMBER(D7),ISNUMBER(G7)),D7-G7,"") -> -2 | K7: =IF(AND(ISNUMBER(D7),ISNUMBER(G7),G7<>0),(D7-G7)/G7,"") -> -0.027777778 | L7: 3 meses | M7: Intencional | N7: 82 | O7: 98 | P7: 29 | Q7: 36 | R7: 30 | S7: =IF(CONFIG!$B$28="No","",IF(AND(ISNUMBER(D7),ISNUMBER(R7),R7>=0,R7<=100,U7<>""),D7*R7/100,"")) -> 21 | T7: =IF(CONFIG!$B$28="No","",IF(AND(ISNUMBER(D7),ISNUMBER(S7)),D7-S7,"")) -> 49 | U7: BIA | V7: =IF(AND(ISNUMBER(N7),ISNUMBER(E7),E7>0),N7/E7,"") -> 0.4969697 | W7: =IF(AND(ISNUMBER(N7),ISNUMBER(O7),O7>0),N7/O7,"") -> 0.83673469 | X7: Adecuada | Y7: Sí | Z7: 09:00 | AA7: Ligera | AB7: No | AC7: No | AD7: BIA | AE7: Condición ficticia | AF7: Equipo ficticio | AG7: PROF-DEMO | AH7: Medido | AI7: PACIENTE FICTICIO PARA PRUEBA — NO UTILIZAR COMO REFERENCIA CLÍNICA | AJ7: =IF(A7="","",COUNTIF($B$7:B7,B7)) -> 1 | AK7: =IF(A7="","",B7&"|"&AJ7) -> P-FICT-A|1 | AL7: =IF(A7="","",IF(COUNTIFS(EVALUACION!$A$7:$A$3006,A7,EVALUACION!$B$7:$B$3006,B7)=0,"✖ Evaluación/paciente inconsistente",IF(OR(D7<0,E7<0,N7<0,O7<0),"✖ Valor negativo",IF(OR(AND(ISNUMBER(D7),OR(D7<CONFIG!$B$38,D7>CONFIG!$B$39)),AND(ISNUMBER(E7),OR(E7<CONFIG!$B$40,E7>CONFIG!$B$41))),"▲ Fuera de límite operativo",IF(AND(ISNUMBER(R7),OR(R7<0,R7>100)),"✖ % grasa fuera de 0–100",IF(AND(ISNUMBER(R7),U7=""),"▲ Falta fuente de % grasa",IF(E7="","▲ Estatura faltante",IF(AC7="Sí","▲ Edema registrado","✔ Correcto")))))))) -> ✔ Correcto
A8: E-B-01 | B8: P-FICT-B | C8: 46143 | D8: 90 | E8: 180 | F8: =IF(AND(ISNUMBER(D8),ISNUMBER(E8),D8>0,E8>0),D8/((E8/100)^2),"") -> 27.777778 | G8: 92 | H8: 88 | I8: 95 | J8: =IF(AND(ISNUMBER(D8),ISNUMBER(G8)),D8-G8,"") -> -2 | K8: =IF(AND(ISNUMBER(D8),ISNUMBER(G8),G8<>0),(D8-G8)/G8,"") -> -0.02173913 | L8: 2 meses | M8: No intencional | N8: 100 | O8: 105 | P8: 33 | Q8: 40 | R8: 25 | S8: =IF(CONFIG!$B$28="No","",IF(AND(ISNUMBER(D8),ISNUMBER(R8),R8>=0,R8<=100,U8<>""),D8*R8/100,"")) -> 22.5 | T8: =IF(CONFIG!$B$28="No","",IF(AND(ISNUMBER(D8),ISNUMBER(S8)),D8-S8,"")) -> 67.5 | U8: BIA | V8: =IF(AND(ISNUMBER(N8),ISNUMBER(E8),E8>0),N8/E8,"") -> 0.55555556 | W8: =IF(AND(ISNUMBER(N8),ISNUMBER(O8),O8>0),N8/O8,"") -> 0.95238095 | X8: Adecuada | Y8: Sí | Z8: 10:00 | AA8: Ligera | AB8: No | AC8: No | AD8: BIA | AE8: Condición ficticia | AF8: Equipo ficticio | AG8: PROF-DEMO | AH8: Medido | AI8: PACIENTE FICTICIO PARA PRUEBA — NO UTILIZAR COMO REFERENCIA CLÍNICA | AJ8: =IF(A8="","",COUNTIF($B$7:B8,B8)) -> 1 | AK8: =IF(A8="","",B8&"|"&AJ8) -> P-FICT-B|1 | AL8: =IF(A8="","",IF(COUNTIFS(EVALUACION!$A$7:$A$3006,A8,EVALUACION!$B$7:$B$3006,B8)=0,"✖ Evaluación/paciente inconsistente",IF(OR(D8<0,E8<0,N8<0,O8<0),"✖ Valor negativo",IF(OR(AND(ISNUMBER(D8),OR(D8<CONFIG!$B$38,D8>CONFIG!$B$39)),AND(ISNUMBER(E8),OR(E8<CONFIG!$B$40,E8>CONFIG!$B$41))),"▲ Fuera de límite operativo",IF(AND(ISNUMBER(R8),OR(R8<0,R8>100)),"✖ % grasa fuera de 0–100",IF(AND(ISNUMBER(R8),U8=""),"▲ Falta fuente de % grasa",IF(E8="","▲ Estatura faltante",IF(AC8="Sí","▲ Edema registrado","✔ Correcto")))))))) -> ✔ Correcto
A9: E-B-02 | B9: P-FICT-B | C9: 46204 | D9: 87 | E9: 180 | F9: =IF(AND(ISNUMBER(D9),ISNUMBER(E9),D9>0,E9>0),D9/((E9/100)^2),"") -> 26.851852 | G9: 92 | H9: 87 | I9: 95 | J9: =IF(AND(ISNUMBER(D9),ISNUMBER(G9)),D9-G9,"") -> -5 | K9: =IF(AND(ISNUMBER(D9),ISNUMBER(G9),G9<>0),(D9-G9)/G9,"") -> -0.054347826 | L9: 2 meses | M9: Acordado | N9: 96 | O9: 103 | P9: 32 | Q9: 39 | R9: 24 | S9: =IF(CONFIG!$B$28="No","",IF(AND(ISNUMBER(D9),ISNUMBER(R9),R9>=0,R9<=100,U9<>""),D9*R9/100,"")) -> 20.88 | T9: =IF(CONFIG!$B$28="No","",IF(AND(ISNUMBER(D9),ISNUMBER(S9)),D9-S9,"")) -> 66.12 | U9: BIA | V9: =IF(AND(ISNUMBER(N9),ISNUMBER(E9),E9>0),N9/E9,"") -> 0.53333333 | W9: =IF(AND(ISNUMBER(N9),ISNUMBER(O9),O9>0),N9/O9,"") -> 0.93203883 | X9: Adecuada | Y9: Sí | Z9: 10:30 | AA9: Ligera | AB9: No | AC9: No | AD9: BIA | AE9: Condición ficticia | AF9: Equipo ficticio | AG9: PROF-DEMO | AH9: Medido | AI9: PACIENTE FICTICIO PARA PRUEBA — NO UTILIZAR COMO REFERENCIA CLÍNICA | AJ9: =IF(A9="","",COUNTIF($B$7:B9,B9)) -> 2 | AK9: =IF(A9="","",B9&"|"&AJ9) -> P-FICT-B|2 | AL9: =IF(A9="","",IF(COUNTIFS(EVALUACION!$A$7:$A$3006,A9,EVALUACION!$B$7:$B$3006,B9)=0,"✖ Evaluación/paciente inconsistente",IF(OR(D9<0,E9<0,N9<0,O9<0),"✖ Valor negativo",IF(OR(AND(ISNUMBER(D9),OR(D9<CONFIG!$B$38,D9>CONFIG!$B$39)),AND(ISNUMBER(E9),OR(E9<CONFIG!$B$40,E9>CONFIG!$B$41))),"▲ Fuera de límite operativo",IF(AND(ISNUMBER(R9),OR(R9<0,R9>100)),"✖ % grasa fuera de 0–100",IF(AND(ISNUMBER(R9),U9=""),"▲ Falta fuente de % grasa",IF(E9="","▲ Estatura faltante",IF(AC9="Sí","▲ Edema registrado","✔ Correcto")))))))) -> ✔ Correcto
A10: E-C-01 | B10: P-FICT-C | C10: 46205 | D10: 65 | F10: =IF(AND(ISNUMBER(D10),ISNUMBER(E10),D10>0,E10>0),D10/((E10/100)^2),"") | G10: 65 | H10: 64 | I10: 66 | J10: =IF(AND(ISNUMBER(D10),ISNUMBER(G10)),D10-G10,"") -> 0 | K10: =IF(AND(ISNUMBER(D10),ISNUMBER(G10),G10<>0),(D10-G10)/G10,"") -> 0 | M10: No informado | S10: =IF(CONFIG!$B$28="No","",IF(AND(ISNUMBER(D10),ISNUMBER(R10),R10>=0,R10<=100,U10<>""),D10*R10/100,"")) | T10: =IF(CONFIG!$B$28="No","",IF(AND(ISNUMBER(D10),ISNUMBER(S10)),D10-S10,"")) | V10: =IF(AND(ISNUMBER(N10),ISNUMBER(E10),E10>0),N10/E10,"") | W10: =IF(AND(ISNUMBER(N10),ISNUMBER(O10),O10>0),N10/O10,"") | X10: Pendiente | Y10: No informado | Z10: 11:00 | AB10: No informado | AC10: No informado | AE10: Medición incompleta ficticia | AG10: PROF-DEMO | AH10: Informado por paciente | AI10: PACIENTE FICTICIO PARA PRUEBA — NO UTILIZAR COMO REFERENCIA CLÍNICA | AJ10: =IF(A10="","",COUNTIF($B$7:B10,B10)) -> 1 | AK10: =IF(A10="","",B10&"|"&AJ10) -> P-FICT-C|1 | AL10: =IF(A10="","",IF(COUNTIFS(EVALUACION!$A$7:$A$3006,A10,EVALUACION!$B$7:$B$3006,B10)=0,"✖ Evaluación/paciente inconsistente",IF(OR(D10<0,E10<0,N10<0,O10<0),"✖ Valor negativo",IF(OR(AND(ISNUMBER(D10),OR(D10<CONFIG!$B$38,D10>CONFIG!$B$39)),AND(ISNUMBER(E10),OR(E10<CONFIG!$B$40,E10>CONFIG!$B$41))),"▲ Fuera de límite operativo",IF(AND(ISNUMBER(R10),OR(R10<0,R10>100)),"✖ % grasa fuera de 0–100",IF(AND(ISNUMBER(R10),U10=""),"▲ Falta fuente de % grasa",IF(E10="","▲ Estatura faltante",IF(AC10="Sí","▲ Edema registrado","✔ Correcto")))))))) -> ▲ Estatura faltante
A11: E-D-01 | B11: P-FICT-D | C11: 46183 | D11: 78 | E11: 168 | F11: =IF(AND(ISNUMBER(D11),ISNUMBER(E11),D11>0,E11>0),D11/((E11/100)^2),"") -> 27.636054 | G11: 80 | H11: 76 | I11: 83 | J11: =IF(AND(ISNUMBER(D11),ISNUMBER(G11)),D11-G11,"") -> -2 | K11: =IF(AND(ISNUMBER(D11),ISNUMBER(G11),G11<>0),(D11-G11)/G11,"") -> -0.025 | L11: 1 mes | M11: No informado | N11: 94 | O11: 104 | P11: 31 | Q11: 38 | S11: =IF(CONFIG!$B$28="No","",IF(AND(ISNUMBER(D11),ISNUMBER(R11),R11>=0,R11<=100,U11<>""),D11*R11/100,"")) | T11: =IF(CONFIG!$B$28="No","",IF(AND(ISNUMBER(D11),ISNUMBER(S11)),D11-S11,"")) | V11: =IF(AND(ISNUMBER(N11),ISNUMBER(E11),E11>0),N11/E11,"") -> 0.55952381 | W11: =IF(AND(ISNUMBER(N11),ISNUMBER(O11),O11>0),N11/O11,"") -> 0.90384615 | X11: Adecuada | Y11: No informado | Z11: 12:00 | AA11: Ligera | AB11: Sí | AC11: Sí | AD11: Balanza | AE11: Condición ficticia con edema | AF11: Equipo ficticio | AG11: PROF-DEMO | AH11: Medido | AI11: PACIENTE FICTICIO PARA PRUEBA — NO UTILIZAR COMO REFERENCIA CLÍNICA | AJ11: =IF(A11="","",COUNTIF($B$7:B11,B11)) -> 1 | AK11: =IF(A11="","",B11&"|"&AJ11) -> P-FICT-D|1 | AL11: =IF(A11="","",IF(COUNTIFS(EVALUACION!$A$7:$A$3006,A11,EVALUACION!$B$7:$B$3006,B11)=0,"✖ Evaluación/paciente inconsistente",IF(OR(D11<0,E11<0,N11<0,O11<0),"✖ Valor negativo",IF(OR(AND(ISNUMBER(D11),OR(D11<CONFIG!$B$38,D11>CONFIG!$B$39)),AND(ISNUMBER(E11),OR(E11<CONFIG!$B$40,E11>CONFIG!$B$41))),"▲ Fuera de límite operativo",IF(AND(ISNUMBER(R11),OR(R11<0,R11>100)),"✖ % grasa fuera de 0–100",IF(AND(ISNUMBER(R11),U11=""),"▲ Falta fuente de % grasa",IF(E11="","▲ Estatura faltante",IF(AC11="Sí","▲ Edema registrado","✔ Correcto")))))))) -> ▲ Edema registrado
A12: E-E-01 | B12: P-FICT-E | C12: 46208 | D12: 82 | E12: 175 | F12: =IF(AND(ISNUMBER(D12),ISNUMBER(E12),D12>0,E12>0),D12/((E12/100)^2),"") -> 26.77551 | G12: 83 | H12: 80 | I12: 85 | J12: =IF(AND(ISNUMBER(D12),ISNUMBER(G12)),D12-G12,"") -> -1 | K12: =IF(AND(ISNUMBER(D12),ISNUMBER(G12),G12<>0),(D12-G12)/G12,"") -> -0.012048193 | L12: 1 mes | M12: No informado | N12: 90 | O12: 100 | P12: 32 | Q12: 39 | R12: 22 | S12: =IF(CONFIG!$B$28="No","",IF(AND(ISNUMBER(D12),ISNUMBER(R12),R12>=0,R12<=100,U12<>""),D12*R12/100,"")) -> 18.04 | T12: =IF(CONFIG!$B$28="No","",IF(AND(ISNUMBER(D12),ISNUMBER(S12)),D12-S12,"")) -> 63.96 | U12: Plicometría | V12: =IF(AND(ISNUMBER(N12),ISNUMBER(E12),E12>0),N12/E12,"") -> 0.51428571 | W12: =IF(AND(ISNUMBER(N12),ISNUMBER(O12),O12>0),N12/O12,"") -> 0.9 | X12: Adecuada | Y12: No | Z12: 13:00 | AA12: Ligera | AB12: No | AC12: No | AD12: Plicómetro | AE12: Condición ficticia | AF12: Equipo ficticio | AG12: PROF-DEMO | AH12: Medido | AI12: PACIENTE FICTICIO PARA PRUEBA — NO UTILIZAR COMO REFERENCIA CLÍNICA | AJ12: =IF(A12="","",COUNTIF($B$7:B12,B12)) -> 1 | AK12: =IF(A12="","",B12&"|"&AJ12) -> P-FICT-E|1 | AL12: =IF(A12="","",IF(COUNTIFS(EVALUACION!$A$7:$A$3006,A12,EVALUACION!$B$7:$B$3006,B12)=0,"✖ Evaluación/paciente inconsistente",IF(OR(D12<0,E12<0,N12<0,O12<0),"✖ Valor negativo",IF(OR(AND(ISNUMBER(D12),OR(D12<CONFIG!$B$38,D12>CONFIG!$B$39)),AND(ISNUMBER(E12),OR(E12<CONFIG!$B$40,E12>CONFIG!$B$41))),"▲ Fuera de límite operativo",IF(AND(ISNUMBER(R12),OR(R12<0,R12>100)),"✖ % grasa fuera de 0–100",IF(AND(ISNUMBER(R12),U12=""),"▲ Falta fuente de % grasa",IF(E12="","▲ Estatura faltante",IF(AC12="Sí","▲ Edema registrado","✔ Correcto")))))))) -> ✔ Correcto
F13: =IF(AND(ISNUMBER(D13),ISNUMBER(E13),D13>0,E13>0),D13/((E13/100)^2),"") | J13: =IF(AND(ISNUMBER(D13),ISNUMBER(G13)),D13-G13,"") | K13: =IF(AND(ISNUMBER(D13),ISNUMBER(G13),G13<>0),(D13-G13)/G13,"") | S13: =IF(CONFIG!$B$28="No","",IF(AND(ISNUMBER(D13),ISNUMBER(R13),R13>=0,R13<=100,U13<>""),D13*R13/100,"")) | T13: =IF(CONFIG!$B$28="No","",IF(AND(ISNUMBER(D13),ISNUMBER(S13)),D13-S13,"")) | V13: =IF(AND(ISNUMBER(N13),ISNUMBER(E13),E13>0),N13/E13,"") | W13: =IF(AND(ISNUMBER(N13),ISNUMBER(O13),O13>0),N13/O13,"") | AJ13: =IF(A13="","",COUNTIF($B$7:B13,B13)) | AK13: =IF(A13="","",B13&"|"&AJ13) | AL13: =IF(A13="","",IF(COUNTIFS(EVALUACION!$A$7:$A$36,A13,EVALUACION!$B$7:$B$36,B13)=0,"✖ Evaluación/paciente inconsistente",IF(OR(D13<0,E13<0,N13<0,O13<0),"✖ Valor negativo",IF(OR(AND(ISNUMBER(D13),OR(D13<CONFIG!$B$38,D13>CONFIG!$B$39)),AND(ISNUMBER(E13),OR(E13<CONFIG!$B$40,E13>CONFIG!$B$41))),"▲ Fuera de límite operativo",IF(AND(ISNUMBER(R13),OR(R13<0,R13>100)),"✖ % grasa fuera de 0–100",IF(AND(ISNUMBER(R13),U13=""),"▲ Falta fuente de % grasa",IF(E13="","▲ Estatura faltante",IF(AC13="Sí","▲ Edema registrado","✔ Correcto"))))))))
F14: =IF(AND(ISNUMBER(D14),ISNUMBER(E14),D14>0,E14>0),D14/((E14/100)^2),"") | J14: =IF(AND(ISNUMBER(D14),ISNUMBER(G14)),D14-G14,"") | K14: =IF(AND(ISNUMBER(D14),ISNUMBER(G14),G14<>0),(D14-G14)/G14,"") | S14: =IF(CONFIG!$B$28="No","",IF(AND(ISNUMBER(D14),ISNUMBER(R14),R14>=0,R14<=100,U14<>""),D14*R14/100,"")) | T14: =IF(CONFIG!$B$28="No","",IF(AND(ISNUMBER(D14),ISNUMBER(S14)),D14-S14,"")) | V14: =IF(AND(ISNUMBER(N14),ISNUMBER(E14),E14>0),N14/E14,"") | W14: =IF(AND(ISNUMBER(N14),ISNUMBER(O14),O14>0),N14/O14,"") | AJ14: =IF(A14="","",COUNTIF($B$7:B14,B14)) | AK14: =IF(A14="","",B14&"|"&AJ14) | AL14: =IF(A14="","",IF(COUNTIFS(EVALUACION!$A$7:$A$36,A14,EVALUACION!$B$7:$B$36,B14)=0,"✖ Evaluación/paciente inconsistente",IF(OR(D14<0,E14<0,N14<0,O14<0),"✖ Valor negativo",IF(OR(AND(ISNUMBER(D14),OR(D14<CONFIG!$B$38,D14>CONFIG!$B$39)),AND(ISNUMBER(E14),OR(E14<CONFIG!$B$40,E14>CONFIG!$B$41))),"▲ Fuera de límite operativo",IF(AND(ISNUMBER(R14),OR(R14<0,R14>100)),"✖ % grasa fuera de 0–100",IF(AND(ISNUMBER(R14),U14=""),"▲ Falta fuente de % grasa",IF(E14="","▲ Estatura faltante",IF(AC14="Sí","▲ Edema registrado","✔ Correcto"))))))))
F15: =IF(AND(ISNUMBER(D15),ISNUMBER(E15),D15>0,E15>0),D15/((E15/100)^2),"") | J15: =IF(AND(ISNUMBER(D15),ISNUMBER(G15)),D15-G15,"") | K15: =IF(AND(ISNUMBER(D15),ISNUMBER(G15),G15<>0),(D15-G15)/G15,"") | S15: =IF(CONFIG!$B$28="No","",IF(AND(ISNUMBER(D15),ISNUMBER(R15),R15>=0,R15<=100,U15<>""),D15*R15/100,"")) | T15: =IF(CONFIG!$B$28="No","",IF(AND(ISNUMBER(D15),ISNUMBER(S15)),D15-S15,"")) | V15: =IF(AND(ISNUMBER(N15),ISNUMBER(E15),E15>0),N15/E15,"") | W15: =IF(AND(ISNUMBER(N15),ISNUMBER(O15),O15>0),N15/O15,"") | AJ15: =IF(A15="","",COUNTIF($B$7:B15,B15)) | AK15: =IF(A15="","",B15&"|"&AJ15) | AL15: =IF(A15="","",IF(COUNTIFS(EVALUACION!$A$7:$A$36,A15,EVALUACION!$B$7:$B$36,B15)=0,"✖ Evaluación/paciente inconsistente",IF(OR(D15<0,E15<0,N15<0,O15<0),"✖ Valor negativo",IF(OR(AND(ISNUMBER(D15),OR(D15<CONFIG!$B$38,D15>CONFIG!$B$39)),AND(ISNUMBER(E15),OR(E15<CONFIG!$B$40,E15>CONFIG!$B$41))),"▲ Fuera de límite operativo",IF(AND(ISNUMBER(R15),OR(R15<0,R15>100)),"✖ % grasa fuera de 0–100",IF(AND(ISNUMBER(R15),U15=""),"▲ Falta fuente de % grasa",IF(E15="","▲ Estatura faltante",IF(AC15="Sí","▲ Edema registrado","✔ Correcto"))))))))
F16: =IF(AND(ISNUMBER(D16),ISNUMBER(E16),D16>0,E16>0),D16/((E16/100)^2),"") | J16: =IF(AND(ISNUMBER(D16),ISNUMBER(G16)),D16-G16,"") | K16: =IF(AND(ISNUMBER(D16),ISNUMBER(G16),G16<>0),(D16-G16)/G16,"") | S16: =IF(CONFIG!$B$28="No","",IF(AND(ISNUMBER(D16),ISNUMBER(R16),R16>=0,R16<=100,U16<>""),D16*R16/100,"")) | T16: =IF(CONFIG!$B$28="No","",IF(AND(ISNUMBER(D16),ISNUMBER(S16)),D16-S16,"")) | V16: =IF(AND(ISNUMBER(N16),ISNUMBER(E16),E16>0),N16/E16,"") | W16: =IF(AND(ISNUMBER(N16),ISNUMBER(O16),O16>0),N16/O16,"") | AJ16: =IF(A16="","",COUNTIF($B$7:B16,B16)) | AK16: =IF(A16="","",B16&"|"&AJ16) | AL16: =IF(A16="","",IF(COUNTIFS(EVALUACION!$A$7:$A$36,A16,EVALUACION!$B$7:$B$36,B16)=0,"✖ Evaluación/paciente inconsistente",IF(OR(D16<0,E16<0,N16<0,O16<0),"✖ Valor negativo",IF(OR(AND(ISNUMBER(D16),OR(D16<CONFIG!$B$38,D16>CONFIG!$B$39)),AND(ISNUMBER(E16),OR(E16<CONFIG!$B$40,E16>CONFIG!$B$41))),"▲ Fuera de límite operativo",IF(AND(ISNUMBER(R16),OR(R16<0,R16>100)),"✖ % grasa fuera de 0–100",IF(AND(ISNUMBER(R16),U16=""),"▲ Falta fuente de % grasa",IF(E16="","▲ Estatura faltante",IF(AC16="Sí","▲ Edema registrado","✔ Correcto"))))))))
F17: =IF(AND(ISNUMBER(D17),ISNUMBER(E17),D17>0,E17>0),D17/((E17/100)^2),"") | J17: =IF(AND(ISNUMBER(D17),ISNUMBER(G17)),D17-G17,"") | K17: =IF(AND(ISNUMBER(D17),ISNUMBER(G17),G17<>0),(D17-G17)/G17,"") | S17: =IF(CONFIG!$B$28="No","",IF(AND(ISNUMBER(D17),ISNUMBER(R17),R17>=0,R17<=100,U17<>""),D17*R17/100,"")) | T17: =IF(CONFIG!$B$28="No","",IF(AND(ISNUMBER(D17),ISNUMBER(S17)),D17-S17,"")) | V17: =IF(AND(ISNUMBER(N17),ISNUMBER(E17),E17>0),N17/E17,"") | W17: =IF(AND(ISNUMBER(N17),ISNUMBER(O17),O17>0),N17/O17,"") | AJ17: =IF(A17="","",COUNTIF($B$7:B17,B17)) | AK17: =IF(A17="","",B17&"|"&AJ17) | AL17: =IF(A17="","",IF(COUNTIFS(EVALUACION!$A$7:$A$36,A17,EVALUACION!$B$7:$B$36,B17)=0,"✖ Evaluación/paciente inconsistente",IF(OR(D17<0,E17<0,N17<0,O17<0),"✖ Valor negativo",IF(OR(AND(ISNUMBER(D17),OR(D17<CONFIG!$B$38,D17>CONFIG!$B$39)),AND(ISNUMBER(E17),OR(E17<CONFIG!$B$40,E17>CONFIG!$B$41))),"▲ Fuera de límite operativo",IF(AND(ISNUMBER(R17),OR(R17<0,R17>100)),"✖ % grasa fuera de 0–100",IF(AND(ISNUMBER(R17),U17=""),"▲ Falta fuente de % grasa",IF(E17="","▲ Estatura faltante",IF(AC17="Sí","▲ Edema registrado","✔ Correcto"))))))))
F18: =IF(AND(ISNUMBER(D18),ISNUMBER(E18),D18>0,E18>0),D18/((E18/100)^2),"") | J18: =IF(AND(ISNUMBER(D18),ISNUMBER(G18)),D18-G18,"") | K18: =IF(AND(ISNUMBER(D18),ISNUMBER(G18),G18<>0),(D18-G18)/G18,"") | S18: =IF(CONFIG!$B$28="No","",IF(AND(ISNUMBER(D18),ISNUMBER(R18),R18>=0,R18<=100,U18<>""),D18*R18/100,"")) | T18: =IF(CONFIG!$B$28="No","",IF(AND(ISNUMBER(D18),ISNUMBER(S18)),D18-S18,"")) | V18: =IF(AND(ISNUMBER(N18),ISNUMBER(E18),E18>0),N18/E18,"") | W18: =IF(AND(ISNUMBER(N18),ISNUMBER(O18),O18>0),N18/O18,"") | AJ18: =IF(A18="","",COUNTIF($B$7:B18,B18)) | AK18: =IF(A18="","",B18&"|"&AJ18) | AL18: =IF(A18="","",IF(COUNTIFS(EVALUACION!$A$7:$A$36,A18,EVALUACION!$B$7:$B$36,B18)=0,"✖ Evaluación/paciente inconsistente",IF(OR(D18<0,E18<0,N18<0,O18<0),"✖ Valor negativo",IF(OR(AND(ISNUMBER(D18),OR(D18<CONFIG!$B$38,D18>CONFIG!$B$39)),AND(ISNUMBER(E18),OR(E18<CONFIG!$B$40,E18>CONFIG!$B$41))),"▲ Fuera de límite operativo",IF(AND(ISNUMBER(R18),OR(R18<0,R18>100)),"✖ % grasa fuera de 0–100",IF(AND(ISNUMBER(R18),U18=""),"▲ Falta fuente de % grasa",IF(E18="","▲ Estatura faltante",IF(AC18="Sí","▲ Edema registrado","✔ Correcto"))))))))
F19: =IF(AND(ISNUMBER(D19),ISNUMBER(E19),D19>0,E19>0),D19/((E19/100)^2),"") | J19: =IF(AND(ISNUMBER(D19),ISNUMBER(G19)),D19-G19,"") | K19: =IF(AND(ISNUMBER(D19),ISNUMBER(G19),G19<>0),(D19-G19)/G19,"") | S19: =IF(CONFIG!$B$28="No","",IF(AND(ISNUMBER(D19),ISNUMBER(R19),R19>=0,R19<=100,U19<>""),D19*R19/100,"")) | T19: =IF(CONFIG!$B$28="No","",IF(AND(ISNUMBER(D19),ISNUMBER(S19)),D19-S19,"")) | V19: =IF(AND(ISNUMBER(N19),ISNUMBER(E19),E19>0),N19/E19,"") | W19: =IF(AND(ISNUMBER(N19),ISNUMBER(O19),O19>0),N19/O19,"") | AJ19: =IF(A19="","",COUNTIF($B$7:B19,B19)) | AK19: =IF(A19="","",B19&"|"&AJ19) | AL19: =IF(A19="","",IF(COUNTIFS(EVALUACION!$A$7:$A$36,A19,EVALUACION!$B$7:$B$36,B19)=0,"✖ Evaluación/paciente inconsistente",IF(OR(D19<0,E19<0,N19<0,O19<0),"✖ Valor negativo",IF(OR(AND(ISNUMBER(D19),OR(D19<CONFIG!$B$38,D19>CONFIG!$B$39)),AND(ISNUMBER(E19),OR(E19<CONFIG!$B$40,E19>CONFIG!$B$41))),"▲ Fuera de límite operativo",IF(AND(ISNUMBER(R19),OR(R19<0,R19>100)),"✖ % grasa fuera de 0–100",IF(AND(ISNUMBER(R19),U19=""),"▲ Falta fuente de % grasa",IF(E19="","▲ Estatura faltante",IF(AC19="Sí","▲ Edema registrado","✔ Correcto"))))))))
F20: =IF(AND(ISNUMBER(D20),ISNUMBER(E20),D20>0,E20>0),D20/((E20/100)^2),"") | J20: =IF(AND(ISNUMBER(D20),ISNUMBER(G20)),D20-G20,"") | K20: =IF(AND(ISNUMBER(D20),ISNUMBER(G20),G20<>0),(D20-G20)/G20,"") | S20: =IF(CONFIG!$B$28="No","",IF(AND(ISNUMBER(D20),ISNUMBER(R20),R20>=0,R20<=100,U20<>""),D20*R20/100,"")) | T20: =IF(CONFIG!$B$28="No","",IF(AND(ISNUMBER(D20),ISNUMBER(S20)),D20-S20,"")) | V20: =IF(AND(ISNUMBER(N20),ISNUMBER(E20),E20>0),N20/E20,"") | W20: =IF(AND(ISNUMBER(N20),ISNUMBER(O20),O20>0),N20/O20,"") | AJ20: =IF(A20="","",COUNTIF($B$7:B20,B20)) | AK20: =IF(A20="","",B20&"|"&AJ20) | AL20: =IF(A20="","",IF(COUNTIFS(EVALUACION!$A$7:$A$36,A20,EVALUACION!$B$7:$B$36,B20)=0,"✖ Evaluación/paciente inconsistente",IF(OR(D20<0,E20<0,N20<0,O20<0),"✖ Valor negativo",IF(OR(AND(ISNUMBER(D20),OR(D20<CONFIG!$B$38,D20>CONFIG!$B$39)),AND(ISNUMBER(E20),OR(E20<CONFIG!$B$40,E20>CONFIG!$B$41))),"▲ Fuera de límite operativo",IF(AND(ISNUMBER(R20),OR(R20<0,R20>100)),"✖ % grasa fuera de 0–100",IF(AND(ISNUMBER(R20),U20=""),"▲ Falta fuente de % grasa",IF(E20="","▲ Estatura faltante",IF(AC20="Sí","▲ Edema registrado","✔ Correcto"))))))))
F21: =IF(AND(ISNUMBER(D21),ISNUMBER(E21),D21>0,E21>0),D21/((E21/100)^2),"") | J21: =IF(AND(ISNUMBER(D21),ISNUMBER(G21)),D21-G21,"") | K21: =IF(AND(ISNUMBER(D21),ISNUMBER(G21),G21<>0),(D21-G21)/G21,"") | S21: =IF(CONFIG!$B$28="No","",IF(AND(ISNUMBER(D21),ISNUMBER(R21),R21>=0,R21<=100,U21<>""),D21*R21/100,"")) | T21: =IF(CONFIG!$B$28="No","",IF(AND(ISNUMBER(D21),ISNUMBER(S21)),D21-S21,"")) | V21: =IF(AND(ISNUMBER(N21),ISNUMBER(E21),E21>0),N21/E21,"") | W21: =IF(AND(ISNUMBER(N21),ISNUMBER(O21),O21>0),N21/O21,"") | AJ21: =IF(A21="","",COUNTIF($B$7:B21,B21)) | AK21: =IF(A21="","",B21&"|"&AJ21) | AL21: =IF(A21="","",IF(COUNTIFS(EVALUACION!$A$7:$A$36,A21,EVALUACION!$B$7:$B$36,B21)=0,"✖ Evaluación/paciente inconsistente",IF(OR(D21<0,E21<0,N21<0,O21<0),"✖ Valor negativo",IF(OR(AND(ISNUMBER(D21),OR(D21<CONFIG!$B$38,D21>CONFIG!$B$39)),AND(ISNUMBER(E21),OR(E21<CONFIG!$B$40,E21>CONFIG!$B$41))),"▲ Fuera de límite operativo",IF(AND(ISNUMBER(R21),OR(R21<0,R21>100)),"✖ % grasa fuera de 0–100",IF(AND(ISNUMBER(R21),U21=""),"▲ Falta fuente de % grasa",IF(E21="","▲ Estatura faltante",IF(AC21="Sí","▲ Edema registrado","✔ Correcto"))))))))
F22: =IF(AND(ISNUMBER(D22),ISNUMBER(E22),D22>0,E22>0),D22/((E22/100)^2),"") | J22: =IF(AND(ISNUMBER(D22),ISNUMBER(G22)),D22-G22,"") | K22: =IF(AND(ISNUMBER(D22),ISNUMBER(G22),G22<>0),(D22-G22)/G22,"") | S22: =IF(CONFIG!$B$28="No","",IF(AND(ISNUMBER(D22),ISNUMBER(R22),R22>=0,R22<=100,U22<>""),D22*R22/100,"")) | T22: =IF(CONFIG!$B$28="No","",IF(AND(ISNUMBER(D22),ISNUMBER(S22)),D22-S22,"")) | V22: =IF(AND(ISNUMBER(N22),ISNUMBER(E22),E22>0),N22/E22,"") | W22: =IF(AND(ISNUMBER(N22),ISNUMBER(O22),O22>0),N22/O22,"") | AJ22: =IF(A22="","",COUNTIF($B$7:B22,B22)) | AK22: =IF(A22="","",B22&"|"&AJ22) | AL22: =IF(A22="","",IF(COUNTIFS(EVALUACION!$A$7:$A$36,A22,EVALUACION!$B$7:$B$36,B22)=0,"✖ Evaluación/paciente inconsistente",IF(OR(D22<0,E22<0,N22<0,O22<0),"✖ Valor negativo",IF(OR(AND(ISNUMBER(D22),OR(D22<CONFIG!$B$38,D22>CONFIG!$B$39)),AND(ISNUMBER(E22),OR(E22<CONFIG!$B$40,E22>CONFIG!$B$41))),"▲ Fuera de límite operativo",IF(AND(ISNUMBER(R22),OR(R22<0,R22>100)),"✖ % grasa fuera de 0–100",IF(AND(ISNUMBER(R22),U22=""),"▲ Falta fuente de % grasa",IF(E22="","▲ Estatura faltante",IF(AC22="Sí","▲ Edema registrado","✔ Correcto"))))))))
F23: =IF(AND(ISNUMBER(D23),ISNUMBER(E23),D23>0,E23>0),D23/((E23/100)^2),"") | J23: =IF(AND(ISNUMBER(D23),ISNUMBER(G23)),D23-G23,"") | K23: =IF(AND(ISNUMBER(D23),ISNUMBER(G23),G23<>0),(D23-G23)/G23,"") | S23: =IF(CONFIG!$B$28="No","",IF(AND(ISNUMBER(D23),ISNUMBER(R23),R23>=0,R23<=100,U23<>""),D23*R23/100,"")) | T23: =IF(CONFIG!$B$28="No","",IF(AND(ISNUMBER(D23),ISNUMBER(S23)),D23-S23,"")) | V23: =IF(AND(ISNUMBER(N23),ISNUMBER(E23),E23>0),N23/E23,"") | W23: =IF(AND(ISNUMBER(N23),ISNUMBER(O23),O23>0),N23/O23,"") | AJ23: =IF(A23="","",COUNTIF($B$7:B23,B23)) | AK23: =IF(A23="","",B23&"|"&AJ23) | AL23: =IF(A23="","",IF(COUNTIFS(EVALUACION!$A$7:$A$36,A23,EVALUACION!$B$7:$B$36,B23)=0,"✖ Evaluación/paciente inconsistente",IF(OR(D23<0,E23<0,N23<0,O23<0),"✖ Valor negativo",IF(OR(AND(ISNUMBER(D23),OR(D23<CONFIG!$B$38,D23>CONFIG!$B$39)),AND(ISNUMBER(E23),OR(E23<CONFIG!$B$40,E23>CONFIG!$B$41))),"▲ Fuera de límite operativo",IF(AND(ISNUMBER(R23),OR(R23<0,R23>100)),"✖ % grasa fuera de 0–100",IF(AND(ISNUMBER(R23),U23=""),"▲ Falta fuente de % grasa",IF(E23="","▲ Estatura faltante",IF(AC23="Sí","▲ Edema registrado","✔ Correcto"))))))))
F24: =IF(AND(ISNUMBER(D24),ISNUMBER(E24),D24>0,E24>0),D24/((E24/100)^2),"") | J24: =IF(AND(ISNUMBER(D24),ISNUMBER(G24)),D24-G24,"") | K24: =IF(AND(ISNUMBER(D24),ISNUMBER(G24),G24<>0),(D24-G24)/G24,"") | S24: =IF(CONFIG!$B$28="No","",IF(AND(ISNUMBER(D24),ISNUMBER(R24),R24>=0,R24<=100,U24<>""),D24*R24/100,"")) | T24: =IF(CONFIG!$B$28="No","",IF(AND(ISNUMBER(D24),ISNUMBER(S24)),D24-S24,"")) | V24: =IF(AND(ISNUMBER(N24),ISNUMBER(E24),E24>0),N24/E24,"") | W24: =IF(AND(ISNUMBER(N24),ISNUMBER(O24),O24>0),N24/O24,"") | AJ24: =IF(A24="","",COUNTIF($B$7:B24,B24)) | AK24: =IF(A24="","",B24&"|"&AJ24) | AL24: =IF(A24="","",IF(COUNTIFS(EVALUACION!$A$7:$A$36,A24,EVALUACION!$B$7:$B$36,B24)=0,"✖ Evaluación/paciente inconsistente",IF(OR(D24<0,E24<0,N24<0,O24<0),"✖ Valor negativo",IF(OR(AND(ISNUMBER(D24),OR(D24<CONFIG!$B$38,D24>CONFIG!$B$39)),AND(ISNUMBER(E24),OR(E24<CONFIG!$B$40,E24>CONFIG!$B$41))),"▲ Fuera de límite operativo",IF(AND(ISNUMBER(R24),OR(R24<0,R24>100)),"✖ % grasa fuera de 0–100",IF(AND(ISNUMBER(R24),U24=""),"▲ Falta fuente de % grasa",IF(E24="","▲ Estatura faltante",IF(AC24="Sí","▲ Edema registrado","✔ Correcto"))))))))
... F36: =IF(AND(ISNUMBER(D36),ISNUMBER(E36),D36>0,E36>0),D36/((E36/100)^2),"") | J36: =IF(AND(ISNUMBER(D36),ISNUMBER(G36)),D36-G36,"") | K36: =IF(AND(ISNUMBER(D36),ISNUMBER(G36),G36<>0),(D36-G36)/G36,"") | S36: =IF(CONFIG!$B$28="No","",IF(AND(ISNUMBER(D36),ISNUMBER(R36),R36>=0,R36<=100,U36<>""),D36*R36/100,"")) | T36: =IF(CONFIG!$B$28="No","",IF(AND(ISNUMBER(D36),ISNUMBER(S36)),D36-S36,"")) | V36: =IF(AND(ISNUMBER(N36),ISNUMBER(E36),E36>0),N36/E36,"") | W36: =IF(AND(ISNUMBER(N36),ISNUMBER(O36),O36>0),N36/O36,"") | AJ36: =IF(A36="","",COUNTIF($B$7:B36,B36)) | AK36: =IF(A36="","",B36&"|"&AJ36) | AL36: =IF(A36="","",IF(COUNTIFS(EVALUACION!$A$7:$A$36,A36,EVALUACION!$B$7:$B$36,B36)=0,"✖ Evaluación/paciente inconsistente",IF(OR(D36<0,E36<0,N36<0,O36<0),"✖ Valor negativo",IF(OR(AND(ISNUMBER(D36),OR(D36<CONFIG!$B$38,D36>CONFIG!$B$39)),AND(ISNUMBER(E36),OR(E36<CONFIG!$B$40,E36>CONFIG!$B$41))),"▲ Fuera de límite operativo",IF(AND(ISNUMBER(R36),OR(R36<0,R36>100)),"✖ % grasa fuera de 0–100",IF(AND(ISNUMBER(R36),U36=""),"▲ Falta fuente de % grasa",IF(E36="","▲ Estatura faltante",IF(AC36="Sí","▲ Edema registrado","✔ Correcto"))))))))

Sheet BIOQUIMICA
A1: BIOQUÍMICA · Resultados con rangos ingresados y revisión profesional
A2: ◀ INICIO | B2: RESUMEN | C2: CONFIG | D2: PRUEBAS
A3: ▲ Los rangos dependen del laboratorio, método, unidad y población. No se generan diagnósticos.
A5: T_BIOQUIMICA
A6: EvaluationID | B6: PatientID | C6: Fecha muestra | D6: Analito | E6: Resultado numérico | F6: Resultado cualitativo | G6: Unidad | H6: Límite inferior | I6: Límite superior | J6: Intervalo referencia textual | K6: Estado calculado | L6: Laboratorio | M6: Condición muestra | N6: Fuente rango | O6: Comentario profesional | P6: Estado revisión | Q6: FechaRegistro | R6: FechaModificacion | S6: Profesional | T6: FuenteDato | U6: Observaciones | V6: Rango señalado | W6: Clave señalada | X6: Control
A7: E-A-01 | B7: P-FICT-A | C7: 46170 | D7: Analito ficticio A | E7: 100 | G7: unidad | H7: 70 | I7: 110 | J7: 70–110 unidad | K7: =IF(CONFIG!$B$23="No","Módulo desactivado",IF(D7="","No evaluable",IF(AND(E7="",F7<>""),"No evaluable",IF(NOT(ISNUMBER(E7)),"No evaluable",IF(OR(H7="",I7=""),"No evaluable",IF(H7>I7,"No evaluable",IF(E7<H7,"Bajo",IF(E7>I7,"Alto","Dentro de rango")))))))) -> Dentro de rango | L7: Laboratorio ficticio | M7: Ayuno ficticio | N7: Informe ficticio | O7: Sin interpretación automática | P7: Revisado | Q7: 46174 | R7: 46216 | S7: PROF-DEMO | T7: Documentado | U7: PACIENTE FICTICIO PARA PRUEBA — NO UTILIZAR COMO REFERENCIA CLÍNICA | V7: =IF(AND(A7<>"",OR(K7="Bajo",K7="Alto",K7="No evaluable")),COUNTIFS($A$7:A7,A7,$K$7:K7,"Bajo")+COUNTIFS($A$7:A7,A7,$K$7:K7,"Alto")+COUNTIFS($A$7:A7,A7,$K$7:K7,"No evaluable"),"") | W7: =IF(V7="","",A7&"|FLAG|"&V7) | X7: =IF(A7="","",IF(CONFIG!$B$23="No","▲ Módulo desactivado",IF(COUNTIFS(EVALUACION!$A$7:$A$3006,A7,EVALUACION!$B$7:$B$3006,B7)=0,"✖ Evaluación/paciente inconsistente",IF(D7="","✖ Analito vacío",IF(AND(E7<>"",F7<>""),"▲ Resultado numérico y cualitativo simultáneos",IF(AND(E7="",F7=""),"✖ Falta resultado",IF(AND(ISNUMBER(H7),ISNUMBER(I7),H7>I7),"✖ Límite inferior mayor",IF(AND(E7<>"",G7=""),"▲ Unidad vacía","✔ Revisar clínicamente")))))))) -> ✔ Revisar clínicamente
A8: E-A-01 | B8: P-FICT-A | C8: 46170 | D8: Analito ficticio B | E8: 130 | G8: unidad | H8: 70 | I8: 110 | J8: 70–110 unidad | K8: =IF(CONFIG!$B$23="No","Módulo desactivado",IF(D8="","No evaluable",IF(AND(E8="",F8<>""),"No evaluable",IF(NOT(ISNUMBER(E8)),"No evaluable",IF(OR(H8="",I8=""),"No evaluable",IF(H8>I8,"No evaluable",IF(E8<H8,"Bajo",IF(E8>I8,"Alto","Dentro de rango")))))))) -> Alto | L8: Laboratorio ficticio | M8: Ayuno ficticio | N8: Informe ficticio | O8: Revisar contexto | P8: Revisado | Q8: 46174 | R8: 46216 | S8: PROF-DEMO | T8: Documentado | U8: PACIENTE FICTICIO PARA PRUEBA — NO UTILIZAR COMO REFERENCIA CLÍNICA | V8: =IF(AND(A8<>"",OR(K8="Bajo",K8="Alto",K8="No evaluable")),COUNTIFS($A$7:A8,A8,$K$7:K8,"Bajo")+COUNTIFS($A$7:A8,A8,$K$7:K8,"Alto")+COUNTIFS($A$7:A8,A8,$K$7:K8,"No evaluable"),"") -> 1 | W8: =IF(V8="","",A8&"|FLAG|"&V8) -> E-A-01|FLAG|1 | X8: =IF(A8="","",IF(CONFIG!$B$23="No","▲ Módulo desactivado",IF(COUNTIFS(EVALUACION!$A$7:$A$3006,A8,EVALUACION!$B$7:$B$3006,B8)=0,"✖ Evaluación/paciente inconsistente",IF(D8="","✖ Analito vacío",IF(AND(E8<>"",F8<>""),"▲ Resultado numérico y cualitativo simultáneos",IF(AND(E8="",F8=""),"✖ Falta resultado",IF(AND(ISNUMBER(H8),ISNUMBER(I8),H8>I8),"✖ Límite inferior mayor",IF(AND(E8<>"",G8=""),"▲ Unidad vacía","✔ Revisar clínicamente")))))))) -> ✔ Revisar clínicamente
A9: E-D-01 | B9: P-FICT-D | C9: 46178 | D9: Analito ficticio A | E9: 90 | G9: unidad | K9: =IF(CONFIG!$B$23="No","Módulo desactivado",IF(D9="","No evaluable",IF(AND(E9="",F9<>""),"No evaluable",IF(NOT(ISNUMBER(E9)),"No evaluable",IF(OR(H9="",I9=""),"No evaluable",IF(H9>I9,"No evaluable",IF(E9<H9,"Bajo",IF(E9>I9,"Alto","Dentro de rango")))))))) -> No evaluable | L9: Laboratorio ficticio | M9: No informado | O9: Pendiente de rango | P9: Pendiente | Q9: 46183 | R9: 46216 | S9: PROF-DEMO | T9: Documentado | U9: PACIENTE FICTICIO PARA PRUEBA — NO UTILIZAR COMO REFERENCIA CLÍNICA | V9: =IF(AND(A9<>"",OR(K9="Bajo",K9="Alto",K9="No evaluable")),COUNTIFS($A$7:A9,A9,$K$7:K9,"Bajo")+COUNTIFS($A$7:A9,A9,$K$7:K9,"Alto")+COUNTIFS($A$7:A9,A9,$K$7:K9,"No evaluable"),"") -> 1 | W9: =IF(V9="","",A9&"|FLAG|"&V9) -> E-D-01|FLAG|1 | X9: =IF(A9="","",IF(CONFIG!$B$23="No","▲ Módulo desactivado",IF(COUNTIFS(EVALUACION!$A$7:$A$3006,A9,EVALUACION!$B$7:$B$3006,B9)=0,"✖ Evaluación/paciente inconsistente",IF(D9="","✖ Analito vacío",IF(AND(E9<>"",F9<>""),"▲ Resultado numérico y cualitativo simultáneos",IF(AND(E9="",F9=""),"✖ Falta resultado",IF(AND(ISNUMBER(H9),ISNUMBER(I9),H9>I9),"✖ Límite inferior mayor",IF(AND(E9<>"",G9=""),"▲ Unidad vacía","✔ Revisar clínicamente")))))))) -> ✔ Revisar clínicamente
A10: E-D-01 | B10: P-FICT-D | C10: 46178 | D10: Analito cualitativo ficticio | F10: Positivo | G10: texto | J10: Resultado cualitativo | K10: =IF(CONFIG!$B$23="No","Módulo desactivado",IF(D10="","No evaluable",IF(AND(E10="",F10<>""),"No evaluable",IF(NOT(ISNUMBER(E10)),"No evaluable",IF(OR(H10="",I10=""),"No evaluable",IF(H10>I10,"No evaluable",IF(E10<H10,"Bajo",IF(E10>I10,"Alto","Dentro de rango")))))))) -> No evaluable | L10: Laboratorio ficticio | M10: No informado | N10: Informe ficticio | O10: No interpretar automáticamente | P10: Pendiente | Q10: 46183 | R10: 46216 | S10: PROF-DEMO | T10: Documentado | U10: PACIENTE FICTICIO PARA PRUEBA — NO UTILIZAR COMO REFERENCIA CLÍNICA | V10: =IF(AND(A10<>"",OR(K10="Bajo",K10="Alto",K10="No evaluable")),COUNTIFS($A$7:A10,A10,$K$7:K10,"Bajo")+COUNTIFS($A$7:A10,A10,$K$7:K10,"Alto")+COUNTIFS($A$7:A10,A10,$K$7:K10,"No evaluable"),"") -> 2 | W10: =IF(V10="","",A10&"|FLAG|"&V10) -> E-D-01|FLAG|2 | X10: =IF(A10="","",IF(CONFIG!$B$23="No","▲ Módulo desactivado",IF(COUNTIFS(EVALUACION!$A$7:$A$3006,A10,EVALUACION!$B$7:$B$3006,B10)=0,"✖ Evaluación/paciente inconsistente",IF(D10="","✖ Analito vacío",IF(AND(E10<>"",F10<>""),"▲ Resultado numérico y cualitativo simultáneos",IF(AND(E10="",F10=""),"✖ Falta resultado",IF(AND(ISNUMBER(H10),ISNUMBER(I10),H10>I10),"✖ Límite inferior mayor",IF(AND(E10<>"",G10=""),"▲ Unidad vacía","✔ Revisar clínicamente")))))))) -> ✔ Revisar clínicamente
K11: =IF(CONFIG!$B$23="No","Módulo desactivado",IF(D11="","No evaluable",IF(AND(E11="",F11<>""),"No evaluable",IF(NOT(ISNUMBER(E11)),"No evaluable",IF(OR(H11="",I11=""),"No evaluable",IF(H11>I11,"No evaluable",IF(E11<H11,"Bajo",IF(E11>I11,"Alto","Dentro de rango")))))))) -> No evaluable | V11: =IF(AND(A11<>"",OR(K11="Bajo",K11="Alto",K11="No evaluable")),COUNTIFS($A$7:A11,A11,$K$7:K11,"Bajo")+COUNTIFS($A$7:A11,A11,$K$7:K11,"Alto")+COUNTIFS($A$7:A11,A11,$K$7:K11,"No evaluable"),"") | W11: =IF(V11="","",A11&"|FLAG|"&V11) | X11: =IF(A11="","",IF(CONFIG!$B$23="No","▲ Módulo desactivado",IF(COUNTIFS(EVALUACION!$A$7:$A$3006,A11,EVALUACION!$B$7:$B$3006,B11)=0,"✖ Evaluación/paciente inconsistente",IF(D11="","✖ Analito vacío",IF(AND(E11<>"",F11<>""),"▲ Resultado numérico y cualitativo simultáneos",IF(AND(E11="",F11=""),"✖ Falta resultado",IF(AND(ISNUMBER(H11),ISNUMBER(I11),H11>I11),"✖ Límite inferior mayor",IF(AND(E11<>"",G11=""),"▲ Unidad vacía","✔ Revisar clínicamente"))))))))
K12: =IF(CONFIG!$B$23="No","Módulo desactivado",IF(D12="","No evaluable",IF(AND(E12="",F12<>""),"No evaluable",IF(NOT(ISNUMBER(E12)),"No evaluable",IF(OR(H12="",I12=""),"No evaluable",IF(H12>I12,"No evaluable",IF(E12<H12,"Bajo",IF(E12>I12,"Alto","Dentro de rango")))))))) -> No evaluable | V12: =IF(AND(A12<>"",OR(K12="Bajo",K12="Alto",K12="No evaluable")),COUNTIFS($A$7:A12,A12,$K$7:K12,"Bajo")+COUNTIFS($A$7:A12,A12,$K$7:K12,"Alto")+COUNTIFS($A$7:A12,A12,$K$7:K12,"No evaluable"),"") | W12: =IF(V12="","",A12&"|FLAG|"&V12) | X12: =IF(A12="","",IF(CONFIG!$B$23="No","▲ Módulo desactivado",IF(COUNTIFS(EVALUACION!$A$7:$A$3006,A12,EVALUACION!$B$7:$B$3006,B12)=0,"✖ Evaluación/paciente inconsistente",IF(D12="","✖ Analito vacío",IF(AND(E12<>"",F12<>""),"▲ Resultado numérico y cualitativo simultáneos",IF(AND(E12="",F12=""),"✖ Falta resultado",IF(AND(ISNUMBER(H12),ISNUMBER(I12),H12>I12),"✖ Límite inferior mayor",IF(AND(E12<>"",G12=""),"▲ Unidad vacía","✔ Revisar clínicamente"))))))))
K13: =IF(CONFIG!$B$23="No","Módulo desactivado",IF(D13="","No evaluable",IF(AND(E13="",F13<>""),"No evaluable",IF(NOT(ISNUMBER(E13)),"No evaluable",IF(OR(H13="",I13=""),"No evaluable",IF(H13>I13,"No evaluable",IF(E13<H13,"Bajo",IF(E13>I13,"Alto","Dentro de rango")))))))) -> No evaluable | V13: =IF(AND(A13<>"",OR(K13="Bajo",K13="Alto",K13="No evaluable")),COUNTIFS($A$7:A13,A13,$K$7:K13,"Bajo")+COUNTIFS($A$7:A13,A13,$K$7:K13,"Alto")+COUNTIFS($A$7:A13,A13,$K$7:K13,"No evaluable"),"") | W13: =IF(V13="","",A13&"|FLAG|"&V13) | X13: =IF(A13="","",IF(CONFIG!$B$23="No","▲ Módulo desactivado",IF(COUNTIFS(EVALUACION!$A$7:$A$3006,A13,EVALUACION!$B$7:$B$3006,B13)=0,"✖ Evaluación/paciente inconsistente",IF(D13="","✖ Analito vacío",IF(AND(E13<>"",F13<>""),"▲ Resultado numérico y cualitativo simultáneos",IF(AND(E13="",F13=""),"✖ Falta resultado",IF(AND(ISNUMBER(H13),ISNUMBER(I13),H13>I13),"✖ Límite inferior mayor",IF(AND(E13<>"",G13=""),"▲ Unidad vacía","✔ Revisar clínicamente"))))))))
K14: =IF(CONFIG!$B$23="No","Módulo desactivado",IF(D14="","No evaluable",IF(AND(E14="",F14<>""),"No evaluable",IF(NOT(ISNUMBER(E14)),"No evaluable",IF(OR(H14="",I14=""),"No evaluable",IF(H14>I14,"No evaluable",IF(E14<H14,"Bajo",IF(E14>I14,"Alto","Dentro de rango")))))))) -> No evaluable | V14: =IF(AND(A14<>"",OR(K14="Bajo",K14="Alto",K14="No evaluable")),COUNTIFS($A$7:A14,A14,$K$7:K14,"Bajo")+COUNTIFS($A$7:A14,A14,$K$7:K14,"Alto")+COUNTIFS($A$7:A14,A14,$K$7:K14,"No evaluable"),"") | W14: =IF(V14="","",A14&"|FLAG|"&V14) | X14: =IF(A14="","",IF(CONFIG!$B$23="No","▲ Módulo desactivado",IF(COUNTIFS(EVALUACION!$A$7:$A$3006,A14,EVALUACION!$B$7:$B$3006,B14)=0,"✖ Evaluación/paciente inconsistente",IF(D14="","✖ Analito vacío",IF(AND(E14<>"",F14<>""),"▲ Resultado numérico y cualitativo simultáneos",IF(AND(E14="",F14=""),"✖ Falta resultado",IF(AND(ISNUMBER(H14),ISNUMBER(I14),H14>I14),"✖ Límite inferior mayor",IF(AND(E14<>"",G14=""),"▲ Unidad vacía","✔ Revisar clínicamente"))))))))
K15: =IF(CONFIG!$B$23="No","Módulo desactivado",IF(D15="","No evaluable",IF(AND(E15="",F15<>""),"No evaluable",IF(NOT(ISNUMBER(E15)),"No evaluable",IF(OR(H15="",I15=""),"No evaluable",IF(H15>I15,"No evaluable",IF(E15<H15,"Bajo",IF(E15>I15,"Alto","Dentro de rango")))))))) -> No evaluable | V15: =IF(AND(A15<>"",OR(K15="Bajo",K15="Alto",K15="No evaluable")),COUNTIFS($A$7:A15,A15,$K$7:K15,"Bajo")+COUNTIFS($A$7:A15,A15,$K$7:K15,"Alto")+COUNTIFS($A$7:A15,A15,$K$7:K15,"No evaluable"),"") | W15: =IF(V15="","",A15&"|FLAG|"&V15) | X15: =IF(A15="","",IF(CONFIG!$B$23="No","▲ Módulo desactivado",IF(COUNTIFS(EVALUACION!$A$7:$A$3006,A15,EVALUACION!$B$7:$B$3006,B15)=0,"✖ Evaluación/paciente inconsistente",IF(D15="","✖ Analito vacío",IF(AND(E15<>"",F15<>""),"▲ Resultado numérico y cualitativo simultáneos",IF(AND(E15="",F15=""),"✖ Falta resultado",IF(AND(ISNUMBER(H15),ISNUMBER(I15),H15>I15),"✖ Límite inferior mayor",IF(AND(E15<>"",G15=""),"▲ Unidad vacía","✔ Revisar clínicamente"))))))))
K16: =IF(CONFIG!$B$23="No","Módulo desactivado",IF(D16="","No evaluable",IF(AND(E16="",F16<>""),"No evaluable",IF(NOT(ISNUMBER(E16)),"No evaluable",IF(OR(H16="",I16=""),"No evaluable",IF(H16>I16,"No evaluable",IF(E16<H16,"Bajo",IF(E16>I16,"Alto","Dentro de rango")))))))) -> No evaluable | V16: =IF(AND(A16<>"",OR(K16="Bajo",K16="Alto",K16="No evaluable")),COUNTIFS($A$7:A16,A16,$K$7:K16,"Bajo")+COUNTIFS($A$7:A16,A16,$K$7:K16,"Alto")+COUNTIFS($A$7:A16,A16,$K$7:K16,"No evaluable"),"") | W16: =IF(V16="","",A16&"|FLAG|"&V16) | X16: =IF(A16="","",IF(CONFIG!$B$23="No","▲ Módulo desactivado",IF(COUNTIFS(EVALUACION!$A$7:$A$36,A16,EVALUACION!$B$7:$B$36,B16)=0,"✖ Evaluación/paciente inconsistente",IF(D16="","✖ Analito vacío",IF(AND(E16<>"",F16<>""),"▲ Resultado numérico y cualitativo simultáneos",IF(AND(E16="",F16=""),"✖ Falta resultado",IF(AND(ISNUMBER(H16),ISNUMBER(I16),H16>I16),"✖ Límite inferior mayor",IF(AND(E16<>"",G16=""),"▲ Unidad vacía","✔ Revisar clínicamente"))))))))
K17: =IF(CONFIG!$B$23="No","Módulo desactivado",IF(D17="","No evaluable",IF(AND(E17="",F17<>""),"No evaluable",IF(NOT(ISNUMBER(E17)),"No evaluable",IF(OR(H17="",I17=""),"No evaluable",IF(H17>I17,"No evaluable",IF(E17<H17,"Bajo",IF(E17>I17,"Alto","Dentro de rango")))))))) -> No evaluable | V17: =IF(AND(A17<>"",OR(K17="Bajo",K17="Alto",K17="No evaluable")),COUNTIFS($A$7:A17,A17,$K$7:K17,"Bajo")+COUNTIFS($A$7:A17,A17,$K$7:K17,"Alto")+COUNTIFS($A$7:A17,A17,$K$7:K17,"No evaluable"),"") | W17: =IF(V17="","",A17&"|FLAG|"&V17) | X17: =IF(A17="","",IF(CONFIG!$B$23="No","▲ Módulo desactivado",IF(COUNTIFS(EVALUACION!$A$7:$A$36,A17,EVALUACION!$B$7:$B$36,B17)=0,"✖ Evaluación/paciente inconsistente",IF(D17="","✖ Analito vacío",IF(AND(E17<>"",F17<>""),"▲ Resultado numérico y cualitativo simultáneos",IF(AND(E17="",F17=""),"✖ Falta resultado",IF(AND(ISNUMBER(H17),ISNUMBER(I17),H17>I17),"✖ Límite inferior mayor",IF(AND(E17<>"",G17=""),"▲ Unidad vacía","✔ Revisar clínicamente"))))))))
K18: =IF(CONFIG!$B$23="No","Módulo desactivado",IF(D18="","No evaluable",IF(AND(E18="",F18<>""),"No evaluable",IF(NOT(ISNUMBER(E18)),"No evaluable",IF(OR(H18="",I18=""),"No evaluable",IF(H18>I18,"No evaluable",IF(E18<H18,"Bajo",IF(E18>I18,"Alto","Dentro de rango")))))))) -> No evaluable | V18: =IF(AND(A18<>"",OR(K18="Bajo",K18="Alto",K18="No evaluable")),COUNTIFS($A$7:A18,A18,$K$7:K18,"Bajo")+COUNTIFS($A$7:A18,A18,$K$7:K18,"Alto")+COUNTIFS($A$7:A18,A18,$K$7:K18,"No evaluable"),"") | W18: =IF(V18="","",A18&"|FLAG|"&V18) | X18: =IF(A18="","",IF(CONFIG!$B$23="No","▲ Módulo desactivado",IF(COUNTIFS(EVALUACION!$A$7:$A$36,A18,EVALUACION!$B$7:$B$36,B18)=0,"✖ Evaluación/paciente inconsistente",IF(D18="","✖ Analito vacío",IF(AND(E18<>"",F18<>""),"▲ Resultado numérico y cualitativo simultáneos",IF(AND(E18="",F18=""),"✖ Falta resultado",IF(AND(ISNUMBER(H18),ISNUMBER(I18),H18>I18),"✖ Límite inferior mayor",IF(AND(E18<>"",G18=""),"▲ Unidad vacía","✔ Revisar clínicamente"))))))))
K19: =IF(CONFIG!$B$23="No","Módulo desactivado",IF(D19="","No evaluable",IF(AND(E19="",F19<>""),"No evaluable",IF(NOT(ISNUMBER(E19)),"No evaluable",IF(OR(H19="",I19=""),"No evaluable",IF(H19>I19,"No evaluable",IF(E19<H19,"Bajo",IF(E19>I19,"Alto","Dentro de rango")))))))) -> No evaluable | V19: =IF(AND(A19<>"",OR(K19="Bajo",K19="Alto",K19="No evaluable")),COUNTIFS($A$7:A19,A19,$K$7:K19,"Bajo")+COUNTIFS($A$7:A19,A19,$K$7:K19,"Alto")+COUNTIFS($A$7:A19,A19,$K$7:K19,"No evaluable"),"") | W19: =IF(V19="","",A19&"|FLAG|"&V19) | X19: =IF(A19="","",IF(CONFIG!$B$23="No","▲ Módulo desactivado",IF(COUNTIFS(EVALUACION!$A$7:$A$36,A19,EVALUACION!$B$7:$B$36,B19)=0,"✖ Evaluación/paciente inconsistente",IF(D19="","✖ Analito vacío",IF(AND(E19<>"",F19<>""),"▲ Resultado numérico y cualitativo simultáneos",IF(AND(E19="",F19=""),"✖ Falta resultado",IF(AND(ISNUMBER(H19),ISNUMBER(I19),H19>I19),"✖ Límite inferior mayor",IF(AND(E19<>"",G19=""),"▲ Unidad vacía","✔ Revisar clínicamente"))))))))
K20: =IF(CONFIG!$B$23="No","Módulo desactivado",IF(D20="","No evaluable",IF(AND(E20="",F20<>""),"No evaluable",IF(NOT(ISNUMBER(E20)),"No evaluable",IF(OR(H20="",I20=""),"No evaluable",IF(H20>I20,"No evaluable",IF(E20<H20,"Bajo",IF(E20>I20,"Alto","Dentro de rango")))))))) -> No evaluable | V20: =IF(AND(A20<>"",OR(K20="Bajo",K20="Alto",K20="No evaluable")),COUNTIFS($A$7:A20,A20,$K$7:K20,"Bajo")+COUNTIFS($A$7:A20,A20,$K$7:K20,"Alto")+COUNTIFS($A$7:A20,A20,$K$7:K20,"No evaluable"),"") | W20: =IF(V20="","",A20&"|FLAG|"&V20) | X20: =IF(A20="","",IF(CONFIG!$B$23="No","▲ Módulo desactivado",IF(COUNTIFS(EVALUACION!$A$7:$A$36,A20,EVALUACION!$B$7:$B$36,B20)=0,"✖ Evaluación/paciente inconsistente",IF(D20="","✖ Analito vacío",IF(AND(E20<>"",F20<>""),"▲ Resultado numérico y cualitativo simultáneos",IF(AND(E20="",F20=""),"✖ Falta resultado",IF(AND(ISNUMBER(H20),ISNUMBER(I20),H20>I20),"✖ Límite inferior mayor",IF(AND(E20<>"",G20=""),"▲ Unidad vacía","✔ Revisar clínicamente"))))))))
K21: =IF(CONFIG!$B$23="No","Módulo desactivado",IF(D21="","No evaluable",IF(AND(E21="",F21<>""),"No evaluable",IF(NOT(ISNUMBER(E21)),"No evaluable",IF(OR(H21="",I21=""),"No evaluable",IF(H21>I21,"No evaluable",IF(E21<H21,"Bajo",IF(E21>I21,"Alto","Dentro de rango")))))))) -> No evaluable | V21: =IF(AND(A21<>"",OR(K21="Bajo",K21="Alto",K21="No evaluable")),COUNTIFS($A$7:A21,A21,$K$7:K21,"Bajo")+COUNTIFS($A$7:A21,A21,$K$7:K21,"Alto")+COUNTIFS($A$7:A21,A21,$K$7:K21,"No evaluable"),"") | W21: =IF(V21="","",A21&"|FLAG|"&V21) | X21: =IF(A21="","",IF(CONFIG!$B$23="No","▲ Módulo desactivado",IF(COUNTIFS(EVALUACION!$A$7:$A$36,A21,EVALUACION!$B$7:$B$36,B21)=0,"✖ Evaluación/paciente inconsistente",IF(D21="","✖ Analito vacío",IF(AND(E21<>"",F21<>""),"▲ Resultado numérico y cualitativo simultáneos",IF(AND(E21="",F21=""),"✖ Falta resultado",IF(AND(ISNUMBER(H21),ISNUMBER(I21),H21>I21),"✖ Límite inferior mayor",IF(AND(E21<>"",G21=""),"▲ Unidad vacía","✔ Revisar clínicamente"))))))))
K22: =IF(CONFIG!$B$23="No","Módulo desactivado",IF(D22="","No evaluable",IF(AND(E22="",F22<>""),"No evaluable",IF(NOT(ISNUMBER(E22)),"No evaluable",IF(OR(H22="",I22=""),"No evaluable",IF(H22>I22,"No evaluable",IF(E22<H22,"Bajo",IF(E22>I22,"Alto","Dentro de rango")))))))) -> No evaluable | V22: =IF(AND(A22<>"",OR(K22="Bajo",K22="Alto",K22="No evaluable")),COUNTIFS($A$7:A22,A22,$K$7:K22,"Bajo")+COUNTIFS($A$7:A22,A22,$K$7:K22,"Alto")+COUNTIFS($A$7:A22,A22,$K$7:K22,"No evaluable"),"") | W22: =IF(V22="","",A22&"|FLAG|"&V22) | X22: =IF(A22="","",IF(CONFIG!$B$23="No","▲ Módulo desactivado",IF(COUNTIFS(EVALUACION!$A$7:$A$36,A22,EVALUACION!$B$7:$B$36,B22)=0,"✖ Evaluación/paciente inconsistente",IF(D22="","✖ Analito vacío",IF(AND(E22<>"",F22<>""),"▲ Resultado numérico y cualitativo simultáneos",IF(AND(E22="",F22=""),"✖ Falta resultado",IF(AND(ISNUMBER(H22),ISNUMBER(I22),H22>I22),"✖ Límite inferior mayor",IF(AND(E22<>"",G22=""),"▲ Unidad vacía","✔ Revisar clínicamente"))))))))
K23: =IF(CONFIG!$B$23="No","Módulo desactivado",IF(D23="","No evaluable",IF(AND(E23="",F23<>""),"No evaluable",IF(NOT(ISNUMBER(E23)),"No evaluable",IF(OR(H23="",I23=""),"No evaluable",IF(H23>I23,"No evaluable",IF(E23<H23,"Bajo",IF(E23>I23,"Alto","Dentro de rango")))))))) -> No evaluable | V23: =IF(AND(A23<>"",OR(K23="Bajo",K23="Alto",K23="No evaluable")),COUNTIFS($A$7:A23,A23,$K$7:K23,"Bajo")+COUNTIFS($A$7:A23,A23,$K$7:K23,"Alto")+COUNTIFS($A$7:A23,A23,$K$7:K23,"No evaluable"),"") | W23: =IF(V23="","",A23&"|FLAG|"&V23) | X23: =IF(A23="","",IF(CONFIG!$B$23="No","▲ Módulo desactivado",IF(COUNTIFS(EVALUACION!$A$7:$A$36,A23,EVALUACION!$B$7:$B$36,B23)=0,"✖ Evaluación/paciente inconsistente",IF(D23="","✖ Analito vacío",IF(AND(E23<>"",F23<>""),"▲ Resultado numérico y cualitativo simultáneos",IF(AND(E23="",F23=""),"✖ Falta resultado",IF(AND(ISNUMBER(H23),ISNUMBER(I23),H23>I23),"✖ Límite inferior mayor",IF(AND(E23<>"",G23=""),"▲ Unidad vacía","✔ Revisar clínicamente"))))))))
K24: =IF(CONFIG!$B$23="No","Módulo desactivado",IF(D24="","No evaluable",IF(AND(E24="",F24<>""),"No evaluable",IF(NOT(ISNUMBER(E24)),"No evaluable",IF(OR(H24="",I24=""),"No evaluable",IF(H24>I24,"No evaluable",IF(E24<H24,"Bajo",IF(E24>I24,"Alto","Dentro de rango")))))))) -> No evaluable | V24: =IF(AND(A24<>"",OR(K24="Bajo",K24="Alto",K24="No evaluable")),COUNTIFS($A$7:A24,A24,$K$7:K24,"Bajo")+COUNTIFS($A$7:A24,A24,$K$7:K24,"Alto")+COUNTIFS($A$7:A24,A24,$K$7:K24,"No evaluable"),"") | W24: =IF(V24="","",A24&"|FLAG|"&V24) | X24: =IF(A24="","",IF(CONFIG!$B$23="No","▲ Módulo desactivado",IF(COUNTIFS(EVALUACION!$A$7:$A$36,A24,EVALUACION!$B$7:$B$36,B24)=0,"✖ Evaluación/paciente inconsistente",IF(D24="","✖ Analito vacío",IF(AND(E24<>"",F24<>""),"▲ Resultado numérico y cualitativo simultáneos",IF(AND(E24="",F24=""),"✖ Falta resultado",IF(AND(ISNUMBER(H24),ISNUMBER(I24),H24>I24),"✖ Límite inferior mayor",IF(AND(E24<>"",G24=""),"▲ Unidad vacía","✔ Revisar clínicamente"))))))))
K25: =IF(CONFIG!$B$23="No","Módulo desactivado",IF(D25="","No evaluable",IF(AND(E25="",F25<>""),"No evaluable",IF(NOT(ISNUMBER(E25)),"No evaluable",IF(OR(H25="",I25=""),"No evaluable",IF(H25>I25,"No evaluable",IF(E25<H25,"Bajo",IF(E25>I25,"Alto","Dentro de rango")))))))) -> No evaluable | V25: =IF(AND(A25<>"",OR(K25="Bajo",K25="Alto",K25="No evaluable")),COUNTIFS($A$7:A25,A25,$K$7:K25,"Bajo")+COUNTIFS($A$7:A25,A25,$K$7:K25,"Alto")+COUNTIFS($A$7:A25,A25,$K$7:K25,"No evaluable"),"") | W25: =IF(V25="","",A25&"|FLAG|"&V25) | X25: =IF(A25="","",IF(CONFIG!$B$23="No","▲ Módulo desactivado",IF(COUNTIFS(EVALUACION!$A$7:$A$36,A25,EVALUACION!$B$7:$B$36,B25)=0,"✖ Evaluación/paciente inconsistente",IF(D25="","✖ Analito vacío",IF(AND(E25<>"",F25<>""),"▲ Resultado numérico y cualitativo simultáneos",IF(AND(E25="",F25=""),"✖ Falta resultado",IF(AND(ISNUMBER(H25),ISNUMBER(I25),H25>I25),"✖ Límite inferior mayor",IF(AND(E25<>"",G25=""),"▲ Unidad vacía","✔ Revisar clínicamente"))))))))
K26: =IF(CONFIG!$B$23="No","Módulo desactivado",IF(D26="","No evaluable",IF(AND(E26="",F26<>""),"No evaluable",IF(NOT(ISNUMBER(E26)),"No evaluable",IF(OR(H26="",I26=""),"No evaluable",IF(H26>I26,"No evaluable",IF(E26<H26,"Bajo",IF(E26>I26,"Alto","Dentro de rango")))))))) -> No evaluable | V26: =IF(AND(A26<>"",OR(K26="Bajo",K26="Alto",K26="No evaluable")),COUNTIFS($A$7:A26,A26,$K$7:K26,"Bajo")+COUNTIFS($A$7:A26,A26,$K$7:K26,"Alto")+COUNTIFS($A$7:A26,A26,$K$7:K26,"No evaluable"),"") | W26: =IF(V26="","",A26&"|FLAG|"&V26) | X26: =IF(A26="","",IF(CONFIG!$B$23="No","▲ Módulo desactivado",IF(COUNTIFS(EVALUACION!$A$7:$A$36,A26,EVALUACION!$B$7:$B$36,B26)=0,"✖ Evaluación/paciente inconsistente",IF(D26="","✖ Analito vacío",IF(AND(E26<>"",F26<>""),"▲ Resultado numérico y cualitativo simultáneos",IF(AND(E26="",F26=""),"✖ Falta resultado",IF(AND(ISNUMBER(H26),ISNUMBER(I26),H26>I26),"✖ Límite inferior mayor",IF(AND(E26<>"",G26=""),"▲ Unidad vacía","✔ Revisar clínicamente"))))))))
K27: =IF(CONFIG!$B$23="No","Módulo desactivado",IF(D27="","No evaluable",IF(AND(E27="",F27<>""),"No evaluable",IF(NOT(ISNUMBER(E27)),"No evaluable",IF(OR(H27="",I27=""),"No evaluable",IF(H27>I27,"No evaluable",IF(E27<H27,"Bajo",IF(E27>I27,"Alto","Dentro de rango")))))))) -> No evaluable | V27: =IF(AND(A27<>"",OR(K27="Bajo",K27="Alto",K27="No evaluable")),COUNTIFS($A$7:A27,A27,$K$7:K27,"Bajo")+COUNTIFS($A$7:A27,A27,$K$7:K27,"Alto")+COUNTIFS($A$7:A27,A27,$K$7:K27,"No evaluable"),"") | W27: =IF(V27="","",A27&"|FLAG|"&V27) | X27: =IF(A27="","",IF(CONFIG!$B$23="No","▲ Módulo desactivado",IF(COUNTIFS(EVALUACION!$A$7:$A$36,A27,EVALUACION!$B$7:$B$36,B27)=0,"✖ Evaluación/paciente inconsistente",IF(D27="","✖ Analito vacío",IF(AND(E27<>"",F27<>""),"▲ Resultado numérico y cualitativo simultáneos",IF(AND(E27="",F27=""),"✖ Falta resultado",IF(AND(ISNUMBER(H27),ISNUMBER(I27),H27>I27),"✖ Límite inferior mayor",IF(AND(E27<>"",G27=""),"▲ Unidad vacía","✔ Revisar clínicamente"))))))))
... K56: =IF(CONFIG!$B$23="No","Módulo desactivado",IF(D56="","No evaluable",IF(AND(E56="",F56<>""),"No evaluable",IF(NOT(ISNUMBER(E56)),"No evaluable",IF(OR(H56="",I56=""),"No evaluable",IF(H56>I56,"No evaluable",IF(E56<H56,"Bajo",IF(E56>I56,"Alto","Dentro de rango")))))))) -> No evaluable | V56: =IF(AND(A56<>"",OR(K56="Bajo",K56="Alto",K56="No evaluable")),COUNTIFS($A$7:A56,A56,$K$7:K56,"Bajo")+COUNTIFS($A$7:A56,A56,$K$7:K56,"Alto")+COUNTIFS($A$7:A56,A56,$K$7:K56,"No evaluable"),"") | W56: =IF(V56="","",A56&"|FLAG|"&V56) | X56: =IF(A56="","",IF(CONFIG!$B$23="No","▲ Módulo desactivado",IF(COUNTIFS(EVALUACION!$A$7:$A$36,A56,EVALUACION!$B$7:$B$36,B56)=0,"✖ Evaluación/paciente inconsistente",IF(D56="","✖ Analito vacío",IF(AND(E56<>"",F56<>""),"▲ Resultado numérico y cualitativo simultáneos",IF(AND(E56="",F56=""),"✖ Falta resultado",IF(AND(ISNUMBER(H56),ISNUMBER(I56),H56>I56),"✖ Límite inferior mayor",IF(AND(E56<>"",G56=""),"▲ Unidad vacía","✔ Revisar clínicamente"))))))))

Sheet CLINICA
A1: CLÍNICA · Signos y síntomas sin inferencia diagnóstica automática
A2: ◀ INICIO | B2: RESUMEN | C2: CONFIG | D2: PRUEBAS
A3: PACIENTE FICTICIO PARA PRUEBA — NO UTILIZAR COMO REFERENCIA CLÍNICA · La derivación es una decisión manual.
A5: T_CLINICA
A6: EvaluationID | B6: PatientID | C6: Sistema o categoría | D6: Signo o síntoma | E6: Presencia | F6: Intensidad | G6: Frecuencia | H6: Duración | I6: Momento aparición | J6: Relación percibida con alimentos | K6: Impacto funcional | L6: FuenteDato | M6: Requiere derivación manual | N6: FechaRegistro | O6: FechaModificacion | P6: Profesional | Q6: Observaciones | R6: Control
A7: E-A-01 | B7: P-FICT-A | C7: Apetito | D7: Apetito ficticio | E7: No | F7: No evaluada | K7: Sin impacto | L7: Informado por paciente | M7: No | N7: 46174 | O7: 46216 | P7: PROF-DEMO | Q7: PACIENTE FICTICIO PARA PRUEBA — NO UTILIZAR COMO REFERENCIA CLÍNICA | R7: =IF(A7="","",IF(COUNTIFS(EVALUACION!$A$7:$A$3006,A7,EVALUACION!$B$7:$B$3006,B7)=0,"✖ Evaluación/paciente inconsistente",IF(D7="","✖ Signo o síntoma vacío",IF(COUNTIF(CATALOGOS!$R$7:$R$10,E7)=0,"✖ Presencia no permitida",IF(M7="Sí","▲ Derivación manual marcada","✔ Correcto"))))) -> ✔ Correcto
A8: E-D-01 | B8: P-FICT-D | C8: Edema | D8: Edema ficticio observado | E8: Sí | F8: Moderada | G8: Intermitente | H8: 1 semana | I8: Reciente | J8: No informada | K8: Limitación ficticia | L8: Observado | M8: Sí | N8: 46183 | O8: 46216 | P8: PROF-DEMO | Q8: PACIENTE FICTICIO PARA PRUEBA — NO UTILIZAR COMO REFERENCIA CLÍNICA | R8: =IF(A8="","",IF(COUNTIFS(EVALUACION!$A$7:$A$3006,A8,EVALUACION!$B$7:$B$3006,B8)=0,"✖ Evaluación/paciente inconsistente",IF(D8="","✖ Signo o síntoma vacío",IF(COUNTIF(CATALOGOS!$R$7:$R$10,E8)=0,"✖ Presencia no permitida",IF(M8="Sí","▲ Derivación manual marcada","✔ Correcto"))))) -> ▲ Derivación manual marcada
R9: =IF(A9="","",IF(COUNTIFS(EVALUACION!$A$7:$A$36,A9,EVALUACION!$B$7:$B$36,B9)=0,"✖ Evaluación/paciente inconsistente",IF(D9="","✖ Signo o síntoma vacío",IF(COUNTIF(CATALOGOS!$R$7:$R$10,E9)=0,"✖ Presencia no permitida",IF(M9="Sí","▲ Derivación manual marcada","✔ Correcto")))))
R10: =IF(A10="","",IF(COUNTIFS(EVALUACION!$A$7:$A$36,A10,EVALUACION!$B$7:$B$36,B10)=0,"✖ Evaluación/paciente inconsistente",IF(D10="","✖ Signo o síntoma vacío",IF(COUNTIF(CATALOGOS!$R$7:$R$10,E10)=0,"✖ Presencia no permitida",IF(M10="Sí","▲ Derivación manual marcada","✔ Correcto")))))
R11: =IF(A11="","",IF(COUNTIFS(EVALUACION!$A$7:$A$36,A11,EVALUACION!$B$7:$B$36,B11)=0,"✖ Evaluación/paciente inconsistente",IF(D11="","✖ Signo o síntoma vacío",IF(COUNTIF(CATALOGOS!$R$7:$R$10,E11)=0,"✖ Presencia no permitida",IF(M11="Sí","▲ Derivación manual marcada","✔ Correcto")))))
R12: =IF(A12="","",IF(COUNTIFS(EVALUACION!$A$7:$A$36,A12,EVALUACION!$B$7:$B$36,B12)=0,"✖ Evaluación/paciente inconsistente",IF(D12="","✖ Signo o síntoma vacío",IF(COUNTIF(CATALOGOS!$R$7:$R$10,E12)=0,"✖ Presencia no permitida",IF(M12="Sí","▲ Derivación manual marcada","✔ Correcto")))))
R13: =IF(A13="","",IF(COUNTIFS(EVALUACION!$A$7:$A$36,A13,EVALUACION!$B$7:$B$36,B13)=0,"✖ Evaluación/paciente inconsistente",IF(D13="","✖ Signo o síntoma vacío",IF(COUNTIF(CATALOGOS!$R$7:$R$10,E13)=0,"✖ Presencia no permitida",IF(M13="Sí","▲ Derivación manual marcada","✔ Correcto")))))
R14: =IF(A14="","",IF(COUNTIFS(EVALUACION!$A$7:$A$36,A14,EVALUACION!$B$7:$B$36,B14)=0,"✖ Evaluación/paciente inconsistente",IF(D14="","✖ Signo o síntoma vacío",IF(COUNTIF(CATALOGOS!$R$7:$R$10,E14)=0,"✖ Presencia no permitida",IF(M14="Sí","▲ Derivación manual marcada","✔ Correcto")))))
R15: =IF(A15="","",IF(COUNTIFS(EVALUACION!$A$7:$A$36,A15,EVALUACION!$B$7:$B$36,B15)=0,"✖ Evaluación/paciente inconsistente",IF(D15="","✖ Signo o síntoma vacío",IF(COUNTIF(CATALOGOS!$R$7:$R$10,E15)=0,"✖ Presencia no permitida",IF(M15="Sí","▲ Derivación manual marcada","✔ Correcto")))))
R16: =IF(A16="","",IF(COUNTIFS(EVALUACION!$A$7:$A$36,A16,EVALUACION!$B$7:$B$36,B16)=0,"✖ Evaluación/paciente inconsistente",IF(D16="","✖ Signo o síntoma vacío",IF(COUNTIF(CATALOGOS!$R$7:$R$10,E16)=0,"✖ Presencia no permitida",IF(M16="Sí","▲ Derivación manual marcada","✔ Correcto")))))
R17: =IF(A17="","",IF(COUNTIFS(EVALUACION!$A$7:$A$36,A17,EVALUACION!$B$7:$B$36,B17)=0,"✖ Evaluación/paciente inconsistente",IF(D17="","✖ Signo o síntoma vacío",IF(COUNTIF(CATALOGOS!$R$7:$R$10,E17)=0,"✖ Presencia no permitida",IF(M17="Sí","▲ Derivación manual marcada","✔ Correcto")))))
R18: =IF(A18="","",IF(COUNTIFS(EVALUACION!$A$7:$A$36,A18,EVALUACION!$B$7:$B$36,B18)=0,"✖ Evaluación/paciente inconsistente",IF(D18="","✖ Signo o síntoma vacío",IF(COUNTIF(CATALOGOS!$R$7:$R$10,E18)=0,"✖ Presencia no permitida",IF(M18="Sí","▲ Derivación manual marcada","✔ Correcto")))))
R19: =IF(A19="","",IF(COUNTIFS(EVALUACION!$A$7:$A$36,A19,EVALUACION!$B$7:$B$36,B19)=0,"✖ Evaluación/paciente inconsistente",IF(D19="","✖ Signo o síntoma vacío",IF(COUNTIF(CATALOGOS!$R$7:$R$10,E19)=0,"✖ Presencia no permitida",IF(M19="Sí","▲ Derivación manual marcada","✔ Correcto")))))
R20: =IF(A20="","",IF(COUNTIFS(EVALUACION!$A$7:$A$36,A20,EVALUACION!$B$7:$B$36,B20)=0,"✖ Evaluación/paciente inconsistente",IF(D20="","✖ Signo o síntoma vacío",IF(COUNTIF(CATALOGOS!$R$7:$R$10,E20)=0,"✖ Presencia no permitida",IF(M20="Sí","▲ Derivación manual marcada","✔ Correcto")))))
... R56: =IF(A56="","",IF(COUNTIFS(EVALUACION!$A$7:$A$36,A56,EVALUACION!$B$7:$B$36,B56)=0,"✖ Evaluación/paciente inconsistente",IF(D56="","✖ Signo o síntoma vacío",IF(COUNTIF(CATALOGOS!$R$7:$R$10,E56)=0,"✖ Presencia no permitida",IF(M56="Sí","▲ Derivación manual marcada","✔ Correcto")))))

Sheet ALIMENTACION
A1: ALIMENTACIÓN · Anamnesis y recordatorio manual de 24 horas
A2: ◀ INICIO | B2: RESUMEN | C2: CONFIG | D2: PRUEBAS
A3: PACIENTE FICTICIO PARA PRUEBA — NO UTILIZAR COMO REFERENCIA CLÍNICA · No contiene base alimentaria completa ni inventa composición.
A5: T_ANAMNESIS
A6: EvaluationID | B6: PatientID | C6: Categoría | D6: Pregunta o variable | E6: Respuesta | F6: Frecuencia | G6: Cantidad | H6: Unidad | I6: FuenteDato | J6: Comentario profesional | K6: FechaRegistro | L6: Profesional | M6: Control
A7: E-A-01 | B7: P-FICT-A | C7: Número de comidas | D7: Comidas habituales | E7: 4 | F7: Diaria | H7: unidad | I7: Informado por paciente | J7: Registro ficticio | K7: 46174 | L7: PROF-DEMO | M7: =IF(A7="","",IF(COUNTIFS(EVALUACION!$A$7:$A$3006,A7,EVALUACION!$B$7:$B$3006,B7)=0,"✖ Evaluación/paciente inconsistente",IF(D7="","✖ Variable vacía",IF(AND(ISNUMBER(G7),G7<0),"✖ Cantidad negativa","✔ Correcto")))) -> ✔ Correcto
A8: E-A-01 | B8: P-FICT-A | C8: Consumo de agua | D8: Agua habitual | E8: 6 | F8: Diaria | G8: 6 | H8: unidad | I8: Informado por paciente | J8: Registro ficticio | K8: 46174 | L8: PROF-DEMO | M8: =IF(A8="","",IF(COUNTIFS(EVALUACION!$A$7:$A$3006,A8,EVALUACION!$B$7:$B$3006,B8)=0,"✖ Evaluación/paciente inconsistente",IF(D8="","✖ Variable vacía",IF(AND(ISNUMBER(G8),G8<0),"✖ Cantidad negativa","✔ Correcto")))) -> ✔ Correcto
A9: E-B-01 | B9: P-FICT-B | C9: Horarios | D9: Regularidad | E9: Variable | F9: Diaria | I9: Informado por paciente | J9: Registro ficticio | K9: 46143 | L9: PROF-DEMO | M9: =IF(A9="","",IF(COUNTIFS(EVALUACION!$A$7:$A$3006,A9,EVALUACION!$B$7:$B$3006,B9)=0,"✖ Evaluación/paciente inconsistente",IF(D9="","✖ Variable vacía",IF(AND(ISNUMBER(G9),G9<0),"✖ Cantidad negativa","✔ Correcto")))) -> ✔ Correcto
A10: E-D-01 | B10: P-FICT-D | C10: Suplementos | D10: Uso declarado | E10: No informado | I10: Informado por paciente | J10: Revisar FARMACOS | K10: 46183 | L10: PROF-DEMO | M10: =IF(A10="","",IF(COUNTIFS(EVALUACION!$A$7:$A$3006,A10,EVALUACION!$B$7:$B$3006,B10)=0,"✖ Evaluación/paciente inconsistente",IF(D10="","✖ Variable vacía",IF(AND(ISNUMBER(G10),G10<0),"✖ Cantidad negativa","✔ Correcto")))) -> ✔ Correcto
M11: =IF(A11="","",IF(COUNTIFS(EVALUACION!$A$7:$A$3006,A11,EVALUACION!$B$7:$B$3006,B11)=0,"✖ Evaluación/paciente inconsistente",IF(D11="","✖ Variable vacía",IF(AND(ISNUMBER(G11),G11<0),"✖ Cantidad negativa","✔ Correcto"))))
M12: =IF(A12="","",IF(COUNTIFS(EVALUACION!$A$7:$A$3006,A12,EVALUACION!$B$7:$B$3006,B12)=0,"✖ Evaluación/paciente inconsistente",IF(D12="","✖ Variable vacía",IF(AND(ISNUMBER(G12),G12<0),"✖ Cantidad negativa","✔ Correcto"))))
M13: =IF(A13="","",IF(COUNTIFS(EVALUACION!$A$7:$A$3006,A13,EVALUACION!$B$7:$B$3006,B13)=0,"✖ Evaluación/paciente inconsistente",IF(D13="","✖ Variable vacía",IF(AND(ISNUMBER(G13),G13<0),"✖ Cantidad negativa","✔ Correcto"))))
M14: =IF(A14="","",IF(COUNTIFS(EVALUACION!$A$7:$A$3006,A14,EVALUACION!$B$7:$B$3006,B14)=0,"✖ Evaluación/paciente inconsistente",IF(D14="","✖ Variable vacía",IF(AND(ISNUMBER(G14),G14<0),"✖ Cantidad negativa","✔ Correcto"))))
M15: =IF(A15="","",IF(COUNTIFS(EVALUACION!$A$7:$A$3006,A15,EVALUACION!$B$7:$B$3006,B15)=0,"✖ Evaluación/paciente inconsistente",IF(D15="","✖ Variable vacía",IF(AND(ISNUMBER(G15),G15<0),"✖ Cantidad negativa","✔ Correcto"))))
M16: =IF(A16="","",IF(COUNTIFS(EVALUACION!$A$7:$A$3006,A16,EVALUACION!$B$7:$B$3006,B16)=0,"✖ Evaluación/paciente inconsistente",IF(D16="","✖ Variable vacía",IF(AND(ISNUMBER(G16),G16<0),"✖ Cantidad negativa","✔ Correcto"))))
M17: =IF(A17="","",IF(COUNTIFS(EVALUACION!$A$7:$A$3006,A17,EVALUACION!$B$7:$B$3006,B17)=0,"✖ Evaluación/paciente inconsistente",IF(D17="","✖ Variable vacía",IF(AND(ISNUMBER(G17),G17<0),"✖ Cantidad negativa","✔ Correcto"))))
M18: =IF(A18="","",IF(COUNTIFS(EVALUACION!$A$7:$A$3006,A18,EVALUACION!$B$7:$B$3006,B18)=0,"✖ Evaluación/paciente inconsistente",IF(D18="","✖ Variable vacía",IF(AND(ISNUMBER(G18),G18<0),"✖ Cantidad negativa","✔ Correcto"))))
M19: =IF(A19="","",IF(COUNTIFS(EVALUACION!$A$7:$A$3006,A19,EVALUACION!$B$7:$B$3006,B19)=0,"✖ Evaluación/paciente inconsistente",IF(D19="","✖ Variable vacía",IF(AND(ISNUMBER(G19),G19<0),"✖ Cantidad negativa","✔ Correcto"))))
M20: =IF(A20="","",IF(COUNTIFS(EVALUACION!$A$7:$A$3006,A20,EVALUACION!$B$7:$B$3006,B20)=0,"✖ Evaluación/paciente inconsistente",IF(D20="","✖ Variable vacía",IF(AND(ISNUMBER(G20),G20<0),"✖ Cantidad negativa","✔ Correcto"))))
M21: =IF(A21="","",IF(COUNTIFS(EVALUACION!$A$7:$A$3006,A21,EVALUACION!$B$7:$B$3006,B21)=0,"✖ Evaluación/paciente inconsistente",IF(D21="","✖ Variable vacía",IF(AND(ISNUMBER(G21),G21<0),"✖ Cantidad negativa","✔ Correcto"))))
M22: =IF(A22="","",IF(COUNTIFS(EVALUACION!$A$7:$A$3006,A22,EVALUACION!$B$7:$B$3006,B22)=0,"✖ Evaluación/paciente inconsistente",IF(D22="","✖ Variable vacía",IF(AND(ISNUMBER(G22),G22<0),"✖ Cantidad negativa","✔ Correcto"))))
... M26: =IF(A26="","",IF(COUNTIFS(EVALUACION!$A$7:$A$3006,A26,EVALUACION!$B$7:$B$3006,B26)=0,"✖ Evaluación/paciente inconsistente",IF(D26="","✖ Variable vacía",IF(AND(ISNUMBER(G26),G26<0),"✖ Cantidad negativa","✔ Correcto"))))
A110: T_R24H · ingreso manual o desde fuente autorizada
A111: EvaluationID | B111: PatientID | C111: Fecha representada | D111: Tipo de día | E111: Tiempo de comida | F111: Hora | G111: Lugar | H111: Alimento o preparación | I111: Cantidad | J111: Unidad casera | K111: Peso g opcional | L111: Energía manual kcal | M111: Proteínas manual g | N111: Carbohidratos manual g | O111: Grasas manual g | P111: Fibra manual g | Q111: Fuente composición | R111: Método estimación | S111: Observaciones | T111: Control
A112: E-A-01 | B112: P-FICT-A | C112: 46173 | D112: Habitual | E112: Desayuno | F112: 0.33333333 | G112: Hogar | H112: Preparación ficticia A | I112: 1 | J112: porción | K112: 200 | L112: 350 | M112: 18 | N112: 45 | O112: 10 | P112: 6 | Q112: Fuente ficticia autorizada | R112: Estimación manual | S112: PACIENTE FICTICIO PARA PRUEBA — NO UTILIZAR COMO REFERENCIA CLÍNICA | T112: =IF(A112="","",IF(CONFIG!$B$24="No","▲ Módulo desactivado",IF(COUNTIFS(EVALUACION!$A$7:$A$3006,A112,EVALUACION!$B$7:$B$3006,B112)=0,"✖ Evaluación/paciente inconsistente",IF(H112="","✖ Preparación vacía",IF(OR(AND(ISNUMBER(I112),I112<0),AND(ISNUMBER(K112),K112<0),AND(ISNUMBER(L112),L112<0),AND(ISNUMBER(M112),M112<0),AND(ISNUMBER(N112),N112<0),AND(ISNUMBER(O112),O112<0),AND(ISNUMBER(P112),P112<0)),"✖ Cantidad o nutriente negativo",IF(AND(L112<>"",COUNT(M112:P112)=0),"▲ Energía sin macros",IF(AND(L112="",COUNT(M112:P112)>0),"▲ Macros sin energía","✔ Correcto"))))))) -> ✔ Correcto
A113: E-A-01 | B113: P-FICT-A | C113: 46173 | D113: Habitual | E113: Almuerzo | F113: 0.54166667 | G113: Hogar | H113: Preparación ficticia B | I113: 1 | J113: porción | K113: 400 | L113: 650 | M113: 32 | N113: 75 | O113: 22 | P113: 10 | Q113: Fuente ficticia autorizada | R113: Estimación manual | S113: PACIENTE FICTICIO PARA PRUEBA — NO UTILIZAR COMO REFERENCIA CLÍNICA | T113: =IF(A113="","",IF(CONFIG!$B$24="No","▲ Módulo desactivado",IF(COUNTIFS(EVALUACION!$A$7:$A$3006,A113,EVALUACION!$B$7:$B$3006,B113)=0,"✖ Evaluación/paciente inconsistente",IF(H113="","✖ Preparación vacía",IF(OR(AND(ISNUMBER(I113),I113<0),AND(ISNUMBER(K113),K113<0),AND(ISNUMBER(L113),L113<0),AND(ISNUMBER(M113),M113<0),AND(ISNUMBER(N113),N113<0),AND(ISNUMBER(O113),O113<0),AND(ISNUMBER(P113),P113<0)),"✖ Cantidad o nutriente negativo",IF(AND(L113<>"",COUNT(M113:P113)=0),"▲ Energía sin macros",IF(AND(L113="",COUNT(M113:P113)>0),"▲ Macros sin energía","✔ Correcto"))))))) -> ✔ Correcto
A114: E-A-01 | B114: P-FICT-A | C114: 46173 | D114: Habitual | E114: Cena | F114: 0.83333333 | G114: Hogar | H114: Preparación ficticia C | I114: 1 | J114: porción | K114: 300 | L114: 500 | M114: 25 | N114: 55 | O114: 18 | P114: 8 | Q114: Fuente ficticia autorizada | R114: Estimación manual | S114: PACIENTE FICTICIO PARA PRUEBA — NO UTILIZAR COMO REFERENCIA CLÍNICA | T114: =IF(A114="","",IF(CONFIG!$B$24="No","▲ Módulo desactivado",IF(COUNTIFS(EVALUACION!$A$7:$A$3006,A114,EVALUACION!$B$7:$B$3006,B114)=0,"✖ Evaluación/paciente inconsistente",IF(H114="","✖ Preparación vacía",IF(OR(AND(ISNUMBER(I114),I114<0),AND(ISNUMBER(K114),K114<0),AND(ISNUMBER(L114),L114<0),AND(ISNUMBER(M114),M114<0),AND(ISNUMBER(N114),N114<0),AND(ISNUMBER(O114),O114<0),AND(ISNUMBER(P114),P114<0)),"✖ Cantidad o nutriente negativo",IF(AND(L114<>"",COUNT(M114:P114)=0),"▲ Energía sin macros",IF(AND(L114="",COUNT(M114:P114)>0),"▲ Macros sin energía","✔ Correcto"))))))) -> ✔ Correcto
A115: E-B-01 | B115: P-FICT-B | C115: 46142 | D115: No habitual | E115: Desayuno | F115: 0.375 | G115: Fuera de hogar | H115: Preparación ficticia D | I115: 1 | J115: porción | K115: 250 | L115: 400 | M115: 15 | N115: 50 | O115: 15 | P115: 5 | Q115: Fuente ficticia autorizada | R115: Estimación manual | S115: PACIENTE FICTICIO PARA PRUEBA — NO UTILIZAR COMO REFERENCIA CLÍNICA | T115: =IF(A115="","",IF(CONFIG!$B$24="No","▲ Módulo desactivado",IF(COUNTIFS(EVALUACION!$A$7:$A$3006,A115,EVALUACION!$B$7:$B$3006,B115)=0,"✖ Evaluación/paciente inconsistente",IF(H115="","✖ Preparación vacía",IF(OR(AND(ISNUMBER(I115),I115<0),AND(ISNUMBER(K115),K115<0),AND(ISNUMBER(L115),L115<0),AND(ISNUMBER(M115),M115<0),AND(ISNUMBER(N115),N115<0),AND(ISNUMBER(O115),O115<0),AND(ISNUMBER(P115),P115<0)),"✖ Cantidad o nutriente negativo",IF(AND(L115<>"",COUNT(M115:P115)=0),"▲ Energía sin macros",IF(AND(L115="",COUNT(M115:P115)>0),"▲ Macros sin energía","✔ Correcto"))))))) -> ✔ Correcto
A116: E-B-01 | B116: P-FICT-B | C116: 46142 | D116: No habitual | E116: Cena | F116: 0.89583333 | G116: Hogar | H116: Preparación ficticia E | I116: 1 | J116: porción | K116: 450 | L116: 800 | M116: 35 | N116: 90 | O116: 30 | P116: 7 | Q116: Fuente ficticia autorizada | R116: Estimación manual | S116: PACIENTE FICTICIO PARA PRUEBA — NO UTILIZAR COMO REFERENCIA CLÍNICA | T116: =IF(A116="","",IF(CONFIG!$B$24="No","▲ Módulo desactivado",IF(COUNTIFS(EVALUACION!$A$7:$A$3006,A116,EVALUACION!$B$7:$B$3006,B116)=0,"✖ Evaluación/paciente inconsistente",IF(H116="","✖ Preparación vacía",IF(OR(AND(ISNUMBER(I116),I116<0),AND(ISNUMBER(K116),K116<0),AND(ISNUMBER(L116),L116<0),AND(ISNUMBER(M116),M116<0),AND(ISNUMBER(N116),N116<0),AND(ISNUMBER(O116),O116<0),AND(ISNUMBER(P116),P116<0)),"✖ Cantidad o nutriente negativo",IF(AND(L116<>"",COUNT(M116:P116)=0),"▲ Energía sin macros",IF(AND(L116="",COUNT(M116:P116)>0),"▲ Macros sin energía","✔ Correcto"))))))) -> ✔ Correcto
A117: E-B-02 | B117: P-FICT-B | C117: 46203 | D117: Habitual | E117: Almuerzo | F117: 0.5625 | G117: Hogar | H117: Preparación ficticia F | I117: 1 | J117: porción | K117: 350 | L117: 600 | M117: 30 | N117: 65 | O117: 20 | P117: 9 | Q117: Fuente ficticia autorizada | R117: Estimación manual | S117: PACIENTE FICTICIO PARA PRUEBA — NO UTILIZAR COMO REFERENCIA CLÍNICA | T117: =IF(A117="","",IF(CONFIG!$B$24="No","▲ Módulo desactivado",IF(COUNTIFS(EVALUACION!$A$7:$A$3006,A117,EVALUACION!$B$7:$B$3006,B117)=0,"✖ Evaluación/paciente inconsistente",IF(H117="","✖ Preparación vacía",IF(OR(AND(ISNUMBER(I117),I117<0),AND(ISNUMBER(K117),K117<0),AND(ISNUMBER(L117),L117<0),AND(ISNUMBER(M117),M117<0),AND(ISNUMBER(N117),N117<0),AND(ISNUMBER(O117),O117<0),AND(ISNUMBER(P117),P117<0)),"✖ Cantidad o nutriente negativo",IF(AND(L117<>"",COUNT(M117:P117)=0),"▲ Energía sin macros",IF(AND(L117="",COUNT(M117:P117)>0),"▲ Macros sin energía","✔ Correcto"))))))) -> ✔ Correcto
T118: =IF(A118="","",IF(CONFIG!$B$24="No","▲ Módulo desactivado",IF(COUNTIFS(EVALUACION!$A$7:$A$36,A118,EVALUACION!$B$7:$B$36,B118)=0,"✖ Evaluación/paciente inconsistente",IF(H118="","✖ Preparación vacía",IF(OR(AND(ISNUMBER(I118),I118<0),AND(ISNUMBER(K118),K118<0),AND(ISNUMBER(L118),L118<0),AND(ISNUMBER(M118),M118<0),AND(ISNUMBER(N118),N118<0),AND(ISNUMBER(O118),O118<0),AND(ISNUMBER(P118),P118<0)),"✖ Cantidad o nutriente negativo",IF(AND(L118<>"",COUNT(M118:P118)=0),"▲ Energía sin macros",IF(AND(L118="",COUNT(M118:P118)>0),"▲ Macros sin energía","✔ Correcto")))))))
T119: =IF(A119="","",IF(CONFIG!$B$24="No","▲ Módulo desactivado",IF(COUNTIFS(EVALUACION!$A$7:$A$36,A119,EVALUACION!$B$7:$B$36,B119)=0,"✖ Evaluación/paciente inconsistente",IF(H119="","✖ Preparación vacía",IF(OR(AND(ISNUMBER(I119),I119<0),AND(ISNUMBER(K119),K119<0),AND(ISNUMBER(L119),L119<0),AND(ISNUMBER(M119),M119<0),AND(ISNUMBER(N119),N119<0),AND(ISNUMBER(O119),O119<0),AND(ISNUMBER(P119),P119<0)),"✖ Cantidad o nutriente negativo",IF(AND(L119<>"",COUNT(M119:P119)=0),"▲ Energía sin macros",IF(AND(L119="",COUNT(M119:P119)>0),"▲ Macros sin energía","✔ Correcto")))))))
T120: =IF(A120="","",IF(CONFIG!$B$24="No","▲ Módulo desactivado",IF(COUNTIFS(EVALUACION!$A$7:$A$36,A120,EVALUACION!$B$7:$B$36,B120)=0,"✖ Evaluación/paciente inconsistente",IF(H120="","✖ Preparación vacía",IF(OR(AND(ISNUMBER(I120),I120<0),AND(ISNUMBER(K120),K120<0),AND(ISNUMBER(L120),L120<0),AND(ISNUMBER(M120),M120<0),AND(ISNUMBER(N120),N120<0),AND(ISNUMBER(O120),O120<0),AND(ISNUMBER(P120),P120<0)),"✖ Cantidad o nutriente negativo",IF(AND(L120<>"",COUNT(M120:P120)=0),"▲ Energía sin macros",IF(AND(L120="",COUNT(M120:P120)>0),"▲ Macros sin energía","✔ Correcto")))))))
T121: =IF(A121="","",IF(CONFIG!$B$24="No","▲ Módulo desactivado",IF(COUNTIFS(EVALUACION!$A$7:$A$36,A121,EVALUACION!$B$7:$B$36,B121)=0,"✖ Evaluación/paciente inconsistente",IF(H121="","✖ Preparación vacía",IF(OR(AND(ISNUMBER(I121),I121<0),AND(ISNUMBER(K121),K121<0),AND(ISNUMBER(L121),L121<0),AND(ISNUMBER(M121),M121<0),AND(ISNUMBER(N121),N121<0),AND(ISNUMBER(O121),O121<0),AND(ISNUMBER(P121),P121<0)),"✖ Cantidad o nutriente negativo",IF(AND(L121<>"",COUNT(M121:P121)=0),"▲ Energía sin macros",IF(AND(L121="",COUNT(M121:P121)>0),"▲ Macros sin energía","✔ Correcto")))))))
T122: =IF(A122="","",IF(CONFIG!$B$24="No","▲ Módulo desactivado",IF(COUNTIFS(EVALUACION!$A$7:$A$36,A122,EVALUACION!$B$7:$B$36,B122)=0,"✖ Evaluación/paciente inconsistente",IF(H122="","✖ Preparación vacía",IF(OR(AND(ISNUMBER(I122),I122<0),AND(ISNUMBER(K122),K122<0),AND(ISNUMBER(L122),L122<0),AND(ISNUMBER(M122),M122<0),AND(ISNUMBER(N122),N122<0),AND(ISNUMBER(O122),O122<0),AND(ISNUMBER(P122),P122<0)),"✖ Cantidad o nutriente negativo",IF(AND(L122<>"",COUNT(M122:P122)=0),"▲ Energía sin macros",IF(AND(L122="",COUNT(M122:P122)>0),"▲ Macros sin energía","✔ Correcto")))))))
T123: =IF(A123="","",IF(CONFIG!$B$24="No","▲ Módulo desactivado",IF(COUNTIFS(EVALUACION!$A$7:$A$36,A123,EVALUACION!$B$7:$B$36,B123)=0,"✖ Evaluación/paciente inconsistente",IF(H123="","✖ Preparación vacía",IF(OR(AND(ISNUMBER(I123),I123<0),AND(ISNUMBER(K123),K123<0),AND(ISNUMBER(L123),L123<0),AND(ISNUMBER(M123),M123<0),AND(ISNUMBER(N123),N123<0),AND(ISNUMBER(O123),O123<0),AND(ISNUMBER(P123),P123<0)),"✖ Cantidad o nutriente negativo",IF(AND(L123<>"",COUNT(M123:P123)=0),"▲ Energía sin macros",IF(AND(L123="",COUNT(M123:P123)>0),"▲ Macros sin energía","✔ Correcto")))))))
T124: =IF(A124="","",IF(CONFIG!$B$24="No","▲ Módulo desactivado",IF(COUNTIFS(EVALUACION!$A$7:$A$36,A124,EVALUACION!$B$7:$B$36,B124)=0,"✖ Evaluación/paciente inconsistente",IF(H124="","✖ Preparación vacía",IF(OR(AND(ISNUMBER(I124),I124<0),AND(ISNUMBER(K124),K124<0),AND(ISNUMBER(L124),L124<0),AND(ISNUMBER(M124),M124<0),AND(ISNUMBER(N124),N124<0),AND(ISNUMBER(O124),O124<0),AND(ISNUMBER(P124),P124<0)),"✖ Cantidad o nutriente negativo",IF(AND(L124<>"",COUNT(M124:P124)=0),"▲ Energía sin macros",IF(AND(L124="",COUNT(M124:P124)>0),"▲ Macros sin energía","✔ Correcto")))))))
T125: =IF(A125="","",IF(CONFIG!$B$24="No","▲ Módulo desactivado",IF(COUNTIFS(EVALUACION!$A$7:$A$36,A125,EVALUACION!$B$7:$B$36,B125)=0,"✖ Evaluación/paciente inconsistente",IF(H125="","✖ Preparación vacía",IF(OR(AND(ISNUMBER(I125),I125<0),AND(ISNUMBER(K125),K125<0),AND(ISNUMBER(L125),L125<0),AND(ISNUMBER(M125),M125<0),AND(ISNUMBER(N125),N125<0),AND(ISNUMBER(O125),O125<0),AND(ISNUMBER(P125),P125<0)),"✖ Cantidad o nutriente negativo",IF(AND(L125<>"",COUNT(M125:P125)=0),"▲ Energía sin macros",IF(AND(L125="",COUNT(M125:P125)>0),"▲ Macros sin energía","✔ Correcto")))))))
T126: =IF(A126="","",IF(CONFIG!$B$24="No","▲ Módulo desactivado",IF(COUNTIFS(EVALUACION!$A$7:$A$36,A126,EVALUACION!$B$7:$B$36,B126)=0,"✖ Evaluación/paciente inconsistente",IF(H126="","✖ Preparación vacía",IF(OR(AND(ISNUMBER(I126),I126<0),AND(ISNUMBER(K126),K126<0),AND(ISNUMBER(L126),L126<0),AND(ISNUMBER(M126),M126<0),AND(ISNUMBER(N126),N126<0),AND(ISNUMBER(O126),O126<0),AND(ISNUMBER(P126),P126<0)),"✖ Cantidad o nutriente negativo",IF(AND(L126<>"",COUNT(M126:P126)=0),"▲ Energía sin macros",IF(AND(L126="",COUNT(M126:P126)>0),"▲ Macros sin energía","✔ Correcto")))))))
T127: =IF(A127="","",IF(CONFIG!$B$24="No","▲ Módulo desactivado",IF(COUNTIFS(EVALUACION!$A$7:$A$36,A127,EVALUACION!$B$7:$B$36,B127)=0,"✖ Evaluación/paciente inconsistente",IF(H127="","✖ Preparación vacía",IF(OR(AND(ISNUMBER(I127),I127<0),AND(ISNUMBER(K127),K127<0),AND(ISNUMBER(L127),L127<0),AND(ISNUMBER(M127),M127<0),AND(ISNUMBER(N127),N127<0),AND(ISNUMBER(O127),O127<0),AND(ISNUMBER(P127),P127<0)),"✖ Cantidad o nutriente negativo",IF(AND(L127<>"",COUNT(M127:P127)=0),"▲ Energía sin macros",IF(AND(L127="",COUNT(M127:P127)>0),"▲ Macros sin energía","✔ Correcto")))))))
T128: =IF(A128="","",IF(CONFIG!$B$24="No","▲ Módulo desactivado",IF(COUNTIFS(EVALUACION!$A$7:$A$36,A128,EVALUACION!$B$7:$B$36,B128)=0,"✖ Evaluación/paciente inconsistente",IF(H128="","✖ Preparación vacía",IF(OR(AND(ISNUMBER(I128),I128<0),AND(ISNUMBER(K128),K128<0),AND(ISNUMBER(L128),L128<0),AND(ISNUMBER(M128),M128<0),AND(ISNUMBER(N128),N128<0),AND(ISNUMBER(O128),O128<0),AND(ISNUMBER(P128),P128<0)),"✖ Cantidad o nutriente negativo",IF(AND(L128<>"",COUNT(M128:P128)=0),"▲ Energía sin macros",IF(AND(L128="",COUNT(M128:P128)>0),"▲ Macros sin energía","✔ Correcto")))))))
T129: =IF(A129="","",IF(CONFIG!$B$24="No","▲ Módulo desactivado",IF(COUNTIFS(EVALUACION!$A$7:$A$36,A129,EVALUACION!$B$7:$B$36,B129)=0,"✖ Evaluación/paciente inconsistente",IF(H129="","✖ Preparación vacía",IF(OR(AND(ISNUMBER(I129),I129<0),AND(ISNUMBER(K129),K129<0),AND(ISNUMBER(L129),L129<0),AND(ISNUMBER(M129),M129<0),AND(ISNUMBER(N129),N129<0),AND(ISNUMBER(O129),O129<0),AND(ISNUMBER(P129),P129<0)),"✖ Cantidad o nutriente negativo",IF(AND(L129<>"",COUNT(M129:P129)=0),"▲ Energía sin macros",IF(AND(L129="",COUNT(M129:P129)>0),"▲ Macros sin energía","✔ Correcto")))))))
... T171: =IF(A171="","",IF(CONFIG!$B$24="No","▲ Módulo desactivado",IF(COUNTIFS(EVALUACION!$A$7:$A$36,A171,EVALUACION!$B$7:$B$36,B171)=0,"✖ Evaluación/paciente inconsistente",IF(H171="","✖ Preparación vacía",IF(OR(AND(ISNUMBER(I171),I171<0),AND(ISNUMBER(K171),K171<0),AND(ISNUMBER(L171),L171<0),AND(ISNUMBER(M171),M171<0),AND(ISNUMBER(N171),N171<0),AND(ISNUMBER(O171),O171<0),AND(ISNUMBER(P171),P171<0)),"✖ Cantidad o nutriente negativo",IF(AND(L171<>"",COUNT(M171:P171)=0),"▲ Energía sin macros",IF(AND(L171="",COUNT(M171:P171)>0),"▲ Macros sin energía","✔ Correcto")))))))

Sheet ACTIVIDAD
A1: ACTIVIDAD · Actividad habitual, ejercicio y sedentarismo
A2: ◀ INICIO | B2: RESUMEN | C2: CONFIG | D2: PRUEBAS
A3: PACIENTE FICTICIO PARA PRUEBA — NO UTILIZAR COMO REFERENCIA CLÍNICA · No se calcula prescripción deportiva automática.
A5: T_ACTIVIDAD
A6: EvaluationID | B6: PatientID | C6: Actividad | D6: Tipo | E6: Frecuencia semanal | F6: Duración min | G6: Intensidad percibida | H6: MET opcional | I6: Fuente MET | J6: Pasos | K6: Trabajo físico | L6: Sedentarismo | M6: Tiempo sentado h | N6: Objetivo | O6: Limitaciones | P6: FechaRegistro | Q6: Observaciones | R6: Control
A7: E-A-01 | B7: P-FICT-A | C7: Caminata ficticia | D7: Actividad habitual | E7: 4 | F7: 30 | G7: Moderada | J7: 7000 | K7: Ligero | L7: Moderado | M7: 7 | N7: Mantener registro | O7: Ninguna ficticia | P7: 46174 | Q7: PACIENTE FICTICIO PARA PRUEBA — NO UTILIZAR COMO REFERENCIA CLÍNICA | R7: =IF(A7="","",IF(CONFIG!$B$25="No","▲ Módulo desactivado",IF(COUNTIFS(EVALUACION!$A$7:$A$3006,A7,EVALUACION!$B$7:$B$3006,B7)=0,"✖ Evaluación/paciente inconsistente",IF(AND(ISNUMBER(F7),F7<0),"✖ Duración negativa",IF(AND(ISNUMBER(H7),I7=""),"▲ MET sin fuente","✔ Correcto"))))) -> ✔ Correcto
A8: E-B-01 | B8: P-FICT-B | C8: Ejercicio ficticio | D8: Ejercicio estructurado | E8: 3 | F8: 45 | G8: Moderada | H8: 5 | I8: Compendium; valor ficticio solo estructura | J8: 8000 | K8: Moderado | L8: Moderado | M8: 6 | N8: Seguimiento | O8: Ninguna ficticia | P8: 46143 | Q8: PACIENTE FICTICIO PARA PRUEBA — NO UTILIZAR COMO REFERENCIA CLÍNICA | R8: =IF(A8="","",IF(CONFIG!$B$25="No","▲ Módulo desactivado",IF(COUNTIFS(EVALUACION!$A$7:$A$3006,A8,EVALUACION!$B$7:$B$3006,B8)=0,"✖ Evaluación/paciente inconsistente",IF(AND(ISNUMBER(F8),F8<0),"✖ Duración negativa",IF(AND(ISNUMBER(H8),I8=""),"▲ MET sin fuente","✔ Correcto"))))) -> ✔ Correcto
R9: =IF(A9="","",IF(CONFIG!$B$25="No","▲ Módulo desactivado",IF(COUNTIFS(EVALUACION!$A$7:$A$36,A9,EVALUACION!$B$7:$B$36,B9)=0,"✖ Evaluación/paciente inconsistente",IF(AND(ISNUMBER(F9),F9<0),"✖ Duración negativa",IF(AND(ISNUMBER(H9),I9=""),"▲ MET sin fuente","✔ Correcto")))))
R10: =IF(A10="","",IF(CONFIG!$B$25="No","▲ Módulo desactivado",IF(COUNTIFS(EVALUACION!$A$7:$A$36,A10,EVALUACION!$B$7:$B$36,B10)=0,"✖ Evaluación/paciente inconsistente",IF(AND(ISNUMBER(F10),F10<0),"✖ Duración negativa",IF(AND(ISNUMBER(H10),I10=""),"▲ MET sin fuente","✔ Correcto")))))
R11: =IF(A11="","",IF(CONFIG!$B$25="No","▲ Módulo desactivado",IF(COUNTIFS(EVALUACION!$A$7:$A$36,A11,EVALUACION!$B$7:$B$36,B11)=0,"✖ Evaluación/paciente inconsistente",IF(AND(ISNUMBER(F11),F11<0),"✖ Duración negativa",IF(AND(ISNUMBER(H11),I11=""),"▲ MET sin fuente","✔ Correcto")))))
R12: =IF(A12="","",IF(CONFIG!$B$25="No","▲ Módulo desactivado",IF(COUNTIFS(EVALUACION!$A$7:$A$36,A12,EVALUACION!$B$7:$B$36,B12)=0,"✖ Evaluación/paciente inconsistente",IF(AND(ISNUMBER(F12),F12<0),"✖ Duración negativa",IF(AND(ISNUMBER(H12),I12=""),"▲ MET sin fuente","✔ Correcto")))))
R13: =IF(A13="","",IF(CONFIG!$B$25="No","▲ Módulo desactivado",IF(COUNTIFS(EVALUACION!$A$7:$A$36,A13,EVALUACION!$B$7:$B$36,B13)=0,"✖ Evaluación/paciente inconsistente",IF(AND(ISNUMBER(F13),F13<0),"✖ Duración negativa",IF(AND(ISNUMBER(H13),I13=""),"▲ MET sin fuente","✔ Correcto")))))
R14: =IF(A14="","",IF(CONFIG!$B$25="No","▲ Módulo desactivado",IF(COUNTIFS(EVALUACION!$A$7:$A$36,A14,EVALUACION!$B$7:$B$36,B14)=0,"✖ Evaluación/paciente inconsistente",IF(AND(ISNUMBER(F14),F14<0),"✖ Duración negativa",IF(AND(ISNUMBER(H14),I14=""),"▲ MET sin fuente","✔ Correcto")))))
R15: =IF(A15="","",IF(CONFIG!$B$25="No","▲ Módulo desactivado",IF(COUNTIFS(EVALUACION!$A$7:$A$36,A15,EVALUACION!$B$7:$B$36,B15)=0,"✖ Evaluación/paciente inconsistente",IF(AND(ISNUMBER(F15),F15<0),"✖ Duración negativa",IF(AND(ISNUMBER(H15),I15=""),"▲ MET sin fuente","✔ Correcto")))))
R16: =IF(A16="","",IF(CONFIG!$B$25="No","▲ Módulo desactivado",IF(COUNTIFS(EVALUACION!$A$7:$A$36,A16,EVALUACION!$B$7:$B$36,B16)=0,"✖ Evaluación/paciente inconsistente",IF(AND(ISNUMBER(F16),F16<0),"✖ Duración negativa",IF(AND(ISNUMBER(H16),I16=""),"▲ MET sin fuente","✔ Correcto")))))
R17: =IF(A17="","",IF(CONFIG!$B$25="No","▲ Módulo desactivado",IF(COUNTIFS(EVALUACION!$A$7:$A$36,A17,EVALUACION!$B$7:$B$36,B17)=0,"✖ Evaluación/paciente inconsistente",IF(AND(ISNUMBER(F17),F17<0),"✖ Duración negativa",IF(AND(ISNUMBER(H17),I17=""),"▲ MET sin fuente","✔ Correcto")))))
R18: =IF(A18="","",IF(CONFIG!$B$25="No","▲ Módulo desactivado",IF(COUNTIFS(EVALUACION!$A$7:$A$36,A18,EVALUACION!$B$7:$B$36,B18)=0,"✖ Evaluación/paciente inconsistente",IF(AND(ISNUMBER(F18),F18<0),"✖ Duración negativa",IF(AND(ISNUMBER(H18),I18=""),"▲ MET sin fuente","✔ Correcto")))))
R19: =IF(A19="","",IF(CONFIG!$B$25="No","▲ Módulo desactivado",IF(COUNTIFS(EVALUACION!$A$7:$A$36,A19,EVALUACION!$B$7:$B$36,B19)=0,"✖ Evaluación/paciente inconsistente",IF(AND(ISNUMBER(F19),F19<0),"✖ Duración negativa",IF(AND(ISNUMBER(H19),I19=""),"▲ MET sin fuente","✔ Correcto")))))
R20: =IF(A20="","",IF(CONFIG!$B$25="No","▲ Módulo desactivado",IF(COUNTIFS(EVALUACION!$A$7:$A$36,A20,EVALUACION!$B$7:$B$36,B20)=0,"✖ Evaluación/paciente inconsistente",IF(AND(ISNUMBER(F20),F20<0),"✖ Duración negativa",IF(AND(ISNUMBER(H20),I20=""),"▲ MET sin fuente","✔ Correcto")))))
... R36: =IF(A36="","",IF(CONFIG!$B$25="No","▲ Módulo desactivado",IF(COUNTIFS(EVALUACION!$A$7:$A$36,A36,EVALUACION!$B$7:$B$36,B36)=0,"✖ Evaluación/paciente inconsistente",IF(AND(ISNUMBER(F36),F36<0),"✖ Duración negativa",IF(AND(ISNUMBER(H36),I36=""),"▲ MET sin fuente","✔ Correcto")))))

Sheet FARMACOS
A1: FÁRMACOS Y SUPLEMENTOS · Registros separados y revisión manual
A2: ◀ INICIO | B2: RESUMEN | C2: CONFIG | D2: PRUEBAS
A3: ▲ No suspender, indicar ni modificar dosis. Interacciones potenciales requieren fuente.
A5: T_FARMACOS
A6: EvaluationID | B6: PatientID | C6: Nombre | D6: Principio activo opcional | E6: Dosis | F6: Unidad | G6: Frecuencia | H6: Horario | I6: Vía | J6: Motivo de uso | K6: Fecha inicio | L6: Fecha término | M6: Prescriptor | N6: Adherencia percibida | O6: Interacción potencial para revisar | P6: Fuente interacción | Q6: Observaciones | R6: Control
A7: E-A-01 | B7: P-FICT-A | C7: Medicamento ficticio A | D7: Principio ficticio | E7: 1 | F7: unidad | G7: Diaria | H7: 08:00 | I7: Oral | J7: Motivo informado | K7: 46023 | M7: Prescriptor ficticio | N7: Declarada | Q7: PACIENTE FICTICIO PARA PRUEBA — NO UTILIZAR COMO REFERENCIA CLÍNICA | R7: =IF(A7="","",IF(CONFIG!$B$26="No","▲ Módulo desactivado",IF(COUNTIFS(EVALUACION!$A$7:$A$3006,A7,EVALUACION!$B$7:$B$3006,B7)=0,"✖ Evaluación/paciente inconsistente",IF(C7="","✖ Medicamento sin nombre",IF(E7="","▲ Medicamento sin dosis",IF(AND(ISNUMBER(K7),ISNUMBER(L7),L7<K7),"✖ Fecha término anterior",IF(AND(O7<>"",P7=""),"▲ Interacción sin fuente","✔ Correcto"))))))) -> ✔ Correcto
A8: E-D-01 | B8: P-FICT-D | C8: Medicamento ficticio D | F8: unidad | G8: Diaria | H8: 09:00 | I8: Oral | J8: Motivo informado | K8: 46174 | M8: Prescriptor ficticio | N8: No evaluada | O8: Pendiente de revisión | Q8: PACIENTE FICTICIO PARA PRUEBA — NO UTILIZAR COMO REFERENCIA CLÍNICA | R8: =IF(A8="","",IF(CONFIG!$B$26="No","▲ Módulo desactivado",IF(COUNTIFS(EVALUACION!$A$7:$A$3006,A8,EVALUACION!$B$7:$B$3006,B8)=0,"✖ Evaluación/paciente inconsistente",IF(C8="","✖ Medicamento sin nombre",IF(E8="","▲ Medicamento sin dosis",IF(AND(ISNUMBER(K8),ISNUMBER(L8),L8<K8),"✖ Fecha término anterior",IF(AND(O8<>"",P8=""),"▲ Interacción sin fuente","✔ Correcto"))))))) -> ▲ Medicamento sin dosis
R9: =IF(A9="","",IF(CONFIG!$B$26="No","▲ Módulo desactivado",IF(COUNTIFS(EVALUACION!$A$7:$A$3006,A9,EVALUACION!$B$7:$B$3006,B9)=0,"✖ Evaluación/paciente inconsistente",IF(C9="","✖ Medicamento sin nombre",IF(E9="","▲ Medicamento sin dosis",IF(AND(ISNUMBER(K9),ISNUMBER(L9),L9<K9),"✖ Fecha término anterior",IF(AND(O9<>"",P9=""),"▲ Interacción sin fuente","✔ Correcto")))))))
R10: =IF(A10="","",IF(CONFIG!$B$26="No","▲ Módulo desactivado",IF(COUNTIFS(EVALUACION!$A$7:$A$3006,A10,EVALUACION!$B$7:$B$3006,B10)=0,"✖ Evaluación/paciente inconsistente",IF(C10="","✖ Medicamento sin nombre",IF(E10="","▲ Medicamento sin dosis",IF(AND(ISNUMBER(K10),ISNUMBER(L10),L10<K10),"✖ Fecha término anterior",IF(AND(O10<>"",P10=""),"▲ Interacción sin fuente","✔ Correcto")))))))
R11: =IF(A11="","",IF(CONFIG!$B$26="No","▲ Módulo desactivado",IF(COUNTIFS(EVALUACION!$A$7:$A$3006,A11,EVALUACION!$B$7:$B$3006,B11)=0,"✖ Evaluación/paciente inconsistente",IF(C11="","✖ Medicamento sin nombre",IF(E11="","▲ Medicamento sin dosis",IF(AND(ISNUMBER(K11),ISNUMBER(L11),L11<K11),"✖ Fecha término anterior",IF(AND(O11<>"",P11=""),"▲ Interacción sin fuente","✔ Correcto")))))))
R12: =IF(A12="","",IF(CONFIG!$B$26="No","▲ Módulo desactivado",IF(COUNTIFS(EVALUACION!$A$7:$A$3006,A12,EVALUACION!$B$7:$B$3006,B12)=0,"✖ Evaluación/paciente inconsistente",IF(C12="","✖ Medicamento sin nombre",IF(E12="","▲ Medicamento sin dosis",IF(AND(ISNUMBER(K12),ISNUMBER(L12),L12<K12),"✖ Fecha término anterior",IF(AND(O12<>"",P12=""),"▲ Interacción sin fuente","✔ Correcto")))))))
R13: =IF(A13="","",IF(CONFIG!$B$26="No","▲ Módulo desactivado",IF(COUNTIFS(EVALUACION!$A$7:$A$3006,A13,EVALUACION!$B$7:$B$3006,B13)=0,"✖ Evaluación/paciente inconsistente",IF(C13="","✖ Medicamento sin nombre",IF(E13="","▲ Medicamento sin dosis",IF(AND(ISNUMBER(K13),ISNUMBER(L13),L13<K13),"✖ Fecha término anterior",IF(AND(O13<>"",P13=""),"▲ Interacción sin fuente","✔ Correcto")))))))
R14: =IF(A14="","",IF(CONFIG!$B$26="No","▲ Módulo desactivado",IF(COUNTIFS(EVALUACION!$A$7:$A$3006,A14,EVALUACION!$B$7:$B$3006,B14)=0,"✖ Evaluación/paciente inconsistente",IF(C14="","✖ Medicamento sin nombre",IF(E14="","▲ Medicamento sin dosis",IF(AND(ISNUMBER(K14),ISNUMBER(L14),L14<K14),"✖ Fecha término anterior",IF(AND(O14<>"",P14=""),"▲ Interacción sin fuente","✔ Correcto")))))))
R15: =IF(A15="","",IF(CONFIG!$B$26="No","▲ Módulo desactivado",IF(COUNTIFS(EVALUACION!$A$7:$A$3006,A15,EVALUACION!$B$7:$B$3006,B15)=0,"✖ Evaluación/paciente inconsistente",IF(C15="","✖ Medicamento sin nombre",IF(E15="","▲ Medicamento sin dosis",IF(AND(ISNUMBER(K15),ISNUMBER(L15),L15<K15),"✖ Fecha término anterior",IF(AND(O15<>"",P15=""),"▲ Interacción sin fuente","✔ Correcto")))))))
R16: =IF(A16="","",IF(CONFIG!$B$26="No","▲ Módulo desactivado",IF(COUNTIFS(EVALUACION!$A$7:$A$3006,A16,EVALUACION!$B$7:$B$3006,B16)=0,"✖ Evaluación/paciente inconsistente",IF(C16="","✖ Medicamento sin nombre",IF(E16="","▲ Medicamento sin dosis",IF(AND(ISNUMBER(K16),ISNUMBER(L16),L16<K16),"✖ Fecha término anterior",IF(AND(O16<>"",P16=""),"▲ Interacción sin fuente","✔ Correcto")))))))
R17: =IF(A17="","",IF(CONFIG!$B$26="No","▲ Módulo desactivado",IF(COUNTIFS(EVALUACION!$A$7:$A$3006,A17,EVALUACION!$B$7:$B$3006,B17)=0,"✖ Evaluación/paciente inconsistente",IF(C17="","✖ Medicamento sin nombre",IF(E17="","▲ Medicamento sin dosis",IF(AND(ISNUMBER(K17),ISNUMBER(L17),L17<K17),"✖ Fecha término anterior",IF(AND(O17<>"",P17=""),"▲ Interacción sin fuente","✔ Correcto")))))))
R18: =IF(A18="","",IF(CONFIG!$B$26="No","▲ Módulo desactivado",IF(COUNTIFS(EVALUACION!$A$7:$A$3006,A18,EVALUACION!$B$7:$B$3006,B18)=0,"✖ Evaluación/paciente inconsistente",IF(C18="","✖ Medicamento sin nombre",IF(E18="","▲ Medicamento sin dosis",IF(AND(ISNUMBER(K18),ISNUMBER(L18),L18<K18),"✖ Fecha término anterior",IF(AND(O18<>"",P18=""),"▲ Interacción sin fuente","✔ Correcto")))))))
R19: =IF(A19="","",IF(CONFIG!$B$26="No","▲ Módulo desactivado",IF(COUNTIFS(EVALUACION!$A$7:$A$3006,A19,EVALUACION!$B$7:$B$3006,B19)=0,"✖ Evaluación/paciente inconsistente",IF(C19="","✖ Medicamento sin nombre",IF(E19="","▲ Medicamento sin dosis",IF(AND(ISNUMBER(K19),ISNUMBER(L19),L19<K19),"✖ Fecha término anterior",IF(AND(O19<>"",P19=""),"▲ Interacción sin fuente","✔ Correcto")))))))
R20: =IF(A20="","",IF(CONFIG!$B$26="No","▲ Módulo desactivado",IF(COUNTIFS(EVALUACION!$A$7:$A$3006,A20,EVALUACION!$B$7:$B$3006,B20)=0,"✖ Evaluación/paciente inconsistente",IF(C20="","✖ Medicamento sin nombre",IF(E20="","▲ Medicamento sin dosis",IF(AND(ISNUMBER(K20),ISNUMBER(L20),L20<K20),"✖ Fecha término anterior",IF(AND(O20<>"",P20=""),"▲ Interacción sin fuente","✔ Correcto")))))))
... R31: =IF(A31="","",IF(CONFIG!$B$26="No","▲ Módulo desactivado",IF(COUNTIFS(EVALUACION!$A$7:$A$3006,A31,EVALUACION!$B$7:$B$3006,B31)=0,"✖ Evaluación/paciente inconsistente",IF(C31="","✖ Medicamento sin nombre",IF(E31="","▲ Medicamento sin dosis",IF(AND(ISNUMBER(K31),ISNUMBER(L31),L31<K31),"✖ Fecha término anterior",IF(AND(O31<>"",P31=""),"▲ Interacción sin fuente","✔ Correcto")))))))
R32: =IF(A32="","",IF(CONFIG!$B$26="No","▲ Módulo desactivado",IF(COUNTIFS(EVALUACION!$A$7:$A$36,A32,EVALUACION!$B$7:$B$36,B32)=0,"✖ Evaluación/paciente inconsistente",IF(C32="","✖ Medicamento sin nombre",IF(E32="","▲ Medicamento sin dosis",IF(AND(ISNUMBER(K32),ISNUMBER(L32),L32<K32),"✖ Fecha término anterior",IF(AND(O32<>"",P32=""),"▲ Interacción sin fuente","✔ Correcto")))))))
R33: =IF(A33="","",IF(CONFIG!$B$26="No","▲ Módulo desactivado",IF(COUNTIFS(EVALUACION!$A$7:$A$36,A33,EVALUACION!$B$7:$B$36,B33)=0,"✖ Evaluación/paciente inconsistente",IF(C33="","✖ Medicamento sin nombre",IF(E33="","▲ Medicamento sin dosis",IF(AND(ISNUMBER(K33),ISNUMBER(L33),L33<K33),"✖ Fecha término anterior",IF(AND(O33<>"",P33=""),"▲ Interacción sin fuente","✔ Correcto")))))))
R34: =IF(A34="","",IF(CONFIG!$B$26="No","▲ Módulo desactivado",IF(COUNTIFS(EVALUACION!$A$7:$A$36,A34,EVALUACION!$B$7:$B$36,B34)=0,"✖ Evaluación/paciente inconsistente",IF(C34="","✖ Medicamento sin nombre",IF(E34="","▲ Medicamento sin dosis",IF(AND(ISNUMBER(K34),ISNUMBER(L34),L34<K34),"✖ Fecha término anterior",IF(AND(O34<>"",P34=""),"▲ Interacción sin fuente","✔ Correcto")))))))
R35: =IF(A35="","",IF(CONFIG!$B$26="No","▲ Módulo desactivado",IF(COUNTIFS(EVALUACION!$A$7:$A$36,A35,EVALUACION!$B$7:$B$36,B35)=0,"✖ Evaluación/paciente inconsistente",IF(C35="","✖ Medicamento sin nombre",IF(E35="","▲ Medicamento sin dosis",IF(AND(ISNUMBER(K35),ISNUMBER(L35),L35<K35),"✖ Fecha término anterior",IF(AND(O35<>"",P35=""),"▲ Interacción sin fuente","✔ Correcto")))))))
R36: =IF(A36="","",IF(CONFIG!$B$26="No","▲ Módulo desactivado",IF(COUNTIFS(EVALUACION!$A$7:$A$36,A36,EVALUACION!$B$7:$B$36,B36)=0,"✖ Evaluación/paciente inconsistente",IF(C36="","✖ Medicamento sin nombre",IF(E36="","▲ Medicamento sin dosis",IF(AND(ISNUMBER(K36),ISNUMBER(L36),L36<K36),"✖ Fecha término anterior",IF(AND(O36<>"",P36=""),"▲ Interacción sin fuente","✔ Correcto")))))))
A310: T_SUPLEMENTOS
A311: EvaluationID | B311: PatientID | C311: Producto | D311: Ingrediente | E311: Dosis | F311: Unidad | G311: Frecuencia | H311: Marca opcional | I311: Motivo | J311: Fuente recomendación | K311: Fecha inicio | L311: Fecha término | M311: Interacción potencial para revisar | N311: Fuente interacción | O311: Observaciones | P311: Estado revisión | Q311: Profesional | R311: Control
A312: E-A-01 | B312: P-FICT-A | C312: Suplemento ficticio A | D312: Ingrediente ficticio | E312: 1 | F312: unidad | G312: Diaria | I312: Motivo informado | J312: No informado | K312: 46054 | O312: PACIENTE FICTICIO PARA PRUEBA — NO UTILIZAR COMO REFERENCIA CLÍNICA | P312: Pendiente | Q312: PROF-DEMO | R312: =IF(A312="","",IF(CONFIG!$B$27="No","▲ Módulo desactivado",IF(COUNTIFS(EVALUACION!$A$7:$A$36,A312,EVALUACION!$B$7:$B$36,B312)=0,"✖ Evaluación/paciente inconsistente",IF(C312="","✖ Suplemento sin producto",IF(E312="","▲ Suplemento sin dosis",IF(AND(ISNUMBER(K312),ISNUMBER(L312),L312<K312),"✖ Fecha término anterior",IF(AND(M312<>"",N312=""),"▲ Interacción sin fuente","✔ Correcto"))))))) -> ✔ Correcto
R313: =IF(A313="","",IF(CONFIG!$B$27="No","▲ Módulo desactivado",IF(COUNTIFS(EVALUACION!$A$7:$A$36,A313,EVALUACION!$B$7:$B$36,B313)=0,"✖ Evaluación/paciente inconsistente",IF(C313="","✖ Suplemento sin producto",IF(E313="","▲ Suplemento sin dosis",IF(AND(ISNUMBER(K313),ISNUMBER(L313),L313<K313),"✖ Fecha término anterior",IF(AND(M313<>"",N313=""),"▲ Interacción sin fuente","✔ Correcto")))))))
R314: =IF(A314="","",IF(CONFIG!$B$27="No","▲ Módulo desactivado",IF(COUNTIFS(EVALUACION!$A$7:$A$36,A314,EVALUACION!$B$7:$B$36,B314)=0,"✖ Evaluación/paciente inconsistente",IF(C314="","✖ Suplemento sin producto",IF(E314="","▲ Suplemento sin dosis",IF(AND(ISNUMBER(K314),ISNUMBER(L314),L314<K314),"✖ Fecha término anterior",IF(AND(M314<>"",N314=""),"▲ Interacción sin fuente","✔ Correcto")))))))
R315: =IF(A315="","",IF(CONFIG!$B$27="No","▲ Módulo desactivado",IF(COUNTIFS(EVALUACION!$A$7:$A$36,A315,EVALUACION!$B$7:$B$36,B315)=0,"✖ Evaluación/paciente inconsistente",IF(C315="","✖ Suplemento sin producto",IF(E315="","▲ Suplemento sin dosis",IF(AND(ISNUMBER(K315),ISNUMBER(L315),L315<K315),"✖ Fecha término anterior",IF(AND(M315<>"",N315=""),"▲ Interacción sin fuente","✔ Correcto")))))))
R316: =IF(A316="","",IF(CONFIG!$B$27="No","▲ Módulo desactivado",IF(COUNTIFS(EVALUACION!$A$7:$A$36,A316,EVALUACION!$B$7:$B$36,B316)=0,"✖ Evaluación/paciente inconsistente",IF(C316="","✖ Suplemento sin producto",IF(E316="","▲ Suplemento sin dosis",IF(AND(ISNUMBER(K316),ISNUMBER(L316),L316<K316),"✖ Fecha término anterior",IF(AND(M316<>"",N316=""),"▲ Interacción sin fuente","✔ Correcto")))))))
R317: =IF(A317="","",IF(CONFIG!$B$27="No","▲ Módulo desactivado",IF(COUNTIFS(EVALUACION!$A$7:$A$36,A317,EVALUACION!$B$7:$B$36,B317)=0,"✖ Evaluación/paciente inconsistente",IF(C317="","✖ Suplemento sin producto",IF(E317="","▲ Suplemento sin dosis",IF(AND(ISNUMBER(K317),ISNUMBER(L317),L317<K317),"✖ Fecha término anterior",IF(AND(M317<>"",N317=""),"▲ Interacción sin fuente","✔ Correcto")))))))
R318: =IF(A318="","",IF(CONFIG!$B$27="No","▲ Módulo desactivado",IF(COUNTIFS(EVALUACION!$A$7:$A$36,A318,EVALUACION!$B$7:$B$36,B318)=0,"✖ Evaluación/paciente inconsistente",IF(C318="","✖ Suplemento sin producto",IF(E318="","▲ Suplemento sin dosis",IF(AND(ISNUMBER(K318),ISNUMBER(L318),L318<K318),"✖ Fecha término anterior",IF(AND(M318<>"",N318=""),"▲ Interacción sin fuente","✔ Correcto")))))))
R319: =IF(A319="","",IF(CONFIG!$B$27="No","▲ Módulo desactivado",IF(COUNTIFS(EVALUACION!$A$7:$A$36,A319,EVALUACION!$B$7:$B$36,B319)=0,"✖ Evaluación/paciente inconsistente",IF(C319="","✖ Suplemento sin producto",IF(E319="","▲ Suplemento sin dosis",IF(AND(ISNUMBER(K319),ISNUMBER(L319),L319<K319),"✖ Fecha término anterior",IF(AND(M319<>"",N319=""),"▲ Interacción sin fuente","✔ Correcto")))))))
R320: =IF(A320="","",IF(CONFIG!$B$27="No","▲ Módulo desactivado",IF(COUNTIFS(EVALUACION!$A$7:$A$36,A320,EVALUACION!$B$7:$B$36,B320)=0,"✖ Evaluación/paciente inconsistente",IF(C320="","✖ Suplemento sin producto",IF(E320="","▲ Suplemento sin dosis",IF(AND(ISNUMBER(K320),ISNUMBER(L320),L320<K320),"✖ Fecha término anterior",IF(AND(M320<>"",N320=""),"▲ Interacción sin fuente","✔ Correcto")))))))
R321: =IF(A321="","",IF(CONFIG!$B$27="No","▲ Módulo desactivado",IF(COUNTIFS(EVALUACION!$A$7:$A$36,A321,EVALUACION!$B$7:$B$36,B321)=0,"✖ Evaluación/paciente inconsistente",IF(C321="","✖ Suplemento sin producto",IF(E321="","▲ Suplemento sin dosis",IF(AND(ISNUMBER(K321),ISNUMBER(L321),L321<K321),"✖ Fecha término anterior",IF(AND(M321<>"",N321=""),"▲ Interacción sin fuente","✔ Correcto")))))))
R322: =IF(A322="","",IF(CONFIG!$B$27="No","▲ Módulo desactivado",IF(COUNTIFS(EVALUACION!$A$7:$A$36,A322,EVALUACION!$B$7:$B$36,B322)=0,"✖ Evaluación/paciente inconsistente",IF(C322="","✖ Suplemento sin producto",IF(E322="","▲ Suplemento sin dosis",IF(AND(ISNUMBER(K322),ISNUMBER(L322),L322<K322),"✖ Fecha término anterior",IF(AND(M322<>"",N322=""),"▲ Interacción sin fuente","✔ Correcto")))))))
R323: =IF(A323="","",IF(CONFIG!$B$27="No","▲ Módulo desactivado",IF(COUNTIFS(EVALUACION!$A$7:$A$36,A323,EVALUACION!$B$7:$B$36,B323)=0,"✖ Evaluación/paciente inconsistente",IF(C323="","✖ Suplemento sin producto",IF(E323="","▲ Suplemento sin dosis",IF(AND(ISNUMBER(K323),ISNUMBER(L323),L323<K323),"✖ Fecha término anterior",IF(AND(M323<>"",N323=""),"▲ Interacción sin fuente","✔ Correcto")))))))
R324: =IF(A324="","",IF(CONFIG!$B$27="No","▲ Módulo desactivado",IF(COUNTIFS(EVALUACION!$A$7:$A$36,A324,EVALUACION!$B$7:$B$36,B324)=0,"✖ Evaluación/paciente inconsistente",IF(C324="","✖ Suplemento sin producto",IF(E324="","▲ Suplemento sin dosis",IF(AND(ISNUMBER(K324),ISNUMBER(L324),L324<K324),"✖ Fecha término anterior",IF(AND(M324<>"",N324=""),"▲ Interacción sin fuente","✔ Correcto")))))))
... R341: =IF(A341="","",IF(CONFIG!$B$27="No","▲ Módulo desactivado",IF(COUNTIFS(EVALUACION!$A$7:$A$36,A341,EVALUACION!$B$7:$B$36,B341)=0,"✖ Evaluación/paciente inconsistente",IF(C341="","✖ Suplemento sin producto",IF(E341="","▲ Suplemento sin dosis",IF(AND(ISNUMBER(K341),ISNUMBER(L341),L341<K341),"✖ Fecha término anterior",IF(AND(M341<>"",N341=""),"▲ Interacción sin fuente","✔ Correcto")))))))

Sheet DIAGNOSTICO
A1: DIAGNÓSTICO NUTRICIONAL · Redacción profesional y estructura PES opcional
A2: ◀ INICIO | B2: RESUMEN | C2: CONFIG | D2: PRUEBAS
A3: ▲ Redactado y revisado por el profesional; no genera diagnóstico médico.
A5: T_DIAGNOSTICOS
A6: EvaluationID | B6: PatientID | C6: Fecha | D6: Dominio | E6: Problema | F6: Etiología | G6: Signos y síntomas | H6: Previsualización PES | I6: Redacción completa editable | J6: Prioridad | K6: Estado | L6: Fuente evidencia | M6: Revisión profesional | N6: Fecha cierre | O6: Motivo cierre | P6: FechaRegistro | Q6: Profesional | R6: Observaciones | S6: Control
A7: E-A-01 | B7: P-FICT-A | C7: 46174 | D7: Conducta | E7: Problema ficticio A | F7: Etiología ficticia A | G7: Signos ficticios A | H7: =IF(E7="","",E7&IF(F7<>""," relacionado con "&F7,"")&IF(G7<>""," evidenciado por "&G7,"")) -> Problema ficticio A relacionado con Etiología ficticia A evidenciado por Signos ficticios A | I7: Problema ficticio A relacionado con etiología ficticia A evidenciado por signos ficticios A | J7: Media | K7: Revisado | L7: Fuente profesional | M7: Sí | P7: 46174 | Q7: PROF-DEMO | R7: PACIENTE FICTICIO PARA PRUEBA — NO UTILIZAR COMO REFERENCIA CLÍNICA | S7: =IF(A7="","",IF(COUNTIFS(EVALUACION!$A$7:$A$3006,A7,EVALUACION!$B$7:$B$3006,B7)=0,"✖ Evaluación/paciente inconsistente",IF(AND(K7="Revisado",E7=""),"✖ Revisado sin problema",IF(E7="","▲ Problema vacío",IF(F7="","▲ Etiología pendiente",IF(G7="","▲ Signos pendientes",IF(AND(K7="Cerrado",NOT(ISNUMBER(N7))),"▲ Cierre sin fecha","✔ Revisión profesional requerida"))))))) -> ✔ Revisión profesional requerida
A8: E-B-01 | B8: P-FICT-B | C8: 46143 | D8: Conducta | E8: Problema ficticio B | F8: Etiología ficticia B | G8: Signos ficticios B | H8: =IF(E8="","",E8&IF(F8<>""," relacionado con "&F8,"")&IF(G8<>""," evidenciado por "&G8,"")) -> Problema ficticio B relacionado con Etiología ficticia B evidenciado por Signos ficticios B | I8: Problema ficticio B relacionado con etiología ficticia B evidenciado por signos ficticios B | J8: Media | K8: Activo | L8: Fuente profesional | M8: Sí | P8: 46143 | Q8: PROF-DEMO | R8: PACIENTE FICTICIO PARA PRUEBA — NO UTILIZAR COMO REFERENCIA CLÍNICA | S8: =IF(A8="","",IF(COUNTIFS(EVALUACION!$A$7:$A$3006,A8,EVALUACION!$B$7:$B$3006,B8)=0,"✖ Evaluación/paciente inconsistente",IF(AND(K8="Revisado",E8=""),"✖ Revisado sin problema",IF(E8="","▲ Problema vacío",IF(F8="","▲ Etiología pendiente",IF(G8="","▲ Signos pendientes",IF(AND(K8="Cerrado",NOT(ISNUMBER(N8))),"▲ Cierre sin fecha","✔ Revisión profesional requerida"))))))) -> ✔ Revisión profesional requerida
H9: =IF(E9="","",E9&IF(F9<>""," relacionado con "&F9,"")&IF(G9<>""," evidenciado por "&G9,"")) | S9: =IF(A9="","",IF(COUNTIFS(EVALUACION!$A$7:$A$36,A9,EVALUACION!$B$7:$B$36,B9)=0,"✖ Evaluación/paciente inconsistente",IF(AND(K9="Revisado",E9=""),"✖ Revisado sin problema",IF(E9="","▲ Problema vacío",IF(F9="","▲ Etiología pendiente",IF(G9="","▲ Signos pendientes",IF(AND(K9="Cerrado",NOT(ISNUMBER(N9))),"▲ Cierre sin fecha","✔ Revisión profesional requerida")))))))
H10: =IF(E10="","",E10&IF(F10<>""," relacionado con "&F10,"")&IF(G10<>""," evidenciado por "&G10,"")) | S10: =IF(A10="","",IF(COUNTIFS(EVALUACION!$A$7:$A$36,A10,EVALUACION!$B$7:$B$36,B10)=0,"✖ Evaluación/paciente inconsistente",IF(AND(K10="Revisado",E10=""),"✖ Revisado sin problema",IF(E10="","▲ Problema vacío",IF(F10="","▲ Etiología pendiente",IF(G10="","▲ Signos pendientes",IF(AND(K10="Cerrado",NOT(ISNUMBER(N10))),"▲ Cierre sin fecha","✔ Revisión profesional requerida")))))))
H11: =IF(E11="","",E11&IF(F11<>""," relacionado con "&F11,"")&IF(G11<>""," evidenciado por "&G11,"")) | S11: =IF(A11="","",IF(COUNTIFS(EVALUACION!$A$7:$A$36,A11,EVALUACION!$B$7:$B$36,B11)=0,"✖ Evaluación/paciente inconsistente",IF(AND(K11="Revisado",E11=""),"✖ Revisado sin problema",IF(E11="","▲ Problema vacío",IF(F11="","▲ Etiología pendiente",IF(G11="","▲ Signos pendientes",IF(AND(K11="Cerrado",NOT(ISNUMBER(N11))),"▲ Cierre sin fecha","✔ Revisión profesional requerida")))))))
H12: =IF(E12="","",E12&IF(F12<>""," relacionado con "&F12,"")&IF(G12<>""," evidenciado por "&G12,"")) | S12: =IF(A12="","",IF(COUNTIFS(EVALUACION!$A$7:$A$36,A12,EVALUACION!$B$7:$B$36,B12)=0,"✖ Evaluación/paciente inconsistente",IF(AND(K12="Revisado",E12=""),"✖ Revisado sin problema",IF(E12="","▲ Problema vacío",IF(F12="","▲ Etiología pendiente",IF(G12="","▲ Signos pendientes",IF(AND(K12="Cerrado",NOT(ISNUMBER(N12))),"▲ Cierre sin fecha","✔ Revisión profesional requerida")))))))
H13: =IF(E13="","",E13&IF(F13<>""," relacionado con "&F13,"")&IF(G13<>""," evidenciado por "&G13,"")) | S13: =IF(A13="","",IF(COUNTIFS(EVALUACION!$A$7:$A$36,A13,EVALUACION!$B$7:$B$36,B13)=0,"✖ Evaluación/paciente inconsistente",IF(AND(K13="Revisado",E13=""),"✖ Revisado sin problema",IF(E13="","▲ Problema vacío",IF(F13="","▲ Etiología pendiente",IF(G13="","▲ Signos pendientes",IF(AND(K13="Cerrado",NOT(ISNUMBER(N13))),"▲ Cierre sin fecha","✔ Revisión profesional requerida")))))))
H14: =IF(E14="","",E14&IF(F14<>""," relacionado con "&F14,"")&IF(G14<>""," evidenciado por "&G14,"")) | S14: =IF(A14="","",IF(COUNTIFS(EVALUACION!$A$7:$A$36,A14,EVALUACION!$B$7:$B$36,B14)=0,"✖ Evaluación/paciente inconsistente",IF(AND(K14="Revisado",E14=""),"✖ Revisado sin problema",IF(E14="","▲ Problema vacío",IF(F14="","▲ Etiología pendiente",IF(G14="","▲ Signos pendientes",IF(AND(K14="Cerrado",NOT(ISNUMBER(N14))),"▲ Cierre sin fecha","✔ Revisión profesional requerida")))))))
H15: =IF(E15="","",E15&IF(F15<>""," relacionado con "&F15,"")&IF(G15<>""," evidenciado por "&G15,"")) | S15: =IF(A15="","",IF(COUNTIFS(EVALUACION!$A$7:$A$36,A15,EVALUACION!$B$7:$B$36,B15)=0,"✖ Evaluación/paciente inconsistente",IF(AND(K15="Revisado",E15=""),"✖ Revisado sin problema",IF(E15="","▲ Problema vacío",IF(F15="","▲ Etiología pendiente",IF(G15="","▲ Signos pendientes",IF(AND(K15="Cerrado",NOT(ISNUMBER(N15))),"▲ Cierre sin fecha","✔ Revisión profesional requerida")))))))
H16: =IF(E16="","",E16&IF(F16<>""," relacionado con "&F16,"")&IF(G16<>""," evidenciado por "&G16,"")) | S16: =IF(A16="","",IF(COUNTIFS(EVALUACION!$A$7:$A$36,A16,EVALUACION!$B$7:$B$36,B16)=0,"✖ Evaluación/paciente inconsistente",IF(AND(K16="Revisado",E16=""),"✖ Revisado sin problema",IF(E16="","▲ Problema vacío",IF(F16="","▲ Etiología pendiente",IF(G16="","▲ Signos pendientes",IF(AND(K16="Cerrado",NOT(ISNUMBER(N16))),"▲ Cierre sin fecha","✔ Revisión profesional requerida")))))))
H17: =IF(E17="","",E17&IF(F17<>""," relacionado con "&F17,"")&IF(G17<>""," evidenciado por "&G17,"")) | S17: =IF(A17="","",IF(COUNTIFS(EVALUACION!$A$7:$A$36,A17,EVALUACION!$B$7:$B$36,B17)=0,"✖ Evaluación/paciente inconsistente",IF(AND(K17="Revisado",E17=""),"✖ Revisado sin problema",IF(E17="","▲ Problema vacío",IF(F17="","▲ Etiología pendiente",IF(G17="","▲ Signos pendientes",IF(AND(K17="Cerrado",NOT(ISNUMBER(N17))),"▲ Cierre sin fecha","✔ Revisión profesional requerida")))))))
H18: =IF(E18="","",E18&IF(F18<>""," relacionado con "&F18,"")&IF(G18<>""," evidenciado por "&G18,"")) | S18: =IF(A18="","",IF(COUNTIFS(EVALUACION!$A$7:$A$36,A18,EVALUACION!$B$7:$B$36,B18)=0,"✖ Evaluación/paciente inconsistente",IF(AND(K18="Revisado",E18=""),"✖ Revisado sin problema",IF(E18="","▲ Problema vacío",IF(F18="","▲ Etiología pendiente",IF(G18="","▲ Signos pendientes",IF(AND(K18="Cerrado",NOT(ISNUMBER(N18))),"▲ Cierre sin fecha","✔ Revisión profesional requerida")))))))
H19: =IF(E19="","",E19&IF(F19<>""," relacionado con "&F19,"")&IF(G19<>""," evidenciado por "&G19,"")) | S19: =IF(A19="","",IF(COUNTIFS(EVALUACION!$A$7:$A$36,A19,EVALUACION!$B$7:$B$36,B19)=0,"✖ Evaluación/paciente inconsistente",IF(AND(K19="Revisado",E19=""),"✖ Revisado sin problema",IF(E19="","▲ Problema vacío",IF(F19="","▲ Etiología pendiente",IF(G19="","▲ Signos pendientes",IF(AND(K19="Cerrado",NOT(ISNUMBER(N19))),"▲ Cierre sin fecha","✔ Revisión profesional requerida")))))))
H20: =IF(E20="","",E20&IF(F20<>""," relacionado con "&F20,"")&IF(G20<>""," evidenciado por "&G20,"")) | S20: =IF(A20="","",IF(COUNTIFS(EVALUACION!$A$7:$A$36,A20,EVALUACION!$B$7:$B$36,B20)=0,"✖ Evaluación/paciente inconsistente",IF(AND(K20="Revisado",E20=""),"✖ Revisado sin problema",IF(E20="","▲ Problema vacío",IF(F20="","▲ Etiología pendiente",IF(G20="","▲ Signos pendientes",IF(AND(K20="Cerrado",NOT(ISNUMBER(N20))),"▲ Cierre sin fecha","✔ Revisión profesional requerida")))))))
... H36: =IF(E36="","",E36&IF(F36<>""," relacionado con "&F36,"")&IF(G36<>""," evidenciado por "&G36,"")) | S36: =IF(A36="","",IF(COUNTIFS(EVALUACION!$A$7:$A$36,A36,EVALUACION!$B$7:$B$36,B36)=0,"✖ Evaluación/paciente inconsistente",IF(AND(K36="Revisado",E36=""),"✖ Revisado sin problema",IF(E36="","▲ Problema vacío",IF(F36="","▲ Etiología pendiente",IF(G36="","▲ Signos pendientes",IF(AND(K36="Cerrado",NOT(ISNUMBER(N36))),"▲ Cierre sin fecha","✔ Revisión profesional requerida")))))))

Sheet OBJETIVOS
A1: OBJETIVOS · Metas acordadas, indicadores y seguimiento
A2: ◀ INICIO | B2: RESUMEN | C2: CONFIG | D2: PRUEBAS
A3: PACIENTE FICTICIO PARA PRUEBA — NO UTILIZAR COMO REFERENCIA CLÍNICA · No se generan metas clínicas universales.
A5: T_OBJETIVOS
A6: EvaluationID | B6: PatientID | C6: ObjetivoID | D6: Categoría | E6: Descripción | F6: Indicador | G6: Valor inicial | H6: Meta | I6: Unidad | J6: Fecha inicio | K6: Fecha objetivo | L6: Prioridad | M6: Responsable | N6: Estado | O6: Porcentaje avance | P6: Criterio éxito | Q6: Barreras | R6: Facilitadores | S6: Observaciones | T6: ClaveObjetivo | U6: Control
A7: E-A-01 | B7: P-FICT-A | C7: O-A-01 | D7: Organización | E7: Objetivo ficticio A | F7: Número de comidas | G7: 3 | H7: 4 | I7: unidad | J7: 46174 | K7: 46235 | L7: Media | M7: PROF-DEMO | N7: Activo | O7: 50 | P7: Criterio ficticio | Q7: Horarios | R7: Planificación | S7: PACIENTE FICTICIO PARA PRUEBA — NO UTILIZAR COMO REFERENCIA CLÍNICA | T7: =IF(C7="","",B7&"|"&C7) -> P-FICT-A|O-A-01 | U7: =IF(A7="","",IF(COUNTIFS(EVALUACION!$A$7:$A$3006,A7,EVALUACION!$B$7:$B$3006,B7)=0,"✖ Evaluación/paciente inconsistente",IF(C7="","✖ ObjetivoID vacío",IF(COUNTIF($C$7:$C$3006,C7)>1,"✖ ObjetivoID duplicado",IF(E7="","✖ Descripción vacía",IF(H7="","▲ Meta vacía",IF(OR(O7<0,O7>100),"✖ Avance fuera de 0–100",IF(AND(ISNUMBER(J7),ISNUMBER(K7),K7<J7),"✖ Fecha objetivo anterior","✔ Correcto")))))))) -> ✔ Correcto
A8: E-B-01 | B8: P-FICT-B | C8: O-B-01 | D8: Actividad física | E8: Objetivo ficticio B | F8: Sesiones semanales | G8: 2 | H8: 3 | I8: veces/semana | J8: 46143 | K8: 46204 | L8: Media | M8: PROF-DEMO | N8: Cumplido | O8: 100 | P8: Criterio ficticio | Q8: Tiempo | R8: Apoyo | S8: PACIENTE FICTICIO PARA PRUEBA — NO UTILIZAR COMO REFERENCIA CLÍNICA | T8: =IF(C8="","",B8&"|"&C8) -> P-FICT-B|O-B-01 | U8: =IF(A8="","",IF(COUNTIFS(EVALUACION!$A$7:$A$3006,A8,EVALUACION!$B$7:$B$3006,B8)=0,"✖ Evaluación/paciente inconsistente",IF(C8="","✖ ObjetivoID vacío",IF(COUNTIF($C$7:$C$3006,C8)>1,"✖ ObjetivoID duplicado",IF(E8="","✖ Descripción vacía",IF(H8="","▲ Meta vacía",IF(OR(O8<0,O8>100),"✖ Avance fuera de 0–100",IF(AND(ISNUMBER(J8),ISNUMBER(K8),K8<J8),"✖ Fecha objetivo anterior","✔ Correcto")))))))) -> ✔ Correcto
A9: E-B-02 | B9: P-FICT-B | C9: O-B-02 | D9: Organización | E9: Objetivo ficticio control | F9: Registro semanal | G9: 0 | H9: 1 | I9: unidad | J9: 46204 | K9: 46235 | L9: Media | M9: PROF-DEMO | N9: Activo | O9: 25 | P9: Criterio ficticio | Q9: Turnos | R9: Planificación | S9: PACIENTE FICTICIO PARA PRUEBA — NO UTILIZAR COMO REFERENCIA CLÍNICA | T9: =IF(C9="","",B9&"|"&C9) -> P-FICT-B|O-B-02 | U9: =IF(A9="","",IF(COUNTIFS(EVALUACION!$A$7:$A$3006,A9,EVALUACION!$B$7:$B$3006,B9)=0,"✖ Evaluación/paciente inconsistente",IF(C9="","✖ ObjetivoID vacío",IF(COUNTIF($C$7:$C$3006,C9)>1,"✖ ObjetivoID duplicado",IF(E9="","✖ Descripción vacía",IF(H9="","▲ Meta vacía",IF(OR(O9<0,O9>100),"✖ Avance fuera de 0–100",IF(AND(ISNUMBER(J9),ISNUMBER(K9),K9<J9),"✖ Fecha objetivo anterior","✔ Correcto")))))))) -> ✔ Correcto
T10: =IF(C10="","",B10&"|"&C10) | U10: =IF(A10="","",IF(COUNTIFS(EVALUACION!$A$7:$A$36,A10,EVALUACION!$B$7:$B$36,B10)=0,"✖ Evaluación/paciente inconsistente",IF(C10="","✖ ObjetivoID vacío",IF(COUNTIF($C$7:$C$36,C10)>1,"✖ ObjetivoID duplicado",IF(E10="","✖ Descripción vacía",IF(H10="","▲ Meta vacía",IF(OR(O10<0,O10>100),"✖ Avance fuera de 0–100",IF(AND(ISNUMBER(J10),ISNUMBER(K10),K10<J10),"✖ Fecha objetivo anterior","✔ Correcto"))))))))
T11: =IF(C11="","",B11&"|"&C11) | U11: =IF(A11="","",IF(COUNTIFS(EVALUACION!$A$7:$A$36,A11,EVALUACION!$B$7:$B$36,B11)=0,"✖ Evaluación/paciente inconsistente",IF(C11="","✖ ObjetivoID vacío",IF(COUNTIF($C$7:$C$36,C11)>1,"✖ ObjetivoID duplicado",IF(E11="","✖ Descripción vacía",IF(H11="","▲ Meta vacía",IF(OR(O11<0,O11>100),"✖ Avance fuera de 0–100",IF(AND(ISNUMBER(J11),ISNUMBER(K11),K11<J11),"✖ Fecha objetivo anterior","✔ Correcto"))))))))
T12: =IF(C12="","",B12&"|"&C12) | U12: =IF(A12="","",IF(COUNTIFS(EVALUACION!$A$7:$A$36,A12,EVALUACION!$B$7:$B$36,B12)=0,"✖ Evaluación/paciente inconsistente",IF(C12="","✖ ObjetivoID vacío",IF(COUNTIF($C$7:$C$36,C12)>1,"✖ ObjetivoID duplicado",IF(E12="","✖ Descripción vacía",IF(H12="","▲ Meta vacía",IF(OR(O12<0,O12>100),"✖ Avance fuera de 0–100",IF(AND(ISNUMBER(J12),ISNUMBER(K12),K12<J12),"✖ Fecha objetivo anterior","✔ Correcto"))))))))
T13: =IF(C13="","",B13&"|"&C13) | U13: =IF(A13="","",IF(COUNTIFS(EVALUACION!$A$7:$A$36,A13,EVALUACION!$B$7:$B$36,B13)=0,"✖ Evaluación/paciente inconsistente",IF(C13="","✖ ObjetivoID vacío",IF(COUNTIF($C$7:$C$36,C13)>1,"✖ ObjetivoID duplicado",IF(E13="","✖ Descripción vacía",IF(H13="","▲ Meta vacía",IF(OR(O13<0,O13>100),"✖ Avance fuera de 0–100",IF(AND(ISNUMBER(J13),ISNUMBER(K13),K13<J13),"✖ Fecha objetivo anterior","✔ Correcto"))))))))
T14: =IF(C14="","",B14&"|"&C14) | U14: =IF(A14="","",IF(COUNTIFS(EVALUACION!$A$7:$A$36,A14,EVALUACION!$B$7:$B$36,B14)=0,"✖ Evaluación/paciente inconsistente",IF(C14="","✖ ObjetivoID vacío",IF(COUNTIF($C$7:$C$36,C14)>1,"✖ ObjetivoID duplicado",IF(E14="","✖ Descripción vacía",IF(H14="","▲ Meta vacía",IF(OR(O14<0,O14>100),"✖ Avance fuera de 0–100",IF(AND(ISNUMBER(J14),ISNUMBER(K14),K14<J14),"✖ Fecha objetivo anterior","✔ Correcto"))))))))
T15: =IF(C15="","",B15&"|"&C15) | U15: =IF(A15="","",IF(COUNTIFS(EVALUACION!$A$7:$A$36,A15,EVALUACION!$B$7:$B$36,B15)=0,"✖ Evaluación/paciente inconsistente",IF(C15="","✖ ObjetivoID vacío",IF(COUNTIF($C$7:$C$36,C15)>1,"✖ ObjetivoID duplicado",IF(E15="","✖ Descripción vacía",IF(H15="","▲ Meta vacía",IF(OR(O15<0,O15>100),"✖ Avance fuera de 0–100",IF(AND(ISNUMBER(J15),ISNUMBER(K15),K15<J15),"✖ Fecha objetivo anterior","✔ Correcto"))))))))
T16: =IF(C16="","",B16&"|"&C16) | U16: =IF(A16="","",IF(COUNTIFS(EVALUACION!$A$7:$A$36,A16,EVALUACION!$B$7:$B$36,B16)=0,"✖ Evaluación/paciente inconsistente",IF(C16="","✖ ObjetivoID vacío",IF(COUNTIF($C$7:$C$36,C16)>1,"✖ ObjetivoID duplicado",IF(E16="","✖ Descripción vacía",IF(H16="","▲ Meta vacía",IF(OR(O16<0,O16>100),"✖ Avance fuera de 0–100",IF(AND(ISNUMBER(J16),ISNUMBER(K16),K16<J16),"✖ Fecha objetivo anterior","✔ Correcto"))))))))
T17: =IF(C17="","",B17&"|"&C17) | U17: =IF(A17="","",IF(COUNTIFS(EVALUACION!$A$7:$A$36,A17,EVALUACION!$B$7:$B$36,B17)=0,"✖ Evaluación/paciente inconsistente",IF(C17="","✖ ObjetivoID vacío",IF(COUNTIF($C$7:$C$36,C17)>1,"✖ ObjetivoID duplicado",IF(E17="","✖ Descripción vacía",IF(H17="","▲ Meta vacía",IF(OR(O17<0,O17>100),"✖ Avance fuera de 0–100",IF(AND(ISNUMBER(J17),ISNUMBER(K17),K17<J17),"✖ Fecha objetivo anterior","✔ Correcto"))))))))
T18: =IF(C18="","",B18&"|"&C18) | U18: =IF(A18="","",IF(COUNTIFS(EVALUACION!$A$7:$A$36,A18,EVALUACION!$B$7:$B$36,B18)=0,"✖ Evaluación/paciente inconsistente",IF(C18="","✖ ObjetivoID vacío",IF(COUNTIF($C$7:$C$36,C18)>1,"✖ ObjetivoID duplicado",IF(E18="","✖ Descripción vacía",IF(H18="","▲ Meta vacía",IF(OR(O18<0,O18>100),"✖ Avance fuera de 0–100",IF(AND(ISNUMBER(J18),ISNUMBER(K18),K18<J18),"✖ Fecha objetivo anterior","✔ Correcto"))))))))
T19: =IF(C19="","",B19&"|"&C19) | U19: =IF(A19="","",IF(COUNTIFS(EVALUACION!$A$7:$A$36,A19,EVALUACION!$B$7:$B$36,B19)=0,"✖ Evaluación/paciente inconsistente",IF(C19="","✖ ObjetivoID vacío",IF(COUNTIF($C$7:$C$36,C19)>1,"✖ ObjetivoID duplicado",IF(E19="","✖ Descripción vacía",IF(H19="","▲ Meta vacía",IF(OR(O19<0,O19>100),"✖ Avance fuera de 0–100",IF(AND(ISNUMBER(J19),ISNUMBER(K19),K19<J19),"✖ Fecha objetivo anterior","✔ Correcto"))))))))
T20: =IF(C20="","",B20&"|"&C20) | U20: =IF(A20="","",IF(COUNTIFS(EVALUACION!$A$7:$A$36,A20,EVALUACION!$B$7:$B$36,B20)=0,"✖ Evaluación/paciente inconsistente",IF(C20="","✖ ObjetivoID vacío",IF(COUNTIF($C$7:$C$36,C20)>1,"✖ ObjetivoID duplicado",IF(E20="","✖ Descripción vacía",IF(H20="","▲ Meta vacía",IF(OR(O20<0,O20>100),"✖ Avance fuera de 0–100",IF(AND(ISNUMBER(J20),ISNUMBER(K20),K20<J20),"✖ Fecha objetivo anterior","✔ Correcto"))))))))
T21: =IF(C21="","",B21&"|"&C21) | U21: =IF(A21="","",IF(COUNTIFS(EVALUACION!$A$7:$A$36,A21,EVALUACION!$B$7:$B$36,B21)=0,"✖ Evaluación/paciente inconsistente",IF(C21="","✖ ObjetivoID vacío",IF(COUNTIF($C$7:$C$36,C21)>1,"✖ ObjetivoID duplicado",IF(E21="","✖ Descripción vacía",IF(H21="","▲ Meta vacía",IF(OR(O21<0,O21>100),"✖ Avance fuera de 0–100",IF(AND(ISNUMBER(J21),ISNUMBER(K21),K21<J21),"✖ Fecha objetivo anterior","✔ Correcto"))))))))
... T36: =IF(C36="","",B36&"|"&C36) | U36: =IF(A36="","",IF(COUNTIFS(EVALUACION!$A$7:$A$36,A36,EVALUACION!$B$7:$B$36,B36)=0,"✖ Evaluación/paciente inconsistente",IF(C36="","✖ ObjetivoID vacío",IF(COUNTIF($C$7:$C$36,C36)>1,"✖ ObjetivoID duplicado",IF(E36="","✖ Descripción vacía",IF(H36="","▲ Meta vacía",IF(OR(O36<0,O36>100),"✖ Avance fuera de 0–100",IF(AND(ISNUMBER(J36),ISNUMBER(K36),K36<J36),"✖ Fecha objetivo anterior","✔ Correcto"))))))))

Sheet INTERVENCION
A1: INTERVENCIÓN · Acciones, acuerdos y coordinación
A2: ◀ INICIO | B2: RESUMEN | C2: CONFIG | D2: PRUEBAS
A3: ▲ Documentación manual; no constituye prescripción automática.
A5: T_INTERVENCIONES
A6: EvaluationID | B6: PatientID | C6: Fecha | D6: Categoría | E6: Intervención | F6: Fundamento | G6: Objetivo relacionado | H6: Responsable | I6: Frecuencia | J6: Material entregado | K6: Acuerdo con paciente | L6: Estado | M6: Fecha revisión | N6: FechaRegistro | O6: Profesional | P6: Observaciones | Q6: Control
A7: E-A-01 | B7: P-FICT-A | C7: 46174 | D7: Organización de comidas | E7: Intervención ficticia A | F7: Fundamento profesional | G7: O-A-01 | H7: PROF-DEMO | I7: Semanal | J7: Material ficticio | K7: Acuerdo ficticio | L7: Activo | M7: 46204 | N7: 46174 | O7: PROF-DEMO | P7: PACIENTE FICTICIO PARA PRUEBA — NO UTILIZAR COMO REFERENCIA CLÍNICA | Q7: =IF(A7="","",IF(COUNTIFS(EVALUACION!$A$7:$A$3006,A7,EVALUACION!$B$7:$B$3006,B7)=0,"✖ Evaluación/paciente inconsistente",IF(E7="","✖ Intervención vacía",IF(AND(G7<>"",COUNTIF(OBJETIVOS!$C$7:$C$3006,G7)=0),"▲ Objetivo inexistente","✔ Correcto")))) -> ✔ Correcto
A8: E-B-01 | B8: P-FICT-B | C8: 46143 | D8: Actividad física | E8: Intervención ficticia B | F8: Fundamento profesional | G8: O-B-01 | H8: PROF-DEMO | I8: Semanal | J8: Material ficticio | K8: Acuerdo ficticio | L8: Completo | M8: 46204 | N8: 46143 | O8: PROF-DEMO | P8: PACIENTE FICTICIO PARA PRUEBA — NO UTILIZAR COMO REFERENCIA CLÍNICA | Q8: =IF(A8="","",IF(COUNTIFS(EVALUACION!$A$7:$A$3006,A8,EVALUACION!$B$7:$B$3006,B8)=0,"✖ Evaluación/paciente inconsistente",IF(E8="","✖ Intervención vacía",IF(AND(G8<>"",COUNTIF(OBJETIVOS!$C$7:$C$3006,G8)=0),"▲ Objetivo inexistente","✔ Correcto")))) -> ✔ Correcto
Q9: =IF(A9="","",IF(COUNTIFS(EVALUACION!$A$7:$A$36,A9,EVALUACION!$B$7:$B$36,B9)=0,"✖ Evaluación/paciente inconsistente",IF(E9="","✖ Intervención vacía",IF(AND(G9<>"",COUNTIF(OBJETIVOS!$C$7:$C$36,G9)=0),"▲ Objetivo inexistente","✔ Correcto"))))
Q10: =IF(A10="","",IF(COUNTIFS(EVALUACION!$A$7:$A$36,A10,EVALUACION!$B$7:$B$36,B10)=0,"✖ Evaluación/paciente inconsistente",IF(E10="","✖ Intervención vacía",IF(AND(G10<>"",COUNTIF(OBJETIVOS!$C$7:$C$36,G10)=0),"▲ Objetivo inexistente","✔ Correcto"))))
Q11: =IF(A11="","",IF(COUNTIFS(EVALUACION!$A$7:$A$36,A11,EVALUACION!$B$7:$B$36,B11)=0,"✖ Evaluación/paciente inconsistente",IF(E11="","✖ Intervención vacía",IF(AND(G11<>"",COUNTIF(OBJETIVOS!$C$7:$C$36,G11)=0),"▲ Objetivo inexistente","✔ Correcto"))))
Q12: =IF(A12="","",IF(COUNTIFS(EVALUACION!$A$7:$A$36,A12,EVALUACION!$B$7:$B$36,B12)=0,"✖ Evaluación/paciente inconsistente",IF(E12="","✖ Intervención vacía",IF(AND(G12<>"",COUNTIF(OBJETIVOS!$C$7:$C$36,G12)=0),"▲ Objetivo inexistente","✔ Correcto"))))
Q13: =IF(A13="","",IF(COUNTIFS(EVALUACION!$A$7:$A$36,A13,EVALUACION!$B$7:$B$36,B13)=0,"✖ Evaluación/paciente inconsistente",IF(E13="","✖ Intervención vacía",IF(AND(G13<>"",COUNTIF(OBJETIVOS!$C$7:$C$36,G13)=0),"▲ Objetivo inexistente","✔ Correcto"))))
Q14: =IF(A14="","",IF(COUNTIFS(EVALUACION!$A$7:$A$36,A14,EVALUACION!$B$7:$B$36,B14)=0,"✖ Evaluación/paciente inconsistente",IF(E14="","✖ Intervención vacía",IF(AND(G14<>"",COUNTIF(OBJETIVOS!$C$7:$C$36,G14)=0),"▲ Objetivo inexistente","✔ Correcto"))))
Q15: =IF(A15="","",IF(COUNTIFS(EVALUACION!$A$7:$A$36,A15,EVALUACION!$B$7:$B$36,B15)=0,"✖ Evaluación/paciente inconsistente",IF(E15="","✖ Intervención vacía",IF(AND(G15<>"",COUNTIF(OBJETIVOS!$C$7:$C$36,G15)=0),"▲ Objetivo inexistente","✔ Correcto"))))
Q16: =IF(A16="","",IF(COUNTIFS(EVALUACION!$A$7:$A$36,A16,EVALUACION!$B$7:$B$36,B16)=0,"✖ Evaluación/paciente inconsistente",IF(E16="","✖ Intervención vacía",IF(AND(G16<>"",COUNTIF(OBJETIVOS!$C$7:$C$36,G16)=0),"▲ Objetivo inexistente","✔ Correcto"))))
Q17: =IF(A17="","",IF(COUNTIFS(EVALUACION!$A$7:$A$36,A17,EVALUACION!$B$7:$B$36,B17)=0,"✖ Evaluación/paciente inconsistente",IF(E17="","✖ Intervención vacía",IF(AND(G17<>"",COUNTIF(OBJETIVOS!$C$7:$C$36,G17)=0),"▲ Objetivo inexistente","✔ Correcto"))))
Q18: =IF(A18="","",IF(COUNTIFS(EVALUACION!$A$7:$A$36,A18,EVALUACION!$B$7:$B$36,B18)=0,"✖ Evaluación/paciente inconsistente",IF(E18="","✖ Intervención vacía",IF(AND(G18<>"",COUNTIF(OBJETIVOS!$C$7:$C$36,G18)=0),"▲ Objetivo inexistente","✔ Correcto"))))
Q19: =IF(A19="","",IF(COUNTIFS(EVALUACION!$A$7:$A$36,A19,EVALUACION!$B$7:$B$36,B19)=0,"✖ Evaluación/paciente inconsistente",IF(E19="","✖ Intervención vacía",IF(AND(G19<>"",COUNTIF(OBJETIVOS!$C$7:$C$36,G19)=0),"▲ Objetivo inexistente","✔ Correcto"))))
Q20: =IF(A20="","",IF(COUNTIFS(EVALUACION!$A$7:$A$36,A20,EVALUACION!$B$7:$B$36,B20)=0,"✖ Evaluación/paciente inconsistente",IF(E20="","✖ Intervención vacía",IF(AND(G20<>"",COUNTIF(OBJETIVOS!$C$7:$C$36,G20)=0),"▲ Objetivo inexistente","✔ Correcto"))))
... Q36: =IF(A36="","",IF(COUNTIFS(EVALUACION!$A$7:$A$36,A36,EVALUACION!$B$7:$B$36,B36)=0,"✖ Evaluación/paciente inconsistente",IF(E36="","✖ Intervención vacía",IF(AND(G36<>"",COUNTIF(OBJETIVOS!$C$7:$C$36,G36)=0),"▲ Objetivo inexistente","✔ Correcto"))))

Sheet SEGUIMIENTO
A1: SEGUIMIENTO · Comparación longitudinal por paciente
A2: ◀ INICIO | B2: RESUMEN | C2: CONFIG | D2: PRUEBAS
A3: PACIENTE FICTICIO PARA PRUEBA — NO UTILIZAR COMO REFERENCIA CLÍNICA · Nunca comparar evaluaciones de pacientes distintos.
A5: T_SEGUIMIENTO
A6: EvaluationID | B6: PatientID | C6: Fecha | D6: EvaluationID anterior | E6: Días desde anterior | F6: Peso actual kg | G6: Peso anterior kg | H6: Cambio peso kg | I6: Cambio peso % | J6: Adherencia percibida | K6: Cumplimiento objetivos | L6: Objetivos cumplidos | M6: Objetivos pendientes | N6: Síntomas | O6: Barreras nuevas | P6: Facilitadores nuevos | Q6: Cambios fármacos | R6: Cambios actividad | S6: Cambios alimentarios | T6: Decisión profesional | U6: Próxima acción | V6: Próxima fecha | W6: Estado | X6: Observaciones | Y6: Control
A7: E-B-02 | B7: P-FICT-B | C7: 46204 | D7: E-B-01 | E7: =IF(D7="","",IF(COUNTIF(EVALUACION!$A$7:$A$3006,D7)=0,"",C7-INDEX(EVALUACION!$C$7:$C$3006,MATCH(D7,EVALUACION!$A$7:$A$3006,0)))) -> 61 | F7: =IF(COUNTIF(ANTROPOMETRIA!$A$7:$A$3006,A7)=0,"",INDEX(ANTROPOMETRIA!$D$7:$D$3006,MATCH(A7,ANTROPOMETRIA!$A$7:$A$3006,0))) -> 87 | G7: =IF(OR(D7="",COUNTIF(ANTROPOMETRIA!$A$7:$A$3006,D7)=0),"",INDEX(ANTROPOMETRIA!$D$7:$D$3006,MATCH(D7,ANTROPOMETRIA!$A$7:$A$3006,0))) -> 90 | H7: =IF(AND(ISNUMBER(F7),ISNUMBER(G7)),F7-G7,"") -> -3 | I7: =IF(AND(ISNUMBER(F7),ISNUMBER(G7),G7<>0),(F7-G7)/G7,"") -> -0.033333333 | J7: Declarada | K7: Parcial | L7: =IF(A7="","",COUNTIFS(OBJETIVOS!$A$7:$A$3006,A7,OBJETIVOS!$N$7:$N$3006,"Cumplido")) -> 0 | M7: =IF(A7="","",COUNTIFS(OBJETIVOS!$A$7:$A$3006,A7,OBJETIVOS!$N$7:$N$3006,"Activo")) -> 1 | N7: Sin cambios ficticios | O7: Turnos | P7: Planificación | Q7: Sin cambios ficticios | R7: Aumentó caminata | S7: Mejor organización | T7: Continuar seguimiento | U7: Registrar próxima semana | V7: 46235 | W7: Completo | X7: PACIENTE FICTICIO PARA PRUEBA — NO UTILIZAR COMO REFERENCIA CLÍNICA | Y7: =IF(A7="","",IF(COUNTIFS(EVALUACION!$A$7:$A$3006,A7,EVALUACION!$B$7:$B$3006,B7)=0,"✖ Evaluación actual inconsistente",IF(D7="","▲ Sin evaluación anterior",IF(COUNTIF(EVALUACION!$A$7:$A$3006,D7)=0,"✖ Evaluación anterior inexistente",IF(COUNTIFS(EVALUACION!$A$7:$A$3006,D7,EVALUACION!$B$7:$B$3006,B7)=0,"✖ Evaluación anterior de otro paciente",IF(INDEX(EVALUACION!$C$7:$C$3006,MATCH(D7,EVALUACION!$A$7:$A$3006,0))>C7,"✖ Fecha anterior posterior",IF(AND(ISNUMBER(V7),V7<C7),"✖ Próxima fecha anterior","✔ Correcto"))))))) -> ✔ Correcto
E8: =IF(D8="","",IF(COUNTIF(EVALUACION!$A$7:$A$36,D8)=0,"",C8-INDEX(EVALUACION!$C$7:$C$36,MATCH(D8,EVALUACION!$A$7:$A$36,0)))) | F8: =IF(COUNTIF(ANTROPOMETRIA!$A$7:$A$36,A8)=0,"",INDEX(ANTROPOMETRIA!$D$7:$D$36,MATCH(A8,ANTROPOMETRIA!$A$7:$A$36,0))) | G8: =IF(OR(D8="",COUNTIF(ANTROPOMETRIA!$A$7:$A$36,D8)=0),"",INDEX(ANTROPOMETRIA!$D$7:$D$36,MATCH(D8,ANTROPOMETRIA!$A$7:$A$36,0))) | H8: =IF(AND(ISNUMBER(F8),ISNUMBER(G8)),F8-G8,"") | I8: =IF(AND(ISNUMBER(F8),ISNUMBER(G8),G8<>0),(F8-G8)/G8,"") | L8: =IF(A8="","",COUNTIFS(OBJETIVOS!$A$7:$A$36,A8,OBJETIVOS!$N$7:$N$36,"Cumplido")) | M8: =IF(A8="","",COUNTIFS(OBJETIVOS!$A$7:$A$36,A8,OBJETIVOS!$N$7:$N$36,"Activo")) | Y8: =IF(A8="","",IF(COUNTIFS(EVALUACION!$A$7:$A$36,A8,EVALUACION!$B$7:$B$36,B8)=0,"✖ Evaluación actual inconsistente",IF(D8="","▲ Sin evaluación anterior",IF(COUNTIF(EVALUACION!$A$7:$A$36,D8)=0,"✖ Evaluación anterior inexistente",IF(COUNTIFS(EVALUACION!$A$7:$A$36,D8,EVALUACION!$B$7:$B$36,B8)=0,"✖ Evaluación anterior de otro paciente",IF(INDEX(EVALUACION!$C$7:$C$36,MATCH(D8,EVALUACION!$A$7:$A$36,0))>C8,"✖ Fecha anterior posterior",IF(AND(ISNUMBER(V8),V8<C8),"✖ Próxima fecha anterior","✔ Correcto")))))))
E9: =IF(D9="","",IF(COUNTIF(EVALUACION!$A$7:$A$36,D9)=0,"",C9-INDEX(EVALUACION!$C$7:$C$36,MATCH(D9,EVALUACION!$A$7:$A$36,0)))) | F9: =IF(COUNTIF(ANTROPOMETRIA!$A$7:$A$36,A9)=0,"",INDEX(ANTROPOMETRIA!$D$7:$D$36,MATCH(A9,ANTROPOMETRIA!$A$7:$A$36,0))) | G9: =IF(OR(D9="",COUNTIF(ANTROPOMETRIA!$A$7:$A$36,D9)=0),"",INDEX(ANTROPOMETRIA!$D$7:$D$36,MATCH(D9,ANTROPOMETRIA!$A$7:$A$36,0))) | H9: =IF(AND(ISNUMBER(F9),ISNUMBER(G9)),F9-G9,"") | I9: =IF(AND(ISNUMBER(F9),ISNUMBER(G9),G9<>0),(F9-G9)/G9,"") | L9: =IF(A9="","",COUNTIFS(OBJETIVOS!$A$7:$A$36,A9,OBJETIVOS!$N$7:$N$36,"Cumplido")) | M9: =IF(A9="","",COUNTIFS(OBJETIVOS!$A$7:$A$36,A9,OBJETIVOS!$N$7:$N$36,"Activo")) | Y9: =IF(A9="","",IF(COUNTIFS(EVALUACION!$A$7:$A$36,A9,EVALUACION!$B$7:$B$36,B9)=0,"✖ Evaluación actual inconsistente",IF(D9="","▲ Sin evaluación anterior",IF(COUNTIF(EVALUACION!$A$7:$A$36,D9)=0,"✖ Evaluación anterior inexistente",IF(COUNTIFS(EVALUACION!$A$7:$A$36,D9,EVALUACION!$B$7:$B$36,B9)=0,"✖ Evaluación anterior de otro paciente",IF(INDEX(EVALUACION!$C$7:$C$36,MATCH(D9,EVALUACION!$A$7:$A$36,0))>C9,"✖ Fecha anterior posterior",IF(AND(ISNUMBER(V9),V9<C9),"✖ Próxima fecha anterior","✔ Correcto")))))))
E10: =IF(D10="","",IF(COUNTIF(EVALUACION!$A$7:$A$36,D10)=0,"",C10-INDEX(EVALUACION!$C$7:$C$36,MATCH(D10,EVALUACION!$A$7:$A$36,0)))) | F10: =IF(COUNTIF(ANTROPOMETRIA!$A$7:$A$36,A10)=0,"",INDEX(ANTROPOMETRIA!$D$7:$D$36,MATCH(A10,ANTROPOMETRIA!$A$7:$A$36,0))) | G10: =IF(OR(D10="",COUNTIF(ANTROPOMETRIA!$A$7:$A$36,D10)=0),"",INDEX(ANTROPOMETRIA!$D$7:$D$36,MATCH(D10,ANTROPOMETRIA!$A$7:$A$36,0))) | H10: =IF(AND(ISNUMBER(F10),ISNUMBER(G10)),F10-G10,"") | I10: =IF(AND(ISNUMBER(F10),ISNUMBER(G10),G10<>0),(F10-G10)/G10,"") | L10: =IF(A10="","",COUNTIFS(OBJETIVOS!$A$7:$A$36,A10,OBJETIVOS!$N$7:$N$36,"Cumplido")) | M10: =IF(A10="","",COUNTIFS(OBJETIVOS!$A$7:$A$36,A10,OBJETIVOS!$N$7:$N$36,"Activo")) | Y10: =IF(A10="","",IF(COUNTIFS(EVALUACION!$A$7:$A$36,A10,EVALUACION!$B$7:$B$36,B10)=0,"✖ Evaluación actual inconsistente",IF(D10="","▲ Sin evaluación anterior",IF(COUNTIF(EVALUACION!$A$7:$A$36,D10)=0,"✖ Evaluación anterior inexistente",IF(COUNTIFS(EVALUACION!$A$7:$A$36,D10,EVALUACION!$B$7:$B$36,B10)=0,"✖ Evaluación anterior de otro paciente",IF(INDEX(EVALUACION!$C$7:$C$36,MATCH(D10,EVALUACION!$A$7:$A$36,0))>C10,"✖ Fecha anterior posterior",IF(AND(ISNUMBER(V10),V10<C10),"✖ Próxima fecha anterior","✔ Correcto")))))))
E11: =IF(D11="","",IF(COUNTIF(EVALUACION!$A$7:$A$36,D11)=0,"",C11-INDEX(EVALUACION!$C$7:$C$36,MATCH(D11,EVALUACION!$A$7:$A$36,0)))) | F11: =IF(COUNTIF(ANTROPOMETRIA!$A$7:$A$36,A11)=0,"",INDEX(ANTROPOMETRIA!$D$7:$D$36,MATCH(A11,ANTROPOMETRIA!$A$7:$A$36,0))) | G11: =IF(OR(D11="",COUNTIF(ANTROPOMETRIA!$A$7:$A$36,D11)=0),"",INDEX(ANTROPOMETRIA!$D$7:$D$36,MATCH(D11,ANTROPOMETRIA!$A$7:$A$36,0))) | H11: =IF(AND(ISNUMBER(F11),ISNUMBER(G11)),F11-G11,"") | I11: =IF(AND(ISNUMBER(F11),ISNUMBER(G11),G11<>0),(F11-G11)/G11,"") | L11: =IF(A11="","",COUNTIFS(OBJETIVOS!$A$7:$A$36,A11,OBJETIVOS!$N$7:$N$36,"Cumplido")) | M11: =IF(A11="","",COUNTIFS(OBJETIVOS!$A$7:$A$36,A11,OBJETIVOS!$N$7:$N$36,"Activo")) | Y11: =IF(A11="","",IF(COUNTIFS(EVALUACION!$A$7:$A$36,A11,EVALUACION!$B$7:$B$36,B11)=0,"✖ Evaluación actual inconsistente",IF(D11="","▲ Sin evaluación anterior",IF(COUNTIF(EVALUACION!$A$7:$A$36,D11)=0,"✖ Evaluación anterior inexistente",IF(COUNTIFS(EVALUACION!$A$7:$A$36,D11,EVALUACION!$B$7:$B$36,B11)=0,"✖ Evaluación anterior de otro paciente",IF(INDEX(EVALUACION!$C$7:$C$36,MATCH(D11,EVALUACION!$A$7:$A$36,0))>C11,"✖ Fecha anterior posterior",IF(AND(ISNUMBER(V11),V11<C11),"✖ Próxima fecha anterior","✔ Correcto")))))))
E12: =IF(D12="","",IF(COUNTIF(EVALUACION!$A$7:$A$36,D12)=0,"",C12-INDEX(EVALUACION!$C$7:$C$36,MATCH(D12,EVALUACION!$A$7:$A$36,0)))) | F12: =IF(COUNTIF(ANTROPOMETRIA!$A$7:$A$36,A12)=0,"",INDEX(ANTROPOMETRIA!$D$7:$D$36,MATCH(A12,ANTROPOMETRIA!$A$7:$A$36,0))) | G12: =IF(OR(D12="",COUNTIF(ANTROPOMETRIA!$A$7:$A$36,D12)=0),"",INDEX(ANTROPOMETRIA!$D$7:$D$36,MATCH(D12,ANTROPOMETRIA!$A$7:$A$36,0))) | H12: =IF(AND(ISNUMBER(F12),ISNUMBER(G12)),F12-G12,"") | I12: =IF(AND(ISNUMBER(F12),ISNUMBER(G12),G12<>0),(F12-G12)/G12,"") | L12: =IF(A12="","",COUNTIFS(OBJETIVOS!$A$7:$A$36,A12,OBJETIVOS!$N$7:$N$36,"Cumplido")) | M12: =IF(A12="","",COUNTIFS(OBJETIVOS!$A$7:$A$36,A12,OBJETIVOS!$N$7:$N$36,"Activo")) | Y12: =IF(A12="","",IF(COUNTIFS(EVALUACION!$A$7:$A$36,A12,EVALUACION!$B$7:$B$36,B12)=0,"✖ Evaluación actual inconsistente",IF(D12="","▲ Sin evaluación anterior",IF(COUNTIF(EVALUACION!$A$7:$A$36,D12)=0,"✖ Evaluación anterior inexistente",IF(COUNTIFS(EVALUACION!$A$7:$A$36,D12,EVALUACION!$B$7:$B$36,B12)=0,"✖ Evaluación anterior de otro paciente",IF(INDEX(EVALUACION!$C$7:$C$36,MATCH(D12,EVALUACION!$A$7:$A$36,0))>C12,"✖ Fecha anterior posterior",IF(AND(ISNUMBER(V12),V12<C12),"✖ Próxima fecha anterior","✔ Correcto")))))))
E13: =IF(D13="","",IF(COUNTIF(EVALUACION!$A$7:$A$36,D13)=0,"",C13-INDEX(EVALUACION!$C$7:$C$36,MATCH(D13,EVALUACION!$A$7:$A$36,0)))) | F13: =IF(COUNTIF(ANTROPOMETRIA!$A$7:$A$36,A13)=0,"",INDEX(ANTROPOMETRIA!$D$7:$D$36,MATCH(A13,ANTROPOMETRIA!$A$7:$A$36,0))) | G13: =IF(OR(D13="",COUNTIF(ANTROPOMETRIA!$A$7:$A$36,D13)=0),"",INDEX(ANTROPOMETRIA!$D$7:$D$36,MATCH(D13,ANTROPOMETRIA!$A$7:$A$36,0))) | H13: =IF(AND(ISNUMBER(F13),ISNUMBER(G13)),F13-G13,"") | I13: =IF(AND(ISNUMBER(F13),ISNUMBER(G13),G13<>0),(F13-G13)/G13,"") | L13: =IF(A13="","",COUNTIFS(OBJETIVOS!$A$7:$A$36,A13,OBJETIVOS!$N$7:$N$36,"Cumplido")) | M13: =IF(A13="","",COUNTIFS(OBJETIVOS!$A$7:$A$36,A13,OBJETIVOS!$N$7:$N$36,"Activo")) | Y13: =IF(A13="","",IF(COUNTIFS(EVALUACION!$A$7:$A$36,A13,EVALUACION!$B$7:$B$36,B13)=0,"✖ Evaluación actual inconsistente",IF(D13="","▲ Sin evaluación anterior",IF(COUNTIF(EVALUACION!$A$7:$A$36,D13)=0,"✖ Evaluación anterior inexistente",IF(COUNTIFS(EVALUACION!$A$7:$A$36,D13,EVALUACION!$B$7:$B$36,B13)=0,"✖ Evaluación anterior de otro paciente",IF(INDEX(EVALUACION!$C$7:$C$36,MATCH(D13,EVALUACION!$A$7:$A$36,0))>C13,"✖ Fecha anterior posterior",IF(AND(ISNUMBER(V13),V13<C13),"✖ Próxima fecha anterior","✔ Correcto")))))))
E14: =IF(D14="","",IF(COUNTIF(EVALUACION!$A$7:$A$36,D14)=0,"",C14-INDEX(EVALUACION!$C$7:$C$36,MATCH(D14,EVALUACION!$A$7:$A$36,0)))) | F14: =IF(COUNTIF(ANTROPOMETRIA!$A$7:$A$36,A14)=0,"",INDEX(ANTROPOMETRIA!$D$7:$D$36,MATCH(A14,ANTROPOMETRIA!$A$7:$A$36,0))) | G14: =IF(OR(D14="",COUNTIF(ANTROPOMETRIA!$A$7:$A$36,D14)=0),"",INDEX(ANTROPOMETRIA!$D$7:$D$36,MATCH(D14,ANTROPOMETRIA!$A$7:$A$36,0))) | H14: =IF(AND(ISNUMBER(F14),ISNUMBER(G14)),F14-G14,"") | I14: =IF(AND(ISNUMBER(F14),ISNUMBER(G14),G14<>0),(F14-G14)/G14,"") | L14: =IF(A14="","",COUNTIFS(OBJETIVOS!$A$7:$A$36,A14,OBJETIVOS!$N$7:$N$36,"Cumplido")) | M14: =IF(A14="","",COUNTIFS(OBJETIVOS!$A$7:$A$36,A14,OBJETIVOS!$N$7:$N$36,"Activo")) | Y14: =IF(A14="","",IF(COUNTIFS(EVALUACION!$A$7:$A$36,A14,EVALUACION!$B$7:$B$36,B14)=0,"✖ Evaluación actual inconsistente",IF(D14="","▲ Sin evaluación anterior",IF(COUNTIF(EVALUACION!$A$7:$A$36,D14)=0,"✖ Evaluación anterior inexistente",IF(COUNTIFS(EVALUACION!$A$7:$A$36,D14,EVALUACION!$B$7:$B$36,B14)=0,"✖ Evaluación anterior de otro paciente",IF(INDEX(EVALUACION!$C$7:$C$36,MATCH(D14,EVALUACION!$A$7:$A$36,0))>C14,"✖ Fecha anterior posterior",IF(AND(ISNUMBER(V14),V14<C14),"✖ Próxima fecha anterior","✔ Correcto")))))))
E15: =IF(D15="","",IF(COUNTIF(EVALUACION!$A$7:$A$36,D15)=0,"",C15-INDEX(EVALUACION!$C$7:$C$36,MATCH(D15,EVALUACION!$A$7:$A$36,0)))) | F15: =IF(COUNTIF(ANTROPOMETRIA!$A$7:$A$36,A15)=0,"",INDEX(ANTROPOMETRIA!$D$7:$D$36,MATCH(A15,ANTROPOMETRIA!$A$7:$A$36,0))) | G15: =IF(OR(D15="",COUNTIF(ANTROPOMETRIA!$A$7:$A$36,D15)=0),"",INDEX(ANTROPOMETRIA!$D$7:$D$36,MATCH(D15,ANTROPOMETRIA!$A$7:$A$36,0))) | H15: =IF(AND(ISNUMBER(F15),ISNUMBER(G15)),F15-G15,"") | I15: =IF(AND(ISNUMBER(F15),ISNUMBER(G15),G15<>0),(F15-G15)/G15,"") | L15: =IF(A15="","",COUNTIFS(OBJETIVOS!$A$7:$A$36,A15,OBJETIVOS!$N$7:$N$36,"Cumplido")) | M15: =IF(A15="","",COUNTIFS(OBJETIVOS!$A$7:$A$36,A15,OBJETIVOS!$N$7:$N$36,"Activo")) | Y15: =IF(A15="","",IF(COUNTIFS(EVALUACION!$A$7:$A$36,A15,EVALUACION!$B$7:$B$36,B15)=0,"✖ Evaluación actual inconsistente",IF(D15="","▲ Sin evaluación anterior",IF(COUNTIF(EVALUACION!$A$7:$A$36,D15)=0,"✖ Evaluación anterior inexistente",IF(COUNTIFS(EVALUACION!$A$7:$A$36,D15,EVALUACION!$B$7:$B$36,B15)=0,"✖ Evaluación anterior de otro paciente",IF(INDEX(EVALUACION!$C$7:$C$36,MATCH(D15,EVALUACION!$A$7:$A$36,0))>C15,"✖ Fecha anterior posterior",IF(AND(ISNUMBER(V15),V15<C15),"✖ Próxima fecha anterior","✔ Correcto")))))))
E16: =IF(D16="","",IF(COUNTIF(EVALUACION!$A$7:$A$36,D16)=0,"",C16-INDEX(EVALUACION!$C$7:$C$36,MATCH(D16,EVALUACION!$A$7:$A$36,0)))) | F16: =IF(COUNTIF(ANTROPOMETRIA!$A$7:$A$36,A16)=0,"",INDEX(ANTROPOMETRIA!$D$7:$D$36,MATCH(A16,ANTROPOMETRIA!$A$7:$A$36,0))) | G16: =IF(OR(D16="",COUNTIF(ANTROPOMETRIA!$A$7:$A$36,D16)=0),"",INDEX(ANTROPOMETRIA!$D$7:$D$36,MATCH(D16,ANTROPOMETRIA!$A$7:$A$36,0))) | H16: =IF(AND(ISNUMBER(F16),ISNUMBER(G16)),F16-G16,"") | I16: =IF(AND(ISNUMBER(F16),ISNUMBER(G16),G16<>0),(F16-G16)/G16,"") | L16: =IF(A16="","",COUNTIFS(OBJETIVOS!$A$7:$A$36,A16,OBJETIVOS!$N$7:$N$36,"Cumplido")) | M16: =IF(A16="","",COUNTIFS(OBJETIVOS!$A$7:$A$36,A16,OBJETIVOS!$N$7:$N$36,"Activo")) | Y16: =IF(A16="","",IF(COUNTIFS(EVALUACION!$A$7:$A$36,A16,EVALUACION!$B$7:$B$36,B16)=0,"✖ Evaluación actual inconsistente",IF(D16="","▲ Sin evaluación anterior",IF(COUNTIF(EVALUACION!$A$7:$A$36,D16)=0,"✖ Evaluación anterior inexistente",IF(COUNTIFS(EVALUACION!$A$7:$A$36,D16,EVALUACION!$B$7:$B$36,B16)=0,"✖ Evaluación anterior de otro paciente",IF(INDEX(EVALUACION!$C$7:$C$36,MATCH(D16,EVALUACION!$A$7:$A$36,0))>C16,"✖ Fecha anterior posterior",IF(AND(ISNUMBER(V16),V16<C16),"✖ Próxima fecha anterior","✔ Correcto")))))))
E17: =IF(D17="","",IF(COUNTIF(EVALUACION!$A$7:$A$36,D17)=0,"",C17-INDEX(EVALUACION!$C$7:$C$36,MATCH(D17,EVALUACION!$A$7:$A$36,0)))) | F17: =IF(COUNTIF(ANTROPOMETRIA!$A$7:$A$36,A17)=0,"",INDEX(ANTROPOMETRIA!$D$7:$D$36,MATCH(A17,ANTROPOMETRIA!$A$7:$A$36,0))) | G17: =IF(OR(D17="",COUNTIF(ANTROPOMETRIA!$A$7:$A$36,D17)=0),"",INDEX(ANTROPOMETRIA!$D$7:$D$36,MATCH(D17,ANTROPOMETRIA!$A$7:$A$36,0))) | H17: =IF(AND(ISNUMBER(F17),ISNUMBER(G17)),F17-G17,"") | I17: =IF(AND(ISNUMBER(F17),ISNUMBER(G17),G17<>0),(F17-G17)/G17,"") | L17: =IF(A17="","",COUNTIFS(OBJETIVOS!$A$7:$A$36,A17,OBJETIVOS!$N$7:$N$36,"Cumplido")) | M17: =IF(A17="","",COUNTIFS(OBJETIVOS!$A$7:$A$36,A17,OBJETIVOS!$N$7:$N$36,"Activo")) | Y17: =IF(A17="","",IF(COUNTIFS(EVALUACION!$A$7:$A$36,A17,EVALUACION!$B$7:$B$36,B17)=0,"✖ Evaluación actual inconsistente",IF(D17="","▲ Sin evaluación anterior",IF(COUNTIF(EVALUACION!$A$7:$A$36,D17)=0,"✖ Evaluación anterior inexistente",IF(COUNTIFS(EVALUACION!$A$7:$A$36,D17,EVALUACION!$B$7:$B$36,B17)=0,"✖ Evaluación anterior de otro paciente",IF(INDEX(EVALUACION!$C$7:$C$36,MATCH(D17,EVALUACION!$A$7:$A$36,0))>C17,"✖ Fecha anterior posterior",IF(AND(ISNUMBER(V17),V17<C17),"✖ Próxima fecha anterior","✔ Correcto")))))))
E18: =IF(D18="","",IF(COUNTIF(EVALUACION!$A$7:$A$36,D18)=0,"",C18-INDEX(EVALUACION!$C$7:$C$36,MATCH(D18,EVALUACION!$A$7:$A$36,0)))) | F18: =IF(COUNTIF(ANTROPOMETRIA!$A$7:$A$36,A18)=0,"",INDEX(ANTROPOMETRIA!$D$7:$D$36,MATCH(A18,ANTROPOMETRIA!$A$7:$A$36,0))) | G18: =IF(OR(D18="",COUNTIF(ANTROPOMETRIA!$A$7:$A$36,D18)=0),"",INDEX(ANTROPOMETRIA!$D$7:$D$36,MATCH(D18,ANTROPOMETRIA!$A$7:$A$36,0))) | H18: =IF(AND(ISNUMBER(F18),ISNUMBER(G18)),F18-G18,"") | I18: =IF(AND(ISNUMBER(F18),ISNUMBER(G18),G18<>0),(F18-G18)/G18,"") | L18: =IF(A18="","",COUNTIFS(OBJETIVOS!$A$7:$A$36,A18,OBJETIVOS!$N$7:$N$36,"Cumplido")) | M18: =IF(A18="","",COUNTIFS(OBJETIVOS!$A$7:$A$36,A18,OBJETIVOS!$N$7:$N$36,"Activo")) | Y18: =IF(A18="","",IF(COUNTIFS(EVALUACION!$A$7:$A$36,A18,EVALUACION!$B$7:$B$36,B18)=0,"✖ Evaluación actual inconsistente",IF(D18="","▲ Sin evaluación anterior",IF(COUNTIF(EVALUACION!$A$7:$A$36,D18)=0,"✖ Evaluación anterior inexistente",IF(COUNTIFS(EVALUACION!$A$7:$A$36,D18,EVALUACION!$B$7:$B$36,B18)=0,"✖ Evaluación anterior de otro paciente",IF(INDEX(EVALUACION!$C$7:$C$36,MATCH(D18,EVALUACION!$A$7:$A$36,0))>C18,"✖ Fecha anterior posterior",IF(AND(ISNUMBER(V18),V18<C18),"✖ Próxima fecha anterior","✔ Correcto")))))))
E19: =IF(D19="","",IF(COUNTIF(EVALUACION!$A$7:$A$36,D19)=0,"",C19-INDEX(EVALUACION!$C$7:$C$36,MATCH(D19,EVALUACION!$A$7:$A$36,0)))) | F19: =IF(COUNTIF(ANTROPOMETRIA!$A$7:$A$36,A19)=0,"",INDEX(ANTROPOMETRIA!$D$7:$D$36,MATCH(A19,ANTROPOMETRIA!$A$7:$A$36,0))) | G19: =IF(OR(D19="",COUNTIF(ANTROPOMETRIA!$A$7:$A$36,D19)=0),"",INDEX(ANTROPOMETRIA!$D$7:$D$36,MATCH(D19,ANTROPOMETRIA!$A$7:$A$36,0))) | H19: =IF(AND(ISNUMBER(F19),ISNUMBER(G19)),F19-G19,"") | I19: =IF(AND(ISNUMBER(F19),ISNUMBER(G19),G19<>0),(F19-G19)/G19,"") | L19: =IF(A19="","",COUNTIFS(OBJETIVOS!$A$7:$A$36,A19,OBJETIVOS!$N$7:$N$36,"Cumplido")) | M19: =IF(A19="","",COUNTIFS(OBJETIVOS!$A$7:$A$36,A19,OBJETIVOS!$N$7:$N$36,"Activo")) | Y19: =IF(A19="","",IF(COUNTIFS(EVALUACION!$A$7:$A$36,A19,EVALUACION!$B$7:$B$36,B19)=0,"✖ Evaluación actual inconsistente",IF(D19="","▲ Sin evaluación anterior",IF(COUNTIF(EVALUACION!$A$7:$A$36,D19)=0,"✖ Evaluación anterior inexistente",IF(COUNTIFS(EVALUACION!$A$7:$A$36,D19,EVALUACION!$B$7:$B$36,B19)=0,"✖ Evaluación anterior de otro paciente",IF(INDEX(EVALUACION!$C$7:$C$36,MATCH(D19,EVALUACION!$A$7:$A$36,0))>C19,"✖ Fecha anterior posterior",IF(AND(ISNUMBER(V19),V19<C19),"✖ Próxima fecha anterior","✔ Correcto")))))))
... E36: =IF(D36="","",IF(COUNTIF(EVALUACION!$A$7:$A$36,D36)=0,"",C36-INDEX(EVALUACION!$C$7:$C$36,MATCH(D36,EVALUACION!$A$7:$A$36,0)))) | F36: =IF(COUNTIF(ANTROPOMETRIA!$A$7:$A$36,A36)=0,"",INDEX(ANTROPOMETRIA!$D$7:$D$36,MATCH(A36,ANTROPOMETRIA!$A$7:$A$36,0))) | G36: =IF(OR(D36="",COUNTIF(ANTROPOMETRIA!$A$7:$A$36,D36)=0),"",INDEX(ANTROPOMETRIA!$D$7:$D$36,MATCH(D36,ANTROPOMETRIA!$A$7:$A$36,0))) | H36: =IF(AND(ISNUMBER(F36),ISNUMBER(G36)),F36-G36,"") | I36: =IF(AND(ISNUMBER(F36),ISNUMBER(G36),G36<>0),(F36-G36)/G36,"") | L36: =IF(A36="","",COUNTIFS(OBJETIVOS!$A$7:$A$36,A36,OBJETIVOS!$N$7:$N$36,"Cumplido")) | M36: =IF(A36="","",COUNTIFS(OBJETIVOS!$A$7:$A$36,A36,OBJETIVOS!$N$7:$N$36,"Activo")) | Y36: =IF(A36="","",IF(COUNTIFS(EVALUACION!$A$7:$A$36,A36,EVALUACION!$B$7:$B$36,B36)=0,"✖ Evaluación actual inconsistente",IF(D36="","▲ Sin evaluación anterior",IF(COUNTIF(EVALUACION!$A$7:$A$36,D36)=0,"✖ Evaluación anterior inexistente",IF(COUNTIFS(EVALUACION!$A$7:$A$36,D36,EVALUACION!$B$7:$B$36,B36)=0,"✖ Evaluación anterior de otro paciente",IF(INDEX(EVALUACION!$C$7:$C$36,MATCH(D36,EVALUACION!$A$7:$A$36,0))>C36,"✖ Fecha anterior posterior",IF(AND(ISNUMBER(V36),V36<C36),"✖ Próxima fecha anterior","✔ Correcto")))))))

Sheet RESUMEN
A1: RESUMEN · Selección por PatientID y EvaluationID
A2: ◀ INICIO | B2: RESUMEN | C2: CONFIG | D2: PRUEBAS
A3: ▲ Resumen clínico imprimible; no constituye diagnóstico médico ni sustituye el juicio profesional.
A5: Selección
A6: PatientID | B6: P-FICT-B | C6: Seleccione paciente
A7: EvaluationID | B7: E-B-02 | C7: Seleccione evaluación
A8: Control | B8: =CALCULOS!B9 -> ✔ Consistente | C8: La evaluación debe pertenecer al paciente
A10: Identificación y evaluación
A11: PatientID | B11: =CALCULOS!B7 -> P-FICT-B
A12: Iniciales | B12: =CALCULOS!B21 -> BFB
A13: Nombre opcional | B13: =CALCULOS!B22 -> Oculto por minimización
A14: Edad | B14: =CALCULOS!B23 -> 40
A15: Fecha | B15: =IF(CALCULOS!B24="","",TEXT(CALCULOS!B24,"yyyy-mm-dd")) -> 2026-07-01
A16: Tipo evaluación | B16: =CALCULOS!B25 -> Control
A17: Profesional | B17: =CALCULOS!B26 -> PROF-DEMO
A18: Motivo | B18: =CALCULOS!B27 -> Control longitudinal ficticio
A20: Antropometría
A21: Peso | B21: =CALCULOS!B31 -> 87
A22: Estatura | B22: =CALCULOS!B32 -> 180
A23: IMC | B23: =CALCULOS!B33 -> 26.851852
A24: Cambio de peso | B24: =CALCULOS!B34 -> -5
A25: Cintura | B25: =CALCULOS!B35 -> 96
A26: % grasa | B26: =CALCULOS!B36 -> 24
A28: Bioquímica y alimentación
A29: Resultados | B29: =CALCULOS!B41 -> 0
A30: Bajos | B30: =CALCULOS!B42 -> 0
A31: Altos | B31: =CALCULOS!B43 -> 0
A32: Sin rango | B32: =CALCULOS!B44 -> 0
A33: Señalado 1 | B33: =CALCULOS!B45
A34: Señalado 2 | B34: =CALCULOS!B46
A35: Señalado 3 | B35: =CALCULOS!B47
A36: Energía R24H | B36: =CALCULOS!B48 -> 600
A37: Proteínas | B37: =CALCULOS!B49 -> 30
A38: Carbohidratos | B38: =CALCULOS!B50 -> 65
A39: Grasas | B39: =CALCULOS!B51 -> 20
A40: Fibra | B40: =CALCULOS!B52 -> 9
A41: Tiempos comida | B41: =CALCULOS!B53 -> 1
A43: Diagnóstico y plan
A44: Diagnósticos revisados | B44: =CALCULOS!B62 -> 0
A45: Objetivos activos | B45: =CALCULOS!B63 -> 1
A46: Objetivos cumplidos | B46: =CALCULOS!B64 -> 0
A47: Intervenciones activas | B47: =CALCULOS!B65 -> 0
A48: Próxima acción | B48: =CALCULOS!B66 -> Registrar próxima semana
A49: Próxima fecha | B49: =IF(CALCULOS!B67="","",TEXT(CALCULOS!B67,"yyyy-mm-dd")) -> 2026-08-01
A50: Estado evaluación | B50: =CALCULOS!B68 -> Completo
A52: =IF(COUNTA(CALCULOS!B74:B83)<2,"▲ No hay datos suficientes para gráficos longitudinales","✔ Gráficos filtrados por PatientID; no mezclan pacientes") -> ✔ Gráficos filtrados por PatientID; no mezclan pacientes

Sheet CALCULOS
A1: CÁLCULOS · Selección, agregados, controles y datos de gráficos
A2: ◀ INICIO | B2: RESUMEN | C2: CONFIG | D2: PRUEBAS
A3: Hoja visible y auditable. Justificada para evitar fórmulas opacas y mezclar pacientes.
A5: Selección y controles globales
A6: Elemento | B6: Resultado | C6: Nota
A7: PatientID seleccionado | B7: =RESUMEN!B6 -> P-FICT-B | C7: Desde RESUMEN
A8: EvaluationID seleccionado | B8: =RESUMEN!B7 -> E-B-02 | C8: Desde RESUMEN
A9: Consistencia selección | B9: =IF(OR(B7="",B8=""),"▲ Selección incompleta",IF(COUNTIFS(EVALUACION!$A$7:$A$3006,B8,EVALUACION!$B$7:$B$3006,B7)=1,"✔ Consistente","✖ EvaluationID no pertenece al PatientID")) -> ✔ Consistente | C9: Mismo paciente
A10: Pacientes registrados | B10: =COUNTA(PACIENTES!$A$7:$A$1006) -> 5 | C10: PatientID no vacío
A11: Evaluaciones registradas | B11: =COUNTA(EVALUACION!$A$7:$A$3006) -> 6 | C11: EvaluationID no vacío
A12: Última fecha registrada | B12: =IF(COUNT(EVALUACION!$C$7:$C$3006)=0,"",MAX(EVALUACION!$C$7:$C$3006)) -> 46208 | C12: Máximo de evaluaciones
A13: PatientID duplicados | B13: =SUMPRODUCT((PACIENTES!$A$7:$A$1006<>"")*(COUNTIF(PACIENTES!$A$7:$A$1006,PACIENTES!$A$7:$A$1006)>1)) -> 0 | C13: Debe ser 0
A14: EvaluationID duplicados | B14: =SUMPRODUCT((EVALUACION!$A$7:$A$3006<>"")*(COUNTIF(EVALUACION!$A$7:$A$3006,EVALUACION!$A$7:$A$3006)>1)) -> 0 | C14: Debe ser 0
A15: Evaluaciones huérfanas | B15: =COUNTIF(EVALUACION!$U$7:$U$3006,"✖ PatientID inexistente") -> 0 | C15: Debe ser 0
A16: Registros ficticios | B16: =COUNTA(PACIENTES!$A$7:$A$1006) -> 5 | C16: Casos de prueba
A19: Datos seleccionados
A20: Elemento | B20: Resultado | C20: Nota
A21: Iniciales | B21: =IF(COUNTIF(PACIENTES!$A$7:$A$1006,$B$7)=0,"",INDEX(PACIENTES!$D$7:$D$1006,MATCH($B$7,PACIENTES!$A$7:$A$1006,0))) -> BFB | C21: Paciente
A22: Nombre directo | B22: =IF(CONFIG!$B$30="Sí",IF(COUNTIF(PACIENTES!$A$7:$A$1006,$B$7)=0,"",INDEX(PACIENTES!$E$7:$E$1006,MATCH($B$7,PACIENTES!$A$7:$A$1006,0))&" "&INDEX(PACIENTES!$F$7:$F$1006,MATCH($B$7,PACIENTES!$A$7:$A$1006,0))),"Oculto por minimización") -> Oculto por minimización | C22: Según interruptor
A23: Edad | B23: =IF(COUNTIF(PACIENTES!$A$7:$A$1006,$B$7)=0,"",INDEX(PACIENTES!$H$7:$H$1006,MATCH($B$7,PACIENTES!$A$7:$A$1006,0))) -> 40 | C23: Paciente
A24: Fecha evaluación | B24: =IF(COUNTIF(EVALUACION!$A$7:$A$3006,$B$8)=0,"",INDEX(EVALUACION!$C$7:$C$3006,MATCH($B$8,EVALUACION!$A$7:$A$3006,0))) -> 46204 | C24: Evaluación
A25: Tipo evaluación | B25: =IF(COUNTIF(EVALUACION!$A$7:$A$3006,$B$8)=0,"",INDEX(EVALUACION!$E$7:$E$3006,MATCH($B$8,EVALUACION!$A$7:$A$3006,0))) -> Control | C25: Evaluación
A26: Profesional | B26: =IF(COUNTIF(EVALUACION!$A$7:$A$3006,$B$8)=0,"",INDEX(EVALUACION!$I$7:$I$3006,MATCH($B$8,EVALUACION!$A$7:$A$3006,0))) -> PROF-DEMO | C26: Evaluación
A27: Motivo consulta | B27: =IF(COUNTIF(EVALUACION!$A$7:$A$3006,$B$8)=0,"",INDEX(EVALUACION!$G$7:$G$3006,MATCH($B$8,EVALUACION!$A$7:$A$3006,0))) -> Control longitudinal ficticio | C27: Evaluación
A29: Antropometría seleccionada
A30: Elemento | B30: Resultado | C30: Unidad
A31: Peso | B31: =IF(COUNTIF(ANTROPOMETRIA!$A$7:$A$3006,$B$8)=0,"",INDEX(ANTROPOMETRIA!$D$7:$D$3006,MATCH($B$8,ANTROPOMETRIA!$A$7:$A$3006,0))) -> 87 | C31: kg
A32: Estatura | B32: =IF(COUNTIF(ANTROPOMETRIA!$A$7:$A$3006,$B$8)=0,"",INDEX(ANTROPOMETRIA!$E$7:$E$3006,MATCH($B$8,ANTROPOMETRIA!$A$7:$A$3006,0))) -> 180 | C32: cm
A33: IMC | B33: =IF(COUNTIF(ANTROPOMETRIA!$A$7:$A$3006,$B$8)=0,"",INDEX(ANTROPOMETRIA!$F$7:$F$3006,MATCH($B$8,ANTROPOMETRIA!$A$7:$A$3006,0))) -> 26.851852 | C33: kg/m²
A34: Cambio peso | B34: =IF(COUNTIF(ANTROPOMETRIA!$A$7:$A$3006,$B$8)=0,"",INDEX(ANTROPOMETRIA!$J$7:$J$3006,MATCH($B$8,ANTROPOMETRIA!$A$7:$A$3006,0))) -> -5 | C34: kg
A35: Cintura | B35: =IF(COUNTIF(ANTROPOMETRIA!$A$7:$A$3006,$B$8)=0,"",INDEX(ANTROPOMETRIA!$N$7:$N$3006,MATCH($B$8,ANTROPOMETRIA!$A$7:$A$3006,0))) -> 96 | C35: cm
A36: % grasa | B36: =IF(COUNTIF(ANTROPOMETRIA!$A$7:$A$3006,$B$8)=0,"",INDEX(ANTROPOMETRIA!$R$7:$R$3006,MATCH($B$8,ANTROPOMETRIA!$A$7:$A$3006,0))) -> 24 | C36: %
A39: Bioquímica y recordatorio 24 h
A40: Elemento | B40: Resultado | C40: Nota
A41: Resultados bioquímicos | B41: =IF(CONFIG!$B$23="No","No aplica",COUNTIF(BIOQUIMICA!$A$7:$A$5006,$B$8)) -> 0 | C41: Total
A42: Bajos | B42: =IF(CONFIG!$B$23="No","No aplica",COUNTIFS(BIOQUIMICA!$A$7:$A$5006,$B$8,BIOQUIMICA!$K$7:$K$5006,"Bajo")) -> 0 | C42: Conteo
A43: Altos | B43: =IF(CONFIG!$B$23="No","No aplica",COUNTIFS(BIOQUIMICA!$A$7:$A$5006,$B$8,BIOQUIMICA!$K$7:$K$5006,"Alto")) -> 0 | C43: Conteo
A44: No evaluables | B44: =IF(CONFIG!$B$23="No","No aplica",COUNTIFS(BIOQUIMICA!$A$7:$A$5006,$B$8,BIOQUIMICA!$K$7:$K$5006,"No evaluable")) -> 0 | C44: Conteo
A45: Resultado señalado 1 | B45: =IF(CONFIG!$B$23="No","No aplica",IF(COUNTIF(BIOQUIMICA!$W$7:$W$5006,$B$8&"|FLAG|1")=0,"",INDEX(BIOQUIMICA!$D$7:$D$5006,MATCH($B$8&"|FLAG|1",BIOQUIMICA!$W$7:$W$5006,0))&" · "&INDEX(BIOQUIMICA!$K$7:$K$5006,MATCH($B$8&"|FLAG|1",BIOQUIMICA!$W$7:$W$5006,0)))) | C45: Primero
A46: Resultado señalado 2 | B46: =IF(CONFIG!$B$23="No","No aplica",IF(COUNTIF(BIOQUIMICA!$W$7:$W$5006,$B$8&"|FLAG|2")=0,"",INDEX(BIOQUIMICA!$D$7:$D$5006,MATCH($B$8&"|FLAG|2",BIOQUIMICA!$W$7:$W$5006,0))&" · "&INDEX(BIOQUIMICA!$K$7:$K$5006,MATCH($B$8&"|FLAG|2",BIOQUIMICA!$W$7:$W$5006,0)))) | C46: Segundo
A47: Resultado señalado 3 | B47: =IF(CONFIG!$B$23="No","No aplica",IF(COUNTIF(BIOQUIMICA!$W$7:$W$5006,$B$8&"|FLAG|3")=0,"",INDEX(BIOQUIMICA!$D$7:$D$5006,MATCH($B$8&"|FLAG|3",BIOQUIMICA!$W$7:$W$5006,0))&" · "&INDEX(BIOQUIMICA!$K$7:$K$5006,MATCH($B$8&"|FLAG|3",BIOQUIMICA!$W$7:$W$5006,0)))) | C47: Tercero
A48: Energía R24H | B48: =IF(CONFIG!$B$24="No","No aplica",SUMIFS(ALIMENTACION!$L$112:$L$5111,ALIMENTACION!$A$112:$A$5111,$B$8)) -> 600 | C48: kcal
A49: Proteínas R24H | B49: =IF(CONFIG!$B$24="No","No aplica",SUMIFS(ALIMENTACION!$M$112:$M$5111,ALIMENTACION!$A$112:$A$5111,$B$8)) -> 30 | C49: g
A50: Carbohidratos R24H | B50: =IF(CONFIG!$B$24="No","No aplica",SUMIFS(ALIMENTACION!$N$112:$N$5111,ALIMENTACION!$A$112:$A$5111,$B$8)) -> 65 | C50: g
A51: Grasas R24H | B51: =IF(CONFIG!$B$24="No","No aplica",SUMIFS(ALIMENTACION!$O$112:$O$5111,ALIMENTACION!$A$112:$A$5111,$B$8)) -> 20 | C51: g
A52: Fibra R24H | B52: =IF(CONFIG!$B$24="No","No aplica",SUMIFS(ALIMENTACION!$P$112:$P$5111,ALIMENTACION!$A$112:$A$5111,$B$8)) -> 9 | C52: g
A53: Tiempos comida | B53: =IF(CONFIG!$B$24="No","No aplica",COUNTIF(ALIMENTACION!$A$112:$A$5111,$B$8)) -> 1 | C53: conteo
A54: Primera comida | B54: =IF(OR(CONFIG!$B$24="No",COUNTIF(ALIMENTACION!$A$112:$A$5111,$B$8)=0),"",SUMPRODUCT(MIN(IF(ALIMENTACION!$A$112:$A$5111=$B$8,ALIMENTACION!$F$112:$F$5111)))) -> #VALUE! | C54: hora
A55: Última comida | B55: =IF(OR(CONFIG!$B$24="No",COUNTIF(ALIMENTACION!$A$112:$A$5111,$B$8)=0),"",SUMPRODUCT(MAX(IF(ALIMENTACION!$A$112:$A$5111=$B$8,ALIMENTACION!$F$112:$F$5111)))) -> #VALUE! | C55: hora
A56: Fármacos | B56: =IF(CONFIG!$B$26="No","No aplica",COUNTIF(FARMACOS!$A$7:$A$3006,$B$8)) -> 0 | C56: conteo
A57: Suplementos | B57: =IF(CONFIG!$B$27="No","No aplica",COUNTIF(FARMACOS!$A$312:$A$3311,$B$8)) -> 0 | C57: conteo
A60: Diagnóstico, objetivos e intervención
A61: Elemento | B61: Resultado | C61: Nota
A62: Diagnósticos revisados | B62: =COUNTIFS(DIAGNOSTICO!$A$7:$A$3006,$B$8,DIAGNOSTICO!$K$7:$K$3006,"Revisado") -> 0 | C62: Conteo
A63: Objetivos activos | B63: =COUNTIFS(OBJETIVOS!$A$7:$A$3006,$B$8,OBJETIVOS!$N$7:$N$3006,"Activo") -> 1 | C63: Conteo
A64: Objetivos cumplidos | B64: =COUNTIFS(OBJETIVOS!$A$7:$A$3006,$B$8,OBJETIVOS!$N$7:$N$3006,"Cumplido") -> 0 | C64: Conteo
A65: Intervenciones activas | B65: =COUNTIFS(INTERVENCION!$A$7:$A$3006,$B$8,INTERVENCION!$L$7:$L$3006,"Activo") -> 0 | C65: Conteo
A66: Próxima acción | B66: =IF(COUNTIF(SEGUIMIENTO!$A$7:$A$3006,$B$8)=0,"",INDEX(SEGUIMIENTO!$U$7:$U$3006,MATCH($B$8,SEGUIMIENTO!$A$7:$A$3006,0))) -> Registrar próxima semana | C66: Seguimiento
A67: Próxima fecha | B67: =IF(COUNTIF(SEGUIMIENTO!$A$7:$A$3006,$B$8)=0,"",INDEX(SEGUIMIENTO!$V$7:$V$3006,MATCH($B$8,SEGUIMIENTO!$A$7:$A$3006,0))) -> 46235 | C67: Seguimiento
A68: Estado evaluación | B68: =IF(COUNTIF(EVALUACION!$A$7:$A$3006,$B$8)=0,"",INDEX(EVALUACION!$J$7:$J$3006,MATCH($B$8,EVALUACION!$A$7:$A$3006,0))) -> Completo | C68: Selección
A72: Datos auxiliares de gráficos por PatientID
A73: Rango | B73: Fecha | C73: Peso | D73: IMC | E73: Cumplimiento objetivos | F73: Evaluaciones | G73: EvaluationID | H73: Fecha | I73: IMC | J73: Fecha | K73: Cumplimiento | L73: Fecha | M73: Evaluaciones
A74: 1 | B74: =IF(G74="","",SUMIFS(EVALUACION!$C$7:$C$3006,EVALUACION!$B$7:$B$3006,$B$7,EVALUACION!$S$7:$S$3006,A74)) -> 46143 | C74: =IF(G74="","",SUMIFS(ANTROPOMETRIA!$D$7:$D$3006,ANTROPOMETRIA!$B$7:$B$3006,$B$7,ANTROPOMETRIA!$AJ$7:$AJ$3006,A74)) -> 90 | D74: =IF(G74="","",SUMIFS(ANTROPOMETRIA!$F$7:$F$3006,ANTROPOMETRIA!$B$7:$B$3006,$B$7,ANTROPOMETRIA!$AJ$7:$AJ$3006,A74)) -> 27.777778 | E74: =IF(G74="","",IF(COUNTIF(OBJETIVOS!$A$7:$A$3006,G74)=0,0,COUNTIFS(OBJETIVOS!$A$7:$A$3006,G74,OBJETIVOS!$N$7:$N$3006,"Cumplido")/COUNTIF(OBJETIVOS!$A$7:$A$3006,G74))) -> 1 | F74: =IF(G74="","",1) -> 1 | G74: =IF(CONFIG!$B$29="No","",IF(SUMPRODUCT((EVALUACION!$B$7:$B$3006=$B$7)*(EVALUACION!$S$7:$S$3006=A74))=0,"",INDEX(EVALUACION!$A$7:$A$3006,SUMPRODUCT((EVALUACION!$B$7:$B$3006=$B$7)*(EVALUACION!$S$7:$S$3006=A74)*(ROW(EVALUACION!$A$7:$A$3006)-ROW(EVALUACION!$A$7)+1))))) -> E-B-01 | H74: =IF(B74="","",TEXT(B74,"yyyy-mm-dd")) -> 2026-05-01 | I74: =IF(D74="","",D74) -> 27.777778 | J74: =IF(B74="","",TEXT(B74,"yyyy-mm-dd")) -> 2026-05-01 | K74: =IF(E74="","",E74) -> 1 | L74: =IF(B74="","",TEXT(B74,"yyyy-mm-dd")) -> 2026-05-01 | M74: =IF(F74="","",F74) -> 1
A75: 2 | B75: =IF(G75="","",SUMIFS(EVALUACION!$C$7:$C$3006,EVALUACION!$B$7:$B$3006,$B$7,EVALUACION!$S$7:$S$3006,A75)) -> 46204 | C75: =IF(G75="","",SUMIFS(ANTROPOMETRIA!$D$7:$D$3006,ANTROPOMETRIA!$B$7:$B$3006,$B$7,ANTROPOMETRIA!$AJ$7:$AJ$3006,A75)) -> 87 | D75: =IF(G75="","",SUMIFS(ANTROPOMETRIA!$F$7:$F$3006,ANTROPOMETRIA!$B$7:$B$3006,$B$7,ANTROPOMETRIA!$AJ$7:$AJ$3006,A75)) -> 26.851852 | E75: =IF(G75="","",IF(COUNTIF(OBJETIVOS!$A$7:$A$3006,G75)=0,0,COUNTIFS(OBJETIVOS!$A$7:$A$3006,G75,OBJETIVOS!$N$7:$N$3006,"Cumplido")/COUNTIF(OBJETIVOS!$A$7:$A$3006,G75))) -> 0 | F75: =IF(G75="","",1) -> 1 | G75: =IF(CONFIG!$B$29="No","",IF(SUMPRODUCT((EVALUACION!$B$7:$B$3006=$B$7)*(EVALUACION!$S$7:$S$3006=A75))=0,"",INDEX(EVALUACION!$A$7:$A$3006,SUMPRODUCT((EVALUACION!$B$7:$B$3006=$B$7)*(EVALUACION!$S$7:$S$3006=A75)*(ROW(EVALUACION!$A$7:$A$3006)-ROW(EVALUACION!$A$7)+1))))) -> E-B-02 | H75: =IF(B75="","",TEXT(B75,"yyyy-mm-dd")) -> 2026-07-01 | I75: =IF(D75="","",D75) -> 26.851852 | J75: =IF(B75="","",TEXT(B75,"yyyy-mm-dd")) -> 2026-07-01 | K75: =IF(E75="","",E75) -> 0 | L75: =IF(B75="","",TEXT(B75,"yyyy-mm-dd")) -> 2026-07-01 | M75: =IF(F75="","",F75) -> 1
A76: 3 | B76: =IF(G76="","",SUMIFS(EVALUACION!$C$7:$C$3006,EVALUACION!$B$7:$B$3006,$B$7,EVALUACION!$S$7:$S$3006,A76)) | C76: =IF(G76="","",SUMIFS(ANTROPOMETRIA!$D$7:$D$3006,ANTROPOMETRIA!$B$7:$B$3006,$B$7,ANTROPOMETRIA!$AJ$7:$AJ$3006,A76)) | D76: =IF(G76="","",SUMIFS(ANTROPOMETRIA!$F$7:$F$3006,ANTROPOMETRIA!$B$7:$B$3006,$B$7,ANTROPOMETRIA!$AJ$7:$AJ$3006,A76)) | E76: =IF(G76="","",IF(COUNTIF(OBJETIVOS!$A$7:$A$3006,G76)=0,0,COUNTIFS(OBJETIVOS!$A$7:$A$3006,G76,OBJETIVOS!$N$7:$N$3006,"Cumplido")/COUNTIF(OBJETIVOS!$A$7:$A$3006,G76))) | F76: =IF(G76="","",1) | G76: =IF(CONFIG!$B$29="No","",IF(SUMPRODUCT((EVALUACION!$B$7:$B$3006=$B$7)*(EVALUACION!$S$7:$S$3006=A76))=0,"",INDEX(EVALUACION!$A$7:$A$3006,SUMPRODUCT((EVALUACION!$B$7:$B$3006=$B$7)*(EVALUACION!$S$7:$S$3006=A76)*(ROW(EVALUACION!$A$7:$A$3006)-ROW(EVALUACION!$A$7)+1))))) | H76: =IF(B76="","",TEXT(B76,"yyyy-mm-dd")) | I76: =IF(D76="","",D76) | J76: =IF(B76="","",TEXT(B76,"yyyy-mm-dd")) | K76: =IF(E76="","",E76) | L76: =IF(B76="","",TEXT(B76,"yyyy-mm-dd")) | M76: =IF(F76="","",F76)
A77: 4 | B77: =IF(G77="","",SUMIFS(EVALUACION!$C$7:$C$3006,EVALUACION!$B$7:$B$3006,$B$7,EVALUACION!$S$7:$S$3006,A77)) | C77: =IF(G77="","",SUMIFS(ANTROPOMETRIA!$D$7:$D$3006,ANTROPOMETRIA!$B$7:$B$3006,$B$7,ANTROPOMETRIA!$AJ$7:$AJ$3006,A77)) | D77: =IF(G77="","",SUMIFS(ANTROPOMETRIA!$F$7:$F$3006,ANTROPOMETRIA!$B$7:$B$3006,$B$7,ANTROPOMETRIA!$AJ$7:$AJ$3006,A77)) | E77: =IF(G77="","",IF(COUNTIF(OBJETIVOS!$A$7:$A$3006,G77)=0,0,COUNTIFS(OBJETIVOS!$A$7:$A$3006,G77,OBJETIVOS!$N$7:$N$3006,"Cumplido")/COUNTIF(OBJETIVOS!$A$7:$A$3006,G77))) | F77: =IF(G77="","",1) | G77: =IF(CONFIG!$B$29="No","",IF(SUMPRODUCT((EVALUACION!$B$7:$B$3006=$B$7)*(EVALUACION!$S$7:$S$3006=A77))=0,"",INDEX(EVALUACION!$A$7:$A$3006,SUMPRODUCT((EVALUACION!$B$7:$B$3006=$B$7)*(EVALUACION!$S$7:$S$3006=A77)*(ROW(EVALUACION!$A$7:$A$3006)-ROW(EVALUACION!$A$7)+1))))) | H77: =IF(B77="","",TEXT(B77,"yyyy-mm-dd")) | I77: =IF(D77="","",D77) | J77: =IF(B77="","",TEXT(B77,"yyyy-mm-dd")) | K77: =IF(E77="","",E77) | L77: =IF(B77="","",TEXT(B77,"yyyy-mm-dd")) | M77: =IF(F77="","",F77)
A78: 5 | B78: =IF(G78="","",SUMIFS(EVALUACION!$C$7:$C$3006,EVALUACION!$B$7:$B$3006,$B$7,EVALUACION!$S$7:$S$3006,A78)) | C78: =IF(G78="","",SUMIFS(ANTROPOMETRIA!$D$7:$D$3006,ANTROPOMETRIA!$B$7:$B$3006,$B$7,ANTROPOMETRIA!$AJ$7:$AJ$3006,A78)) | D78: =IF(G78="","",SUMIFS(ANTROPOMETRIA!$F$7:$F$3006,ANTROPOMETRIA!$B$7:$B$3006,$B$7,ANTROPOMETRIA!$AJ$7:$AJ$3006,A78)) | E78: =IF(G78="","",IF(COUNTIF(OBJETIVOS!$A$7:$A$3006,G78)=0,0,COUNTIFS(OBJETIVOS!$A$7:$A$3006,G78,OBJETIVOS!$N$7:$N$3006,"Cumplido")/COUNTIF(OBJETIVOS!$A$7:$A$3006,G78))) | F78: =IF(G78="","",1) | G78: =IF(CONFIG!$B$29="No","",IF(SUMPRODUCT((EVALUACION!$B$7:$B$3006=$B$7)*(EVALUACION!$S$7:$S$3006=A78))=0,"",INDEX(EVALUACION!$A$7:$A$3006,SUMPRODUCT((EVALUACION!$B$7:$B$3006=$B$7)*(EVALUACION!$S$7:$S$3006=A78)*(ROW(EVALUACION!$A$7:$A$3006)-ROW(EVALUACION!$A$7)+1))))) | H78: =IF(B78="","",TEXT(B78,"yyyy-mm-dd")) | I78: =IF(D78="","",D78) | J78: =IF(B78="","",TEXT(B78,"yyyy-mm-dd")) | K78: =IF(E78="","",E78) | L78: =IF(B78="","",TEXT(B78,"yyyy-mm-dd")) | M78: =IF(F78="","",F78)
A79: 6 | B79: =IF(G79="","",SUMIFS(EVALUACION!$C$7:$C$3006,EVALUACION!$B$7:$B$3006,$B$7,EVALUACION!$S$7:$S$3006,A79)) | C79: =IF(G79="","",SUMIFS(ANTROPOMETRIA!$D$7:$D$3006,ANTROPOMETRIA!$B$7:$B$3006,$B$7,ANTROPOMETRIA!$AJ$7:$AJ$3006,A79)) | D79: =IF(G79="","",SUMIFS(ANTROPOMETRIA!$F$7:$F$3006,ANTROPOMETRIA!$B$7:$B$3006,$B$7,ANTROPOMETRIA!$AJ$7:$AJ$3006,A79)) | E79: =IF(G79="","",IF(COUNTIF(OBJETIVOS!$A$7:$A$3006,G79)=0,0,COUNTIFS(OBJETIVOS!$A$7:$A$3006,G79,OBJETIVOS!$N$7:$N$3006,"Cumplido")/COUNTIF(OBJETIVOS!$A$7:$A$3006,G79))) | F79: =IF(G79="","",1) | G79: =IF(CONFIG!$B$29="No","",IF(SUMPRODUCT((EVALUACION!$B$7:$B$3006=$B$7)*(EVALUACION!$S$7:$S$3006=A79))=0,"",INDEX(EVALUACION!$A$7:$A$3006,SUMPRODUCT((EVALUACION!$B$7:$B$3006=$B$7)*(EVALUACION!$S$7:$S$3006=A79)*(ROW(EVALUACION!$A$7:$A$3006)-ROW(EVALUACION!$A$7)+1))))) | H79: =IF(B79="","",TEXT(B79,"yyyy-mm-dd")) | I79: =IF(D79="","",D79) | J79: =IF(B79="","",TEXT(B79,"yyyy-mm-dd")) | K79: =IF(E79="","",E79) | L79: =IF(B79="","",TEXT(B79,"yyyy-mm-dd")) | M79: =IF(F79="","",F79)
A80: 7 | B80: =IF(G80="","",SUMIFS(EVALUACION!$C$7:$C$3006,EVALUACION!$B$7:$B$3006,$B$7,EVALUACION!$S$7:$S$3006,A80)) | C80: =IF(G80="","",SUMIFS(ANTROPOMETRIA!$D$7:$D$3006,ANTROPOMETRIA!$B$7:$B$3006,$B$7,ANTROPOMETRIA!$AJ$7:$AJ$3006,A80)) | D80: =IF(G80="","",SUMIFS(ANTROPOMETRIA!$F$7:$F$3006,ANTROPOMETRIA!$B$7:$B$3006,$B$7,ANTROPOMETRIA!$AJ$7:$AJ$3006,A80)) | E80: =IF(G80="","",IF(COUNTIF(OBJETIVOS!$A$7:$A$3006,G80)=0,0,COUNTIFS(OBJETIVOS!$A$7:$A$3006,G80,OBJETIVOS!$N$7:$N$3006,"Cumplido")/COUNTIF(OBJETIVOS!$A$7:$A$3006,G80))) | F80: =IF(G80="","",1) | G80: =IF(CONFIG!$B$29="No","",IF(SUMPRODUCT((EVALUACION!$B$7:$B$3006=$B$7)*(EVALUACION!$S$7:$S$3006=A80))=0,"",INDEX(EVALUACION!$A$7:$A$3006,SUMPRODUCT((EVALUACION!$B$7:$B$3006=$B$7)*(EVALUACION!$S$7:$S$3006=A80)*(ROW(EVALUACION!$A$7:$A$3006)-ROW(EVALUACION!$A$7)+1))))) | H80: =IF(B80="","",TEXT(B80,"yyyy-mm-dd")) | I80: =IF(D80="","",D80) | J80: =IF(B80="","",TEXT(B80,"yyyy-mm-dd")) | K80: =IF(E80="","",E80) | L80: =IF(B80="","",TEXT(B80,"yyyy-mm-dd")) | M80: =IF(F80="","",F80)
A81: 8 | B81: =IF(G81="","",SUMIFS(EVALUACION!$C$7:$C$3006,EVALUACION!$B$7:$B$3006,$B$7,EVALUACION!$S$7:$S$3006,A81)) | C81: =IF(G81="","",SUMIFS(ANTROPOMETRIA!$D$7:$D$3006,ANTROPOMETRIA!$B$7:$B$3006,$B$7,ANTROPOMETRIA!$AJ$7:$AJ$3006,A81)) | D81: =IF(G81="","",SUMIFS(ANTROPOMETRIA!$F$7:$F$3006,ANTROPOMETRIA!$B$7:$B$3006,$B$7,ANTROPOMETRIA!$AJ$7:$AJ$3006,A81)) | E81: =IF(G81="","",IF(COUNTIF(OBJETIVOS!$A$7:$A$3006,G81)=0,0,COUNTIFS(OBJETIVOS!$A$7:$A$3006,G81,OBJETIVOS!$N$7:$N$3006,"Cumplido")/COUNTIF(OBJETIVOS!$A$7:$A$3006,G81))) | F81: =IF(G81="","",1) | G81: =IF(CONFIG!$B$29="No","",IF(SUMPRODUCT((EVALUACION!$B$7:$B$3006=$B$7)*(EVALUACION!$S$7:$S$3006=A81))=0,"",INDEX(EVALUACION!$A$7:$A$3006,SUMPRODUCT((EVALUACION!$B$7:$B$3006=$B$7)*(EVALUACION!$S$7:$S$3006=A81)*(ROW(EVALUACION!$A$7:$A$3006)-ROW(EVALUACION!$A$7)+1))))) | H81: =IF(B81="","",TEXT(B81,"yyyy-mm-dd")) | I81: =IF(D81="","",D81) | J81: =IF(B81="","",TEXT(B81,"yyyy-mm-dd")) | K81: =IF(E81="","",E81) | L81: =IF(B81="","",TEXT(B81,"yyyy-mm-dd")) | M81: =IF(F81="","",F81)
A82: 9 | B82: =IF(G82="","",SUMIFS(EVALUACION!$C$7:$C$3006,EVALUACION!$B$7:$B$3006,$B$7,EVALUACION!$S$7:$S$3006,A82)) | C82: =IF(G82="","",SUMIFS(ANTROPOMETRIA!$D$7:$D$3006,ANTROPOMETRIA!$B$7:$B$3006,$B$7,ANTROPOMETRIA!$AJ$7:$AJ$3006,A82)) | D82: =IF(G82="","",SUMIFS(ANTROPOMETRIA!$F$7:$F$3006,ANTROPOMETRIA!$B$7:$B$3006,$B$7,ANTROPOMETRIA!$AJ$7:$AJ$3006,A82)) | E82: =IF(G82="","",IF(COUNTIF(OBJETIVOS!$A$7:$A$3006,G82)=0,0,COUNTIFS(OBJETIVOS!$A$7:$A$3006,G82,OBJETIVOS!$N$7:$N$3006,"Cumplido")/COUNTIF(OBJETIVOS!$A$7:$A$3006,G82))) | F82: =IF(G82="","",1) | G82: =IF(CONFIG!$B$29="No","",IF(SUMPRODUCT((EVALUACION!$B$7:$B$3006=$B$7)*(EVALUACION!$S$7:$S$3006=A82))=0,"",INDEX(EVALUACION!$A$7:$A$3006,SUMPRODUCT((EVALUACION!$B$7:$B$3006=$B$7)*(EVALUACION!$S$7:$S$3006=A82)*(ROW(EVALUACION!$A$7:$A$3006)-ROW(EVALUACION!$A$7)+1))))) | H82: =IF(B82="","",TEXT(B82,"yyyy-mm-dd")) | I82: =IF(D82="","",D82) | J82: =IF(B82="","",TEXT(B82,"yyyy-mm-dd")) | K82: =IF(E82="","",E82) | L82: =IF(B82="","",TEXT(B82,"yyyy-mm-dd")) | M82: =IF(F82="","",F82)
A83: 10 | B83: =IF(G83="","",SUMIFS(EVALUACION!$C$7:$C$3006,EVALUACION!$B$7:$B$3006,$B$7,EVALUACION!$S$7:$S$3006,A83)) | C83: =IF(G83="","",SUMIFS(ANTROPOMETRIA!$D$7:$D$3006,ANTROPOMETRIA!$B$7:$B$3006,$B$7,ANTROPOMETRIA!$AJ$7:$AJ$3006,A83)) | D83: =IF(G83="","",SUMIFS(ANTROPOMETRIA!$F$7:$F$3006,ANTROPOMETRIA!$B$7:$B$3006,$B$7,ANTROPOMETRIA!$AJ$7:$AJ$3006,A83)) | E83: =IF(G83="","",IF(COUNTIF(OBJETIVOS!$A$7:$A$3006,G83)=0,0,COUNTIFS(OBJETIVOS!$A$7:$A$3006,G83,OBJETIVOS!$N$7:$N$3006,"Cumplido")/COUNTIF(OBJETIVOS!$A$7:$A$3006,G83))) | F83: =IF(G83="","",1) | G83: =IF(CONFIG!$B$29="No","",IF(SUMPRODUCT((EVALUACION!$B$7:$B$3006=$B$7)*(EVALUACION!$S$7:$S$3006=A83))=0,"",INDEX(EVALUACION!$A$7:$A$3006,SUMPRODUCT((EVALUACION!$B$7:$B$3006=$B$7)*(EVALUACION!$S$7:$S$3006=A83)*(ROW(EVALUACION!$A$7:$A$3006)-ROW(EVALUACION!$A$7)+1))))) | H83: =IF(B83="","",TEXT(B83,"yyyy-mm-dd")) | I83: =IF(D83="","",D83) | J83: =IF(B83="","",TEXT(B83,"yyyy-mm-dd")) | K83: =IF(E83="","",E83) | L83: =IF(B83="","",TEXT(B83,"yyyy-mm-dd")) | M83: =IF(F83="","",F83)

Sheet CATALOGOS
A1: CATÁLOGOS · Listas configurables y referencias verificables
A2: ◀ INICIO | B2: RESUMEN | C2: CONFIG | D2: PRUEBAS
A3: DATO FICTICIO — NO UTILIZAR EN CONSULTA · No utilizar como referencia clínica.
A5: Listas maestras para validación
A6: Estados paciente | B6: Tipos evaluación | C6: Modalidades | D6: Categorías antecedentes | E6: Sistemas clínicos | F6: Tiempos comida | G6: Tipos actividad | H6: Estados diagnóstico | I6: Prioridades | J6: Estados objetivos | K6: Categorías intervención | L6: Unidades | M6: Fuentes dato | N6: Consentimiento | O6: Estados registro | P6: Confiabilidad relato | Q6: Intensidad | R6: Presencia | S6: Tipo día | T6: Estado bioquímico | U6: Sí / No / NA
A7: Activo | B7: Inicial | C7: Presencial | D7: Personales | E7: Gastrointestinal | F7: Desayuno | G7: Actividad habitual | H7: Borrador | I7: Baja | J7: Borrador | K7: Educación alimentaria | L7: kg | M7: Informado por paciente | N7: Sí | O7: Borrador | P7: Alta | Q7: Leve | R7: Sí | S7: Habitual | T7: Bajo | U7: Sí
A8: Inactivo | B8: Control | C8: Remota | D8: Familiares | E8: Apetito | F8: Colación mañana | G8: Ejercicio estructurado | H8: Activo | I8: Media | J8: Activo | K8: Organización de comidas | L8: cm | M8: Observado | N8: No | O8: Completo | P8: Media | Q8: Moderada | R8: No | S8: No habitual | T8: Dentro de rango | U8: No
A9: Alta | B9: Reevaluación | C9: Mixta | D9: Cirugías | E9: Deglución | F9: Almuerzo | G9: Trabajo físico | H9: Revisado | I9: Alta | J9: Pausado | K9: Planificación | L9: m | M9: Documentado | N9: Pendiente | O9: Revisado | P9: Baja | Q9: Severa | R9: Intermitente | S9: Fin de semana | T9: Alto | U9: No aplica
A10: Derivado | B10: Cierre | D10: Hospitalizaciones | E10: Masticación | F10: Colación tarde | G10: Desplazamiento activo | H10: Cerrado | I10: Crítica | J10: Cumplido | K10: Modificación de textura | L10: g | M10: Medido | N10: Revocado | O10: Cerrado | P10: No evaluada | Q10: No evaluada | R10: No evaluada | S10: Laboral | T10: No evaluable
A11: Archivado | D11: Alergias | E11: Náuseas | F11: Once / merienda | G11: Rehabilitación | H11: Anulado | J11: Cancelado | K11: Hidratación | L11: mg | M11: Estimado | O11: Anulado | S11: Festivo
D12: Intolerancias | E12: Vómitos | F12: Cena | G12: Otro | K12: Actividad física | L12: µg | M12: Pendiente de confirmar | O12: Pendiente | S12: Otro
D13: Salud digestiva | E13: Diarrea | F13: Consumo nocturno | K13: Derivación | L13: mL
D14: Salud endocrina | E14: Estreñimiento | F14: Otro | K14: Seguimiento | L14: L
D15: Salud cardiovascular | E15: Dolor | K15: Coordinación interdisciplinaria | L15: kcal
D16: Salud renal | E16: Fatiga | K16: Otro | L16: g/día
D17: Salud hepática | E17: Sueño | L17: mg/dL
D18: Salud respiratoria | E18: Piel | L18: mmol/L
D19: Salud neurológica | E19: Cabello | L19: unidad
D20: Salud mental | E20: Uñas | L20: porción
D21: Salud reproductiva | E21: Edema | L21: minutos
D22: Sueño | E22: Hidratación | L22: horas
D23: Tabaquismo | E23: Menstruación | L23: veces/semana
D24: Alcohol | E24: Estrés | L24: %
D25: Otras sustancias | E25: Estado de ánimo
D26: Situación social | E26: Otros
D27: Seguridad alimentaria
A28: T_ANALITOS
A29: Código | B29: Analito | C29: Unidad sugerida | D29: Activo | E29: Observaciones
A30: AN-DEMO-01 | B30: Analito ficticio A | C30: unidad | D30: Sí | E30: DATO FICTICIO — NO UTILIZAR EN CONSULTA
A31: AN-DEMO-02 | B31: Analito ficticio B | C31: unidad | D31: Sí | E31: DATO FICTICIO — NO UTILIZAR EN CONSULTA
A32: AN-DEMO-03 | B32: Analito cualitativo ficticio | C32: texto | D32: Sí | E32: DATO FICTICIO — NO UTILIZAR EN CONSULTA
A50: T_RANGOS_BIOQUIMICOS
A51: Analito | B51: Sexo/población | C51: Edad mínima | D51: Edad máxima | E51: Unidad | F51: Límite inferior | G51: Límite superior | H51: Fuente | I51: Fecha | J51: Laboratorio/guía | K51: Estado verificación | L51: Observaciones
A52: Analito ficticio A | B52: Adultos ficticios | C52: 18 | D52: 120 | E52: unidad | F52: 70 | G52: 110 | H52: Fuente ficticia | I52: 46216 | J52: Laboratorio ficticio | K52: No verificado | L52: DATO FICTICIO — NO UTILIZAR EN CONSULTA
A72: T_PROFESIONALES
A73: ProfesionalID | B73: Nombre | C73: Registro | D73: Centro | E73: Activo | F73: Fecha actualización | G73: Observaciones
A74: PROF-DEMO | B74: PROFESIONAL FICTICIO | C74: REGISTRO FICTICIO | D74: CENTRO FICTICIO | E74: Sí | F74: 46216 | G74: DATO FICTICIO — NO UTILIZAR EN CONSULTA
A89: T_CATALOGOS_GENERAL
A90: Catálogo | B90: Código | C90: Valor | D90: Orden | E90: Activo | F90: Fuente | G90: Fecha revisión | H90: Observaciones
A91: Estados paciente | B91: A01 | C91: Activo | D91: 1 | E91: Sí | F91: Configuración interna | G91: 46216 | H91: DATO FICTICIO — NO UTILIZAR EN CONSULTA
A92: Estados paciente | B92: A02 | C92: Inactivo | D92: 2 | E92: Sí | F92: Configuración interna | G92: 46216 | H92: DATO FICTICIO — NO UTILIZAR EN CONSULTA
A93: Estados paciente | B93: A03 | C93: Alta | D93: 3 | E93: Sí | F93: Configuración interna | G93: 46216 | H93: DATO FICTICIO — NO UTILIZAR EN CONSULTA
A94: Estados paciente | B94: A04 | C94: Derivado | D94: 4 | E94: Sí | F94: Configuración interna | G94: 46216 | H94: DATO FICTICIO — NO UTILIZAR EN CONSULTA
A95: Estados paciente | B95: A05 | C95: Archivado | D95: 5 | E95: Sí | F95: Configuración interna | G95: 46216 | H95: DATO FICTICIO — NO UTILIZAR EN CONSULTA
A96: Tipos evaluación | B96: B01 | C96: Inicial | D96: 1 | E96: Sí | F96: Configuración interna | G96: 46216 | H96: DATO FICTICIO — NO UTILIZAR EN CONSULTA
A97: Tipos evaluación | B97: B02 | C97: Control | D97: 2 | E97: Sí | F97: Configuración interna | G97: 46216 | H97: DATO FICTICIO — NO UTILIZAR EN CONSULTA
A98: Tipos evaluación | B98: B03 | C98: Reevaluación | D98: 3 | E98: Sí | F98: Configuración interna | G98: 46216 | H98: DATO FICTICIO — NO UTILIZAR EN CONSULTA
A99: Tipos evaluación | B99: B04 | C99: Cierre | D99: 4 | E99: Sí | F99: Configuración interna | G99: 46216 | H99: DATO FICTICIO — NO UTILIZAR EN CONSULTA
A100: Modalidades | B100: C01 | C100: Presencial | D100: 1 | E100: Sí | F100: Configuración interna | G100: 46216 | H100: DATO FICTICIO — NO UTILIZAR EN CONSULTA
A101: Modalidades | B101: C02 | C101: Remota | D101: 2 | E101: Sí | F101: Configuración interna | G101: 46216 | H101: DATO FICTICIO — NO UTILIZAR EN CONSULTA
A102: Modalidades | B102: C03 | C102: Mixta | D102: 3 | E102: Sí | F102: Configuración interna | G102: 46216 | H102: DATO FICTICIO — NO UTILIZAR EN CONSULTA
... A240: Sí / No / NA | B240: U03 | C240: No aplica | D240: 3 | E240: Sí | F240: Configuración interna | G240: 46216 | H240: DATO FICTICIO — NO UTILIZAR EN CONSULTA

Sheet PRUEBAS
A1: PRUEBAS · 90 casos reproducibles, auditoría y resultados
A2: ◀ INICIO | B2: RESUMEN | C2: CONFIG | D2: PRUEBAS
A3: Los estados se calculan por fórmula. Las pruebas manuales no se marcan falsamente como aprobadas.
A5: ID | B5: Módulo | C5: Descripción | D5: Entrada 1 | E5: Entrada 2 | F5: Entrada 3 | G5: Esperado | H5: Mecanismo | I5: Obtenido | J5: Diferencia | K5: Estado | L5: Evidencia | M5: Observaciones
A6: T01 | B6: Pacientes | C6: PatientID válido | D6: P-X | G6: VÁLIDO | H6: Fórmula | I6: =IF(D6<>"","VÁLIDO","VACÍO") -> VÁLIDO | J6: =IF(AND(ISNUMBER(G6),ISNUMBER(I6)),ABS(I6-G6),"") | K6: =IF(I6="NO EVALUADA","NO EVALUADA",IF(LEFT(I6,6)="ERROR:","ERROR",IF(AND(ISNUMBER(G6),ISNUMBER(I6)),IF(J6<=CONFIG!$B$48,"APROBADA","FALLIDA"),IF(G6=I6,"APROBADA","FALLIDA")))) -> APROBADA | L6: Fórmula reproducible
A7: T02 | B7: Pacientes | C7: PatientID vacío | G7: VACÍO | H7: Fórmula | I7: =IF(D7="","VACÍO","VÁLIDO") -> VACÍO | J7: =IF(AND(ISNUMBER(G7),ISNUMBER(I7)),ABS(I7-G7),"") | K7: =IF(I7="NO EVALUADA","NO EVALUADA",IF(LEFT(I7,6)="ERROR:","ERROR",IF(AND(ISNUMBER(G7),ISNUMBER(I7)),IF(J7<=CONFIG!$B$48,"APROBADA","FALLIDA"),IF(G7=I7,"APROBADA","FALLIDA")))) -> APROBADA | L7: Fórmula reproducible
A8: T03 | B8: Pacientes | C8: PatientID duplicado | D8: P-X | E8: P-X | G8: DUPLICADO | H8: Fórmula | I8: =IF(D8=E8,"DUPLICADO","ÚNICO") -> DUPLICADO | J8: =IF(AND(ISNUMBER(G8),ISNUMBER(I8)),ABS(I8-G8),"") | K8: =IF(I8="NO EVALUADA","NO EVALUADA",IF(LEFT(I8,6)="ERROR:","ERROR",IF(AND(ISNUMBER(G8),ISNUMBER(I8)),IF(J8<=CONFIG!$B$48,"APROBADA","FALLIDA"),IF(G8=I8,"APROBADA","FALLIDA")))) -> APROBADA | L8: Fórmula reproducible
A9: T04 | B9: Pacientes | C9: Fecha nacimiento válida | D9: 32874 | E9: 46216 | G9: VÁLIDA | H9: Fórmula | I9: =IF(D9<=E9,"VÁLIDA","FUTURA") -> VÁLIDA | J9: =IF(AND(ISNUMBER(G9),ISNUMBER(I9)),ABS(I9-G9),"") | K9: =IF(I9="NO EVALUADA","NO EVALUADA",IF(LEFT(I9,6)="ERROR:","ERROR",IF(AND(ISNUMBER(G9),ISNUMBER(I9)),IF(J9<=CONFIG!$B$48,"APROBADA","FALLIDA"),IF(G9=I9,"APROBADA","FALLIDA")))) -> APROBADA | L9: Fórmula reproducible
A10: T05 | B10: Pacientes | C10: Fecha nacimiento futura | D10: 46388 | E10: 46216 | G10: FUTURA | H10: Fórmula | I10: =IF(D10>E10,"FUTURA","VÁLIDA") -> FUTURA | J10: =IF(AND(ISNUMBER(G10),ISNUMBER(I10)),ABS(I10-G10),"") | K10: =IF(I10="NO EVALUADA","NO EVALUADA",IF(LEFT(I10,6)="ERROR:","ERROR",IF(AND(ISNUMBER(G10),ISNUMBER(I10)),IF(J10<=CONFIG!$B$48,"APROBADA","FALLIDA"),IF(G10=I10,"APROBADA","FALLIDA")))) -> APROBADA | L10: Fórmula reproducible
