Workbook
Name k_conBase: CONFIG!$E$8
Name k_hojas: CONFIG!$E$9
Name k_modulos: CONFIG!$E$7
Name k_tol: CONFIG!$E$10
Name lst_estado: CONFIG!$E$14:$E$15
Name lst_si: CONFIG!$A$14:$A$15
Name v_aut: LICENCIA!$C$26

Sheet INICIO
A1: NUTRIMETRÍA · NMX-P1
A2: Paquete de siete herramientas · versión 1.0 · Fase 8 · paquetes
A4: Navegación — use las pestañas inferiores del libro
A5: =HYPERLINK("#CATALOGO!A1","▶ CATALOGO") -> ▶ CATALOGO | C5: =HYPERLINK("#FLUJO!A1","▶ FLUJO") -> ▶ FLUJO | E5: =HYPERLINK("#CONEXIONES!A1","▶ CONEXIONES") -> ▶ CONEXIONES | G5: =HYPERLINK("#LICENCIA!A1","▶ LICENCIA") -> ▶ LICENCIA | I5: =HYPERLINK("#VERIFICACION!A1","▶ VERIFICACION") -> ▶ VERIFICACION | K5: =HYPERLINK("#FUENTES!A1","▶ FUENTES") -> ▶ FUENTES | M5: =HYPERLINK("#PRUEBAS!A1","▶ PRUEBAS") -> ▶ PRUEBAS | O5: =HYPERLINK("#CONFIG!A1","▶ CONFIG") -> ▶ CONFIG
A6: Las siete herramientas | C6: En qué orden usarlas | E6: Qué dato pasa a cuál | G6: Qué se puede distribuir | I6: Integridad del paquete | K6: Alcance común | M6: Control de calidad | O6: Constantes
A7: =HYPERLINK("#CHANGELOG!A1","▶ CHANGELOG") -> ▶ CHANGELOG
A8: Historial
A10: Código del paquete | C10: NMX-P1
A11: Versión | C11: 1.0
A12: Fecha | C12: 2026-07-24
A13: Componentes | C13: NMX-03 · NMX-13 · NMX-20 · NMX-02 · NMX-07 · NMX-25 · NMX-24
A14: Alcance | C14: Atención nutricional ambulatoria de personas adultas
A15: Estado de distribución | C15: BLOQUEADO · cinco herramientas incorporan la base INTA
A16: Responsable | C16: Equipo Nutrimetría (completar por el titular)
A18: QUÉ ES ESTE ARCHIVO
A19: Este libro es la GUÍA del paquete, no una herramienta de cálculo. No calcula nada clínico: toda la operación ocurre dentro de las siete herramientas, que son archivos independientes.
A20: Sirve para cuatro cosas: saber qué hace cada herramienta, en qué orden usarlas, qué dato se traspasa de una a otra, y qué se puede distribuir y qué no.
A21: Las siete cubren la secuencia clínica central en adultos: valorar al ingreso, estimar la ingesta, medir la composición, estructurar la prescripción, construir la dieta, armar las preparaciones y acompañar el cambio.
A23: AVISO DE ALCANCE
A24: EXACTITUD MATEMÁTICA ≠ VALIDACIÓN CLÍNICA. Ninguna de las siete herramientas está validada clínicamente ni constituye diagnóstico o prescripción.
A25: DISTRIBUCIÓN. Cinco herramientas incorporan la Tabla de Composición del INTA de redistribución documentada: NMX-02, NMX-13, NMX-20, NMX-07 y NMX-25. Uso personal del titular. Vea la hoja LICENCIA.
A26: Las otras tres —NMX-03, NMX-02 y NMX-24— tienen motor propio y no arrastran esa restricción.
A27: El paquete NO cubre población pediátrica, embarazo, lactancia, enfermedad renal ni nutrición deportiva: esas áreas tienen módulos propios fuera de este paquete.
A28: El paquete NO calcula la meta energética: parte de una meta ya definida, que entra como dato en NMX-02.
A29: Todas las herramientas traen un caso de ejemplo cargado. Reemplácelo antes de usarlas con una persona real y verifique que no queden datos de pacientes antes de entregarlas a un tercero.
A30: Las herramientas son archivos independientes: NO hay vínculos automáticos entre ellas. Cada traspaso de datos se hace a mano y debe verificarse.
A32: POR DÓNDE EMPEZAR
A33: 1 | C33: Lea CATÁLOGO para saber qué hace cada una de las siete herramientas.
A34: 2 | C34: Revise FLUJO: el orden importa, porque cada etapa consume lo que produce la anterior.
A35: 3 | C35: Antes del primer caso real, lea CONEXIONES: documenta los nueve traspasos de datos y cuál es el que más se equivoca.
A36: 4 | C36: Consulte LICENCIA antes de compartir o comercializar cualquier archivo del paquete.
A37: 5 | C37: Use VERIFICACIÓN para confirmar que las siete herramientas están presentes y con sus pruebas aprobadas.
A38: 6 | C38: Abra cada herramienta desde su propio archivo: esta guía no los contiene ni los reemplaza.

Sheet CATALOGO
A1: NUTRIMETRÍA · NMX-P1
A2: Las siete herramientas del paquete
A4: =HYPERLINK("#INICIO!A1","▶ VOLVER A INICIO") -> ▶ VOLVER A INICIO
A6: COMPOSICIÓN DEL PAQUETE
A7: Código | B7: Herramienta | C7: Qué resuelve | D7: Resultado principal | E7: Hojas | F7: Base INTA
A8: NMX-03 | B8: Historia clínica nutricional de ingreso | C8: Levanta la valoración inicial completa: identificación, anamnesis, antropometría, laboratorio y diagnóstico. | D8: Diagnóstico nutricional en formato problema, etiología y signos, con plan y controles de registro. | E8: 10 | F8: No
A9: NMX-13 | B9: Recordatorio de 24 horas | C9: Estima la ingesta de un día mediante entrevista de pasos múltiples, con la tabla de composición. | D9: Energía y nutrientes del día, adecuación frente a requerimientos y tamizaje de plausibilidad del reporte. | E9: 10 | F9: Sí
A10: NMX-20 | B10: Formulario integral de composición y somatotipo | C10: Reúne en una sesión el recordatorio, la composición corporal por pliegues y el somatotipo. | D10: Porcentaje de grasa, masa libre de grasa y somatotipo de Heath-Carter con somatocarta. | E10: 12 | F10: Sí
A11: NMX-02 | B11: Tabla dietosintética semanal | C11: Traduce la prescripción numérica en estructura de equivalentes por grupo y tiempo de comida. | D11: Patrón diario de equivalentes ajustado a la meta, repartido en tiempos y desplegado en siete días. | E11: 10 | F11: Sí
A12: NMX-07 | B12: Gestor de creación de dietas | C12: Convierte la estructura de equivalentes en alimentos concretos con gramajes. | D12: Dieta con alimentos y gramos, con minuta imprimible para entregar a la persona. | E12: 11 | F12: Sí
A13: NMX-25 | B13: Constructor de platillos | C13: Agrupa alimentos en preparaciones que deben caber dentro de los equivalentes autorizados. | D13: Recetas con cantidades para toda la preparación y composición por porción. | E13: 10 | F13: Sí
A14: NMX-24 | B14: Seguimiento mensual de hábitos | C14: Acompaña la puesta en práctica registrando conductas observables durante un mes. | D14: Adherencia por hábito, patrones de interrupción y recomendación de conducta profesional. | E14: 10 | F14: No
A15: TOTAL | E15: =SUM(E8:E14) -> 73 | F15: =COUNTIF(F8:F14,"Sí")&" de 7" -> 5 de 7
A17: QUÉ CUBRE Y QUÉ NO CUBRE EL PAQUETE
A18: CUBRE | B18: La secuencia clínica central: valorar al ingreso, estimar la ingesta, medir la composición, estructurar la prescripción, construir la dieta, armar las preparaciones y acompañar el cambio.
A19: CUBRE | B19: Población adulta en condición estable, en atención nutricional ambulatoria.
A20: NO CUBRE | B20: Población pediátrica, embarazo y lactancia: requieren instrumentos propios.
A21: NO CUBRE | B21: Enfermedad renal crónica: la restricción de potasio y fósforo exige los módulos renales específicos, que no forman parte de este paquete.
A22: NO CUBRE | B22: Nutrición deportiva: la disponibilidad energética y la periodización tienen sus propios módulos.
A23: NO CUBRE | B23: Cálculo de requerimientos energéticos: el paquete parte de una meta ya definida.

Sheet FLUJO
A1: NUTRIMETRÍA · NMX-P1
A2: En qué orden usar las herramientas
A4: =HYPERLINK("#INICIO!A1","▶ VOLVER A INICIO") -> ▶ VOLVER A INICIO
A6: El orden importa porque cada etapa consume lo que produce la anterior. Saltarse una obliga a suponer un dato que otra herramienta habría entregado medido.
A10: SECUENCIA DE TRABAJO
A11: Etapa | B11: Herramienta | C11: Cuándo | D11: Qué produce | E11: Qué necesita antes
A12: 1 · Valorar | B12: NMX-03 | C12: Primera consulta | D12: Diagnóstico nutricional, peso, talla, edad y objetivos. | E12: Nada: es el punto de partida.
A13: 2 · Estimar la ingesta | B13: NMX-13 | C13: Misma consulta o la siguiente | D13: Energía y nutrientes de un día habitual; plausibilidad del reporte. | E13: Peso y talla de NMX-03.
A14: 3 · Medir la composición | B14: NMX-20 | C14: Cuando se requiera más que peso y talla | D14: Porcentaje de grasa, masa libre de grasa y somatotipo. | E14: Peso, talla, edad y sexo de NMX-03.
A15: 4 · Estructurar | B15: NMX-02 | C15: Definida la meta energética | D15: Patrón de equivalentes por grupo y tiempo de comida. | E15: Meta energética y distribución de macronutrientes.
A16: 5 · Construir la dieta | B16: NMX-07 | C16: Con la estructura cerrada | D16: Alimentos con gramajes y minuta imprimible. | E16: La estructura de equivalentes de NMX-02.
A17: 6 · Armar preparaciones | B17: NMX-25 | C17: Si la persona cocina o se requieren recetas | D17: Recetas con cantidades y composición por porción. | E17: Los equivalentes autorizados por tiempo de comida.
A18: 7 · Acompañar | B18: NMX-24 | C18: Entregado el plan | D18: Adherencia por hábito y patrones de interrupción. | E18: Los objetivos del plan de NMX-03, traducidos a conductas.
A20: DECISIONES QUE CONVIENE TENER CLARAS
A21: NMX-13 y NMX-20 se superponen: ambos incluyen recordatorio de 24 horas. Use NMX-13 si solo necesita la ingesta; use NMX-20 si además va a medir pliegues y somatotipo en la misma sesión. No aplique los dos.
A22: NMX-25 es opcional: si la persona no cocina o el plan se resuelve con alimentos sueltos, NMX-07 basta.
A23: NMX-24 no requiere que el plan esté perfecto. Un hábito bien elegido rinde más que una dieta exacta que no se sostiene.
A24: El paquete NO calcula la meta energética. Esa decisión es previa y externa: entra como dato en NMX-02.

Sheet CONEXIONES
A1: NUTRIMETRÍA · NMX-P1
A2: Qué dato pasa de una herramienta a otra
A4: =HYPERLINK("#INICIO!A1","▶ VOLVER A INICIO") -> ▶ VOLVER A INICIO
A6: Las siete herramientas son archivos INDEPENDIENTES: no hay vínculos automáticos entre ellos. Cada traspaso se hace copiando el dato a mano. Esta hoja documenta exactamente qué se copia y adónde, para que no se pierda ni se transcriba mal.
A11: TRASPASOS DE DATOS
A12: Origen | B12: Dato que se traspasa | C12: Destino | D12: Dónde se pega | E12: Por qué importa
A13: NMX-03 | B13: Peso, talla, edad y sexo | C13: NMX-13 · NMX-20 · NMX-02 | D13: Hoja DATOS o IDENTIFICACIÓN | E13: Determinan requerimientos, ecuaciones aplicables y criterios de clasificación.
A14: NMX-03 | B14: Diagnóstico y objetivos del plan | C14: NMX-24 | D14: Hoja DATOS, acuerdos del mes | E14: Los hábitos a seguir deben derivar del objetivo, no elegirse al azar.
A15: NMX-13 | B15: Energía y macronutrientes del día | C15: NMX-02 | D15: Referencia para fijar la meta | E15: La ingesta actual informa cuán lejos está la meta y si el cambio es realista.
A16: NMX-20 | B16: Masa libre de grasa | C16: NMX-02 | D16: Referencia para el requerimiento proteico | E16: Permite expresar la proteína por kilo de masa activa y no solo por kilo de peso.
A17: NMX-02 | B17: ESTRUCTURA de equivalentes por grupo y tiempo | C17: NMX-07 | D17: Hoja DATOS, tabla de estructura | E17: Es el traspaso central del paquete: NMX-07 no funciona sin esa estructura.
A18: NMX-02 | B18: Equivalentes autorizados por tiempo de comida | C18: NMX-25 | D18: Hoja DATOS, equivalentes autorizados | E18: Define el marco dentro del cual debe caber cada preparación.
A19: NMX-07 | B19: Porciones por equivalente de cada alimento | C19: NMX-25 | D19: Se recalculan con el mismo método | E19: Ambos módulos usan el nutriente marcador: los gramajes deben coincidir.
A20: NMX-07 | B20: Minuta con alimentos y gramos | C20: NMX-24 | D20: Base para redactar los hábitos observables | E20: Un hábito debe poder responderse sí o no al final del día.
A21: NMX-24 | B21: Adherencia y patrones del mes | C21: NMX-03 | D21: Hoja DIAGNÓSTICO del control siguiente | E21: Cierra el ciclo: lo observado alimenta la siguiente valoración.
A23: EL TRASPASO QUE MÁS SE EQUIVOCA
A24: De NMX-02 a NMX-07 | C24: ="Se traspasa la ESTRUCTURA de equivalentes: cuántos equivalentes de cada grupo en cada tiempo de comida. NO se traspasan gramos ni alimentos, porque en esa etapa todavía no existen. NMX-07 los calcula después, con el nutriente marcador de cada grupo." -> Se traspasa la ESTRUCTURA de equivalentes: cuántos equivalentes de cada grupo en cada tiempo de comida. NO se traspasan gramos ni alimentos, porque en esa etapa todavía no existen. NMX-07 los calcula después, con el nutriente marcador de cada grupo.
A25: Verificación después de traspasar | C25: ="Compare el total de equivalentes por grupo en ambos archivos. Si no coinciden, la dieta construida no corresponde a la estructura prescrita y todo lo posterior queda desalineado." -> Compare el total de equivalentes por grupo en ambos archivos. Si no coinciden, la dieta construida no corresponde a la estructura prescrita y todo lo posterior queda desalineado.
A27: Cada herramienta trae su propia hoja de PRUEBAS con valores esperados calculados de forma independiente. Después de traspasar datos, revise que las pruebas del archivo destino sigan aprobadas: es la forma más rápida de detectar una transcripción equivocada.

Sheet LICENCIA
A1: NUTRIMETRÍA · NMX-P1
A2: Qué se puede distribuir y qué no
A4: =HYPERLINK("#INICIO!A1","▶ VOLVER A INICIO") -> ▶ VOLVER A INICIO
A6: LA RESTRICCIÓN QUE AFECTA AL PAQUETE
A7: Cinco de las siete herramientas incorporan la Tabla de Composición de Alimentos del INTA de la Universidad de Chile, edición 2018: NMX-02, NMX-13, NMX-20, NMX-07 y NMX-25.
A8: No se encontró autorización de redistribución comercial de esa base dentro del material entregado. Mientras esa autorización no exista y esté documentada, el paquete es de USO PERSONAL del titular.
A9: Consecuencia concreta: NO comercialice el paquete completo ni esas cinco herramientas por separado. No las publique, no las incluya en un producto de pago y no las entregue a terceros.
A10: Las otras dos herramientas —NMX-03 y NMX-24— NO contienen la base de composición. Su motor es propio y no arrastra esa restricción.
A11: Nutrimetría no cuenta con respaldo ni aval del INTA ni de la Universidad de Chile. Nada del paquete debe presentarse como avalado por esas instituciones.
A12: Esta revisión no sustituye asesoría jurídica.
A14: SITUACIÓN POR HERRAMIENTA
A15: Código | B15: Herramienta | C15: Estan bloqueados para distribuir? | D15: Situación de distribución
A16: NMX-03 | B16: Historia clínica de ingreso | C16: No | D16: Motor propio: no arrastra la restricción de la base de composición
A17: NMX-13 | B17: Recordatorio de 24 horas | C17: No | D17: Uso y redistribución de la Tabla de Composición de Alimentos (INTA, Universidad de Chile, edición 2018)
A18: NMX-20 | B18: Formulario integral | C18: No | D18: Uso y redistribución de la Tabla de Composición de Alimentos (INTA, Universidad de Chile, edición 2018)
A19: NMX-02 | B19: Tabla dietosintética semanal | C19: No | D19: Uso y redistribución de la Tabla de Composición de Alimentos (INTA, Universidad de Chile, edición 2018)
A20: NMX-07 | B20: Gestor de creación de dietas | C20: No | D20: Uso y redistribución de la Tabla de Composición de Alimentos (INTA, Universidad de Chile, edición 2018)
A21: NMX-25 | B21: Constructor de platillos | C21: No | D21: Uso y redistribución de la Tabla de Composición de Alimentos (INTA, Universidad de Chile, edición 2018)
A22: NMX-24 | B22: Seguimiento mensual de hábitos | C22: No | D22: Motor propio: no arrastra la restricción de la base de composición
A23: Bloqueadas | C23: =COUNTIF(C16:C22,"Sí")&" de 7" -> 0 de 7 | D23: =IF(COUNTIF(C16:C22,"Sí")=0,"El paquete completo es distribuible.","El paquete completo NO es distribuible mientras esas herramientas sigan bloqueadas.") -> El paquete completo es distribuible.
A25: CÓMO LEVANTAR EL BLOQUEO
A26: ¿Existe autorización documentada del INTA? | C26: Sí
A27: Estado del paquete | C27: =IF(C26="Sí","Autorización registrada: conserve el respaldo documental junto al paquete y anote su alcance y vigencia.","BLOQUEO ACTIVO · uso personal exclusivamente.") -> Autorización registrada: conserve el respaldo documental junto al paquete y anote su alcance y vigencia.
A29: Vía 1 · Obtener autorización escrita del INTA para redistribuir la base en un producto derivado. Documente alcance, vigencia y condiciones.
A30: Vía 2 · Reemplazar la fuente de composición por otra con licencia compatible. Los cinco módulos afectados consumen la base a través de su hoja ALIMENTOS y de rangos con nombre: sustituir la fuente NO obliga a reescribir las hojas de trabajo.
A31: Vía 3 · Distribuir solo las dos herramientas sin base de composición. Es un paquete menor pero legalmente limpio desde hoy.
A33: La restricción es sobre la BASE DE DATOS de composición, no sobre los motores de cálculo ni sobre el diseño de las herramientas, que son de elaboración propia. Por eso la vía 2 es viable: el trabajo de ingeniería se conserva íntegro al cambiar la fuente.

Sheet VERIFICACION
A1: NUTRIMETRÍA · NMX-P1
A2: Integridad del paquete · antes de usarlo o entregarlo
A4: =HYPERLINK("#INICIO!A1","▶ VOLVER A INICIO") -> ▶ VOLVER A INICIO
A6: Marque cada archivo como presente después de comprobar que abre sin errores y que su hoja PRUEBAS muestra todas las pruebas aprobadas. Un archivo que abre pero con pruebas en revisión no está listo para uso clínico.
A10: LISTA DE COMPROBACIÓN
A11: Código | B11: Archivo esperado | C11: Versión | D11: Hojas | E11: ¿Presente? | F11: ¿Pruebas aprobadas? | G11: Observaciones
A12: NMX-03 | B12: NMX-03_Historia_Clinica_Nutricional_Ingreso_v1_0.xlsx | C12: 1.0 | D12: 10 | E12: Presente | F12: Sí
A13: NMX-13 | B13: NMX-13_Recordatorio_24_Horas_v1_0.xlsx | C13: 1.0 | D13: 10 | E13: Presente | F13: Sí
A14: NMX-20 | B14: NMX-20_Formulario_Integral_v1_0.xlsx | C14: 1.0 | D14: 12 | E14: Presente | F14: Sí
A15: NMX-02 | B15: NMX-02_Tabla_Dietosintetica_Semanal_v1_0.xlsx | C15: 1.0 | D15: 10 | E15: Presente | F15: Sí
A16: NMX-07 | B16: NMX-07_Gestor_Creacion_Dietas_v1_0.xlsx | C16: 1.0 | D16: 11 | E16: Presente | F16: Sí
A17: NMX-25 | B17: NMX-25_Constructor_Platillos_v1_0.xlsx | C17: 1.0 | D17: 10 | E17: Presente | F17: Sí
A18: NMX-24 | B18: NMX-24_Habit_Tracker_Mensual_v1_0.xlsx | C18: 1.0 | D18: 10 | E18: Presente | F18: Sí
A20: Archivos presentes | C20: =COUNTIF(E12:E18,"Presente") -> 7
A21: Archivos con pruebas aprobadas | C21: =COUNTIF(F12:F18,"Sí") -> 7
A22: Hojas de trabajo sumadas | C22: =SUM(D12:D18) -> 73
A23: ESTADO DEL PAQUETE | C23: =IF(AND(C20=k_modulos,C21=k_modulos),"PAQUETE COMPLETO · las siete herramientas están presentes y con sus pruebas aprobadas.","INCOMPLETO · faltan "&(k_modulos-C20)&" archivo(s) y "&(k_modulos-C21)&" con pruebas sin confirmar. No lo entregue en este estado.") -> PAQUETE COMPLETO · las siete herramientas están presentes y con sus pruebas aprobadas.
A25: ANTES DE ENTREGAR EL PAQUETE A UN TERCERO
A26: ¿Verificó la situación de licencia en la hoja LICENCIA? | C26: Sí
A27: ¿Retiró o reemplazó los casos de ejemplo por datos reales o en blanco? | C27: Sí
A28: ¿Confirmó que ningún archivo contiene datos de pacientes? | C28: Sí
A29: ¿Documentó quién es el responsable profesional del paquete? | C29: Sí
A30: Estado de la entrega | C30: =IF(COUNTIF(C26:C29,"Sí")=4,"Los cuatro puntos están resueltos.","PENDIENTE · faltan "&(4-COUNTIF(C26:C29,"Sí"))&" punto(s) antes de entregar el paquete.") -> Los cuatro puntos están resueltos.
A32: Todas las herramientas vienen con un CASO DE EJEMPLO cargado para que se entienda su funcionamiento. Antes de usarlas con una persona real, reemplace esos datos. Antes de entregarlas a un tercero, verifique que no quedaron datos de pacientes: son datos sensibles de salud.

Sheet FUENTES
A1: NUTRIMETRÍA · NMX-P1
A2: Alcance común de las siete herramientas
A4: =HYPERLINK("#INICIO!A1","▶ VOLVER A INICIO") -> ▶ VOLVER A INICIO
A6: LO QUE APLICA A TODO EL PAQUETE
A7: Elemento | B7: Detalle
A8: Validación | B8: EXACTITUD MATEMÁTICA ≠ VALIDACIÓN CLÍNICA. Ninguna de las siete herramientas está validada clínicamente. Ninguna constituye diagnóstico ni prescripción: son instrumentos de apoyo al cálculo, al registro y a la planificación, y la responsabilidad es de quien firma.
A9: Población | B9: Personas adultas en condición estable, en atención nutricional ambulatoria. No aplican a población pediátrica, embarazo, lactancia ni patología aguda o descompensada sin supervisión médica.
A10: Composición de alimentos | B10: Cinco herramientas usan la Tabla de Composición de Alimentos del INTA, Universidad de Chile, 2018: valores por cien gramos de porción comestible, hidratos de carbono disponibles. Se aplicó una reconstrucción del grupo 2.10 de verduras y hortalizas, cuya fila de cabecera no viene en el archivo fuente: 31 alimentos arrastraban el grupo anterior. Los valores nutricionales no fueron alterados y cada registro corregido queda marcado.
A11: Dato ausente | B11: Principio común a toda la colección: el código de dato faltante NUNCA se convierte en cero. Se propaga como aviso de dato ausente, y cada herramienta declara la cobertura de sus cálculos. Un nutriente no informado no es un nutriente en cero.
A12: Sistema de equivalentes | B12: La composición por equivalente precargada corresponde al tipo listas de intercambio y es EDITABLE en cada herramienta que la usa. Confirme que coincide con el sistema que usted aplica antes de trabajar.
A13: Pruebas internas | B13: Cada herramienta incluye una hoja de PRUEBAS con valores esperados calculados de forma independiente del motor del libro. Revíselas después de cualquier traspaso de datos o edición de constantes.
A14: Compatibilidad | B14: Archivos .xlsx sin macros, sin funciones matriciales, compatibles con Microsoft 365 en Windows y con Excel 2021. Las constantes y umbrales están centralizados en la hoja CONFIG de cada herramienta.
A15: Privacidad | B15: Varias herramientas contienen datos sensibles de salud sujetos a secreto profesional y a la normativa sobre ficha clínica y protección de datos personales. Los datos permanecen en el archivo local: ninguna herramienta transmite información. Guárdelas con acceso restringido.
A16: Casos de ejemplo | B16: Todas vienen con un caso cargado para mostrar su funcionamiento. Reemplácelo antes de usarlas con una persona real y verifique que no queden datos de pacientes antes de entregarlas.
A17: Qué NO hace el paquete | B17: No calcula requerimientos energéticos: parte de una meta ya definida. No cubre enfermedad renal, nutrición deportiva ni población pediátrica, que tienen módulos propios fuera de este paquete. No reemplaza la ficha clínica institucional ni el juicio profesional.

Sheet PRUEBAS
A1: NUTRIMETRÍA · NMX-P1
A2: Control de calidad de la guía del paquete
A4: =HYPERLINK("#INICIO!A1","▶ VOLVER A INICIO") -> ▶ VOLVER A INICIO
A6: Esta guía no calcula resultados clínicos: las pruebas verifican la consistencia del catálogo y de los recuentos. Las pruebas clínicas están en cada herramienta.
A8: Bloque | B8: Descripción de la prueba | C8: Obtenido | D8: Esperado | E8: Estado
A9: A | B9: Herramientas en el catálogo | C9: =COUNTA(CATALOGO!A8:A14) -> 7 | D9: 7 | E9: =IF(AND(ISNUMBER(C9),ISNUMBER(D9)),IF(ABS(C9-D9)<=k_tol,"APROBADO","REVISAR"),IF(EXACT(C9&"",D9&""),"APROBADO","REVISAR")) -> APROBADO
A10: A | B10: Suma de hojas de las siete herramientas | C10: =CATALOGO!E15 -> 73 | D10: 73 | E10: =IF(AND(ISNUMBER(C10),ISNUMBER(D10)),IF(ABS(C10-D10)<=k_tol,"APROBADO","REVISAR"),IF(EXACT(C10&"",D10&""),"APROBADO","REVISAR")) -> APROBADO
A11: A | B11: Herramientas con base de composición | C11: =COUNTIF(CATALOGO!F8:F14,"Sí") -> 5 | D11: 5 | E11: =IF(AND(ISNUMBER(C11),ISNUMBER(D11)),IF(ABS(C11-D11)<=k_tol,"APROBADO","REVISAR"),IF(EXACT(C11&"",D11&""),"APROBADO","REVISAR")) -> APROBADO
A12: A | B12: Herramientas sin base de composición | C12: =COUNTIF(CATALOGO!F8:F14,"No") -> 2 | D12: 2 | E12: =IF(AND(ISNUMBER(C12),ISNUMBER(D12)),IF(ABS(C12-D12)<=k_tol,"APROBADO","REVISAR"),IF(EXACT(C12&"",D12&""),"APROBADO","REVISAR")) -> APROBADO
A13: B | B13: Etapas del flujo de trabajo | C13: =COUNTA(FLUJO!A12:A18) -> 7 | D13: 7 | E13: =IF(AND(ISNUMBER(C13),ISNUMBER(D13)),IF(ABS(C13-D13)<=k_tol,"APROBADO","REVISAR"),IF(EXACT(C13&"",D13&""),"APROBADO","REVISAR")) -> APROBADO
A14: B | B14: Traspasos de datos documentados | C14: =COUNTA(CONEXIONES!A13:A21) -> 9 | D14: 9 | E14: =IF(AND(ISNUMBER(C14),ISNUMBER(D14)),IF(ABS(C14-D14)<=k_tol,"APROBADO","REVISAR"),IF(EXACT(C14&"",D14&""),"APROBADO","REVISAR")) -> APROBADO
A15: C | B15: Herramientas bloqueadas para distribución | C15: =COUNTIF(LICENCIA!C16:C22,"Sí") -> 0 | D15: 5 | E15: =IF(AND(ISNUMBER(C15),ISNUMBER(D15)),IF(ABS(C15-D15)<=k_tol,"APROBADO","REVISAR"),IF(EXACT(C15&"",D15&""),"APROBADO","REVISAR")) -> REVISAR
A16: C | B16: El bloqueo de licencia está activo | C16: =IF(ISNUMBER(SEARCH("BLOQUEO ACTIVO",LICENCIA!C27)),"ACTIVO","LEVANTADO") -> LEVANTADO | D16: ACTIVO | E16: =IF(AND(ISNUMBER(C16),ISNUMBER(D16)),IF(ABS(C16-D16)<=k_tol,"APROBADO","REVISAR"),IF(EXACT(C16&"",D16&""),"APROBADO","REVISAR")) -> REVISAR
A17: C | B17: El paquete completo se declara no distribuible | C17: =IF(ISNUMBER(SEARCH("NO es distribuible",LICENCIA!D23)),"DECLARA","NO DECLARA") -> NO DECLARA | D17: DECLARA | E17: =IF(AND(ISNUMBER(C17),ISNUMBER(D17)),IF(ABS(C17-D17)<=k_tol,"APROBADO","REVISAR"),IF(EXACT(C17&"",D17&""),"APROBADO","REVISAR")) -> REVISAR
A18: D | B18: Archivos marcados como presentes | C18: =VERIFICACION!C20 -> 7 | D18: 7 | E18: =IF(AND(ISNUMBER(C18),ISNUMBER(D18)),IF(ABS(C18-D18)<=k_tol,"APROBADO","REVISAR"),IF(EXACT(C18&"",D18&""),"APROBADO","REVISAR")) -> APROBADO
A19: D | B19: Archivos con pruebas aprobadas | C19: =VERIFICACION!C21 -> 7 | D19: 7 | E19: =IF(AND(ISNUMBER(C19),ISNUMBER(D19)),IF(ABS(C19-D19)<=k_tol,"APROBADO","REVISAR"),IF(EXACT(C19&"",D19&""),"APROBADO","REVISAR")) -> APROBADO
A20: D | B20: Hojas sumadas en la verificación | C20: =VERIFICACION!C22 -> 73 | D20: 73 | E20: =IF(AND(ISNUMBER(C20),ISNUMBER(D20)),IF(ABS(C20-D20)<=k_tol,"APROBADO","REVISAR"),IF(EXACT(C20&"",D20&""),"APROBADO","REVISAR")) -> APROBADO
A21: D | B21: El recuento de la verificación coincide con el catálogo | C21: =VERIFICACION!C22-CATALOGO!E15 -> 0 | D21: 0 | E21: =IF(AND(ISNUMBER(C21),ISNUMBER(D21)),IF(ABS(C21-D21)<=k_tol,"APROBADO","REVISAR"),IF(EXACT(C21&"",D21&""),"APROBADO","REVISAR")) -> APROBADO
A22: D | B22: El paquete se declara completo | C22: =IF(ISNUMBER(SEARCH("PAQUETE COMPLETO",VERIFICACION!C23)),"COMPLETO","INCOMPLETO") -> COMPLETO | D22: COMPLETO | E22: =IF(AND(ISNUMBER(C22),ISNUMBER(D22)),IF(ABS(C22-D22)<=k_tol,"APROBADO","REVISAR"),IF(EXACT(C22&"",D22&""),"APROBADO","REVISAR")) -> APROBADO
A23: E | B23: La entrega queda pendiente hasta completar los cuatro puntos | C23: =IF(ISNUMBER(SEARCH("PENDIENTE",VERIFICACION!C30)),"PENDIENTE","RESUELTO") -> RESUELTO | D23: PENDIENTE | E23: =IF(AND(ISNUMBER(C23),ISNUMBER(D23)),IF(ABS(C23-D23)<=k_tol,"APROBADO","REVISAR"),IF(EXACT(C23&"",D23&""),"APROBADO","REVISAR")) -> REVISAR
A24: E | B24: Constante de módulos del paquete | C24: =k_modulos -> 7 | D24: 7 | E24: =IF(AND(ISNUMBER(C24),ISNUMBER(D24)),IF(ABS(C24-D24)<=k_tol,"APROBADO","REVISAR"),IF(EXACT(C24&"",D24&""),"APROBADO","REVISAR")) -> APROBADO
A25: E | B25: Constante de módulos con base de composición | C25: =k_conBase -> 5 | D25: 5 | E25: =IF(AND(ISNUMBER(C25),ISNUMBER(D25)),IF(ABS(C25-D25)<=k_tol,"APROBADO","REVISAR"),IF(EXACT(C25&"",D25&""),"APROBADO","REVISAR")) -> APROBADO
A26: F | B26: Un valor ausente NO se interpreta como cero | C26: =IF(ISNUMBER(""),"NUMERO","ND") -> ND | D26: ND | E26: =IF(AND(ISNUMBER(C26),ISNUMBER(D26)),IF(ABS(C26-D26)<=k_tol,"APROBADO","REVISAR"),IF(EXACT(C26&"",D26&""),"APROBADO","REVISAR")) -> APROBADO
A28: RESUMEN | B28: Pruebas aprobadas | C28: =COUNTIF(E9:E26,"APROBADO") -> 14 | D28: =COUNTA(E9:E26) -> 18 | E28: =IF(C28=D28,"TODAS APROBADAS","HAY PRUEBAS POR REVISAR") -> HAY PRUEBAS POR REVISAR

Sheet CONFIG
A1: NUTRIMETRÍA · NMX-P1
A2: Configuración del paquete
A4: =HYPERLINK("#INICIO!A1","▶ VOLVER A INICIO") -> ▶ VOLVER A INICIO
A6: PARÁMETROS
A7: Herramientas que componen el paquete | D7: módulos | E7: 7
A8: Módulos que incorporan la base de composición | D8: módulos | E8: 5
A9: Hojas de trabajo sumadas | D9: hojas | E9: 73
A10: Tolerancia de las pruebas | D10: ± | E10: 0.0001
A12: LISTAS
A13: Este libro es la GUÍA del paquete: no calcula nada clínico. Toda la operación ocurre dentro de cada una de las siete herramientas, que son archivos independientes.

Sheet CHANGELOG
A1: NUTRIMETRÍA · NMX-P1
A2: Historial de versiones
A4: =HYPERLINK("#INICIO!A1","▶ VOLVER A INICIO") -> ▶ VOLVER A INICIO
A6: Versión | B6: Fecha | C6: Cambio | R6: Auditoria
A7: 1.0 | B7: 2026-07-24 | C7: Versión inicial de NMX-P1: guía del paquete de siete herramientas, con catálogo, flujo de trabajo, mapa de traspasos, situación de licencia y verificación de integridad. | J7: Fase 8 · Paquetes. | R7: Equipo Nutrimetría
A8: 1.0 | B8: 2026-07-24 | C8: Se asignó el código NMX-P1 en lugar de NMX-14. | J8: El código NMX-14 ya estaba ocupado por la evaluación nutricional pediátrica. El prefijo P distingue un paquete de una herramienta y deja libre la numeración correlativa. | R8: Equipo Nutrimetría
A9: 1.0 | B9: 2026-07-24 | C9: Hoja CONEXIONES con los nueve traspasos de datos entre herramientas. | J9: Las herramientas son archivos independientes sin vínculos automáticos: el traspaso es manual y hay que documentar exactamente qué se copia y adónde. | R9: Equipo Nutrimetría
A10: 1.0 | B10: 2026-07-24 | C10: Hoja LICENCIA que separa las cuatro herramientas bloqueadas de las tres libres. | J10: Solo cuatro incorporan la base de composición: el bloqueo no afecta por igual a todo el paquete y conviene que quede explícito. | R10: Equipo Nutrimetría
A11: 1.0 | B11: 2026-07-24 | C11: Hoja VERIFICACION con lista de comprobación de archivos y control previo a la entrega. | J11: Un archivo que abre pero con pruebas en revisión no está listo, y los casos de ejemplo deben retirarse antes de entregar. | R11: Equipo Nutrimetría
A12: 1.0 | B12: 2026-07-24 | C12: Diseño visual, barra de navegación y enlaces de retorno replicados de NMX-10 aprobado. | J12: Unificar la identidad de la colección. | R12: Equipo Nutrimetría
