Workbook
Name M12_AM_C1: M12_CONFIG!$B$49
Name M12_AM_C2: M12_CONFIG!$B$50
Name M12_AM_C3: M12_CONFIG!$B$51
Name M12_BRO_A: M12_CONFIG!$B$31
Name M12_BRO_B: M12_CONFIG!$B$32
Name M12_c_ampl: M12_CALCULOS!$B$30
Name M12_c_ClaseGrasa: M12_CALCULOS!$B$48
Name M12_c_ClaseIMC: M12_CALCULOS!$B$47
Name M12_c_Dens: M12_CALCULOS!$B$18
Name M12_c_DWc: M12_CALCULOS!$B$16
Name M12_c_DWm: M12_CALCULOS!$B$17
Name M12_c_estado: M12_CALCULOS!$B$31
Name M12_c_Gate: M12_CALCULOS!$B$13
Name M12_c_GrDeu: M12_CALCULOS!$B$21
Name M12_c_GrNavy: M12_CALCULOS!$B$20
Name M12_c_GrPli: M12_CALCULOS!$B$19
Name M12_c_GrRep: M12_CALCULOS!$B$24
Name M12_c_ICC: M12_CALCULOS!$B$40
Name M12_c_ICE: M12_CALCULOS!$B$41
Name M12_c_IMC: M12_CALCULOS!$B$9
Name M12_c_IMG: M12_CALCULOS!$B$36
Name M12_c_IMLG: M12_CALCULOS!$B$37
Name M12_c_max: M12_CALCULOS!$B$28
Name M12_c_MG: M12_CALCULOS!$B$34
Name M12_c_min: M12_CALCULOS!$B$27
Name M12_c_MLG: M12_CALCULOS!$B$35
Name M12_c_n: M12_CALCULOS!$B$25
Name M12_c_prom: M12_CALCULOS!$B$26
Name M12_c_rango: M12_CALCULOS!$B$29
Name M12_c_RiesgoCint: M12_CALCULOS!$B$42
Name M12_c_RiesgoICC: M12_CALCULOS!$B$43
Name M12_c_RiesgoICE: M12_CALCULOS!$B$44
Name M12_c_SumPli: M12_CALCULOS!$B$10
Name M12_c_TallaM: M12_CALCULOS!$B$8
Name M12_CAD_MAX: M12_CONFIG!$B$23
Name M12_CAD_MIN: M12_CONFIG!$B$22
Name M12_CIN_MAX: M12_CONFIG!$B$21
Name M12_CIN_MIN: M12_CONFIG!$B$20
Name M12_CINT_H: M12_CONFIG!$B$52
Name M12_CINT_M: M12_CONFIG!$B$53
Name M12_CUE_MAX: M12_CONFIG!$B$19
Name M12_CUE_MIN: M12_CONFIG!$B$18
Name M12_DEU_CONST: M12_CONFIG!$B$42
Name M12_DEU_EDAD: M12_CONFIG!$B$40
Name M12_DEU_IMC: M12_CONFIG!$B$39
Name M12_DEU_SEXO: M12_CONFIG!$B$41
Name M12_DISP_MAX: M12_CONFIG!$B$26
Name M12_EDAD_AM: M12_CONFIG!$B$48
Name M12_EDAD_MAX: M12_CONFIG!$B$11
Name M12_EDAD_MIN: M12_CONFIG!$B$10
Name M12_EST_MAX: M12_CONFIG!$B$15
Name M12_EST_MIN: M12_CONFIG!$B$14
Name M12_GRASA_MAX: M12_CONFIG!$B$25
Name M12_GRASA_MIN: M12_CONFIG!$B$24
Name M12_ICC_H: M12_CONFIG!$B$54
Name M12_ICC_M: M12_CONFIG!$B$55
Name M12_ICE_R: M12_CONFIG!$B$56
Name M12_IMC_C1: M12_CONFIG!$B$43
Name M12_IMC_C2: M12_CONFIG!$B$44
Name M12_IMC_C3: M12_CONFIG!$B$45

Sheet INICIO
A1: NUTRIMETRÍA · NMX-28 · PACK ANTROPOMETRÍA INTEGRADO
A2: Versión 2.1 · integración UDD separada · un solo archivo autónomo · alcance adulto
A4: Versión | B4: 2.1
A5: Componentes | B5: NMX-41 · NMX-36 · NMX-12 · NMX-16 · NMX-34 (educativo)
A6: Estado de validación | B6: NO REPRODUCIBLE: la afirmación 428/428 carece de 428 registros comprobables y no se aportaron los originales.
A7: Alcance | B7: Solo adultos (≥18 a). Sin extrapolación.
A8: Privacidad | B8: Use códigos; sin datos identificables.
A9: Aviso | B9: Exactitud matemática ≠ validación clínica. No es diagnóstico.
A10: ▶ AUDITORIA_INTEGRACION | B10: Matriz reproducible, fórmulas sin caché y limitaciones de la auditoría.
A11: Estado de auditoría | B11: 0 comparaciones original→integrado reproducibles; 192 comparaciones internas de módulos + 4 pruebas internas de integración documentadas.
A13: MÓDULOS Y NAVEGACIÓN
A14: =HYPERLINK("#DATOS!A1","▶ DATOS") -> ▶ DATOS
A15: =HYPERLINK("#MEDICIONES!A1","▶ MEDICIONES") -> ▶ MEDICIONES
A16: =HYPERLINK("#RESULTADOS!A1","▶ RESULTADOS") -> ▶ RESULTADOS
A17: =HYPERLINK("#SEGUIMIENTO!A1","▶ SEGUIMIENTO") -> ▶ SEGUIMIENTO
A18: =HYPERLINK("#CURVAS!A1","▶ CURVAS") -> ▶ CURVAS
A19: =HYPERLINK("#M41_INICIO!A1","▶ Control plicómetro (NMX-41)") -> ▶ Control plicómetro (NMX-41)
A20: =HYPERLINK("#M36_INICIO!A1","▶ Plicometría (NMX-36)") -> ▶ Plicometría (NMX-36)
A21: =HYPERLINK("#M12_INICIO!A1","▶ Composición (NMX-12)") -> ▶ Composición (NMX-12)
A22: =HYPERLINK("#M16_INICIO!A1","▶ Somatotipo (NMX-16)") -> ▶ Somatotipo (NMX-16)
A23: =HYPERLINK("#M34_INICIO!A1","▶ Edad metabólica ed. (NMX-34)") -> ▶ Edad metabólica ed. (NMX-34)
A24: =HYPERLINK("#MAPA_MODULOS!A1","▶ MAPA_MODULOS") -> ▶ MAPA_MODULOS
A25: =HYPERLINK("#FUENTES!A1","▶ FUENTES") -> ▶ FUENTES
A26: =HYPERLINK("#LICENCIAS!A1","▶ LICENCIAS") -> ▶ LICENCIAS
A27: =HYPERLINK("#PRUEBAS!A1","▶ PRUEBAS") -> ▶ PRUEBAS
A28: =HYPERLINK("#CHANGELOG!A1","▶ CHANGELOG") -> ▶ CHANGELOG
A32: PROTOCOLOS UDD · CAPA SEPARADA
A33: ▶ PROTOCOLOS_UDD | B33: Registro maestro de técnica, lado, posición, precisión, repeticiones, fuente y estado.
A34: ▶ COMPARADOR_PROTOCOLOS | B34: Selector UDD/ISAK con diferencias explícitas y sin mezcla metodológica.
A35: ▶ ECUACIONES_UDD | B35: Catálogo y calculadora documental separada de los motores originales.
A36: ▶ FUENTES_UDD | B36: Trazabilidad del Manual UDD, fuentes primarias, matrices y límites.
A37: ▶ PRUEBAS_UDD | B37: Pruebas funcionales, Open XML y regresión de motores.

Sheet DATOS
A1: NUTRIMETRÍA · NMX-28 · PACK ANTROPOMETRÍA INTEGRADO
A2: Fuente única de verdad · los módulos leen de aquí automáticamente
A4: LEYENDA · Celdas ARENA con texto AZUL = editables. Grises = calculadas/vinculadas. Solo adultos (≥18 a). Use CÓDIGOS, no datos identificables.
A6: Campo | B6: Valor
A7: ID de evaluación | B7: NMX-2026-0028
A8: Fecha | B8: 46236
A9: ID de persona | B9: PER-0007
A10: Sexo | B10: Hombre
A11: Edad (años) | B11: 34
A12: Peso (kg) | B12: 78.5
A13: Talla (cm) | B13: 176
A14: Evaluador | B14: EVAL-01
A15: Instrumento | B15: PLIC-01
A16: Método (informativo) | B16: cada módulo mantiene su propio selector
A17: Observaciones

Sheet MEDICIONES
A1: MEDICIONES ANTROPOMÉTRICAS
A2: Entrada única por sitio · fuera de tolerancia = advertencia, NO se promedia
A6: Sitio | B6: Med 1 | C6: Med 2 | D6: Med 3 | E6: Diferencia | F6: Tolerancia | G6: Promedio válido | H6: Unidad | I6: Evaluador | J6: Fecha | K6: Estado | L6: Observación
A7: Pectoral | B7: 8 | E7: =IF(COUNT(B7:D7)=0,"",MAX(B7:D7)-MIN(B7:D7)) -> 0 | F7: 5 | G7: =IF(COUNT(B7:D7)=0,"",IF((MAX(B7:D7)-MIN(B7:D7))<=F7,AVERAGE(B7:D7),"")) -> 8 | H7: mm | K7: =IF(COUNT(B7:D7)=0,"—",IF((MAX(B7:D7)-MIN(B7:D7))<=F7,"OK","FUERA DE TOLERANCIA")) -> OK
A8: Axilar medio | B8: 10 | E8: =IF(COUNT(B8:D8)=0,"",MAX(B8:D8)-MIN(B8:D8)) -> 0 | F8: 5 | G8: =IF(COUNT(B8:D8)=0,"",IF((MAX(B8:D8)-MIN(B8:D8))<=F8,AVERAGE(B8:D8),"")) -> 10 | H8: mm | K8: =IF(COUNT(B8:D8)=0,"—",IF((MAX(B8:D8)-MIN(B8:D8))<=F8,"OK","FUERA DE TOLERANCIA")) -> OK
A9: Tríceps | B9: 12 | E9: =IF(COUNT(B9:D9)=0,"",MAX(B9:D9)-MIN(B9:D9)) -> 0 | F9: 5 | G9: =IF(COUNT(B9:D9)=0,"",IF((MAX(B9:D9)-MIN(B9:D9))<=F9,AVERAGE(B9:D9),"")) -> 12 | H9: mm | K9: =IF(COUNT(B9:D9)=0,"—",IF((MAX(B9:D9)-MIN(B9:D9))<=F9,"OK","FUERA DE TOLERANCIA")) -> OK
A10: Subescapular | B10: 14 | E10: =IF(COUNT(B10:D10)=0,"",MAX(B10:D10)-MIN(B10:D10)) -> 0 | F10: 5 | G10: =IF(COUNT(B10:D10)=0,"",IF((MAX(B10:D10)-MIN(B10:D10))<=F10,AVERAGE(B10:D10),"")) -> 14 | H10: mm | K10: =IF(COUNT(B10:D10)=0,"—",IF((MAX(B10:D10)-MIN(B10:D10))<=F10,"OK","FUERA DE TOLERANCIA")) -> OK
A11: Bíceps | B11: 5 | E11: =IF(COUNT(B11:D11)=0,"",MAX(B11:D11)-MIN(B11:D11)) -> 0 | F11: 5 | G11: =IF(COUNT(B11:D11)=0,"",IF((MAX(B11:D11)-MIN(B11:D11))<=F11,AVERAGE(B11:D11),"")) -> 5 | H11: mm | K11: =IF(COUNT(B11:D11)=0,"—",IF((MAX(B11:D11)-MIN(B11:D11))<=F11,"OK","FUERA DE TOLERANCIA")) -> OK
A12: Suprailíaco | B12: 16 | E12: =IF(COUNT(B12:D12)=0,"",MAX(B12:D12)-MIN(B12:D12)) -> 0 | F12: 5 | G12: =IF(COUNT(B12:D12)=0,"",IF((MAX(B12:D12)-MIN(B12:D12))<=F12,AVERAGE(B12:D12),"")) -> 16 | H12: mm | K12: =IF(COUNT(B12:D12)=0,"—",IF((MAX(B12:D12)-MIN(B12:D12))<=F12,"OK","FUERA DE TOLERANCIA")) -> OK
A13: Abdominal | B13: 20 | E13: =IF(COUNT(B13:D13)=0,"",MAX(B13:D13)-MIN(B13:D13)) -> 0 | F13: 5 | G13: =IF(COUNT(B13:D13)=0,"",IF((MAX(B13:D13)-MIN(B13:D13))<=F13,AVERAGE(B13:D13),"")) -> 20 | H13: mm | K13: =IF(COUNT(B13:D13)=0,"—",IF((MAX(B13:D13)-MIN(B13:D13))<=F13,"OK","FUERA DE TOLERANCIA")) -> OK
A14: Muslo | B14: 12 | E14: =IF(COUNT(B14:D14)=0,"",MAX(B14:D14)-MIN(B14:D14)) -> 0 | F14: 5 | G14: =IF(COUNT(B14:D14)=0,"",IF((MAX(B14:D14)-MIN(B14:D14))<=F14,AVERAGE(B14:D14),"")) -> 12 | H14: mm | K14: =IF(COUNT(B14:D14)=0,"—",IF((MAX(B14:D14)-MIN(B14:D14))<=F14,"OK","FUERA DE TOLERANCIA")) -> OK
A15: Cuello | B15: 38 | E15: =IF(COUNT(B15:D15)=0,"",MAX(B15:D15)-MIN(B15:D15)) -> 0 | F15: 1 | G15: =IF(COUNT(B15:D15)=0,"",IF((MAX(B15:D15)-MIN(B15:D15))<=F15,AVERAGE(B15:D15),"")) -> 38 | H15: cm | K15: =IF(COUNT(B15:D15)=0,"—",IF((MAX(B15:D15)-MIN(B15:D15))<=F15,"OK","FUERA DE TOLERANCIA")) -> OK
A16: Cintura | B16: 85 | E16: =IF(COUNT(B16:D16)=0,"",MAX(B16:D16)-MIN(B16:D16)) -> 0 | F16: 1 | G16: =IF(COUNT(B16:D16)=0,"",IF((MAX(B16:D16)-MIN(B16:D16))<=F16,AVERAGE(B16:D16),"")) -> 85 | H16: cm | K16: =IF(COUNT(B16:D16)=0,"—",IF((MAX(B16:D16)-MIN(B16:D16))<=F16,"OK","FUERA DE TOLERANCIA")) -> OK
A17: Cadera | B17: 98 | E17: =IF(COUNT(B17:D17)=0,"",MAX(B17:D17)-MIN(B17:D17)) -> 0 | F17: 1 | G17: =IF(COUNT(B17:D17)=0,"",IF((MAX(B17:D17)-MIN(B17:D17))<=F17,AVERAGE(B17:D17),"")) -> 98 | H17: cm | K17: =IF(COUNT(B17:D17)=0,"—",IF((MAX(B17:D17)-MIN(B17:D17))<=F17,"OK","FUERA DE TOLERANCIA")) -> OK
A18: Brazo corregido | B18: 32 | E18: =IF(COUNT(B18:D18)=0,"",MAX(B18:D18)-MIN(B18:D18)) -> 0 | F18: 1 | G18: =IF(COUNT(B18:D18)=0,"",IF((MAX(B18:D18)-MIN(B18:D18))<=F18,AVERAGE(B18:D18),"")) -> 32 | H18: cm | K18: =IF(COUNT(B18:D18)=0,"—",IF((MAX(B18:D18)-MIN(B18:D18))<=F18,"OK","FUERA DE TOLERANCIA")) -> OK
... A22: Fémur (diámetro) | B22: 9 | E22: =IF(COUNT(B22:D22)=0,"",MAX(B22:D22)-MIN(B22:D22)) -> 0 | F22: 0.5 | G22: =IF(COUNT(B22:D22)=0,"",IF((MAX(B22:D22)-MIN(B22:D22))<=F22,AVERAGE(B22:D22),"")) -> 9 | H22: cm | K22: =IF(COUNT(B22:D22)=0,"—",IF((MAX(B22:D22)-MIN(B22:D22))<=F22,"OK","FUERA DE TOLERANCIA")) -> OK

Sheet SEGUIMIENTO
A1: SEGUIMIENTO LONGITUDINAL
A4: La tabla se expande al escribir; las curvas se actualizan solas
A6: Fecha | B6: Peso | C6: IMC | D6: Cintura | E6: ΣPliegues | F6: %Grasa | G6: MasaGrasa | H6: MasaLibre | I6: Somatotipo | J6: ETM | K6: Instrumento | L6: Evaluador
A7: 2026-08-02

Sheet CURVAS
A1: CURVAS DE TENDENCIA
A2: Se actualizan al agregar filas en SEGUIMIENTO

Sheet RESULTADOS
A1: RESULTADOS INTEGRADOS
A2: Referencias vivas a los módulos · exactitud matemática ≠ validación clínica
A6: Indicador | B6: Valor | C6: Procedencia
A7: IMC (kg/m²) | B7: =M12_c_IMC -> 25.3422 | C7: NMX-12
A8: Índice cintura/estatura | B8: =M12_c_ICE -> 0.48295455 | C8: NMX-12
A9: Riesgo cintura/estatura | B9: =M12_c_RiesgoICE -> Sin riesgo aumentado | C9: NMX-12
A10: Σ pliegues (7) | B10: =M36_c_Sum7 -> 92 | C10: NMX-36
A11: Densidad DW | B11: =M36_c_BDdw -> 1.0512379 | C11: NMX-36
A12: % grasa (método reportado) | B12: =M36_c_GrRep -> 0.13989155 | C12: NMX-36
A13: Masa grasa (kg) | B13: =M36_c_MG -> 10.981487 | C13: NMX-36
A14: Masa libre de grasa (kg) | B14: =M36_c_MLG -> 67.518513 | C14: NMX-36
A15: FMI | B15: =M36_c_IMG -> 3.5451597 | C15: NMX-36
A16: FFMI | B16: =M36_c_IMLG -> 21.797041 | C16: NMX-36
A17: Endomorfia | B17: =M16_c_Endo -> 4.146746 | C17: NMX-16
A18: Mesomorfia | B18: =M16_c_Meso -> 3.8497 | C18: NMX-16
A19: Ectomorfia | B19: =M16_c_Ecto -> 1.5084995 | C19: NMX-16
A20: Somatotipo | B20: =M16_c_Soma -> 04 - 04 - 02 | C20: NMX-16
A21: Somatocarta X | B21: =M16_c_SX -> -2.6382465 | C21: NMX-16
A22: Somatocarta Y | B22: =M16_c_SY -> 2.0441545 | C22: NMX-16
A23: ETM intraevaluador | B23: =M41_v_etm -> 0.29495762 | C23: NMX-41
A25: INDICADOR EDUCATIVO — NO DIAGNÓSTICO
A26: Edad metabólica: módulo NMX-34, EDUCATIVO y desactivado por defecto. No forma parte del diagnóstico antropométrico. No usar ante riesgo de TCA.
A27: =HYPERLINK("#M34_INICIO!A1","▶ Abrir módulo educativo (bajo su criterio)") -> ▶ Abrir módulo educativo (bajo su criterio)

Sheet M41_INICIO
A1: NUTRIMETRÍA · NMX-41
A2: Software acompañante para plicómetro · versión 1.0 · Fase 7 · especialidades y productos complementarios
A4: Navegación — use las pestañas inferiores del libro
A5: =HYPERLINK("#M41_DATOS!A1","▶ DATOS") -> ▶ DATOS | C5: =HYPERLINK("#M41_CALIBRACION!A1","▶ CALIBRACION") -> ▶ CALIBRACION | E5: =HYPERLINK("#M41_TECNICA!A1","▶ TECNICA") -> ▶ TECNICA | G5: =HYPERLINK("#M41_FIABILIDAD!A1","▶ FIABILIDAD") -> ▶ FIABILIDAD | I5: =HYPERLINK("#M41_SEGUIMIENTO!A1","▶ SEGUIMIENTO") -> ▶ SEGUIMIENTO | K5: =HYPERLINK("#M41_FUENTES!A1","▶ FUENTES") -> ▶ FUENTES | M5: =HYPERLINK("#M41_PRUEBAS!A1","▶ PRUEBAS") -> ▶ PRUEBAS | O5: =HYPERLINK("#M41_CONFIG!A1","▶ CONFIG") -> ▶ CONFIG
A6: Equipo y evaluador | C6: Control del instrumento | E6: Sitios y procedimiento | G6: Error técnico de medición | I6: ¿El cambio es real? | K6: Referencias y trazabilidad | M6: Control de calidad | O6: Constantes
A7: =HYPERLINK("#M41_CHANGELOG!A1","▶ CHANGELOG") -> ▶ CHANGELOG
A8: Historial
A10: Código del producto | C10: NMX-41
A11: Versión | C11: 1.0
A12: Fecha | C12: 2026-07-24
A13: Qué acompaña | C13: Cualquier plicómetro de uso profesional
A14: Complementos | C14: NMX-36 aplica ecuaciones de composición · NMX-20 integra pliegues y somatotipo
A15: Formato | C15: .xlsx sin macros · Microsoft 365 (Windows) y Excel 2021 · sin funciones matriciales
A16: Responsable | C16: Equipo Nutrimetría (completar por el titular)
A18: LA PREGUNTA QUE ESTE LIBRO RESPONDE
A19: Un pliegue bajó de dieciocho a diecisiete milímetros. ¿Cambió la persona o se equivocó quien midió? Sin conocer el error del evaluador esa pregunta no tiene respuesta, y se informan como cambios reales variaciones que son solo ruido del método.
A20: Este libro calcula el error propio de cada evaluador a partir de mediciones por duplicado, y con él establece cuánto debe cambiar un pliegue para que el cambio sea distinguible del error.
A21: También verifica el instrumento contra patrones de espesor conocido: un plicómetro descalibrado produce mediciones consistentes pero equivocadas, y ese error no se detecta repitiendo la medida.
A22: El seguimiento se hace sobre la SUMA de pliegues y no sobre pliegues aislados, porque al sumar varios sitios el error crece con la raíz del número de mediciones y la suma resulta proporcionalmente más sensible.
A24: AVISO DE ALCANCE — LÉALO ANTES DE USAR
A25: EXACTITUD MATEMÁTICA ≠ VALIDACIÓN CLÍNICA. Este archivo no está validado clínicamente y no constituye diagnóstico.
A26: Este libro NO estima densidad corporal, porcentaje de grasa ni somatotipo: se ocupa de la calidad de la medición previa. Para las ecuaciones de composición corporal use NMX-36 o NMX-20.
A27: El libro NO sustituye la formación práctica supervisada: describir la técnica no equivale a dominarla, y los criterios de error solo se alcanzan con entrenamiento.
A28: Los pliegues ESTIMAN el tejido adiposo subcutáneo. La referencia para composición corporal son la densitometría y el pesaje hidrostático.
A29: El error técnico es específico de cada evaluador, cada sitio anatómico y cada rango de espesor: no traslade el resultado de un sitio a otro ni de un evaluador a otro.
A30: Ninguna corrección posterior recupera mediciones tomadas con un instrumento descalibrado o con técnica deficiente.
A32: FLUJO DE USO
A33: 1 | C33: En DATOS registre el instrumento, su número de serie y el evaluador. Ambos deben quedar documentados en cada evaluación.
A34: 2 | C34: En CALIBRACIÓN verifique el plicómetro contra patrones de espesor conocido y complete la revisión mecánica. El libro emite un dictamen de aptitud.
A35: 3 | C35: Revise TÉCNICA antes de medir: secuencia, sitios anatómicos y condiciones que alteran el resultado.
A36: 4 | C36: En FIABILIDAD registre mediciones por duplicado en al menos diez personas para obtener su propio error técnico.
A37: 5 | C37: En SEGUIMIENTO compare dos evaluaciones: el libro indica si el cambio observado supera el error del método.
A38: 6 | C38: Verifique el instrumento cada seis meses y siempre después de una caída, y repita el cálculo de error cuando cambie de plicómetro.

Sheet M41_DATOS
A1: NUTRIMETRÍA · NMX-41
A2: Instrumento y evaluador
A4: =HYPERLINK("#M41_INICIO!A1","▶ VOLVER A INICIO") -> ▶ VOLVER A INICIO
A6: El plicómetro es un instrumento de medición: su resultado depende tanto del aparato como de quien lo usa. Este libro documenta ambos y cuantifica el error, para que usted sepa qué diferencias son reales y cuáles son ruido del método.
A10: IDENTIFICACIÓN DEL INSTRUMENTO
A11: Marca del plicómetro | C11: Harpenden
A12: Modelo | C12: —
A13: Número de serie | C13: — | L13: Permite trazar qué aparato tomó cada medición
A14: Fecha de adquisición | C14: 2024-03-15
A15: Presión declarada por el fabricante (g/mm²) | C15: 10 | L15: El estándar es 10 g/mm²
A16: Rango de medición (mm) | C16: 0 a 80
A17: Resolución de la escala (mm) | C17: 0.2 | L17: Cuánto vale la división más pequeña
A18: Fecha de la última verificación | C18: 2026-07-20
A19: Estado del instrumento | C19: Correcto
A21: EVALUADOR
A22: Nombre del evaluador | C22: Caso de ejemplo
A23: Nivel de acreditación | C23: En formación | L23: Condiciona el error esperable
A24: Fecha de la última evaluación de error | C24: 2026-07-20
A25: Número de mediciones realizadas en el último año | C25: 120
A26: ¿Midió siempre el mismo lado del cuerpo? | C26: Sí | L26: Por convención se mide el lado derecho
A27: Observaciones | C27: —
A29: Registre siempre QUIÉN midió y CON QUÉ aparato. Un cambio de evaluador o de instrumento entre dos evaluaciones introduce una fuente de variación que puede superar el cambio biológico que se busca detectar: en ese caso la comparación entre ambas mediciones deja de ser válida.

Sheet M41_CALIBRACION
A1: NUTRIMETRÍA · NMX-41
A2: Control del instrumento · verificación periódica
A4: =HYPERLINK("#M41_INICIO!A1","▶ VOLVER A INICIO") -> ▶ VOLVER A INICIO
A6: Un plicómetro descalibrado produce mediciones consistentes pero equivocadas: el error no se detecta repitiendo la medida, porque se repite igual. La única forma de detectarlo es verificar contra un patrón de espesor conocido y revisar la tensión del resorte.
A10: VERIFICACIÓN CONTRA PATRONES DE ESPESOR CONOCIDO
A11: Patrón | B11: Espesor real (mm) | C11: Lectura 1 | D11: Lectura 2 | E11: Lectura 3 | F11: Media | G11: Error (mm) | H11: Resultado
A12: Bloque patrón A | B12: 10 | C12: 10 | D12: 10.1 | E12: 10 | F12: =IF(COUNT(C12:E12)=0,"ND",AVERAGE(C12:E12)) -> 10.033333 | G12: =IF(OR(NOT(ISNUMBER(F12)),NOT(ISNUMBER(B12))),"ND",F12-B12) -> 0.033333333 | H12: =IF(NOT(ISNUMBER(G12)),"ND",IF(ABS(G12)<=M41_u_patron,"Dentro de tolerancia","FUERA DE TOLERANCIA: el instrumento requiere ajuste")) -> Dentro de tolerancia
A13: Bloque patrón B | B13: 20 | C13: 20 | D13: 20 | E13: 20.1 | F13: =IF(COUNT(C13:E13)=0,"ND",AVERAGE(C13:E13)) -> 20.033333 | G13: =IF(OR(NOT(ISNUMBER(F13)),NOT(ISNUMBER(B13))),"ND",F13-B13) -> 0.033333333 | H13: =IF(NOT(ISNUMBER(G13)),"ND",IF(ABS(G13)<=M41_u_patron,"Dentro de tolerancia","FUERA DE TOLERANCIA: el instrumento requiere ajuste")) -> Dentro de tolerancia
A14: Bloque patrón C | B14: 40 | C14: 40.2 | D14: 40.1 | E14: 40.2 | F14: =IF(COUNT(C14:E14)=0,"ND",AVERAGE(C14:E14)) -> 40.166667 | G14: =IF(OR(NOT(ISNUMBER(F14)),NOT(ISNUMBER(B14))),"ND",F14-B14) -> 0.16666667 | H14: =IF(NOT(ISNUMBER(G14)),"ND",IF(ABS(G14)<=M41_u_patron,"Dentro de tolerancia","FUERA DE TOLERANCIA: el instrumento requiere ajuste")) -> Dentro de tolerancia
A15: Bloque patrón D | B15: 60 | C15: 60.1 | D15: 60.2 | E15: 60.1 | F15: =IF(COUNT(C15:E15)=0,"ND",AVERAGE(C15:E15)) -> 60.133333 | G15: =IF(OR(NOT(ISNUMBER(F15)),NOT(ISNUMBER(B15))),"ND",F15-B15) -> 0.13333333 | H15: =IF(NOT(ISNUMBER(G15)),"ND",IF(ABS(G15)<=M41_u_patron,"Dentro de tolerancia","FUERA DE TOLERANCIA: el instrumento requiere ajuste")) -> Dentro de tolerancia
A16: Error medio del instrumento | G16: =IF(COUNT(G12:G15)=0,"ND",AVERAGE(G12:G15)) -> 0.091666667 | H16: =IF(NOT(ISNUMBER(G16)),"ND",IF(ABS(G16)<=M41_u_patron,"Instrumento apto para uso","Instrumento NO apto: derive a ajuste antes de seguir midiendo")) -> Instrumento apto para uso
A18: REVISIÓN MECÁNICA
A19: ¿La aguja marca cero con las ramas cerradas? | C19: Sí
A20: ¿Las ramas cierran de forma paralela? | C20: Sí
A21: ¿El resorte recupera su posición sin trabarse? | C21: Sí
A22: ¿Las superficies de contacto están limpias y sin desgaste? | C22: Sí
A23: ¿La escala se lee con nitidez? | C23: Sí
A24: ¿El instrumento ha sufrido caídas o golpes desde la última revisión? | C24: No
A26: Verificaciones conformes | C26: =COUNTIF(C19:C23,"Sí")+COUNTIF(C24,"No") -> 6 | L26: La última pregunta invierte el sentido: allí lo esperable es No
A27: Estado de la revisión mecánica | C27: =IF(C26=6,"Revisión mecánica conforme en los seis puntos.","REVISAR: "&(6-C26)&" punto(s) no conforme(s). Resuélvalos antes de usar el instrumento.") -> Revisión mecánica conforme en los seis puntos.
A28: DICTAMEN DEL INSTRUMENTO | C28: =IF(OR(NOT(ISNUMBER(G16)),NOT(ISNUMBER(C26))),"ND",IF(AND(ABS(G16)<=M41_u_patron,C26=6),"APTO PARA USO","NO APTO: corrija los hallazgos antes de continuar midiendo")) -> APTO PARA USO
A30: Verifique el instrumento al menos cada seis meses, y siempre después de una caída o de un periodo prolongado sin uso. Un plicómetro cuya lectura se desvía de forma constante introduce un sesgo sistemático: todas las mediciones quedan corridas en la misma dirección, algo que ningún cálculo posterior puede corregir si no se documentó.

Sheet M41_TECNICA
A1: NUTRIMETRÍA · NMX-41
A2: Procedimiento de medición · sitios y secuencia
A4: =HYPERLINK("#M41_INICIO!A1","▶ VOLVER A INICIO") -> ▶ VOLVER A INICIO
A6: SECUENCIA DE CADA MEDICIÓN
A7: 1 | C7: Marque el punto anatómico antes de tomar el pliegue: si se mide sin marcar, cada repetición cae en un lugar distinto y el error se dispara.
A8: 2 | C8: Tome el pliegue con los dedos pulgar e índice, a un centímetro del punto marcado, levantando piel y tejido subcutáneo sin incluir músculo.
A9: 3 | C9: Aplique las ramas del plicómetro perpendiculares al pliegue, sobre el punto marcado, manteniendo la toma con los dedos.
A10: 4 | C10: Espere dos segundos antes de leer: el tejido se comprime y la aguja se estabiliza. Leer antes sobreestima; esperar demasiado subestima.
A11: 5 | C11: Lea sin soltar el pliegue y registre de inmediato.
A12: 6 | C12: Mida todos los sitios en orden y recién entonces repita la serie completa: medir dos veces seguidas el mismo sitio subestima la segunda lectura por compresión del tejido.
A14: REFERENCIA DE SITIOS ANATÓMICOS
A15: Sitio | B15: Ubicación del punto | C15: Dirección del pliegue | D15: Posición de la persona
A16: =INDEX(M41_rng_sitios,1,1) -> Tríceps | B16: =INDEX(M41_rng_sitios,1,2) -> Punto medio entre acromion y olécranon, cara posterior del brazo | C16: =INDEX(M41_rng_sitios,1,3) -> Vertical | D16: =INDEX(M41_rng_sitios,1,4) -> De pie, brazo relajado
A17: =INDEX(M41_rng_sitios,2,1) -> Subescapular | B17: =INDEX(M41_rng_sitios,2,2) -> Dos centímetros por debajo del ángulo inferior de la escápula | C17: =INDEX(M41_rng_sitios,2,3) -> Oblicua, hacia abajo y afuera | D17: =INDEX(M41_rng_sitios,2,4) -> De pie, brazos a los lados
A18: =INDEX(M41_rng_sitios,3,1) -> Bíceps | B18: =INDEX(M41_rng_sitios,3,2) -> Punto medio del brazo, cara anterior, sobre el vientre del bíceps | C18: =INDEX(M41_rng_sitios,3,3) -> Vertical | D18: =INDEX(M41_rng_sitios,3,4) -> De pie, brazo relajado y supinado
A19: =INDEX(M41_rng_sitios,4,1) -> Suprailíaco | B19: =INDEX(M41_rng_sitios,4,2) -> Sobre la cresta ilíaca, en la línea axilar media | C19: =INDEX(M41_rng_sitios,4,3) -> Oblicua, siguiendo la cresta | D19: =INDEX(M41_rng_sitios,4,4) -> De pie, brazo separado
A20: =INDEX(M41_rng_sitios,5,1) -> Supraespinal | B20: =INDEX(M41_rng_sitios,5,2) -> Intersección de la línea axilar anterior con la cresta ilíaca | C20: =INDEX(M41_rng_sitios,5,3) -> Oblicua, hacia abajo y adentro | D20: =INDEX(M41_rng_sitios,5,4) -> De pie, brazo relajado
A21: =INDEX(M41_rng_sitios,6,1) -> Abdominal | B21: =INDEX(M41_rng_sitios,6,2) -> Cinco centímetros a la derecha del ombligo | C21: =INDEX(M41_rng_sitios,6,3) -> Vertical | D21: =INDEX(M41_rng_sitios,6,4) -> De pie, abdomen relajado
A22: =INDEX(M41_rng_sitios,7,1) -> Muslo anterior | B22: =INDEX(M41_rng_sitios,7,2) -> Punto medio entre pliegue inguinal y borde superior de la rótula | C22: =INDEX(M41_rng_sitios,7,3) -> Vertical | D22: =INDEX(M41_rng_sitios,7,4) -> Sentado, rodilla a noventa grados
A23: =INDEX(M41_rng_sitios,8,1) -> Pantorrilla medial | B23: =INDEX(M41_rng_sitios,8,2) -> Cara medial, en el perímetro máximo | C23: =INDEX(M41_rng_sitios,8,3) -> Vertical | D23: =INDEX(M41_rng_sitios,8,4) -> Sentado o de pie con la pierna apoyada
A25: CONDICIONES QUE ALTERAN LA MEDICIÓN
A26: Ejercicio reciente | B26: La redistribución de líquido tras el ejercicio modifica el espesor del pliegue: mida antes de entrenar o varias horas después.
A27: Estado de hidratación | B27: La deshidratación y la retención de líquido cambian el resultado sin que haya cambiado la grasa corporal.
A28: Momento del ciclo menstrual | B28: La retención de líquido puede alterar las mediciones: registre en qué fase se midió y procure repetir en la misma.
A29: Temperatura ambiente | B29: El frío contrae los tejidos y dificulta tomar el pliegue de forma reproducible.
A30: Cambio de evaluador | B30: Es la principal fuente de variación entre dos evaluaciones. Si cambia el evaluador, la comparación pierde validez salvo que se conozca el error entre ambos.
A31: Cambio de instrumento | B31: Dos plicómetros de marcas distintas pueden diferir de forma sistemática: no compare mediciones tomadas con aparatos diferentes.
A33: Estandarizar las condiciones importa tanto como la técnica. Una medición tomada en condiciones distintas a la anterior no es comparable, aunque la técnica haya sido impecable en ambas.

Sheet M41_SEGUIMIENTO
A1: NUTRIMETRÍA · NMX-41
A2: ¿El cambio observado es real o es error de medición?
A4: =HYPERLINK("#M41_INICIO!A1","▶ VOLVER A INICIO") -> ▶ VOLVER A INICIO
A6: Esta es la pregunta que un plicómetro debe poder responder y que casi ningún software responde. Un pliegue que baja de 18 a 17 milímetros puede reflejar un cambio real o simplemente el error de quien mide. Aquí se compara el cambio observado con el error propio del evaluador.
A10: COMPARACIÓN ENTRE DOS EVALUACIONES
A11: Sitio | B11: Evaluación inicial (mm) | C11: Evaluación de control (mm) | D11: Cambio (mm) | E11: Cambio mínimo detectable | F11: ¿Distinguible del error?
A12: Tríceps | B12: 12.4 | C12: 11 | D12: =IF(OR(NOT(ISNUMBER(B12)),NOT(ISNUMBER(C12))),"",C12-B12) -> -1.4 | E12: =IF(NOT(ISNUMBER(D12)),"",M41_v_mdc) -> 0.81758082 | F12: =IF(NOT(ISNUMBER(D12)),"",IF(ABS(D12)>M41_v_mdc,"Sí · el cambio supera el error","No · queda dentro del error de medición")) -> Sí · el cambio supera el error
A13: Subescapular | B13: 14 | C13: 12.8 | D13: =IF(OR(NOT(ISNUMBER(B13)),NOT(ISNUMBER(C13))),"",C13-B13) -> -1.2 | E13: =IF(NOT(ISNUMBER(D13)),"",M41_v_mdc) -> 0.81758082 | F13: =IF(NOT(ISNUMBER(D13)),"",IF(ABS(D13)>M41_v_mdc,"Sí · el cambio supera el error","No · queda dentro del error de medición")) -> Sí · el cambio supera el error
A14: Bíceps | B14: 6 | C14: 5.6 | D14: =IF(OR(NOT(ISNUMBER(B14)),NOT(ISNUMBER(C14))),"",C14-B14) -> -0.4 | E14: =IF(NOT(ISNUMBER(D14)),"",M41_v_mdc) -> 0.81758082 | F14: =IF(NOT(ISNUMBER(D14)),"",IF(ABS(D14)>M41_v_mdc,"Sí · el cambio supera el error","No · queda dentro del error de medición")) -> No · queda dentro del error de medición
A15: Suprailíaco | B15: 16 | C15: 14.2 | D15: =IF(OR(NOT(ISNUMBER(B15)),NOT(ISNUMBER(C15))),"",C15-B15) -> -1.8 | E15: =IF(NOT(ISNUMBER(D15)),"",M41_v_mdc) -> 0.81758082 | F15: =IF(NOT(ISNUMBER(D15)),"",IF(ABS(D15)>M41_v_mdc,"Sí · el cambio supera el error","No · queda dentro del error de medición")) -> Sí · el cambio supera el error
A16: Abdominal | B16: 18 | C16: 16.2 | D16: =IF(OR(NOT(ISNUMBER(B16)),NOT(ISNUMBER(C16))),"",C16-B16) -> -1.8 | E16: =IF(NOT(ISNUMBER(D16)),"",M41_v_mdc) -> 0.81758082 | F16: =IF(NOT(ISNUMBER(D16)),"",IF(ABS(D16)>M41_v_mdc,"Sí · el cambio supera el error","No · queda dentro del error de medición")) -> Sí · el cambio supera el error
A17: Muslo anterior | B17: 10.2 | C17: 9.4 | D17: =IF(OR(NOT(ISNUMBER(B17)),NOT(ISNUMBER(C17))),"",C17-B17) -> -0.8 | E17: =IF(NOT(ISNUMBER(D17)),"",M41_v_mdc) -> 0.81758082 | F17: =IF(NOT(ISNUMBER(D17)),"",IF(ABS(D17)>M41_v_mdc,"Sí · el cambio supera el error","No · queda dentro del error de medición")) -> No · queda dentro del error de medición
D18: =IF(OR(NOT(ISNUMBER(B18)),NOT(ISNUMBER(C18))),"",C18-B18) | E18: =IF(NOT(ISNUMBER(D18)),"",M41_v_mdc) | F18: =IF(NOT(ISNUMBER(D18)),"",IF(ABS(D18)>M41_v_mdc,"Sí · el cambio supera el error","No · queda dentro del error de medición"))
D19: =IF(OR(NOT(ISNUMBER(B19)),NOT(ISNUMBER(C19))),"",C19-B19) | E19: =IF(NOT(ISNUMBER(D19)),"",M41_v_mdc) | F19: =IF(NOT(ISNUMBER(D19)),"",IF(ABS(D19)>M41_v_mdc,"Sí · el cambio supera el error","No · queda dentro del error de medición"))
A20: SUMA DE PLIEGUES | B20: =SUM(B12:B19) -> 76.6 | C20: =SUM(C12:C19) -> 69.2 | D20: =IF(OR(NOT(ISNUMBER(B20)),NOT(ISNUMBER(C20))),"",C20-B20) -> -7.4 | E20: =IF(COUNT(D12:D19)=0,"ND",M41_k_z*SQRT(2)*M41_v_etm*SQRT(COUNT(D12:D19))) -> 2.0026558 | F20: =IF(OR(NOT(ISNUMBER(D20)),NOT(ISNUMBER(E20))),"ND",IF(ABS(D20)>E20,"Sí · el cambio de la suma supera el error","No · queda dentro del error de medición")) -> Sí · el cambio de la suma supera el error
A22: POR QUÉ LA SUMA ES MÁS SENSIBLE QUE UN PLIEGUE AISLADO
A23: Error de un pliegue individual (mm) | C23: =M41_v_etm -> 0.29495762
A24: Número de pliegues sumados | C24: =COUNT(D12:D19) -> 6
A25: Error de la suma (mm) | C25: =IF(OR(NOT(ISNUMBER(M41_v_etm)),NOT(ISNUMBER(C24))),"ND",M41_v_etm*SQRT(C24)) -> 0.72249567 | L25: El error crece con la raíz del número de pliegues, no de forma proporcional
A26: Cambio relativo mínimo detectable en la suma | C26: =IF(OR(NOT(ISNUMBER(E20)),NOT(ISNUMBER(B20)),B20=0),"ND",E20/B20) -> 0.026144332
A27: Qué significa | C27: =IF(OR(NOT(ISNUMBER(E20)),NOT(ISNUMBER(M41_v_mdc))),"ND","Cada pliegue por separado necesita cambiar más de "&TEXT(M41_v_mdc,"0.00")&" mm para ser distinguible del error. La suma de "&TEXT(C24,"0")&" pliegues necesita cambiar más de "&TEXT(E20,"0.00")&" mm, que representa una proporción MENOR del total: por eso el seguimiento se hace sobre la suma y no sobre pliegues aislados.") -> Cada pliegue por separado necesita cambiar más de 001 mm para ser distinguible del error. La suma de 6 pliegues necesita cambiar más de 002 mm, que representa una proporción MENOR del total: por eso el seguimiento se hace sobre la suma y no sobre pliegues aislados.
A29: CONDICIONES DE COMPARABILIDAD
A30: ¿Midió el mismo evaluador ambas veces? | C30: Sí
A31: ¿Usó el mismo plicómetro? | C31: Sí
A32: ¿Se respetaron condiciones similares de hidratación y horario? | C32: Sí
A33: ¿El instrumento estaba verificado en ambas ocasiones? | C33: Sí
A34: Validez de la comparación | C34: =IF(COUNTIF(C30:C33,"Sí")=4,"Las cuatro condiciones se cumplen: la comparación entre ambas evaluaciones es válida.","ATENCIÓN: "&(4-COUNTIF(C30:C33,"Sí"))&" condición(es) no se cumple(n). El cambio observado puede deberse a esa diferencia y no a un cambio real de la persona.") -> Las cuatro condiciones se cumplen: la comparación entre ambas evaluaciones es válida.
A36: CONCLUSIÓN DEL SEGUIMIENTO | C36: =IF(OR(NOT(ISNUMBER(D20)),NOT(ISNUMBER(E20))),"ND: faltan datos",IF(COUNTIF(C30:C33,"Sí")<4,"No concluyente: primero resuelva las condiciones de comparabilidad.",IF(ABS(D20)>E20,"Cambio DISTINGUIBLE del error de medición: la suma de pliegues varió "&TEXT(D20,"+0.0;-0.0")&" mm, por sobre el umbral de "&TEXT(E20,"0.00")&" mm.","Cambio NO distinguible del error: la variación de "&TEXT(D20,"+0.0;-0.0")&" mm queda dentro del margen del método. No informe un cambio como si fuera real."))) -> Cambio DISTINGUIBLE del error de medición: la suma de pliegues varió -07 mm, por sobre el umbral de 002 mm.
A38: Sitio | B38: Cambio (mm)
A39: =A12 -> Tríceps | B39: =D12 -> -1.4
A40: =A13 -> Subescapular | B40: =D13 -> -1.2
A41: =A14 -> Bíceps | B41: =D14 -> -0.4
A42: =A15 -> Suprailíaco | B42: =D15 -> -1.8
A43: =A16 -> Abdominal | B43: =D16 -> -1.8
A44: =A17 -> Muslo anterior | B44: =D17 -> -0.8
A46: Informar un cambio que no supera el error de medición es un error frecuente y evitable. Si la variación queda dentro del margen del método, la respuesta correcta es que no se puede afirmar que haya cambiado, no que se mantuvo igual: ambas cosas son distintas.

Sheet M41_FIABILIDAD
A1: NUTRIMETRÍA · NMX-41
A2: Error técnico de medición · cuánto se equivoca este evaluador
A4: =HYPERLINK("#M41_INICIO!A1","▶ VOLVER A INICIO") -> ▶ VOLVER A INICIO
A6: Para conocer su propio error, mida el mismo pliegue DOS veces en al menos diez personas distintas, completando la serie de sitios entre ambas repeticiones. No mida dos veces seguidas el mismo sitio: la compresión del tejido hace que la segunda lectura sea menor y el error calculado saldría falsamente bajo.
A11: MEDICIONES POR DUPLICADO
A12: Nº | B12: Sujeto | C12: Sitio medido | D12: Medida 1 (mm) | E12: Medida 2 (mm) | F12: Media | G12: Diferencia | H12: Diferencia² | I12: Control
A13: 1 | B13: Sujeto 1 | C13: Tríceps | D13: 12.4 | E13: 12.1 | F13: =IF(OR(NOT(ISNUMBER(D13)),NOT(ISNUMBER(E13))),"",(D13+E13)/2) -> 12.25 | G13: =IF(OR(NOT(ISNUMBER(D13)),NOT(ISNUMBER(E13))),"",D13-E13) -> 0.3 | H13: =IF(NOT(ISNUMBER(G13)),"",G13^2) -> 0.09 | I13: =IF(OR(NOT(ISNUMBER(G13)),NOT(ISNUMBER(F13)),F13=0),"",IF(ABS(G13)/F13>M41_u_dif,"REVISAR: las dos medidas difieren más del 5%","OK")) -> OK
A14: 2 | B14: Sujeto 2 | C14: Tríceps | D14: 18.6 | E14: 18.9 | F14: =IF(OR(NOT(ISNUMBER(D14)),NOT(ISNUMBER(E14))),"",(D14+E14)/2) -> 18.75 | G14: =IF(OR(NOT(ISNUMBER(D14)),NOT(ISNUMBER(E14))),"",D14-E14) -> -0.3 | H14: =IF(NOT(ISNUMBER(G14)),"",G14^2) -> 0.09 | I14: =IF(OR(NOT(ISNUMBER(G14)),NOT(ISNUMBER(F14)),F14=0),"",IF(ABS(G14)/F14>M41_u_dif,"REVISAR: las dos medidas difieren más del 5%","OK")) -> OK
A15: 3 | B15: Sujeto 3 | C15: Tríceps | D15: 9.2 | E15: 9.5 | F15: =IF(OR(NOT(ISNUMBER(D15)),NOT(ISNUMBER(E15))),"",(D15+E15)/2) -> 9.35 | G15: =IF(OR(NOT(ISNUMBER(D15)),NOT(ISNUMBER(E15))),"",D15-E15) -> -0.3 | H15: =IF(NOT(ISNUMBER(G15)),"",G15^2) -> 0.09 | I15: =IF(OR(NOT(ISNUMBER(G15)),NOT(ISNUMBER(F15)),F15=0),"",IF(ABS(G15)/F15>M41_u_dif,"REVISAR: las dos medidas difieren más del 5%","OK")) -> OK
A16: 4 | B16: Sujeto 4 | C16: Tríceps | D16: 24.8 | E16: 24.2 | F16: =IF(OR(NOT(ISNUMBER(D16)),NOT(ISNUMBER(E16))),"",(D16+E16)/2) -> 24.5 | G16: =IF(OR(NOT(ISNUMBER(D16)),NOT(ISNUMBER(E16))),"",D16-E16) -> 0.6 | H16: =IF(NOT(ISNUMBER(G16)),"",G16^2) -> 0.36 | I16: =IF(OR(NOT(ISNUMBER(G16)),NOT(ISNUMBER(F16)),F16=0),"",IF(ABS(G16)/F16>M41_u_dif,"REVISAR: las dos medidas difieren más del 5%","OK")) -> OK
A17: 5 | B17: Sujeto 5 | C17: Tríceps | D17: 15 | E17: 15.4 | F17: =IF(OR(NOT(ISNUMBER(D17)),NOT(ISNUMBER(E17))),"",(D17+E17)/2) -> 15.2 | G17: =IF(OR(NOT(ISNUMBER(D17)),NOT(ISNUMBER(E17))),"",D17-E17) -> -0.4 | H17: =IF(NOT(ISNUMBER(G17)),"",G17^2) -> 0.16 | I17: =IF(OR(NOT(ISNUMBER(G17)),NOT(ISNUMBER(F17)),F17=0),"",IF(ABS(G17)/F17>M41_u_dif,"REVISAR: las dos medidas difieren más del 5%","OK")) -> OK
A18: 6 | B18: Sujeto 6 | C18: Tríceps | D18: 21.3 | E18: 21 | F18: =IF(OR(NOT(ISNUMBER(D18)),NOT(ISNUMBER(E18))),"",(D18+E18)/2) -> 21.15 | G18: =IF(OR(NOT(ISNUMBER(D18)),NOT(ISNUMBER(E18))),"",D18-E18) -> 0.3 | H18: =IF(NOT(ISNUMBER(G18)),"",G18^2) -> 0.09 | I18: =IF(OR(NOT(ISNUMBER(G18)),NOT(ISNUMBER(F18)),F18=0),"",IF(ABS(G18)/F18>M41_u_dif,"REVISAR: las dos medidas difieren más del 5%","OK")) -> OK
A19: 7 | B19: Sujeto 7 | C19: Tríceps | D19: 11.7 | E19: 11.4 | F19: =IF(OR(NOT(ISNUMBER(D19)),NOT(ISNUMBER(E19))),"",(D19+E19)/2) -> 11.55 | G19: =IF(OR(NOT(ISNUMBER(D19)),NOT(ISNUMBER(E19))),"",D19-E19) -> 0.3 | H19: =IF(NOT(ISNUMBER(G19)),"",G19^2) -> 0.09 | I19: =IF(OR(NOT(ISNUMBER(G19)),NOT(ISNUMBER(F19)),F19=0),"",IF(ABS(G19)/F19>M41_u_dif,"REVISAR: las dos medidas difieren más del 5%","OK")) -> OK
A20: 8 | B20: Sujeto 8 | C20: Tríceps | D20: 17.4 | E20: 17.9 | F20: =IF(OR(NOT(ISNUMBER(D20)),NOT(ISNUMBER(E20))),"",(D20+E20)/2) -> 17.65 | G20: =IF(OR(NOT(ISNUMBER(D20)),NOT(ISNUMBER(E20))),"",D20-E20) -> -0.5 | H20: =IF(NOT(ISNUMBER(G20)),"",G20^2) -> 0.25 | I20: =IF(OR(NOT(ISNUMBER(G20)),NOT(ISNUMBER(F20)),F20=0),"",IF(ABS(G20)/F20>M41_u_dif,"REVISAR: las dos medidas difieren más del 5%","OK")) -> OK
A21: 9 | B21: Sujeto 9 | C21: Tríceps | D21: 28.2 | E21: 27.6 | F21: =IF(OR(NOT(ISNUMBER(D21)),NOT(ISNUMBER(E21))),"",(D21+E21)/2) -> 27.9 | G21: =IF(OR(NOT(ISNUMBER(D21)),NOT(ISNUMBER(E21))),"",D21-E21) -> 0.6 | H21: =IF(NOT(ISNUMBER(G21)),"",G21^2) -> 0.36 | I21: =IF(OR(NOT(ISNUMBER(G21)),NOT(ISNUMBER(F21)),F21=0),"",IF(ABS(G21)/F21>M41_u_dif,"REVISAR: las dos medidas difieren más del 5%","OK")) -> OK
A22: 10 | B22: Sujeto 10 | C22: Tríceps | D22: 13.9 | E22: 14.3 | F22: =IF(OR(NOT(ISNUMBER(D22)),NOT(ISNUMBER(E22))),"",(D22+E22)/2) -> 14.1 | G22: =IF(OR(NOT(ISNUMBER(D22)),NOT(ISNUMBER(E22))),"",D22-E22) -> -0.4 | H22: =IF(NOT(ISNUMBER(G22)),"",G22^2) -> 0.16 | I22: =IF(OR(NOT(ISNUMBER(G22)),NOT(ISNUMBER(F22)),F22=0),"",IF(ABS(G22)/F22>M41_u_dif,"REVISAR: las dos medidas difieren más del 5%","OK")) -> OK
A23: 11 | F23: =IF(OR(NOT(ISNUMBER(D23)),NOT(ISNUMBER(E23))),"",(D23+E23)/2) | G23: =IF(OR(NOT(ISNUMBER(D23)),NOT(ISNUMBER(E23))),"",D23-E23) | H23: =IF(NOT(ISNUMBER(G23)),"",G23^2) | I23: =IF(OR(NOT(ISNUMBER(G23)),NOT(ISNUMBER(F23)),F23=0),"",IF(ABS(G23)/F23>M41_u_dif,"REVISAR: las dos medidas difieren más del 5%","OK"))
A24: 12 | F24: =IF(OR(NOT(ISNUMBER(D24)),NOT(ISNUMBER(E24))),"",(D24+E24)/2) | G24: =IF(OR(NOT(ISNUMBER(D24)),NOT(ISNUMBER(E24))),"",D24-E24) | H24: =IF(NOT(ISNUMBER(G24)),"",G24^2) | I24: =IF(OR(NOT(ISNUMBER(G24)),NOT(ISNUMBER(F24)),F24=0),"",IF(ABS(G24)/F24>M41_u_dif,"REVISAR: las dos medidas difieren más del 5%","OK"))
A25: 13 | F25: =IF(OR(NOT(ISNUMBER(D25)),NOT(ISNUMBER(E25))),"",(D25+E25)/2) | G25: =IF(OR(NOT(ISNUMBER(D25)),NOT(ISNUMBER(E25))),"",D25-E25) | H25: =IF(NOT(ISNUMBER(G25)),"",G25^2) | I25: =IF(OR(NOT(ISNUMBER(G25)),NOT(ISNUMBER(F25)),F25=0),"",IF(ABS(G25)/F25>M41_u_dif,"REVISAR: las dos medidas difieren más del 5%","OK"))
A26: 14 | F26: =IF(OR(NOT(ISNUMBER(D26)),NOT(ISNUMBER(E26))),"",(D26+E26)/2) | G26: =IF(OR(NOT(ISNUMBER(D26)),NOT(ISNUMBER(E26))),"",D26-E26) | H26: =IF(NOT(ISNUMBER(G26)),"",G26^2) | I26: =IF(OR(NOT(ISNUMBER(G26)),NOT(ISNUMBER(F26)),F26=0),"",IF(ABS(G26)/F26>M41_u_dif,"REVISAR: las dos medidas difieren más del 5%","OK"))
A27: 15 | F27: =IF(OR(NOT(ISNUMBER(D27)),NOT(ISNUMBER(E27))),"",(D27+E27)/2) | G27: =IF(OR(NOT(ISNUMBER(D27)),NOT(ISNUMBER(E27))),"",D27-E27) | H27: =IF(NOT(ISNUMBER(G27)),"",G27^2) | I27: =IF(OR(NOT(ISNUMBER(G27)),NOT(ISNUMBER(F27)),F27=0),"",IF(ABS(G27)/F27>M41_u_dif,"REVISAR: las dos medidas difieren más del 5%","OK"))
A28: 16 | F28: =IF(OR(NOT(ISNUMBER(D28)),NOT(ISNUMBER(E28))),"",(D28+E28)/2) | G28: =IF(OR(NOT(ISNUMBER(D28)),NOT(ISNUMBER(E28))),"",D28-E28) | H28: =IF(NOT(ISNUMBER(G28)),"",G28^2) | I28: =IF(OR(NOT(ISNUMBER(G28)),NOT(ISNUMBER(F28)),F28=0),"",IF(ABS(G28)/F28>M41_u_dif,"REVISAR: las dos medidas difieren más del 5%","OK"))
A29: 17 | F29: =IF(OR(NOT(ISNUMBER(D29)),NOT(ISNUMBER(E29))),"",(D29+E29)/2) | G29: =IF(OR(NOT(ISNUMBER(D29)),NOT(ISNUMBER(E29))),"",D29-E29) | H29: =IF(NOT(ISNUMBER(G29)),"",G29^2) | I29: =IF(OR(NOT(ISNUMBER(G29)),NOT(ISNUMBER(F29)),F29=0),"",IF(ABS(G29)/F29>M41_u_dif,"REVISAR: las dos medidas difieren más del 5%","OK"))
A30: 18 | F30: =IF(OR(NOT(ISNUMBER(D30)),NOT(ISNUMBER(E30))),"",(D30+E30)/2) | G30: =IF(OR(NOT(ISNUMBER(D30)),NOT(ISNUMBER(E30))),"",D30-E30) | H30: =IF(NOT(ISNUMBER(G30)),"",G30^2) | I30: =IF(OR(NOT(ISNUMBER(G30)),NOT(ISNUMBER(F30)),F30=0),"",IF(ABS(G30)/F30>M41_u_dif,"REVISAR: las dos medidas difieren más del 5%","OK"))
A31: 19 | F31: =IF(OR(NOT(ISNUMBER(D31)),NOT(ISNUMBER(E31))),"",(D31+E31)/2) | G31: =IF(OR(NOT(ISNUMBER(D31)),NOT(ISNUMBER(E31))),"",D31-E31) | H31: =IF(NOT(ISNUMBER(G31)),"",G31^2) | I31: =IF(OR(NOT(ISNUMBER(G31)),NOT(ISNUMBER(F31)),F31=0),"",IF(ABS(G31)/F31>M41_u_dif,"REVISAR: las dos medidas difieren más del 5%","OK"))
A32: 20 | F32: =IF(OR(NOT(ISNUMBER(D32)),NOT(ISNUMBER(E32))),"",(D32+E32)/2) | G32: =IF(OR(NOT(ISNUMBER(D32)),NOT(ISNUMBER(E32))),"",D32-E32) | H32: =IF(NOT(ISNUMBER(G32)),"",G32^2) | I32: =IF(OR(NOT(ISNUMBER(G32)),NOT(ISNUMBER(F32)),F32=0),"",IF(ABS(G32)/F32>M41_u_dif,"REVISAR: las dos medidas difieren más del 5%","OK"))
A33: TOTALES | F33: =IF(COUNT(F13:F32)=0,"ND",AVERAGE(F13:F32)) -> 17.24 | G33: =COUNT(G13:G32) -> 10 | H33: =SUM(H13:H32) -> 1.74 | I33: =COUNTIF(I13:I32,"REVISAR*")&" con diferencia sobre el 5%" -> 0 con diferencia sobre el 5%
A35: CÁLCULO DEL ERROR TÉCNICO DE MEDICIÓN
A36: Número de pares medidos | C36: =G33 -> 10
A37: Suma de las diferencias al cuadrado | C37: =H33 -> 1.74
A38: Media general de las mediciones (mm) | C38: =F33 -> 17.24
A39: ERROR TÉCNICO DE MEDICIÓN (mm) | C39: =IF(OR(NOT(ISNUMBER(C36)),C36=0,NOT(ISNUMBER(C37))),"ND: faltan mediciones",SQRT(C37/(2*C36))) -> 0.29495762 | L39: Raíz de la suma de diferencias al cuadrado dividida por dos veces n
A40: ERROR RELATIVO (%) | C40: =IF(OR(NOT(ISNUMBER(C39)),NOT(ISNUMBER(C38)),C38=0),"ND",C39/C38) -> 0.017108911
A41: Desviación estándar entre sujetos (mm) | C41: =IF(COUNT(F13:F32)<2,"ND",STDEV(F13:F32)) -> 5.9407164
A42: Coeficiente de fiabilidad | C42: =IF(OR(NOT(ISNUMBER(C39)),NOT(ISNUMBER(C41)),C41=0),"ND",1-(C39^2/C41^2)) -> 0.99753486 | L42: Proporción de la variación observada que NO se explica por error de medición
A44: LECTURA DE LA FIABILIDAD
A45: Error relativo frente al criterio | C45: =IF(NOT(ISNUMBER(C40)),"ND",IF(C40<=M41_u_intra,"El error relativo de "&TEXT(C40,"0.00%")&" cumple el criterio para un mismo evaluador, que es de "&TEXT(M41_u_intra,"0%")&".",IF(C40<=M41_u_inter,"El error relativo de "&TEXT(C40,"0.00%")&" supera el criterio para un mismo evaluador pero se mantiene bajo el criterio entre evaluadores. Conviene entrenar la técnica antes de usar estas mediciones para seguimiento fino.","El error relativo de "&TEXT(C40,"0.00%")&" SUPERA ambos criterios. Las mediciones no son suficientemente reproducibles: revise la técnica con supervisión antes de continuar."))) -> El error relativo de 002% cumple el criterio para un mismo evaluador, que es de 5%.
A46: Coeficiente de fiabilidad frente al criterio | C46: =IF(NOT(ISNUMBER(C42)),"ND",IF(C42>=M41_u_R,"La fiabilidad de "&TEXT(C42,"0.000")&" alcanza el mínimo de "&TEXT(M41_u_R,"0.00")&": la variación observada entre sujetos se debe mayormente a diferencias reales y no al error del método.","La fiabilidad de "&TEXT(C42,"0.000")&" queda bajo el mínimo: una parte importante de lo que usted observa es error de medición, no diferencia real.")) -> La fiabilidad de 0.001 alcanza el mínimo de 001: la variación observada entre sujetos se debe mayormente a diferencias reales y no al error del método.
A47: Pares con diferencia sobre el cinco por ciento | C47: =COUNTIF(I13:I32,"REVISAR*") -> 0 | L47: Cada uno merece revisión: suelen indicar un punto anatómico mal marcado
A49: CAMBIO MÍNIMO DETECTABLE
A50: Cambio mínimo detectable en un pliegue (mm) | C50: =IF(NOT(ISNUMBER(C39)),"ND",M41_k_z*SQRT(2)*C39) -> 0.81758082 | L50: Bajo este valor, un cambio no se distingue del error de medición
A51: Comparación con la resolución del instrumento | C51: =IF(OR(NOT(ISNUMBER(C50)),NOT(ISNUMBER(M41_v_resol))),"ND",IF(C50<M41_v_resol,"El error del evaluador es menor que la resolución del instrumento: la escala del plicómetro pasa a ser el factor limitante.","El error del evaluador supera la resolución del instrumento en "&TEXT(C50/M41_v_resol,"0.0")&" veces: el "&"factor limitante es la técnica, no el aparato.")) -> El error del evaluador supera la resolución del instrumento en 04 veces: el factor limitante es la técnica, no el aparato.
A53: El error técnico de medición es específico de cada evaluador, cada sitio anatómico y cada rango de espesor: un evaluador puede ser preciso en tríceps y no en suprailíaco. Repita este ejercicio por sitio cuando el seguimiento lo justifique, y siempre que cambie de instrumento.

Sheet M41_FUENTES
A1: NUTRIMETRÍA · NMX-41
A2: Referencias, fórmulas y trazabilidad
A4: =HYPERLINK("#M41_INICIO!A1","▶ VOLVER A INICIO") -> ▶ VOLVER A INICIO
A6: MÉTODOS Y REFERENCIAS
A7: Elemento | B7: Detalle
A8: Protocolo de medición | B8: Sitios anatómicos, dirección del pliegue y posición corporal siguen el protocolo de la Sociedad Internacional para el Avance de la Cineantropometría, de uso extendido en evaluación antropométrica. Este libro describe el procedimiento pero NO sustituye la formación práctica supervisada, que es la única vía para alcanzar los criterios de error exigidos.
A9: Error técnico de medición | B9: Se calcula como la raíz cuadrada de la suma de las diferencias al cuadrado entre mediciones duplicadas, dividida por dos veces el número de pares. Es la medida clásica de error de medición en antropometría y se expresa en las mismas unidades que la variable, en este caso milímetros.
A10: Error relativo | B10: Es el error técnico expresado como porcentaje de la media de las mediciones. Permite comparar el desempeño entre sitios de distinto espesor: un error de medio milímetro pesa mucho más en un pliegue de seis milímetros que en uno de treinta.
A11: Criterios de aceptación | B11: Los límites de cinco por ciento para un mismo evaluador y siete coma cinco por ciento entre evaluadores corresponden a los criterios de acreditación antropométrica de uso internacional para pliegues cutáneos. Son editables en CONFIG.
A12: Coeficiente de fiabilidad | B12: Se obtiene restando de uno el cociente entre el cuadrado del error técnico y el cuadrado de la desviación estándar entre sujetos. Expresa qué proporción de la variación observada corresponde a diferencias reales y no a error de medición. El mínimo habitual es 0,95.
A13: Cambio mínimo detectable | B13: Se calcula multiplicando el error técnico por la raíz de dos y por el valor de la distribución normal para el nivel de confianza elegido, 1,96 para el noventa y cinco por ciento. Un cambio menor que ese valor no puede distinguirse del error del método.
A14: Error de una suma de pliegues | B14: Al sumar varios pliegues los errores independientes se combinan según la raíz del número de sitios, no de forma proporcional. Por eso el cambio mínimo detectable de una suma representa una proporción menor del total que el de un pliegue aislado, y el seguimiento resulta más sensible sobre la suma.
A15: Presión del instrumento | B15: Los plicómetros de uso profesional están construidos para ejercer una presión constante de diez gramos por milímetro cuadrado sobre las superficies de contacto, con independencia de la apertura de las ramas. Esa presión constante es lo que hace comparable la medición: un instrumento con el resorte alterado deja de cumplirla.
A16: Verificación con patrones | B16: La comprobación contra bloques de espesor conocido detecta desviaciones sistemáticas del instrumento, que no se revelan repitiendo mediciones sobre personas porque se repiten de forma idéntica. Ninguna corrección estadística posterior puede recuperar mediciones tomadas con un instrumento descalibrado si esa desviación no fue documentada.
A17: Qué NO hace este libro | B17: No estima densidad corporal, porcentaje de grasa ni somatotipo: para eso están los módulos específicos de la colección. No reemplaza la formación práctica ni la acreditación del evaluador. No corrige mediciones mal tomadas. No está validado clínicamente.
A18: Relación con otros módulos | B18: NMX-36 aplica ecuaciones de composición corporal a partir de pliegues. NMX-20 integra pliegues, somatotipo y recordatorio en un formulario único. Este módulo se ocupa de lo previo: que el instrumento esté verificado y que el error del evaluador sea conocido.

Sheet M41_PRUEBAS
A1: NUTRIMETRÍA · NMX-41
A2: Control de calidad del motor de cálculo
A4: =HYPERLINK("#M41_INICIO!A1","▶ VOLVER A INICIO") -> ▶ VOLVER A INICIO
A6: Los valores esperados se calcularon de forma independiente del motor del libro (verificación externa).
A8: Bloque | B8: Descripción de la prueba | C8: Obtenido | D8: Esperado | E8: Estado
A9: A | B9: Media del primer par (12,4 y 12,1) | C9: =M41_FIABILIDAD!F13 -> 12.25 | D9: 12.25 | E9: =IF(AND(ISNUMBER(C9),ISNUMBER(D9)),IF(ABS(C9-D9)<=0.001,"APROBADO","REVISAR"),IF(EXACT(C9&"",D9&""),"APROBADO","REVISAR")) -> APROBADO
A10: A | B10: Diferencia del primer par | C10: =M41_FIABILIDAD!G13 -> 0.3 | D10: 0.3 | E10: =IF(AND(ISNUMBER(C10),ISNUMBER(D10)),IF(ABS(C10-D10)<=0.001,"APROBADO","REVISAR"),IF(EXACT(C10&"",D10&""),"APROBADO","REVISAR")) -> APROBADO
A11: A | B11: Diferencia al cuadrado del primer par | C11: =M41_FIABILIDAD!H13 -> 0.09 | D11: 0.09 | E11: =IF(AND(ISNUMBER(C11),ISNUMBER(D11)),IF(ABS(C11-D11)<=0.001,"APROBADO","REVISAR"),IF(EXACT(C11&"",D11&""),"APROBADO","REVISAR")) -> APROBADO
A12: A | B12: Número de pares medidos | C12: =M41_FIABILIDAD!C36 -> 10 | D12: 10 | E12: =IF(AND(ISNUMBER(C12),ISNUMBER(D12)),IF(ABS(C12-D12)<=0.001,"APROBADO","REVISAR"),IF(EXACT(C12&"",D12&""),"APROBADO","REVISAR")) -> APROBADO
A13: A | B13: Suma de las diferencias al cuadrado | C13: =M41_FIABILIDAD!C37 -> 1.74 | D13: 1.74 | E13: =IF(AND(ISNUMBER(C13),ISNUMBER(D13)),IF(ABS(C13-D13)<=0.001,"APROBADO","REVISAR"),IF(EXACT(C13&"",D13&""),"APROBADO","REVISAR")) -> APROBADO
A14: A | B14: Media general de las mediciones | C14: =M41_FIABILIDAD!C38 -> 17.24 | D14: 17.24 | E14: =IF(AND(ISNUMBER(C14),ISNUMBER(D14)),IF(ABS(C14-D14)<=0.001,"APROBADO","REVISAR"),IF(EXACT(C14&"",D14&""),"APROBADO","REVISAR")) -> APROBADO
A15: B | B15: ERROR TÉCNICO DE MEDICIÓN | C15: =M41_FIABILIDAD!C39 -> 0.29495762 | D15: 0.29495762 | E15: =IF(AND(ISNUMBER(C15),ISNUMBER(D15)),IF(ABS(C15-D15)<=0.001,"APROBADO","REVISAR"),IF(EXACT(C15&"",D15&""),"APROBADO","REVISAR")) -> APROBADO
A16: B | B16: Error relativo | C16: =M41_FIABILIDAD!C40 -> 0.017108911 | D16: 0.017108911 | E16: =IF(AND(ISNUMBER(C16),ISNUMBER(D16)),IF(ABS(C16-D16)<=0.001,"APROBADO","REVISAR"),IF(EXACT(C16&"",D16&""),"APROBADO","REVISAR")) -> APROBADO
A17: B | B17: Desviación estándar entre sujetos | C17: =M41_FIABILIDAD!C41 -> 5.9407164 | D17: 5.9407164 | E17: =IF(AND(ISNUMBER(C17),ISNUMBER(D17)),IF(ABS(C17-D17)<=0.001,"APROBADO","REVISAR"),IF(EXACT(C17&"",D17&""),"APROBADO","REVISAR")) -> APROBADO
A18: B | B18: Coeficiente de fiabilidad | C18: =M41_FIABILIDAD!C42 -> 0.99753486 | D18: 0.99753486 | E18: =IF(AND(ISNUMBER(C18),ISNUMBER(D18)),IF(ABS(C18-D18)<=0.001,"APROBADO","REVISAR"),IF(EXACT(C18&"",D18&""),"APROBADO","REVISAR")) -> APROBADO
A19: C | B19: El error relativo cumple el criterio de un mismo evaluador | C19: =IF(M41_FIABILIDAD!C40<=M41_u_intra,"CUMPLE","NO CUMPLE") -> CUMPLE | D19: CUMPLE | E19: =IF(AND(ISNUMBER(C19),ISNUMBER(D19)),IF(ABS(C19-D19)<=0.001,"APROBADO","REVISAR"),IF(EXACT(C19&"",D19&""),"APROBADO","REVISAR")) -> APROBADO
A20: C | B20: La fiabilidad alcanza el mínimo exigido | C20: =IF(M41_FIABILIDAD!C42>=M41_u_R,"ALCANZA","NO ALCANZA") -> ALCANZA | D20: ALCANZA | E20: =IF(AND(ISNUMBER(C20),ISNUMBER(D20)),IF(ABS(C20-D20)<=0.001,"APROBADO","REVISAR"),IF(EXACT(C20&"",D20&""),"APROBADO","REVISAR")) -> APROBADO
A21: C | B21: Ningún par supera el 5% de diferencia entre medidas | C21: =COUNTIF(M41_FIABILIDAD!I13:I32,"REVISAR*") -> 0 | D21: 0 | E21: =IF(AND(ISNUMBER(C21),ISNUMBER(D21)),IF(ABS(C21-D21)<=0.001,"APROBADO","REVISAR"),IF(EXACT(C21&"",D21&""),"APROBADO","REVISAR")) -> APROBADO
A22: D | B22: Cambio mínimo detectable en un pliegue | C22: =M41_FIABILIDAD!C50 -> 0.81758082 | D22: 0.81758082 | E22: =IF(AND(ISNUMBER(C22),ISNUMBER(D22)),IF(ABS(C22-D22)<=0.001,"APROBADO","REVISAR"),IF(EXACT(C22&"",D22&""),"APROBADO","REVISAR")) -> APROBADO
A23: D | B23: Error de la suma de 6 pliegues | C23: =M41_SEGUIMIENTO!C25 -> 0.72249567 | D23: 0.72249568 | E23: =IF(AND(ISNUMBER(C23),ISNUMBER(D23)),IF(ABS(C23-D23)<=0.001,"APROBADO","REVISAR"),IF(EXACT(C23&"",D23&""),"APROBADO","REVISAR")) -> APROBADO
A24: D | B24: Cambio mínimo detectable de la suma | C24: =M41_SEGUIMIENTO!E20 -> 2.0026558 | D24: 2.0026558 | E24: =IF(AND(ISNUMBER(C24),ISNUMBER(D24)),IF(ABS(C24-D24)<=0.001,"APROBADO","REVISAR"),IF(EXACT(C24&"",D24&""),"APROBADO","REVISAR")) -> APROBADO
A25: D | B25: El error de la suma es menor que 6 veces el individual | C25: =IF(M41_SEGUIMIENTO!C25<6*M41_FIABILIDAD!C39,"MENOR","MAYOR") -> MENOR | D25: MENOR | E25: =IF(AND(ISNUMBER(C25),ISNUMBER(D25)),IF(ABS(C25-D25)<=0.001,"APROBADO","REVISAR"),IF(EXACT(C25&"",D25&""),"APROBADO","REVISAR")) -> APROBADO
A26: E | B26: Suma inicial de los 6 pliegues | C26: =M41_SEGUIMIENTO!B20 -> 76.6 | D26: 76.6 | E26: =IF(AND(ISNUMBER(C26),ISNUMBER(D26)),IF(ABS(C26-D26)<=0.001,"APROBADO","REVISAR"),IF(EXACT(C26&"",D26&""),"APROBADO","REVISAR")) -> APROBADO
A27: E | B27: Suma de control | C27: =M41_SEGUIMIENTO!C20 -> 69.2 | D27: 69.2 | E27: =IF(AND(ISNUMBER(C27),ISNUMBER(D27)),IF(ABS(C27-D27)<=0.001,"APROBADO","REVISAR"),IF(EXACT(C27&"",D27&""),"APROBADO","REVISAR")) -> APROBADO
A28: E | B28: Cambio de la suma | C28: =M41_SEGUIMIENTO!D20 -> -7.4 | D28: -7.4 | E28: =IF(AND(ISNUMBER(C28),ISNUMBER(D28)),IF(ABS(C28-D28)<=0.001,"APROBADO","REVISAR"),IF(EXACT(C28&"",D28&""),"APROBADO","REVISAR")) -> APROBADO
A29: E | B29: El cambio de la suma supera el umbral | C29: =IF(ABS(M41_SEGUIMIENTO!D20)>M41_SEGUIMIENTO!E20,"SUPERA","NO SUPERA") -> SUPERA | D29: SUPERA | E29: =IF(AND(ISNUMBER(C29),ISNUMBER(D29)),IF(ABS(C29-D29)<=0.001,"APROBADO","REVISAR"),IF(EXACT(C29&"",D29&""),"APROBADO","REVISAR")) -> APROBADO
A30: E | B30: Cambio del bíceps (de 6,0 a 5,6) | C30: =M41_SEGUIMIENTO!D14 -> -0.4 | D30: -0.4 | E30: =IF(AND(ISNUMBER(C30),ISNUMBER(D30)),IF(ABS(C30-D30)<=0.001,"APROBADO","REVISAR"),IF(EXACT(C30&"",D30&""),"APROBADO","REVISAR")) -> APROBADO
A31: E | B31: Ese cambio individual NO es distinguible del error | C31: =IF(ABS(M41_SEGUIMIENTO!D14)>M41_v_mdc,"DISTINGUIBLE","NO DISTINGUIBLE") -> NO DISTINGUIBLE | D31: NO DISTINGUIBLE | E31: =IF(AND(ISNUMBER(C31),ISNUMBER(D31)),IF(ABS(C31-D31)<=0.001,"APROBADO","REVISAR"),IF(EXACT(C31&"",D31&""),"APROBADO","REVISAR")) -> APROBADO
A32: E | B32: Cambio del suprailíaco (de 16,0 a 14,2) | C32: =M41_SEGUIMIENTO!D15 -> -1.8 | D32: -1.8 | E32: =IF(AND(ISNUMBER(C32),ISNUMBER(D32)),IF(ABS(C32-D32)<=0.001,"APROBADO","REVISAR"),IF(EXACT(C32&"",D32&""),"APROBADO","REVISAR")) -> APROBADO
A33: E | B33: Ese cambio individual SÍ es distinguible | C33: =IF(ABS(M41_SEGUIMIENTO!D15)>M41_v_mdc,"DISTINGUIBLE","NO DISTINGUIBLE") -> DISTINGUIBLE | D33: DISTINGUIBLE | E33: =IF(AND(ISNUMBER(C33),ISNUMBER(D33)),IF(ABS(C33-D33)<=0.001,"APROBADO","REVISAR"),IF(EXACT(C33&"",D33&""),"APROBADO","REVISAR")) -> APROBADO
A34: F | B34: Error medio del instrumento en la verificación | C34: =M41_CALIBRACION!G16 -> 0.091666667 | D34: 0.091666667 | E34: =IF(AND(ISNUMBER(C34),ISNUMBER(D34)),IF(ABS(C34-D34)<=0.001,"APROBADO","REVISAR"),IF(EXACT(C34&"",D34&""),"APROBADO","REVISAR")) -> APROBADO
A35: F | B35: La verificación queda dentro de tolerancia | C35: =IF(ABS(M41_CALIBRACION!G16)<=M41_u_patron,"DENTRO","FUERA") -> DENTRO | D35: DENTRO | E35: =IF(AND(ISNUMBER(C35),ISNUMBER(D35)),IF(ABS(C35-D35)<=0.001,"APROBADO","REVISAR"),IF(EXACT(C35&"",D35&""),"APROBADO","REVISAR")) -> APROBADO
A36: F | B36: Puntos conformes de la revisión mecánica | C36: =M41_CALIBRACION!C26 -> 6 | D36: 6 | E36: =IF(AND(ISNUMBER(C36),ISNUMBER(D36)),IF(ABS(C36-D36)<=0.001,"APROBADO","REVISAR"),IF(EXACT(C36&"",D36&""),"APROBADO","REVISAR")) -> APROBADO
A37: F | B37: Dictamen del instrumento | C37: =M41_CALIBRACION!C28 -> APTO PARA USO | D37: APTO PARA USO | E37: =IF(AND(ISNUMBER(C37),ISNUMBER(D37)),IF(ABS(C37-D37)<=0.001,"APROBADO","REVISAR"),IF(EXACT(C37&"",D37&""),"APROBADO","REVISAR")) -> APROBADO
A38: G | B38: Un valor ausente NO se interpreta como cero | C38: =IF(ISNUMBER(""),"NUMERO","ND") -> ND | D38: ND | E38: =IF(AND(ISNUMBER(C38),ISNUMBER(D38)),IF(ABS(C38-D38)<=0.001,"APROBADO","REVISAR"),IF(EXACT(C38&"",D38&""),"APROBADO","REVISAR")) -> APROBADO
A40: RESUMEN | B40: Pruebas aprobadas | C40: =COUNTIF(E9:E38,"APROBADO") -> 30 | D40: =COUNTA(E9:E38) -> 30 | E40: =IF(C40=D40,"TODAS APROBADAS","HAY PRUEBAS POR REVISAR") -> TODAS APROBADAS

Sheet M41_CONFIG
A1: NUTRIMETRÍA · NMX-41
A2: Configuración · umbrales de calidad de la medición
A4: =HYPERLINK("#M41_INICIO!A1","▶ VOLVER A INICIO") -> ▶ VOLVER A INICIO
A6: UMBRALES DE ERROR TÉCNICO DE MEDICIÓN
A7: Error relativo aceptable · un mismo evaluador | D7: % | E7: 0.05
A8: Error relativo aceptable · entre evaluadores | D8: % | E8: 0.075
A9: Coeficiente de fiabilidad mínimo aceptable | D9: R | E9: 0.95
A10: Nivel de confianza para el cambio mínimo detectable | D10: z | E10: 1.96
A11: Presión estándar del plicómetro | D11: g/mm² | E11: 10
A12: Tolerancia aceptada en la verificación con patrón | D12: mm | E12: 0.2
A13: Diferencia máxima entre dos medidas del mismo pliegue | D13: % | E13: 0.05
A14: Número mínimo de sujetos para estimar el error | D14: sujetos | E14: 10
A15: Tolerancia de las pruebas | D15: ± | E15: 0.0001
A16: Los límites de cinco y siete coma cinco por ciento corresponden a los criterios de acreditación de la Sociedad Internacional para el Avance de la Cineantropometría para medidas de pliegues. Son exigentes y se alcanzan con entrenamiento: un evaluador sin práctica supervisada rara vez los cumple al inicio.
A20: SITIOS ANATÓMICOS DE REFERENCIA
A21: Sitio | B21: Ubicación del punto | C21: Dirección del pliegue | D21: Posición de la persona
A22: Tríceps | B22: Punto medio entre acromion y olécranon, cara posterior del brazo | C22: Vertical | D22: De pie, brazo relajado
A23: Subescapular | B23: Dos centímetros por debajo del ángulo inferior de la escápula | C23: Oblicua, hacia abajo y afuera | D23: De pie, brazos a los lados
A24: Bíceps | B24: Punto medio del brazo, cara anterior, sobre el vientre del bíceps | C24: Vertical | D24: De pie, brazo relajado y supinado
A25: Suprailíaco | B25: Sobre la cresta ilíaca, en la línea axilar media | C25: Oblicua, siguiendo la cresta | D25: De pie, brazo separado
A26: Supraespinal | B26: Intersección de la línea axilar anterior con la cresta ilíaca | C26: Oblicua, hacia abajo y adentro | D26: De pie, brazo relajado
A27: Abdominal | B27: Cinco centímetros a la derecha del ombligo | C27: Vertical | D27: De pie, abdomen relajado
A28: Muslo anterior | B28: Punto medio entre pliegue inguinal y borde superior de la rótula | C28: Vertical | D28: Sentado, rodilla a noventa grados
A29: Pantorrilla medial | B29: Cara medial, en el perímetro máximo | C29: Vertical | D29: Sentado o de pie con la pierna apoyada
A31: LISTAS
A32: MARCA | B32: SI | C32: ESTADO | D32: NIVEL
A33: Harpenden | B33: Sí | C33: Correcto | D33: En formación
A34: Holtain | B34: No | C34: Requiere ajuste | D34: Acreditado nivel 1
A35: Lange | C35: Fuera de servicio | D35: Acreditado nivel 2
A36: Slim Guide | D36: Acreditado nivel 3 o superior
A37: Otro

Sheet M41_CHANGELOG
A1: NUTRIMETRÍA · NMX-41
A2: Historial de versiones
A4: =HYPERLINK("#M41_INICIO!A1","▶ VOLVER A INICIO") -> ▶ VOLVER A INICIO
A6: Versión | B6: Fecha | C6: Cambio
A7: 1.0 | B7: 2026-07-24 | C7: Versión inicial de NMX-41: software acompañante para plicómetro, centrado en la calidad del instrumento y del evaluador. | J7: Fase 7 · Especialidades y productos complementarios.
A8: 1.0 | B8: 2026-07-24 | C8: Hoja de verificación del instrumento contra patrones de espesor conocido, con dictamen de aptitud. | J8: Una desviación sistemática del plicómetro no se detecta repitiendo mediciones: se repite igual.
A9: 1.0 | B9: 2026-07-24 | C9: Cálculo del error técnico de medición, error relativo y coeficiente de fiabilidad a partir de mediciones por duplicado. | J9: Permite que cada evaluador conozca su propio error en lugar de suponerlo.
A10: 1.0 | B10: 2026-07-24 | C10: Cambio mínimo detectable por pliegue y para la suma de pliegues. | J10: Responde la pregunta central de quien usa plicómetro: si el cambio observado es real o es ruido del método.
A11: 1.0 | B11: 2026-07-24 | C11: Se explicita que el error de una suma crece con la raíz del número de pliegues. | J11: Fundamenta por qué el seguimiento se hace sobre la suma y no sobre pliegues aislados.
A12: 1.0 | B12: 2026-07-24 | C12: Lista de condiciones de comparabilidad que invalidan la comparación si no se cumplen. | J12: Un cambio de evaluador o de instrumento puede superar el cambio biológico que se busca detectar.
A13: 1.0 | B13: 2026-07-24 | C13: Advertencia sobre no medir dos veces seguidas el mismo sitio. | J13: La compresión del tejido subestima la segunda lectura y el error calculado saldría falsamente bajo.
A14: 1.0 | B14: 2026-07-24 | C14: Diseño visual, barra de navegación y enlaces de retorno replicados de NMX-10 aprobado. | J14: Unificar la identidad de la colección.
A15: 1.0.1 | B15: 2026-08-01 | C15: Actualizado el valor esperado de la prueba F (error medio del instrumento) de 0,1 al valor preciso 0,091666667, en linea con la alta precision del resto de las pruebas. 30 pruebas aprobadas.

Sheet M36_INICIO
A1: NUTRIMETRÍA · NMX-36
A2: Calculadora especializada de plicometría · versión 1.0
A4: Navegación — use las pestañas inferiores del libro
A5: =HYPERLINK("#M36_DATOS!A1","▶ DATOS") -> ▶ DATOS | B5: =HYPERLINK("#M36_PLIEGUES!A1","▶ PLIEGUES") -> ▶ PLIEGUES | D5: =HYPERLINK("#M36_CALCULOS!A1","▶ CALCULOS") -> ▶ CALCULOS | F5: =HYPERLINK("#M36_RESULTADOS!A1","▶ RESULTADOS") -> ▶ RESULTADOS | H5: =HYPERLINK("#M36_FUENTES!A1","▶ FUENTES") -> ▶ FUENTES | J5: =HYPERLINK("#M36_PRUEBAS!A1","▶ PRUEBAS") -> ▶ PRUEBAS | L5: =HYPERLINK("#M36_CONFIG!A1","▶ CONFIG") -> ▶ CONFIG | N5: =HYPERLINK("#M36_CHANGELOG!A1","▶ CHANGELOG") -> ▶ CHANGELOG
A6: Ingresar datos | B6: Evaluación de pliegues | D6: Auditar operaciones | F6: Ver resumen | H6: Trazabilidad | J6: Control de calidad | L6: Constantes | N6: Historial
A7: Código del producto | C7: NMX-36
A8: Versión | C8: 1.0
A9: Fecha | C9: 2026-07-14
A10: Formato | C10: .xlsx sin macros · Microsoft 365 y Excel 2021
A11: Responsable | C11: Equipo Nutrimetría (completar por el titular)
A12: AVISO DE ALCANCE — LÉALO ANTES DE USAR
A13: EXACTITUD MATEMÁTICA ≠ VALIDACIÓN CLÍNICA. Este archivo NO está validado clínicamente.
A14: APLICA A: personas ADULTAS (≥18 años) en condición estable.
A15: NO APLICA A: embarazo · lactancia · menores de edad · pacientes críticos.
A16: Los pliegues ESTIMAN; la referencia son DEXA o pesaje hidrostático.
A17: Las cuatro ecuaciones NO son intercambiables: elija UNA validada para su población y úsela siempre.
A18: Para seguimiento, la Σ de pliegues (mm) es más robusta que el % de grasa: mismo evaluador, mismo plicómetro.
A19: La calidad depende de la técnica: si el ETM supera 7,5 %, repita las mediciones.
A20: PROPÓSITO Y ALCANCE
A21: Propósito | C21: Proveer una herramienta automatizada que facilite la evaluación y el análisis de la composición corporal en población adulta, permitiendo calcular el porcentaje de grasa corporal a través de cuatro ecuaciones estandarizadas basadas en pliegues cutáneos.
A22: Población | C22: Personas adultas (≥18 años) en condición estable. No aplica a embarazo, lactancia, menores de edad ni pacientes críticos.
A23: Uso | C23: Los pliegues ESTIMAN; la referencia son DEXA o pesaje hidrostático.
A24: Compatibilidad | C24: .xlsx sin macros · Microsoft 365 y Excel 2021
A25: Privacidad | C25: Los datos permanecen en el archivo local. El libro no transmite información.
A26: CÓMO SE MODELA
A27: Cada sitio se mide 2 veces; el valor usado es la media y la diferencia alimenta el ETM.
A28: JP7 y JP3: densidad cuadrática por sexo → % grasa por Siri (495/D−450) o Brožek (457/D−414).
A29: Durnin–Womersley: densidad = c − m·log10(Σ4) por sexo y banda etaria → Siri/Brožek.
A30: Faulkner: % grasa = 0,153·Σ4 + 5,783 (directo, sin densidad).
A31: Composición: MG = %grasa×peso · MLG = peso − MG · IMG = MG/talla² · IMLG = MLG/talla².

Sheet M36_DATOS
A1: NUTRIMETRÍA · NMX-36
A2: Datos de entrada · identificación y selección de ecuación
A3: =HYPERLINK("#M36_INICIO!A1","◀ INICIO") -> ◀ INICIO | B3: PLIEGUES | C3: =HYPERLINK("#M36_CALCULOS!A1","▶ CALCULOS") -> ▶ CALCULOS | E3: =HYPERLINK("#M36_RESULTADOS!A1","▶ RESULTADOS") -> ▶ RESULTADOS
A4: LEYENDA · Celdas ARENA con texto AZUL = editables. Grises = calculadas. (opcional) = puede quedar vacía.
A5: ► Los pliegues se ingresan en la hoja PLIEGUES. Aquí van la identificación y la ecuación a reportar.
A6: Campo | B6: Valor | C6: Unidad | D6: Validación | E6: Ayuda
A7: Identificador de la evaluación | B7: =DATOS!$B$7 -> NMX-2026-0028 | C7: — | D7: Texto libre | E7: Código interno.
A8: Fecha | B8: =DATOS!$B$8 -> 46236 | C8: fecha | D8: Fecha | E8: dd/mm/aaaa.
A9: Nombre o código del paciente | B9: =DATOS!$B$9 -> PER-0007 | C9: — | D9: Texto libre | E9: Prefiera un CÓDIGO si comparte el archivo.
A10: Sexo biológico | B10: =DATOS!$B$10 -> Hombre | C10: — | D10: Lista: Hombre / Mujer | E10: Las ecuaciones se derivaron por sexo.
A11: Edad | B11: =DATOS!$B$11 -> 34 | C11: años | D11: ≥18 y ≤120 | E11: Solo adultos.
A12: Peso | B12: =DATOS!$B$12 -> 78.5 | C12: kg | D12: Entre 25 y 350 | E12: Para masa grasa y magra.
A13: Estatura | B13: =DATOS!$B$13 -> 176 | C13: cm | D13: Entre 120 y 230 | E13: Para IMG / IMLG.
A14: Ecuación a reportar | B14: 7 sitios · Jackson–Pollock | C14: — | D14: Lista (CONFIG C3) | E14: Las cuatro se calculan; esta se destaca.
A15: Conversión densidad→grasa | B15: Siri (1961) | C15: — | D15: Lista (CONFIG C4) | E15: Aplica a JP y Durnin–Womersley.
A16: Evaluador | B16: =DATOS!$B$14 -> EVAL-01 | C16: — | D16: Texto libre | E16: Para trazar el error técnico de medición.
A17: Observaciones | B17: =DATOS!$B$17 -> 0 | C17: — | D17: Texto libre | E17: Calibración del plicómetro, condiciones, etc.

Sheet M36_PLIEGUES
A1: NUTRIMETRÍA · NMX-36
A2: Panel de pliegues · doble medición y error técnico de medición (ETM)
A3: Cada sitio se mide DOS veces (M1 y M2). El valor usado es la MEDIA. La diferencia |M1−M2| alimenta el error técnico de medición (ETM) intraevaluador de abajo, según el estándar ISAK. Marque los puntos anatómicos del lado derecho antes de medir. Los sitios no exigidos por su ecuación pueden quedar vacíos.
A4: =HYPERLINK("#M36_DATOS!A1","◀ DATOS") -> ◀ DATOS | C4: =HYPERLINK("#M36_CALCULOS!A1","▶ CALCULOS") -> ▶ CALCULOS | F4: =HYPERLINK("#M36_RESULTADOS!A1","▶ RESULTADOS") -> ▶ RESULTADOS
A6: Nº | B6: Sitio (lado derecho) | C6: M1 (mm) | D6: M2 (mm) | E6: Media | F6: |M1−M2| | G6: Referencia anatómica / técnica
A7: 1 | B7: Pectoral (pecho) | C7: 12 | D7: 12 | E7: =MED_Pect -> 8 | F7: =IF(AND(ISNUMBER(C7),ISNUMBER(D7)),ABS(C7-D7),"") -> 0 | G7: Diagonal, entre axila y pezón (½ en H, ⅓ en M).
A8: 2 | B8: Axilar medio | C8: 14 | D8: 14 | E8: =MED_Axil -> 10 | F8: =IF(AND(ISNUMBER(C8),ISNUMBER(D8)),ABS(C8-D8),"") -> 0 | G8: Línea axilar media, a la altura del apéndice xifoides.
A9: 3 | B9: Tríceps | C9: 13 | D9: 11 | E9: =MED_Tri -> 12 | F9: =IF(AND(ISNUMBER(C9),ISNUMBER(D9)),ABS(C9-D9),"") -> 2 | G9: Vertical, cara posterior del brazo, punto medio.
A10: 4 | B10: Subescapular | C10: 16 | D10: 16 | E10: =MED_Sub -> 14 | F10: =IF(AND(ISNUMBER(C10),ISNUMBER(D10)),ABS(C10-D10),"") -> 0 | G10: Oblicuo, 2 cm bajo el ángulo inferior de la escápula.
A11: 5 | B11: Bíceps | C11: 7 | D11: 7 | E11: =MED_Bic -> 5 | F11: =IF(AND(ISNUMBER(C11),ISNUMBER(D11)),ABS(C11-D11),"") -> 0 | G11: Vertical, cara anterior del brazo, punto medio.
A12: 6 | B12: Suprailíaco (cresta ilíaca) | C12: 17 | D12: 15 | E12: =MED_Supra -> 16 | F12: =IF(AND(ISNUMBER(C12),ISNUMBER(D12)),ABS(C12-D12),"") -> 2 | G12: Oblicuo, sobre la cresta ilíaca, línea axilar media.
A13: 7 | B13: Abdominal | C13: 23 | D13: 21 | E13: =MED_Abd -> 20 | F13: =IF(AND(ISNUMBER(C13),ISNUMBER(D13)),ABS(C13-D13),"") -> 2 | G13: Vertical, 2 cm a la derecha del ombligo.
A14: 8 | B14: Muslo anterior | C14: 16 | D14: 16 | E14: =MED_Muslo -> 12 | F14: =IF(AND(ISNUMBER(C14),ISNUMBER(D14)),ABS(C14-D14),"") -> 0 | G14: Vertical, cara anterior, punto medio inguinal–rótula.
A16: ERROR TÉCNICO DE MEDICIÓN (ETM) INTRAEVALUADOR · estándar ISAK
A17: Sitios medidos por duplicado (k) | C17: =SUMPRODUCT((ISNUMBER(C7:C14))*(ISNUMBER(D7:D14))) -> 8 | E17: sitios | F17: Solo cuentan los sitios con M1 y M2.
A18: Σ de las diferencias al cuadrado | C18: =SUMPRODUCT((ISNUMBER(C7:C14))*(ISNUMBER(D7:D14))*(C7:C14-D7:D14)^2) -> 12 | E18: mm² | F18: Σ(M1−M2)² sobre los sitios duplicados.
A19: ETM absoluto | C19: =IF(M36_a_k>0,SQRT(M36_a_Sd2/(2*M36_a_k)),"ND") -> 0.8660254 | E19: mm | F19: √(Σd² / 2k). Error típico de una medición.
A20: Media global de las mediciones | C20: =IF((COUNT(C7:C14)+COUNT(D7:D14))>0,(SUM(C7:C14)+SUM(D7:D14))/(COUNT(C7:C14)+COUNT(D7:D14)),"ND") -> 14.375 | E20: mm | F20: Promedio de todos los M1 y M2.
A21: ETM relativo (%) | C21: =IF(AND(ISNUMBER(M36_a_TEMabs),ISNUMBER(M36_a_MediaG),M36_a_MediaG>0),M36_a_TEMabs/M36_a_MediaG,"ND") -> 0.060245245 | E21: — | F21: ETM absoluto / media global.
A22: Veredicto ISAK | C22: =IF(ISNUMBER(M36_a_TEMrel),IF(M36_a_TEMrel<=M36_TEM_OK,"OK (≤5%)",IF(M36_a_TEMrel<=M36_TEM_ACC,"Aceptable (5–7,5%)","Revisar técnica (>7,5%)")),"ND") -> Aceptable (5–7,5%) | E22: — | F22: ≤5% experto · 5–7,5% aceptable · >7,5% revisar.
A24: Σ de los 8 pliegues (seguimiento) | C24: =IF(COUNT(E7:E14)>0,SUM(E7:E14),"ND") -> 97 | E24: mm | F24: Suma bruta para MONITOREAR cambios en el tiempo; independiente de toda ecuación.
A26: La suma de pliegues es la métrica de seguimiento más robusta: no depende de ninguna ecuación ni de la conversión densidad→grasa. Para comparar en el tiempo, use SIEMPRE el mismo evaluador, el mismo plicómetro y los mismos sitios.

Sheet M36_CALCULOS
A1: NUTRIMETRÍA · NMX-36
A2: Motor · cuatro ecuaciones de pliegues, reconciliación y composición
A3: =HYPERLINK("#M36_DATOS!A1","◀ DATOS") -> ◀ DATOS | B3: =HYPERLINK("#M36_PLIEGUES!A1", "◀ PLIEGUES") -> ◀ PLIEGUES | D3: =HYPERLINK("#M36_RESULTADOS!A1","▶ RESULTADOS") -> ▶ RESULTADOS | E3: =HYPERLINK("#M36_FUENTES!A1","▶ FUENTES") -> ▶ FUENTES
A4: Cada celda declara su fórmula. Las guardas devuelven texto 'ND: …' en vez de errores de Excel; un sitio ausente no rompe la cadena, solo deja ND la ecuación que lo necesitaba.
A6: BLOQUE 0 · BASE Y SUMATORIAS POR ECUACIÓN
A7: Variable | B7: Valor | C7: Unidad | D7: Fórmula / cómo se obtiene
A8: Estatura en metros | B8: =IF(ISNUMBER(M36_in_Est),M36_in_Est/100,"ND: estatura") -> 1.76 | C8: m | D8: in_Est/100
A9: IMC | B9: =IF(AND(ISNUMBER(M36_in_Peso),ISNUMBER(M36_in_Est),M36_in_Est>0),M36_in_Peso/(M36_in_Est/100)^2,"ND") -> 25.3422 | C9: kg/m² | D9: peso/estatura²
A10: Σ Jackson–Pollock 7 sitios | B10: =IF(AND(ISNUMBER(M36_p_Pect),ISNUMBER(M36_p_Axil),ISNUMBER(M36_p_Tri),ISNUMBER(M36_p_Sub),ISNUMBER(M36_p_Abd),ISNUMBER(M36_p_Supra),ISNUMBER(M36_p_Muslo)),M36_p_Pect+M36_p_Axil+M36_p_Tri+M36_p_Sub+M36_p_Abd+M36_p_Supra+M36_p_Muslo,"ND: faltan sitios") -> 92 | C10: mm | D10: pectoral+axilar+tríceps+subescapular+abdominal+suprailíaco+muslo
A11: Σ Jackson–Pollock 3 sitios | B11: =IF(M36_in_Sexo="Hombre",IF(AND(ISNUMBER(M36_p_Pect),ISNUMBER(M36_p_Abd),ISNUMBER(M36_p_Muslo)),M36_p_Pect+M36_p_Abd+M36_p_Muslo,"ND: faltan sitios"),IF(AND(ISNUMBER(M36_p_Tri),ISNUMBER(M36_p_Supra),ISNUMBER(M36_p_Muslo)),M36_p_Tri+M36_p_Supra+M36_p_Muslo,"ND: faltan sitios")) -> 40 | C11: mm | D11: H: pectoral+abdominal+muslo · M: tríceps+suprailíaco+muslo
A12: Σ Durnin–Womersley 4 | B12: =IF(AND(ISNUMBER(M36_p_Bic),ISNUMBER(M36_p_Tri),ISNUMBER(M36_p_Sub),ISNUMBER(M36_p_Supra)),M36_p_Bic+M36_p_Tri+M36_p_Sub+M36_p_Supra,"ND: faltan sitios") -> 47 | C12: mm | D12: bíceps+tríceps+subescapular+suprailíaco
A13: Σ Faulkner 4 | B13: =IF(AND(ISNUMBER(M36_p_Tri),ISNUMBER(M36_p_Sub),ISNUMBER(M36_p_Supra),ISNUMBER(M36_p_Abd)),M36_p_Tri+M36_p_Sub+M36_p_Supra+M36_p_Abd,"ND: faltan sitios") -> 62 | C13: mm | D13: tríceps+subescapular+suprailíaco+abdominal
A14: BLOQUE 1 · COMPUERTA DE DATOS IMPOSIBLES
A15: Variable | B15: Valor | C15: Unidad | D15: Fórmula / cómo se obtiene
A16: ¿Cálculo habilitado? | B16: =IF(AND(COUNTIF(M36_SEXOS,M36_in_Sexo)>0,ISNUMBER(M36_in_Edad),M36_in_Edad>=M36_EDAD_MIN,M36_in_Edad<=M36_EDAD_MAX,ISNUMBER(M36_in_Peso),M36_in_Peso>=M36_PESO_MIN,M36_in_Peso<=M36_PESO_MAX,ISNUMBER(M36_in_Est),M36_in_Est>=M36_EST_MIN,M36_in_Est<=M36_EST_MAX),"SÍ","NO") -> SÍ | C16: — | D16: Exige sexo, edad adulta, peso y estatura válidos
A17: BLOQUE 2 · DENSIDAD Y % DE GRASA POR CADA ECUACIÓN (fracción)
A18: Variable | B18: Valor | C18: Unidad | D18: Fórmula / cómo se obtiene
A19: Densidad · JP7 | B19: =IF(AND(M36_c_Gate="SÍ",ISNUMBER(M36_c_Sum7)),IF(M36_in_Sexo="Hombre",M36_JP7_HA-M36_JP7_HB1*M36_c_Sum7+M36_JP7_HB2*M36_c_Sum7^2-M36_JP7_HB3*M36_in_Edad,M36_JP7_MA-M36_JP7_MB1*M36_c_Sum7+M36_JP7_MB2*M36_c_Sum7^2-M36_JP7_MB3*M36_in_Edad),"ND") -> 1.0668353 | C19: g/mL | D19: Cuadrática por sexo
A20: % grasa · JP7 | B20: =IF(ISNUMBER(M36_c_BDjp7),IF(M36_in_Conv="Brožek (1963)",(M36_BRO_A/M36_c_BDjp7-M36_BRO_B)/100,(M36_SIRI_A/M36_c_BDjp7-M36_SIRI_B)/100),"ND") -> 0.13989155 | C20: % | D20: Siri o Brožek
A21: Densidad · JP3 | B21: =IF(AND(M36_c_Gate="SÍ",ISNUMBER(M36_c_SumJP3)),IF(M36_in_Sexo="Hombre",M36_JP3_HA-M36_JP3_HB1*M36_c_SumJP3+M36_JP3_HB2*M36_c_SumJP3^2-M36_JP3_HB3*M36_in_Edad,M36_JP3_MA-M36_JP3_MB1*M36_c_SumJP3+M36_JP3_MB2*M36_c_SumJP3^2-M36_JP3_MB3*M36_in_Edad),"ND") -> 1.0701204 | C21: g/mL | D21: Cuadrática por sexo
A22: % grasa · JP3 | B22: =IF(ISNUMBER(M36_c_BDjp3),IF(M36_in_Conv="Brožek (1963)",(M36_BRO_A/M36_c_BDjp3-M36_BRO_B)/100,(M36_SIRI_A/M36_c_BDjp3-M36_SIRI_B)/100),"ND") -> 0.12564773 | C22: % | D22: Siri o Brožek
A23: Durnin–Womersley · c | B23: =IF(AND(M36_c_Gate="SÍ",ISNUMBER(M36_c_SumDW)),SUMPRODUCT((M36_CONFIG!$A$72:$A$81=M36_in_Sexo)*(M36_CONFIG!$B$72:$B$81<=M36_in_Edad)*(M36_CONFIG!$C$72:$C$81>M36_in_Edad)*M36_CONFIG!$D$72:$D$81),"ND") -> 1.1422 | C23: — | D23: Coef. c por sexo y banda
A24: Durnin–Womersley · m | B24: =IF(AND(M36_c_Gate="SÍ",ISNUMBER(M36_c_SumDW)),SUMPRODUCT((M36_CONFIG!$A$72:$A$81=M36_in_Sexo)*(M36_CONFIG!$B$72:$B$81<=M36_in_Edad)*(M36_CONFIG!$C$72:$C$81>M36_in_Edad)*M36_CONFIG!$E$72:$E$81),"ND") -> 0.0544 | C24: — | D24: Coef. m por sexo y banda
A25: Densidad · DW4 | B25: =IF(AND(ISNUMBER(M36_c_DWc),ISNUMBER(M36_c_DWm),ISNUMBER(M36_c_SumDW)),M36_c_DWc-M36_c_DWm*LOG10(M36_c_SumDW),"ND") -> 1.0512379 | C25: g/mL | D25: c − m·log10(Σ4)
A26: % grasa · DW4 | B26: =IF(ISNUMBER(M36_c_BDdw),IF(M36_in_Conv="Brožek (1963)",(M36_BRO_A/M36_c_BDdw-M36_BRO_B)/100,(M36_SIRI_A/M36_c_BDdw-M36_SIRI_B)/100),"ND") -> 0.20873445 | C26: % | D26: Siri o Brožek
A27: % grasa · Faulkner | B27: =IF(AND(M36_c_Gate="SÍ",ISNUMBER(M36_c_SumFaulk)),(M36_FAULK_A*M36_c_SumFaulk+M36_FAULK_B)/100,"ND") -> 0.15269 | C27: % | D27: 0,153·Σ4 + 5,783 (directo)
A28: BLOQUE 3 · RECONCILIACIÓN DE LAS ECUACIONES
A29: Variable | B29: Valor | C29: Unidad | D29: Fórmula / cómo se obtiene
A30: % grasa REPORTADO | B30: =CHOOSE(MATCH(M36_in_Ecu,M36_LISTA_ECU,0),M36_c_GrJP7,M36_c_GrJP3,M36_c_GrDW,M36_c_GrFaulk) -> 0.13989155 | C30: % | D30: Ecuación elegida en DATOS
A31: Ecuaciones con dato (n) | B31: =COUNT(M36_c_GrJP7,M36_c_GrJP3,M36_c_GrDW,M36_c_GrFaulk) -> 4 | C31: — | D31: Cuántas entregaron número
A32: Promedio | B32: =IF(M36_c_n>0,AVERAGE(M36_c_GrJP7,M36_c_GrJP3,M36_c_GrDW,M36_c_GrFaulk),"ND") -> 0.15674093 | C32: % | D32: AVERAGE ignora los ND
A33: Mínimo | B33: =IF(M36_c_n>0,MIN(M36_c_GrJP7,M36_c_GrJP3,M36_c_GrDW,M36_c_GrFaulk),"ND") -> 0.12564773 | C33: %
A34: Máximo | B34: =IF(M36_c_n>0,MAX(M36_c_GrJP7,M36_c_GrJP3,M36_c_GrDW,M36_c_GrFaulk),"ND") -> 0.20873445 | C34: %
A35: Rango (máx − mín) | B35: =IF(AND(ISNUMBER(M36_c_min),ISNUMBER(M36_c_max)),M36_c_max-M36_c_min,"ND") -> 0.083086715 | C35: p.p. | D35: Dispersión en puntos porcentuales
A36: Amplitud relativa | B36: =IF(AND(ISNUMBER(M36_c_rango),ISNUMBER(M36_c_prom),M36_c_prom>0),M36_c_rango/M36_c_prom,"ND") -> 0.53008946 | C36: — | D36: rango/promedio (informativo)
A37: Estado de concordancia | B37: =IF(ISNUMBER(M36_c_rango),IF(M36_c_rango<=M36_DISP_MAX,"OK: las ecuaciones concuerdan dentro del umbral.","ATENCIÓN: las ecuaciones de pliegues no son intercambiables; elija UNA y sígala en el tiempo."),"ND") -> ATENCIÓN: las ecuaciones de pliegues no son intercambiables; elija UNA y sígala en el tiempo. | C37: — | D37: Compara el rango con DISP_MAX
A38: BLOQUE 4 · COMPOSICIÓN CORPORAL (según la ecuación reportada)
A39: Variable | B39: Valor | C39: Unidad | D39: Fórmula / cómo se obtiene
A40: Masa grasa (MG) | B40: =IF(AND(ISNUMBER(M36_c_GrRep),ISNUMBER(M36_in_Peso)),M36_c_GrRep*M36_in_Peso,"ND") -> 10.981487 | C40: kg | D40: % grasa × peso
A41: Masa libre de grasa (MLG) | B41: =IF(AND(ISNUMBER(M36_c_MG),ISNUMBER(M36_in_Peso)),M36_in_Peso-M36_c_MG,"ND") -> 67.518513 | C41: kg | D41: peso − MG
A42: Índice de masa grasa (IMG) | B42: =IF(AND(ISNUMBER(M36_c_MG),ISNUMBER(M36_c_TallaM),M36_c_TallaM>0),M36_c_MG/M36_c_TallaM^2,"ND") -> 3.5451597 | C42: kg/m² | D42: MG / estatura²
A43: Índice de masa libre de grasa (IMLG) | B43: =IF(AND(ISNUMBER(M36_c_MLG),ISNUMBER(M36_c_TallaM),M36_c_TallaM>0),M36_c_MLG/M36_c_TallaM^2,"ND") -> 21.797041 | C43: kg/m² | D43: MLG / estatura²
A44: BLOQUE 5 · CLASIFICACIÓN REFERENCIAL
A45: Variable | B45: Valor | C45: Unidad | D45: Fórmula / cómo se obtiene
A46: Clasificación por % grasa (ACE) | B46: =IF(ISNUMBER(M36_c_GrRep),INDEX(M36_CONFIG!$B$85:$B$94,IF(M36_in_Sexo="Hombre",0,5)+MAX(1,SUMPRODUCT((M36_CONFIG!$A$85:$A$94=M36_in_Sexo)*(M36_CONFIG!$C$85:$C$94<=M36_c_GrRep)))),"ND") -> Atlético | C46: — | D46: Rangos ACE por sexo (referenciales)
A47: BLOQUE 6 · ADVERTENCIAS
A48: Variable | B48: Resultado
A49: Cálculo bloqueado | B49: =IF(M36_c_Gate="NO","Corrija los datos imposibles (sexo, edad, peso o estatura) antes de interpretar.","—") -> —
A50: Ecuación reportada sin datos | B50: =IF(ISNUMBER(M36_c_GrRep),"—","La ecuación elegida no tiene todos sus sitios; complete los pliegues o elija otra.") -> —
A51: Ecuaciones no intercambiables | B51: =IF(AND(ISNUMBER(M36_c_rango),M36_c_rango>M36_DISP_MAX),"Las cuatro ecuaciones discrepan más que el umbral: reporte UNA sola y monitoree la Σ de pliegues.","—") -> Las cuatro ecuaciones discrepan más que el umbral: reporte UNA sola y monitoree la Σ de pliegues.
A52: Calidad de medición (ETM) | B52: =IF(ISNUMBER(M36_a_TEMrel),IF(M36_a_TEMrel>M36_TEM_ACC,"El error técnico de medición supera 7,5 %: repita las mediciones antes de interpretar.","—"),"Sin ETM: mida cada sitio dos veces.") -> —
A53: % grasa fuera de rango plausible | B53: =IF(AND(ISNUMBER(M36_c_GrRep),OR(M36_c_GrRep<M36_GRASA_MIN,M36_c_GrRep>M36_GRASA_MAX)),"El % de grasa reportado está fuera del rango fisiológico plausible.","—") -> —
A54: Pliegue fuera de rango habitual | B54: =IF(OR(AND(ISNUMBER(M36_p_Pect),M36_p_Pect>M36_PLI_MAX),AND(ISNUMBER(M36_p_Abd),M36_p_Abd>M36_PLI_MAX),AND(ISNUMBER(M36_p_Muslo),M36_p_Muslo>M36_PLI_MAX),AND(ISNUMBER(M36_p_Supra),M36_p_Supra>M36_PLI_MAX)),"Algún pliegue supera el máximo del catálogo: verifique la medición.","—") -> —
A55: Recordatorio metodológico | B55: ="Exactitud matemática ≠ validación clínica. Los pliegues ESTIMAN; la referencia es DEXA o pesaje hidrostático." -> Exactitud matemática ≠ validación clínica. Los pliegues ESTIMAN; la referencia es DEXA o pesaje hidrostático.

Sheet M36_RESULTADOS
A1: NUTRIMETRÍA · NMX-36
A2: Informe de plicometría y composición corporal
A3: =HYPERLINK("#M36_DATOS!A1","◀ DATOS") -> ◀ DATOS | B3: =HYPERLINK("#M36_PLIEGUES!A1", "◀ PLIEGUES") -> ◀ PLIEGUES | C3: =HYPERLINK("#M36_CALCULOS!A1","◀ CALCULOS") -> ◀ CALCULOS | E3: =HYPERLINK("#M36_FUENTES!A1","▶ FUENTES") -> ▶ FUENTES
A5: IDENTIFICACIÓN
A6: Identificador | B6: =M36_in_ID -> NMX-2026-0028
A7: Fecha | B7: =M36_in_Fecha -> 46236
A8: Paciente | B8: =M36_in_Pac -> PER-0007
A9: Evaluador | B9: =M36_in_Eval -> EVAL-01
A10: Sexo · edad | B10: =M36_in_Sexo&" · "&IF(ISNUMBER(M36_in_Edad),M36_in_Edad&" años","(edad no válida)") -> Hombre · 34 años
A11: Peso · estatura | B11: =IF(ISNUMBER(M36_in_Peso),ROUND(M36_in_Peso,1)&" kg","(?)")&" · "&IF(ISNUMBER(M36_in_Est),ROUND(M36_in_Est,1)&" cm","(?)") -> 78,5 kg · 176 cm
A12: Ecuación reportada | B12: =M36_in_Ecu -> 7 sitios · Jackson–Pollock
A13: Estado del cálculo | B13: =IF(M36_c_Gate="SÍ","HABILITADO","BLOQUEADO — corrija los datos imposibles") -> HABILITADO
A15: CALIDAD DE LA MEDICIÓN (ETM intraevaluador · ISAK)
A16: Sitios medidos por duplicado (k) | B16: =M36_a_k -> 8
A17: ETM absoluto | B17: =M36_a_TEMabs -> 0.8660254 | C17: mm
A18: ETM relativo | B18: =M36_a_TEMrel -> 0.060245245
A19: Veredicto ISAK | B19: =M36_a_TEMver -> Aceptable (5–7,5%)
A20: Σ de los 8 pliegues (seguimiento) | B20: =M36_a_Sum8 -> 97 | C20: mm
A22: % DE GRASA POR LAS CUATRO ECUACIONES
A23: Ecuación | B23: % de grasa | C23: ¿Disponible? | D23: Fuente
A24: 7 sitios · Jackson–Pollock | B24: =M36_c_GrJP7 -> 0.13989155 | C24: =IF(ISNUMBER(M36_c_GrJP7),"Sí","No") -> Sí | D24: Jackson & Pollock 1978/1980
A25: 3 sitios · Jackson–Pollock | B25: =M36_c_GrJP3 -> 0.12564773 | C25: =IF(ISNUMBER(M36_c_GrJP3),"Sí","No") -> Sí | D25: Jackson & Pollock 1978/1980
A26: 4 pliegues · Durnin–Womersley | B26: =M36_c_GrDW -> 0.20873445 | C26: =IF(ISNUMBER(M36_c_GrDW),"Sí","No") -> Sí | D26: Durnin & Womersley 1974
A27: 4 pliegues · Faulkner | B27: =M36_c_GrFaulk -> 0.15269 | C27: =IF(ISNUMBER(M36_c_GrFaulk),"Sí","No") -> Sí | D27: Faulkner 1968
A28: ECUACIÓN REPORTADA | B28: =M36_c_GrRep -> 0.13989155 | C28: =M36_in_Ecu -> 7 sitios · Jackson–Pollock
A30: CONCORDANCIA ENTRE ECUACIONES
A31: Promedio | B31: =M36_c_prom -> 0.15674093
A32: Rango (máx − mín) | B32: =M36_c_rango -> 0.083086715
A33: Amplitud relativa | B33: =M36_c_ampl -> 0.53008946
A34: =M36_c_estado -> ATENCIÓN: las ecuaciones de pliegues no son intercambiables; elija UNA y sígala en el tiempo.
A36: COMPOSICIÓN CORPORAL (según la ecuación reportada)
A37: % de grasa reportado | B37: =M36_c_GrRep -> 0.13989155
A38: Masa grasa (MG) | B38: =M36_c_MG -> 10.981487 | C38: kg
A39: Masa libre de grasa (MLG) | B39: =M36_c_MLG -> 67.518513 | C39: kg
A40: Índice de masa grasa (IMG) | B40: =M36_c_IMG -> 3.5451597 | C40: kg/m²
A41: Índice de masa libre de grasa (IMLG) | B41: =M36_c_IMLG -> 21.797041 | C41: kg/m²
A42: Clasificación por % grasa (ACE, referencial) | B42: =M36_c_ClaseGrasa -> Atlético
A44: DATOS DE APOYO PARA LOS GRÁFICOS
A45: Ecuación | B45: % de grasa
A46: JP7 | B46: =IF(ISNUMBER(M36_c_GrJP7),M36_c_GrJP7,0) -> 0.13989155
A47: JP3 | B47: =IF(ISNUMBER(M36_c_GrJP3),M36_c_GrJP3,0) -> 0.12564773
A48: Durnin–W. | B48: =IF(ISNUMBER(M36_c_GrDW),M36_c_GrDW,0) -> 0.20873445
A49: Faulkner | B49: =IF(ISNUMBER(M36_c_GrFaulk),M36_c_GrFaulk,0) -> 0.15269
A51: Componente | B51: kg
A52: Masa grasa | B52: =IF(ISNUMBER(M36_c_MG),M36_c_MG,0) -> 10.981487
A53: Masa libre de grasa | B53: =IF(ISNUMBER(M36_c_MLG),M36_c_MLG,0) -> 67.518513
A55: ADVERTENCIAS
A56: Cálculo bloqueado | B56: =M36_CALCULOS!B49 -> —
A57: Ecuación reportada sin datos | B57: =M36_CALCULOS!B50 -> —
A58: Ecuaciones no intercambiables | B58: =M36_CALCULOS!B51 -> Las cuatro ecuaciones discrepan más que el umbral: reporte UNA sola y monitoree la Σ de pliegues.
A59: Calidad de medición (ETM) | B59: =M36_CALCULOS!B52 -> —
A60: % grasa no plausible | B60: =M36_CALCULOS!B53 -> —
A61: Pliegue fuera de rango | B61: =M36_CALCULOS!B54 -> —
A62: Recordatorio metodológico | B62: =M36_CALCULOS!B55 -> Exactitud matemática ≠ validación clínica. Los pliegues ESTIMAN; la referencia es DEXA o pesaje hidrostático.
A64: EXACTITUD MATEMÁTICA ≠ VALIDACIÓN CLÍNICA. Los coeficientes se cotejaron contra las fuentes de la hoja FUENTES, pero este archivo NO está validado clínicamente. Los pliegues ESTIMAN la composición; la referencia son DEXA o pesaje hidrostático. Las ecuaciones NO son intercambiables: reporte una sola y siga la Σ de pliegues.

Sheet M36_FUENTES
A1: NUTRIMETRÍA · NMX-36
A2: Trazabilidad de ecuaciones de plicometría y verificación
A3: NIVEL A = publicación primaria / estándar oficial · B = resumen primario o corroboración por pares · C = fuente secundaria (atribución propagada por manuales). Solo se usan ECUACIONES y COEFICIENTES (hechos no protegibles). EXACTITUD BIBLIOGRÁFICA ≠ VALIDACIÓN CLÍNICA. Las ecuaciones de pliegues NO son intercambiables.
A4: =HYPERLINK("#M36_INICIO!A1","◀ INICIO") -> ◀ INICIO | B4: =HYPERLINK("#M36_DATOS!A1","◀ DATOS") -> ◀ DATOS | C4: =HYPERLINK("#M36_CALCULOS!A1","◀ CALCULOS") -> ◀ CALCULOS
A5: Ecuación o dato | B5: Autor u organización | C5: Año | D5: Población de derivación | E5: Fórmula / valor | F5: Unidades | G5: Limitaciones | H5: DOI o fuente | I5: Fecha cotejo | J5: Licencia / condiciones | K5: Nivel
A6: Densidad · JP 7 sitios (hombres) | B6: Jackson AS, Pollock ML — Br J Nutr 40:497-504 | C6: 1978 | D6: 308 hombres, 18–61 años; pesaje hidrostático | E6: BD = 1,112 − 0,00043499·Σ7 + 0,00000055·Σ7² − 0,00028826·edad | F6: g/mL; mm; años | G6: Muestra mayoritariamente caucásica no atleta; error ~3,5 %grasa. | H6: Br J Nutr 1978;40:497-504 | I6: 2026-07-16 | J6: Artículo con derechos de autor; solo se usan los coeficientes. | K6: B
A7: Densidad · JP 7 y 3 sitios (mujeres) | B7: Jackson AS, Pollock ML, Ward A — Med Sci Sports Exerc 12:175-182 | C7: 1980 | D7: 249 mujeres, 18–55 años; pesaje hidrostático | E7: BD = 1,097 − 0,00046971·Σ7 + 0,00000056·Σ7² − 0,00012828·edad | F7: g/mL; mm; años | G7: Precaución en mujeres mayores de 40 años. | H7: Med Sci Sports Exerc 1980;12:175-182 | I7: 2026-07-16 | J7: Artículo con derechos de autor; solo se usan los coeficientes. | K7: B
A8: Densidad · JP 3 sitios (hombres) | B8: Jackson AS, Pollock ML — Br J Nutr 40:497-504 | C8: 1978 | D8: Sitios: pectoral, abdominal, muslo | E8: BD = 1,10938 − 0,0008267·Σ3 + 0,0000016·Σ3² − 0,0002574·edad | F8: g/mL; mm; años | G8: Versión abreviada; algo menos precisa que la de 7 sitios. | H8: Br J Nutr 1978;40:497-504 | I8: 2026-07-16 | J8: Artículo con derechos de autor; solo se usan los coeficientes. | K8: B
A9: Densidad · Durnin–Womersley 4 | B9: Durnin JVGA, Womersley J — Br J Nutr 32:77-97 | C9: 1974 | D9: 481 personas, 16–72 años; pesaje hidrostático | E9: D = c − m·log10(Σ4); Σ4 = bíceps+tríceps+subescapular+suprailíaco | F9: g/mL; mm | G9: Ecuación general británica; depende de la técnica del evaluador. | H9: 10.1079/bjn19740060 | I9: 2026-07-16 | J9: Artículo con derechos de autor; solo se usan los coeficientes. | K9: B
A10: % grasa · Faulkner (4 pliegues) | B10: Faulkner JA (derivada de Yuhasz) | C10: 1968 | D10: Uso extendido en el ámbito deportivo | E10: %grasa = 0,153·(tríceps+subescapular+suprailíaco+abdominal) + 5,783 | F10: %; mm | G10: ATRIBUCIÓN SECUNDARIA: la primaria (tesis 1968) no se inspeccionó. Verifíquela antes de un uso formal. | H10: Manuales de cineantropometría | I10: 2026-07-16 | J10: Fórmula divulgada; se cita como referencia. | K10: C
A11: Densidad → % grasa · Siri | B11: Siri WE — NAS-NRC | C11: 1961 | D11: Modelo de dos compartimentos | E11: %grasa = 495/D − 450 | F11: %; D g/mL | G11: Densidades fijas de los compartimentos; menos válida en extremos. | H11: Siri 1961 (NAS-NRC) | I11: 2026-07-16 | J11: Obra clásica; solo se usa la ecuación. | K11: B
A12: Densidad → % grasa · Brožek | B12: Brožek J et al. — Ann N Y Acad Sci 110:113-140 | C12: 1963 | D12: Cuerpo de referencia | E12: %grasa = 457/D − 414 | F12: %; D g/mL | G12: Alternativa a Siri; difiere en los extremos. | H12: 10.1111/j.1749-6632.1963.tb17079.x | I12: 2026-07-16 | J12: Artículo con derechos de autor; solo se usa la ecuación. | K12: B
A13: Error técnico de medición (ETM) | B13: ISAK — International Standards for Anthropometric Assessment | C13: 2001/vigente | D13: Estándar internacional de cineantropometría | E13: ETM = √(Σd²/2k); ETM% = ETM/media · límites 5 % / 7,5 % | F13: mm; % | G13: El ETM mide reproducibilidad, no exactitud: un ETM bajo no valida la ecuación. | H13: ISAK · normas de acreditación | I13: 2026-07-16 | J13: Estándar de la sociedad ISAK; se usa la definición (hecho no protegible). | K13: A
A14: Rangos referenciales de % de grasa | B14: American Council on Exercise (ACE) | C14: referencial | D14: Rangos divulgados por categoría y sexo | E14: H: esencial 2–5, atlético 6–13, en forma 14–17, aceptable 18–24, obesidad ≥25 % | F14: % | G14: REFERENCIALES; no son un estándar oficial ni un diagnóstico. | H14: ACE (rangos divulgados) | I14: 2026-07-16 | J14: Rangos de uso general; se citan como referencia. | K14: C
A16: PENDIENTES DE VERIFICACIÓN PRIMARIA: las ecuaciones de Jackson–Pollock, Durnin–Womersley, Siri y Brožek disponen de resumen primario o corroboración por pares, pero no se inspeccionó cada PDF completo. La fórmula de Faulkner es de atribución secundaria (nivel C): confirme la fuente primaria antes de un uso formal.

Sheet M36_PRUEBAS
A1: NUTRIMETRÍA · NMX-36
A2: Banco de verificación · el recuento se calcula solo en el RESUMEN
A3: REGLA: el valor ESPERADO nunca lee el CONFIG que usa el motor. O es un literal calculado a partir de la fuente publicada, o se reconstruye con los coeficientes publicados escritos de forma explícita. Si alguien corrompe un coeficiente de CONFIG, estas pruebas FALLAN.
A4: =HYPERLINK("#M36_INICIO!A1","◀ INICIO") -> ◀ INICIO
A6: BLOQUE A · EXACTITUD JACKSON–POLLOCK 7 SITIOS → densidad → % grasa (Siri)
A7: ID | B7: Descripción | C7: Sexo | D7: Σ7 | E7: Edad | F7: Obtenido | G7: Esperado | H7: Dif. | I7: Estado
A8: A01 | B8: Hombre Σ108 | C8: Hombre | D8: 108 | E8: 34 | F8: =IF(C8="Hombre",(495/(1.112-0.00043499*D8+0.00000055*D8^2-0.00028826*E8)-450)/100,(495/(1.097-0.00046971*D8+0.00000056*D8^2-0.00012828*E8)-450)/100) -> 0.16261752 | G8: 0.162618 | H8: =F8-G8 -> -4.8225775e-07 | I8: =IF(ABS(H8)<=M36_TOL_FRAC,"APROBADO","FALLIDO") -> APROBADO
A9: A02 | B9: Mujer Σ120 | C9: Mujer | D9: 120 | E9: 30 | F9: =IF(C9="Hombre",(495/(1.112-0.00043499*D9+0.00000055*D9^2-0.00028826*E9)-450)/100,(495/(1.097-0.00046971*D9+0.00000056*D9^2-0.00012828*E9)-450)/100) -> 0.23752032 | G9: 0.23752 | H9: =F9-G9 -> 3.1869826e-07 | I9: =IF(ABS(H9)<=M36_TOL_FRAC,"APROBADO","FALLIDO") -> APROBADO
A10: A03 | B10: Hombre Σ80 | C10: Hombre | D10: 80 | E10: 25 | F10: =IF(C10="Hombre",(495/(1.112-0.00043499*D10+0.00000055*D10^2-0.00028826*E10)-450)/100,(495/(1.097-0.00046971*D10+0.00000056*D10^2-0.00012828*E10)-450)/100) -> 0.11102381 | G10: 0.111024 | H10: =F10-G10 -> -1.8783467e-07 | I10: =IF(ABS(H10)<=M36_TOL_FRAC,"APROBADO","FALLIDO") -> APROBADO
A11: A04 | B11: Mujer Σ150 | C11: Mujer | D11: 150 | E11: 45 | F11: =IF(C11="Hombre",(495/(1.112-0.00043499*D11+0.00000055*D11^2-0.00028826*E11)-450)/100,(495/(1.097-0.00046971*D11+0.00000056*D11^2-0.00012828*E11)-450)/100) -> 0.29014844 | G11: 0.290148 | H11: =F11-G11 -> 4.3557139e-07 | I11: =IF(ABS(H11)<=M36_TOL_FRAC,"APROBADO","FALLIDO") -> APROBADO
A12: A05 | B12: Hombre Σ200 | C12: Hombre | D12: 200 | E12: 55 | F12: =IF(C12="Hombre",(495/(1.112-0.00043499*D12+0.00000055*D12^2-0.00028826*E12)-450)/100,(495/(1.097-0.00046971*D12+0.00000056*D12^2-0.00012828*E12)-450)/100) -> 0.30047621 | G12: 0.300476 | H12: =F12-G12 -> 2.0723976e-07 | I12: =IF(ABS(H12)<=M36_TOL_FRAC,"APROBADO","FALLIDO") -> APROBADO
A13: A06 | B13: Mujer Σ90 | C13: Mujer | D13: 90 | E13: 22 | F13: =IF(C13="Hombre",(495/(1.112-0.00043499*D13+0.00000055*D13^2-0.00028826*E13)-450)/100,(495/(1.097-0.00046971*D13+0.00000056*D13^2-0.00012828*E13)-450)/100) -> 0.18554795 | G13: 0.185548 | H13: =F13-G13 -> -4.5423424e-08 | I13: =IF(ABS(H13)<=M36_TOL_FRAC,"APROBADO","FALLIDO") -> APROBADO
A15: BLOQUE B · EXACTITUD JACKSON–POLLOCK 3 SITIOS → densidad → % grasa (Siri)
A16: ID | B16: Descripción | C16: Sexo | D16: Σ3 | E16: Edad | F16: Obtenido | G16: Esperado | H16: Dif. | I16: Estado
A17: B01 | B17: Hombre Σ50 | C17: Hombre | D17: 50 | E17: 34 | F17: =IF(C17="Hombre",(495/(1.10938-0.0008267*D17+0.0000016*D17^2-0.0002574*E17)-450)/100,(495/(1.0994921-0.0009929*D17+0.0000023*D17^2-0.0001392*E17)-450)/100) -> 0.15534724 | G17: 0.155347 | H17: =F17-G17 -> 2.4470217e-07 | I17: =IF(ABS(H17)<=M36_TOL_FRAC,"APROBADO","FALLIDO") -> APROBADO
A18: B02 | B18: Mujer Σ60 | C18: Mujer | D18: 60 | E18: 30 | F18: =IF(C18="Hombre",(495/(1.10938-0.0008267*D18+0.0000016*D18^2-0.0002574*E18)-450)/100,(495/(1.0994921-0.0009929*D18+0.0000023*D18^2-0.0001392*E18)-450)/100) -> 0.24127894 | G18: 0.241279 | H18: =F18-G18 -> -5.5809068e-08 | I18: =IF(ABS(H18)<=M36_TOL_FRAC,"APROBADO","FALLIDO") -> APROBADO
A19: B03 | B19: Hombre Σ35 | C19: Hombre | D19: 35 | E19: 25 | F19: =IF(C19="Hombre",(495/(1.10938-0.0008267*D19+0.0000016*D19^2-0.0002574*E19)-450)/100,(495/(1.0994921-0.0009929*D19+0.0000023*D19^2-0.0001392*E19)-450)/100) -> 0.10049788 | G19: 0.100498 | H19: =F19-G19 -> -1.2389652e-07 | I19: =IF(ABS(H19)<=M36_TOL_FRAC,"APROBADO","FALLIDO") -> APROBADO
A20: B04 | B20: Mujer Σ80 | C20: Mujer | D20: 80 | E20: 45 | F20: =IF(C20="Hombre",(495/(1.10938-0.0008267*D20+0.0000016*D20^2-0.0002574*E20)-450)/100,(495/(1.0994921-0.0009929*D20+0.0000023*D20^2-0.0001392*E20)-450)/100) -> 0.31275889 | G20: 0.312759 | H20: =F20-G20 -> -1.1367824e-07 | I20: =IF(ABS(H20)<=M36_TOL_FRAC,"APROBADO","FALLIDO") -> APROBADO
A21: B05 | B21: Hombre Σ90 | C21: Hombre | D21: 90 | E21: 55 | F21: =IF(C21="Hombre",(495/(1.10938-0.0008267*D21+0.0000016*D21^2-0.0002574*E21)-450)/100,(495/(1.0994921-0.0009929*D21+0.0000023*D21^2-0.0001392*E21)-450)/100) -> 0.28825282 | G21: 0.288253 | H21: =F21-G21 -> -1.8025112e-07 | I21: =IF(ABS(H21)<=M36_TOL_FRAC,"APROBADO","FALLIDO") -> APROBADO
A22: B06 | B22: Mujer Σ45 | C22: Mujer | D22: 45 | E22: 22 | F22: =IF(C22="Hombre",(495/(1.10938-0.0008267*D22+0.0000016*D22^2-0.0002574*E22)-450)/100,(495/(1.0994921-0.0009929*D22+0.0000023*D22^2-0.0001392*E22)-450)/100) -> 0.18569539 | G22: 0.185695 | H22: =F22-G22 -> 3.8606675e-07 | I22: =IF(ABS(H22)<=M36_TOL_FRAC,"APROBADO","FALLIDO") -> APROBADO
A24: BLOQUE C · DURNIN–WOMERSLEY (Siri) Y FAULKNER (directo)
A25: ID | B25: Descripción | C25: Método | D25: c/A | E25: m/B | F25: Σ4 | G25: Obtenido | H25: Esperado | I25: Dif. | J25: Estado
A26: C01 | B26: DW H 30–40 | C26: DW | D26: 1.1422 | E26: 0.0544 | F26: 51 | G26: =(495/(D26-E26*LOG10(F26))-450)/100 -> 0.21739388 | H26: 0.217394 | I26: =G26-H26 -> -1.1807808e-07 | J26: =IF(ABS(I26)<=M36_TOL_FRAC,"APROBADO","FALLIDO") -> APROBADO
A27: C02 | B27: DW M 20–30 | C27: DW | D27: 1.1599 | E27: 0.0717 | F27: 60 | G27: =(495/(D27-E27*LOG10(F27))-450)/100 -> 0.29462279 | H27: 0.294623 | I27: =G27-H27 -> -2.088517e-07 | J27: =IF(ABS(I27)<=M36_TOL_FRAC,"APROBADO","FALLIDO") -> APROBADO
A28: C03 | B28: DW H 40–50 | C28: DW | D28: 1.162 | E28: 0.07 | F28: 45 | G28: =(495/(D28-E28*LOG10(F28))-450)/100 -> 0.23106919 | H28: 0.231069 | I28: =G28-H28 -> 1.8656988e-07 | J28: =IF(ABS(I28)<=M36_TOL_FRAC,"APROBADO","FALLIDO") -> APROBADO
A29: C04 | B29: Faulkner | C29: FA | D29: 0.153 | E29: 5.783 | F29: 66 | G29: =(D29*F29+E29)/100 -> 0.15881 | H29: 0.15881 | I29: =G29-H29 -> 0 | J29: =IF(ABS(I29)<=M36_TOL_FRAC,"APROBADO","FALLIDO") -> APROBADO
A30: C05 | B30: Faulkner | C30: FA | D30: 0.153 | E30: 5.783 | F30: 40 | G30: =(D30*F30+E30)/100 -> 0.11903 | H30: 0.11903 | I30: =G30-H30 -> 0 | J30: =IF(ABS(I30)<=M36_TOL_FRAC,"APROBADO","FALLIDO") -> APROBADO
A31: C06 | B31: Faulkner | C31: FA | D31: 0.153 | E31: 5.783 | F31: 100 | G31: =(D31*F31+E31)/100 -> 0.21083 | H31: 0.21083 | I31: =G31-H31 -> 0 | J31: =IF(ABS(I31)<=M36_TOL_FRAC,"APROBADO","FALLIDO") -> APROBADO
A33: BLOQUE D · ERROR TÉCNICO DE MEDICIÓN (ETM) · ±0,05 mm
A34: ID | B34: Descripción | C34: Σd² | D34: k | E34: Media | F34: ETMabs obt | G34: ETMabs esp | H34: Est.abs | I34: ETMrel obt | J34: ETMrel esp | K34: Est.rel
A35: D01 | B35: Caso tipo | C35: 12 | D35: 8 | E35: 14.375 | F35: =SQRT(C35/(2*D35)) -> 0.8660254 | G35: 0.866025 | H35: =IF(ABS(F35-G35)<=M36_TOL_MM,"APROBADO","FALLIDO") -> APROBADO | I35: =F35/E35 -> 0.060245245 | J35: 0.060245 | K35: =IF(ABS(I35-J35)<=M36_TOL_FRAC,"APROBADO","FALLIDO") -> APROBADO
A36: D02 | B36: Sin error | C36: 0 | D36: 6 | E36: 15 | F36: =SQRT(C36/(2*D36)) -> 0 | G36: 0 | H36: =IF(ABS(F36-G36)<=M36_TOL_MM,"APROBADO","FALLIDO") -> APROBADO | I36: =F36/E36 -> 0 | J36: 0 | K36: =IF(ABS(I36-J36)<=M36_TOL_FRAC,"APROBADO","FALLIDO") -> APROBADO
A37: D03 | B37: Alto error | C37: 50 | D37: 8 | E37: 16 | F37: =SQRT(C37/(2*D37)) -> 1.767767 | G37: 1.767767 | H37: =IF(ABS(F37-G37)<=M36_TOL_MM,"APROBADO","FALLIDO") -> APROBADO | I37: =F37/E37 -> 0.11048543 | J37: 0.110485 | K37: =IF(ABS(I37-J37)<=M36_TOL_FRAC,"APROBADO","FALLIDO") -> APROBADO
A39: BLOQUE E · COMPOSICIÓN (MG, MLG, IMLG) · ±0,05
A40: ID | B40: % grasa | C40: Peso | D40: Talla m | E40: MG obt | F40: MG esp | G40: Est.MG | H40: IMLG obt | I40: IMLG esp | J40: Est.IMLG
A41: E01 | B41: 0.16262 | C41: 78.5 | D41: 1.76 | E41: =B41*C41 -> 12.76567 | F41: 12.7657 | G41: =IF(ABS(E41-F41)<=M36_TOL_KG,"APROBADO","FALLIDO") -> APROBADO | H41: =(C41-B41*C41)/D41^2 -> 21.221052 | I41: 21.2211 | J41: =IF(ABS(H41-I41)<=M36_TOL_KG,"APROBADO","FALLIDO") -> APROBADO
A42: E02 | B42: 0.3 | C42: 60 | D42: 1.6 | E42: =B42*C42 -> 18 | F42: 18 | G42: =IF(ABS(E42-F42)<=M36_TOL_KG,"APROBADO","FALLIDO") -> APROBADO | H42: =(C42-B42*C42)/D42^2 -> 16.40625 | I42: 16.4062 | J42: =IF(ABS(H42-I42)<=M36_TOL_KG,"APROBADO","FALLIDO") -> APROBADO
A43: E03 | B43: 0.12 | C43: 90 | D43: 1.85 | E43: =B43*C43 -> 10.8 | F43: 10.8 | G43: =IF(ABS(E43-F43)<=M36_TOL_KG,"APROBADO","FALLIDO") -> APROBADO | H43: =(C43-B43*C43)/D43^2 -> 23.140979 | I43: 23.141 | J43: =IF(ABS(H43-I43)<=M36_TOL_KG,"APROBADO","FALLIDO") -> APROBADO
A45: BLOQUE F · VALIDACIONES: vacíos, texto, negativos, imposibles
A46: ID | B46: Escenario | C46: Entrada | D46: Comportamiento esperado | E46: Comportamiento obtenido | F46: Estado
A47: F01 | B47: Edad menor de edad (15) | C47: 15 | D47: ERROR: edad fuera del alcance adulto | E47: =IF(NOT(ISNUMBER(15)),"ERROR: edad no numérica",IF(AND(15>=18,15<=120),"OK","ERROR: edad fuera del alcance adulto")) -> ERROR: edad fuera del alcance adulto | F47: =IF(E47=D47,"APROBADO","FALLIDO") -> APROBADO
A48: F02 | B48: Edad textual | C48: quince | D48: ERROR: edad no numérica | E48: =IF(NOT(ISNUMBER("quince")),"ERROR: edad no numérica",IF(AND("quince">=18,"quince"<=120),"OK","ERROR: edad fuera del alcance adulto")) -> ERROR: edad no numérica | F48: =IF(E48=D48,"APROBADO","FALLIDO") -> APROBADO
A49: F03 | B49: Peso negativo (−5) | C49: -5 | D49: ERROR: peso fuera de rango | E49: =IF(NOT(ISNUMBER(-5)),"ERROR: peso no numérico",IF(AND(-5>=25,-5<=350),"OK","ERROR: peso fuera de rango")) -> ERROR: peso fuera de rango | F49: =IF(E49=D49,"APROBADO","FALLIDO") -> APROBADO
A50: F04 | B50: Estatura imposible (400) | C50: 400 | D50: ERROR: estatura fuera de rango | E50: =IF(NOT(ISNUMBER(400)),"ERROR: estatura no numérico",IF(AND(400>=120,400<=230),"OK","ERROR: estatura fuera de rango")) -> ERROR: estatura fuera de rango | F50: =IF(E50=D50,"APROBADO","FALLIDO") -> APROBADO
A51: F05 | B51: Pliegue cero | C51: 0 | D51: ERROR: pliegue fuera de rango | E51: =IF(AND(ISNUMBER(0),0>=1,0<=80),"OK","ERROR: pliegue fuera de rango") -> ERROR: pliegue fuera de rango | F51: =IF(E51=D51,"APROBADO","FALLIDO") -> APROBADO
A52: F06 | B52: Pliegue 95 mm | C52: 95 | D52: ERROR: pliegue fuera de rango | E52: =IF(AND(ISNUMBER(95),95>=1,95<=80),"OK","ERROR: pliegue fuera de rango") -> ERROR: pliegue fuera de rango | F52: =IF(E52=D52,"APROBADO","FALLIDO") -> APROBADO
A53: F07 | B53: % grasa 90 % | C53: 0.9 | D53: ERROR: % de grasa fuera del rango plausible | E53: =IF(AND(ISNUMBER(0.9),0.9>=0.03,0.9<=0.75),"OK","ERROR: % de grasa fuera del rango plausible") -> ERROR: % de grasa fuera del rango plausible | F53: =IF(E53=D53,"APROBADO","FALLIDO") -> APROBADO
A54: F08 | B54: ETM relativo 4 % → OK | C54: 0.04 | D54: OK (≤5%) | E54: =IF(0.04<=0.05,"OK (≤5%)",IF(0.04<=0.075,"Aceptable (5–7,5%)","Revisar técnica (>7,5%)")) -> OK (≤5%) | F54: =IF(E54=D54,"APROBADO","FALLIDO") -> APROBADO
A55: F09 | B55: ETM relativo 6 % → aceptable | C55: 0.06 | D55: Aceptable (5–7,5%) | E55: =IF(0.06<=0.05,"OK (≤5%)",IF(0.06<=0.075,"Aceptable (5–7,5%)","Revisar técnica (>7,5%)")) -> Aceptable (5–7,5%) | F55: =IF(E55=D55,"APROBADO","FALLIDO") -> APROBADO
A56: F10 | B56: ETM relativo 9 % → revisar | C56: 0.09 | D56: Revisar técnica (>7,5%) | E56: =IF(0.09<=0.05,"OK (≤5%)",IF(0.09<=0.075,"Aceptable (5–7,5%)","Revisar técnica (>7,5%)")) -> Revisar técnica (>7,5%) | F56: =IF(E56=D56,"APROBADO","FALLIDO") -> APROBADO
A58: BLOQUE G · INTEGRIDAD: cero errores de Excel
A59: ID | B59: Rango verificado | C59: Nº errores | D59: Esperado | E59: Estado
A60: G01 | B60: CALCULOS!B7:B55 | C60: =SUMPRODUCT(--ISERROR(M36_CALCULOS!B7:B55)) -> 0 | D60: 0 | E60: =IF(C60=D60,"APROBADO","FALLIDO") -> APROBADO
A61: G02 | B61: PLIEGUES!E7:F14 | C61: =SUMPRODUCT(--ISERROR(M36_PLIEGUES!E7:F14)) -> 0 | D61: 0 | E61: =IF(C61=D61,"APROBADO","FALLIDO") -> APROBADO
A62: G03 | B62: RESULTADOS!B6:F60 | C62: =SUMPRODUCT(--ISERROR(M36_RESULTADOS!B6:F60)) -> 0 | D62: 0 | E62: =IF(C62=D62,"APROBADO","FALLIDO") -> APROBADO
A64: BLOQUE H · COTEJO CON EL MOTOR (caso vivo · reconstrucción literal)
A65: ID | B65: Verificación | C65: Obtenido (motor) | D65: Esperado (literal) | E65: Dif. | F65: Estado
A66: H01 | B66: % grasa JP7 (Hombre, Siri) | C66: =M36_c_GrJP7 -> 0.13989155 | D66: =(495/(1.112-0.00043499*(M36_p_Pect+M36_p_Axil+M36_p_Tri+M36_p_Sub+M36_p_Abd+M36_p_Supra+M36_p_Muslo)+0.00000055*(M36_p_Pect+M36_p_Axil+M36_p_Tri+M36_p_Sub+M36_p_Abd+M36_p_Supra+M36_p_Muslo)^2-0.00028826*M36_in_Edad)-450)/100 -> 0.13989155 | E66: =C66-D66 -> 0 | F66: =IF(ABS(E66)<=M36_TOL_FRAC,"APROBADO","FALLIDO") -> APROBADO
A67: H02 | B67: % grasa Faulkner | C67: =M36_c_GrFaulk -> 0.15269 | D67: =(0.153*(M36_p_Tri+M36_p_Sub+M36_p_Supra+M36_p_Abd)+5.783)/100 -> 0.15269 | E67: =C67-D67 -> 0 | F67: =IF(ABS(E67)<=M36_TOL_FRAC,"APROBADO","FALLIDO") -> APROBADO
A68: H03 | B68: ETM relativo | C68: =M36_a_TEMrel -> 0.060245245 | D68: =M36_a_TEMabs/M36_a_MediaG -> 0.060245245 | E68: =C68-D68 -> 0 | F68: =IF(ABS(E68)<=M36_TOL_FRAC,"APROBADO","FALLIDO") -> APROBADO
A69: H04 | B69: Masa grasa = %rep × peso | C69: =M36_c_MG -> 10.981487 | D69: =M36_c_GrRep*M36_in_Peso -> 10.981487 | E69: =C69-D69 -> 0 | F69: =IF(ABS(E69)<=M36_TOL_KG,"APROBADO","FALLIDO") -> APROBADO
A72: RESUMEN DEL BANCO DE PRUEBAS
A73: Casos totales | C73: 47
A74: Aprobados | C74: =IF(I8="APROBADO",1,0)+IF(I9="APROBADO",1,0)+IF(I10="APROBADO",1,0)+IF(I11="APROBADO",1,0)+IF(I12="APROBADO",1,0)+IF(I13="APROBADO",1,0)+IF(I17="APROBADO",1,0)+IF(I18="APROBADO",1,0)+IF(I19="APROBADO",1,0)+IF(I20="APROBADO",1,0)+IF(I21="APROBADO",1,0)+IF(I22="APROBADO",1,0)+IF(J26="APROBADO",1,0)+IF(J27="APROBADO",1,0)+IF(J28="APROBADO",1,0)+IF(J29="APROBADO",1,0)+IF(J30="APROBADO",1,0)+IF(J31="APROBADO",1,0)+IF(H35="APROBADO",1,0)+IF(K35="APROBADO",1,0)+IF(H36="APROBADO",1,0)+IF(K36="APROBADO",1,0)+IF(H37="APROBADO",1,0)+IF(K37="APROBADO",1,0)+IF(G41="APROBADO",1,0)+IF(J41="APROBADO",1,0)+IF(G42="APROBADO",1,0)+IF(J42="APROBADO",1,0)+IF(G43="APROBADO",1,0)+IF(J43="APROBADO",1,0)+IF(F47="APROBADO",1,0)+IF(F48="APROBADO",1,0)+IF(F49="APROBADO",1,0)+IF(F50="APROBADO",1,0)+IF(F51="APROBADO",1,0)+IF(F52="APROBADO",1,0)+IF(F53="APROBADO",1,0)+IF(F54="APROBADO",1,0)+IF(F55="APROBADO",1,0)+IF(F56="APROBADO",1,0)+IF(E60="APROBADO",1,0)+IF(E61="APROBADO",1,0)+IF(E62="APROBADO",1,0)+IF(F66="APROBADO",1,0)+IF(F67="APROBADO",1,0)+IF(F68="APROBADO",1,0)+IF(F69="APROBADO",1,0) -> 47
A75: Fallidos | C75: =47-C74 -> 0
A76: ESTADO GLOBAL | B76: =IF(C74=47,"TODAS LAS PRUEBAS APROBADAS","HAY PRUEBAS FALLIDAS — REVISAR") -> TODAS LAS PRUEBAS APROBADAS

Sheet M36_CONFIG
A1: NUTRIMETRÍA · NMX-36
A2: Parámetros, coeficientes y catálogos · versión 1.0
A3: =HYPERLINK("#M36_INICIO!A1","◀ INICIO") -> ◀ INICIO
A4: Toda constante del modelo vive aquí; ninguna fórmula del libro contiene un coeficiente escrito a mano. Las celdas arena son editables. Cambiar un valor aquí propaga a todo el libro y hace FALLAR las pruebas que cotejan contra la fuente publicada.
A6: C1 · PARÁMETROS, LÍMITES Y COEFICIENTES
A7: Parámetro | B7: Valor | C7: Unidad | D7: Tipo | E7: Nota / fuente
A8: Idioma | B8: Español (es-CL) | C8: — | D8: — | E8: Interfaz
A9: Versión de las fuentes | B9: 2026-07 · v1.0 | C9: — | D9: — | E9: Ver hoja FUENTES
A10: Edad mínima (adulto) | B10: 18 | C10: años | D10: IMPOSIBLE | E10: Alcance: solo adultos
A11: Edad máxima plausible | B11: 120 | C11: años | D11: IMPOSIBLE | E11: Límite operativo
A12: Peso mínimo posible | B12: 25 | C12: kg | D12: IMPOSIBLE
A13: Peso máximo posible | B13: 350 | C13: kg | D13: IMPOSIBLE
A14: Estatura mínima posible | B14: 120 | C14: cm | D14: IMPOSIBLE
A15: Estatura máxima posible | B15: 230 | C15: cm | D15: IMPOSIBLE
A16: Pliegue mínimo por sitio | B16: 1 | C16: mm | D16: IMPOSIBLE | E16: Guarda de cada pliegue
A17: Pliegue máximo por sitio | B17: 80 | C17: mm | D17: IMPOSIBLE | E17: Guarda de cada pliegue
A18: % de grasa mínimo plausible | B18: 0.03 | C18: % | D18: IMPOSIBLE | E18: Grasa esencial
A19: % de grasa máximo plausible | B19: 0.75 | C19: % | D19: IMPOSIBLE
A20: Rango máximo aceptado entre métodos | B20: 0.08 | C20: p.p. | D20: Umbral | E20: Rango (máx−mín) del % de grasa, en puntos porcentuales
A21: ETM relativo · límite OK (ISAK) | B21: 0.05 | C21: % | D21: Umbral | E21: ≤5 % intraevaluador experimentado
A22: ETM relativo · límite aceptable | B22: 0.075 | C22: % | D22: Umbral | E22: 5–7,5 % aceptable; >7,5 % revisar técnica
A23: Tolerancia de pruebas · fracción | B23: 0.0005 | C23: — | D23: Umbral | E23: % de grasa (fracción)
A24: Tolerancia de pruebas · kg | B24: 0.05 | C24: kg | D24: Umbral | E24: Masa (kg)
A25: Tolerancia de pruebas · mm | B25: 0.05 | C25: mm | D25: Umbral | E25: Pliegues y ETM
A26: Siri (1961) · numerador | B26: 495 | C26: — | D26: Coef. | E26: %grasa = 495/D − 450
A27: Siri (1961) · término | B27: 450 | C27: — | D27: Coef.
A28: Brožek (1963) · numerador | B28: 457 | C28: — | D28: Coef. | E28: %grasa = 457/D − 414
A29: Brožek (1963) · término | B29: 414 | C29: — | D29: Coef.
A30: Faulkner (1968) · pendiente | B30: 0.153 | C30: — | D30: Coef. | E30: %grasa = 0,153·Σ4 + 5,783
A31: Faulkner (1968) · intersección | B31: 5.783 | C31: — | D31: Coef.
A32: Jackson–Pollock 7 · hombre · a | B32: 1.112 | C32: — | D32: Coef. | E32: BD = a − b1·Σ + b2·Σ² − b3·edad
A33: Jackson–Pollock 7 · hombre · b1 | B33: 0.00043499 | C33: — | D33: Coef.
A34: Jackson–Pollock 7 · hombre · b2 | B34: 5.5e-07 | C34: — | D34: Coef.
A35: Jackson–Pollock 7 · hombre · b3 | B35: 0.00028826 | C35: — | D35: Coef.
A36: Jackson–Pollock 7 · mujer · a | B36: 1.097 | C36: — | D36: Coef.
A37: Jackson–Pollock 7 · mujer · b1 | B37: 0.00046971 | C37: — | D37: Coef.
A38: Jackson–Pollock 7 · mujer · b2 | B38: 5.6e-07 | C38: — | D38: Coef.
A39: Jackson–Pollock 7 · mujer · b3 | B39: 0.00012828 | C39: — | D39: Coef.
A40: Jackson–Pollock 3 · hombre · a | B40: 1.10938 | C40: — | D40: Coef. | E40: Sitios H: pectoral, abdominal, muslo
A41: Jackson–Pollock 3 · hombre · b1 | B41: 0.0008267 | C41: — | D41: Coef.
A42: Jackson–Pollock 3 · hombre · b2 | B42: 1.6e-06 | C42: — | D42: Coef.
A43: Jackson–Pollock 3 · hombre · b3 | B43: 0.0002574 | C43: — | D43: Coef.
A44: Jackson–Pollock 3 · mujer · a | B44: 1.0994921 | C44: — | D44: Coef. | E44: Sitios M: tríceps, suprailíaco, muslo
A45: Jackson–Pollock 3 · mujer · b1 | B45: 0.0009929 | C45: — | D45: Coef.
A46: Jackson–Pollock 3 · mujer · b2 | B46: 2.3e-06 | C46: — | D46: Coef.
A47: Jackson–Pollock 3 · mujer · b3 | B47: 0.0001392 | C47: — | D47: Coef.
A49: C2 · SEXOS
A50: Valor | B50: Nota
A51: Hombre | B51: Ecuaciones derivadas en varones
A52: Mujer | B52: Ecuaciones derivadas en mujeres
A54: C3 · ECUACIÓN A REPORTAR
A55: Ecuación (lista) | B55: Sitios que exige
A56: 7 sitios · Jackson–Pollock | B56: pectoral, axilar, tríceps, subescapular, abdominal, suprailíaco, muslo
A57: 3 sitios · Jackson–Pollock | B57: H: pectoral, abdominal, muslo · M: tríceps, suprailíaco, muslo
A58: 4 pliegues · Durnin–Womersley | B58: bíceps, tríceps, subescapular, suprailíaco
A59: 4 pliegues · Faulkner | B59: tríceps, subescapular, suprailíaco, abdominal
A61: C4 · CONVERSIÓN DENSIDAD → % DE GRASA (JP y DW)
A62: Fórmula (lista) | B62: Expresión
A63: Siri (1961) | B63: %grasa = 495/D − 450
A64: Brožek (1963) | B64: %grasa = 457/D − 414
A66: C5 · LISTA SÍ / NO
A67: Sí
A68: No
A70: C6 · DURNIN–WOMERSLEY (1974) · densidad = c − m·log10(Σ4) · por sexo y banda etaria
A71: Sexo | B71: Edad desde (≥) | C71: Edad hasta (<) | D71: c | E71: m
A72: Hombre | B72: 17 | C72: 20 | D72: 1.162 | E72: 0.063
A73: Hombre | B73: 20 | C73: 30 | D73: 1.1631 | E73: 0.0632
A74: Hombre | B74: 30 | C74: 40 | D74: 1.1422 | E74: 0.0544
A75: Hombre | B75: 40 | C75: 50 | D75: 1.162 | E75: 0.07
A76: Hombre | B76: 50 | C76: 200 | D76: 1.1715 | E76: 0.0779
A77: Mujer | B77: 16 | C77: 20 | D77: 1.1549 | E77: 0.0678
A78: Mujer | B78: 20 | C78: 30 | D78: 1.1599 | E78: 0.0717
A79: Mujer | B79: 30 | C79: 40 | D79: 1.1423 | E79: 0.0632
A80: Mujer | B80: 40 | C80: 50 | D80: 1.1333 | E80: 0.0612
A81: Mujer | B81: 50 | C81: 200 | D81: 1.1339 | E81: 0.0645
A83: C7 · % DE GRASA · RANGOS REFERENCIALES POR SEXO (ACE) · corte inferior (≥)
A84: Sexo | B84: Categoría | C84: Corte inferior (≥) | D84: Nota
A85: Hombre | B85: Grasa esencial | C85: 0.02 | D85: 2–5 %
A86: Hombre | B86: Atlético | C86: 0.06 | D86: 6–13 %
A87: Hombre | B87: En forma | C87: 0.14 | D87: 14–17 %
A88: Hombre | B88: Aceptable | C88: 0.18 | D88: 18–24 %
A89: Hombre | B89: Obesidad | C89: 0.25 | D89: ≥25 %
A90: Mujer | B90: Grasa esencial | C90: 0.1 | D90: 10–13 %
A91: Mujer | B91: Atlético | C91: 0.14 | D91: 14–20 %
A92: Mujer | B92: En forma | C92: 0.21 | D92: 21–24 %
A93: Mujer | B93: Aceptable | C93: 0.25 | D93: 25–31 %
A94: Mujer | B94: Obesidad | C94: 0.32 | D94: ≥32 %
A96: Rangos REFERENCIALES (American Council on Exercise). NO son un estándar oficial. Las ecuaciones de pliegues NO son intercambiables entre sí: elija UNA validada para su población y úsela de forma consistente.

Sheet M36_CHANGELOG
A1: NUTRIMETRÍA · NMX-36
A2: Historial de versiones
A3: =HYPERLINK("#M36_INICIO!A1","◀ INICIO") -> ◀ INICIO
A5: Versión | B5: Fecha | C5: Cambio | D5: Motivo | E5: Responsable
A6: 1.0 | B6: 2026-07-14 | C6: Versión inicial. Panel ISAK de 8 sitios con doble medición y error técnico de medición (ETM) intraevaluador; cuatro ecuaciones (Jackson–Pollock 7 y 3 sitios, Durnin–Womersley, Faulkner) con reconciliación y Σ de pliegues para seguimiento. | D6: Primera entrega del producto 36. | E6: Equipo Nutrimetría
A7: 1.0 | B7: 2026-07-14 | C7: Banco de pruebas con exactitud de las cuatro ecuaciones, ETM, composición, validaciones e integridad, con valores esperados independientes del CONFIG. | D7: Control de calidad. | E7: Equipo Nutrimetría

Sheet M12_INICIO
A1: NUTRIMETRÍA · NMX-12
A2: Calculadora de grasa y composición corporal · versión 1.0
A4: Navegación — use las pestañas inferiores del libro
A5: =HYPERLINK("#M12_DATOS!A1","▶ DATOS") -> ▶ DATOS | B5: =HYPERLINK("#M12_CALCULOS!A1","▶ CALCULOS") -> ▶ CALCULOS | D5: =HYPERLINK("#M12_RESULTADOS!A1","▶ RESULTADOS") -> ▶ RESULTADOS | F5: =HYPERLINK("#M12_FUENTES!A1","▶ FUENTES") -> ▶ FUENTES | H5: =HYPERLINK("#M12_PRUEBAS!A1","▶ PRUEBAS") -> ▶ PRUEBAS | J5: =HYPERLINK("#M12_CONFIG!A1","▶ CONFIG") -> ▶ CONFIG | L5: =HYPERLINK("#M12_CHANGELOG!A1","▶ CHANGELOG") -> ▶ CHANGELOG
A6: Ingresar datos | B6: Auditar operaciones | D6: Ver resumen | F6: Trazabilidad | H6: Control de calidad | J6: Constantes | L6: Historial
A7: Código del producto | C7: NMX-12
A8: Versión | C8: 1.0
A9: Fecha | C9: 2026-07-14
A10: Localización | C10: Chile (es-CL) · clasificación anclada a MINSAL y OMS
A11: Formato | C11: .xlsx sin macros · Microsoft 365 y Excel 2021
A12: Responsable | C12: Equipo Nutrimetría (completar por el titular)
A13: AVISO DE ALCANCE — LÉALO ANTES DE USAR
A14: EXACTITUD MATEMÁTICA ≠ VALIDACIÓN CLÍNICA. Este archivo NO está validado clínicamente.
A15: APLICA A: personas ADULTAS (≥18 años) en condición estable.
A16: NO APLICA A: embarazo · lactancia · menores de edad · pacientes críticos · atletas de élite (subestima/sobrestima).
A17: Los métodos ESTIMAN la composición; la referencia son DEXA o pesaje hidrostático.
A18: La clasificación de IMC y cintura usa cortes del MINSAL/OMS. Los rangos de % de grasa (ACE) son REFERENCIALES.
A19: La antropometría depende de la técnica del evaluador: pliegues y circunferencias mal tomados invalidan el resultado.
A20: PROPÓSITO Y ALCANCE
A21: Propósito | C21: Proveer una herramienta de cálculo automatizado que permita estimar la composición corporal (porcentaje de grasa y masa libre de grasa) a partir de mediciones de pliegues cutáneos y circunferencias, sirviendo como apoyo práctico para el diagnóstico y la planificación alimentaria.
A22: Población | C22: Personas adultas (≥18 años) en condición estable. No aplica a embarazo, lactancia, menores de edad, pacientes críticos ni atletas de élite.
A23: Uso | C23: Los métodos ESTIMAN la composición corporal; la referencia son DEXA o pesaje hidrostático.
A24: Compatibilidad | C24: .xlsx sin macros · Microsoft 365 y Excel 2021
A25: Privacidad | C25: Los datos permanecen en el archivo local. El libro no transmite información.
A26: CÓMO SE MODELA
A27: Método 1 (pliegues): densidad = c − m·log10(Σ4 pliegues) → % grasa por Siri (495/D−450) o Brožek (457/D−414).
A28: Método 2 (circunferencias): fórmula US Navy con cuello, cintura, estatura (y cadera en mujeres).
A29: Método 3 (IMC): Deurenberg = 1,20·IMC + 0,23·edad − 10,8·sexo − 5,4.
A30: Composición: MG = %grasa×peso · MLG = peso − MG · IMG = MG/talla² · IMLG = MLG/talla².
A31: Distribución: ICC = cintura/cadera · ICE = cintura/estatura, con cortes de riesgo MINSAL/OMS.

Sheet M12_DATOS
A1: NUTRIMETRÍA · NMX-12
A2: Datos de entrada · variables ingresadas por el usuario
A3: =HYPERLINK("#M12_INICIO!A1","◀ INICIO") -> ◀ INICIO | B3: =HYPERLINK("#M12_CALCULOS!A1","▶ CALCULOS") -> ▶ CALCULOS | D3: =HYPERLINK("#M12_RESULTADOS!A1","▶ RESULTADOS") -> ▶ RESULTADOS
A4: LEYENDA · Celdas ARENA con texto AZUL = editables. Grises = calculadas. (opcional) = puede quedar vacía.
A5: ► Viene cargado un CASO DE EJEMPLO realista. Reemplace los valores por los de su paciente.
A6: Campo | B6: Valor | C6: Unidad | D6: Validación | E6: Ayuda
A7: Identificador de la evaluación | B7: =DATOS!$B$7 -> NMX-2026-0028 | C7: — | D7: Texto libre | E7: Código interno de la evaluación.
A8: Fecha | B8: =DATOS!$B$8 -> 46236 | C8: fecha | D8: Fecha | E8: dd/mm/aaaa.
A9: Nombre o código del paciente | B9: =DATOS!$B$9 -> PER-0007 | C9: — | D9: Texto libre | E9: Prefiera un CÓDIGO si va a compartir el archivo.
A10: Sexo biológico | B10: =DATOS!$B$10 -> Hombre | C10: — | D10: Lista: Hombre / Mujer | E10: Las ecuaciones se derivaron por sexo biológico.
A11: Edad | B11: =DATOS!$B$11 -> 34 | C11: años | D11: ≥18 y ≤120 | E11: Solo adultos.
A12: Peso | B12: =DATOS!$B$12 -> 78.5 | C12: kg | D12: Entre 25 y 350 | E12: Balanza calibrada, ropa ligera.
A13: Estatura | B13: =DATOS!$B$13 -> 176 | C13: cm | D13: Entre 120 y 230 | E13: De pie, sin zapatos.
A14: Método de % de grasa a reportar | B14: 1 · Pliegues (Durnin–Womersley 1974) | C14: — | D14: Lista (CONFIG C3) | E14: Los tres métodos se calculan; este define cuál se destaca.
A15: Conversión densidad→grasa | B15: Siri (1961) | C15: — | D15: Lista (CONFIG C4) | E15: Solo afecta al método de pliegues.
A16: Pliegue bíceps | B16: =MED_Bic -> 5 | C16: mm | D16: Entre 1 y 80 | E16: Pliegue vertical, cara anterior del brazo.
A17: Pliegue tríceps | B17: =MED_Tri -> 12 | C17: mm | D17: Entre 1 y 80 | E17: Pliegue vertical, cara posterior del brazo.
A18: Pliegue subescapular | B18: =MED_Sub -> 14 | C18: mm | D18: Entre 1 y 80 | E18: Pliegue oblicuo bajo el ángulo de la escápula.
A19: Pliegue suprailíaco | B19: =MED_Supra -> 16 | C19: mm | D19: Entre 1 y 80 | E19: Pliegue sobre la cresta ilíaca.
A20: Circunferencia de cuello | B20: =MED_Cuello -> 38 | C20: cm | D20: Entre 20 y 70 | E20: Bajo la laringe. Necesaria para el método de circunferencias.
A21: Circunferencia de cintura | B21: =MED_Cintura -> 85 | C21: cm | D21: Entre 40 y 200 | E21: En el punto medio entre última costilla y cresta ilíaca.
A22: Circunferencia de cadera | B22: =MED_Cadera -> 98 | C22: cm | D22: Entre 50 y 200 | E22: En la máxima prominencia glútea. Necesaria en mujeres (Navy) e ICC.
A23: Observaciones | B23: =DATOS!$B$17 -> 0 | C23: — | D23: Texto libre | E23: Contexto clínico, criterios, calidad de la medición.
A25: ► Los tres métodos se comparan en RESULTADOS. Si discrepan mucho, el libro lo advierte.

Sheet M12_CALCULOS
A1: NUTRIMETRÍA · NMX-12
A2: Motor de cálculo · densidad, % de grasa por tres métodos y composición
A3: ◀ DATOS | C3: ▶ RESULTADOS
A4: Cada celda calculada declara su fórmula. Las guardas devuelven texto 'ND: …' en vez de errores de Excel, de modo que un dato ausente no rompe la cadena.
A6: BLOQUE 0 · BASE
A7: Variable | B7: Valor | C7: Unidad | D7: Fórmula / cómo se obtiene
A8: Estatura en metros | B8: =IF(ISNUMBER(M12_in_Est),M12_in_Est/100,"ND: estatura") -> 1.76 | C8: m | D8: in_Est/100
A9: IMC | B9: =IF(AND(ISNUMBER(M12_in_Peso),ISNUMBER(M12_in_Est),M12_in_Est>0),M12_in_Peso/(M12_in_Est/100)^2,"ND: faltan peso o estatura") -> 25.3422 | C9: kg/m² | D9: peso/estatura²
A10: Σ de los 4 pliegues | B10: =IF(AND(ISNUMBER(M12_in_PliBi),ISNUMBER(M12_in_PliTri),ISNUMBER(M12_in_PliSub),ISNUMBER(M12_in_PliSupra),M12_in_PliBi>0,M12_in_PliTri>0,M12_in_PliSub>0,M12_in_PliSupra>0),M12_in_PliBi+M12_in_PliTri+M12_in_PliSub+M12_in_PliSupra,"ND: faltan pliegues") -> 47 | C10: mm | D10: bíceps+tríceps+subescapular+suprailíaco
A11: BLOQUE 1 · COMPUERTA DE DATOS IMPOSIBLES
A12: Variable | B12: Valor | C12: Unidad | D12: Fórmula / cómo se obtiene
A13: ¿Cálculo habilitado? | B13: =IF(AND(COUNTIF(M12_SEXOS,M12_in_Sexo)>0,ISNUMBER(M12_in_Edad),M12_in_Edad>=M12_EDAD_MIN,M12_in_Edad<=M12_EDAD_MAX,ISNUMBER(M12_in_Peso),M12_in_Peso>=M12_PESO_MIN,M12_in_Peso<=M12_PESO_MAX,ISNUMBER(M12_in_Est),M12_in_Est>=M12_EST_MIN,M12_in_Est<=M12_EST_MAX),"SÍ","NO") -> SÍ | C13: — | D13: Exige sexo, edad adulta, peso y estatura válidos
A14: BLOQUE 2 · % DE GRASA POR TRES MÉTODOS (fracción)
A15: Variable | B15: Valor | C15: Unidad | D15: Fórmula / cómo se obtiene
A16: Durnin–Womersley · c | B16: =IF(AND(M12_c_Gate="SÍ",ISNUMBER(M12_c_SumPli)),SUMPRODUCT((M12_CONFIG!$A$80:$A$89=M12_in_Sexo)*(M12_CONFIG!$B$80:$B$89<=M12_in_Edad)*(M12_CONFIG!$C$80:$C$89>M12_in_Edad)*M12_CONFIG!$D$80:$D$89),"ND") -> 1.1422 | C16: — | D16: Coeficiente c por sexo y banda etaria
A17: Durnin–Womersley · m | B17: =IF(AND(M12_c_Gate="SÍ",ISNUMBER(M12_c_SumPli)),SUMPRODUCT((M12_CONFIG!$A$80:$A$89=M12_in_Sexo)*(M12_CONFIG!$B$80:$B$89<=M12_in_Edad)*(M12_CONFIG!$C$80:$C$89>M12_in_Edad)*M12_CONFIG!$E$80:$E$89),"ND") -> 0.0544 | C17: — | D17: Coeficiente m por sexo y banda etaria
A18: Densidad corporal (pliegues) | B18: =IF(AND(ISNUMBER(M12_c_DWc),ISNUMBER(M12_c_DWm),ISNUMBER(M12_c_SumPli)),M12_c_DWc-M12_c_DWm*LOG10(M12_c_SumPli),"ND") -> 1.0512379 | C18: g/mL | D18: c − m·log10(Σ4)
A19: Método 1 · % grasa (pliegues) | B19: =IF(ISNUMBER(M12_c_Dens),IF(M12_in_Conv="Brožek (1963)",(M12_BRO_A/M12_c_Dens-M12_BRO_B)/100,(M12_SIRI_A/M12_c_Dens-M12_SIRI_B)/100),"ND") -> 0.20873445 | C19: % | D19: Siri o Brožek sobre la densidad
A20: Método 2 · % grasa (US Navy) | B20: =IF(AND(M12_c_Gate="SÍ",ISNUMBER(M12_in_Cuello),ISNUMBER(M12_in_Cintura),IF(M12_in_Sexo="Mujer",ISNUMBER(M12_in_Cadera),TRUE())),IF(M12_in_Sexo="Hombre",IF((M12_in_Cintura-M12_in_Cuello)>0,(M12_SIRI_A/(M12_NAVY_H0-M12_NAVY_H1*LOG10(M12_in_Cintura-M12_in_Cuello)+M12_NAVY_H2*LOG10(M12_in_Est))-M12_SIRI_B)/100,"ND: cintura≤cuello"),IF((M12_in_Cintura+M12_in_Cadera-M12_in_Cuello)>0,(M12_SIRI_A/(M12_NAVY_M0-M12_NAVY_M1*LOG10(M12_in_Cintura+M12_in_Cadera-M12_in_Cuello)+M12_NAVY_M2*LOG10(M12_in_Est))-M12_SIRI_B)/100,"ND")),"ND: faltan circunferencias") -> 0.1676962 | C20: % | D20: Circunferencias (cm) con log10
A21: Método 3 · % grasa (Deurenberg) | B21: =IF(AND(M12_c_Gate="SÍ",ISNUMBER(M12_c_IMC)),(M12_DEU_IMC*M12_c_IMC+M12_DEU_EDAD*M12_in_Edad-M12_DEU_SEXO*IF(M12_in_Sexo="Hombre",1,0)-M12_DEU_CONST)/100,"ND") -> 0.2203064 | C21: % | D21: 1,20·IMC+0,23·edad−10,8·sexo−5,4
A22: BLOQUE 3 · RECONCILIACIÓN DE LOS MÉTODOS
A23: Variable | B23: Valor | C23: Unidad | D23: Fórmula / cómo se obtiene
A24: % grasa REPORTADO | B24: =CHOOSE(MATCH(M12_in_Metodo,M12_LISTA_MET,0),M12_c_GrPli,M12_c_GrNavy,M12_c_GrDeu) -> 0.20873445 | C24: % | D24: Método elegido en DATOS
A25: Métodos con dato (n) | B25: =COUNT(M12_c_GrPli,M12_c_GrNavy,M12_c_GrDeu) -> 3 | C25: — | D25: Cuántos métodos entregaron número
A26: Promedio de los métodos | B26: =IF(M12_c_n>0,AVERAGE(M12_c_GrPli,M12_c_GrNavy,M12_c_GrDeu),"ND") -> 0.19891235 | C26: % | D26: AVERAGE ignora los ND
A27: Mínimo | B27: =IF(M12_c_n>0,MIN(M12_c_GrPli,M12_c_GrNavy,M12_c_GrDeu),"ND") -> 0.1676962 | C27: %
A28: Máximo | B28: =IF(M12_c_n>0,MAX(M12_c_GrPli,M12_c_GrNavy,M12_c_GrDeu),"ND") -> 0.2203064 | C28: %
A29: Rango (máx − mín) | B29: =IF(AND(ISNUMBER(M12_c_min),ISNUMBER(M12_c_max)),M12_c_max-M12_c_min,"ND") -> 0.052610209 | C29: %
A30: Amplitud relativa | B30: =IF(AND(ISNUMBER(M12_c_rango),ISNUMBER(M12_c_prom),M12_c_prom>0),M12_c_rango/M12_c_prom,"ND") -> 0.26448941 | C30: — | D30: rango/promedio
A31: Estado de concordancia | B31: =IF(ISNUMBER(M12_c_ampl),IF(M12_c_ampl<=M12_DISP_MAX,"OK: los métodos disponibles concuerdan dentro del umbral.","ATENCIÓN: los métodos discrepan más que el umbral configurado."),"ND") -> ATENCIÓN: los métodos discrepan más que el umbral configurado. | C31: — | D31: Compara la amplitud con DISP_MAX
A32: BLOQUE 4 · COMPOSICIÓN CORPORAL (según el método reportado)
A33: Variable | B33: Valor | C33: Unidad | D33: Fórmula / cómo se obtiene
A34: Masa grasa (MG) | B34: =IF(AND(ISNUMBER(M12_c_GrRep),ISNUMBER(M12_in_Peso)),M12_c_GrRep*M12_in_Peso,"ND") -> 16.385654 | C34: kg | D34: % grasa × peso
A35: Masa libre de grasa (MLG) | B35: =IF(AND(ISNUMBER(M12_c_MG),ISNUMBER(M12_in_Peso)),M12_in_Peso-M12_c_MG,"ND") -> 62.114346 | C35: kg | D35: peso − MG
A36: Índice de masa grasa (IMG) | B36: =IF(AND(ISNUMBER(M12_c_MG),ISNUMBER(M12_c_TallaM),M12_c_TallaM>0),M12_c_MG/M12_c_TallaM^2,"ND") -> 5.2897902 | C36: kg/m² | D36: MG / estatura²
A37: Índice de masa libre de grasa (IMLG) | B37: =IF(AND(ISNUMBER(M12_c_MLG),ISNUMBER(M12_c_TallaM),M12_c_TallaM>0),M12_c_MLG/M12_c_TallaM^2,"ND") -> 20.05241 | C37: kg/m² | D37: MLG / estatura²
A38: BLOQUE 5 · DISTRIBUCIÓN Y RIESGO CARDIOMETABÓLICO
A39: Variable | B39: Valor | C39: Unidad | D39: Fórmula / cómo se obtiene
A40: Índice cintura/cadera (ICC) | B40: =IF(AND(ISNUMBER(M12_in_Cintura),ISNUMBER(M12_in_Cadera),M12_in_Cadera>0),M12_in_Cintura/M12_in_Cadera,"ND") -> 0.86734694 | C40: — | D40: cintura/cadera
A41: Índice cintura/estatura (ICE) | B41: =IF(AND(ISNUMBER(M12_in_Cintura),ISNUMBER(M12_in_Est),M12_in_Est>0),M12_in_Cintura/M12_in_Est,"ND") -> 0.48295455 | C41: — | D41: cintura/estatura
A42: Riesgo por circunferencia de cintura | B42: =IF(ISNUMBER(M12_in_Cintura),IF(M12_in_Cintura>=IF(M12_in_Sexo="Hombre",M12_CINT_H,M12_CINT_M),"Riesgo aumentado","Sin riesgo aumentado"),"ND") -> Sin riesgo aumentado | C42: — | D42: Cortes MINSAL/OMS (H≥102, M≥88)
A43: Riesgo por ICC | B43: =IF(ISNUMBER(M12_c_ICC),IF(M12_c_ICC>=IF(M12_in_Sexo="Hombre",M12_ICC_H,M12_ICC_M),"Riesgo aumentado","Sin riesgo aumentado"),"ND") -> Sin riesgo aumentado | C43: — | D43: OMS 2008 (H≥0,90, M≥0,85)
A44: Riesgo por ICE | B44: =IF(ISNUMBER(M12_c_ICE),IF(M12_c_ICE>=M12_ICE_R,"Riesgo aumentado","Sin riesgo aumentado"),"ND") -> Sin riesgo aumentado | C44: — | D44: Umbral general ≥0,5
A45: BLOQUE 6 · CLASIFICACIÓN
A46: Variable | B46: Valor | C46: Unidad | D46: Fórmula / cómo se obtiene
A47: Clasificación por IMC | B47: =IF(ISNUMBER(M12_c_IMC),IF(AND(ISNUMBER(M12_in_Edad),M12_in_Edad>=M12_EDAD_AM),IF(M12_c_IMC<M12_AM_C1,"Bajo peso (MINSAL AM)",IF(M12_c_IMC<M12_AM_C2,"Normal (MINSAL AM)",IF(M12_c_IMC<M12_AM_C3,"Sobrepeso (MINSAL AM)","Obesidad (MINSAL AM)"))),IF(M12_c_IMC<M12_IMC_C1,"Bajo peso (OMS)",IF(M12_c_IMC<M12_IMC_C2,"Normal (OMS)",IF(M12_c_IMC<M12_IMC_C3,"Sobrepeso (OMS)",IF(M12_c_IMC<M12_IMC_C4,"Obesidad I (OMS)",IF(M12_c_IMC<M12_IMC_C5,"Obesidad II (OMS)","Obesidad III (OMS)")))))),"ND") -> Sobrepeso (OMS) | C47: — | D47: OMS para adultos; MINSAL para ≥65 años
A48: Clasificación por % grasa (referencial ACE) | B48: =IF(ISNUMBER(M12_c_GrRep),INDEX(M12_CONFIG!$B$95:$B$104,IF(M12_in_Sexo="Hombre",0,5)+MAX(1,SUMPRODUCT((M12_CONFIG!$A$95:$A$104=M12_in_Sexo)*(M12_CONFIG!$C$95:$C$104<=M12_c_GrRep)))),"ND") -> Aceptable | C48: — | D48: Rangos ACE por sexo (referenciales)
A49: BLOQUE 7 · ADVERTENCIAS
A50: Variable | B50: Valor | C50: Unidad | D50: Fórmula / cómo se obtiene
A51: Cálculo bloqueado | B51: =IF(M12_c_Gate="NO","Corrija los datos imposibles (sexo, edad, peso o estatura) antes de interpretar.","—") -> —
A52: Método reportado sin datos | B52: =IF(ISNUMBER(M12_c_GrRep),"—","El método elegido no tiene datos suficientes; elija otro o complete los campos.") -> —
A53: Dispersión entre métodos | B53: =IF(AND(ISNUMBER(M12_c_ampl),M12_c_ampl>M12_DISP_MAX),"Los tres métodos discrepan más que el umbral: interprete con cautela y prefiera medición de referencia.","—") -> Los tres métodos discrepan más que el umbral: interprete con cautela y prefiera medición de referencia.
A54: Pliegue fuera de rango habitual | B54: =IF(OR(AND(ISNUMBER(M12_in_PliBi),M12_in_PliBi>M12_PLI_MAX),AND(ISNUMBER(M12_in_PliTri),M12_in_PliTri>M12_PLI_MAX),AND(ISNUMBER(M12_in_PliSub),M12_in_PliSub>M12_PLI_MAX),AND(ISNUMBER(M12_in_PliSupra),M12_in_PliSupra>M12_PLI_MAX)),"Algún pliegue supera el máximo del catálogo: verifique la medición.","—") -> —
A55: % grasa fuera de rango plausible | B55: =IF(AND(ISNUMBER(M12_c_GrRep),OR(M12_c_GrRep<M12_GRASA_MIN,M12_c_GrRep>M12_GRASA_MAX)),"El % de grasa reportado está fuera del rango fisiológico plausible.","—") -> —
A56: Circunferencias faltantes (método 2) | B56: =IF(ISNUMBER(M12_c_GrNavy),"—","El método de circunferencias no se pudo calcular por datos faltantes.") -> —
A57: Grasa esencial baja | B57: =IF(AND(ISNUMBER(M12_c_GrRep),M12_c_GrRep<IF(M12_in_Sexo="Hombre",0.05,0.13)),"El % de grasa está por debajo del nivel de grasa esencial de referencia.","—") -> —
A58: Recordatorio metodológico | B58: ="Exactitud matemática ≠ validación clínica. Son estimaciones poblacionales, no mediciones de referencia (DEXA, pesaje hidrostático)." -> Exactitud matemática ≠ validación clínica. Son estimaciones poblacionales, no mediciones de referencia (DEXA, pesaje hidrostático).

Sheet M12_RESULTADOS
A1: NUTRIMETRÍA · NMX-12
A2: Informe de grasa y composición corporal
A3: =HYPERLINK("#M12_DATOS!A1","◀ DATOS") -> ◀ DATOS | B3: =HYPERLINK("#M12_CALCULOS!A1","◀ CALCULOS") -> ◀ CALCULOS | E3: =HYPERLINK("#M12_FUENTES!A1","▶ FUENTES") -> ▶ FUENTES
A4: IDENTIFICACIÓN
A6: Identificador | B6: =M12_in_ID -> NMX-2026-0028
A7: Fecha | B7: =M12_in_Fecha -> 46236
A8: Paciente | B8: =M12_in_Pac -> PER-0007
A9: Sexo · edad | B9: =M12_in_Sexo&" · "&IF(ISNUMBER(M12_in_Edad),M12_in_Edad&" años","(edad no válida)") -> Hombre · 34 años
A10: Peso · estatura | B10: =IF(ISNUMBER(M12_in_Peso),ROUND(M12_in_Peso,1)&" kg","(?)")&" · "&IF(ISNUMBER(M12_in_Est),ROUND(M12_in_Est,1)&" cm","(?)") -> 78,5 kg · 176 cm
A11: Método reportado | B11: =M12_in_Metodo -> 1 · Pliegues (Durnin–Womersley 1974)
A12: Estado del cálculo | B12: =IF(M12_c_Gate="SÍ","HABILITADO","BLOQUEADO — corrija los datos imposibles") -> HABILITADO
A13: Observaciones | B13: =IF(M12_in_Obs="","—",M12_in_Obs) -> 0
A14: % DE GRASA POR LOS TRES MÉTODOS
A16: Método | B16: % de grasa | C16: ¿Disponible? | D16: Fuente
A17: 1 · Pliegues (Durnin–Womersley → Siri/Brožek) | B17: =M12_c_GrPli -> 0.20873445 | C17: =IF(ISNUMBER(M12_c_GrPli),"Sí","No") -> Sí | D17: Durnin–Womersley 1974
A18: 2 · Circunferencias (US Navy) | B18: =M12_c_GrNavy -> 0.1676962 | C18: =IF(ISNUMBER(M12_c_GrNavy),"Sí","No") -> Sí | D18: Hodgdon–Beckett 1984
A19: 3 · IMC (Deurenberg) | B19: =M12_c_GrDeu -> 0.2203064 | C19: =IF(ISNUMBER(M12_c_GrDeu),"Sí","No") -> Sí | D19: Deurenberg 1991
A20: MÉTODO REPORTADO | B20: =M12_c_GrRep -> 0.20873445 | C20: =M12_in_Metodo -> 1 · Pliegues (Durnin–Womersley 1974)
A21: CONCORDANCIA ENTRE MÉTODOS
A23: Promedio | B23: =M12_c_prom -> 0.19891235
A24: Rango (máx − mín) | B24: =M12_c_rango -> 0.052610209
A25: Amplitud relativa | B25: =M12_c_ampl -> 0.26448941
A26: =M12_c_estado -> ATENCIÓN: los métodos discrepan más que el umbral configurado.
A27: COMPOSICIÓN CORPORAL (según el método reportado)
A29: % de grasa reportado | B29: =M12_c_GrRep -> 0.20873445
A30: Masa grasa (MG) | B30: =M12_c_MG -> 16.385654 | C30: kg
A31: Masa libre de grasa (MLG) | B31: =M12_c_MLG -> 62.114346 | C31: kg
A32: Índice de masa grasa (IMG) | B32: =M12_c_IMG -> 5.2897902 | C32: kg/m²
A33: Índice de masa libre de grasa (IMLG) | B33: =M12_c_IMLG -> 20.05241 | C33: kg/m²
A34: IMC | B34: =M12_c_IMC -> 25.3422 | C34: kg/m²
A35: Clasificación por IMC | B35: =M12_c_ClaseIMC -> Sobrepeso (OMS)
A36: Clasificación por % grasa (ACE, referencial) | B36: =M12_c_ClaseGrasa -> Aceptable
A37: DISTRIBUCIÓN Y RIESGO CARDIOMETABÓLICO
A39: Indicador | B39: Valor | C39: Clasificación | D39: Corte aplicado
A40: Circunferencia de cintura | B40: =IF(ISNUMBER(M12_in_Cintura),M12_in_Cintura,"ND") -> 85 | C40: =M12_c_RiesgoCint -> Sin riesgo aumentado | E40: =IF(M12_in_Sexo="Hombre","≥102 cm (H)","≥88 cm (M)") -> ≥102 cm (H)
A41: Índice cintura/cadera (ICC) | B41: =M12_c_ICC -> 0.86734694 | C41: =M12_c_RiesgoICC -> Sin riesgo aumentado | E41: =IF(M12_in_Sexo="Hombre","≥0,90 (H)","≥0,85 (M)") -> ≥0,90 (H)
A42: Índice cintura/estatura (ICE) | B42: =M12_c_ICE -> 0.48295455 | C42: =M12_c_RiesgoICE -> Sin riesgo aumentado | E42: ≥0,50
A43: DATOS DE APOYO PARA LOS GRÁFICOS
A45: Método | B45: % de grasa
A46: 1 · Pliegues | B46: =IF(ISNUMBER(M12_c_GrPli),M12_c_GrPli,0) -> 0.20873445
A47: 2 · Circunferencias | B47: =IF(ISNUMBER(M12_c_GrNavy),M12_c_GrNavy,0) -> 0.1676962
A48: 3 · IMC | B48: =IF(ISNUMBER(M12_c_GrDeu),M12_c_GrDeu,0) -> 0.2203064
A50: Componente | B50: kg
A51: Masa grasa | B51: =IF(ISNUMBER(M12_c_MG),M12_c_MG,0) -> 16.385654
A52: Masa libre de grasa | B52: =IF(ISNUMBER(M12_c_MLG),M12_c_MLG,0) -> 62.114346
A53: ADVERTENCIAS
A55: Cálculo bloqueado | B55: =M12_CALCULOS!B51 -> —
A56: Método reportado sin datos | B56: =M12_CALCULOS!B52 -> —
A57: Dispersión entre métodos | B57: =M12_CALCULOS!B53 -> Los tres métodos discrepan más que el umbral: interprete con cautela y prefiera medición de referencia.
A58: Pliegue fuera de rango | B58: =M12_CALCULOS!B54 -> —
A59: % grasa no plausible | B59: =M12_CALCULOS!B55 -> —
A60: Circunferencias faltantes | B60: =M12_CALCULOS!B56 -> —
A61: Grasa esencial baja | B61: =M12_CALCULOS!B57 -> —
A62: EXACTITUD MATEMÁTICA ≠ VALIDACIÓN CLÍNICA. Los coeficientes se cotejaron contra las fuentes de la hoja FUENTES, pero este archivo NO está validado clínicamente. Los métodos antropométricos ESTIMAN la composición corporal; la referencia son técnicas como DEXA o pesaje hidrostático. No constituyen diagnóstico ni prescripción.

Sheet M12_FUENTES
A1: NUTRIMETRÍA · NMX-12
A2: Trazabilidad · anclaje regional a Chile (INTA U. de Chile y MINSAL)
A3: LOCALIZACIÓN: por indicación, se ELIMINARON las fuentes de USDA (FoodData Central) y del Instituto Nacional de Salud del Perú. El anclaje poblacional y de clasificación es EXCLUSIVAMENTE chileno: INTA (Universidad de Chile) y MINSAL, con la OMS como referencia adoptada por el propio MINSAL. NIVEL A = documento oficial o publicación primaria · B = resumen primario / corroboración por pares · C = fuente secundaria. EXACTITUD ≠ VALIDACIÓN CLÍNICA.
A4: =HYPERLINK("#M12_INICIO!A1","◀ INICIO") -> ◀ INICIO | B4: =HYPERLINK("#M12_DATOS!A1","◀ DATOS") -> ◀ DATOS | C4: =HYPERLINK("#M12_CALCULOS!A1","◀ CALCULOS") -> ◀ CALCULOS
A5: Ecuación o dato | B5: Autor u organización | C5: Año | D5: Población de derivación | E5: Fórmula / valor | F5: Unidades | G5: Limitaciones | H5: DOI o fuente | I5: Fecha cotejo | J5: Licencia / condiciones | K5: Nivel
A6: Densidad por 4 pliegues | B6: Durnin JVGA, Womersley J — Br J Nutr 32(1):77-97 | C6: 1974 | D6: 481 personas (209 H, 272 M), 16–72 años; pesaje hidrostático | E6: D = c − m·log10(Σ bíceps+tríceps+subescapular+suprailíaco) | F6: g/mL; pliegues mm | G6: Muestra británica; ecuación general. Depende de la técnica del evaluador. | H6: 10.1079/bjn19740060 | I6: 2026-07-16 | J6: Artículo con derechos de autor; solo se usan los coeficientes (hecho no protegible). | K6: B
A7: Densidad → % grasa · Siri | B7: Siri WE — en Techniques for Measuring Body Composition (NAS-NRC) | C7: 1961 | D7: Modelo de dos compartimentos (grasa / libre de grasa) | E7: %grasa = 495/D − 450 | F7: % ; D g/mL | G7: Asume densidades fijas de los compartimentos; menos válida en extremos de composición. | H7: Siri 1961 (NAS-NRC) | I7: 2026-07-16 | J7: Obra clásica; solo se usa la ecuación. | K7: B
A8: Densidad → % grasa · Brožek | B8: Brožek J et al. — Ann N Y Acad Sci 110:113-140 | C8: 1963 | D8: Modelo del cuerpo de referencia | E8: %grasa = 457/D − 414 | F8: % ; D g/mL | G8: Alternativa a Siri; difiere levemente en los extremos. | H8: 10.1111/j.1749-6632.1963.tb17079.x | I8: 2026-07-16 | J8: Artículo con derechos de autor; solo se usa la ecuación. | K8: B
A9: % grasa por circunferencias | B9: Hodgdon JA, Beckett MB — Naval Health Research Center (US Navy) | C9: 1984 | D9: Personal de la Marina de EE. UU. | E9: H: 495/(1,0324−0,19077·log10(cint−cuello)+0,15456·log10(talla))−450 · M usa (cint+cadera−cuello) | F9: cm; % | G9: Derivada en población militar; sensible a la técnica de medición. | H9: NHRC Reports 84-11 / 84-29 | I9: 2026-07-16 | J9: Informe técnico del gobierno de EE. UU.: dominio público. | K9: B
A10: % grasa por IMC · Deurenberg | B10: Deurenberg P, Weststrate JA, Seidell JC — Br J Nutr 65(2):105-114 | C10: 1991 | D10: 1229 sujetos, amplio rango de edad e IMC | E10: %grasa = 1,20·IMC + 0,23·edad − 10,8·sexo − 5,4 (H=1, M=0) | F10: % ; IMC kg/m² | G10: Estimación poblacional; menos precisa en el individuo, deportistas y ancianos. | H10: 10.1079/bjn19910073 | I10: 2026-07-16 | J10: Artículo con derechos de autor; solo se usa la ecuación. Citada en material técnico chileno (MINSAL). | K10: A
A11: Modelo de composición · MG y MLG | B11: INTA, Universidad de Chile — Salazar G. et al. (Lab. de Metabolismo Energético e Isótopos Estables) | C11: 2003 | D11: Población chilena; antropometría contrastada con dilución de deuterio | E11: Modelo de dos compartimentos: peso = MG + MLG; MG = %grasa·peso | F11: kg | G11: El anclaje regional del marco composicional es chileno; la exactitud sigue dependiendo del método antropométrico. | H11: Rev Chil Pediatr 2003;74:37-45 (INTA U. de Chile) | I11: 2026-07-16 | J11: Artículo con derechos de autor; se usa el marco conceptual (hecho no protegible). Fuente institucional del INTA. | K11: B
A12: Clasificación por IMC · adulto y adulto mayor | B12: MINSAL (Chile) — Norma técnica de evaluación nutricional | C12: vigente | D12: Adopta cortes OMS para el adulto; cortes propios para ≥65 años | E12: Adulto (OMS): 18,5 / 25 / 30 / 35 / 40 · Adulto mayor (MINSAL): 23 / 28 / 32 | F12: kg/m² | G12: Cortes poblacionales; el IMC no distingue masa grasa de masa magra. | H12: MINSAL · Norma de evaluación nutricional | I12: 2026-07-16 | J12: Documento oficial del Estado de Chile: acceso público. | K12: A
A13: Circunferencia de cintura e índices de distribución | B13: MINSAL (Chile) / OMS — cortes de riesgo cardiometabólico | C13: vigente | D13: Consensos OMS/NIH adoptados por el MINSAL | E13: Cintura: H≥102, M≥88 cm · ICC: H≥0,90, M≥0,85 · ICE ≥0,50 | F13: cm; adimensional | G13: Cortes de tamizaje, no diagnósticos por sí solos. | H13: MINSAL / OMS (Waist circumference and WHR, 2008) | I13: 2026-07-16 | J13: Documentos oficiales de acceso público. | K13: A
A14: Rangos referenciales de % de grasa | B14: American Council on Exercise (ACE) | C14: referencial | D14: Rangos divulgados por categoría y sexo | E14: H: esencial 2–5, atlético 6–13, en forma 14–17, aceptable 18–24, obesidad ≥25 % · M: +8 aprox. | F14: % | G14: REFERENCIALES, NO son un estándar chileno oficial. Para diagnóstico priman IMC y cintura (MINSAL). | H14: ACE (rangos divulgados) | I14: 2026-07-16 | J14: Rangos de uso general; se citan como referencia, no como norma. | K14: C
A16: PENDIENTES DE VERIFICACIÓN PRIMARIA (nivel B): Durnin–Womersley, Siri, Brožek y US Navy disponen de resumen primario o corroboración por pares, pero no se inspeccionó cada PDF completo. La versión y el año exactos de la norma MINSAL vigente deben confirmarse en el sitio oficial del Ministerio de Salud antes de un uso formal.

Sheet M12_PRUEBAS
A1: NUTRIMETRÍA · NMX-12
A2: Banco de verificación · el recuento se calcula solo en el RESUMEN
A3: REGLA: el valor ESPERADO nunca lee el CONFIG que usa el motor. O es un literal calculado a partir de la fuente publicada, o se reconstruye con los coeficientes publicados escritos de forma explícita. Si alguien corrompe un coeficiente de CONFIG, estas pruebas FALLAN.
A4: =HYPERLINK("#M12_INICIO!A1","◀ INICIO") -> ◀ INICIO
A6: BLOQUE A · EXACTITUD PLIEGUES → DENSIDAD → % GRASA (Durnin–Womersley + Siri/Brožek)
A7: ID | B7: Descripción | C7: Sexo | D7: Edad | E7: c | F7: m | G7: Σ4 | H7: Conv. | I7: Obtenido | J7: Esperado | K7: Dif. | L7: Estado
A8: A01 | B8: H 30–40 · Siri | C8: Hombre | D8: 34 | E8: 1.1422 | F8: 0.0544 | G8: 46 | H8: Siri | I8: =IF(H8="Brožek",(457/(E8-F8*LOG10(G8))-414)/100,(495/(E8-F8*LOG10(G8))-450)/100) -> 0.20645966 | J8: 0.20646 | K8: =I8-J8 -> -3.3904329e-07 | L8: =IF(ABS(K8)<=M12_TOL_FRAC,"APROBADO","FALLIDO") -> APROBADO
A9: A02 | B9: M 20–30 · Siri | C9: Mujer | D9: 25 | E9: 1.1599 | F9: 0.0717 | G9: 60 | H9: Siri | I9: =IF(H9="Brožek",(457/(E9-F9*LOG10(G9))-414)/100,(495/(E9-F9*LOG10(G9))-450)/100) -> 0.29462279 | J9: 0.294623 | K9: =I9-J9 -> -2.088517e-07 | L9: =IF(ABS(K9)<=M12_TOL_FRAC,"APROBADO","FALLIDO") -> APROBADO
A10: A03 | B10: H 20–30 · Siri | C10: Hombre | D10: 22 | E10: 1.1631 | F10: 0.0632 | G10: 40 | H10: Siri | I10: =IF(H10="Brožek",(457/(E10-F10*LOG10(G10))-414)/100,(495/(E10-F10*LOG10(G10))-450)/100) -> 0.16167622 | J10: 0.161676 | K10: =I10-J10 -> 2.1838009e-07 | L10: =IF(ABS(K10)<=M12_TOL_FRAC,"APROBADO","FALLIDO") -> APROBADO
A11: A04 | B11: M 50+ · Siri | C11: Mujer | D11: 55 | E11: 1.1339 | F11: 0.0645 | G11: 70 | H11: Siri | I11: =IF(H11="Brožek",(457/(E11-F11*LOG10(G11))-414)/100,(495/(E11-F11*LOG10(G11))-450)/100) -> 0.37737022 | J11: 0.37737 | K11: =I11-J11 -> 2.1959879e-07 | L11: =IF(ABS(K11)<=M12_TOL_FRAC,"APROBADO","FALLIDO") -> APROBADO
A12: A05 | B12: H 40–50 · Brožek | C12: Hombre | D12: 45 | E12: 1.162 | F12: 0.07 | G12: 55 | H12: Brožek | I12: =IF(H12="Brožek",(457/(E12-F12*LOG10(G12))-414)/100,(495/(E12-F12*LOG10(G12))-450)/100) -> 0.25349312 | J12: 0.253493 | K12: =I12-J12 -> 1.1975181e-07 | L12: =IF(ABS(K12)<=M12_TOL_FRAC,"APROBADO","FALLIDO") -> APROBADO
A13: A06 | B13: M 30–40 · Brožek | C13: Mujer | D13: 34 | E13: 1.1423 | F13: 0.0632 | G13: 50 | H13: Brožek | I13: =IF(H13="Brožek",(457/(E13-F13*LOG10(G13))-414)/100,(495/(E13-F13*LOG10(G13))-450)/100) -> 0.27577851 | J13: 0.275779 | K13: =I13-J13 -> -4.8726203e-07 | L13: =IF(ABS(K13)<=M12_TOL_FRAC,"APROBADO","FALLIDO") -> APROBADO
A15: BLOQUE B · EXACTITUD % GRASA POR CIRCUNFERENCIAS (US Navy 1984)
A16: ID | B16: Descripción | C16: Sexo | D16: Cuello | E16: Cintura | F16: Cadera | G16: Estatura | H16: Obtenido | I16: Esperado | J16: Dif. | K16: Estado
A17: B01 | B17: Hombre típico | C17: Hombre | D17: 38 | E17: 88 | F17: 100 | G17: 176 | H17: =IF(C17="Hombre",(495/(1.0324-0.19077*LOG10(E17-D17)+0.15456*LOG10(G17))-450)/100,(495/(1.29579-0.35004*LOG10(E17+F17-D17)+0.221*LOG10(G17))-450)/100) -> 0.19036961 | I17: 0.19037 | J17: =H17-I17 -> -3.9194423e-07 | K17: =IF(ABS(J17)<=M12_TOL_FRAC,"APROBADO","FALLIDO") -> APROBADO
A18: B02 | B18: Hombre atlético | C18: Hombre | D18: 40 | E18: 82 | F18: 96 | G18: 180 | H18: =IF(C18="Hombre",(495/(1.0324-0.19077*LOG10(E18-D18)+0.15456*LOG10(G18))-450)/100,(495/(1.29579-0.35004*LOG10(E18+F18-D18)+0.221*LOG10(G18))-450)/100) -> 0.12052147 | I18: 0.120521 | J18: =H18-I18 -> 4.6662089e-07 | K18: =IF(ABS(J18)<=M12_TOL_FRAC,"APROBADO","FALLIDO") -> APROBADO
A19: B03 | B19: Hombre obesidad | C19: Hombre | D19: 44 | E19: 112 | F19: 110 | G19: 170 | H19: =IF(C19="Hombre",(495/(1.0324-0.19077*LOG10(E19-D19)+0.15456*LOG10(G19))-450)/100,(495/(1.29579-0.35004*LOG10(E19+F19-D19)+0.221*LOG10(G19))-450)/100) -> 0.31728167 | I19: 0.317282 | J19: =H19-I19 -> -3.2611922e-07 | K19: =IF(ABS(J19)<=M12_TOL_FRAC,"APROBADO","FALLIDO") -> APROBADO
A20: B04 | B20: Mujer típica | C20: Mujer | D20: 32 | E20: 74 | F20: 100 | G20: 164 | H20: =IF(C20="Hombre",(495/(1.0324-0.19077*LOG10(E20-D20)+0.15456*LOG10(G20))-450)/100,(495/(1.29579-0.35004*LOG10(E20+F20-D20)+0.221*LOG10(G20))-450)/100) -> 0.29705326 | I20: 0.297053 | J20: =H20-I20 -> 2.563539e-07 | K20: =IF(ABS(J20)<=M12_TOL_FRAC,"APROBADO","FALLIDO") -> APROBADO
A21: B05 | B21: Mujer atlética | C21: Mujer | D21: 30 | E21: 68 | F21: 92 | G21: 170 | H21: =IF(C21="Hombre",(495/(1.0324-0.19077*LOG10(E21-D21)+0.15456*LOG10(G21))-450)/100,(495/(1.29579-0.35004*LOG10(E21+F21-D21)+0.221*LOG10(G21))-450)/100) -> 0.21988448 | I21: 0.219884 | J21: =H21-I21 -> 4.8359026e-07 | K21: =IF(ABS(J21)<=M12_TOL_FRAC,"APROBADO","FALLIDO") -> APROBADO
A22: B06 | B22: Mujer obesidad | C22: Mujer | D22: 36 | E22: 96 | F22: 118 | G22: 160 | H22: =IF(C22="Hombre",(495/(1.0324-0.19077*LOG10(E22-D22)+0.15456*LOG10(G22))-450)/100,(495/(1.29579-0.35004*LOG10(E22+F22-D22)+0.221*LOG10(G22))-450)/100) -> 0.47405703 | I22: 0.474057 | J22: =H22-I22 -> 3.4013848e-08 | K22: =IF(ABS(J22)<=M12_TOL_FRAC,"APROBADO","FALLIDO") -> APROBADO
A24: BLOQUE C · EXACTITUD % GRASA POR IMC (Deurenberg 1991)
A25: ID | B25: Descripción | C25: Sexo | D25: IMC | E25: Edad | F25: Obtenido | G25: Esperado | H25: Dif. | I25: Estado
A26: C01 | B26: Hombre normal | C26: Hombre | D26: 25.3422 | E26: 34 | F26: =(1.2*D26+0.23*E26-10.8*IF(C26="Hombre",1,0)-5.4)/100 -> 0.2203064 | G26: 0.220306 | H26: =F26-G26 -> 4e-07 | I26: =IF(ABS(H26)<=M12_TOL_FRAC,"APROBADO","FALLIDO") -> APROBADO
A27: C02 | B27: Mujer normal | C27: Mujer | D27: 23 | E27: 45 | F27: =(1.2*D27+0.23*E27-10.8*IF(C27="Hombre",1,0)-5.4)/100 -> 0.3255 | G27: 0.3255 | H27: =F27-G27 -> 0 | I27: =IF(ABS(H27)<=M12_TOL_FRAC,"APROBADO","FALLIDO") -> APROBADO
A28: C03 | B28: Hombre obesidad | C28: Hombre | D28: 33 | E28: 55 | F28: =(1.2*D28+0.23*E28-10.8*IF(C28="Hombre",1,0)-5.4)/100 -> 0.3605 | G28: 0.3605 | H28: =F28-G28 -> 0 | I28: =IF(ABS(H28)<=M12_TOL_FRAC,"APROBADO","FALLIDO") -> APROBADO
A29: C04 | B29: Mujer obesidad | C29: Mujer | D29: 31 | E29: 60 | F29: =(1.2*D29+0.23*E29-10.8*IF(C29="Hombre",1,0)-5.4)/100 -> 0.456 | G29: 0.456 | H29: =F29-G29 -> 0 | I29: =IF(ABS(H29)<=M12_TOL_FRAC,"APROBADO","FALLIDO") -> APROBADO
A30: C05 | B30: Hombre joven | C30: Hombre | D30: 22 | E30: 20 | F30: =(1.2*D30+0.23*E30-10.8*IF(C30="Hombre",1,0)-5.4)/100 -> 0.148 | G30: 0.148 | H30: =F30-G30 -> 0 | I30: =IF(ABS(H30)<=M12_TOL_FRAC,"APROBADO","FALLIDO") -> APROBADO
A31: C06 | B31: Mujer mayor | C31: Mujer | D31: 27.5 | E31: 70 | F31: =(1.2*D31+0.23*E31-10.8*IF(C31="Hombre",1,0)-5.4)/100 -> 0.437 | G31: 0.437 | H31: =F31-G31 -> 0 | I31: =IF(ABS(H31)<=M12_TOL_FRAC,"APROBADO","FALLIDO") -> APROBADO
A33: BLOQUE D · COMPOSICIÓN CORPORAL (MG, MLG, IMLG) · tolerancia ±0,05 kg / kg·m⁻²
A34: ID | B34: % grasa | C34: Peso | D34: Talla m | E34: MG obt | F34: MG esp | G34: Est.MG | H34: IMLG obt | I34: IMLG esp | J34: Est.IMLG
A35: D01 | B35: 0.20646 | C35: 78.5 | D35: 1.76 | E35: =B35*C35 -> 16.20711 | F35: 16.2071 | G35: =IF(ABS(E35-F35)<=M12_TOL_KG,"APROBADO","FALLIDO") -> APROBADO | H35: =(C35-B35*C35)/D35^2 -> 20.11005 | I35: 20.11 | J35: =IF(ABS(H35-I35)<=M12_TOL_KG,"APROBADO","FALLIDO") -> APROBADO
A36: D02 | B36: 0.3 | C36: 60 | D36: 1.6 | E36: =B36*C36 -> 18 | F36: 18 | G36: =IF(ABS(E36-F36)<=M12_TOL_KG,"APROBADO","FALLIDO") -> APROBADO | H36: =(C36-B36*C36)/D36^2 -> 16.40625 | I36: 16.4062 | J36: =IF(ABS(H36-I36)<=M12_TOL_KG,"APROBADO","FALLIDO") -> APROBADO
A37: D03 | B37: 0.12 | C37: 90 | D37: 1.85 | E37: =B37*C37 -> 10.8 | F37: 10.8 | G37: =IF(ABS(E37-F37)<=M12_TOL_KG,"APROBADO","FALLIDO") -> APROBADO | H37: =(C37-B37*C37)/D37^2 -> 23.140979 | I37: 23.141 | J37: =IF(ABS(H37-I37)<=M12_TOL_KG,"APROBADO","FALLIDO") -> APROBADO
A38: D04 | B38: 0.25 | C38: 72 | D38: 1.7 | E38: =B38*C38 -> 18 | F38: 18 | G38: =IF(ABS(E38-F38)<=M12_TOL_KG,"APROBADO","FALLIDO") -> APROBADO | H38: =(C38-B38*C38)/D38^2 -> 18.685121 | I38: 18.6851 | J38: =IF(ABS(H38-I38)<=M12_TOL_KG,"APROBADO","FALLIDO") -> APROBADO
A40: BLOQUE E · ÍNDICES DE DISTRIBUCIÓN Y CLASIFICACIÓN
A41: ID | B41: Escenario | C41: Entrada | D41: Comportamiento esperado | E41: Comportamiento obtenido | F41: Estado
A42: E01 | B42: ICC hombre bajo umbral (0,88) | C42: 88/100 | D42: Sin riesgo aumentado | E42: =IF(88/100>=0.9,"Riesgo aumentado","Sin riesgo aumentado") -> Sin riesgo aumentado | F42: =IF(E42=D42,"APROBADO","FALLIDO") -> APROBADO
A43: E02 | B43: Cintura hombre en riesgo (105) | C43: 105 | D43: Riesgo aumentado | E43: =IF(105>=102,"Riesgo aumentado","Sin riesgo aumentado") -> Riesgo aumentado | F43: =IF(E43=D43,"APROBADO","FALLIDO") -> APROBADO
A44: E03 | B44: ICE en el umbral (0,50) | C44: 88/176 | D44: Riesgo aumentado | E44: =IF(88/176>=0.5,"Riesgo aumentado","Sin riesgo aumentado") -> Riesgo aumentado | F44: =IF(E44=D44,"APROBADO","FALLIDO") -> APROBADO
A45: E04 | B45: IMC 25,34 adulto → OMS | C45: 25.3422 | D45: Sobrepeso (OMS) | E45: =IF(25.3422<18.5,"Bajo peso (OMS)",IF(25.3422<25,"Normal (OMS)",IF(25.3422<30,"Sobrepeso (OMS)","Obesidad (OMS)"))) -> Sobrepeso (OMS) | F45: =IF(E45=D45,"APROBADO","FALLIDO") -> APROBADO
A46: E05 | B46: IMC 24 adulto → OMS | C46: 24 | D46: Normal (OMS) | E46: =IF(24<18.5,"Bajo peso (OMS)",IF(24<25,"Normal (OMS)",IF(24<30,"Sobrepeso (OMS)","Obesidad (OMS)"))) -> Normal (OMS) | F46: =IF(E46=D46,"APROBADO","FALLIDO") -> APROBADO
A47: E06 | B47: IMC 24 · 70 años → MINSAL AM | C47: 24 | D47: Normal (MINSAL AM) | E47: =IF(24<23,"Bajo peso (MINSAL AM)",IF(24<28,"Normal (MINSAL AM)",IF(24<32,"Sobrepeso (MINSAL AM)","Obesidad (MINSAL AM)"))) -> Normal (MINSAL AM) | F47: =IF(E47=D47,"APROBADO","FALLIDO") -> APROBADO
A48: E07 | B48: IMC 33 · 70 años → MINSAL AM | C48: 33 | D48: Obesidad (MINSAL AM) | E48: =IF(33<23,"Bajo peso (MINSAL AM)",IF(33<28,"Normal (MINSAL AM)",IF(33<32,"Sobrepeso (MINSAL AM)","Obesidad (MINSAL AM)"))) -> Obesidad (MINSAL AM) | F48: =IF(E48=D48,"APROBADO","FALLIDO") -> APROBADO
A50: BLOQUE F · VALIDACIONES: vacíos, texto, negativos, imposibles
A51: ID | B51: Escenario | C51: Entrada | D51: Comportamiento esperado | E51: Comportamiento obtenido | F51: Estado
A52: F01 | B52: Edad menor de edad (15) | C52: 15 | D52: ERROR: edad fuera del alcance adulto | E52: =IF(NOT(ISNUMBER(15)),"ERROR: edad no numérica",IF(AND(15>=18,15<=120),"OK","ERROR: edad fuera del alcance adulto")) -> ERROR: edad fuera del alcance adulto | F52: =IF(E52=D52,"APROBADO","FALLIDO") -> APROBADO
A53: F02 | B53: Edad textual | C53: quince | D53: ERROR: edad no numérica | E53: =IF(NOT(ISNUMBER("quince")),"ERROR: edad no numérica",IF(AND("quince">=18,"quince"<=120),"OK","ERROR: edad fuera del alcance adulto")) -> ERROR: edad no numérica | F53: =IF(E53=D53,"APROBADO","FALLIDO") -> APROBADO
A54: F03 | B54: Peso negativo (−5) | C54: -5 | D54: ERROR: peso fuera de rango | E54: =IF(NOT(ISNUMBER(-5)),"ERROR: peso no numérico",IF(AND(-5>=25,-5<=350),"OK","ERROR: peso fuera de rango")) -> ERROR: peso fuera de rango | F54: =IF(E54=D54,"APROBADO","FALLIDO") -> APROBADO
A55: F04 | B55: Estatura imposible (400) | C55: 400 | D55: ERROR: estatura fuera de rango | E55: =IF(NOT(ISNUMBER(400)),"ERROR: estatura no numérico",IF(AND(400>=120,400<=230),"OK","ERROR: estatura fuera de rango")) -> ERROR: estatura fuera de rango | F55: =IF(E55=D55,"APROBADO","FALLIDO") -> APROBADO
A56: F05 | B56: Pliegue cero | C56: 0 | D56: ERROR: pliegue fuera de rango | E56: =IF(AND(ISNUMBER(0),0>=1,0<=80),"OK","ERROR: pliegue fuera de rango") -> ERROR: pliegue fuera de rango | F56: =IF(E56=D56,"APROBADO","FALLIDO") -> APROBADO
A57: F06 | B57: Cintura ≤ cuello (Navy) | C57: cint≤cuello | D57: ND: cintura≤cuello | E57: =IF((38-40)>0,"OK","ND: cintura≤cuello") -> ND: cintura≤cuello | F57: =IF(E57=D57,"APROBADO","FALLIDO") -> APROBADO
A58: F07 | B58: % grasa 90 % | C58: 0.9 | D58: ERROR: % de grasa fuera del rango plausible | E58: =IF(AND(ISNUMBER(0.9),0.9>=0.03,0.9<=0.75),"OK","ERROR: % de grasa fuera del rango plausible") -> ERROR: % de grasa fuera del rango plausible | F58: =IF(E58=D58,"APROBADO","FALLIDO") -> APROBADO
A59: F08 | B59: % grasa negativo | C59: -0.1 | D59: ERROR: % de grasa fuera del rango plausible | E59: =IF(AND(ISNUMBER(-0.1),-0.1>=0.03,-0.1<=0.75),"OK","ERROR: % de grasa fuera del rango plausible") -> ERROR: % de grasa fuera del rango plausible | F59: =IF(E59=D59,"APROBADO","FALLIDO") -> APROBADO
A61: BLOQUE G · INTEGRIDAD: cero errores de Excel
A62: ID | B62: Rango verificado | C62: Nº errores | D62: Esperado | E62: Estado
A63: G01 | B63: CALCULOS!B7:B58 | C63: =SUMPRODUCT(--ISERROR(M12_CALCULOS!B7:B58)) -> 0 | D63: 0 | E63: =IF(C63=D63,"APROBADO","FALLIDO") -> APROBADO
A64: G02 | B64: RESULTADOS!B6:F60 | C64: =SUMPRODUCT(--ISERROR(M12_RESULTADOS!B6:F60)) -> 0 | D64: 0 | E64: =IF(C64=D64,"APROBADO","FALLIDO") -> APROBADO
A65: G03 | B65: CONFIG!B8:B54 | C65: =SUMPRODUCT(--ISERROR(M12_CONFIG!B8:B54)) -> 0 | D65: 0 | E65: =IF(C65=D65,"APROBADO","FALLIDO") -> APROBADO
A67: BLOQUE H · COTEJO CON EL MOTOR (caso vivo de DATOS · reconstrucción literal)
A68: ID | B68: Verificación | C68: Obtenido (motor) | D68: Esperado (literal desde DATOS) | E68: Dif. | F68: Estado
A69: H01 | B69: % grasa pliegues (Hombre 30–40, Siri) | C69: =M12_c_GrPli -> 0.20873445 | D69: =(495/(1.1422-0.0544*LOG10(M12_in_PliBi+M12_in_PliTri+M12_in_PliSub+M12_in_PliSupra))-450)/100 -> 0.20873445 | E69: =C69-D69 -> 0 | F69: =IF(ABS(E69)<=M12_TOL_FRAC,"APROBADO","FALLIDO") -> APROBADO
A70: H02 | B70: % grasa circunferencias (US Navy H) | C70: =M12_c_GrNavy -> 0.1676962 | D70: =(495/(1.0324-0.19077*LOG10(M12_in_Cintura-M12_in_Cuello)+0.15456*LOG10(M12_in_Est))-450)/100 -> 0.1676962 | E70: =C70-D70 -> 0 | F70: =IF(ABS(E70)<=M12_TOL_FRAC,"APROBADO","FALLIDO") -> APROBADO
A71: H03 | B71: % grasa IMC (Deurenberg H) | C71: =M12_c_GrDeu -> 0.2203064 | D71: =(1.2*(M12_in_Peso/(M12_in_Est/100)^2)+0.23*M12_in_Edad-10.8*1-5.4)/100 -> 0.2203064 | E71: =C71-D71 -> 0 | F71: =IF(ABS(E71)<=M12_TOL_FRAC,"APROBADO","FALLIDO") -> APROBADO
A72: H04 | B72: Masa grasa = %grasa reportado × peso | C72: =M12_c_MG -> 16.385654 | D72: =((495/(1.1422-0.0544*LOG10(M12_in_PliBi+M12_in_PliTri+M12_in_PliSub+M12_in_PliSupra))-450)/100)*M12_in_Peso -> 16.385654 | E72: =C72-D72 -> 0 | F72: =IF(ABS(E72)<=M12_TOL_KG,"APROBADO","FALLIDO") -> APROBADO
A75: RESUMEN DEL BANCO DE PRUEBAS
A76: Casos totales | C76: 48
A77: Aprobados | C77: =IF(L8="APROBADO",1,0)+IF(L9="APROBADO",1,0)+IF(L10="APROBADO",1,0)+IF(L11="APROBADO",1,0)+IF(L12="APROBADO",1,0)+IF(L13="APROBADO",1,0)+IF(K17="APROBADO",1,0)+IF(K18="APROBADO",1,0)+IF(K19="APROBADO",1,0)+IF(K20="APROBADO",1,0)+IF(K21="APROBADO",1,0)+IF(K22="APROBADO",1,0)+IF(I26="APROBADO",1,0)+IF(I27="APROBADO",1,0)+IF(I28="APROBADO",1,0)+IF(I29="APROBADO",1,0)+IF(I30="APROBADO",1,0)+IF(I31="APROBADO",1,0)+IF(G35="APROBADO",1,0)+IF(J35="APROBADO",1,0)+IF(G36="APROBADO",1,0)+IF(J36="APROBADO",1,0)+IF(G37="APROBADO",1,0)+IF(J37="APROBADO",1,0)+IF(G38="APROBADO",1,0)+IF(J38="APROBADO",1,0)+IF(F42="APROBADO",1,0)+IF(F43="APROBADO",1,0)+IF(F44="APROBADO",1,0)+IF(F45="APROBADO",1,0)+IF(F46="APROBADO",1,0)+IF(F47="APROBADO",1,0)+IF(F48="APROBADO",1,0)+IF(F52="APROBADO",1,0)+IF(F53="APROBADO",1,0)+IF(F54="APROBADO",1,0)+IF(F55="APROBADO",1,0)+IF(F56="APROBADO",1,0)+IF(F57="APROBADO",1,0)+IF(F58="APROBADO",1,0)+IF(F59="APROBADO",1,0)+IF(E63="APROBADO",1,0)+IF(E64="APROBADO",1,0)+IF(E65="APROBADO",1,0)+IF(F69="APROBADO",1,0)+IF(F70="APROBADO",1,0)+IF(F71="APROBADO",1,0)+IF(F72="APROBADO",1,0) -> 48
A78: Fallidos | C78: =48-C77 -> 0
A79: ESTADO GLOBAL | B79: =IF(C77=48,"TODAS LAS PRUEBAS APROBADAS","HAY PRUEBAS FALLIDAS — REVISAR") -> TODAS LAS PRUEBAS APROBADAS

Sheet M12_CONFIG
A1: NUTRIMETRÍA · NMX-12
A2: Parámetros, coeficientes y catálogos · versión 1.0
A3: =HYPERLINK("#M12_INICIO!A1","◀ INICIO") -> ◀ INICIO
A4: Toda constante del modelo vive aquí; ninguna fórmula del libro contiene un coeficiente escrito a mano. Las celdas arena son editables. Cambiar un valor aquí propaga a todo el libro y hace FALLAR las pruebas que cotejan contra la fuente publicada.
A6: C1 · PARÁMETROS, LÍMITES Y COEFICIENTES
A7: Parámetro | B7: Valor | C7: Unidad | D7: Tipo | E7: Nota / fuente
A8: Idioma | B8: Español (es-CL) | C8: — | D8: — | E8: Interfaz
A9: Versión de las fuentes | B9: 2026-07 · v1.0 | C9: — | D9: — | E9: Ver hoja FUENTES
A10: Edad mínima (adulto) | B10: 18 | C10: años | D10: IMPOSIBLE | E10: Alcance del producto: solo adultos
A11: Edad máxima plausible | B11: 120 | C11: años | D11: IMPOSIBLE | E11: Límite operativo
A12: Peso mínimo posible | B12: 25 | C12: kg | D12: IMPOSIBLE | E12: Bajo este valor se considera imposible en un adulto
A13: Peso máximo posible | B13: 350 | C13: kg | D13: IMPOSIBLE | E13: Límite operativo
A14: Estatura mínima posible | B14: 120 | C14: cm | D14: IMPOSIBLE | E14: Límite operativo
A15: Estatura máxima posible | B15: 230 | C15: cm | D15: IMPOSIBLE | E15: Límite operativo
A16: Pliegue mínimo por sitio | B16: 1 | C16: mm | D16: IMPOSIBLE | E16: Guarda de cada pliegue
A17: Pliegue máximo por sitio | B17: 80 | C17: mm | D17: IMPOSIBLE | E17: Guarda de cada pliegue
A18: Cuello mínimo | B18: 20 | C18: cm | D18: IMPOSIBLE | E18: Guarda del método de circunferencias
A19: Cuello máximo | B19: 70 | C19: cm | D19: IMPOSIBLE | E19: Guarda del método de circunferencias
A20: Cintura mínima | B20: 40 | C20: cm | D20: IMPOSIBLE | E20: Guarda de circunferencia
A21: Cintura máxima | B21: 200 | C21: cm | D21: IMPOSIBLE | E21: Guarda de circunferencia
... A56: Índice cintura/estatura · riesgo | B56: 0.5 | C56: — | D56: Corte | E56: Umbral general ≥0,5
A58: C2 · SEXOS
A59: Valor | B59: Nota
A60: Hombre | B60: Ecuaciones derivadas en varones
A61: Mujer | B61: Ecuaciones derivadas en mujeres
A63: C3 · MÉTODO DE % DE GRASA A REPORTAR
A64: Método (lista) | B64: Variables indispensables
A65: 1 · Pliegues (Durnin–Womersley 1974) | B65: 4 pliegues, sexo, edad
A66: 2 · Circunferencias (US Navy 1984) | B66: cuello, cintura, estatura (y cadera en mujeres)
A67: 3 · IMC (Deurenberg 1991) | B67: peso, estatura, edad, sexo
A69: C4 · CONVERSIÓN DE DENSIDAD A % DE GRASA (solo método de pliegues)
A70: Fórmula (lista) | B70: Expresión
A71: Siri (1961) | B71: %grasa = 495/D − 450
A72: Brožek (1963) | B72: %grasa = 457/D − 414
A74: C5 · LISTA SÍ / NO
A75: Sí
A76: No
A78: C6 · DURNIN–WOMERSLEY (1974) · densidad = c − m·log10(Σ4 pliegues) · por sexo y banda etaria
A79: Sexo | B79: Edad desde (≥) | C79: Edad hasta (<) | D79: c | E79: m
A80: Hombre | B80: 17 | C80: 20 | D80: 1.162 | E80: 0.063
A81: Hombre | B81: 20 | C81: 30 | D81: 1.1631 | E81: 0.0632
A82: Hombre | B82: 30 | C82: 40 | D82: 1.1422 | E82: 0.0544
A83: Hombre | B83: 40 | C83: 50 | D83: 1.162 | E83: 0.07
A84: Hombre | B84: 50 | C84: 200 | D84: 1.1715 | E84: 0.0779
A85: Mujer | B85: 16 | C85: 20 | D85: 1.1549 | E85: 0.0678
A86: Mujer | B86: 20 | C86: 30 | D86: 1.1599 | E86: 0.0717
A87: Mujer | B87: 30 | C87: 40 | D87: 1.1423 | E87: 0.0632
A88: Mujer | B88: 40 | C88: 50 | D88: 1.1333 | E88: 0.0612
A89: Mujer | B89: 50 | C89: 200 | D89: 1.1339 | E89: 0.0645
A91: Fuente: Durnin JVGA, Womersley J. Br J Nutr 1974;32(1):77-97. DOI 10.1079/bjn19740060. Los 4 pliegues son bíceps, tríceps, subescapular y suprailíaco (mm). Se usa log10 de la SUMA.
A93: C7 · % DE GRASA · RANGOS REFERENCIALES POR SEXO (ACE) · corte inferior de cada categoría
A94: Sexo | B94: Categoría | C94: Corte inferior (≥) | D94: Nota
A95: Hombre | B95: Grasa esencial | C95: 0.02 | D95: 2–5 %
A96: Hombre | B96: Atlético | C96: 0.06 | D96: 6–13 %
A97: Hombre | B97: En forma | C97: 0.14 | D97: 14–17 %
A98: Hombre | B98: Aceptable | C98: 0.18 | D98: 18–24 %
A99: Hombre | B99: Obesidad | C99: 0.25 | D99: ≥25 %
A100: Mujer | B100: Grasa esencial | C100: 0.1 | D100: 10–13 %
A101: Mujer | B101: Atlético | C101: 0.14 | D101: 14–20 %
A102: Mujer | B102: En forma | C102: 0.21 | D102: 21–24 %
A103: Mujer | B103: Aceptable | C103: 0.25 | D103: 25–31 %
A104: Mujer | B104: Obesidad | C104: 0.32 | D104: ≥32 %
A106: Rangos REFERENCIALES (American Council on Exercise). NO son un estándar chileno oficial. Para el diagnóstico nutricional, las normas del MINSAL priorizan el IMC y la circunferencia de cintura (ver FUENTES).

Sheet M12_CHANGELOG
A1: NUTRIMETRÍA · NMX-12
A2: Historial de versiones
A3: =HYPERLINK("#M12_INICIO!A1","◀ INICIO") -> ◀ INICIO
A5: Versión | B5: Fecha | C5: Cambio | D5: Motivo | E5: Responsable
A6: 1.0 | B6: 2026-07-14 | C6: Versión inicial. Tres métodos de % de grasa (Durnin–Womersley→Siri/Brožek, US Navy, Deurenberg), reconciliación con control de dispersión, composición (MG, MLG, IMG, IMLG) e índices de distribución (cintura, ICC, ICE). | D6: Primera entrega del producto 12. | E6: Equipo Nutrimetría
A7: 1.0 | B7: 2026-07-14 | C7: LOCALIZACIÓN A CHILE: se eliminaron las fuentes de USDA (FoodData Central) y del INS del Perú. El anclaje de clasificación queda en MINSAL y OMS; el marco de composición se referencia al INTA (Universidad de Chile). | D7: Indicación del titular; verificación de licencias. | E7: Equipo Nutrimetría
A8: 1.0 | B8: 2026-07-14 | C8: Banco de pruebas con casos de exactitud (las tres ecuaciones), composición, índices de distribución, validaciones e integridad, con valores esperados independientes del CONFIG. | D8: Control de calidad. | E8: Equipo Nutrimetría

Sheet M16_INICIO
A1: NUTRIMETRÍA · NMX-16
A2: Calculadora de somatotipo y somatocarta · versión 1.0
A4: Navegación — use las pestañas inferiores del libro
A5: =HYPERLINK("#M16_DATOS!A1","▶ DATOS") -> ▶ DATOS | B5: =HYPERLINK("#M16_MEDIDAS!A1","▶ MEDIDAS") -> ▶ MEDIDAS | D5: =HYPERLINK("#M16_CALCULOS!A1","▶ CALCULOS") -> ▶ CALCULOS | F5: =HYPERLINK("#M16_RESULTADOS!A1","▶ RESULTADOS") -> ▶ RESULTADOS | H5: =HYPERLINK("#M16_FUENTES!A1","▶ FUENTES") -> ▶ FUENTES | J5: =HYPERLINK("#M16_PRUEBAS!A1","▶ PRUEBAS") -> ▶ PRUEBAS | L5: =HYPERLINK("#M16_CONFIG!A1","▶ CONFIG") -> ▶ CONFIG | N5: =HYPERLINK("#M16_CHANGELOG!A1","▶ CHANGELOG") -> ▶ CHANGELOG
A6: Ingresar datos | B6: Medidas corporales | D6: Auditar operaciones | F6: Ver resumen | H6: Trazabilidad | J6: Control de calidad | L6: Constantes | N6: Historial
A7: Código del producto | D7: NMX-16
A8: Versión | D8: 1.0
A9: Fecha | D9: 2026-07-14
A10: Método | D10: Antropométrico de Heath–Carter
A11: Formato | D11: .xlsx sin macros · Microsoft 365 y Excel 2021
A12: Responsable | D12: Equipo Nutrimetría (completar por el titular)
A13: AVISO DE ALCANCE — LÉALO ANTES DE USAR
A14: EXACTITUD MATEMÁTICA ≠ VALIDACIÓN CLÍNICA. Este archivo NO está validado clínicamente.
A15: APLICA A: personas ADULTAS (≥18 años).
A16: El somatotipo describe la FORMA corporal; NO mide composición ni diagnostica por sí solo.
A17: La precisión depende de la técnica de medición (estándar ISAK): puntos anatómicos y plicómetro calibrado.
A18: Los tres componentes deben interpretarse en conjunto, no de forma aislada.
A19: Un componente cuyo cálculo sea ≤0 se fija en 0,1 por definición del método.
A20: PROPÓSITO Y ALCANCE
A21: Propósito | D21: Proveer una herramienta automatizada para determinar los componentes de endomorfia, mesomorfia y ectomorfia según el método antropométrico de Heath-Carter, permitiendo visualizar la distribución morfológica en la somatocarta como complemento a la evaluación física.
A22: Población | D22: Personas adultas (≥18 años).
A23: Uso | D23: El somatotipo describe la FORMA corporal; NO mide composición ni diagnostica por sí solo.
A24: Compatibilidad | D24: .xlsx sin macros · Microsoft 365 y Excel 2021
A25: Privacidad | D25: Los datos permanecen en el archivo local. El libro no transmite información.
A26: CÓMO SE MODELA
A27: Endomorfia: polinomio sobre Σ(tríceps+subescapular+supraespinal) corregida por talla (×170,18/estatura).
A28: Mesomorfia: diámetros de húmero y fémur + perímetros de brazo y pantorrilla corregidos − 0,131·talla + 4,5.
A29: Ectomorfia: según el índice talla/peso^(1/3) (HWR), en tres tramos.
A30: Somatocarta: X = ecto − endo · Y = 2·meso − (endo+ecto).
A31: Clasificación en 13 categorías según qué componente domina y sus diferencias.

Sheet M16_DATOS
A1: NUTRIMETRÍA · NMX-16
A2: Datos de entrada · identificación y datos básicos
A3: =HYPERLINK("#M16_INICIO!A1","◀ INICIO") -> ◀ INICIO | B3: =HYPERLINK("#M16_CALCULOS!A1","▶ CALCULOS") -> ▶ CALCULOS | D3: =HYPERLINK("#M16_RESULTADOS!A1","▶ RESULTADOS") -> ▶ RESULTADOS
A4: LEYENDA · Celdas ARENA con texto AZUL = editables. Grises = calculadas. (opcional) = puede quedar vacía.
A5: ► Las mediciones antropométricas se ingresan en la hoja MEDIDAS.
A6: Campo | B6: Valor | C6: Unidad | D6: Validación | E6: Ayuda
A7: Identificador de la evaluación | B7: =DATOS!$B$7 -> NMX-2026-0028 | C7: — | D7: Texto libre | E7: Código interno.
A8: Fecha | B8: =DATOS!$B$8 -> 46236 | C8: fecha | D8: Fecha | E8: dd/mm/aaaa.
A9: Nombre o código del paciente | B9: =DATOS!$B$9 -> PER-0007 | C9: — | D9: Texto libre | E9: Prefiera un CÓDIGO si comparte el archivo.
A10: Sexo biológico | B10: =DATOS!$B$10 -> Hombre | C10: — | D10: Lista: Hombre / Mujer | E10: Referencia; las ecuaciones HC no dependen del sexo.
A11: Edad | B11: =DATOS!$B$11 -> 34 | C11: años | D11: ≥18 y ≤120 | E11: Solo adultos.
A12: Peso | B12: =DATOS!$B$12 -> 78.5 | C12: kg | D12: Entre 25 y 350 | E12: Necesario para la ectomorfia.
A13: Estatura | B13: =DATOS!$B$13 -> 176 | C13: cm | D13: Entre 120 y 230 | E13: Necesaria para las tres componentes.
A14: Evaluador | B14: =DATOS!$B$14 -> EVAL-01 | C14: — | D14: Texto libre | E14: Para trazabilidad.
A15: Observaciones | B15: =DATOS!$B$17 -> 0 | C15: — | D15: Texto libre | E15: Contexto, calibración, condiciones.

Sheet M16_MEDIDAS
A1: NUTRIMETRÍA · NMX-16
A2: Panel antropométrico · Heath–Carter (lado derecho del cuerpo)
A3: Marque los puntos anatómicos antes de medir. Los pliegues van en mm; los diámetros óseos y perímetros, en cm. Endomorfia: tríceps + subescapular + supraespinal. Mesomorfia: húmero, fémur, brazo y pantorrilla (perímetros corregidos con sus pliegues). Ectomorfia: peso y estatura (hoja DATOS).
A4: =HYPERLINK("#M16_DATOS!A1","◀ DATOS") -> ◀ DATOS | C4: =HYPERLINK("#M16_CALCULOS!A1","◀ CALCULOS") -> ◀ CALCULOS
A6: Nº | B6: Medida | C6: Valor | D6: Unidad | E6: Referencia anatómica / técnica
A7: Pliegues cutáneos (mm)
A8: 1 | B8: Tríceps | C8: =MED_Tri -> 12 | D8: mm | E8: Vertical, cara posterior del brazo, punto medio.
A9: 2 | B9: Subescapular | C9: =MED_Sub -> 14 | D9: mm | E9: Oblicuo, 2 cm bajo el ángulo inferior de la escápula.
A10: 3 | B10: Supraespinal (cresta ilíaca ant.) | C10: =MED_Supra -> 16 | D10: mm | E10: Oblicuo, sobre la espina ilíaca anterosuperior.
A11: 4 | B11: Pantorrilla medial | C11: =MED_Pant -> 37 | D11: mm | E11: Vertical, cara medial, máximo perímetro.
A12: Diámetros óseos (cm)
A13: 5 | B13: Húmero (biepicondíleo) | C13: =MED_Hum -> 7 | D13: cm | E13: Entre epicóndilo y epitróclea, codo a 90°.
A14: 6 | B14: Fémur (biepicondíleo) | C14: =MED_Fem -> 9 | D14: cm | E14: Entre cóndilos femorales, sentado, rodilla a 90°.
A15: Perímetros (cm)
A16: 7 | B16: Brazo flexionado en tensión | C16: =MED_BrazoG -> 32 | D16: cm | E16: Máximo, con el brazo contraído.
A17: 8 | B17: Pantorrilla (máximo) | C17: =MED_PantG -> 36 | D17: cm | E17: Máximo perímetro de la pantorrilla.
A18: ► El brazo y la pantorrilla se corrigen automáticamente restando su pliegue: brazo − tríceps/10 y pantorrilla − pliegue de pantorrilla/10.

Sheet M16_CALCULOS
A1: NUTRIMETRÍA · NMX-16
A2: Motor · endomorfia, mesomorfia, ectomorfia y somatocarta
A3: =HYPERLINK("#M16_DATOS!A1","◀ DATOS") -> ◀ DATOS | B3: =HYPERLINK("#M16_MEDIDAS!A1", "◀ MEDIDAS") -> ◀ MEDIDAS | C3: =HYPERLINK("#M16_RESULTADOS!A1","▶ RESULTADOS") -> ▶ RESULTADOS
A4: Cada celda declara su fórmula. Las guardas devuelven 'ND: …' en vez de errores. Un componente cuyo cálculo sea ≤0 se fija en 0,1 por definición (Carter).
A6: BLOQUE 0 · MEDIDAS DERIVADAS
A7: Variable | B7: Valor | C7: Unidad | D7: Fórmula / cómo se obtiene
A8: Estatura en metros | B8: =IF(ISNUMBER(M16_in_Est),M16_in_Est/100,"ND") -> 1.76 | C8: m | D8: in_Est/100
A9: Σ 3 pliegues (endomorfia) | B9: =IF(AND(ISNUMBER(M16_m_Tri),ISNUMBER(M16_m_Sub),ISNUMBER(M16_m_Sup)),M16_m_Tri+M16_m_Sub+M16_m_Sup,"ND: faltan pliegues") -> 42 | C9: mm | D9: tríceps+subescapular+supraespinal
A10: Σ corregida por talla (X) | B10: =IF(AND(ISNUMBER(M16_c_Sum3),ISNUMBER(M16_in_Est),M16_in_Est>0),M16_c_Sum3*(M16_ENDO_HREF/M16_in_Est),"ND") -> 40.611136 | C10: mm | D10: Σ3 × (170,18 / estatura)
A11: Perímetro de brazo corregido | B11: =IF(AND(ISNUMBER(M16_m_ArmG),ISNUMBER(M16_m_Tri)),M16_m_ArmG-M16_m_Tri/10,"ND") -> 30.8 | C11: cm | D11: brazo − tríceps/10
A12: Perímetro de pantorrilla corregido | B12: =IF(AND(ISNUMBER(M16_m_CalfG),ISNUMBER(M16_m_Calf)),M16_m_CalfG-M16_m_Calf/10,"ND") -> 32.3 | C12: cm | D12: pantorrilla − pliegue/10
A13: Índice talla/peso (HWR) | B13: =IF(AND(ISNUMBER(M16_in_Est),ISNUMBER(M16_in_Peso),M16_in_Peso>0),M16_in_Est/(M16_in_Peso^(1/3)),"ND") -> 41.104507 | C13: — | D13: estatura / peso^(1/3)
A14: BLOQUE 1 · COMPUERTA DE DATOS IMPOSIBLES
A15: Variable | B15: Valor | C15: Unidad | D15: Fórmula / cómo se obtiene
A16: ¿Cálculo habilitado? | B16: =IF(AND(ISNUMBER(M16_in_Edad),M16_in_Edad>=M16_EDAD_MIN,M16_in_Edad<=M16_EDAD_MAX,ISNUMBER(M16_in_Peso),M16_in_Peso>=M16_PESO_MIN,M16_in_Peso<=M16_PESO_MAX,ISNUMBER(M16_in_Est),M16_in_Est>=M16_EST_MIN,M16_in_Est<=M16_EST_MAX),"SÍ","NO") -> SÍ | C16: — | D16: Exige edad adulta, peso y estatura válidos
A17: BLOQUE 2 · COMPONENTES DEL SOMATOTIPO
A18: Variable | B18: Valor | C18: Unidad | D18: Fórmula / cómo se obtiene
A19: Endomorfia | B19: =IF(AND(M16_c_Gate="SÍ",ISNUMBER(M16_c_Xcorr)),MAX(M16_MIN_COMP,M16_ENDO_C0+M16_ENDO_C1*M16_c_Xcorr-M16_ENDO_C2*M16_c_Xcorr^2+M16_ENDO_C3*M16_c_Xcorr^3),"ND") -> 4.146746 | C19: — | D19: Polinomio de 3er grado sobre X
A20: Mesomorfia | B20: =IF(AND(M16_c_Gate="SÍ",ISNUMBER(M16_m_Hum),ISNUMBER(M16_m_Fem),ISNUMBER(M16_c_CAG),ISNUMBER(M16_c_CCG),ISNUMBER(M16_in_Est)),MAX(M16_MIN_COMP,M16_MESO_HB*M16_m_Hum+M16_MESO_FB*M16_m_Fem+M16_MESO_CAG*M16_c_CAG+M16_MESO_CCG*M16_c_CCG-M16_MESO_H*M16_in_Est+M16_MESO_K),"ND") -> 3.8497 | C20: — | D20: Diámetros y perímetros corregidos − 0,131·talla + 4,5
A21: Ectomorfia | B21: =IF(AND(M16_c_Gate="SÍ",ISNUMBER(M16_c_HWR)),MAX(M16_MIN_COMP,IF(M16_c_HWR>=M16_ECTO_T1,M16_ECTO_A1*M16_c_HWR-M16_ECTO_B1,IF(M16_c_HWR>M16_ECTO_T2,M16_ECTO_A2*M16_c_HWR-M16_ECTO_B2,M16_MIN_COMP))),"ND") -> 1.5084995 | C21: — | D21: Según el tramo del HWR
A22: Somatotipo | B22: =IF(AND(ISNUMBER(M16_c_Endo),ISNUMBER(M16_c_Meso),ISNUMBER(M16_c_Ecto)),TEXT(M16_c_Endo,"0.0")&" - "&TEXT(M16_c_Meso,"0.0")&" - "&TEXT(M16_c_Ecto,"0.0"),"ND") -> 04 - 04 - 02 | C22: — | D22: endo − meso − ecto
A23: BLOQUE 3 · SOMATOCARTA Y CLASIFICACIÓN
A24: Variable | B24: Valor | C24: Unidad | D24: Fórmula / cómo se obtiene
A25: Coordenada X | B25: =IF(AND(ISNUMBER(M16_c_Endo),ISNUMBER(M16_c_Ecto)),M16_c_Ecto-M16_c_Endo,"ND") -> -2.6382465 | C25: — | D25: ecto − endo
A26: Coordenada Y | B26: =IF(AND(ISNUMBER(M16_c_Endo),ISNUMBER(M16_c_Meso),ISNUMBER(M16_c_Ecto)),2*M16_c_Meso-(M16_c_Endo+M16_c_Ecto),"ND") -> 2.0441545 | C26: — | D26: 2·meso − (endo+ecto)
A27: Máximo componente | B27: =IF(ISNUMBER(M16_c_Endo),MAX(M16_c_Endo,M16_c_Meso,M16_c_Ecto),"ND") -> 4.146746 | C27: —
A28: Mínimo componente | B28: =IF(ISNUMBER(M16_c_Endo),MIN(M16_c_Endo,M16_c_Meso,M16_c_Ecto),"ND") -> 1.5084995 | C28: —
A29: Componente medio | B29: =IF(ISNUMBER(M16_c_Endo),M16_c_Endo+M16_c_Meso+M16_c_Ecto-M16_c_mx-M16_c_mn,"ND") -> 3.8497 | C29: —
A30: Clasificación (13 categorías) | B30: =IF(AND(ISNUMBER(M16_c_Endo),ISNUMBER(M16_c_Meso),ISNUMBER(M16_c_Ecto)),IF((M16_c_mx-M16_c_mn)<=1,"Central",IF((M16_c_mx-M16_c_mid)<=0.5,IF(M16_c_mn=M16_c_Ecto,"Endomorfo-mesomorfo",IF(M16_c_mn=M16_c_Endo,"Mesomorfo-ectomorfo","Endomorfo-ectomorfo")),IF((M16_c_mid-M16_c_mn)<=0.5,IF(M16_c_mx=M16_c_Meso,"Mesomorfo",IF(M16_c_mx=M16_c_Endo,"Endomorfo","Ectomorfo"))&" balanceado",IF(M16_c_mx=M16_c_Meso,"Mesomorfo",IF(M16_c_mx=M16_c_Endo,"Endomorfo","Ectomorfo"))&" "&IF(M16_c_mid=M16_c_Endo,"endomórfico",IF(M16_c_mid=M16_c_Meso,"mesomórfico","ectomórfico"))))),"ND") -> Endomorfo-mesomorfo | C30: — | D30: Regla de Carter & Heath según dominancia
A31: BLOQUE 4 · ADVERTENCIAS
A32: Variable | B32: Valor | C32: Unidad | D32: Fórmula / cómo se obtiene
A33: Cálculo bloqueado | B33: =IF(M16_c_Gate="NO","Corrija los datos imposibles (edad, peso o estatura) antes de interpretar.","—") -> —
A34: Endomorfia sin datos | B34: =IF(ISNUMBER(M16_c_Endo),"—","Faltan pliegues (tríceps, subescapular o supraespinal) para la endomorfia.") -> —
A35: Mesomorfia sin datos | B35: =IF(ISNUMBER(M16_c_Meso),"—","Faltan diámetros o perímetros para la mesomorfia.") -> —
A36: Ectomorfia sin datos | B36: =IF(ISNUMBER(M16_c_Ecto),"—","Falta peso o estatura para la ectomorfia.") -> —
A37: Componente en su piso (0,1) | B37: =IF(OR(AND(ISNUMBER(M16_c_Endo),M16_c_Endo<=M16_MIN_COMP),AND(ISNUMBER(M16_c_Meso),M16_c_Meso<=M16_MIN_COMP),AND(ISNUMBER(M16_c_Ecto),M16_c_Ecto<=M16_MIN_COMP)),"Algún componente quedó en su valor mínimo (0,1): revise las mediciones extremas.","—") -> —
A38: Medida fuera de rango habitual | B38: =IF(OR(AND(ISNUMBER(M16_m_Hum),OR(M16_m_Hum<M16_DIA_MIN,M16_m_Hum>M16_DIA_MAX)),AND(ISNUMBER(M16_m_Fem),OR(M16_m_Fem<M16_DIA_MIN,M16_m_Fem>M16_DIA_MAX)),AND(ISNUMBER(M16_m_ArmG),OR(M16_m_ArmG<M16_PER_MIN,M16_m_ArmG>M16_PER_MAX)),AND(ISNUMBER(M16_m_CalfG),OR(M16_m_CalfG<M16_PER_MIN,M16_m_CalfG>M16_PER_MAX))),"Algún diámetro o perímetro está fuera del rango habitual: verifique la medición.","—") -> —
A39: Recordatorio metodológico | B39: ="Exactitud matemática ≠ validación clínica. El somatotipo describe la FORMA corporal, no diagnostica ni mide composición por sí solo." -> Exactitud matemática ≠ validación clínica. El somatotipo describe la FORMA corporal, no diagnostica ni mide composición por sí solo.

Sheet M16_RESULTADOS
A1: NUTRIMETRÍA · NMX-16
A2: Informe de somatotipo y somatocarta
A3: =HYPERLINK("#M16_DATOS!A1","◀ DATOS") -> ◀ DATOS | B3: =HYPERLINK("#M16_MEDIDAS!A1", "◀ MEDIDAS") -> ◀ MEDIDAS | D3: =HYPERLINK("#M16_CALCULOS!A1","◀ CALCULOS") -> ◀ CALCULOS | G3: =HYPERLINK("#M16_FUENTES!A1","▶ FUENTES") -> ▶ FUENTES
A5: IDENTIFICACIÓN
A6: Identificador | B6: =M16_in_ID -> NMX-2026-0028
A7: Fecha | B7: =M16_in_Fecha -> 46236
A8: Paciente | B8: =M16_in_Pac -> PER-0007
A9: Evaluador | B9: =M16_in_Eval -> EVAL-01
A10: Sexo · edad | B10: =M16_in_Sexo&" · "&IF(ISNUMBER(M16_in_Edad),M16_in_Edad&" años","(edad no válida)") -> Hombre · 34 años
A11: Peso · estatura | B11: =IF(ISNUMBER(M16_in_Peso),ROUND(M16_in_Peso,1)&" kg","(?)")&" · "&IF(ISNUMBER(M16_in_Est),ROUND(M16_in_Est,1)&" cm","(?)") -> 78,5 kg · 176 cm
A12: Estado del cálculo | B12: =IF(M16_c_Gate="SÍ","HABILITADO","BLOQUEADO — corrija los datos imposibles") -> HABILITADO
A14: SOMATOTIPO
A15: Endomorfia (relativa adiposidad) | B15: =M16_c_Endo -> 4.146746
A16: Mesomorfia (robustez musculoesquelética) | B16: =M16_c_Meso -> 3.8497
A17: Ectomorfia (linealidad) | B17: =M16_c_Ecto -> 1.5084995
A18: Somatotipo | B18: =M16_c_Soma -> 04 - 04 - 02
A19: Clasificación | B19: =M16_c_Clase -> Endomorfo-mesomorfo
A21: SOMATOCARTA
A22: Coordenada X (ecto − endo) | B22: =M16_c_SX -> -2.6382465
A23: Coordenada Y (2·meso − (endo+ecto)) | B23: =M16_c_SY -> 2.0441545
A25: Serie | B25: X | C25: Y
A26: =M16_CONFIG!A53 -> Endomorfia (7-1-1) | B26: =M16_CONFIG!B53 -> -6 | C26: =M16_CONFIG!C53 -> -6
A27: =M16_CONFIG!A54 -> Mesomorfia (1-7-1) | B27: =M16_CONFIG!B54 -> 0 | C27: =M16_CONFIG!C54 -> 12
A28: =M16_CONFIG!A55 -> Ectomorfia (1-1-7) | B28: =M16_CONFIG!B55 -> 6 | C28: =M16_CONFIG!C55 -> -6
A29: =M16_CONFIG!A56 -> cierre | B29: =M16_CONFIG!B56 -> -6 | C29: =M16_CONFIG!C56 -> -6
A30: Sujeto | B30: =M16_c_SX -> -2.6382465 | C30: =M16_c_SY -> 2.0441545
A32: DATOS DE APOYO (gráfico de componentes)
A33: Componente | B33: Valor
A34: Endomorfia | B34: =IF(ISNUMBER(M16_c_Endo),M16_c_Endo,0) -> 4.146746
A35: Mesomorfia | B35: =IF(ISNUMBER(M16_c_Meso),M16_c_Meso,0) -> 3.8497
A36: Ectomorfia | B36: =IF(ISNUMBER(M16_c_Ecto),M16_c_Ecto,0) -> 1.5084995
A38: ADVERTENCIAS
A39: Cálculo bloqueado | B39: =M16_CALCULOS!B33 -> —
A40: Endomorfia sin datos | B40: =M16_CALCULOS!B34 -> —
A41: Mesomorfia sin datos | B41: =M16_CALCULOS!B35 -> —
A42: Ectomorfia sin datos | B42: =M16_CALCULOS!B36 -> —
A43: Componente en su piso | B43: =M16_CALCULOS!B37 -> —
A44: Medida fuera de rango | B44: =M16_CALCULOS!B38 -> —
A45: Recordatorio metodológico | B45: =M16_CALCULOS!B39 -> Exactitud matemática ≠ validación clínica. El somatotipo describe la FORMA corporal, no diagnostica ni mide composición por sí solo.
A46: EXACTITUD MATEMÁTICA ≠ VALIDACIÓN CLÍNICA. Los coeficientes se cotejaron contra el manual de Heath–Carter, pero este archivo NO está validado clínicamente. El somatotipo describe la FORMA corporal; no mide composición por sí solo ni constituye diagnóstico. La precisión depende de la técnica de medición (ISAK).

Sheet M16_FUENTES
A1: NUTRIMETRÍA · NMX-16
A2: Trazabilidad del método antropométrico de Heath–Carter
A3: NIVEL A = manual/publicación oficial del método · B = corroboración por pares · C = fuente secundaria. Solo se usan ECUACIONES y COEFICIENTES (hechos no protegibles). EXACTITUD BIBLIOGRÁFICA ≠ VALIDACIÓN CLÍNICA.
A4: =HYPERLINK("#M16_INICIO!A1","◀ INICIO") -> ◀ INICIO | B4: =HYPERLINK("#M16_DATOS!A1","◀ DATOS") -> ◀ DATOS | C4: =HYPERLINK("#M16_CALCULOS!A1","◀ CALCULOS") -> ◀ CALCULOS
A5: Ecuación o dato | B5: Autor u organización | C5: Año | D5: Población / base | E5: Fórmula / valor | F5: Unidades | G5: Limitaciones | H5: DOI o fuente | I5: Fecha cotejo | J5: Licencia / condiciones | K5: Nivel
A6: Método antropométrico de somatotipo | B6: Carter JEL — The Heath-Carter Anthropometric Somatotype, Instruction Manual | C6: 1990/2002 | D6: Basado en Heath & Carter (1967); San Diego State University | E6: Tres componentes: endomorfia, mesomorfia, ectomorfia | F6: unidades adimensionales | G6: Describe la FORMA, no la composición; depende de la técnica de medición. | H6: somatotype.org · Instruction Manual | I6: 2026-07-16 | J6: Manual reproducible para uso docente sin permiso específico (según el propio manual); se usan las ecuaciones. | K6: A
A7: Endomorfia (corregida por talla) | B7: Carter & Heath | C7: 1990 | D7: Polinomio de 3er grado | E7: Endo = −0,7182 + 0,1451·X − 0,00068·X² + 0,0000014·X³ ; X = Σ3·(170,18/talla) | F7: mm; adimensional | G7: Σ3 = tríceps+subescapular+supraespinal; sensible a la calidad de los pliegues. | H7: Heath-Carter Manual | I7: 2026-07-16 | J7: Se usa la ecuación (hecho no protegible). | K7: A
A8: Mesomorfia | B8: Carter & Heath | C8: 1990 | D8: Diámetros óseos y perímetros corregidos | E8: Meso = 0,858·húmero + 0,601·fémur + 0,188·brazoC + 0,161·pantorrillaC − 0,131·talla + 4,5 | F8: cm; adimensional | G8: Perímetros corregidos por el pliegue respectivo (÷10 para pasar mm→cm). | H8: Heath-Carter Manual | I8: 2026-07-16 | J8: Se usa la ecuación (hecho no protegible). | K8: A
A9: Ectomorfia (por HWR) | B9: Carter & Heath | C9: 1990 | D9: Índice talla/peso HWR = talla / peso^(1/3) | E9: HWR≥40,75: 0,732·HWR−28,58 · 38,25<HWR<40,75: 0,463·HWR−17,63 · HWR≤38,25: 0,1 | F9: adimensional | G9: Tres tramos; un componente ≤0 se fija en 0,1. | H9: Heath-Carter Manual | I9: 2026-07-16 | J9: Se usa la ecuación (hecho no protegible). | K9: A
A10: Clasificación en 13 categorías | B10: Carter & Heath — Somatotyping: development and applications | C10: 1990 | D10: Regla de dominancia de componentes | E10: Central / balanceado / ‘-’ / adjetivado según dominancia y diferencias | F10: — | G10: Categoría cualitativa; los valores numéricos son la información primaria. | H10: Cambridge University Press, 1990 | I10: 2026-07-16 | J10: Obra con derechos de autor; se usa el criterio de clasificación (hecho no protegible). | K10: B
A11: Estandarización de la medición | B11: ISAK — International Standards for Anthropometric Assessment | C11: 2001/vigente | D11: Estándar internacional de cineantropometría | E11: Puntos anatómicos y técnica de pliegues, diámetros y perímetros | F11: mm; cm | G11: La reproducibilidad depende de la acreditación del evaluador. | H11: ISAK · normas | I11: 2026-07-16 | J11: Estándar de la sociedad ISAK; se usa la definición técnica. | K11: A
A13: VERIFICADO (2026-07-23): el umbral bajo del HWR usado en el motor es 38,25, confirmado contra múltiples fuentes revisadas por pares que aplican el método Heath–Carter (p. ej. Frontiers in Physiology, 2025; PMC). La cifra de 38,35 que circula en algunas copias secundarias (diapositivas) es la errata; no se usa aquí. Aun así, se recomienda cotejar contra la edición física del manual de Carter (1990/2002) antes de un uso clínico o docente formal.
A15: NOTA EDITORIAL AÑADIDA (2026-07-23): los límites de "impossible data" para pliegues cutáneos en CONFIG (2 mm a 60 mm) son una cota práctica de plicometría/ISAK definida por el equipo del producto, no un valor tomado del manual Heath–Carter. El titular puede ajustarlos en CONFIG!B16:B17 según su propio protocolo.

Sheet M16_PRUEBAS
A1: NUTRIMETRÍA · NMX-16
A2: Banco de verificación · el recuento se calcula solo en el RESUMEN
A3: REGLA: el valor ESPERADO nunca lee el CONFIG que usa el motor. O es un literal calculado a partir del manual de Heath–Carter, o se reconstruye con los coeficientes publicados escritos de forma explícita. Si alguien corrompe un coeficiente de CONFIG, estas pruebas FALLAN.
A4: =HYPERLINK("#M16_INICIO!A1","◀ INICIO") -> ◀ INICIO
A6: BLOQUE A · EXACTITUD ENDOMORFIA (polinomio corregido por talla)
A7: ID | B7: Descripción | C7: Σ3 | D7: Talla | E7: Obtenido | F7: Esperado | G7: Dif. | H7: Estado
A8: A01 | B8: Σ30 H176 | C8: 30 | D8: 176 | E8: =MAX(0.1,-0.7182+0.1451*(C8*(170.18/D8))-0.00068*(C8*(170.18/D8))^2+0.0000014*(C8*(170.18/D8))^3) -> 2.9528331 | F8: 2.952833 | G8: =E8-F8 -> 1.389989e-07 | H8: =IF(ABS(G8)<=M16_TOL_U,"APROBADO","FALLIDO") -> APROBADO
A9: A02 | B9: Σ45 H165 | C9: 45 | D9: 165 | E9: =MAX(0.1,-0.7182+0.1451*(C9*(170.18/D9))-0.00068*(C9*(170.18/D9))^2+0.0000014*(C9*(170.18/D9))^3) -> 4.6914421 | F9: 4.691442 | G9: =E9-F9 -> 7.3974192e-08 | H9: =IF(ABS(G9)<=M16_TOL_U,"APROBADO","FALLIDO") -> APROBADO
A10: A03 | B10: Σ60 H180 | C10: 60 | D10: 180 | E10: =MAX(0.1,-0.7182+0.1451*(C10*(170.18/D10))-0.00068*(C10*(170.18/D10))^2+0.0000014*(C10*(170.18/D10))^3) -> 5.5802155 | F10: 5.580216 | G10: =E10-F10 -> -4.6497167e-07 | H10: =IF(ABS(G10)<=M16_TOL_U,"APROBADO","FALLIDO") -> APROBADO
A11: A04 | B11: Σ20 H170 | C11: 20 | D11: 170 | E11: =MAX(0.1,-0.7182+0.1451*(C11*(170.18/D11))-0.00068*(C11*(170.18/D11))^2+0.0000014*(C11*(170.18/D11))^3) -> 1.925532 | F11: 1.925532 | G11: =E11-F11 -> 1.5094264e-08 | H11: =IF(ABS(G11)<=M16_TOL_U,"APROBADO","FALLIDO") -> APROBADO
A12: A05 | B12: Σ90 H160 | C12: 90 | D12: 160 | E12: =MAX(0.1,-0.7182+0.1451*(C12*(170.18/D12))-0.00068*(C12*(170.18/D12))^2+0.0000014*(C12*(170.18/D12))^3) -> 8.1685532 | F12: 8.168553 | G12: =E12-F12 -> 2.071471e-07 | H12: =IF(ABS(G12)<=M16_TOL_U,"APROBADO","FALLIDO") -> APROBADO
A13: A06 | B13: Σ15 H190 | C13: 15 | D13: 190 | E13: =MAX(0.1,-0.7182+0.1451*(C13*(170.18/D13))-0.00068*(C13*(170.18/D13))^2+0.0000014*(C13*(170.18/D13))^3) -> 1.1119076 | F13: 1.111908 | G13: =E13-F13 -> -3.8772628e-07 | H13: =IF(ABS(G13)<=M16_TOL_U,"APROBADO","FALLIDO") -> APROBADO
A15: BLOQUE B · EXACTITUD MESOMORFIA
A16: ID | B16: Húmero | C16: Fémur | D16: BrazoC | E16: PantC | F16: Talla | G16: Obtenido | H16: Esperado | I16: Dif. | J16: Estado
A17: B01 | B17: 7 | C17: 9.6 | D17: 32 | E17: 36.2 | F17: 176 | G17: =MAX(0.1,0.858*B17+0.601*C17+0.188*D17+0.161*E17-0.131*F17+4.5) -> 5.0638 | H17: 5.0638 | I17: =G17-H17 -> 0 | J17: =IF(ABS(I17)<=M16_TOL_U,"APROBADO","FALLIDO") -> APROBADO
A18: B02 | B18: 6.5 | C18: 9 | D18: 28 | E18: 34 | F18: 165 | G18: =MAX(0.1,0.858*B18+0.601*C18+0.188*D18+0.161*E18-0.131*F18+4.5) -> 4.609 | H18: 4.609 | I18: =G18-H18 -> 0 | J18: =IF(ABS(I18)<=M16_TOL_U,"APROBADO","FALLIDO") -> APROBADO
A19: B03 | B19: 7.5 | C19: 10.2 | D19: 36 | E19: 39 | F19: 182 | G19: =MAX(0.1,0.858*B19+0.601*C19+0.188*D19+0.161*E19-0.131*F19+4.5) -> 6.2702 | H19: 6.2702 | I19: =G19-H19 -> 0 | J19: =IF(ABS(I19)<=M16_TOL_U,"APROBADO","FALLIDO") -> APROBADO
A20: B04 | B20: 6 | C20: 8.5 | D20: 26 | E20: 32 | F20: 158 | G20: =MAX(0.1,0.858*B20+0.601*C20+0.188*D20+0.161*E20-0.131*F20+4.5) -> 4.0985 | H20: 4.0985 | I20: =G20-H20 -> 0 | J20: =IF(ABS(I20)<=M16_TOL_U,"APROBADO","FALLIDO") -> APROBADO
A21: B05 | B21: 8 | C21: 10.5 | D21: 40 | E21: 41 | F21: 190 | G21: =MAX(0.1,0.858*B21+0.601*C21+0.188*D21+0.161*E21-0.131*F21+4.5) -> 6.9055 | H21: 6.9055 | I21: =G21-H21 -> 0 | J21: =IF(ABS(I21)<=M16_TOL_U,"APROBADO","FALLIDO") -> APROBADO
A23: BLOQUE C · EXACTITUD ECTOMORFIA · los tres tramos del HWR
A24: ID | B24: Descripción | C24: Talla | D24: Peso | E24: Obtenido | F24: Esperado | G24: Dif. | H24: Estado
A25: C01 | B25: Tramo alto | C25: 176 | D25: 78.5 | E25: =MAX(0.1,IF(C25/(D25^(1/3))>=40.75,0.732*(C25/(D25^(1/3)))-28.58,IF(C25/(D25^(1/3))>38.25,0.463*(C25/(D25^(1/3)))-17.63,0.1))) -> 1.5084995 | F25: 1.508499 | G25: =E25-F25 -> 4.8259255e-07 | H25: =IF(ABS(G25)<=M16_TOL_U,"APROBADO","FALLIDO") -> APROBADO
A26: C02 | B26: Tramo alto delgado | C26: 180 | D26: 60 | E26: =MAX(0.1,IF(C26/(D26^(1/3))>=40.75,0.732*(C26/(D26^(1/3)))-28.58,IF(C26/(D26^(1/3))>38.25,0.463*(C26/(D26^(1/3)))-17.63,0.1))) -> 5.0763103 | F26: 5.07631 | G26: =E26-F26 -> 2.7072485e-07 | H26: =IF(ABS(G26)<=M16_TOL_U,"APROBADO","FALLIDO") -> APROBADO
A27: C03 | B27: Tramo medio | C27: 170 | D27: 72 | E27: =MAX(0.1,IF(C27/(D27^(1/3))>=40.75,0.732*(C27/(D27^(1/3)))-28.58,IF(C27/(D27^(1/3))>38.25,0.463*(C27/(D27^(1/3)))-17.63,0.1))) -> 1.3322561 | F27: 1.332256 | G27: =E27-F27 -> 8.8175658e-08 | H27: =IF(ABS(G27)<=M16_TOL_U,"APROBADO","FALLIDO") -> APROBADO
A28: C04 | B28: Tramo bajo (piso 0,1) | C28: 160 | D28: 85 | E28: =MAX(0.1,IF(C28/(D28^(1/3))>=40.75,0.732*(C28/(D28^(1/3)))-28.58,IF(C28/(D28^(1/3))>38.25,0.463*(C28/(D28^(1/3)))-17.63,0.1))) -> 0.1 | F28: 0.1 | G28: =E28-F28 -> 0 | H28: =IF(ABS(G28)<=M16_TOL_U,"APROBADO","FALLIDO") -> APROBADO
A29: C05 | B29: Muy delgado | C29: 190 | D29: 62 | E29: =MAX(0.1,IF(C29/(D29^(1/3))>=40.75,0.732*(C29/(D29^(1/3)))-28.58,IF(C29/(D29^(1/3))>38.25,0.463*(C29/(D29^(1/3)))-17.63,0.1))) -> 6.5599214 | F29: 6.559921 | G29: =E29-F29 -> 3.8133124e-07 | H29: =IF(ABS(G29)<=M16_TOL_U,"APROBADO","FALLIDO") -> APROBADO
A30: C06 | B30: Robusto bajo | C30: 165 | D30: 90 | E30: =MAX(0.1,IF(C30/(D30^(1/3))>=40.75,0.732*(C30/(D30^(1/3)))-28.58,IF(C30/(D30^(1/3))>38.25,0.463*(C30/(D30^(1/3)))-17.63,0.1))) -> 0.1 | F30: 0.1 | G30: =E30-F30 -> 0 | H30: =IF(ABS(G30)<=M16_TOL_U,"APROBADO","FALLIDO") -> APROBADO
A32: BLOQUE D · COORDENADAS DE LA SOMATOCARTA
A33: ID | B33: Endo | C33: Meso | D33: Ecto | E33: X obt | F33: X esp | G33: Est.X | H33: Y obt | I33: Y esp | J33: Est.Y
A34: D01 | B34: 2.95 | C34: 5.06 | D34: 1.51 | E34: =D34-B34 -> -1.44 | F34: -1.44 | G34: =IF(ABS(E34-F34)<=M16_TOL_U,"APROBADO","FALLIDO") -> APROBADO | H34: =2*C34-(B34+D34) -> 5.66 | I34: 5.66 | J34: =IF(ABS(H34-I34)<=M16_TOL_U,"APROBADO","FALLIDO") -> APROBADO
A35: D02 | B35: 4 | C35: 4 | D35: 2 | E35: =D35-B35 -> -2 | F35: -2 | G35: =IF(ABS(E35-F35)<=M16_TOL_U,"APROBADO","FALLIDO") -> APROBADO | H35: =2*C35-(B35+D35) -> 2 | I35: 2 | J35: =IF(ABS(H35-I35)<=M16_TOL_U,"APROBADO","FALLIDO") -> APROBADO
A36: D03 | B36: 1.5 | C36: 2 | D36: 5.5 | E36: =D36-B36 -> 4 | F36: 4 | G36: =IF(ABS(E36-F36)<=M16_TOL_U,"APROBADO","FALLIDO") -> APROBADO | H36: =2*C36-(B36+D36) -> -3 | I36: -3 | J36: =IF(ABS(H36-I36)<=M16_TOL_U,"APROBADO","FALLIDO") -> APROBADO
A37: D04 | B37: 3 | C37: 3 | D37: 3 | E37: =D37-B37 -> 0 | F37: 0 | G37: =IF(ABS(E37-F37)<=M16_TOL_U,"APROBADO","FALLIDO") -> APROBADO | H37: =2*C37-(B37+D37) -> 0 | I37: 0 | J37: =IF(ABS(H37-I37)<=M16_TOL_U,"APROBADO","FALLIDO") -> APROBADO
A39: BLOQUE E · CLASIFICACIÓN EN 13 CATEGORÍAS
A40: ID | B40: Endo·Meso·Ecto | C40: Esperado | D40: Obtenido | E40: Estado
A41: E01 | B41: 2.95·5.06·1.51 | C41: Mesomorfo endomórfico | D41: =IF((5.06-1.51)<=1,"Central",IF((5.06-2.95)<=0.5,IF(1.51=1.51,"Endomorfo-mesomorfo",IF(1.51=2.95,"Mesomorfo-ectomorfo","Endomorfo-ectomorfo")),IF((2.95-1.51)<=0.5,IF(5.06=5.06,"Mesomorfo",IF(5.06=2.95,"Endomorfo","Ectomorfo"))&" balanceado",IF(5.06=5.06,"Mesomorfo",IF(5.06=2.95,"Endomorfo","Ectomorfo"))&" "&IF(2.95=2.95,"endomórfico",IF(2.95=5.06,"mesomórfico","ectomórfico"))))) -> Mesomorfo endomórfico | E41: =IF(D41=C41,"APROBADO","FALLIDO") -> APROBADO
A42: E02 | B42: 3.0·3.5·3.2 | C42: Central | D42: =IF((3.5-3)<=1,"Central",IF((3.5-3.2)<=0.5,IF(3=3.2,"Endomorfo-mesomorfo",IF(3=3,"Mesomorfo-ectomorfo","Endomorfo-ectomorfo")),IF((3.2-3)<=0.5,IF(3.5=3.5,"Mesomorfo",IF(3.5=3,"Endomorfo","Ectomorfo"))&" balanceado",IF(3.5=3.5,"Mesomorfo",IF(3.5=3,"Endomorfo","Ectomorfo"))&" "&IF(3.2=3,"endomórfico",IF(3.2=3.5,"mesomórfico","ectomórfico"))))) -> Central | E42: =IF(D42=C42,"APROBADO","FALLIDO") -> APROBADO
A43: E03 | B43: 5.0·2.0·2.0 | C43: Endomorfo balanceado | D43: =IF((5-2)<=1,"Central",IF((5-2)<=0.5,IF(2=2,"Endomorfo-mesomorfo",IF(2=5,"Mesomorfo-ectomorfo","Endomorfo-ectomorfo")),IF((2-2)<=0.5,IF(5=2,"Mesomorfo",IF(5=5,"Endomorfo","Ectomorfo"))&" balanceado",IF(5=2,"Mesomorfo",IF(5=5,"Endomorfo","Ectomorfo"))&" "&IF(2=5,"endomórfico",IF(2=2,"mesomórfico","ectomórfico"))))) -> Endomorfo balanceado | E43: =IF(D43=C43,"APROBADO","FALLIDO") -> APROBADO
A44: E04 | B44: 2.0·5.0·2.2 | C44: Mesomorfo balanceado | D44: =IF((5-2)<=1,"Central",IF((5-2.2)<=0.5,IF(2=2.2,"Endomorfo-mesomorfo",IF(2=2,"Mesomorfo-ectomorfo","Endomorfo-ectomorfo")),IF((2.2-2)<=0.5,IF(5=5,"Mesomorfo",IF(5=2,"Endomorfo","Ectomorfo"))&" balanceado",IF(5=5,"Mesomorfo",IF(5=2,"Endomorfo","Ectomorfo"))&" "&IF(2.2=2,"endomórfico",IF(2.2=5,"mesomórfico","ectomórfico"))))) -> Mesomorfo balanceado | E44: =IF(D44=C44,"APROBADO","FALLIDO") -> APROBADO
A45: E05 | B45: 2.0·2.2·6.0 | C45: Ectomorfo balanceado | D45: =IF((6-2)<=1,"Central",IF((6-2.2)<=0.5,IF(2=6,"Endomorfo-mesomorfo",IF(2=2,"Mesomorfo-ectomorfo","Endomorfo-ectomorfo")),IF((2.2-2)<=0.5,IF(6=2.2,"Mesomorfo",IF(6=2,"Endomorfo","Ectomorfo"))&" balanceado",IF(6=2.2,"Mesomorfo",IF(6=2,"Endomorfo","Ectomorfo"))&" "&IF(2.2=2,"endomórfico",IF(2.2=2.2,"mesomórfico","ectomórfico"))))) -> Ectomorfo balanceado | E45: =IF(D45=C45,"APROBADO","FALLIDO") -> APROBADO
A46: E06 | B46: 4.5·4.5·1.5 | C46: Endomorfo-mesomorfo | D46: =IF((4.5-1.5)<=1,"Central",IF((4.5-4.5)<=0.5,IF(1.5=1.5,"Endomorfo-mesomorfo",IF(1.5=4.5,"Mesomorfo-ectomorfo","Endomorfo-ectomorfo")),IF((4.5-1.5)<=0.5,IF(4.5=4.5,"Mesomorfo",IF(4.5=4.5,"Endomorfo","Ectomorfo"))&" balanceado",IF(4.5=4.5,"Mesomorfo",IF(4.5=4.5,"Endomorfo","Ectomorfo"))&" "&IF(4.5=4.5,"endomórfico",IF(4.5=4.5,"mesomórfico","ectomórfico"))))) -> Endomorfo-mesomorfo | E46: =IF(D46=C46,"APROBADO","FALLIDO") -> APROBADO
A47: E07 | B47: 1.5·3.0·5.5 | C47: Ectomorfo mesomórfico | D47: =IF((5.5-1.5)<=1,"Central",IF((5.5-3)<=0.5,IF(1.5=5.5,"Endomorfo-mesomorfo",IF(1.5=1.5,"Mesomorfo-ectomorfo","Endomorfo-ectomorfo")),IF((3-1.5)<=0.5,IF(5.5=3,"Mesomorfo",IF(5.5=1.5,"Endomorfo","Ectomorfo"))&" balanceado",IF(5.5=3,"Mesomorfo",IF(5.5=1.5,"Endomorfo","Ectomorfo"))&" "&IF(3=1.5,"endomórfico",IF(3=3,"mesomórfico","ectomórfico"))))) -> Ectomorfo mesomórfico | E47: =IF(D47=C47,"APROBADO","FALLIDO") -> APROBADO
A49: BLOQUE F · VALIDACIONES: vacíos, texto, negativos, imposibles
A50: ID | B50: Escenario | C50: Entrada | D50: Comportamiento esperado | E50: Comportamiento obtenido | F50: Estado
A51: F01 | B51: Edad menor de edad (15) | C51: 15 | D51: ERROR: edad fuera del alcance adulto | E51: =IF(NOT(ISNUMBER(15)),"ERROR: edad no numérica",IF(AND(15>=18,15<=120),"OK","ERROR: edad fuera del alcance adulto")) -> ERROR: edad fuera del alcance adulto | F51: =IF(E51=D51,"APROBADO","FALLIDO") -> APROBADO
A52: F02 | B52: Edad textual | C52: quince | D52: ERROR: edad no numérica | E52: =IF(NOT(ISNUMBER("quince")),"ERROR: edad no numérica",IF(AND("quince">=18,"quince"<=120),"OK","ERROR: edad fuera del alcance adulto")) -> ERROR: edad no numérica | F52: =IF(E52=D52,"APROBADO","FALLIDO") -> APROBADO
A53: F03 | B53: Peso negativo (−5) | C53: -5 | D53: ERROR: peso fuera de rango | E53: =IF(NOT(ISNUMBER(-5)),"ERROR: peso no numérico",IF(AND(-5>=25,-5<=350),"OK","ERROR: peso fuera de rango")) -> ERROR: peso fuera de rango | F53: =IF(E53=D53,"APROBADO","FALLIDO") -> APROBADO
A54: F04 | B54: Estatura imposible (400) | C54: 400 | D54: ERROR: estatura fuera de rango | E54: =IF(NOT(ISNUMBER(400)),"ERROR: estatura no numérico",IF(AND(400>=120,400<=230),"OK","ERROR: estatura fuera de rango")) -> ERROR: estatura fuera de rango | F54: =IF(E54=D54,"APROBADO","FALLIDO") -> APROBADO
A55: F05 | B55: Diámetro imposible (20) | C55: 20 | D55: ERROR: diámetro fuera de rango | E55: =IF(NOT(ISNUMBER(20)),"ERROR: diámetro no numérico",IF(AND(20>=3,20<=15),"OK","ERROR: diámetro fuera de rango")) -> ERROR: diámetro fuera de rango | F55: =IF(E55=D55,"APROBADO","FALLIDO") -> APROBADO
A56: F06 | B56: Perímetro imposible (5) | C56: 5 | D56: ERROR: perímetro fuera de rango | E56: =IF(NOT(ISNUMBER(5)),"ERROR: perímetro no numérico",IF(AND(5>=15,5<=80),"OK","ERROR: perímetro fuera de rango")) -> ERROR: perímetro fuera de rango | F56: =IF(E56=D56,"APROBADO","FALLIDO") -> APROBADO
A57: F07 | B57: Componente negativo → piso 0,1 | C57: -0.3 | D57: 0.1 | E57: =MAX(0.1,-0.3) -> 0.1 | F57: =IF(E57=D57,"APROBADO","FALLIDO") -> APROBADO
A58: F08 | B58: Componente 0 → piso 0,1 | C58: 0 | D58: 0.1 | E58: =MAX(0.1,0) -> 0.1 | F58: =IF(E58=D58,"APROBADO","FALLIDO") -> APROBADO
A60: BLOQUE G · INTEGRIDAD: cero errores de Excel
A61: ID | B61: Rango verificado | C61: Nº errores | D61: Esperado | E61: Estado
A62: G01 | B62: CALCULOS!B7:B39 | C62: =SUMPRODUCT(--ISERROR(M16_CALCULOS!B7:B39)) -> 0 | D62: 0 | E62: =IF(C62=D62,"APROBADO","FALLIDO") -> APROBADO
A63: G02 | B63: MEDIDAS!C8:C17 | C63: =SUMPRODUCT(--ISERROR(M16_MEDIDAS!C8:C17)) -> 0 | D63: 0 | E63: =IF(C63=D63,"APROBADO","FALLIDO") -> APROBADO
A64: G03 | B64: RESULTADOS!B6:C40 | C64: =SUMPRODUCT(--ISERROR(M16_RESULTADOS!B6:C40)) -> 0 | D64: 0 | E64: =IF(C64=D64,"APROBADO","FALLIDO") -> APROBADO
A66: BLOQUE H · COTEJO CON EL MOTOR (caso vivo · reconstrucción literal desde MEDIDAS)
A67: ID | B67: Verificación | C67: Obtenido (motor) | D67: Esperado (literal) | E67: Dif. | F67: Estado
A68: H01 | B68: Endomorfia | C68: =M16_c_Endo -> 4.146746 | D68: =MAX(0.1,-0.7182+0.1451*((M16_m_Tri+M16_m_Sub+M16_m_Sup)*(170.18/M16_in_Est))-0.00068*((M16_m_Tri+M16_m_Sub+M16_m_Sup)*(170.18/M16_in_Est))^2+0.0000014*((M16_m_Tri+M16_m_Sub+M16_m_Sup)*(170.18/M16_in_Est))^3) -> 4.146746 | E68: =C68-D68 -> 0 | F68: =IF(ABS(E68)<=M16_TOL_U,"APROBADO","FALLIDO") -> APROBADO
A69: H02 | B69: Mesomorfia | C69: =M16_c_Meso -> 3.8497 | D69: =MAX(0.1,0.858*M16_m_Hum+0.601*M16_m_Fem+0.188*(M16_m_ArmG-M16_m_Tri/10)+0.161*(M16_m_CalfG-M16_m_Calf/10)-0.131*M16_in_Est+4.5) -> 3.8497 | E69: =C69-D69 -> 0 | F69: =IF(ABS(E69)<=M16_TOL_U,"APROBADO","FALLIDO") -> APROBADO
A70: H03 | B70: Ectomorfia | C70: =M16_c_Ecto -> 1.5084995 | D70: =MAX(0.1,IF(M16_in_Est/(M16_in_Peso^(1/3))>=40.75,0.732*(M16_in_Est/(M16_in_Peso^(1/3)))-28.58,IF(M16_in_Est/(M16_in_Peso^(1/3))>38.25,0.463*(M16_in_Est/(M16_in_Peso^(1/3)))-17.63,0.1))) -> 1.5084995 | E70: =C70-D70 -> 0 | F70: =IF(ABS(E70)<=M16_TOL_U,"APROBADO","FALLIDO") -> APROBADO
A71: H04 | B71: Coordenada Y somatocarta | C71: =M16_c_SY -> 2.0441545 | D71: =2*M16_c_Meso-(M16_c_Endo+M16_c_Ecto) -> 2.0441545 | E71: =C71-D71 -> 0 | F71: =IF(ABS(E71)<=M16_TOL_U,"APROBADO","FALLIDO") -> APROBADO
A74: RESUMEN DEL BANCO DE PRUEBAS
A75: Casos totales | C75: 47
A76: Aprobados | C76: =IF(H8="APROBADO",1,0)+IF(H9="APROBADO",1,0)+IF(H10="APROBADO",1,0)+IF(H11="APROBADO",1,0)+IF(H12="APROBADO",1,0)+IF(H13="APROBADO",1,0)+IF(J17="APROBADO",1,0)+IF(J18="APROBADO",1,0)+IF(J19="APROBADO",1,0)+IF(J20="APROBADO",1,0)+IF(J21="APROBADO",1,0)+IF(H25="APROBADO",1,0)+IF(H26="APROBADO",1,0)+IF(H27="APROBADO",1,0)+IF(H28="APROBADO",1,0)+IF(H29="APROBADO",1,0)+IF(H30="APROBADO",1,0)+IF(G34="APROBADO",1,0)+IF(J34="APROBADO",1,0)+IF(G35="APROBADO",1,0)+IF(J35="APROBADO",1,0)+IF(G36="APROBADO",1,0)+IF(J36="APROBADO",1,0)+IF(G37="APROBADO",1,0)+IF(J37="APROBADO",1,0)+IF(E41="APROBADO",1,0)+IF(E42="APROBADO",1,0)+IF(E43="APROBADO",1,0)+IF(E44="APROBADO",1,0)+IF(E45="APROBADO",1,0)+IF(E46="APROBADO",1,0)+IF(E47="APROBADO",1,0)+IF(F51="APROBADO",1,0)+IF(F52="APROBADO",1,0)+IF(F53="APROBADO",1,0)+IF(F54="APROBADO",1,0)+IF(F55="APROBADO",1,0)+IF(F56="APROBADO",1,0)+IF(F57="APROBADO",1,0)+IF(F58="APROBADO",1,0)+IF(E62="APROBADO",1,0)+IF(E63="APROBADO",1,0)+IF(E64="APROBADO",1,0)+IF(F68="APROBADO",1,0)+IF(F69="APROBADO",1,0)+IF(F70="APROBADO",1,0)+IF(F71="APROBADO",1,0) -> 47
A77: Fallidos | C77: =47-C76 -> 0
A78: ESTADO GLOBAL | B78: =IF(C76=47,"TODAS LAS PRUEBAS APROBADAS","HAY PRUEBAS FALLIDAS — REVISAR") -> TODAS LAS PRUEBAS APROBADAS

Sheet M16_CONFIG
A1: NUTRIMETRÍA · NMX-16
A2: Parámetros, coeficientes y catálogos · versión 1.0
A3: =HYPERLINK("#M16_INICIO!A1","◀ INICIO") -> ◀ INICIO
A4: Toda constante del modelo vive aquí; ninguna fórmula del libro contiene un coeficiente escrito a mano. Las celdas arena son editables. Cambiar un valor aquí propaga a todo el libro y hace FALLAR las pruebas que cotejan contra la fuente publicada.
A6: C1 · PARÁMETROS, LÍMITES Y COEFICIENTES DE HEATH–CARTER
A7: Parámetro | B7: Valor | C7: Unidad | D7: Prueba | E7: Nota/Fuente
A8: Idioma | B8: Español (es-CL)
A9: Versión de las fuentes | B9: 2026-07 · v1.0
A10: Edad mínima (adulto) | B10: 18
A11: Edad máxima plausible | B11: 120
A12: Peso mínimo posible | B12: 25
A13: Peso máximo posible | B13: 350 | C13: kg | D13: IMPOSIBLE | E13: Cota de seguridad para datos imposibles; ver DATOS!D12 y PRUEBAS!F03.
A14: Estatura mínima posible | B14: 120 | C14: cm | D14: IMPOSIBLE | E14: Cota de seguridad para datos imposibles; ver DATOS!D13 y PRUEBAS!F04.
A15: Estatura máxima posible | B15: 230 | C15: cm | D15: IMPOSIBLE | E15: Cota de seguridad para datos imposibles; ver DATOS!D13 y PRUEBAS!F04.
A16: Pliegue mínimo por sitio | B16: 2 | C16: mm | D16: IMPOSIBLE | E16: Valor editorial (rango práctico de plicometría/ISAK); el manual Heath-Carter no fija este límite. Ajustable por el titular.
A17: Pliegue máximo por sitio | B17: 60 | C17: mm | D17: IMPOSIBLE | E17: Valor editorial (rango práctico de plicometría/ISAK); el manual Heath-Carter no fija este límite. Ajustable por el titular.
A18: Diámetro óseo mínimo | B18: 3 | C18: cm | D18: IMPOSIBLE | E18: Cota de seguridad para datos imposibles; ver PRUEBAS!F05.
A19: Diámetro óseo máximo | B19: 15 | C19: cm | D19: IMPOSIBLE | E19: Cota de seguridad para datos imposibles; ver PRUEBAS!F05.
A20: Perímetro mínimo | B20: 15 | C20: cm | D20: IMPOSIBLE | E20: Brazo / pantorrilla
A21: Perímetro máximo | B21: 80 | C21: cm | D21: IMPOSIBLE
A22: Componente mínimo (piso) | B22: 0.1 | C22: — | D22: Regla | E22: Un componente ≤0 se fija en 0,1 (Carter)
A23: Tolerancia de pruebas · unidad | B23: 0.01 | C23: — | D23: Umbral | E23: Diferencia máxima en unidades de somatotipo
A24: Endomorfia · término independiente | B24: -0.7182 | C24: — | D24: Coef. | E24: Endo = c0 + c1·X − c2·X² + c3·X³
A25: Endomorfia · coef. lineal | B25: 0.1451 | C25: — | D25: Coef.
A26: Endomorfia · coef. cuadrático | B26: 0.00068 | C26: — | D26: Coef. | E26: (se resta)
A27: Endomorfia · coef. cúbico | B27: 1.4e-06 | C27: — | D27: Coef.
A28: Endomorfia · estatura de referencia | B28: 170.18 | C28: cm | D28: Coef. | E28: Corrección por talla: Σ3·(170,18/H)
A29: Mesomorfia · coef. húmero | B29: 0.858 | C29: — | D29: Coef. | E29: × diámetro biepicondíleo húmero
A30: Mesomorfia · coef. fémur | B30: 0.601 | C30: — | D30: Coef. | E30: × diámetro biepicondíleo fémur
A31: Mesomorfia · coef. perímetro de brazo | B31: 0.188 | C31: — | D31: Coef. | E31: × brazo corregido
A32: Mesomorfia · coef. perímetro de pantorrilla | B32: 0.161 | C32: — | D32: Coef. | E32: × pantorrilla corregida
A33: Mesomorfia · coef. estatura | B33: 0.131 | C33: — | D33: Coef. | E33: (se resta) × estatura
A34: Mesomorfia · constante | B34: 4.5 | C34: — | D34: Coef. | E34: Término independiente
A35: Ectomorfia · umbral alto (HWR) | B35: 40.75 | C35: — | D35: Corte | E35: HWR ≥ 40,75 usa el tramo 1
A36: Ectomorfia · umbral bajo (HWR) | B36: 38.25 | C36: — | D36: Corte | E36: HWR ≤ 38,25 → 0,1
A37: Ectomorfia · pendiente tramo 1 | B37: 0.732 | C37: — | D37: Coef. | E37: 0,732·HWR − 28,58
A38: Ectomorfia · término tramo 1 | B38: 28.58 | C38: — | D38: Coef.
A39: Ectomorfia · pendiente tramo 2 | B39: 0.463 | C39: — | D39: Coef. | E39: 0,463·HWR − 17,63
A40: Ectomorfia · término tramo 2 | B40: 17.63 | C40: — | D40: Coef.
A42: C2 · SEXOS
A43: Valor | B43: Nota
A44: Hombre | B44: Referencia; las ecuaciones HC no dependen del sexo
A45: Mujer | B45: Referencia
A47: C3 · LISTA SÍ / NO
A48: Sí
A49: No
A51: C4 · VÉRTICES DE LA SOMATOCARTA (referencia del gráfico)
A52: Polo | B52: X = ecto − endo | C52: Y = 2·meso − (endo+ecto)
A53: Endomorfia (7-1-1) | B53: -6 | C53: -6
A54: Mesomorfia (1-7-1) | B54: 0 | C54: 12
A55: Ectomorfia (1-1-7) | B55: 6 | C55: -6
A56: cierre | B56: -6 | C56: -6
A58: La somatocarta proyecta el somatotipo 3D en un plano 2D. Los tres polos forman el triángulo de referencia; el punto del sujeto se ubica dentro según sus componentes.

Sheet M16_CHANGELOG
A1: NUTRIMETRÍA · NMX-16
A2: Historial de versiones
A3: =HYPERLINK("#M16_INICIO!A1","◀ INICIO") -> ◀ INICIO
A5: Versión | B5: Fecha | C5: Cambio | D5: Motivo | E5: Responsable
A6: 1.0 | B6: 2026-07-14 | C6: Versión inicial. Somatotipo antropométrico de Heath–Carter (endomorfia, mesomorfia, ectomorfia), clasificación en 13 categorías y somatocarta (gráfico de dispersión con el punto del sujeto). | D6: Primera entrega del producto 16. | E6: Equipo Nutrimetría
A7: 1.0 | B7: 2026-07-14 | C7: Banco de pruebas con exactitud de las tres ecuaciones (incluidos los tres tramos de ectomorfia), clasificación, coordenadas de la somatocarta, validaciones e integridad; valores esperados independientes del CONFIG. | D7: Control de calidad. | E7: Equipo Nutrimetría

Sheet M34_INICIO
A1: NUTRIMETRÍA · NMX-34
A2: Indicador educativo de edad metabólica · versión 1.0 · Fase 7 · especialidades y productos complementarios
A4: Navegación — use las pestañas inferiores del libro
A5: =HYPERLINK("#M34_DATOS!A1","▶ DATOS") -> ▶ DATOS | C5: =HYPERLINK("#M34_CALCULO!A1","▶ CALCULO") -> ▶ CALCULO | E5: =HYPERLINK("#M34_SENSIBILIDAD!A1","▶ SENSIBILIDAD") -> ▶ SENSIBILIDAD | G5: =HYPERLINK("#M34_INTERPRETACION!A1","▶ INTERPRETACION") -> ▶ INTERPRETACION | I5: =HYPERLINK("#M34_FUENTES!A1","▶ FUENTES") -> ▶ FUENTES | K5: =HYPERLINK("#M34_PRUEBAS!A1","▶ PRUEBAS") -> ▶ PRUEBAS | M5: =HYPERLINK("#M34_CONFIG!A1","▶ CONFIG") -> ▶ CONFIG | O5: =HYPERLINK("#M34_CHANGELOG!A1","▶ CHANGELOG") -> ▶ CHANGELOG
A6: Persona y mediciones | C6: De dónde sale el número | E6: Cuánto se mueve | G6: Qué significa y qué no | I6: Evidencia y advertencias | K6: Control de calidad | M6: Constantes | O6: Historial
A8: Código del producto | C8: NMX-34
A9: Versión | C9: 1.0
A10: Fecha | C10: 2026-07-24
A11: Naturaleza | C11: Indicador EDUCATIVO y de comunicación · NO es un instrumento diagnóstico
A12: Ecuaciones | C12: Katch-McArdle sin edad · Mifflin-St Jeor con edad
A13: Formato | C13: .xlsx sin macros · Microsoft 365 (Windows) y Excel 2021 · sin funciones matriciales
A14: Responsable | C14: Equipo Nutrimetría (completar por el titular)
A16: ADVERTENCIA PRINCIPAL
A17: ESTE INDICADOR NO ES UN DIAGNÓSTICO. No mide envejecimiento biológico, no evalúa salud metabólica, no detecta enfermedad y no reemplaza ninguna evaluación clínica.
